Workbook
Name A83728543L: 'ABS-total-value-dwellings'!$AF$1:$AF$10,'ABS-total-value-dwellings'!$AF$11:$AF$106
Name A83728543L_Data: 'ABS-total-value-dwellings'!$AF$11:$AF$106
Name A83728543L_Latest: 'ABS-total-value-dwellings'!$AF$106
Name A83728544R: 'ABS-total-value-dwellings'!$AU$1:$AU$10,'ABS-total-value-dwellings'!$AU$17:$AU$106
Name A83728544R_Data: 'ABS-total-value-dwellings'!$AU$17:$AU$106
Name A83728544R_Latest: 'ABS-total-value-dwellings'!$AU$106
Name A83728545T: 'ABS-total-value-dwellings'!$B$1:$B$10,'ABS-total-value-dwellings'!$B$11:$B$106
Name A83728545T_Data: 'ABS-total-value-dwellings'!$B$11:$B$106
Name A83728545T_Latest: 'ABS-total-value-dwellings'!$B$106
Name A83728546V: 'ABS-total-value-dwellings'!$Q$1:$Q$10,'ABS-total-value-dwellings'!$Q$17:$Q$106
Name A83728546V_Data: 'ABS-total-value-dwellings'!$Q$17:$Q$106
Name A83728546V_Latest: 'ABS-total-value-dwellings'!$Q$106
Name A83728547W: 'ABS-total-value-dwellings'!$AH$1:$AH$10,'ABS-total-value-dwellings'!$AH$11:$AH$106
Name A83728547W_Data: 'ABS-total-value-dwellings'!$AH$11:$AH$106
Name A83728547W_Latest: 'ABS-total-value-dwellings'!$AH$106
Name A83728548X: 'ABS-total-value-dwellings'!$AW$1:$AW$10,'ABS-total-value-dwellings'!$AW$17:$AW$106
Name A83728548X_Data: 'ABS-total-value-dwellings'!$AW$17:$AW$106
Name A83728548X_Latest: 'ABS-total-value-dwellings'!$AW$106
Name A83728549A: 'ABS-total-value-dwellings'!$D$1:$D$10,'ABS-total-value-dwellings'!$D$11:$D$106
Name A83728549A_Data: 'ABS-total-value-dwellings'!$D$11:$D$106
Name A83728549A_Latest: 'ABS-total-value-dwellings'!$D$106
Name A83728550K: 'ABS-total-value-dwellings'!$S$1:$S$10,'ABS-total-value-dwellings'!$S$17:$S$106
Name A83728550K_Data: 'ABS-total-value-dwellings'!$S$17:$S$106
Name A83728550K_Latest: 'ABS-total-value-dwellings'!$S$106
Name A83728551L: 'ABS-total-value-dwellings'!$AJ$1:$AJ$10,'ABS-total-value-dwellings'!$AJ$11:$AJ$106
Name A83728551L_Data: 'ABS-total-value-dwellings'!$AJ$11:$AJ$106
Name A83728551L_Latest: 'ABS-total-value-dwellings'!$AJ$106
Name A83728552R: 'ABS-total-value-dwellings'!$AY$1:$AY$10,'ABS-total-value-dwellings'!$AY$17:$AY$106
Name A83728552R_Data: 'ABS-total-value-dwellings'!$AY$17:$AY$106
Name A83728552R_Latest: 'ABS-total-value-dwellings'!$AY$106
Name A83728553T: 'ABS-total-value-dwellings'!$F$1:$F$10,'ABS-total-value-dwellings'!$F$11:$F$106
Name A83728553T_Data: 'ABS-total-value-dwellings'!$F$11:$F$106
Name A83728553T_Latest: 'ABS-total-value-dwellings'!$F$106
Name A83728554V: 'ABS-total-value-dwellings'!$U$1:$U$10,'ABS-total-value-dwellings'!$U$17:$U$106
Name A83728554V_Data: 'ABS-total-value-dwellings'!$U$17:$U$106
Name A83728554V_Latest: 'ABS-total-value-dwellings'!$U$106
Name A83728555W: 'ABS-total-value-dwellings'!$AL$1:$AL$10,'ABS-total-value-dwellings'!$AL$11:$AL$106
Name A83728555W_Data: 'ABS-total-value-dwellings'!$AL$11:$AL$106
Name A83728555W_Latest: 'ABS-total-value-dwellings'!$AL$106
Name A83728556X: 'ABS-total-value-dwellings'!$BA$1:$BA$10,'ABS-total-value-dwellings'!$BA$17:$BA$106
Name A83728556X_Data: 'ABS-total-value-dwellings'!$BA$17:$BA$106
Name A83728556X_Latest: 'ABS-total-value-dwellings'!$BA$106
Name A83728557A: 'ABS-total-value-dwellings'!$H$1:$H$10,'ABS-total-value-dwellings'!$H$11:$H$106
Name A83728557A_Data: 'ABS-total-value-dwellings'!$H$11:$H$106
Name A83728557A_Latest: 'ABS-total-value-dwellings'!$H$106
Name A83728558C: 'ABS-total-value-dwellings'!$W$1:$W$10,'ABS-total-value-dwellings'!$W$17:$W$106
Name A83728558C_Data: 'ABS-total-value-dwellings'!$W$17:$W$106
Name A83728558C_Latest: 'ABS-total-value-dwellings'!$W$106
Name A83728559F: 'ABS-total-value-dwellings'!$AN$1:$AN$10,'ABS-total-value-dwellings'!$AN$11:$AN$106
Name A83728559F_Data: 'ABS-total-value-dwellings'!$AN$11:$AN$106
Name A83728559F_Latest: 'ABS-total-value-dwellings'!$AN$106
Name A83728560R: 'ABS-total-value-dwellings'!$BC$1:$BC$10,'ABS-total-value-dwellings'!$BC$17:$BC$106
Name A83728560R_Data: 'ABS-total-value-dwellings'!$BC$17:$BC$106
Name A83728560R_Latest: 'ABS-total-value-dwellings'!$BC$106
Name A83728561T: 'ABS-total-value-dwellings'!$J$1:$J$10,'ABS-total-value-dwellings'!$J$11:$J$106
Name A83728561T_Data: 'ABS-total-value-dwellings'!$J$11:$J$106
Name A83728561T_Latest: 'ABS-total-value-dwellings'!$J$106
Name A83728562V: 'ABS-total-value-dwellings'!$Y$1:$Y$10,'ABS-total-value-dwellings'!$Y$17:$Y$106
Name A83728562V_Data: 'ABS-total-value-dwellings'!$Y$17:$Y$106
Name A83728562V_Latest: 'ABS-total-value-dwellings'!$Y$106

Sheet analysis
A1: Rent vs buy analysis - Brisbane | B1: Set values | C1: Default values | T1: Renter calcs >> | X1: {=SUM(_xlfn._xlws.FILTER(X3:X82,ISNUMBER(X3:X82)))} -> 426808.35 | AI1: CGT calcs | AR1: Buyer calcs >> | AY1: Maintenance and renovation | BB1: Mortgage | BG1: {=SUM(_xlfn._xlws.FILTER(BG3:BG82,ISNUMBER(BG3:BG82)))} -> 622431.06 | BH1: Comparison vs inflation
A2: Ending renter-to-owner wealth ratio | B2: =_xlfn.XLOOKUP(Q_end,L:L,O:O) -> 0.98793046 | E2: ="Renter vs owner wealth, "&Council_Area&IF(B10="2BR_F"," 2-bedroom flat"," 3-bedroom house") -> Renter vs owner wealth, Brisbane 3-bedroom house | L2: Quarter ending | M2: Renter's portfolio | N2: Owner's home equity | O2: Renter-to-owner wealth ratio | P2: Renter-to-owner cash needs | Q2: Quarter of analysis | R2: Days in quarter | T2: Median weekly rents, new bonds | U2: Renter's rents | V2: Quarterly rent | W2: Other renter costs | X2: Renter's cashflow costs | Y2: Renter additional cashflow | Z2: Tax concessions | AA2: Renter investment contributions | AB2: Contributions (CPI-adjusted to Q_end) | AC2: MSCI World index, start Q | AD2: MSCI Aus index, start Q | AE2: Portfolio, start Q | AF2: MSCI World index, end Q | AG2: MSCI Aus index, end Q | AH2: Investment fees | AI2: Portfolio, end Q, before CGT | AJ2: Cost base (nominal) | AK2: Nominal gains ($) | AL2: Cost base (CPI-adjusted to Q_end) | AM2: Cost base + CPI to current quarter | AN2: Real gains ($) | AO2: CGT on withdrawals | AP2: Portfolio, end Q | AR2: Median home price | AS2: Depreciation | AT2: Home purchase costs | AU2: Home sale costs | AV2: Renovation | AW2: Renovation, cumulative | AX2: Adjusted home price | AY2: Maintenance | AZ2: Total p.a. as % of home value | BA2: Total p.a. as % of rent | BB2: Mortgage rates | BC2: Loan balance | BD2: Mortgage payment | BE2: Mortgage interest | BF2: Mortgage - principal component | BG2: Owner's cashflow costs | BH2: CPI | BI2: CPI (Q_st art = 100) | BJ2: MSCI World (Q_start=100) | BK2: MSCI Aus (Q_start=100) | BL2: Portfolio index (Q_start=100) | BM2: Portfolio (Q_start=100) | BN2: Median home price (Q_start = 100) | BO2: Adjusted home price (Q_start = 100)
A3: Average renter-to-owner cashflow needs excl. home purchase costs | B3: {=SUM(_xlfn._xlws.FILTER($X$3:$X$82,ISNUMBER($X$3:$X$82)))/(SUM(_xlfn._xlws.FILTER($BG$3:$BG$82,ISNUMBER($BG$3:$BG$82)))-AT3)} -> 0.78644479 | L3: =Q_start -> 38777 | M3: =AP3 -> 89388.034 | N3: =AX3-BC3 -> 56753.125 | O3: =M3/N3 -> 1.5750328 | P3: =X3/BG3 -> 0.037910859 | Q3: 1 | R3: =EOMONTH(L3,0)-EOMONTH(L3,-3) -> 90 | T3: =IF($B$10="3BR_H", INDEX('3BR_H-processed'!$E:$E,MATCH($L3,'3BR_H-processed'!$B:$B,0),MATCH(Council_Area,'3BR_H-processed'!$E$1:$E$1,0)), INDEX('2BR_F-processed'!$E:$E,MATCH($L3,'2BR_F-processed'!$B:$B,0),MATCH(Council_Area,'2BR_F-processed'!$E$1:$E$1,0))) -> 245 | U3: =IF(MOD(Q3,4)=1,T3,U2) -> 245 | V3: =U3*(R3)/7 -> 3150 | W3: =$B$53/4*BH3/_xlfn.XLOOKUP(Q_end,cpi!A:A,cpi!B:B) -> 116.93158 | X3: =V3+W3 -> 3266.9316 | Y3: =BG3-X3 -> 82907.101 | Z3: =MAX(0,Y3*$B$47) -> 0 | AA3: {=(Y3+Z3)*eff_invest} -> 82907.101 | AB3: =AA3*(_xlfn.XLOOKUP(Q_end,cpi!A:A,cpi!B:B)/BH3) -> 141804.46 | AC3: {=INDEX('msci-indices'!C:C,MATCH($L3,'msci-indices'!$B:$B)-2)} -> 754.87961 | AD3: {=INDEX('msci-indices'!D:D,MATCH($L3,'msci-indices'!$B:$B)-2)} -> 712.95625 | AE3: =AA3 -> 82907.101 | AF3: {=INDEX('msci-indices'!C:C,MATCH($L3,'msci-indices'!$B:$B)+1)} -> 809.32012 | AG3: {=INDEX('msci-indices'!D:D,MATCH($L3,'msci-indices'!$B:$B)+1)} -> 780.24347 | AH3: =(InvestFees/4)*AE3 -> 51.816938 | AI3: =((AF3/AC3)*GlobalPortfolio+(AG3/AD3)*AusPortfolio)*AE3-AH3 -> 89388.034 | AJ3: =AA3 -> 82907.101 | AK3: =AI3-AJ3 -> 6480.933 | AL3: =AJ3*(_xlfn.XLOOKUP(Q_end,cpi!A:A,cpi!B:B)/BH3) -> 141804.46 | AM3: =AA3 -> 82907.101 | AN3: =AI3-AM3 -> 6480.933 | AO3: =IF($B$49="Real gains",MAX($B$50*AN3,0),IF($B$49="Discounted nominal gains",MAX($B$50*AK3/2,0),0)) -> 0 | AP3: =AI3-AO3 -> 89388.034 | AR3: =IF($B$10="3BR_H", INDEX('ns-combined'!$C:$D,MATCH($L3,'ns-combined'!$B:$B,0),MATCH(Council_Area,'ns-combined'!$C$1:$D$1,0))*1000, INDEX('s-combined'!$C:$D,MATCH($L3,'s-combined'!$B:$B,0),MATCH(Council_Area,'s-combined'!$C$1:$D$1,0))*1000) -> 325000 | AS3: =AR3*$B$14/4 -> 812.5 | AT3: =SUM(B20:B26)*AR3 -> 79725 | AU3: =SUM($B$28:$B$29)*AR3 -> 6500 | AV3: =AR3*$B$15/4 -> 934.375 | AW3: =SUM($AV$3:AV3) -> 934.375 | AX3: =AR3-AS3-AU3-AW3 -> 316753.12 | AY3: =$B$36*V3 -> 1102.5 | AZ3: =SUM(AY3:AY3)*4/AR3 -> 0.013569231 | BA3: =SUM(AY3:AY3)/V3 -> 0.35 | BB3: =IF(MortgageRate="Discounted",_xlfn.XLOOKUP(L3,'mortgage-rates'!$A:$A,'mortgage-rates'!$E:$E)/100,_xlfn.XLOOKUP(L3,'mortgage-rates'!$A:$A,'mortgage-rates'!$D:$D)/100) -> 0.0664 | BC3: =(1-B20)*AR3 -> 260000 | BD3: =IF($B$16*12/3-Q3+1>0,-PMT($BB3/4,$B$16*12/3-Q3+1,BC3),0) -> 5346.5324 | BE3: =BC3*($BB3/4) -> 4316 | BF3: =BD3-BE3 -> 1030.5324 | BG3: =AT3+AY3+BD3 -> 86174.032 | BH3: =INDEX(cpi!B:B,MATCH($L3,cpi!A:A)) -> 84.6 | BI3: =100*BH3/BH$3 -> 100 | BJ3: =100*AC3/AC$3 -> 100 | BK3: =100*AD3/AD$3 -> 100 | BL3: =BJ3*GlobalPortfolio+BK3*AusPortfolio -> 100 | BM3: =100*AE3/$AE$3 -> 100 | BN3: =100*AR3/AR$3 -> 100 | BO3: =100*AX3/AX$3 -> 100
A4: Median home price growth p.a. | B4: =((_xlfn.XLOOKUP(Q_end,L:L,AR:AR)/_xlfn.XLOOKUP(Q_start,L:L,AR:AR))^(1/YEARFRAC(EOMONTH(Q_start,-3)+1,EOMONTH(Q_end,0))))-1 -> 0.062858539 | L4: =IF(DATE(YEAR(L3),MONTH(L3)+3,1)<=Q_end,DATE(YEAR(L3),MONTH(L3)+3,1),"") -> 38869 | M4: =AP4 -> 92087.217 | N4: =AX4-BC4 -> 60922.407 | O4: =M4/N4 -> 1.5115492 | P4: =X4/BG4 -> 0.50028919 | Q4: 2 | R4: =EOMONTH(L4,0)-EOMONTH(L4,-3) -> 91 | T4: =IF($B$10="3BR_H", INDEX('3BR_H-processed'!$E:$E,MATCH($L4,'3BR_H-processed'!$B:$B,0),MATCH(Council_Area,'3BR_H-processed'!$E$1:$E$1,0)), INDEX('2BR_F-processed'!$E:$E,MATCH($L4,'2BR_F-processed'!$B:$B,0),MATCH(Council_Area,'2BR_F-processed'!$E$1:$E$1,0))) -> 240 | U4: =IF(MOD(Q4,4)=1,T4,U3) -> 245 | V4: =U4*(R4)/7 -> 3185 | W4: =$B$53/4*BH4/_xlfn.XLOOKUP(Q_end,cpi!A:A,cpi!B:B) -> 118.7284 | X4: =V4+W4 -> 3303.7284 | Y4: =BG4-X4 -> 3299.909 | Z4: =Y4*$B$47 -> 0 | AA4: {=(Y4+Z4)*eff_invest} -> 3299.909 | AB4: =AA4*(_xlfn.XLOOKUP(Q_end,cpi!A:A,cpi!B:B)/BH4) -> 5558.7524 | AC4: {=INDEX('msci-indices'!C:C,MATCH($L4,'msci-indices'!$B:$B)-2)} -> 809.32012 | AD4: {=INDEX('msci-indices'!D:D,MATCH($L4,'msci-indices'!$B:$B)-2)} -> 780.24347 | AE4: =AI3+AA4 -> 92687.943 | AF4: {=INDEX('msci-indices'!C:C,MATCH($L4,'msci-indices'!$B:$B)+1)} -> 802.64573 | AG4: {=INDEX('msci-indices'!D:D,MATCH($L4,'msci-indices'!$B:$B)+1)} -> 780.02674 | AH4: =(InvestFees/4)*AE4 -> 57.929964 | AI4: =((AF4/AC4)*GlobalPortfolio+(AG4/AD4)*AusPortfolio)*AE4-AH4 -> 92087.217 | AJ4: =AJ3+AA4 -> 86207.01 | AK4: =AI4-AJ4 -> 5880.2071 | AL4: =AJ4*(_xlfn.XLOOKUP(Q_end,cpi!A:A,cpi!B:B)/BH4) -> 145217.16 | AM4: {=SUMPRODUCT($AA$3:AA4,_xlfn.SORTBY($BH$3:BH4,_xlfn.SEQUENCE(ROWS($BH$3:BH4)),-1)/$BH$3)} -> 87480.996 | AN4: =AI4-AM4 -> 4606.221 | AO4: =IF($B$49="Real gains",MAX($B$50*AN4,0),IF($B$49="Discounted nominal gains",MAX($B$50*AK4/2,0),0)) -> 0 | AP4: =AI4-AO4 -> 92087.217 | AR4: =IF($B$10="3BR_H", INDEX('ns-combined'!$C:$D,MATCH($L4,'ns-combined'!$B:$B,0),MATCH(Council_Area,'ns-combined'!$C$1:$D$1,0))*1000, INDEX('s-combined'!$C:$D,MATCH($L4,'s-combined'!$B:$B,0),MATCH(Council_Area,'s-combined'!$C$1:$D$1,0))*1000) -> 330000 | AS4: =AS3+$AS$3 -> 1625 | AT4: 0 | AU4: =SUM($B$28:$B$29)*AR4 -> 6600 | AV4: =AR4*$B$15/4 -> 948.75 | AW4: =SUM($AV$3:AV4) -> 1883.125 | AX4: =AR4-AS4-AU4-AW4 -> 319891.88 | AY4: =$B$36*V4 -> 1114.75 | AZ4: =SUM(AY4:AY4)*4/AR4 -> 0.013512121 | BA4: =SUM(AY4:AY4)/V4 -> 0.35 | BB4: =IF(MortgageRate="Discounted",_xlfn.XLOOKUP(L4,'mortgage-rates'!$A:$A,'mortgage-rates'!$E:$E)/100,_xlfn.XLOOKUP(L4,'mortgage-rates'!$A:$A,'mortgage-rates'!$D:$D)/100) -> 0.0693 | BC4: =BC3-BF3 -> 258969.47 | BD4: =IF($B$16*12/3-Q4+1>0,-PMT($BB4/4,$B$16*12/3-Q4+1,BC4),0) -> 5488.8874 | BE4: =BC4*($BB4/4) -> 4486.646 | BF4: =BD4-BE4 -> 1002.2414 | BG4: =AT4+AY4+BD4 -> 6603.6374 | BH4: =INDEX(cpi!B:B,MATCH($L4,cpi!A:A)) -> 85.9 | BI4: =100*BH4/BH$3 -> 101.53664 | BJ4: =100*AC4/AC$3 -> 107.21181 | BK4: =100*AD4/AD$3 -> 109.43778 | BL4: =BJ4*GlobalPortfolio+BK4*AusPortfolio -> 107.8796 | BM4: =100*AE4/$AE$3 -> 111.79735 | BN4: =100*AR4/AR$3 -> 101.53846 | BO4: =100*AX4/AX$3 -> 100.99091
A5: Adjusted home price growth p.a. | B5: =((_xlfn.XLOOKUP(Q_end,L:L,AX:AX)/_xlfn.XLOOKUP(Q_start,L:L,AX:AX))^(1/YEARFRAC(EOMONTH(Q_start,-3)+1,EOMONTH(Q_end,0))))-1 -> 0.052783781 | L5: =DATE(YEAR(L4),MONTH(L4)+3,1) -> 38961 | M5: =AP5 -> 98932.035 | N5: =AX5-BC5 -> 65049.024 | O5: =M5/N5 -> 1.5208842 | P5: =X5/BG5 -> 0.49411542 | Q5: 3 | R5: =EOMONTH(L5,0)-EOMONTH(L5,-3) -> 92 | T5: =IF($B$10="3BR_H", INDEX('3BR_H-processed'!$E:$E,MATCH($L5,'3BR_H-processed'!$B:$B,0),MATCH(Council_Area,'3BR_H-processed'!$E$1:$E$1,0)), INDEX('2BR_F-processed'!$E:$E,MATCH($L5,'2BR_F-processed'!$B:$B,0),MATCH(Council_Area,'2BR_F-processed'!$E$1:$E$1,0))) -> 250 | U5: =IF(MOD(Q5,4)=1,T5,U4) -> 245 | V5: =U5*(R5)/7 -> 3220 | W5: =$B$53/4*BH5/_xlfn.XLOOKUP(Q_end,cpi!A:A,cpi!B:B) -> 119.69592 | X5: =V5+W5 -> 3339.6959 | Y5: =BG5-X5 -> 3419.2429 | Z5: =Y5*$B$47 -> 0 | AA5: {=(Y5+Z5)*eff_invest} -> 3419.2429 | AB5: =AA5*(_xlfn.XLOOKUP(Q_end,cpi!A:A,cpi!B:B)/BH5) -> 5713.2153 | AC5: {=INDEX('msci-indices'!C:C,MATCH($L5,'msci-indices'!$B:$B)-2)} -> 802.64573 | AD5: {=INDEX('msci-indices'!D:D,MATCH($L5,'msci-indices'!$B:$B)-2)} -> 780.02674 | AE5: =AI4+AA5 -> 95506.46 | AF5: {=INDEX('msci-indices'!C:C,MATCH($L5,'msci-indices'!$B:$B)+1)} -> 835.13401 | AG5: {=INDEX('msci-indices'!D:D,MATCH($L5,'msci-indices'!$B:$B)+1)} -> 801.24067 | AH5: =(InvestFees/4)*AE5 -> 59.691537 | AI5: =((AF5/AC5)*GlobalPortfolio+(AG5/AD5)*AusPortfolio)*AE5-AH5 -> 98932.035 | AJ5: =AJ4+AA5 -> 89626.253 | AK5: =AI5-AJ5 -> 9305.7819 | AL5: =AJ5*(_xlfn.XLOOKUP(Q_end,cpi!A:A,cpi!B:B)/BH5) -> 149756.57 | AM5: {=SUMPRODUCT($AA$3:AA5,_xlfn.SORTBY($BH$3:BH5,_xlfn.SEQUENCE(ROWS($BH$3:BH5)),-1)/$BH$3)} -> 91636.939 | AN5: =AI5-AM5 -> 7295.0953 | AO5: =IF($B$49="Real gains",MAX($B$50*AN5,0),IF($B$49="Discounted nominal gains",MAX($B$50*AK5/2,0),0)) -> 0 | AP5: =AI5-AO5 -> 98932.035 | AR5: =IF($B$10="3BR_H", INDEX('ns-combined'!$C:$D,MATCH($L5,'ns-combined'!$B:$B,0),MATCH(Council_Area,'ns-combined'!$C$1:$D$1,0))*1000, INDEX('s-combined'!$C:$D,MATCH($L5,'s-combined'!$B:$B,0),MATCH(Council_Area,'s-combined'!$C$1:$D$1,0))*1000) -> 335000 | AS5: =AS4+$AS$3 -> 2437.5 | AT5: 0 | AU5: =SUM($B$28:$B$29)*AR5 -> 6700 | AV5: =AR5*$B$15/4 -> 963.125 | AW5: =SUM($AV$3:AV5) -> 2846.25 | AX5: =AR5-AS5-AU5-AW5 -> 323016.25 | AY5: =$B$36*V5 -> 1127 | AZ5: =SUM(AY5:AY5)*4/AR5 -> 0.013456716 | BA5: =SUM(AY5:AY5)/V5 -> 0.35 | BB5: =IF(MortgageRate="Discounted",_xlfn.XLOOKUP(L5,'mortgage-rates'!$A:$A,'mortgage-rates'!$E:$E)/100,_xlfn.XLOOKUP(L5,'mortgage-rates'!$A:$A,'mortgage-rates'!$D:$D)/100) -> 0.0722 | BC5: =BC4-BF4 -> 257967.23 | BD5: =IF($B$16*12/3-Q5+1>0,-PMT($BB5/4,$B$16*12/3-Q5+1,BC5),0) -> 5631.9388 | BE5: =BC5*($BB5/4) -> 4656.3084 | BF5: =BD5-BE5 -> 975.63039 | BG5: =AT5+AY5+BD5 -> 6758.9388 | BH5: =INDEX(cpi!B:B,MATCH($L5,cpi!A:A)) -> 86.6 | BI5: =100*BH5/BH$3 -> 102.36407 | BJ5: =100*AC5/AC$3 -> 106.32765 | BK5: =100*AD5/AD$3 -> 109.40738 | BL5: =BJ5*GlobalPortfolio+BK5*AusPortfolio -> 107.25157 | BM5: =100*AE5/$AE$3 -> 115.19696 | BN5: =100*AR5/AR$3 -> 103.07692 | BO5: =100*AX5/AX$3 -> 101.97729
A6: Rent growth p.a. | B6: =((_xlfn.XLOOKUP(Q_end,L:L,U:U)/_xlfn.XLOOKUP(Q_start,L:L,U:U))^(1/YEARFRAC(EOMONTH(Q_start,-3)+1,EOMONTH(Q_end,0))))-1 -> 0.046836134 | L6: =DATE(YEAR(L5),MONTH(L5)+3,1) -> 39052 | M6: =AP6 -> 111773.69 | N6: =AX6-BC6 -> 72554.592 | O6: =M6/N6 -> 1.5405461 | P6: =X6/BG6 -> 0.48524891 | Q6: 4 | R6: =EOMONTH(L6,0)-EOMONTH(L6,-3) -> 92 | T6: =IF($B$10="3BR_H", INDEX('3BR_H-processed'!$E:$E,MATCH($L6,'3BR_H-processed'!$B:$B,0),MATCH(Council_Area,'3BR_H-processed'!$E$1:$E$1,0)), INDEX('2BR_F-processed'!$E:$E,MATCH($L6,'2BR_F-processed'!$B:$B,0),MATCH(Council_Area,'2BR_F-processed'!$E$1:$E$1,0))) -> 250 | U6: =IF(MOD(Q6,4)=1,T6,U5) -> 245 | V6: =U6*(R6)/7 -> 3220 | W6: =$B$53/4*BH6/_xlfn.XLOOKUP(Q_end,cpi!A:A,cpi!B:B) -> 119.83414 | X6: =V6+W6 -> 3339.8341 | Y6: =BG6-X6 -> 3542.8894 | Z6: =Y6*$B$47 -> 0 | AA6: {=(Y6+Z6)*eff_invest} -> 3542.8894 | AB6: =AA6*(_xlfn.XLOOKUP(Q_end,cpi!A:A,cpi!B:B)/BH6) -> 5912.9885 | AC6: {=INDEX('msci-indices'!C:C,MATCH($L6,'msci-indices'!$B:$B)-2)} -> 835.13401 | AD6: {=INDEX('msci-indices'!D:D,MATCH($L6,'msci-indices'!$B:$B)-2)} -> 801.24067 | AE6: =AI5+AA6 -> 102474.92 | AF6: {=INDEX('msci-indices'!C:C,MATCH($L6,'msci-indices'!$B:$B)+1)} -> 906.58022 | AG6: {=INDEX('msci-indices'!D:D,MATCH($L6,'msci-indices'!$B:$B)+1)} -> 885.32149 | AH6: =(InvestFees/4)*AE6 -> 64.046828 | AI6: =((AF6/AC6)*GlobalPortfolio+(AG6/AD6)*AusPortfolio)*AE6-AH6 -> 111773.69 | AJ6: =AJ5+AA6 -> 93169.142 | AK6: =AI6-AJ6 -> 18604.551 | AL6: =AJ6*(_xlfn.XLOOKUP(Q_end,cpi!A:A,cpi!B:B)/BH6) -> 155496.83 | AM6: {=SUMPRODUCT($AA$3:AA6,_xlfn.SORTBY($BH$3:BH6,_xlfn.SEQUENCE(ROWS($BH$3:BH6)),-1)/$BH$3)} -> 95357.673 | AN6: =AI6-AM6 -> 16416.02 | AO6: =IF($B$49="Real gains",MAX($B$50*AN6,0),IF($B$49="Discounted nominal gains",MAX($B$50*AK6/2,0),0)) -> 0 | AP6: =AI6-AO6 -> 111773.69 | AR6: =IF($B$10="3BR_H", INDEX('ns-combined'!$C:$D,MATCH($L6,'ns-combined'!$B:$B,0),MATCH(Council_Area,'ns-combined'!$C$1:$D$1,0))*1000, INDEX('s-combined'!$C:$D,MATCH($L6,'s-combined'!$B:$B,0),MATCH(Council_Area,'s-combined'!$C$1:$D$1,0))*1000) -> 343500 | AS6: =AS5+$AS$3 -> 3250 | AT6: 0 | AU6: =SUM($B$28:$B$29)*AR6 -> 6870 | AV6: =AR6*$B$15/4 -> 987.5625 | AW6: =SUM($AV$3:AV6) -> 3833.8125 | AX6: =AR6-AS6-AU6-AW6 -> 329546.19 | AY6: =$B$36*V6 -> 1127 | AZ6: =SUM(AY6:AY6)*4/AR6 -> 0.013123726 | BA6: =SUM(AY6:AY6)/V6 -> 0.35 | BB6: =IF(MortgageRate="Discounted",_xlfn.XLOOKUP(L6,'mortgage-rates'!$A:$A,'mortgage-rates'!$E:$E)/100,_xlfn.XLOOKUP(L6,'mortgage-rates'!$A:$A,'mortgage-rates'!$D:$D)/100) -> 0.0747 | BC6: =BC5-BF5 -> 256991.6 | BD6: =IF($B$16*12/3-Q6+1>0,-PMT($BB6/4,$B$16*12/3-Q6+1,BC6),0) -> 5755.7236 | BE6: =BC6*($BB6/4) -> 4799.3181 | BF6: =BD6-BE6 -> 956.40552 | BG6: =AT6+AY6+BD6 -> 6882.7236 | BH6: =INDEX(cpi!B:B,MATCH($L6,cpi!A:A)) -> 86.7 | BI6: =100*BH6/BH$3 -> 102.48227 | BJ6: =100*AC6/AC$3 -> 110.63142 | BK6: =100*AD6/AD$3 -> 112.38287 | BL6: =BJ6*GlobalPortfolio+BK6*AusPortfolio -> 111.15685 | BM6: =100*AE6/$AE$3 -> 123.60211 | BN6: =100*AR6/AR$3 -> 105.69231 | BO6: =100*AX6/AX$3 -> 104.03881
A7: Investment index (country-weighted) growth p.a. | B7: =((_xlfn.XLOOKUP(Q_end,L:L,BL:BL)/_xlfn.XLOOKUP(Q_start,L:L,BL:BL))^(1/YEARFRAC(EOMONTH(Q_start,-3)+1,EOMONTH(Q_end,0))))-1 -> 0.080631422 | L7: =DATE(YEAR(L6),MONTH(L6)+3,1) -> 39142 | M7: =AP7 -> 119808.04 | N7: =AX7-BC7 -> 80016.497 | O7: =M7/N7 -> 1.4972917 | P7: =X7/BG7 -> 0.49997538 | Q7: 5 | R7: =EOMONTH(L7,0)-EOMONTH(L7,-3) -> 90 | T7: =IF($B$10="3BR_H", INDEX('3BR_H-processed'!$E:$E,MATCH($L7,'3BR_H-processed'!$B:$B,0),MATCH(Council_Area,'3BR_H-processed'!$E$1:$E$1,0)), INDEX('2BR_F-processed'!$E:$E,MATCH($L7,'2BR_F-processed'!$B:$B,0),MATCH(Council_Area,'2BR_F-processed'!$E$1:$E$1,0))) -> 260 | U7: =IF(MOD(Q7,4)=1,T7,U6) -> 260 | V7: =U7*(R7)/7 -> 3342.8571 | W7: =$B$53/4*BH7/_xlfn.XLOOKUP(Q_end,cpi!A:A,cpi!B:B) -> 119.83414 | X7: =V7+W7 -> 3462.6913 | Y7: =BG7-X7 -> 3463.0323 | Z7: =Y7*$B$47 -> 0 | AA7: {=(Y7+Z7)*eff_invest} -> 3463.0323 | AB7: =AA7*(_xlfn.XLOOKUP(Q_end,cpi!A:A,cpi!B:B)/BH7) -> 5779.709 | AC7: {=INDEX('msci-indices'!C:C,MATCH($L7,'msci-indices'!$B:$B)-2)} -> 906.58022 | AD7: {=INDEX('msci-indices'!D:D,MATCH($L7,'msci-indices'!$B:$B)-2)} -> 885.32149 | AE7: =AI6+AA7 -> 115236.73 | AF7: {=INDEX('msci-indices'!C:C,MATCH($L7,'msci-indices'!$B:$B)+1)} -> 932.09759 | AG7: {=INDEX('msci-indices'!D:D,MATCH($L7,'msci-indices'!$B:$B)+1)} -> 946.08734 | AH7: =(InvestFees/4)*AE7 -> 72.022953 | AI7: =((AF7/AC7)*GlobalPortfolio+(AG7/AD7)*AusPortfolio)*AE7-AH7 -> 119808.04 | AJ7: =AJ6+AA7 -> 96632.174 | AK7: =AI7-AJ7 -> 23175.866 | AL7: =AJ7*(_xlfn.XLOOKUP(Q_end,cpi!A:A,cpi!B:B)/BH7) -> 161276.54 | AM7: {=SUMPRODUCT($AA$3:AA7,_xlfn.SORTBY($BH$3:BH7,_xlfn.SEQUENCE(ROWS($BH$3:BH7)),-1)/$BH$3)} -> 98907.34 | AN7: =AI7-AM7 -> 20900.701 | AO7: =IF($B$49="Real gains",MAX($B$50*AN7,0),IF($B$49="Discounted nominal gains",MAX($B$50*AK7/2,0),0)) -> 0 | AP7: =AI7-AO7 -> 119808.04 | AR7: =IF($B$10="3BR_H", INDEX('ns-combined'!$C:$D,MATCH($L7,'ns-combined'!$B:$B,0),MATCH(Council_Area,'ns-combined'!$C$1:$D$1,0))*1000, INDEX('s-combined'!$C:$D,MATCH($L7,'s-combined'!$B:$B,0),MATCH(Council_Area,'s-combined'!$C$1:$D$1,0))*1000) -> 352000 | AS7: =AS6+$AS$3 -> 4062.5 | AT7: 0 | AU7: =SUM($B$28:$B$29)*AR7 -> 7040 | AV7: =AR7*$B$15/4 -> 1012 | AW7: =SUM($AV$3:AV7) -> 4845.8125 | AX7: =AR7-AS7-AU7-AW7 -> 336051.69 | AY7: =$B$36*V7 -> 1170 | AZ7: =SUM(AY7:AY7)*4/AR7 -> 0.013295455 | BA7: =SUM(AY7:AY7)/V7 -> 0.35 | BB7: =IF(MortgageRate="Discounted",_xlfn.XLOOKUP(L7,'mortgage-rates'!$A:$A,'mortgage-rates'!$E:$E)/100,_xlfn.XLOOKUP(L7,'mortgage-rates'!$A:$A,'mortgage-rates'!$D:$D)/100) -> 0.0747 | BC7: =BC6-BF6 -> 256035.19 | BD7: =IF($B$16*12/3-Q7+1>0,-PMT($BB7/4,$B$16*12/3-Q7+1,BC7),0) -> 5755.7236 | BE7: =BC7*($BB7/4) -> 4781.4572 | BF7: =BD7-BE7 -> 974.2664 | BG7: =AT7+AY7+BD7 -> 6925.7236 | BH7: =INDEX(cpi!B:B,MATCH($L7,cpi!A:A)) -> 86.7 | BI7: =100*BH7/BH$3 -> 102.48227 | BJ7: =100*AC7/AC$3 -> 120.096 | BK7: =100*AD7/AD$3 -> 124.17613 | BL7: =BJ7*GlobalPortfolio+BK7*AusPortfolio -> 121.32004 | BM7: =100*AE7/$AE$3 -> 138.995 | BN7: =100*AR7/AR$3 -> 108.30769 | BO7: =100*AX7/AX$3 -> 106.09262
A8: CPI growth p.a. | B8: =((_xlfn.XLOOKUP(Q_end,L:L,BI:BI)/_xlfn.XLOOKUP(Q_start,L:L,BI:BI))^(1/YEARFRAC(EOMONTH(Q_start,-3)+1,EOMONTH(Q_end,0))))-1 -> 0.027199758 | L8: =DATE(YEAR(L7),MONTH(L7)+3,1) -> 39234 | M8: =AP8 -> 130831.02 | N8: =AX8-BC8 -> 101640.14 | O8: =M8/N8 -> 1.2871984 | P8: =X8/BG8 -> 0.50459083 | Q8: 6 | R8: =EOMONTH(L8,0)-EOMONTH(L8,-3) -> 91 | T8: =IF($B$10="3BR_H", INDEX('3BR_H-processed'!$E:$E,MATCH($L8,'3BR_H-processed'!$B:$B,0),MATCH(Council_Area,'3BR_H-processed'!$E$1:$E$1,0)), INDEX('2BR_F-processed'!$E:$E,MATCH($L8,'2BR_F-processed'!$B:$B,0),MATCH(Council_Area,'2BR_F-processed'!$E$1:$E$1,0))) -> 260 | U8: =IF(MOD(Q8,4)=1,T8,U7) -> 260 | V8: =U8*(R8)/7 -> 3380 | W8: =$B$53/4*BH8/_xlfn.XLOOKUP(Q_end,cpi!A:A,cpi!B:B) -> 121.21631 | X8: =V8+W8 -> 3501.2163 | Y8: =BG8-X8 -> 3437.5073 | Z8: =Y8*$B$47 -> 0 | AA8: {=(Y8+Z8)*eff_invest} -> 3437.5073 | AB8: =AA8*(_xlfn.XLOOKUP(Q_end,cpi!A:A,cpi!B:B)/BH8) -> 5671.691 | AC8: {=INDEX('msci-indices'!C:C,MATCH($L8,'msci-indices'!$B:$B)-2)} -> 932.09759 | AD8: {=INDEX('msci-indices'!D:D,MATCH($L8,'msci-indices'!$B:$B)-2)} -> 946.08734 | AE8: =AI7+AA8 -> 123245.55 | AF8: {=INDEX('msci-indices'!C:C,MATCH($L8,'msci-indices'!$B:$B)+1)} -> 991.70582 | AG8: {=INDEX('msci-indices'!D:D,MATCH($L8,'msci-indices'!$B:$B)+1)} -> 1000.9831 | AH8: =(InvestFees/4)*AE8 -> 77.028467 | AI8: =((AF8/AC8)*GlobalPortfolio+(AG8/AD8)*AusPortfolio)*AE8-AH8 -> 130831.02 | AJ8: =AJ7+AA8 -> 100069.68 | AK8: =AI8-AJ8 -> 30761.338 | AL8: =AJ8*(_xlfn.XLOOKUP(Q_end,cpi!A:A,cpi!B:B)/BH8) -> 165109.27 | AM8: {=SUMPRODUCT($AA$3:AA8,_xlfn.SORTBY($BH$3:BH8,_xlfn.SEQUENCE(ROWS($BH$3:BH8)),-1)/$BH$3)} -> 103411.41 | AN8: =AI8-AM8 -> 27419.613 | AO8: =IF($B$49="Real gains",MAX($B$50*AN8,0),IF($B$49="Discounted nominal gains",MAX($B$50*AK8/2,0),0)) -> 0 | AP8: =AI8-AO8 -> 130831.02 | AR8: =IF($B$10="3BR_H", INDEX('ns-combined'!$C:$D,MATCH($L8,'ns-combined'!$B:$B,0),MATCH(Council_Area,'ns-combined'!$C$1:$D$1,0))*1000, INDEX('s-combined'!$C:$D,MATCH($L8,'s-combined'!$B:$B,0),MATCH(Council_Area,'s-combined'!$C$1:$D$1,0))*1000) -> 375000 | AS8: =AS7+$AS$3 -> 4875 | AT8: 0 | AU8: =SUM($B$28:$B$29)*AR8 -> 7500 | AV8: =AR8*$B$15/4 -> 1078.125 | AW8: =SUM($AV$3:AV8) -> 5923.9375 | AX8: =AR8-AS8-AU8-AW8 -> 356701.06 | AY8: =$B$36*V8 -> 1183 | AZ8: =SUM(AY8:AY8)*4/AR8 -> 0.012618667 | BA8: =SUM(AY8:AY8)/V8 -> 0.35 | BB8: =IF(MortgageRate="Discounted",_xlfn.XLOOKUP(L8,'mortgage-rates'!$A:$A,'mortgage-rates'!$E:$E)/100,_xlfn.XLOOKUP(L8,'mortgage-rates'!$A:$A,'mortgage-rates'!$D:$D)/100) -> 0.0747 | BC8: =BC7-BF7 -> 255060.92 | BD8: =IF($B$16*12/3-Q8+1>0,-PMT($BB8/4,$B$16*12/3-Q8+1,BC8),0) -> 5755.7236 | BE8: =BC8*($BB8/4) -> 4763.2628 | BF8: =BD8-BE8 -> 992.46082 | BG8: =AT8+AY8+BD8 -> 6938.7236 | BH8: =INDEX(cpi!B:B,MATCH($L8,cpi!A:A)) -> 87.7 | BI8: =100*BH8/BH$3 -> 103.6643 | BJ8: =100*AC8/AC$3 -> 123.47632 | BK8: =100*AD8/AD$3 -> 132.69921 | BL8: =BJ8*GlobalPortfolio+BK8*AusPortfolio -> 126.24319 | BM8: =100*AE8/$AE$3 -> 148.655 | BN8: =100*AR8/AR$3 -> 115.38462 | BO8: =100*AX8/AX$3 -> 112.61169
L9: =DATE(YEAR(L8),MONTH(L8)+3,1) -> 39326 | M9: =AP9 -> 138424.52 | N9: =AX9-BC9 -> 115398.85 | O9: =M9/N9 -> 1.1995312 | P9: =X9/BG9 -> 0.50027709 | Q9: 7 | R9: =EOMONTH(L9,0)-EOMONTH(L9,-3) -> 92 | T9: =IF($B$10="3BR_H", INDEX('3BR_H-processed'!$E:$E,MATCH($L9,'3BR_H-processed'!$B:$B,0),MATCH(Council_Area,'3BR_H-processed'!$E$1:$E$1,0)), INDEX('2BR_F-processed'!$E:$E,MATCH($L9,'2BR_F-processed'!$B:$B,0),MATCH(Council_Area,'2BR_F-processed'!$E$1:$E$1,0))) -> 265 | U9: =IF(MOD(Q9,4)=1,T9,U8) -> 260 | V9: =U9*(R9)/7 -> 3417.1429 | W9: =$B$53/4*BH9/_xlfn.XLOOKUP(Q_end,cpi!A:A,cpi!B:B) -> 121.90739 | X9: =V9+W9 -> 3539.0503 | Y9: =BG9-X9 -> 3535.1299 | Z9: =Y9*$B$47 -> 0 | AA9: {=(Y9+Z9)*eff_invest} -> 3535.1299 | AB9: =AA9*(_xlfn.XLOOKUP(Q_end,cpi!A:A,cpi!B:B)/BH9) -> 5799.6972 | AC9: {=INDEX('msci-indices'!C:C,MATCH($L9,'msci-indices'!$B:$B)-2)} -> 991.70582 | AD9: {=INDEX('msci-indices'!D:D,MATCH($L9,'msci-indices'!$B:$B)-2)} -> 1000.9831 | AE9: =AI8+AA9 -> 134366.15 | AF9: {=INDEX('msci-indices'!C:C,MATCH($L9,'msci-indices'!$B:$B)+1)} -> 1009.8701 | AG9: {=INDEX('msci-indices'!D:D,MATCH($L9,'msci-indices'!$B:$B)+1)} -> 1061.067 | AH9: =(InvestFees/4)*AE9 -> 83.978844 | AI9: =((AF9/AC9)*GlobalPortfolio+(AG9/AD9)*AusPortfolio)*AE9-AH9 -> 138424.52 | AJ9: =AJ8+AA9 -> 103604.81 | AK9: =AI9-AJ9 -> 34819.71 | AL9: =AJ9*(_xlfn.XLOOKUP(Q_end,cpi!A:A,cpi!B:B)/BH9) -> 169972.97 | AM9: {=SUMPRODUCT($AA$3:AA9,_xlfn.SORTBY($BH$3:BH9,_xlfn.SEQUENCE(ROWS($BH$3:BH9)),-1)/$BH$3)} -> 107561.2 | AN9: =AI9-AM9 -> 30863.32 | AO9: =IF($B$49="Real gains",MAX($B$50*AN9,0),IF($B$49="Discounted nominal gains",MAX($B$50*AK9/2,0),0)) -> 0 | AP9: =AI9-AO9 -> 138424.52 | AR9: =IF($B$10="3BR_H", INDEX('ns-combined'!$C:$D,MATCH($L9,'ns-combined'!$B:$B,0),MATCH(Council_Area,'ns-combined'!$C$1:$D$1,0))*1000, INDEX('s-combined'!$C:$D,MATCH($L9,'s-combined'!$B:$B,0),MATCH(Council_Area,'s-combined'!$C$1:$D$1,0))*1000) -> 390000 | AS9: =AS8+$AS$3 -> 5687.5 | AT9: 0 | AU9: =SUM($B$28:$B$29)*AR9 -> 7800 | AV9: =AR9*$B$15/4 -> 1121.25 | AW9: =SUM($AV$3:AV9) -> 7045.1875 | AX9: =AR9-AS9-AU9-AW9 -> 369467.31 | AY9: =$B$36*V9 -> 1196 | AZ9: =SUM(AY9:AY9)*4/AR9 -> 0.012266667 | BA9: =SUM(AY9:AY9)/V9 -> 0.35 | BB9: =IF(MortgageRate="Discounted",_xlfn.XLOOKUP(L9,'mortgage-rates'!$A:$A,'mortgage-rates'!$E:$E)/100,_xlfn.XLOOKUP(L9,'mortgage-rates'!$A:$A,'mortgage-rates'!$D:$D)/100) -> 0.0772 | BC9: =BC8-BF8 -> 254068.46 | BD9: =IF($B$16*12/3-Q9+1>0,-PMT($BB9/4,$B$16*12/3-Q9+1,BC9),0) -> 5878.1802 | BE9: =BC9*($BB9/4) -> 4903.5213 | BF9: =BD9-BE9 -> 974.65882 | BG9: =AT9+AY9+BD9 -> 7074.1802 | BH9: =INDEX(cpi!B:B,MATCH($L9,cpi!A:A)) -> 88.2 | BI9: =100*BH9/BH$3 -> 104.25532 | BJ9: =100*AC9/AC$3 -> 131.37271 | BK9: =100*AD9/AD$3 -> 140.39895 | BL9: =BJ9*GlobalPortfolio+BK9*AusPortfolio -> 134.08059 | BM9: =100*AE9/$AE$3 -> 162.06833 | BN9: =100*AR9/AR$3 -> 120 | BO9: =100*AX9/AX$3 -> 116.64204
A10: Dwelling type (3br house, 3BR_H; or 2br flat, 2BR_F) | B10: 3BR_H | C10: 3BR_H | L10: =DATE(YEAR(L9),MONTH(L9)+3,1) -> 39417 | M10: =AP10 -> 138152.19 | N10: =AX10-BC10 -> 138867.88 | O10: =M10/N10 -> 0.99484625 | P10: =X10/BG10 -> 0.49195736 | Q10: 8 | R10: =EOMONTH(L10,0)-EOMONTH(L10,-3) -> 92 | T10: =IF($B$10="3BR_H", INDEX('3BR_H-processed'!$E:$E,MATCH($L10,'3BR_H-processed'!$B:$B,0),MATCH(Council_Area,'3BR_H-processed'!$E$1:$E$1,0)), INDEX('2BR_F-processed'!$E:$E,MATCH($L10,'2BR_F-processed'!$B:$B,0),MATCH(Council_Area,'2BR_F-processed'!$E$1:$E$1,0))) -> 270 | U10: =IF(MOD(Q10,4)=1,T10,U9) -> 260 | V10: =U10*(R10)/7 -> 3417.1429 | W10: =$B$53/4*BH10/_xlfn.XLOOKUP(Q_end,cpi!A:A,cpi!B:B) -> 123.42778 | X10: =V10+W10 -> 3540.5706 | Y10: =BG10-X10 -> 3656.3349 | Z10: =Y10*$B$47 -> 0 | AA10: {=(Y10+Z10)*eff_invest} -> 3656.3349 | AB10: =AA10*(_xlfn.XLOOKUP(Q_end,cpi!A:A,cpi!B:B)/BH10) -> 5924.6547 | AC10: {=INDEX('msci-indices'!C:C,MATCH($L10,'msci-indices'!$B:$B)-2)} -> 1009.8701 | AD10: {=INDEX('msci-indices'!D:D,MATCH($L10,'msci-indices'!$B:$B)-2)} -> 1061.067 | AE10: =AI9+AA10 -> 142080.86 | AF10: {=INDEX('msci-indices'!C:C,MATCH($L10,'msci-indices'!$B:$B)+1)} -> 983.50383 | AG10: {=INDEX('msci-indices'!D:D,MATCH($L10,'msci-indices'!$B:$B)+1)} -> 1030.1196 | AH10: =(InvestFees/4)*AE10 -> 88.800536 | AI10: =((AF10/AC10)*GlobalPortfolio+(AG10/AD10)*AusPortfolio)*AE10-AH10 -> 138152.19 | AJ10: =AJ9+AA10 -> 107261.15 | AK10: =AI10-AJ10 -> 30891.046 | AL10: =AJ10*(_xlfn.XLOOKUP(Q_end,cpi!A:A,cpi!B:B)/BH10) -> 173803.9 | AM10: {=SUMPRODUCT($AA$3:AA10,_xlfn.SORTBY($BH$3:BH10,_xlfn.SEQUENCE(ROWS($BH$3:BH10)),-1)/$BH$3)} -> 112442.3 | AN10: =AI10-AM10 -> 25709.89 | AO10: =IF($B$49="Real gains",MAX($B$50*AN10,0),IF($B$49="Discounted nominal gains",MAX($B$50*AK10/2,0),0)) -> 0 | AP10: =AI10-AO10 -> 138152.19 | AR10: =IF($B$10="3BR_H", INDEX('ns-combined'!$C:$D,MATCH($L10,'ns-combined'!$B:$B,0),MATCH(Council_Area,'ns-combined'!$C$1:$D$1,0))*1000, INDEX('s-combined'!$C:$D,MATCH($L10,'s-combined'!$B:$B,0),MATCH(Council_Area,'s-combined'!$C$1:$D$1,0))*1000) -> 415000 | AS10: =AS9+$AS$3 -> 6500 | AT10: 0 | AU10: =SUM($B$28:$B$29)*AR10 -> 8300 | AV10: =AR10*$B$15/4 -> 1193.125 | AW10: =SUM($AV$3:AV10) -> 8238.3125 | AX10: =AR10-AS10-AU10-AW10 -> 391961.69 | AY10: =$B$36*V10 -> 1196 | AZ10: =SUM(AY10:AY10)*4/AR10 -> 0.011527711 | BA10: =SUM(AY10:AY10)/V10 -> 0.35 | BB10: =IF(MortgageRate="Discounted",_xlfn.XLOOKUP(L10,'mortgage-rates'!$A:$A,'mortgage-rates'!$E:$E)/100,_xlfn.XLOOKUP(L10,'mortgage-rates'!$A:$A,'mortgage-rates'!$D:$D)/100) -> 0.0797 | BC10: =BC9-BF9 -> 253093.8 | BD10: =IF($B$16*12/3-Q10+1>0,-PMT($BB10/4,$B$16*12/3-Q10+1,BC10),0) -> 6000.9056 | BE10: =BC10*($BB10/4) -> 5042.894 | BF10: =BD10-BE10 -> 958.01153 | BG10: =AT10+AY10+BD10 -> 7196.9056 | BH10: =INDEX(cpi!B:B,MATCH($L10,cpi!A:A)) -> 89.3 | BI10: =100*BH10/BH$3 -> 105.55556 | BJ10: =100*AC10/AC$3 -> 133.77897 | BK10: =100*AD10/AD$3 -> 148.82639 | BL10: =BJ10*GlobalPortfolio+BK10*AusPortfolio -> 138.29319 | BM10: =100*AE10/$AE$3 -> 171.37357 | BN10: =100*AR10/AR$3 -> 127.69231 | BO10: =100*AX10/AX$3 -> 123.74359
A11: Analysis start quarter | B11: 38777 | C11: 38777 | L11: =DATE(YEAR(L10),MONTH(L10)+3,1) -> 39508 | M11: =AP11 -> 126829.86 | N11: =AX11-BC11 -> 147591.52 | O11: =M11/N11 -> 0.85933027 | P11: =X11/BG11 -> 0.49299655 | Q11: 9 | R11: =EOMONTH(L11,0)-EOMONTH(L11,-3) -> 91 | T11: =IF($B$10="3BR_H", INDEX('3BR_H-processed'!$E:$E,MATCH($L11,'3BR_H-processed'!$B:$B,0),MATCH(Council_Area,'3BR_H-processed'!$E$1:$E$1,0)), INDEX('2BR_F-processed'!$E:$E,MATCH($L11,'2BR_F-processed'!$B:$B,0),MATCH(Council_Area,'2BR_F-processed'!$E$1:$E$1,0))) -> 280 | U11: =IF(MOD(Q11,4)=1,T11,U10) -> 280 | V11: =U11*(R11)/7 -> 3640 | W11: =$B$53/4*BH11/_xlfn.XLOOKUP(Q_end,cpi!A:A,cpi!B:B) -> 124.94817 | X11: =V11+W11 -> 3764.9482 | Y11: =BG11-X11 -> 3871.917 | Z11: =Y11*$B$47 -> 0 | AA11: {=(Y11+Z11)*eff_invest} -> 3871.917 | AB11: =AA11*(_xlfn.XLOOKUP(Q_end,cpi!A:A,cpi!B:B)/BH11) -> 6197.6371 | AC11: {=INDEX('msci-indices'!C:C,MATCH($L11,'msci-indices'!$B:$B)-2)} -> 983.50383 | AD11: {=INDEX('msci-indices'!D:D,MATCH($L11,'msci-indices'!$B:$B)-2)} -> 1030.1196 | AE11: =AI10+AA11 -> 142024.11 | AF11: {=INDEX('msci-indices'!C:C,MATCH($L11,'msci-indices'!$B:$B)+1)} -> 894.99836 | AG11: {=INDEX('msci-indices'!D:D,MATCH($L11,'msci-indices'!$B:$B)+1)} -> 881.21373 | AH11: =(InvestFees/4)*AE11 -> 88.765069 | AI11: =((AF11/AC11)*GlobalPortfolio+(AG11/AD11)*AusPortfolio)*AE11-AH11 -> 126829.86 | AJ11: =AJ10+AA11 -> 111133.06 | AK11: =AI11-AJ11 -> 15696.797 | AL11: =AJ11*(_xlfn.XLOOKUP(Q_end,cpi!A:A,cpi!B:B)/BH11) -> 177886.66 | AM11: {=SUMPRODUCT($AA$3:AA11,_xlfn.SORTBY($BH$3:BH11,_xlfn.SEQUENCE(ROWS($BH$3:BH11)),-1)/$BH$3)} -> 117586.7 | AN11: =AI11-AM11 -> 9243.1608 | AO11: =IF($B$49="Real gains",MAX($B$50*AN11,0),IF($B$49="Discounted nominal gains",MAX($B$50*AK11/2,0),0)) -> 0 | AP11: =AI11-AO11 -> 126829.86 | AR11: =IF($B$10="3BR_H", INDEX('ns-combined'!$C:$D,MATCH($L11,'ns-combined'!$B:$B,0),MATCH(Council_Area,'ns-combined'!$C$1:$D$1,0))*1000, INDEX('s-combined'!$C:$D,MATCH($L11,'s-combined'!$B:$B,0),MATCH(Council_Area,'s-combined'!$C$1:$D$1,0))*1000) -> 425000 | AS11: =AS10+$AS$3 -> 7312.5 | AT11: 0 | AU11: =SUM($B$28:$B$29)*AR11 -> 8500 | AV11: =AR11*$B$15/4 -> 1221.875 | AW11: =SUM($AV$3:AV11) -> 9460.1875 | AX11: =AR11-AS11-AU11-AW11 -> 399727.31 | AY11: =$B$36*V11 -> 1274 | AZ11: =SUM(AY11:AY11)*4/AR11 -> 0.011990588 | BA11: =SUM(AY11:AY11)/V11 -> 0.35 | BB11: =IF(MortgageRate="Discounted",_xlfn.XLOOKUP(L11,'mortgage-rates'!$A:$A,'mortgage-rates'!$E:$E)/100,_xlfn.XLOOKUP(L11,'mortgage-rates'!$A:$A,'mortgage-rates'!$D:$D)/100) -> 0.087 | BC11: =BC10-BF10 -> 252135.79 | BD11: =IF($B$16*12/3-Q11+1>0,-PMT($BB11/4,$B$16*12/3-Q11+1,BC11),0) -> 6362.8652 | BE11: =BC11*($BB11/4) -> 5483.9535 | BF11: =BD11-BE11 -> 878.91172 | BG11: =AT11+AY11+BD11 -> 7636.8652 | BH11: =INDEX(cpi!B:B,MATCH($L11,cpi!A:A)) -> 90.4 | BI11: =100*BH11/BH$3 -> 106.85579 | BJ11: =100*AC11/AC$3 -> 130.28618 | BK11: =100*AD11/AD$3 -> 144.48568 | BL11: =BJ11*GlobalPortfolio+BK11*AusPortfolio -> 134.54603 | BM11: =100*AE11/$AE$3 -> 171.30512 | BN11: =100*AR11/AR$3 -> 130.76923 | BO11: =100*AX11/AX$3 -> 126.19522
A12: Analysis end quarter | B12: 45992 | C12: 45992 | L12: =DATE(YEAR(L11),MONTH(L11)+3,1) -> 39600 | M12: =AP12 -> 128723.12 | N12: =AX12-BC12 -> 146436.06 | O12: =M12/N12 -> 0.87903979 | P12: =X12/BG12 -> 0.48873695 | Q12: 10 | R12: =EOMONTH(L12,0)-EOMONTH(L12,-3) -> 91 | T12: =IF($B$10="3BR_H", INDEX('3BR_H-processed'!$E:$E,MATCH($L12,'3BR_H-processed'!$B:$B,0),MATCH(Council_Area,'3BR_H-processed'!$E$1:$E$1,0)), INDEX('2BR_F-processed'!$E:$E,MATCH($L12,'2BR_F-processed'!$B:$B,0),MATCH(Council_Area,'2BR_F-processed'!$E$1:$E$1,0))) -> 280 | U12: =IF(MOD(Q12,4)=1,T12,U11) -> 280 | V12: =U12*(R12)/7 -> 3640 | W12: =$B$53/4*BH12/_xlfn.XLOOKUP(Q_end,cpi!A:A,cpi!B:B) -> 126.60677 | X12: =V12+W12 -> 3766.6068 | Y12: =BG12-X12 -> 3940.2114 | Z12: =Y12*$B$47 -> 0 | AA12: {=(Y12+Z12)*eff_invest} -> 3940.2114 | AB12: =AA12*(_xlfn.XLOOKUP(Q_end,cpi!A:A,cpi!B:B)/BH12) -> 6224.3295 | AC12: {=INDEX('msci-indices'!C:C,MATCH($L12,'msci-indices'!$B:$B)-2)} -> 894.99836 | AD12: {=INDEX('msci-indices'!D:D,MATCH($L12,'msci-indices'!$B:$B)-2)} -> 881.21373 | AE12: =AI11+AA12 -> 130770.07 | AF12: {=INDEX('msci-indices'!C:C,MATCH($L12,'msci-indices'!$B:$B)+1)} -> 881.79174 | AG12: {=INDEX('msci-indices'!D:D,MATCH($L12,'msci-indices'!$B:$B)+1)} -> 867.41147 | AH12: =(InvestFees/4)*AE12 -> 81.731295 | AI12: =((AF12/AC12)*GlobalPortfolio+(AG12/AD12)*AusPortfolio)*AE12-AH12 -> 128723.12 | AJ12: =AJ11+AA12 -> 115073.28 | AK12: =AI12-AJ12 -> 13649.845 | AL12: =AJ12*(_xlfn.XLOOKUP(Q_end,cpi!A:A,cpi!B:B)/BH12) -> 181780.6 | AM12: {=SUMPRODUCT($AA$3:AA12,_xlfn.SORTBY($BH$3:BH12,_xlfn.SEQUENCE(ROWS($BH$3:BH12)),-1)/$BH$3)} -> 122946.07 | AN12: =AI12-AM12 -> 5777.0543 | AO12: =IF($B$49="Real gains",MAX($B$50*AN12,0),IF($B$49="Discounted nominal gains",MAX($B$50*AK12/2,0),0)) -> 0 | AP12: =AI12-AO12 -> 128723.12 | AR12: =IF($B$10="3BR_H", INDEX('ns-combined'!$C:$D,MATCH($L12,'ns-combined'!$B:$B,0),MATCH(Council_Area,'ns-combined'!$C$1:$D$1,0))*1000, INDEX('s-combined'!$C:$D,MATCH($L12,'s-combined'!$B:$B,0),MATCH(Council_Area,'s-combined'!$C$1:$D$1,0))*1000) -> 425000 | AS12: =AS11+$AS$3 -> 8125 | AT12: 0 | AU12: =SUM($B$28:$B$29)*AR12 -> 8500 | AV12: =AR12*$B$15/4 -> 1221.875 | AW12: =SUM($AV$3:AV12) -> 10682.062 | AX12: =AR12-AS12-AU12-AW12 -> 397692.94 | AY12: =$B$36*V12 -> 1274 | AZ12: =SUM(AY12:AY12)*4/AR12 -> 0.011990588 | BA12: =SUM(AY12:AY12)/V12 -> 0.35 | BB12: =IF(MortgageRate="Discounted",_xlfn.XLOOKUP(L12,'mortgage-rates'!$A:$A,'mortgage-rates'!$E:$E)/100,_xlfn.XLOOKUP(L12,'mortgage-rates'!$A:$A,'mortgage-rates'!$D:$D)/100) -> 0.0884 | BC12: =BC11-BF11 -> 251256.88 | BD12: =IF($B$16*12/3-Q12+1>0,-PMT($BB12/4,$B$16*12/3-Q12+1,BC12),0) -> 6432.8181 | BE12: =BC12*($BB12/4) -> 5552.7771 | BF12: =BD12-BE12 -> 880.04107 | BG12: =AT12+AY12+BD12 -> 7706.8181 | BH12: =INDEX(cpi!B:B,MATCH($L12,cpi!A:A)) -> 91.6 | BI12: =100*BH12/BH$3 -> 108.27423 | BJ12: =100*AC12/AC$3 -> 118.56173 | BK12: =100*AD12/AD$3 -> 123.59997 | BL12: =BJ12*GlobalPortfolio+BK12*AusPortfolio -> 120.07321 | BM12: =100*AE12/$AE$3 -> 157.73085 | BN12: =100*AR12/AR$3 -> 130.76923 | BO12: =100*AX12/AX$3 -> 125.55296
A13: Council/Area | B13: Brisbane | C13: Brisbane | L13: =DATE(YEAR(L12),MONTH(L12)+3,1) -> 39692 | M13: =AP13 -> 114190.82 | N13: =AX13-BC13 -> 130624.85 | O13: =M13/N13 -> 0.87418914 | P13: =X13/BG13 -> 0.49576292 | Q13: 11 | R13: =EOMONTH(L13,0)-EOMONTH(L13,-3) -> 92 | T13: =IF($B$10="3BR_H", INDEX('3BR_H-processed'!$E:$E,MATCH($L13,'3BR_H-processed'!$B:$B,0),MATCH(Council_Area,'3BR_H-processed'!$E$1:$E$1,0)), INDEX('2BR_F-processed'!$E:$E,MATCH($L13,'2BR_F-processed'!$B:$B,0),MATCH(Council_Area,'2BR_F-processed'!$E$1:$E$1,0))) -> 285 | U13: =IF(MOD(Q13,4)=1,T13,U12) -> 280 | V13: =U13*(R13)/7 -> 3680 | W13: =$B$53/4*BH13/_xlfn.XLOOKUP(Q_end,cpi!A:A,cpi!B:B) -> 127.98894 | X13: =V13+W13 -> 3807.9889 | Y13: =BG13-X13 -> 3873.0796 | Z13: =Y13*$B$47 -> 0 | AA13: {=(Y13+Z13)*eff_invest} -> 3873.0796 | AB13: =AA13*(_xlfn.XLOOKUP(Q_end,cpi!A:A,cpi!B:B)/BH13) -> 6052.2096 | AC13: {=INDEX('msci-indices'!C:C,MATCH($L13,'msci-indices'!$B:$B)-2)} -> 881.79174 | AD13: {=INDEX('msci-indices'!D:D,MATCH($L13,'msci-indices'!$B:$B)-2)} -> 867.41147 | AE13: =AI12+AA13 -> 132596.2 | AF13: {=INDEX('msci-indices'!C:C,MATCH($L13,'msci-indices'!$B:$B)+1)} -> 747.65998 | AG13: {=INDEX('msci-indices'!D:D,MATCH($L13,'msci-indices'!$B:$B)+1)} -> 775.74397 | AH13: =(InvestFees/4)*AE13 -> 82.872625 | AI13: =((AF13/AC13)*GlobalPortfolio+(AG13/AD13)*AusPortfolio)*AE13-AH13 -> 114190.82 | AJ13: =AJ12+AA13 -> 118946.35 | AK13: =AI13-AJ13 -> -4755.532 | AL13: =AJ13*(_xlfn.XLOOKUP(Q_end,cpi!A:A,cpi!B:B)/BH13) -> 185869.74 | AM13: {=SUMPRODUCT($AA$3:AA13,_xlfn.SORTBY($BH$3:BH13,_xlfn.SEQUENCE(ROWS($BH$3:BH13)),-1)/$BH$3)} -> 128094.47 | AN13: =AI13-AM13 -> -13903.649 | AO13: =IF($B$49="Real gains",MAX($B$50*AN13,0),IF($B$49="Discounted nominal gains",MAX($B$50*AK13/2,0),0)) -> 0 | AP13: =AI13-AO13 -> 114190.82 | AR13: =IF($B$10="3BR_H", INDEX('ns-combined'!$C:$D,MATCH($L13,'ns-combined'!$B:$B,0),MATCH(Council_Area,'ns-combined'!$C$1:$D$1,0))*1000, INDEX('s-combined'!$C:$D,MATCH($L13,'s-combined'!$B:$B,0),MATCH(Council_Area,'s-combined'!$C$1:$D$1,0))*1000) -> 410000 | AS13: =AS12+$AS$3 -> 8937.5 | AT13: 0 | AU13: =SUM($B$28:$B$29)*AR13 -> 8200 | AV13: =AR13*$B$15/4 -> 1178.75 | AW13: =SUM($AV$3:AV13) -> 11860.812 | AX13: =AR13-AS13-AU13-AW13 -> 381001.69 | AY13: =$B$36*V13 -> 1288 | AZ13: =SUM(AY13:AY13)*4/AR13 -> 0.012565854 | BA13: =SUM(AY13:AY13)/V13 -> 0.35 | BB13: =IF(MortgageRate="Discounted",_xlfn.XLOOKUP(L13,'mortgage-rates'!$A:$A,'mortgage-rates'!$E:$E)/100,_xlfn.XLOOKUP(L13,'mortgage-rates'!$A:$A,'mortgage-rates'!$D:$D)/100) -> 0.0876 | BC13: =BC12-BF12 -> 250376.84 | BD13: =IF($B$16*12/3-Q13+1>0,-PMT($BB13/4,$B$16*12/3-Q13+1,BC13),0) -> 6393.0685 | BE13: =BC13*($BB13/4) -> 5483.2528 | BF13: =BD13-BE13 -> 909.81572 | BG13: =AT13+AY13+BD13 -> 7681.0685 | BH13: =INDEX(cpi!B:B,MATCH($L13,cpi!A:A)) -> 92.6 | BI13: =100*BH13/BH$3 -> 109.45626 | BJ13: =100*AC13/AC$3 -> 116.81223 | BK13: =100*AD13/AD$3 -> 121.66405 | BL13: =BJ13*GlobalPortfolio+BK13*AusPortfolio -> 118.26778 | BM13: =100*AE13/$AE$3 -> 159.93347 | BN13: =100*AR13/AR$3 -> 126.15385 | BO13: =100*AX13/AX$3 -> 120.28348
A14: Depreciation (% of initial home value per year) | B14: 0.01 | C14: 0.01 | L14: =DATE(YEAR(L13),MONTH(L13)+3,1) -> 39783 | M14: =AP14 -> 92103.954 | N14: =AX14-BC14 -> 118795.04 | O14: =M14/N14 -> 0.77531819 | P14: =X14/BG14 -> 0.58820162 | Q14: 12 | R14: =EOMONTH(L14,0)-EOMONTH(L14,-3) -> 92 | T14: =IF($B$10="3BR_H", INDEX('3BR_H-processed'!$E:$E,MATCH($L14,'3BR_H-processed'!$B:$B,0),MATCH(Council_Area,'3BR_H-processed'!$E$1:$E$1,0)), INDEX('2BR_F-processed'!$E:$E,MATCH($L14,'2BR_F-processed'!$B:$B,0),MATCH(Council_Area,'2BR_F-processed'!$E$1:$E$1,0))) -> 300 | U14: =IF(MOD(Q14,4)=1,T14,U13) -> 280 | V14: =U14*(R14)/7 -> 3680 | W14: =$B$53/4*BH14/_xlfn.XLOOKUP(Q_end,cpi!A:A,cpi!B:B) -> 127.98894 | X14: =V14+W14 -> 3807.9889 | Y14: =BG14-X14 -> 2665.9629 | Z14: =Y14*$B$47 -> 0 | AA14: {=(Y14+Z14)*eff_invest} -> 2665.9629 | AB14: =AA14*(_xlfn.XLOOKUP(Q_end,cpi!A:A,cpi!B:B)/BH14) -> 4165.9269 | AC14: {=INDEX('msci-indices'!C:C,MATCH($L14,'msci-indices'!$B:$B)-2)} -> 747.65998 | AD14: {=INDEX('msci-indices'!D:D,MATCH($L14,'msci-indices'!$B:$B)-2)} -> 775.74397 | AE14: =AI13+AA14 -> 116856.79 | AF14: {=INDEX('msci-indices'!C:C,MATCH($L14,'msci-indices'!$B:$B)+1)} -> 582.01082 | AG14: {=INDEX('msci-indices'!D:D,MATCH($L14,'msci-indices'!$B:$B)+1)} -> 630.6613 | AH14: =(InvestFees/4)*AE14 -> 73.035491 | AI14: =((AF14/AC14)*GlobalPortfolio+(AG14/AD14)*AusPortfolio)*AE14-AH14 -> 92103.954 | AJ14: =AJ13+AA14 -> 121612.32 | AK14: =AI14-AJ14 -> -29508.363 | AL14: =AJ14*(_xlfn.XLOOKUP(Q_end,cpi!A:A,cpi!B:B)/BH14) -> 190035.66 | AM14: {=SUMPRODUCT($AA$3:AA14,_xlfn.SORTBY($BH$3:BH14,_xlfn.SEQUENCE(ROWS($BH$3:BH14)),-1)/$BH$3)} -> 131097.83 | AN14: =AI14-AM14 -> -38993.877 | AO14: =IF($B$49="Real gains",MAX($B$50*AN14,0),IF($B$49="Discounted nominal gains",MAX($B$50*AK14/2,0),0)) -> 0 | AP14: =AI14-AO14 -> 92103.954 | AR14: =IF($B$10="3BR_H", INDEX('ns-combined'!$C:$D,MATCH($L14,'ns-combined'!$B:$B,0),MATCH(Council_Area,'ns-combined'!$C$1:$D$1,0))*1000, INDEX('s-combined'!$C:$D,MATCH($L14,'s-combined'!$B:$B,0),MATCH(Council_Area,'s-combined'!$C$1:$D$1,0))*1000) -> 399000 | AS14: =AS13+$AS$3 -> 9750 | AT14: 0 | AU14: =SUM($B$28:$B$29)*AR14 -> 7980 | AV14: =AR14*$B$15/4 -> 1147.125 | AW14: =SUM($AV$3:AV14) -> 13007.938 | AX14: =AR14-AS14-AU14-AW14 -> 368262.06 | AY14: =$B$36*V14 -> 1288 | AZ14: =SUM(AY14:AY14)*4/AR14 -> 0.012912281 | BA14: =SUM(AY14:AY14)/V14 -> 0.35 | BB14: =IF(MortgageRate="Discounted",_xlfn.XLOOKUP(L14,'mortgage-rates'!$A:$A,'mortgage-rates'!$E:$E)/100,_xlfn.XLOOKUP(L14,'mortgage-rates'!$A:$A,'mortgage-rates'!$D:$D)/100) -> 0.062 | BC14: =BC13-BF13 -> 249467.02 | BD14: =IF($B$16*12/3-Q14+1>0,-PMT($BB14/4,$B$16*12/3-Q14+1,BC14),0) -> 5185.9518 | BE14: =BC14*($BB14/4) -> 3866.7389 | BF14: =BD14-BE14 -> 1319.213 | BG14: =AT14+AY14+BD14 -> 6473.9518 | BH14: =INDEX(cpi!B:B,MATCH($L14,cpi!A:A)) -> 92.6 | BI14: =100*BH14/BH$3 -> 109.45626 | BJ14: =100*AC14/AC$3 -> 99.043605 | BK14: =100*AD14/AD$3 -> 108.80667 | BL14: =BJ14*GlobalPortfolio+BK14*AusPortfolio -> 101.97253 | BM14: =100*AE14/$AE$3 -> 140.94907 | BN14: =100*AR14/AR$3 -> 122.76923 | BO14: =100*AX14/AX$3 -> 116.26154
A15: Renovations, alterations, and additions (% of current home value per year) | B15: 0.0115 | C15: 0.0115 | L15: =DATE(YEAR(L14),MONTH(L14)+3,1) -> 39873 | M15: =AP15 -> 85876.737 | N15: =AX15-BC15 -> 119131.75 | O15: =M15/N15 -> 0.72085515 | P15: =X15/BG15 -> 0.67830311 | Q15: 13 | R15: =EOMONTH(L15,0)-EOMONTH(L15,-3) -> 90 | T15: =IF($B$10="3BR_H", INDEX('3BR_H-processed'!$E:$E,MATCH($L15,'3BR_H-processed'!$B:$B,0),MATCH(Council_Area,'3BR_H-processed'!$E$1:$E$1,0)), INDEX('2BR_F-processed'!$E:$E,MATCH($L15,'2BR_F-processed'!$B:$B,0),MATCH(Council_Area,'2BR_F-processed'!$E$1:$E$1,0))) -> 315 | U15: =IF(MOD(Q15,4)=1,T15,U14) -> 315 | V15: =U15*(R15)/7 -> 4050 | W15: =$B$53/4*BH15/_xlfn.XLOOKUP(Q_end,cpi!A:A,cpi!B:B) -> 127.85073 | X15: =V15+W15 -> 4177.8507 | Y15: =BG15-X15 -> 1981.4174 | Z15: =Y15*$B$47 -> 0 | AA15: {=(Y15+Z15)*eff_invest} -> 1981.4174 | AB15: =AA15*(_xlfn.XLOOKUP(Q_end,cpi!A:A,cpi!B:B)/BH15) -> 3099.5795 | AC15: {=INDEX('msci-indices'!C:C,MATCH($L15,'msci-indices'!$B:$B)-2)} -> 582.01082 | AD15: {=INDEX('msci-indices'!D:D,MATCH($L15,'msci-indices'!$B:$B)-2)} -> 630.6613 | AE15: =AI14+AA15 -> 94085.371 | AF15: {=INDEX('msci-indices'!C:C,MATCH($L15,'msci-indices'!$B:$B)+1)} -> 513.55423 | AG15: {=INDEX('msci-indices'!D:D,MATCH($L15,'msci-indices'!$B:$B)+1)} -> 621.64895 | AH15: =(InvestFees/4)*AE15 -> 58.803357 | AI15: =((AF15/AC15)*GlobalPortfolio+(AG15/AD15)*AusPortfolio)*AE15-AH15 -> 85876.737 | AJ15: =AJ14+AA15 -> 123593.73 | AK15: =AI15-AJ15 -> -37716.998 | AL15: =AJ15*(_xlfn.XLOOKUP(Q_end,cpi!A:A,cpi!B:B)/BH15) -> 193340.69 | AM15: {=SUMPRODUCT($AA$3:AA15,_xlfn.SORTBY($BH$3:BH15,_xlfn.SEQUENCE(ROWS($BH$3:BH15)),-1)/$BH$3)} -> 133303.43 | AN15: =AI15-AM15 -> -47426.689 | AO15: =IF($B$49="Real gains",MAX($B$50*AN15,0),IF($B$49="Discounted nominal gains",MAX($B$50*AK15/2,0),0)) -> 0 | AP15: =AI15-AO15 -> 85876.737 | AR15: =IF($B$10="3BR_H", INDEX('ns-combined'!$C:$D,MATCH($L15,'ns-combined'!$B:$B,0),MATCH(Council_Area,'ns-combined'!$C$1:$D$1,0))*1000, INDEX('s-combined'!$C:$D,MATCH($L15,'s-combined'!$B:$B,0),MATCH(Council_Area,'s-combined'!$C$1:$D$1,0))*1000) -> 400000 | AS15: =AS14+$AS$3 -> 10562.5 | AT15: 0 | AU15: =SUM($B$28:$B$29)*AR15 -> 8000 | AV15: =AR15*$B$15/4 -> 1150 | AW15: =SUM($AV$3:AV15) -> 14157.938 | AX15: =AR15-AS15-AU15-AW15 -> 367279.56 | AY15: =$B$36*V15 -> 1417.5 | AZ15: =SUM(AY15:AY15)*4/AR15 -> 0.014175 | BA15: =SUM(AY15:AY15)/V15 -> 0.35 | BB15: =IF(MortgageRate="Discounted",_xlfn.XLOOKUP(L15,'mortgage-rates'!$A:$A,'mortgage-rates'!$E:$E)/100,_xlfn.XLOOKUP(L15,'mortgage-rates'!$A:$A,'mortgage-rates'!$D:$D)/100) -> 0.0518 | BC15: =BC14-BF14 -> 248147.81 | BD15: =IF($B$16*12/3-Q15+1>0,-PMT($BB15/4,$B$16*12/3-Q15+1,BC15),0) -> 4741.7682 | BE15: =BC15*($BB15/4) -> 3213.5142 | BF15: =BD15-BE15 -> 1528.254 | BG15: =AT15+AY15+BD15 -> 6159.2682 | BH15: =INDEX(cpi!B:B,MATCH($L15,cpi!A:A)) -> 92.5 | BI15: =100*BH15/BH$3 -> 109.33806 | BJ15: =100*AC15/AC$3 -> 77.099819 | BK15: =100*AD15/AD$3 -> 88.457223 | BL15: =BJ15*GlobalPortfolio+BK15*AusPortfolio -> 80.50704 | BM15: =100*AE15/$AE$3 -> 113.48289 | BN15: =100*AR15/AR$3 -> 123.07692 | BO15: =100*AX15/AX$3 -> 115.95136
A16: Loan term (years) | B16: 25 | C16: 25 | L16: =DATE(YEAR(L15),MONTH(L15)+3,1) -> 39965 | M16: =AP16 -> 104103.22 | N16: =AX16-BC16 -> 138240.01 | O16: =M16/N16 -> 0.75306143 | P16: =X16/BG16 -> 0.68584497 | Q16: 14 | R16: =EOMONTH(L16,0)-EOMONTH(L16,-3) -> 91 | T16: =IF($B$10="3BR_H", INDEX('3BR_H-processed'!$E:$E,MATCH($L16,'3BR_H-processed'!$B:$B,0),MATCH(Council_Area,'3BR_H-processed'!$E$1:$E$1,0)), INDEX('2BR_F-processed'!$E:$E,MATCH($L16,'2BR_F-processed'!$B:$B,0),MATCH(Council_Area,'2BR_F-processed'!$E$1:$E$1,0))) -> 315 | U16: =IF(MOD(Q16,4)=1,T16,U15) -> 315 | V16: =U16*(R16)/7 -> 4095 | W16: =$B$53/4*BH16/_xlfn.XLOOKUP(Q_end,cpi!A:A,cpi!B:B) -> 128.54181 | X16: =V16+W16 -> 4223.5418 | Y16: =BG16-X16 -> 1934.6164 | Z16: =Y16*$B$47 -> 0 | AA16: {=(Y16+Z16)*eff_invest} -> 1934.6164 | AB16: =AA16*(_xlfn.XLOOKUP(Q_end,cpi!A:A,cpi!B:B)/BH16) -> 3010.0967 | AC16: {=INDEX('msci-indices'!C:C,MATCH($L16,'msci-indices'!$B:$B)-2)} -> 513.55423 | AD16: {=INDEX('msci-indices'!D:D,MATCH($L16,'msci-indices'!$B:$B)-2)} -> 621.64895 | AE16: =AI15+AA16 -> 87811.353 | AF16: {=INDEX('msci-indices'!C:C,MATCH($L16,'msci-indices'!$B:$B)+1)} -> 624.35598 | AG16: {=INDEX('msci-indices'!D:D,MATCH($L16,'msci-indices'!$B:$B)+1)} -> 694.44245 | AH16: =(InvestFees/4)*AE16 -> 54.882096 | AI16: =((AF16/AC16)*GlobalPortfolio+(AG16/AD16)*AusPortfolio)*AE16-AH16 -> 104103.22 | AJ16: =AJ15+AA16 -> 125528.35 | AK16: =AI16-AJ16 -> -21425.135 | AL16: =AJ16*(_xlfn.XLOOKUP(Q_end,cpi!A:A,cpi!B:B)/BH16) -> 195311.32 | AM16: {=SUMPRODUCT($AA$3:AA16,_xlfn.SORTBY($BH$3:BH16,_xlfn.SEQUENCE(ROWS($BH$3:BH16)),-1)/$BH$3)} -> 136030.26 | AN16: =AI16-AM16 -> -31927.042 | AO16: =IF($B$49="Real gains",MAX($B$50*AN16,0),IF($B$49="Discounted nominal gains",MAX($B$50*AK16/2,0),0)) -> 0 | AP16: =AI16-AO16 -> 104103.22 | AR16: =IF($B$10="3BR_H", INDEX('ns-combined'!$C:$D,MATCH($L16,'ns-combined'!$B:$B,0),MATCH(Council_Area,'ns-combined'!$C$1:$D$1,0))*1000, INDEX('s-combined'!$C:$D,MATCH($L16,'s-combined'!$B:$B,0),MATCH(Council_Area,'s-combined'!$C$1:$D$1,0))*1000) -> 420000 | AS16: =AS15+$AS$3 -> 11375 | AT16: 0 | AU16: =SUM($B$28:$B$29)*AR16 -> 8400 | AV16: =AR16*$B$15/4 -> 1207.5 | AW16: =SUM($AV$3:AV16) -> 15365.438 | AX16: =AR16-AS16-AU16-AW16 -> 384859.56 | AY16: =$B$36*V16 -> 1433.25 | AZ16: =SUM(AY16:AY16)*4/AR16 -> 0.01365 | BA16: =SUM(AY16:AY16)/V16 -> 0.35 | BB16: =IF(MortgageRate="Discounted",_xlfn.XLOOKUP(L16,'mortgage-rates'!$A:$A,'mortgage-rates'!$E:$E)/100,_xlfn.XLOOKUP(L16,'mortgage-rates'!$A:$A,'mortgage-rates'!$D:$D)/100) -> 0.0514 | BC16: =BC15-BF15 -> 246619.56 | BD16: =IF($B$16*12/3-Q16+1>0,-PMT($BB16/4,$B$16*12/3-Q16+1,BC16),0) -> 4724.9082 | BE16: =BC16*($BB16/4) -> 3169.0613 | BF16: =BD16-BE16 -> 1555.8469 | BG16: =AT16+AY16+BD16 -> 6158.1582 | BH16: =INDEX(cpi!B:B,MATCH($L16,cpi!A:A)) -> 93 | BI16: =100*BH16/BH$3 -> 109.92908 | BJ16: =100*AC16/AC$3 -> 68.031276 | BK16: =100*AD16/AD$3 -> 87.193142 | BL16: =BJ16*GlobalPortfolio+BK16*AusPortfolio -> 73.779836 | BM16: =100*AE16/$AE$3 -> 105.91536 | BN16: =100*AR16/AR$3 -> 129.23077 | BO16: =100*AX16/AX$3 -> 121.50143
L17: =DATE(YEAR(L16),MONTH(L16)+3,1) -> 40057 | M17: =AP17 -> 126408.54 | N17: =AX17-BC17 -> 147547.1 | O17: =M17/N17 -> 0.85673344 | P17: =X17/BG17 -> 0.69154079 | Q17: 15 | R17: =EOMONTH(L17,0)-EOMONTH(L17,-3) -> 92 | T17: =IF($B$10="3BR_H", INDEX('3BR_H-processed'!$E:$E,MATCH($L17,'3BR_H-processed'!$B:$B,0),MATCH(Council_Area,'3BR_H-processed'!$E$1:$E$1,0)), INDEX('2BR_F-processed'!$E:$E,MATCH($L17,'2BR_F-processed'!$B:$B,0),MATCH(Council_Area,'2BR_F-processed'!$E$1:$E$1,0))) -> 325 | U17: =IF(MOD(Q17,4)=1,T17,U16) -> 315 | V17: =U17*(R17)/7 -> 4140 | W17: =$B$53/4*BH17/_xlfn.XLOOKUP(Q_end,cpi!A:A,cpi!B:B) -> 129.50933 | X17: =V17+W17 -> 4269.5093 | Y17: =BG17-X17 -> 1904.3989 | Z17: =Y17*$B$47 -> 0 | AA17: {=(Y17+Z17)*eff_invest} -> 1904.3989 | AB17: =AA17*(_xlfn.XLOOKUP(Q_end,cpi!A:A,cpi!B:B)/BH17) -> 2940.9447 | AC17: {=INDEX('msci-indices'!C:C,MATCH($L17,'msci-indices'!$B:$B)-2)} -> 624.35598 | AD17: {=INDEX('msci-indices'!D:D,MATCH($L17,'msci-indices'!$B:$B)-2)} -> 694.44245 | AE17: =AI16+AA17 -> 106007.61 | AF17: {=INDEX('msci-indices'!C:C,MATCH($L17,'msci-indices'!$B:$B)+1)} -> 736.86333 | AG17: {=INDEX('msci-indices'!D:D,MATCH($L17,'msci-indices'!$B:$B)+1)} -> 849.38296 | AH17: =(InvestFees/4)*AE17 -> 66.254759 | AI17: =((AF17/AC17)*GlobalPortfolio+(AG17/AD17)*AusPortfolio)*AE17-AH17 -> 126408.54 | AJ17: =AJ16+AA17 -> 127432.75 | AK17: =AI17-AJ17 -> -1024.2135 | AL17: =AJ17*(_xlfn.XLOOKUP(Q_end,cpi!A:A,cpi!B:B)/BH17) -> 196793.16 | AM17: {=SUMPRODUCT($AA$3:AA17,_xlfn.SORTBY($BH$3:BH17,_xlfn.SEQUENCE(ROWS($BH$3:BH17)),-1)/$BH$3)} -> 138938.04 | AN17: =AI17-AM17 -> -12529.506 | AO17: =IF($B$49="Real gains",MAX($B$50*AN17,0),IF($B$49="Discounted nominal gains",MAX($B$50*AK17/2,0),0)) -> 0 | AP17: =AI17-AO17 -> 126408.54 | AR17: =IF($B$10="3BR_H", INDEX('ns-combined'!$C:$D,MATCH($L17,'ns-combined'!$B:$B,0),MATCH(Council_Area,'ns-combined'!$C$1:$D$1,0))*1000, INDEX('s-combined'!$C:$D,MATCH($L17,'s-combined'!$B:$B,0),MATCH(Council_Area,'s-combined'!$C$1:$D$1,0))*1000) -> 430000 | AS17: =AS16+$AS$3 -> 12187.5 | AT17: 0 | AU17: =SUM($B$28:$B$29)*AR17 -> 8600 | AV17: =AR17*$B$15/4 -> 1236.25 | AW17: =SUM($AV$3:AV17) -> 16601.688 | AX17: =AR17-AS17-AU17-AW17 -> 392610.81 | AY17: =$B$36*V17 -> 1449 | AZ17: =SUM(AY17:AY17)*4/AR17 -> 0.01347907 | BA17: =SUM(AY17:AY17)/V17 -> 0.35 | BB17: =IF(MortgageRate="Discounted",_xlfn.XLOOKUP(L17,'mortgage-rates'!$A:$A,'mortgage-rates'!$E:$E)/100,_xlfn.XLOOKUP(L17,'mortgage-rates'!$A:$A,'mortgage-rates'!$D:$D)/100) -> 0.0514 | BC17: =BC16-BF16 -> 245063.71 | BD17: =IF($B$16*12/3-Q17+1>0,-PMT($BB17/4,$B$16*12/3-Q17+1,BC17),0) -> 4724.9082 | BE17: =BC17*($BB17/4) -> 3149.0687 | BF17: =BD17-BE17 -> 1575.8395 | BG17: =AT17+AY17+BD17 -> 6173.9082 | BH17: =INDEX(cpi!B:B,MATCH($L17,cpi!A:A)) -> 93.7 | BI17: =100*BH17/BH$3 -> 110.7565 | BJ17: =100*AC17/AC$3 -> 82.709345 | BK17: =100*AD17/AD$3 -> 97.403235 | BL17: =BJ17*GlobalPortfolio+BK17*AusPortfolio -> 87.117512 | BM17: =100*AE17/$AE$3 -> 127.86313 | BN17: =100*AR17/AR$3 -> 132.30769 | BO17: =100*AX17/AX$3 -> 123.94852
A18: Mortgage | L18: =DATE(YEAR(L17),MONTH(L17)+3,1) -> 40148 | M18: =AP18 -> 133440.04 | N18: =AX18-BC18 -> 171502.32 | O18: =M18/N18 -> 0.77806554 | P18: =X18/BG18 -> 0.65335632 | Q18: 16 | R18: =EOMONTH(L18,0)-EOMONTH(L18,-3) -> 92 | T18: =IF($B$10="3BR_H", INDEX('3BR_H-processed'!$E:$E,MATCH($L18,'3BR_H-processed'!$B:$B,0),MATCH(Council_Area,'3BR_H-processed'!$E$1:$E$1,0)), INDEX('2BR_F-processed'!$E:$E,MATCH($L18,'2BR_F-processed'!$B:$B,0),MATCH(Council_Area,'2BR_F-processed'!$E$1:$E$1,0))) -> 330 | U18: =IF(MOD(Q18,4)=1,T18,U17) -> 315 | V18: =U18*(R18)/7 -> 4140 | W18: =$B$53/4*BH18/_xlfn.XLOOKUP(Q_end,cpi!A:A,cpi!B:B) -> 130.61507 | X18: =V18+W18 -> 4270.6151 | Y18: =BG18-X18 -> 2265.8107 | Z18: =Y18*$B$47 -> 0 | AA18: {=(Y18+Z18)*eff_invest} -> 2265.8107 | AB18: =AA18*(_xlfn.XLOOKUP(Q_end,cpi!A:A,cpi!B:B)/BH18) -> 3469.4477 | AC18: {=INDEX('msci-indices'!C:C,MATCH($L18,'msci-indices'!$B:$B)-2)} -> 736.86333 | AD18: {=INDEX('msci-indices'!D:D,MATCH($L18,'msci-indices'!$B:$B)-2)} -> 849.38296 | AE18: =AI17+AA18 -> 128674.35 | AF18: {=INDEX('msci-indices'!C:C,MATCH($L18,'msci-indices'!$B:$B)+1)} -> 765.74116 | AG18: {=INDEX('msci-indices'!D:D,MATCH($L18,'msci-indices'!$B:$B)+1)} -> 878.3433 | AH18: =(InvestFees/4)*AE18 -> 80.421467 | AI18: =((AF18/AC18)*GlobalPortfolio+(AG18/AD18)*AusPortfolio)*AE18-AH18 -> 133440.04 | AJ18: =AJ17+AA18 -> 129698.56 | AK18: =AI18-AJ18 -> 3741.4819 | AL18: =AJ18*(_xlfn.XLOOKUP(Q_end,cpi!A:A,cpi!B:B)/BH18) -> 198596.63 | AM18: {=SUMPRODUCT($AA$3:AA18,_xlfn.SORTBY($BH$3:BH18,_xlfn.SEQUENCE(ROWS($BH$3:BH18)),-1)/$BH$3)} -> 142336.51 | AN18: =AI18-AM18 -> -8896.4693 | AO18: =IF($B$49="Real gains",MAX($B$50*AN18,0),IF($B$49="Discounted nominal gains",MAX($B$50*AK18/2,0),0)) -> 0 | AP18: =AI18-AO18 -> 133440.04 | AR18: =IF($B$10="3BR_H", INDEX('ns-combined'!$C:$D,MATCH($L18,'ns-combined'!$B:$B,0),MATCH(Council_Area,'ns-combined'!$C$1:$D$1,0))*1000, INDEX('s-combined'!$C:$D,MATCH($L18,'s-combined'!$B:$B,0),MATCH(Council_Area,'s-combined'!$C$1:$D$1,0))*1000) -> 455000 | AS18: =AS17+$AS$3 -> 13000 | AT18: 0 | AU18: =SUM($B$28:$B$29)*AR18 -> 9100 | AV18: =AR18*$B$15/4 -> 1308.125 | AW18: =SUM($AV$3:AV18) -> 17909.812 | AX18: =AR18-AS18-AU18-AW18 -> 414990.19 | AY18: =$B$36*V18 -> 1449 | AZ18: =SUM(AY18:AY18)*4/AR18 -> 0.012738462 | BA18: =SUM(AY18:AY18)/V18 -> 0.35 | BB18: =IF(MortgageRate="Discounted",_xlfn.XLOOKUP(L18,'mortgage-rates'!$A:$A,'mortgage-rates'!$E:$E)/100,_xlfn.XLOOKUP(L18,'mortgage-rates'!$A:$A,'mortgage-rates'!$D:$D)/100) -> 0.06 | BC18: =BC17-BF17 -> 243487.87 | BD18: =IF($B$16*12/3-Q18+1>0,-PMT($BB18/4,$B$16*12/3-Q18+1,BC18),0) -> 5087.4258 | BE18: =BC18*($BB18/4) -> 3652.3181 | BF18: =BD18-BE18 -> 1435.1077 | BG18: =AT18+AY18+BD18 -> 6536.4258 | BH18: =INDEX(cpi!B:B,MATCH($L18,cpi!A:A)) -> 94.5 | BI18: =100*BH18/BH$3 -> 111.70213 | BJ18: =100*AC18/AC$3 -> 97.613357 | BK18: =100*AD18/AD$3 -> 119.13536 | BL18: =BJ18*GlobalPortfolio+BK18*AusPortfolio -> 104.06996 | BM18: =100*AE18/$AE$3 -> 155.20305 | BN18: =100*AR18/AR$3 -> 140 | BO18: =100*AX18/AX$3 -> 131.01376
A19: Mortgage rates (Standard/Discounted) | B19: Discounted | C19: Discounted | L19: =DATE(YEAR(L18),MONTH(L18)+3,1) -> 40238 | M19: =AP19 -> 139780.98 | N19: =AX19-BC19 -> 175702.42 | O19: =M19/N19 -> 0.79555524 | P19: =X19/BG19 -> 0.68419557 | Q19: 17 | R19: =EOMONTH(L19,0)-EOMONTH(L19,-3) -> 90 | T19: =IF($B$10="3BR_H", INDEX('3BR_H-processed'!$E:$E,MATCH($L19,'3BR_H-processed'!$B:$B,0),MATCH(Council_Area,'3BR_H-processed'!$E$1:$E$1,0)), INDEX('2BR_F-processed'!$E:$E,MATCH($L19,'2BR_F-processed'!$B:$B,0),MATCH(Council_Area,'2BR_F-processed'!$E$1:$E$1,0))) -> 350 | U19: =IF(MOD(Q19,4)=1,T19,U18) -> 350 | V19: =U19*(R19)/7 -> 4500 | W19: =$B$53/4*BH19/_xlfn.XLOOKUP(Q_end,cpi!A:A,cpi!B:B) -> 131.58258 | X19: =V19+W19 -> 4631.5826 | Y19: =BG19-X19 -> 2137.8014 | Z19: =Y19*$B$47 -> 0 | AA19: {=(Y19+Z19)*eff_invest} -> 2137.8014 | AB19: =AA19*(_xlfn.XLOOKUP(Q_end,cpi!A:A,cpi!B:B)/BH19) -> 3249.3684 | AC19: {=INDEX('msci-indices'!C:C,MATCH($L19,'msci-indices'!$B:$B)-2)} -> 765.74116 | AD19: {=INDEX('msci-indices'!D:D,MATCH($L19,'msci-indices'!$B:$B)-2)} -> 878.3433 | AE19: =AI18+AA19 -> 135577.84 | AF19: {=INDEX('msci-indices'!C:C,MATCH($L19,'msci-indices'!$B:$B)+1)} -> 794.63718 | AG19: {=INDEX('msci-indices'!D:D,MATCH($L19,'msci-indices'!$B:$B)+1)} -> 893.60148 | AH19: =(InvestFees/4)*AE19 -> 84.736153 | AI19: =((AF19/AC19)*GlobalPortfolio+(AG19/AD19)*AusPortfolio)*AE19-AH19 -> 139780.98 | AJ19: =AJ18+AA19 -> 131836.36 | AK19: =AI19-AJ19 -> 7944.6214 | AL19: =AJ19*(_xlfn.XLOOKUP(Q_end,cpi!A:A,cpi!B:B)/BH19) -> 200385.73 | AM19: {=SUMPRODUCT($AA$3:AA19,_xlfn.SORTBY($BH$3:BH19,_xlfn.SEQUENCE(ROWS($BH$3:BH19)),-1)/$BH$3)} -> 145539.14 | AN19: =AI19-AM19 -> -5758.1546 | AO19: =IF($B$49="Real gains",MAX($B$50*AN19,0),IF($B$49="Discounted nominal gains",MAX($B$50*AK19/2,0),0)) -> 0 | AP19: =AI19-AO19 -> 139780.98 | AR19: =IF($B$10="3BR_H", INDEX('ns-combined'!$C:$D,MATCH($L19,'ns-combined'!$B:$B,0),MATCH(Council_Area,'ns-combined'!$C$1:$D$1,0))*1000, INDEX('s-combined'!$C:$D,MATCH($L19,'s-combined'!$B:$B,0),MATCH(Council_Area,'s-combined'!$C$1:$D$1,0))*1000) -> 460000 | AS19: =AS18+$AS$3 -> 13812.5 | AT19: 0 | AU19: =SUM($B$28:$B$29)*AR19 -> 9200 | AV19: =AR19*$B$15/4 -> 1322.5 | AW19: =SUM($AV$3:AV19) -> 19232.312 | AX19: =AR19-AS19-AU19-AW19 -> 417755.19 | AY19: =$B$36*V19 -> 1575 | AZ19: =SUM(AY19:AY19)*4/AR19 -> 0.013695652 | BA19: =SUM(AY19:AY19)/V19 -> 0.35 | BB19: =IF(MortgageRate="Discounted",_xlfn.XLOOKUP(L19,'mortgage-rates'!$A:$A,'mortgage-rates'!$E:$E)/100,_xlfn.XLOOKUP(L19,'mortgage-rates'!$A:$A,'mortgage-rates'!$D:$D)/100) -> 0.0625 | BC19: =BC18-BF18 -> 242052.76 | BD19: =IF($B$16*12/3-Q19+1>0,-PMT($BB19/4,$B$16*12/3-Q19+1,BC19),0) -> 5194.384 | BE19: =BC19*($BB19/4) -> 3782.0744 | BF19: =BD19-BE19 -> 1412.3096 | BG19: =AT19+AY19+BD19 -> 6769.384 | BH19: =INDEX(cpi!B:B,MATCH($L19,cpi!A:A)) -> 95.2 | BI19: =100*BH19/BH$3 -> 112.52955 | BJ19: =100*AC19/AC$3 -> 101.43885 | BK19: =100*AD19/AD$3 -> 123.19736 | BL19: =BJ19*GlobalPortfolio+BK19*AusPortfolio -> 107.9664 | BM19: =100*AE19/$AE$3 -> 163.52983 | BN19: =100*AR19/AR$3 -> 141.53846 | BO19: =100*AX19/AX$3 -> 131.88668
A20: Deposit (% of home purchase price) | B20: 0.2 | C20: 0.2 | L20: =DATE(YEAR(L19),MONTH(L19)+3,1) -> 40330 | M20: =AP20 -> 124590.84 | N20: =AX20-BC20 -> 179865.36 | O20: =M20/N20 -> 0.69268946 | P20: =X20/BG20 -> 0.66871074 | Q20: 18 | R20: =EOMONTH(L20,0)-EOMONTH(L20,-3) -> 91 | T20: =IF($B$10="3BR_H", INDEX('3BR_H-processed'!$E:$E,MATCH($L20,'3BR_H-processed'!$B:$B,0),MATCH(Council_Area,'3BR_H-processed'!$E$1:$E$1,0)), INDEX('2BR_F-processed'!$E:$E,MATCH($L20,'2BR_F-processed'!$B:$B,0),MATCH(Council_Area,'2BR_F-processed'!$E$1:$E$1,0))) -> 350 | U20: =IF(MOD(Q20,4)=1,T20,U19) -> 350 | V20: =U20*(R20)/7 -> 4550 | W20: =$B$53/4*BH20/_xlfn.XLOOKUP(Q_end,cpi!A:A,cpi!B:B) -> 132.41189 | X20: =V20+W20 -> 4682.4119 | Y20: =BG20-X20 -> 2319.7366 | Z20: =Y20*$B$47 -> 0 | AA20: {=(Y20+Z20)*eff_invest} -> 2319.7366 | AB20: =AA20*(_xlfn.XLOOKUP(Q_end,cpi!A:A,cpi!B:B)/BH20) -> 3503.8193 | AC20: {=INDEX('msci-indices'!C:C,MATCH($L20,'msci-indices'!$B:$B)-2)} -> 794.63718 | AD20: {=INDEX('msci-indices'!D:D,MATCH($L20,'msci-indices'!$B:$B)-2)} -> 893.60148 | AE20: =AI19+AA20 -> 142100.72 | AF20: {=INDEX('msci-indices'!C:C,MATCH($L20,'msci-indices'!$B:$B)+1)} -> 696.18018 | AG20: {=INDEX('msci-indices'!D:D,MATCH($L20,'msci-indices'!$B:$B)+1)} -> 786.77037 | AH20: =(InvestFees/4)*AE20 -> 88.81295 | AI20: =((AF20/AC20)*GlobalPortfolio+(AG20/AD20)*AusPortfolio)*AE20-AH20 -> 124590.84 | AJ20: =AJ19+AA20 -> 134156.1 | AK20: =AI20-AJ20 -> -9565.2611 | AL20: =AJ20*(_xlfn.XLOOKUP(Q_end,cpi!A:A,cpi!B:B)/BH20) -> 202634.53 | AM20: {=SUMPRODUCT($AA$3:AA20,_xlfn.SORTBY($BH$3:BH20,_xlfn.SEQUENCE(ROWS($BH$3:BH20)),-1)/$BH$3)} -> 148844.98 | AN20: =AI20-AM20 -> -24254.145 | AO20: =IF($B$49="Real gains",MAX($B$50*AN20,0),IF($B$49="Discounted nominal gains",MAX($B$50*AK20/2,0),0)) -> 0 | AP20: =AI20-AO20 -> 124590.84 | AR20: =IF($B$10="3BR_H", INDEX('ns-combined'!$C:$D,MATCH($L20,'ns-combined'!$B:$B,0),MATCH(Council_Area,'ns-combined'!$C$1:$D$1,0))*1000, INDEX('s-combined'!$C:$D,MATCH($L20,'s-combined'!$B:$B,0),MATCH(Council_Area,'s-combined'!$C$1:$D$1,0))*1000) -> 465000 | AS20: =AS19+$AS$3 -> 14625 | AT20: 0 | AU20: =SUM($B$28:$B$29)*AR20 -> 9300 | AV20: =AR20*$B$15/4 -> 1336.875 | AW20: =SUM($AV$3:AV20) -> 20569.188 | AX20: =AR20-AS20-AU20-AW20 -> 420505.81 | AY20: =$B$36*V20 -> 1592.5 | AZ20: =SUM(AY20:AY20)*4/AR20 -> 0.013698925 | BA20: =SUM(AY20:AY20)/V20 -> 0.35 | BB20: =IF(MortgageRate="Discounted",_xlfn.XLOOKUP(L20,'mortgage-rates'!$A:$A,'mortgage-rates'!$E:$E)/100,_xlfn.XLOOKUP(L20,'mortgage-rates'!$A:$A,'mortgage-rates'!$D:$D)/100) -> 0.0675 | BC20: =BC19-BF19 -> 240640.45 | BD20: =IF($B$16*12/3-Q20+1>0,-PMT($BB20/4,$B$16*12/3-Q20+1,BC20),0) -> 5409.6485 | BE20: =BC20*($BB20/4) -> 4060.8077 | BF20: =BD20-BE20 -> 1348.8409 | BG20: =AT20+AY20+BD20 -> 7002.1485 | BH20: =INDEX(cpi!B:B,MATCH($L20,cpi!A:A)) -> 95.8 | BI20: =100*BH20/BH$3 -> 113.23877 | BJ20: =100*AC20/AC$3 -> 105.26674 | BK20: =100*AD20/AD$3 -> 125.33749 | BL20: =BJ20*GlobalPortfolio+BK20*AusPortfolio -> 111.28797 | BM20: =100*AE20/$AE$3 -> 171.39753 | BN20: =100*AR20/AR$3 -> 143.07692 | BO20: =100*AX20/AX$3 -> 132.75506
A21: Lenders' mortgage insurance (% of home purchase price) | B21: 0 | C21: 0 | L21: =DATE(YEAR(L20),MONTH(L20)+3,1) -> 40422 | M21: =AP21 -> 142478.85 | N21: =AX21-BC21 -> 174179.2 | O21: =M21/N21 -> 0.8180015 | P21: =X21/BG21 -> 0.67428464 | Q21: 19 | R21: =EOMONTH(L21,0)-EOMONTH(L21,-3) -> 92 | T21: =IF($B$10="3BR_H", INDEX('3BR_H-processed'!$E:$E,MATCH($L21,'3BR_H-processed'!$B:$B,0),MATCH(Council_Area,'3BR_H-processed'!$E$1:$E$1,0)), INDEX('2BR_F-processed'!$E:$E,MATCH($L21,'2BR_F-processed'!$B:$B,0),MATCH(Council_Area,'2BR_F-processed'!$E$1:$E$1,0))) -> 360 | U21: =IF(MOD(Q21,4)=1,T21,U20) -> 350 | V21: =U21*(R21)/7 -> 4600 | W21: =$B$53/4*BH21/_xlfn.XLOOKUP(Q_end,cpi!A:A,cpi!B:B) -> 133.24119 | X21: =V21+W21 -> 4733.2412 | Y21: =BG21-X21 -> 2286.4073 | Z21: =Y21*$B$47 -> 0 | AA21: {=(Y21+Z21)*eff_invest} -> 2286.4073 | AB21: =AA21*(_xlfn.XLOOKUP(Q_end,cpi!A:A,cpi!B:B)/BH21) -> 3431.9828 | AC21: {=INDEX('msci-indices'!C:C,MATCH($L21,'msci-indices'!$B:$B)-2)} -> 696.18018 | AD21: {=INDEX('msci-indices'!D:D,MATCH($L21,'msci-indices'!$B:$B)-2)} -> 786.77037 | AE21: =AI20+AA21 -> 126877.25 | AF21: {=INDEX('msci-indices'!C:C,MATCH($L21,'msci-indices'!$B:$B)+1)} -> 792.86986 | AG21: {=INDEX('msci-indices'!D:D,MATCH($L21,'msci-indices'!$B:$B)+1)} -> 855.9299 | AH21: =(InvestFees/4)*AE21 -> 79.298278 | AI21: =((AF21/AC21)*GlobalPortfolio+(AG21/AD21)*AusPortfolio)*AE21-AH21 -> 142478.85 | AJ21: =AJ20+AA21 -> 136442.51 | AK21: =AI21-AJ21 -> 6036.3412 | AL21: =AJ21*(_xlfn.XLOOKUP(Q_end,cpi!A:A,cpi!B:B)/BH21) -> 204805.3 | AM21: {=SUMPRODUCT($AA$3:AA21,_xlfn.SORTBY($BH$3:BH21,_xlfn.SEQUENCE(ROWS($BH$3:BH21)),-1)/$BH$3)} -> 152126.64 | AN21: =AI21-AM21 -> -9647.7962 | AO21: =IF($B$49="Real gains",MAX($B$50*AN21,0),IF($B$49="Discounted nominal gains",MAX($B$50*AK21/2,0),0)) -> 0 | AP21: =AI21-AO21 -> 142478.85 | AR21: =IF($B$10="3BR_H", INDEX('ns-combined'!$C:$D,MATCH($L21,'ns-combined'!$B:$B,0),MATCH(Council_Area,'ns-combined'!$C$1:$D$1,0))*1000, INDEX('s-combined'!$C:$D,MATCH($L21,'s-combined'!$B:$B,0),MATCH(Council_Area,'s-combined'!$C$1:$D$1,0))*1000) -> 460000 | AS21: =AS20+$AS$3 -> 15437.5 | AT21: 0 | AU21: =SUM($B$28:$B$29)*AR21 -> 9200 | AV21: =AR21*$B$15/4 -> 1322.5 | AW21: =SUM($AV$3:AV21) -> 21891.688 | AX21: =AR21-AS21-AU21-AW21 -> 413470.81 | AY21: =$B$36*V21 -> 1610 | AZ21: =SUM(AY21:AY21)*4/AR21 -> 0.014 | BA21: =SUM(AY21:AY21)/V21 -> 0.35 | BB21: =IF(MortgageRate="Discounted",_xlfn.XLOOKUP(L21,'mortgage-rates'!$A:$A,'mortgage-rates'!$E:$E)/100,_xlfn.XLOOKUP(L21,'mortgage-rates'!$A:$A,'mortgage-rates'!$D:$D)/100) -> 0.0675 | BC21: =BC20-BF20 -> 239291.61 | BD21: =IF($B$16*12/3-Q21+1>0,-PMT($BB21/4,$B$16*12/3-Q21+1,BC21),0) -> 5409.6485 | BE21: =BC21*($BB21/4) -> 4038.046 | BF21: =BD21-BE21 -> 1371.6026 | BG21: =AT21+AY21+BD21 -> 7019.6485 | BH21: =INDEX(cpi!B:B,MATCH($L21,cpi!A:A)) -> 96.4 | BI21: =100*BH21/BH$3 -> 113.94799 | BJ21: =100*AC21/AC$3 -> 92.224001 | BK21: =100*AD21/AD$3 -> 110.35325 | BL21: =BJ21*GlobalPortfolio+BK21*AusPortfolio -> 97.662775 | BM21: =100*AE21/$AE$3 -> 153.03544 | BN21: =100*AR21/AR$3 -> 141.53846 | BO21: =100*AX21/AX$3 -> 130.53409
L22: =DATE(YEAR(L21),MONTH(L21)+3,1) -> 40513 | M22: =AP22 -> 156613.73 | N22: =AX22-BC22 -> 173415.8 | O22: =M22/N22 -> 0.90311109 | P22: =X22/BG22 -> 0.65825741 | Q22: 20 | R22: =EOMONTH(L22,0)-EOMONTH(L22,-3) -> 92 | T22: =IF($B$10="3BR_H", INDEX('3BR_H-processed'!$E:$E,MATCH($L22,'3BR_H-processed'!$B:$B,0),MATCH(Council_Area,'3BR_H-processed'!$E$1:$E$1,0)), INDEX('2BR_F-processed'!$E:$E,MATCH($L22,'2BR_F-processed'!$B:$B,0),MATCH(Council_Area,'2BR_F-processed'!$E$1:$E$1,0))) -> 360 | U22: =IF(MOD(Q22,4)=1,T22,U21) -> 350 | V22: =U22*(R22)/7 -> 4600 | W22: =$B$53/4*BH22/_xlfn.XLOOKUP(Q_end,cpi!A:A,cpi!B:B) -> 134.07049 | X22: =V22+W22 -> 4734.0705 | Y22: =BG22-X22 -> 2457.7521 | Z22: =Y22*$B$47 -> 0 | AA22: {=(Y22+Z22)*eff_invest} -> 2457.7521 | AB22: =AA22*(_xlfn.XLOOKUP(Q_end,cpi!A:A,cpi!B:B)/BH22) -> 3666.358 | AC22: {=INDEX('msci-indices'!C:C,MATCH($L22,'msci-indices'!$B:$B)-2)} -> 792.86986 | AD22: {=INDEX('msci-indices'!D:D,MATCH($L22,'msci-indices'!$B:$B)-2)} -> 855.9299 | AE22: =AI21+AA22 -> 144936.6 | AF22: {=INDEX('msci-indices'!C:C,MATCH($L22,'msci-indices'!$B:$B)+1)} -> 869.42368 | AG22: {=INDEX('msci-indices'!D:D,MATCH($L22,'msci-indices'!$B:$B)+1)} -> 894.74694 | AH22: =(InvestFees/4)*AE22 -> 90.585375 | AI22: =((AF22/AC22)*GlobalPortfolio+(AG22/AD22)*AusPortfolio)*AE22-AH22 -> 156613.73 | AJ22: =AJ21+AA22 -> 138900.26 | AK22: =AI22-AJ22 -> 17713.475 | AL22: =AJ22*(_xlfn.XLOOKUP(Q_end,cpi!A:A,cpi!B:B)/BH22) -> 207204.82 | AM22: {=SUMPRODUCT($AA$3:AA22,_xlfn.SORTBY($BH$3:BH22,_xlfn.SEQUENCE(ROWS($BH$3:BH22)),-1)/$BH$3)} -> 155579.86 | AN22: =AI22-AM22 -> 1033.8765 | AO22: =IF($B$49="Real gains",MAX($B$50*AN22,0),IF($B$49="Discounted nominal gains",MAX($B$50*AK22/2,0),0)) -> 0 | AP22: =AI22-AO22 -> 156613.73 | AR22: =IF($B$10="3BR_H", INDEX('ns-combined'!$C:$D,MATCH($L22,'ns-combined'!$B:$B,0),MATCH(Council_Area,'ns-combined'!$C$1:$D$1,0))*1000, INDEX('s-combined'!$C:$D,MATCH($L22,'s-combined'!$B:$B,0),MATCH(Council_Area,'s-combined'!$C$1:$D$1,0))*1000) -> 460000 | AS22: =AS21+$AS$3 -> 16250 | AT22: 0 | AU22: =SUM($B$28:$B$29)*AR22 -> 9200 | AV22: =AR22*$B$15/4 -> 1322.5 | AW22: =SUM($AV$3:AV22) -> 23214.188 | AX22: =AR22-AS22-AU22-AW22 -> 411335.81 | AY22: =$B$36*V22 -> 1610 | AZ22: =SUM(AY22:AY22)*4/AR22 -> 0.014 | BA22: =SUM(AY22:AY22)/V22 -> 0.35 | BB22: =IF(MortgageRate="Discounted",_xlfn.XLOOKUP(L22,'mortgage-rates'!$A:$A,'mortgage-rates'!$E:$E)/100,_xlfn.XLOOKUP(L22,'mortgage-rates'!$A:$A,'mortgage-rates'!$D:$D)/100) -> 0.0715 | BC22: =BC21-BF21 -> 237920.01 | BD22: =IF($B$16*12/3-Q22+1>0,-PMT($BB22/4,$B$16*12/3-Q22+1,BC22),0) -> 5581.8225 | BE22: =BC22*($BB22/4) -> 4252.8202 | BF22: =BD22-BE22 -> 1329.0024 | BG22: =AT22+AY22+BD22 -> 7191.8225 | BH22: =INDEX(cpi!B:B,MATCH($L22,cpi!A:A)) -> 97 | BI22: =100*BH22/BH$3 -> 114.65721 | BJ22: =100*AC22/AC$3 -> 105.03262 | BK22: =100*AD22/AD$3 -> 120.05364 | BL22: =BJ22*GlobalPortfolio+BK22*AusPortfolio -> 109.53893 | BM22: =100*AE22/$AE$3 -> 174.81808 | BN22: =100*AR22/AR$3 -> 141.53846 | BO22: =100*AX22/AX$3 -> 129.86006
A23: Home transaction costs (% of home value) | L23: =DATE(YEAR(L22),MONTH(L22)+3,1) -> 40603 | M23: =AP23 -> 165997.14 | N23: =AX23-BC23 -> 162838.55 | O23: =M23/N23 -> 1.019397 | P23: =X23/BG23 -> 0.67681761 | Q23: 21 | R23: =EOMONTH(L23,0)-EOMONTH(L23,-3) -> 90 | T23: =IF($B$10="3BR_H", INDEX('3BR_H-processed'!$E:$E,MATCH($L23,'3BR_H-processed'!$B:$B,0),MATCH(Council_Area,'3BR_H-processed'!$E$1:$E$1,0)), INDEX('2BR_F-processed'!$E:$E,MATCH($L23,'2BR_F-processed'!$B:$B,0),MATCH(Council_Area,'2BR_F-processed'!$E$1:$E$1,0))) -> 370 | U23: =IF(MOD(Q23,4)=1,T23,U22) -> 370 | V23: =U23*(R23)/7 -> 4757.1429 | W23: =$B$53/4*BH23/_xlfn.XLOOKUP(Q_end,cpi!A:A,cpi!B:B) -> 136.00553 | X23: =V23+W23 -> 4893.1484 | Y23: =BG23-X23 -> 2336.4927 | Z23: =Y23*$B$47 -> 0 | AA23: {=(Y23+Z23)*eff_invest} -> 2336.4927 | AB23: =AA23*(_xlfn.XLOOKUP(Q_end,cpi!A:A,cpi!B:B)/BH23) -> 3435.879 | AC23: {=INDEX('msci-indices'!C:C,MATCH($L23,'msci-indices'!$B:$B)-2)} -> 869.42368 | AD23: {=INDEX('msci-indices'!D:D,MATCH($L23,'msci-indices'!$B:$B)-2)} -> 894.74694 | AE23: =AI22+AA23 -> 158950.23 | AF23: {=INDEX('msci-indices'!C:C,MATCH($L23,'msci-indices'!$B:$B)+1)} -> 912.83804 | AG23: {=INDEX('msci-indices'!D:D,MATCH($L23,'msci-indices'!$B:$B)+1)} -> 924.58629 | AH23: =(InvestFees/4)*AE23 -> 99.343892 | AI23: =((AF23/AC23)*GlobalPortfolio+(AG23/AD23)*AusPortfolio)*AE23-AH23 -> 165997.14 | AJ23: =AJ22+AA23 -> 141236.75 | AK23: =AI23-AJ23 -> 24760.39 | AL23: =AJ23*(_xlfn.XLOOKUP(Q_end,cpi!A:A,cpi!B:B)/BH23) -> 207692.66 | AM23: {=SUMPRODUCT($AA$3:AA23,_xlfn.SORTBY($BH$3:BH23,_xlfn.SEQUENCE(ROWS($BH$3:BH23)),-1)/$BH$3)} -> 159700.54 | AN23: =AI23-AM23 -> 6296.6035 | AO23: =IF($B$49="Real gains",MAX($B$50*AN23,0),IF($B$49="Discounted nominal gains",MAX($B$50*AK23/2,0),0)) -> 0 | AP23: =AI23-AO23 -> 165997.14 | AR23: =IF($B$10="3BR_H", INDEX('ns-combined'!$C:$D,MATCH($L23,'ns-combined'!$B:$B,0),MATCH(Council_Area,'ns-combined'!$C$1:$D$1,0))*1000, INDEX('s-combined'!$C:$D,MATCH($L23,'s-combined'!$B:$B,0),MATCH(Council_Area,'s-combined'!$C$1:$D$1,0))*1000) -> 450000 | AS23: =AS22+$AS$3 -> 17062.5 | AT23: 0 | AU23: =SUM($B$28:$B$29)*AR23 -> 9000 | AV23: =AR23*$B$15/4 -> 1293.75 | AW23: =SUM($AV$3:AV23) -> 24507.938 | AX23: =AR23-AS23-AU23-AW23 -> 399429.56 | AY23: =$B$36*V23 -> 1665 | AZ23: =SUM(AY23:AY23)*4/AR23 -> 0.0148 | BA23: =SUM(AY23:AY23)/V23 -> 0.35 | BB23: =IF(MortgageRate="Discounted",_xlfn.XLOOKUP(L23,'mortgage-rates'!$A:$A,'mortgage-rates'!$E:$E)/100,_xlfn.XLOOKUP(L23,'mortgage-rates'!$A:$A,'mortgage-rates'!$D:$D)/100) -> 0.0711 | BC23: =BC22-BF22 -> 236591.01 | BD23: =IF($B$16*12/3-Q23+1>0,-PMT($BB23/4,$B$16*12/3-Q23+1,BC23),0) -> 5564.6411 | BE23: =BC23*($BB23/4) -> 4205.4052 | BF23: =BD23-BE23 -> 1359.2359 | BG23: =AT23+AY23+BD23 -> 7229.6411 | BH23: =INDEX(cpi!B:B,MATCH($L23,cpi!A:A)) -> 98.4 | BI23: =100*BH23/BH$3 -> 116.31206 | BJ23: =100*AC23/AC$3 -> 115.17382 | BK23: =100*AD23/AD$3 -> 125.49816 | BL23: =BJ23*GlobalPortfolio+BK23*AusPortfolio -> 118.27112 | BM23: =100*AE23/$AE$3 -> 191.72088 | BN23: =100*AR23/AR$3 -> 138.46154 | BO23: =100*AX23/AX$3 -> 126.10122
A24: When buying the house (cashflow costs) | L24: =DATE(YEAR(L23),MONTH(L23)+3,1) -> 40695 | M24: =AP24 -> 166337.03 | N24: =AX24-BC24 -> 154274.54 | O24: =M24/N24 -> 1.0781885 | P24: =X24/BG24 -> 0.68536625 | Q24: 22 | R24: =EOMONTH(L24,0)-EOMONTH(L24,-3) -> 91 | T24: =IF($B$10="3BR_H", INDEX('3BR_H-processed'!$E:$E,MATCH($L24,'3BR_H-processed'!$B:$B,0),MATCH(Council_Area,'3BR_H-processed'!$E$1:$E$1,0)), INDEX('2BR_F-processed'!$E:$E,MATCH($L24,'2BR_F-processed'!$B:$B,0),MATCH(Council_Area,'2BR_F-processed'!$E$1:$E$1,0))) -> 368.02415 | U24: =IF(MOD(Q24,4)=1,T24,U23) -> 370 | V24: =U24*(R24)/7 -> 4810 | W24: =$B$53/4*BH24/_xlfn.XLOOKUP(Q_end,cpi!A:A,cpi!B:B) -> 137.24948 | X24: =V24+W24 -> 4947.2495 | Y24: =BG24-X24 -> 2271.1531 | Z24: =Y24*$B$47 -> 0 | AA24: {=(Y24+Z24)*eff_invest} -> 2271.1531 | AB24: =AA24*(_xlfn.XLOOKUP(Q_end,cpi!A:A,cpi!B:B)/BH24) -> 3309.5252 | AC24: {=INDEX('msci-indices'!C:C,MATCH($L24,'msci-indices'!$B:$B)-2)} -> 912.83804 | AD24: {=INDEX('msci-indices'!D:D,MATCH($L24,'msci-indices'!$B:$B)-2)} -> 924.58629 | AE24: =AI23+AA24 -> 168268.29 | AF24: {=INDEX('msci-indices'!C:C,MATCH($L24,'msci-indices'!$B:$B)+1)} -> 915.80494 | AG24: {=INDEX('msci-indices'!D:D,MATCH($L24,'msci-indices'!$B:$B)+1)} -> 884.12823 | AH24: =(InvestFees/4)*AE24 -> 105.16768 | AI24: =((AF24/AC24)*GlobalPortfolio+(AG24/AD24)*AusPortfolio)*AE24-AH24 -> 166337.03 | AJ24: =AJ23+AA24 -> 143507.9 | AK24: =AI24-AJ24 -> 22829.13 | AL24: =AJ24*(_xlfn.XLOOKUP(Q_end,cpi!A:A,cpi!B:B)/BH24) -> 209119.78 | AM24: {=SUMPRODUCT($AA$3:AA24,_xlfn.SORTBY($BH$3:BH24,_xlfn.SEQUENCE(ROWS($BH$3:BH24)),-1)/$BH$3)} -> 163299.72 | AN24: =AI24-AM24 -> 3037.3189 | AO24: =IF($B$49="Real gains",MAX($B$50*AN24,0),IF($B$49="Discounted nominal gains",MAX($B$50*AK24/2,0),0)) -> 0 | AP24: =AI24-AO24 -> 166337.03 | AR24: =IF($B$10="3BR_H", INDEX('ns-combined'!$C:$D,MATCH($L24,'ns-combined'!$B:$B,0),MATCH(Council_Area,'ns-combined'!$C$1:$D$1,0))*1000, INDEX('s-combined'!$C:$D,MATCH($L24,'s-combined'!$B:$B,0),MATCH(Council_Area,'s-combined'!$C$1:$D$1,0))*1000) -> 442000 | AS24: =AS23+$AS$3 -> 17875 | AT24: 0 | AU24: =SUM($B$28:$B$29)*AR24 -> 8840 | AV24: =AR24*$B$15/4 -> 1270.75 | AW24: =SUM($AV$3:AV24) -> 25778.688 | AX24: =AR24-AS24-AU24-AW24 -> 389506.31 | AY24: =$B$36*V24 -> 1683.5 | AZ24: =SUM(AY24:AY24)*4/AR24 -> 0.015235294 | BA24: =SUM(AY24:AY24)/V24 -> 0.35 | BB24: =IF(MortgageRate="Discounted",_xlfn.XLOOKUP(L24,'mortgage-rates'!$A:$A,'mortgage-rates'!$E:$E)/100,_xlfn.XLOOKUP(L24,'mortgage-rates'!$A:$A,'mortgage-rates'!$D:$D)/100) -> 0.0704 | BC24: =BC23-BF23 -> 235231.77 | BD24: =IF($B$16*12/3-Q24+1>0,-PMT($BB24/4,$B$16*12/3-Q24+1,BC24),0) -> 5534.9025 | BE24: =BC24*($BB24/4) -> 4140.0792 | BF24: =BD24-BE24 -> 1394.8234 | BG24: =AT24+AY24+BD24 -> 7218.4025 | BH24: =INDEX(cpi!B:B,MATCH($L24,cpi!A:A)) -> 99.3 | BI24: =100*BH24/BH$3 -> 117.37589 | BJ24: =100*AC24/AC$3 -> 120.92498 | BK24: =100*AD24/AD$3 -> 129.68345 | BL24: =BJ24*GlobalPortfolio+BK24*AusPortfolio -> 123.55252 | BM24: =100*AE24/$AE$3 -> 202.96005 | BN24: =100*AR24/AR$3 -> 136 | BO24: =100*AX24/AX$3 -> 122.96842
A25: Real estate agent commissions (purchase) | B25: 0.015 | C25: 0.015 | L25: =DATE(YEAR(L24),MONTH(L24)+3,1) -> 40787 | M25: =AP25 -> 142058.03 | N25: =AX25-BC25 -> 144791.99 | O25: =M25/N25 -> 0.98111801 | P25: =X25/BG25 -> 0.69139603 | Q25: 23 | R25: =EOMONTH(L25,0)-EOMONTH(L25,-3) -> 92 | T25: =IF($B$10="3BR_H", INDEX('3BR_H-processed'!$E:$E,MATCH($L25,'3BR_H-processed'!$B:$B,0),MATCH(Council_Area,'3BR_H-processed'!$E$1:$E$1,0)), INDEX('2BR_F-processed'!$E:$E,MATCH($L25,'2BR_F-processed'!$B:$B,0),MATCH(Council_Area,'2BR_F-processed'!$E$1:$E$1,0))) -> 366.0483 | U25: =IF(MOD(Q25,4)=1,T25,U24) -> 370 | V25: =U25*(R25)/7 -> 4862.8571 | W25: =$B$53/4*BH25/_xlfn.XLOOKUP(Q_end,cpi!A:A,cpi!B:B) -> 137.80235 | X25: =V25+W25 -> 5000.6595 | Y25: =BG25-X25 -> 2232.0397 | Z25: =Y25*$B$47 -> 0 | AA25: {=(Y25+Z25)*eff_invest} -> 2232.0397 | AB25: =AA25*(_xlfn.XLOOKUP(Q_end,cpi!A:A,cpi!B:B)/BH25) -> 3239.4799 | AC25: {=INDEX('msci-indices'!C:C,MATCH($L25,'msci-indices'!$B:$B)-2)} -> 915.80494 | AD25: {=INDEX('msci-indices'!D:D,MATCH($L25,'msci-indices'!$B:$B)-2)} -> 884.12823 | AE25: =AI24+AA25 -> 168569.07 | AF25: {=INDEX('msci-indices'!C:C,MATCH($L25,'msci-indices'!$B:$B)+1)} -> 758.74852 | AG25: {=INDEX('msci-indices'!D:D,MATCH($L25,'msci-indices'!$B:$B)+1)} -> 776.26676 | AH25: =(InvestFees/4)*AE25 -> 105.35567 | AI25: =((AF25/AC25)*GlobalPortfolio+(AG25/AD25)*AusPortfolio)*AE25-AH25 -> 142058.03 | AJ25: =AJ24+AA25 -> 145739.94 | AK25: =AI25-AJ25 -> -3681.9157 | AL25: =AJ25*(_xlfn.XLOOKUP(Q_end,cpi!A:A,cpi!B:B)/BH25) -> 211520.26 | AM25: {=SUMPRODUCT($AA$3:AA25,_xlfn.SORTBY($BH$3:BH25,_xlfn.SEQUENCE(ROWS($BH$3:BH25)),-1)/$BH$3)} -> 166406.36 | AN25: =AI25-AM25 -> -24348.327 | AO25: =IF($B$49="Real gains",MAX($B$50*AN25,0),IF($B$49="Discounted nominal gains",MAX($B$50*AK25/2,0),0)) -> 0 | AP25: =AI25-AO25 -> 142058.03 | AR25: =IF($B$10="3BR_H", INDEX('ns-combined'!$C:$D,MATCH($L25,'ns-combined'!$B:$B,0),MATCH(Council_Area,'ns-combined'!$C$1:$D$1,0))*1000, INDEX('s-combined'!$C:$D,MATCH($L25,'s-combined'!$B:$B,0),MATCH(Council_Area,'s-combined'!$C$1:$D$1,0))*1000) -> 433000 | AS25: =AS24+$AS$3 -> 18687.5 | AT25: 0 | AU25: =SUM($B$28:$B$29)*AR25 -> 8660 | AV25: =AR25*$B$15/4 -> 1244.875 | AW25: =SUM($AV$3:AV25) -> 27023.562 | AX25: =AR25-AS25-AU25-AW25 -> 378628.94 | AY25: =$B$36*V25 -> 1702 | AZ25: =SUM(AY25:AY25)*4/AR25 -> 0.015722864 | BA25: =SUM(AY25:AY25)/V25 -> 0.35 | BB25: =IF(MortgageRate="Discounted",_xlfn.XLOOKUP(L25,'mortgage-rates'!$A:$A,'mortgage-rates'!$E:$E)/100,_xlfn.XLOOKUP(L25,'mortgage-rates'!$A:$A,'mortgage-rates'!$D:$D)/100) -> 0.0703 | BC25: =BC24-BF24 -> 233836.95 | BD25: =IF($B$16*12/3-Q25+1>0,-PMT($BB25/4,$B$16*12/3-Q25+1,BC25),0) -> 5530.6992 | BE25: =BC25*($BB25/4) -> 4109.6844 | BF25: =BD25-BE25 -> 1421.0148 | BG25: =AT25+AY25+BD25 -> 7232.6992 | BH25: =INDEX(cpi!B:B,MATCH($L25,cpi!A:A)) -> 99.7 | BI25: =100*BH25/BH$3 -> 117.8487 | BJ25: =100*AC25/AC$3 -> 121.31801 | BK25: =100*AD25/AD$3 -> 124.00876 | BL25: =BJ25*GlobalPortfolio+BK25*AusPortfolio -> 122.12524 | BM25: =100*AE25/$AE$3 -> 203.32284 | BN25: =100*AR25/AR$3 -> 133.23077 | BO25: =100*AX25/AX$3 -> 119.5344
A26: Stamp duty (purchase) | B26: =(7225+(3.5/100)*(AR3-250000))/AR3 -> 0.030307692 | C26: 0.03 | L26: =DATE(YEAR(L25),MONTH(L25)+3,1) -> 40878 | M26: =AP26 -> 152530.11 | N26: =AX26-BC26 -> 141224.25 | O26: =M26/N26 -> 1.080056 | P26: =X26/BG26 -> 0.71131699 | Q26: 24 | R26: =EOMONTH(L26,0)-EOMONTH(L26,-3) -> 92 | T26: =IF($B$10="3BR_H", INDEX('3BR_H-processed'!$E:$E,MATCH($L26,'3BR_H-processed'!$B:$B,0),MATCH(Council_Area,'3BR_H-processed'!$E$1:$E$1,0)), INDEX('2BR_F-processed'!$E:$E,MATCH($L26,'2BR_F-processed'!$B:$B,0),MATCH(Council_Area,'2BR_F-processed'!$E$1:$E$1,0))) -> 364.07245 | U26: =IF(MOD(Q26,4)=1,T26,U25) -> 370 | V26: =U26*(R26)/7 -> 4862.8571 | W26: =$B$53/4*BH26/_xlfn.XLOOKUP(Q_end,cpi!A:A,cpi!B:B) -> 138.07878 | X26: =V26+W26 -> 5000.9359 | Y26: =BG26-X26 -> 2029.5948 | Z26: =Y26*$B$47 -> 0 | AA26: {=(Y26+Z26)*eff_invest} -> 2029.5948 | AB26: =AA26*(_xlfn.XLOOKUP(Q_end,cpi!A:A,cpi!B:B)/BH26) -> 2939.7635 | AC26: {=INDEX('msci-indices'!C:C,MATCH($L26,'msci-indices'!$B:$B)-2)} -> 758.74852 | AD26: {=INDEX('msci-indices'!D:D,MATCH($L26,'msci-indices'!$B:$B)-2)} -> 776.26676 | AE26: =AI25+AA26 -> 144087.62 | AF26: {=INDEX('msci-indices'!C:C,MATCH($L26,'msci-indices'!$B:$B)+1)} -> 816.9754 | AG26: {=INDEX('msci-indices'!D:D,MATCH($L26,'msci-indices'!$B:$B)+1)} -> 790.49635 | AH26: =(InvestFees/4)*AE26 -> 90.054764 | AI26: =((AF26/AC26)*GlobalPortfolio+(AG26/AD26)*AusPortfolio)*AE26-AH26 -> 152530.11 | AJ26: =AJ25+AA26 -> 147769.54 | AK26: =AI26-AJ26 -> 4760.5711 | AL26: =AJ26*(_xlfn.XLOOKUP(Q_end,cpi!A:A,cpi!B:B)/BH26) -> 214036.56 | AM26: {=SUMPRODUCT($AA$3:AA26,_xlfn.SORTBY($BH$3:BH26,_xlfn.SEQUENCE(ROWS($BH$3:BH26)),-1)/$BH$3)} -> 169139.5 | AN26: =AI26-AM26 -> -16609.392 | AO26: =IF($B$49="Real gains",MAX($B$50*AN26,0),IF($B$49="Discounted nominal gains",MAX($B$50*AK26/2,0),0)) -> 0 | AP26: =AI26-AO26 -> 152530.11 | AR26: =IF($B$10="3BR_H", INDEX('ns-combined'!$C:$D,MATCH($L26,'ns-combined'!$B:$B,0),MATCH(Council_Area,'ns-combined'!$C$1:$D$1,0))*1000, INDEX('s-combined'!$C:$D,MATCH($L26,'s-combined'!$B:$B,0),MATCH(Council_Area,'s-combined'!$C$1:$D$1,0))*1000) -> 430000 | AS26: =AS25+$AS$3 -> 19500 | AT26: 0 | AU26: =SUM($B$28:$B$29)*AR26 -> 8600 | AV26: =AR26*$B$15/4 -> 1236.25 | AW26: =SUM($AV$3:AV26) -> 28259.812 | AX26: =AR26-AS26-AU26-AW26 -> 373640.19 | AY26: =$B$36*V26 -> 1702 | AZ26: =SUM(AY26:AY26)*4/AR26 -> 0.015832558 | BA26: =SUM(AY26:AY26)/V26 -> 0.35 | BB26: =IF(MortgageRate="Discounted",_xlfn.XLOOKUP(L26,'mortgage-rates'!$A:$A,'mortgage-rates'!$E:$E)/100,_xlfn.XLOOKUP(L26,'mortgage-rates'!$A:$A,'mortgage-rates'!$D:$D)/100) -> 0.0654 | BC26: =BC25-BF25 -> 232415.93 | BD26: =IF($B$16*12/3-Q26+1>0,-PMT($BB26/4,$B$16*12/3-Q26+1,BC26),0) -> 5328.5307 | BE26: =BC26*($BB26/4) -> 3800.0005 | BF26: =BD26-BE26 -> 1528.5302 | BG26: =AT26+AY26+BD26 -> 7030.5307 | BH26: =INDEX(cpi!B:B,MATCH($L26,cpi!A:A)) -> 99.9 | BI26: =100*BH26/BH$3 -> 118.08511 | BJ26: =100*AC26/AC$3 -> 100.51252 | BK26: =100*AD26/AD$3 -> 108.88 | BL26: =BJ26*GlobalPortfolio+BK26*AusPortfolio -> 103.02276 | BM26: =100*AE26/$AE$3 -> 173.79407 | BN26: =100*AR26/AR$3 -> 132.30769 | BO26: =100*AX26/AX$3 -> 117.95943
A27: When selling the house (derating of home value) | L27: =DATE(YEAR(L26),MONTH(L26)+3,1) -> 40969 | M27: =AP27 -> 171436.67 | N27: =AX27-BC27 -> 140704.03 | O27: =M27/N27 -> 1.2184204 | P27: =X27/BG27 -> 0.68775839 | Q27: 25 | R27: =EOMONTH(L27,0)-EOMONTH(L27,-3) -> 91 | T27: =IF($B$10="3BR_H", INDEX('3BR_H-processed'!$E:$E,MATCH($L27,'3BR_H-processed'!$B:$B,0),MATCH(Council_Area,'3BR_H-processed'!$E$1:$E$1,0)), INDEX('2BR_F-processed'!$E:$E,MATCH($L27,'2BR_F-processed'!$B:$B,0),MATCH(Council_Area,'2BR_F-processed'!$E$1:$E$1,0))) -> 362.09659 | U27: =IF(MOD(Q27,4)=1,T27,U26) -> 362.09659 | V27: =U27*(R27)/7 -> 4707.2557 | W27: =$B$53/4*BH27/_xlfn.XLOOKUP(Q_end,cpi!A:A,cpi!B:B) -> 138.07878 | X27: =V27+W27 -> 4845.3345 | Y27: =BG27-X27 -> 2199.7769 | Z27: =Y27*$B$47 -> 0 | AA27: {=(Y27+Z27)*eff_invest} -> 2199.7769 | AB27: =AA27*(_xlfn.XLOOKUP(Q_end,cpi!A:A,cpi!B:B)/BH27) -> 3186.2635 | AC27: {=INDEX('msci-indices'!C:C,MATCH($L27,'msci-indices'!$B:$B)-2)} -> 816.9754 | AD27: {=INDEX('msci-indices'!D:D,MATCH($L27,'msci-indices'!$B:$B)-2)} -> 790.49635 | AE27: =AI26+AA27 -> 154729.89 | AF27: {=INDEX('msci-indices'!C:C,MATCH($L27,'msci-indices'!$B:$B)+1)} -> 913.58723 | AG27: {=INDEX('msci-indices'!D:D,MATCH($L27,'msci-indices'!$B:$B)+1)} -> 858.5317 | AH27: =(InvestFees/4)*AE27 -> 96.706179 | AI27: =((AF27/AC27)*GlobalPortfolio+(AG27/AD27)*AusPortfolio)*AE27-AH27 -> 171436.67 | AJ27: =AJ26+AA27 -> 149969.32 | AK27: =AI27-AJ27 -> 21467.35 | AL27: =AJ27*(_xlfn.XLOOKUP(Q_end,cpi!A:A,cpi!B:B)/BH27) -> 217222.82 | AM27: {=SUMPRODUCT($AA$3:AA27,_xlfn.SORTBY($BH$3:BH27,_xlfn.SEQUENCE(ROWS($BH$3:BH27)),-1)/$BH$3)} -> 171855.9 | AN27: =AI27-AM27 -> -419.23341 | AO27: =IF($B$49="Real gains",MAX($B$50*AN27,0),IF($B$49="Discounted nominal gains",MAX($B$50*AK27/2,0),0)) -> 0 | AP27: =AI27-AO27 -> 171436.67 | AR27: =IF($B$10="3BR_H", INDEX('ns-combined'!$C:$D,MATCH($L27,'ns-combined'!$B:$B,0),MATCH(Council_Area,'ns-combined'!$C$1:$D$1,0))*1000, INDEX('s-combined'!$C:$D,MATCH($L27,'s-combined'!$B:$B,0),MATCH(Council_Area,'s-combined'!$C$1:$D$1,0))*1000) -> 430000 | AS27: =AS26+$AS$3 -> 20312.5 | AT27: 0 | AU27: =SUM($B$28:$B$29)*AR27 -> 8600 | AV27: =AR27*$B$15/4 -> 1236.25 | AW27: =SUM($AV$3:AV27) -> 29496.062 | AX27: =AR27-AS27-AU27-AW27 -> 371591.44 | AY27: =$B$36*V27 -> 1647.5395 | AZ27: =SUM(AY27:AY27)*4/AR27 -> 0.015325949 | BA27: =SUM(AY27:AY27)/V27 -> 0.35 | BB27: =IF(MortgageRate="Discounted",_xlfn.XLOOKUP(L27,'mortgage-rates'!$A:$A,'mortgage-rates'!$E:$E)/100,_xlfn.XLOOKUP(L27,'mortgage-rates'!$A:$A,'mortgage-rates'!$D:$D)/100) -> 0.0671 | BC27: =BC26-BF26 -> 230887.4 | BD27: =IF($B$16*12/3-Q27+1>0,-PMT($BB27/4,$B$16*12/3-Q27+1,BC27),0) -> 5397.5719 | BE27: =BC27*($BB27/4) -> 3873.1362 | BF27: =BD27-BE27 -> 1524.4357 | BG27: =AT27+AY27+BD27 -> 7045.1114 | BH27: =INDEX(cpi!B:B,MATCH($L27,cpi!A:A)) -> 99.9 | BI27: =100*BH27/BH$3 -> 118.08511 | BJ27: =100*AC27/AC$3 -> 108.22592 | BK27: =100*AD27/AD$3 -> 110.87586 | BL27: =BJ27*GlobalPortfolio+BK27*AusPortfolio -> 109.0209 | BM27: =100*AE27/$AE$3 -> 186.63044 | BN27: =100*AR27/AR$3 -> 132.30769 | BO27: =100*AX27/AX$3 -> 117.31264
A28: Real estate agent commissions (sale) | B28: 0.015 | C28: 0.015 | L28: =DATE(YEAR(L27),MONTH(L27)+3,1) -> 41061 | M28: =AP28 -> 164194.21 | N28: =AX28-BC28 -> 145065.34 | O28: =M28/N28 -> 1.1318638 | P28: =X28/BG28 -> 0.71124152 | Q28: 26 | R28: =EOMONTH(L28,0)-EOMONTH(L28,-3) -> 91 | T28: =IF($B$10="3BR_H", INDEX('3BR_H-processed'!$E:$E,MATCH($L28,'3BR_H-processed'!$B:$B,0),MATCH(Council_Area,'3BR_H-processed'!$E$1:$E$1,0)), INDEX('2BR_F-processed'!$E:$E,MATCH($L28,'2BR_F-processed'!$B:$B,0),MATCH(Council_Area,'2BR_F-processed'!$E$1:$E$1,0))) -> 352.71793 | U28: =IF(MOD(Q28,4)=1,T28,U27) -> 362.09659 | V28: =U28*(R28)/7 -> 4707.2557 | W28: =$B$53/4*BH28/_xlfn.XLOOKUP(Q_end,cpi!A:A,cpi!B:B) -> 138.90809 | X28: =V28+W28 -> 4846.1638 | Y28: =BG28-X28 -> 1967.5045 | Z28: =Y28*$B$47 -> 0 | AA28: {=(Y28+Z28)*eff_invest} -> 1967.5045 | AB28: =AA28*(_xlfn.XLOOKUP(Q_end,cpi!A:A,cpi!B:B)/BH28) -> 2832.8149 | AC28: {=INDEX('msci-indices'!C:C,MATCH($L28,'msci-indices'!$B:$B)-2)} -> 913.58723 | AD28: {=INDEX('msci-indices'!D:D,MATCH($L28,'msci-indices'!$B:$B)-2)} -> 858.5317 | AE28: =AI27+AA28 -> 173404.17 | AF28: {=INDEX('msci-indices'!C:C,MATCH($L28,'msci-indices'!$B:$B)+1)} -> 865.80589 | AG28: {=INDEX('msci-indices'!D:D,MATCH($L28,'msci-indices'!$B:$B)+1)} -> 813.09506 | AH28: =(InvestFees/4)*AE28 -> 108.37761 | AI28: =((AF28/AC28)*GlobalPortfolio+(AG28/AD28)*AusPortfolio)*AE28-AH28 -> 164194.21 | AJ28: =AJ27+AA28 -> 151936.82 | AK28: =AI28-AJ28 -> 12257.394 | AL28: =AJ28*(_xlfn.XLOOKUP(Q_end,cpi!A:A,cpi!B:B)/BH28) -> 218758.78 | AM28: {=SUMPRODUCT($AA$3:AA28,_xlfn.SORTBY($BH$3:BH28,_xlfn.SEQUENCE(ROWS($BH$3:BH28)),-1)/$BH$3)} -> 174921.51 | AN28: =AI28-AM28 -> -10727.292 | AO28: =IF($B$49="Real gains",MAX($B$50*AN28,0),IF($B$49="Discounted nominal gains",MAX($B$50*AK28/2,0),0)) -> 0 | AP28: =AI28-AO28 -> 164194.21 | AR28: =IF($B$10="3BR_H", INDEX('ns-combined'!$C:$D,MATCH($L28,'ns-combined'!$B:$B,0),MATCH(Council_Area,'ns-combined'!$C$1:$D$1,0))*1000, INDEX('s-combined'!$C:$D,MATCH($L28,'s-combined'!$B:$B,0),MATCH(Council_Area,'s-combined'!$C$1:$D$1,0))*1000) -> 435000 | AS28: =AS27+$AS$3 -> 21125 | AT28: 0 | AU28: =SUM($B$28:$B$29)*AR28 -> 8700 | AV28: =AR28*$B$15/4 -> 1250.625 | AW28: =SUM($AV$3:AV28) -> 30746.688 | AX28: =AR28-AS28-AU28-AW28 -> 374428.31 | AY28: =$B$36*V28 -> 1647.5395 | AZ28: =SUM(AY28:AY28)*4/AR28 -> 0.015149789 | BA28: =SUM(AY28:AY28)/V28 -> 0.35 | BB28: =IF(MortgageRate="Discounted",_xlfn.XLOOKUP(L28,'mortgage-rates'!$A:$A,'mortgage-rates'!$E:$E)/100,_xlfn.XLOOKUP(L28,'mortgage-rates'!$A:$A,'mortgage-rates'!$D:$D)/100) -> 0.0613 | BC28: =BC27-BF27 -> 229362.97 | BD28: =IF($B$16*12/3-Q28+1>0,-PMT($BB28/4,$B$16*12/3-Q28+1,BC28),0) -> 5166.1288 | BE28: =BC28*($BB28/4) -> 3514.9875 | BF28: =BD28-BE28 -> 1651.1413 | BG28: =AT28+AY28+BD28 -> 6813.6683 | BH28: =INDEX(cpi!B:B,MATCH($L28,cpi!A:A)) -> 100.5 | BI28: =100*BH28/BH$3 -> 118.79433 | BJ28: =100*AC28/AC$3 -> 121.02423 | BK28: =100*AD28/AD$3 -> 120.41857 | BL28: =BJ28*GlobalPortfolio+BK28*AusPortfolio -> 120.84253 | BM28: =100*AE28/$AE$3 -> 209.15479 | BN28: =100*AR28/AR$3 -> 133.84615 | BO28: =100*AX28/AX$3 -> 118.20825
A29: Other selling costs | B29: 0.005 | C29: 0.005 | L29: =DATE(YEAR(L28),MONTH(L28)+3,1) -> 41153 | M29: =AP29 -> 178109.92 | N29: =AX29-BC29 -> 144653.36 | O29: =M29/N29 -> 1.2312878 | P29: =X29/BG29 -> 0.71920468 | Q29: 27 | R29: =EOMONTH(L29,0)-EOMONTH(L29,-3) -> 92 | T29: =IF($B$10="3BR_H", INDEX('3BR_H-processed'!$E:$E,MATCH($L29,'3BR_H-processed'!$B:$B,0),MATCH(Council_Area,'3BR_H-processed'!$E$1:$E$1,0)), INDEX('2BR_F-processed'!$E:$E,MATCH($L29,'2BR_F-processed'!$B:$B,0),MATCH(Council_Area,'2BR_F-processed'!$E$1:$E$1,0))) -> 358.10837 | U29: =IF(MOD(Q29,4)=1,T29,U28) -> 362.09659 | V29: =U29*(R29)/7 -> 4758.9838 | W29: =$B$53/4*BH29/_xlfn.XLOOKUP(Q_end,cpi!A:A,cpi!B:B) -> 140.42847 | X29: =V29+W29 -> 4899.4123 | Y29: =BG29-X29 -> 1912.8519 | Z29: =Y29*$B$47 -> 0 | AA29: {=(Y29+Z29)*eff_invest} -> 1912.8519 | AB29: =AA29*(_xlfn.XLOOKUP(Q_end,cpi!A:A,cpi!B:B)/BH29) -> 2724.3078 | AC29: {=INDEX('msci-indices'!C:C,MATCH($L29,'msci-indices'!$B:$B)-2)} -> 865.80589 | AD29: {=INDEX('msci-indices'!D:D,MATCH($L29,'msci-indices'!$B:$B)-2)} -> 813.09506 | AE29: =AI28+AA29 -> 166107.07 | AF29: {=INDEX('msci-indices'!C:C,MATCH($L29,'msci-indices'!$B:$B)+1)} -> 923.8995 | AG29: {=INDEX('msci-indices'!D:D,MATCH($L29,'msci-indices'!$B:$B)+1)} -> 883.33647 | AH29: =(InvestFees/4)*AE29 -> 103.81692 | AI29: =((AF29/AC29)*GlobalPortfolio+(AG29/AD29)*AusPortfolio)*AE29-AH29 -> 178109.92 | AJ29: =AJ28+AA29 -> 153849.67 | AK29: =AI29-AJ29 -> 24260.244 | AL29: =AJ29*(_xlfn.XLOOKUP(Q_end,cpi!A:A,cpi!B:B)/BH29) -> 219114.64 | AM29: {=SUMPRODUCT($AA$3:AA29,_xlfn.SORTBY($BH$3:BH29,_xlfn.SEQUENCE(ROWS($BH$3:BH29)),-1)/$BH$3)} -> 178431.09 | AN29: =AI29-AM29 -> -321.17201 | AO29: =IF($B$49="Real gains",MAX($B$50*AN29,0),IF($B$49="Discounted nominal gains",MAX($B$50*AK29/2,0),0)) -> 0 | AP29: =AI29-AO29 -> 178109.92 | AR29: =IF($B$10="3BR_H", INDEX('ns-combined'!$C:$D,MATCH($L29,'ns-combined'!$B:$B,0),MATCH(Council_Area,'ns-combined'!$C$1:$D$1,0))*1000, INDEX('s-combined'!$C:$D,MATCH($L29,'s-combined'!$B:$B,0),MATCH(Council_Area,'s-combined'!$C$1:$D$1,0))*1000) -> 435000 | AS29: =AS28+$AS$3 -> 21937.5 | AT29: 0 | AU29: =SUM($B$28:$B$29)*AR29 -> 8700 | AV29: =AR29*$B$15/4 -> 1250.625 | AW29: =SUM($AV$3:AV29) -> 31997.312 | AX29: =AR29-AS29-AU29-AW29 -> 372365.19 | AY29: =$B$36*V29 -> 1665.6443 | AZ29: =SUM(AY29:AY29)*4/AR29 -> 0.01531627 | BA29: =SUM(AY29:AY29)/V29 -> 0.35 | BB29: =IF(MortgageRate="Discounted",_xlfn.XLOOKUP(L29,'mortgage-rates'!$A:$A,'mortgage-rates'!$E:$E)/100,_xlfn.XLOOKUP(L29,'mortgage-rates'!$A:$A,'mortgage-rates'!$D:$D)/100) -> 0.0608 | BC29: =BC28-BF28 -> 227711.83 | BD29: =IF($B$16*12/3-Q29+1>0,-PMT($BB29/4,$B$16*12/3-Q29+1,BC29),0) -> 5146.6199 | BE29: =BC29*($BB29/4) -> 3461.2198 | BF29: =BD29-BE29 -> 1685.4001 | BG29: =AT29+AY29+BD29 -> 6812.2642 | BH29: =INDEX(cpi!B:B,MATCH($L29,cpi!A:A)) -> 101.6 | BI29: =100*BH29/BH$3 -> 120.09456 | BJ29: =100*AC29/AC$3 -> 114.69457 | BK29: =100*AD29/AD$3 -> 114.04558 | BL29: =BJ29*GlobalPortfolio+BK29*AusPortfolio -> 114.49987 | BM29: =100*AE29/$AE$3 -> 200.35324 | BN29: =100*AR29/AR$3 -> 133.84615 | BO29: =100*AX29/AX$3 -> 117.55691
L30: =DATE(YEAR(L29),MONTH(L29)+3,1) -> 41244 | M30: =AP30 -> 186748.99 | N30: =AX30-BC30 -> 149161.26 | O30: =M30/N30 -> 1.2519939 | P30: =X30/BG30 -> 0.73582132 | Q30: 28 | R30: =EOMONTH(L30,0)-EOMONTH(L30,-3) -> 92 | T30: =IF($B$10="3BR_H", INDEX('3BR_H-processed'!$E:$E,MATCH($L30,'3BR_H-processed'!$B:$B,0),MATCH(Council_Area,'3BR_H-processed'!$E$1:$E$1,0)), INDEX('2BR_F-processed'!$E:$E,MATCH($L30,'2BR_F-processed'!$B:$B,0),MATCH(Council_Area,'2BR_F-processed'!$E$1:$E$1,0))) -> 360.26913 | U30: =IF(MOD(Q30,4)=1,T30,U29) -> 362.09659 | V30: =U30*(R30)/7 -> 4758.9838 | W30: =$B$53/4*BH30/_xlfn.XLOOKUP(Q_end,cpi!A:A,cpi!B:B) -> 140.98134 | X30: =V30+W30 -> 4899.9651 | Y30: =BG30-X30 -> 1759.2129 | Z30: =Y30*$B$47 -> 0 | AA30: {=(Y30+Z30)*eff_invest} -> 1759.2129 | AB30: =AA30*(_xlfn.XLOOKUP(Q_end,cpi!A:A,cpi!B:B)/BH30) -> 2495.6677 | AC30: {=INDEX('msci-indices'!C:C,MATCH($L30,'msci-indices'!$B:$B)-2)} -> 923.8995 | AD30: {=INDEX('msci-indices'!D:D,MATCH($L30,'msci-indices'!$B:$B)-2)} -> 883.33647 | AE30: =AI29+AA30 -> 179869.13 | AF30: {=INDEX('msci-indices'!C:C,MATCH($L30,'msci-indices'!$B:$B)+1)} -> 948.15111 | AG30: {=INDEX('msci-indices'!D:D,MATCH($L30,'msci-indices'!$B:$B)+1)} -> 943.69729 | AH30: =(InvestFees/4)*AE30 -> 112.41821 | AI30: =((AF30/AC30)*GlobalPortfolio+(AG30/AD30)*AusPortfolio)*AE30-AH30 -> 186748.99 | AJ30: =AJ29+AA30 -> 155608.88 | AK30: =AI30-AJ30 -> 31140.104 | AL30: =AJ30*(_xlfn.XLOOKUP(Q_end,cpi!A:A,cpi!B:B)/BH30) -> 220751.04 | AM30: {=SUMPRODUCT($AA$3:AA30,_xlfn.SORTBY($BH$3:BH30,_xlfn.SEQUENCE(ROWS($BH$3:BH30)),-1)/$BH$3)} -> 181130.53 | AN30: =AI30-AM30 -> 5618.4593 | AO30: =IF($B$49="Real gains",MAX($B$50*AN30,0),IF($B$49="Discounted nominal gains",MAX($B$50*AK30/2,0),0)) -> 0 | AP30: =AI30-AO30 -> 186748.99 | AR30: =IF($B$10="3BR_H", INDEX('ns-combined'!$C:$D,MATCH($L30,'ns-combined'!$B:$B,0),MATCH(Council_Area,'ns-combined'!$C$1:$D$1,0))*1000, INDEX('s-combined'!$C:$D,MATCH($L30,'s-combined'!$B:$B,0),MATCH(Council_Area,'s-combined'!$C$1:$D$1,0))*1000) -> 440000 | AS30: =AS29+$AS$3 -> 22750 | AT30: 0 | AU30: =SUM($B$28:$B$29)*AR30 -> 8800 | AV30: =AR30*$B$15/4 -> 1265 | AW30: =SUM($AV$3:AV30) -> 33262.312 | AX30: =AR30-AS30-AU30-AW30 -> 375187.69 | AY30: =$B$36*V30 -> 1665.6443 | AZ30: =SUM(AY30:AY30)*4/AR30 -> 0.015142221 | BA30: =SUM(AY30:AY30)/V30 -> 0.35 | BB30: =IF(MortgageRate="Discounted",_xlfn.XLOOKUP(L30,'mortgage-rates'!$A:$A,'mortgage-rates'!$E:$E)/100,_xlfn.XLOOKUP(L30,'mortgage-rates'!$A:$A,'mortgage-rates'!$D:$D)/100) -> 0.0568 | BC30: =BC29-BF29 -> 226026.43 | BD30: =IF($B$16*12/3-Q30+1>0,-PMT($BB30/4,$B$16*12/3-Q30+1,BC30),0) -> 4993.5337 | BE30: =BC30*($BB30/4) -> 3209.5753 | BF30: =BD30-BE30 -> 1783.9584 | BG30: =AT30+AY30+BD30 -> 6659.178 | BH30: =INDEX(cpi!B:B,MATCH($L30,cpi!A:A)) -> 102 | BI30: =100*BH30/BH$3 -> 120.56738 | BJ30: =100*AC30/AC$3 -> 122.39031 | BK30: =100*AD30/AD$3 -> 123.89771 | BL30: =BJ30*GlobalPortfolio+BK30*AusPortfolio -> 122.84253 | BM30: =100*AE30/$AE$3 -> 216.95262 | BN30: =100*AR30/AR$3 -> 135.38462 | BO30: =100*AX30/AX$3 -> 118.44798
A31: Home ownership running costs (% of gross rents) | L31: =DATE(YEAR(L30),MONTH(L30)+3,1) -> 41334 | M31: =AP31 -> 203673.32 | N31: =AX31-BC31 -> 148867.72 | O31: =M31/N31 -> 1.3681496 | P31: =X31/BG31 -> 0.74043282 | Q31: 29 | R31: =EOMONTH(L31,0)-EOMONTH(L31,-3) -> 90 | T31: =IF($B$10="3BR_H", INDEX('3BR_H-processed'!$E:$E,MATCH($L31,'3BR_H-processed'!$B:$B,0),MATCH(Council_Area,'3BR_H-processed'!$E$1:$E$1,0)), INDEX('2BR_F-processed'!$E:$E,MATCH($L31,'2BR_F-processed'!$B:$B,0),MATCH(Council_Area,'2BR_F-processed'!$E$1:$E$1,0))) -> 371.55948 | U31: =IF(MOD(Q31,4)=1,T31,U30) -> 371.55948 | V31: =U31*(R31)/7 -> 4777.1934 | W31: =$B$53/4*BH31/_xlfn.XLOOKUP(Q_end,cpi!A:A,cpi!B:B) -> 141.53421 | X31: =V31+W31 -> 4918.7276 | Y31: =BG31-X31 -> 1724.3161 | Z31: =Y31*$B$47 -> 0 | AA31: {=(Y31+Z31)*eff_invest} -> 1724.3161 | AB31: =AA31*(_xlfn.XLOOKUP(Q_end,cpi!A:A,cpi!B:B)/BH31) -> 2436.6069 | AC31: {=INDEX('msci-indices'!C:C,MATCH($L31,'msci-indices'!$B:$B)-2)} -> 948.15111 | AD31: {=INDEX('msci-indices'!D:D,MATCH($L31,'msci-indices'!$B:$B)-2)} -> 943.69729 | AE31: =AI30+AA31 -> 188473.3 | AF31: {=INDEX('msci-indices'!C:C,MATCH($L31,'msci-indices'!$B:$B)+1)} -> 1024.7053 | AG31: {=INDEX('msci-indices'!D:D,MATCH($L31,'msci-indices'!$B:$B)+1)} -> 1021.5673 | AH31: =(InvestFees/4)*AE31 -> 117.79582 | AI31: =((AF31/AC31)*GlobalPortfolio+(AG31/AD31)*AusPortfolio)*AE31-AH31 -> 203673.32 | AJ31: =AJ30+AA31 -> 157333.2 | AK31: =AI31-AJ31 -> 46340.117 | AL31: =AJ31*(_xlfn.XLOOKUP(Q_end,cpi!A:A,cpi!B:B)/BH31) -> 222325.33 | AM31: {=SUMPRODUCT($AA$3:AA31,_xlfn.SORTBY($BH$3:BH31,_xlfn.SEQUENCE(ROWS($BH$3:BH31)),-1)/$BH$3)} -> 183799.64 | AN31: =AI31-AM31 -> 19873.678 | AO31: =IF($B$49="Real gains",MAX($B$50*AN31,0),IF($B$49="Discounted nominal gains",MAX($B$50*AK31/2,0),0)) -> 0 | AP31: =AI31-AO31 -> 203673.32 | AR31: =IF($B$10="3BR_H", INDEX('ns-combined'!$C:$D,MATCH($L31,'ns-combined'!$B:$B,0),MATCH(Council_Area,'ns-combined'!$C$1:$D$1,0))*1000, INDEX('s-combined'!$C:$D,MATCH($L31,'s-combined'!$B:$B,0),MATCH(Council_Area,'s-combined'!$C$1:$D$1,0))*1000) -> 440000 | AS31: =AS30+$AS$3 -> 23562.5 | AT31: 0 | AU31: =SUM($B$28:$B$29)*AR31 -> 8800 | AV31: =AR31*$B$15/4 -> 1265 | AW31: =SUM($AV$3:AV31) -> 34527.312 | AX31: =AR31-AS31-AU31-AW31 -> 373110.19 | AY31: =$B$36*V31 -> 1672.0177 | AZ31: =SUM(AY31:AY31)*4/AR31 -> 0.015200161 | BA31: =SUM(AY31:AY31)/V31 -> 0.35 | BB31: =IF(MortgageRate="Discounted",_xlfn.XLOOKUP(L31,'mortgage-rates'!$A:$A,'mortgage-rates'!$E:$E)/100,_xlfn.XLOOKUP(L31,'mortgage-rates'!$A:$A,'mortgage-rates'!$D:$D)/100) -> 0.0562 | BC31: =BC30-BF30 -> 224242.47 | BD31: =IF($B$16*12/3-Q31+1>0,-PMT($BB31/4,$B$16*12/3-Q31+1,BC31),0) -> 4971.026 | BE31: =BC31*($BB31/4) -> 3150.6067 | BF31: =BD31-BE31 -> 1820.4193 | BG31: =AT31+AY31+BD31 -> 6643.0437 | BH31: =INDEX(cpi!B:B,MATCH($L31,cpi!A:A)) -> 102.4 | BI31: =100*BH31/BH$3 -> 121.04019 | BJ31: =100*AC31/AC$3 -> 125.60296 | BK31: =100*AD31/AD$3 -> 132.36398 | BL31: =BJ31*GlobalPortfolio+BK31*AusPortfolio -> 127.63126 | BM31: =100*AE31/$AE$3 -> 227.33071 | BN31: =100*AR31/AR$3 -> 135.38462 | BO31: =100*AX31/AX$3 -> 117.79211
A32: Council rates | B32: 0.07 | C32: 0.07 | L32: =DATE(YEAR(L31),MONTH(L31)+3,1) -> 41426 | M32: =AP32 -> 203951.18 | N32: =AX32-BC32 -> 153496.26 | O32: =M32/N32 -> 1.3287046 | P32: =X32/BG32 -> 0.75733549 | Q32: 30 | R32: =EOMONTH(L32,0)-EOMONTH(L32,-3) -> 91 | T32: =IF($B$10="3BR_H", INDEX('3BR_H-processed'!$E:$E,MATCH($L32,'3BR_H-processed'!$B:$B,0),MATCH(Council_Area,'3BR_H-processed'!$E$1:$E$1,0)), INDEX('2BR_F-processed'!$E:$E,MATCH($L32,'2BR_F-processed'!$B:$B,0),MATCH(Council_Area,'2BR_F-processed'!$E$1:$E$1,0))) -> 362.18946 | U32: =IF(MOD(Q32,4)=1,T32,U31) -> 371.55948 | V32: =U32*(R32)/7 -> 4830.2733 | W32: =$B$53/4*BH32/_xlfn.XLOOKUP(Q_end,cpi!A:A,cpi!B:B) -> 142.22529 | X32: =V32+W32 -> 4972.4986 | Y32: =BG32-X32 -> 1593.2819 | Z32: =Y32*$B$47 -> 0 | AA32: {=(Y32+Z32)*eff_invest} -> 1593.2819 | AB32: =AA32*(_xlfn.XLOOKUP(Q_end,cpi!A:A,cpi!B:B)/BH32) -> 2240.5043 | AC32: {=INDEX('msci-indices'!C:C,MATCH($L32,'msci-indices'!$B:$B)-2)} -> 1024.7053 | AD32: {=INDEX('msci-indices'!D:D,MATCH($L32,'msci-indices'!$B:$B)-2)} -> 1021.5673 | AE32: =AI31+AA32 -> 205266.6 | AF32: {=INDEX('msci-indices'!C:C,MATCH($L32,'msci-indices'!$B:$B)+1)} -> 1030.5184 | AG32: {=INDEX('msci-indices'!D:D,MATCH($L32,'msci-indices'!$B:$B)+1)} -> 988.35138 | AH32: =(InvestFees/4)*AE32 -> 128.29162 | AI32: =((AF32/AC32)*GlobalPortfolio+(AG32/AD32)*AusPortfolio)*AE32-AH32 -> 203951.18 | AJ32: =AJ31+AA32 -> 158926.48 | AK32: =AI32-AJ32 -> 45024.702 | AL32: =AJ32*(_xlfn.XLOOKUP(Q_end,cpi!A:A,cpi!B:B)/BH32) -> 223485.54 | AM32: {=SUMPRODUCT($AA$3:AA32,_xlfn.SORTBY($BH$3:BH32,_xlfn.SEQUENCE(ROWS($BH$3:BH32)),-1)/$BH$3)} -> 186442.49 | AN32: =AI32-AM32 -> 17508.692 | AO32: =IF($B$49="Real gains",MAX($B$50*AN32,0),IF($B$49="Discounted nominal gains",MAX($B$50*AK32/2,0),0)) -> 0 | AP32: =AI32-AO32 -> 203951.18 | AR32: =IF($B$10="3BR_H", INDEX('ns-combined'!$C:$D,MATCH($L32,'ns-combined'!$B:$B,0),MATCH(Council_Area,'ns-combined'!$C$1:$D$1,0))*1000, INDEX('s-combined'!$C:$D,MATCH($L32,'s-combined'!$B:$B,0),MATCH(Council_Area,'s-combined'!$C$1:$D$1,0))*1000) -> 445000 | AS32: =AS31+$AS$3 -> 24375 | AT32: 0 | AU32: =SUM($B$28:$B$29)*AR32 -> 8900 | AV32: =AR32*$B$15/4 -> 1279.375 | AW32: =SUM($AV$3:AV32) -> 35806.688 | AX32: =AR32-AS32-AU32-AW32 -> 375918.31 | AY32: =$B$36*V32 -> 1690.5956 | AZ32: =SUM(AY32:AY32)*4/AR32 -> 0.015196365 | BA32: =SUM(AY32:AY32)/V32 -> 0.35 | BB32: =IF(MortgageRate="Discounted",_xlfn.XLOOKUP(L32,'mortgage-rates'!$A:$A,'mortgage-rates'!$E:$E)/100,_xlfn.XLOOKUP(L32,'mortgage-rates'!$A:$A,'mortgage-rates'!$D:$D)/100) -> 0.0536 | BC32: =BC31-BF31 -> 222422.05 | BD32: =IF($B$16*12/3-Q32+1>0,-PMT($BB32/4,$B$16*12/3-Q32+1,BC32),0) -> 4875.1848 | BE32: =BC32*($BB32/4) -> 2980.4554 | BF32: =BD32-BE32 -> 1894.7294 | BG32: =AT32+AY32+BD32 -> 6565.7805 | BH32: =INDEX(cpi!B:B,MATCH($L32,cpi!A:A)) -> 102.9 | BI32: =100*BH32/BH$3 -> 121.63121 | BJ32: =100*AC32/AC$3 -> 135.7442 | BK32: =100*AD32/AD$3 -> 143.28611 | BL32: =BJ32*GlobalPortfolio+BK32*AusPortfolio -> 138.00677 | BM32: =100*AE32/$AE$3 -> 247.58627 | BN32: =100*AR32/AR$3 -> 136.92308 | BO32: =100*AX32/AX$3 -> 118.67864
A33: Maintenance incl. body corporate fees | B33: 0.16 | C33: 0.16 | L33: =DATE(YEAR(L32),MONTH(L32)+3,1) -> 41518 | M33: =AP33 -> 223927.36 | N33: =AX33-BC33 -> 157207.62 | O33: =M33/N33 -> 1.4244052 | P33: =X33/BG33 -> 0.77535621 | Q33: 31 | R33: =EOMONTH(L33,0)-EOMONTH(L33,-3) -> 92 | T33: =IF($B$10="3BR_H", INDEX('3BR_H-processed'!$E:$E,MATCH($L33,'3BR_H-processed'!$B:$B,0),MATCH(Council_Area,'3BR_H-processed'!$E$1:$E$1,0)), INDEX('2BR_F-processed'!$E:$E,MATCH($L33,'2BR_F-processed'!$B:$B,0),MATCH(Council_Area,'2BR_F-processed'!$E$1:$E$1,0))) -> 367.98433 | U33: =IF(MOD(Q33,4)=1,T33,U32) -> 371.55948 | V33: =U33*(R33)/7 -> 4883.3532 | W33: =$B$53/4*BH33/_xlfn.XLOOKUP(Q_end,cpi!A:A,cpi!B:B) -> 143.60746 | X33: =V33+W33 -> 5026.9607 | Y33: =BG33-X33 -> 1456.4603 | Z33: =Y33*$B$47 -> 0 | AA33: {=(Y33+Z33)*eff_invest} -> 1456.4603 | AB33: =AA33*(_xlfn.XLOOKUP(Q_end,cpi!A:A,cpi!B:B)/BH33) -> 2028.3908 | AC33: {=INDEX('msci-indices'!C:C,MATCH($L33,'msci-indices'!$B:$B)-2)} -> 1030.5184 | AD33: {=INDEX('msci-indices'!D:D,MATCH($L33,'msci-indices'!$B:$B)-2)} -> 988.35138 | AE33: =AI32+AA33 -> 205407.65 | AF33: {=INDEX('msci-indices'!C:C,MATCH($L33,'msci-indices'!$B:$B)+1)} -> 1119.4371 | AG33: {=INDEX('msci-indices'!D:D,MATCH($L33,'msci-indices'!$B:$B)+1)} -> 1088.4582 | AH33: =(InvestFees/4)*AE33 -> 128.37978 | AI33: =((AF33/AC33)*GlobalPortfolio+(AG33/AD33)*AusPortfolio)*AE33-AH33 -> 223927.36 | AJ33: =AJ32+AA33 -> 160382.94 | AK33: =AI33-AJ33 -> 63544.414 | AL33: =AJ33*(_xlfn.XLOOKUP(Q_end,cpi!A:A,cpi!B:B)/BH33) -> 223362.96 | AM33: {=SUMPRODUCT($AA$3:AA33,_xlfn.SORTBY($BH$3:BH33,_xlfn.SEQUENCE(ROWS($BH$3:BH33)),-1)/$BH$3)} -> 189438.62 | AN33: =AI33-AM33 -> 34488.733 | AO33: =IF($B$49="Real gains",MAX($B$50*AN33,0),IF($B$49="Discounted nominal gains",MAX($B$50*AK33/2,0),0)) -> 0 | AP33: =AI33-AO33 -> 223927.36 | AR33: =IF($B$10="3BR_H", INDEX('ns-combined'!$C:$D,MATCH($L33,'ns-combined'!$B:$B,0),MATCH(Council_Area,'ns-combined'!$C$1:$D$1,0))*1000, INDEX('s-combined'!$C:$D,MATCH($L33,'s-combined'!$B:$B,0),MATCH(Council_Area,'s-combined'!$C$1:$D$1,0))*1000) -> 449000 | AS33: =AS32+$AS$3 -> 25187.5 | AT33: 0 | AU33: =SUM($B$28:$B$29)*AR33 -> 8980 | AV33: =AR33*$B$15/4 -> 1290.875 | AW33: =SUM($AV$3:AV33) -> 37097.562 | AX33: =AR33-AS33-AU33-AW33 -> 377734.94 | AY33: =$B$36*V33 -> 1709.1736 | AZ33: =SUM(AY33:AY33)*4/AR33 -> 0.015226491 | BA33: =SUM(AY33:AY33)/V33 -> 0.35 | BB33: =IF(MortgageRate="Discounted",_xlfn.XLOOKUP(L33,'mortgage-rates'!$A:$A,'mortgage-rates'!$E:$E)/100,_xlfn.XLOOKUP(L33,'mortgage-rates'!$A:$A,'mortgage-rates'!$D:$D)/100) -> 0.0508 | BC33: =BC32-BF32 -> 220527.32 | BD33: =IF($B$16*12/3-Q33+1>0,-PMT($BB33/4,$B$16*12/3-Q33+1,BC33),0) -> 4774.2473 | BE33: =BC33*($BB33/4) -> 2800.697 | BF33: =BD33-BE33 -> 1973.5504 | BG33: =AT33+AY33+BD33 -> 6483.4209 | BH33: =INDEX(cpi!B:B,MATCH($L33,cpi!A:A)) -> 103.9 | BI33: =100*BH33/BH$3 -> 122.81324 | BJ33: =100*AC33/AC$3 -> 136.51427 | BK33: =100*AD33/AD$3 -> 138.62721 | BL33: =BJ33*GlobalPortfolio+BK33*AusPortfolio -> 137.14815 | BM33: =100*AE33/$AE$3 -> 247.7564 | BN33: =100*AR33/AR$3 -> 138.15385 | BO33: =100*AX33/AX$3 -> 119.25216
A34: Plant depreciation | B34: 0.07 | C34: 0.07 | L34: =DATE(YEAR(L33),MONTH(L33)+3,1) -> 41609 | M34: =AP34 -> 240001.66 | N34: =AX34-BC34 -> 172711.79 | O34: =M34/N34 -> 1.3896078 | P34: =X34/BG34 -> 0.77467988 | Q34: 32 | R34: =EOMONTH(L34,0)-EOMONTH(L34,-3) -> 92 | T34: =IF($B$10="3BR_H", INDEX('3BR_H-processed'!$E:$E,MATCH($L34,'3BR_H-processed'!$B:$B,0),MATCH(Council_Area,'3BR_H-processed'!$E$1:$E$1,0)), INDEX('2BR_F-processed'!$E:$E,MATCH($L34,'2BR_F-processed'!$B:$B,0),MATCH(Council_Area,'2BR_F-processed'!$E$1:$E$1,0))) -> 368.5779 | U34: =IF(MOD(Q34,4)=1,T34,U33) -> 371.55948 | V34: =U34*(R34)/7 -> 4883.3532 | W34: =$B$53/4*BH34/_xlfn.XLOOKUP(Q_end,cpi!A:A,cpi!B:B) -> 144.7132 | X34: =V34+W34 -> 5028.0664 | Y34: =BG34-X34 -> 1462.4422 | Z34: =Y34*$B$47 -> 0 | AA34: {=(Y34+Z34)*eff_invest} -> 1462.4422 | AB34: =AA34*(_xlfn.XLOOKUP(Q_end,cpi!A:A,cpi!B:B)/BH34) -> 2021.1594 | AC34: {=INDEX('msci-indices'!C:C,MATCH($L34,'msci-indices'!$B:$B)-2)} -> 1119.4371 | AD34: {=INDEX('msci-indices'!D:D,MATCH($L34,'msci-indices'!$B:$B)-2)} -> 1088.4582 | AE34: =AI33+AA34 -> 225389.8 | AF34: {=INDEX('msci-indices'!C:C,MATCH($L34,'msci-indices'!$B:$B)+1)} -> 1208.1074 | AG34: {=INDEX('msci-indices'!D:D,MATCH($L34,'msci-indices'!$B:$B)+1)} -> 1124.7671 | AH34: =(InvestFees/4)*AE34 -> 140.86862 | AI34: =((AF34/AC34)*GlobalPortfolio+(AG34/AD34)*AusPortfolio)*AE34-AH34 -> 240001.66 | AJ34: =AJ33+AA34 -> 161845.39 | AK34: =AI34-AJ34 -> 78156.275 | AL34: =AJ34*(_xlfn.XLOOKUP(Q_end,cpi!A:A,cpi!B:B)/BH34) -> 223677.43 | AM34: {=SUMPRODUCT($AA$3:AA34,_xlfn.SORTBY($BH$3:BH34,_xlfn.SEQUENCE(ROWS($BH$3:BH34)),-1)/$BH$3)} -> 192255.65 | AN34: =AI34-AM34 -> 47746.008 | AO34: =IF($B$49="Real gains",MAX($B$50*AN34,0),IF($B$49="Discounted nominal gains",MAX($B$50*AK34/2,0),0)) -> 0 | AP34: =AI34-AO34 -> 240001.66 | AR34: =IF($B$10="3BR_H", INDEX('ns-combined'!$C:$D,MATCH($L34,'ns-combined'!$B:$B,0),MATCH(Council_Area,'ns-combined'!$C$1:$D$1,0))*1000, INDEX('s-combined'!$C:$D,MATCH($L34,'s-combined'!$B:$B,0),MATCH(Council_Area,'s-combined'!$C$1:$D$1,0))*1000) -> 465000 | AS34: =AS33+$AS$3 -> 26000 | AT34: 0 | AU34: =SUM($B$28:$B$29)*AR34 -> 9300 | AV34: =AR34*$B$15/4 -> 1336.875 | AW34: =SUM($AV$3:AV34) -> 38434.438 | AX34: =AR34-AS34-AU34-AW34 -> 391265.56 | AY34: =$B$36*V34 -> 1709.1736 | AZ34: =SUM(AY34:AY34)*4/AR34 -> 0.014702569 | BA34: =SUM(AY34:AY34)/V34 -> 0.35 | BB34: =IF(MortgageRate="Discounted",_xlfn.XLOOKUP(L34,'mortgage-rates'!$A:$A,'mortgage-rates'!$E:$E)/100,_xlfn.XLOOKUP(L34,'mortgage-rates'!$A:$A,'mortgage-rates'!$D:$D)/100) -> 0.051 | BC34: =BC33-BF33 -> 218553.77 | BD34: =IF($B$16*12/3-Q34+1>0,-PMT($BB34/4,$B$16*12/3-Q34+1,BC34),0) -> 4781.335 | BE34: =BC34*($BB34/4) -> 2786.5606 | BF34: =BD34-BE34 -> 1994.7744 | BG34: =AT34+AY34+BD34 -> 6490.5086 | BH34: =INDEX(cpi!B:B,MATCH($L34,cpi!A:A)) -> 104.7 | BI34: =100*BH34/BH$3 -> 123.75887 | BJ34: =100*AC34/AC$3 -> 148.29346 | BK34: =100*AD34/AD$3 -> 152.6683 | BL34: =BJ34*GlobalPortfolio+BK34*AusPortfolio -> 149.60591 | BM34: =100*AE34/$AE$3 -> 271.85826 | BN34: =100*AR34/AR$3 -> 143.07692 | BO34: =100*AX34/AX$3 -> 123.52382
A35: Other expenses | B35: 0.05 | C35: 0.05 | L35: =DATE(YEAR(L34),MONTH(L34)+3,1) -> 41699 | M35: =AP35 -> 245420.48 | N35: =AX35-BC35 -> 155946.07 | O35: =M35/N35 -> 1.5737523 | P35: =X35/BG35 -> 0.77091116 | Q35: 33 | R35: =EOMONTH(L35,0)-EOMONTH(L35,-3) -> 90 | T35: =IF($B$10="3BR_H", INDEX('3BR_H-processed'!$E:$E,MATCH($L35,'3BR_H-processed'!$B:$B,0),MATCH(Council_Area,'3BR_H-processed'!$E$1:$E$1,0)), INDEX('2BR_F-processed'!$E:$E,MATCH($L35,'2BR_F-processed'!$B:$B,0),MATCH(Council_Area,'2BR_F-processed'!$E$1:$E$1,0))) -> 376.5327 | U35: =IF(MOD(Q35,4)=1,T35,U34) -> 376.5327 | V35: =U35*(R35)/7 -> 4841.1347 | W35: =$B$53/4*BH35/_xlfn.XLOOKUP(Q_end,cpi!A:A,cpi!B:B) -> 145.68072 | X35: =V35+W35 -> 4986.8155 | Y35: =BG35-X35 -> 1481.9137 | Z35: =Y35*$B$47 -> 0 | AA35: {=(Y35+Z35)*eff_invest} -> 1481.9137 | AB35: =AA35*(_xlfn.XLOOKUP(Q_end,cpi!A:A,cpi!B:B)/BH35) -> 2034.4678 | AC35: {=INDEX('msci-indices'!C:C,MATCH($L35,'msci-indices'!$B:$B)-2)} -> 1208.1074 | AD35: {=INDEX('msci-indices'!D:D,MATCH($L35,'msci-indices'!$B:$B)-2)} -> 1124.7671 | AE35: =AI34+AA35 -> 241483.57 | AF35: {=INDEX('msci-indices'!C:C,MATCH($L35,'msci-indices'!$B:$B)+1)} -> 1225.92 | AG35: {=INDEX('msci-indices'!D:D,MATCH($L35,'msci-indices'!$B:$B)+1)} -> 1149.5384 | AH35: =(InvestFees/4)*AE35 -> 150.92723 | AI35: =((AF35/AC35)*GlobalPortfolio+(AG35/AD35)*AusPortfolio)*AE35-AH35 -> 245420.48 | AJ35: =AJ34+AA35 -> 163327.3 | AK35: =AI35-AJ35 -> 82093.179 | AL35: =AJ35*(_xlfn.XLOOKUP(Q_end,cpi!A:A,cpi!B:B)/BH35) -> 224226.38 | AM35: {=SUMPRODUCT($AA$3:AA35,_xlfn.SORTBY($BH$3:BH35,_xlfn.SEQUENCE(ROWS($BH$3:BH35)),-1)/$BH$3)} -> 195000.89 | AN35: =AI35-AM35 -> 50419.591 | AO35: =IF($B$49="Real gains",MAX($B$50*AN35,0),IF($B$49="Discounted nominal gains",MAX($B$50*AK35/2,0),0)) -> 0 | AP35: =AI35-AO35 -> 245420.48 | AR35: =IF($B$10="3BR_H", INDEX('ns-combined'!$C:$D,MATCH($L35,'ns-combined'!$B:$B,0),MATCH(Council_Area,'ns-combined'!$C$1:$D$1,0))*1000, INDEX('s-combined'!$C:$D,MATCH($L35,'s-combined'!$B:$B,0),MATCH(Council_Area,'s-combined'!$C$1:$D$1,0))*1000) -> 448000 | AS35: =AS34+$AS$3 -> 26812.5 | AT35: 0 | AU35: =SUM($B$28:$B$29)*AR35 -> 8960 | AV35: =AR35*$B$15/4 -> 1288 | AW35: =SUM($AV$3:AV35) -> 39722.438 | AX35: =AR35-AS35-AU35-AW35 -> 372505.06 | AY35: =$B$36*V35 -> 1694.3972 | AZ35: =SUM(AY35:AY35)*4/AR35 -> 0.015128546 | BA35: =SUM(AY35:AY35)/V35 -> 0.35 | BB35: =IF(MortgageRate="Discounted",_xlfn.XLOOKUP(L35,'mortgage-rates'!$A:$A,'mortgage-rates'!$E:$E)/100,_xlfn.XLOOKUP(L35,'mortgage-rates'!$A:$A,'mortgage-rates'!$D:$D)/100) -> 0.0508 | BC35: =BC34-BF34 -> 216558.99 | BD35: =IF($B$16*12/3-Q35+1>0,-PMT($BB35/4,$B$16*12/3-Q35+1,BC35),0) -> 4774.332 | BE35: =BC35*($BB35/4) -> 2750.2992 | BF35: =BD35-BE35 -> 2024.0327 | BG35: =AT35+AY35+BD35 -> 6468.7291 | BH35: =INDEX(cpi!B:B,MATCH($L35,cpi!A:A)) -> 105.4 | BI35: =100*BH35/BH$3 -> 124.58629 | BJ35: =100*AC35/AC$3 -> 160.03975 | BK35: =100*AD35/AD$3 -> 157.76103 | BL35: =BJ35*GlobalPortfolio+BK35*AusPortfolio -> 159.35613 | BM35: =100*AE35/$AE$3 -> 291.27007 | BN35: =100*AR35/AR$3 -> 137.84615 | BO35: =100*AX35/AX$3 -> 117.60107
A36: Total home ownership running costs | B36: =SUM(B32:B35) -> 0.35 | C36: 0.35 | L36: =DATE(YEAR(L35),MONTH(L35)+3,1) -> 41791 | M36: =AP36 -> 255314.99 | N36: =AX36-BC36 -> 166617.98 | O36: =M36/N36 -> 1.5323376 | P36: =X36/BG36 -> 0.77711445 | Q36: 34 | R36: =EOMONTH(L36,0)-EOMONTH(L36,-3) -> 91 | T36: =IF($B$10="3BR_H", INDEX('3BR_H-processed'!$E:$E,MATCH($L36,'3BR_H-processed'!$B:$B,0),MATCH(Council_Area,'3BR_H-processed'!$E$1:$E$1,0)), INDEX('2BR_F-processed'!$E:$E,MATCH($L36,'2BR_F-processed'!$B:$B,0),MATCH(Council_Area,'2BR_F-processed'!$E$1:$E$1,0))) -> 370.15856 | U36: =IF(MOD(Q36,4)=1,T36,U35) -> 376.5327 | V36: =U36*(R36)/7 -> 4894.9251 | W36: =$B$53/4*BH36/_xlfn.XLOOKUP(Q_end,cpi!A:A,cpi!B:B) -> 146.64824 | X36: =V36+W36 -> 5041.5734 | Y36: =BG36-X36 -> 1445.9824 | Z36: =Y36*$B$47 -> 0 | AA36: {=(Y36+Z36)*eff_invest} -> 1445.9824 | AB36: =AA36*(_xlfn.XLOOKUP(Q_end,cpi!A:A,cpi!B:B)/BH36) -> 1972.042 | AC36: {=INDEX('msci-indices'!C:C,MATCH($L36,'msci-indices'!$B:$B)-2)} -> 1225.92 | AD36: {=INDEX('msci-indices'!D:D,MATCH($L36,'msci-indices'!$B:$B)-2)} -> 1149.5384 | AE36: =AI35+AA36 -> 246866.46 | AF36: {=INDEX('msci-indices'!C:C,MATCH($L36,'msci-indices'!$B:$B)+1)} -> 1282.9431 | AG36: {=INDEX('msci-indices'!D:D,MATCH($L36,'msci-indices'!$B:$B)+1)} -> 1158.3053 | AH36: =(InvestFees/4)*AE36 -> 154.29154 | AI36: =((AF36/AC36)*GlobalPortfolio+(AG36/AD36)*AusPortfolio)*AE36-AH36 -> 255314.99 | AJ36: =AJ35+AA36 -> 164773.28 | AK36: =AI36-AJ36 -> 90541.709 | AL36: =AJ36*(_xlfn.XLOOKUP(Q_end,cpi!A:A,cpi!B:B)/BH36) -> 224719.07 | AM36: {=SUMPRODUCT($AA$3:AA36,_xlfn.SORTBY($BH$3:BH36,_xlfn.SEQUENCE(ROWS($BH$3:BH36)),-1)/$BH$3)} -> 197727.7 | AN36: =AI36-AM36 -> 57587.288 | AO36: =IF($B$49="Real gains",MAX($B$50*AN36,0),IF($B$49="Discounted nominal gains",MAX($B$50*AK36/2,0),0)) -> 0 | AP36: =AI36-AO36 -> 255314.99 | AR36: =IF($B$10="3BR_H", INDEX('ns-combined'!$C:$D,MATCH($L36,'ns-combined'!$B:$B,0),MATCH(Council_Area,'ns-combined'!$C$1:$D$1,0))*1000, INDEX('s-combined'!$C:$D,MATCH($L36,'s-combined'!$B:$B,0),MATCH(Council_Area,'s-combined'!$C$1:$D$1,0))*1000) -> 459000 | AS36: =AS35+$AS$3 -> 27625 | AT36: 0 | AU36: =SUM($B$28:$B$29)*AR36 -> 9180 | AV36: =AR36*$B$15/4 -> 1319.625 | AW36: =SUM($AV$3:AV36) -> 41042.062 | AX36: =AR36-AS36-AU36-AW36 -> 381152.94 | AY36: =$B$36*V36 -> 1713.2238 | AZ36: =SUM(AY36:AY36)*4/AR36 -> 0.014930055 | BA36: =SUM(AY36:AY36)/V36 -> 0.35 | BB36: =IF(MortgageRate="Discounted",_xlfn.XLOOKUP(L36,'mortgage-rates'!$A:$A,'mortgage-rates'!$E:$E)/100,_xlfn.XLOOKUP(L36,'mortgage-rates'!$A:$A,'mortgage-rates'!$D:$D)/100) -> 0.0508 | BC36: =BC35-BF35 -> 214534.96 | BD36: =IF($B$16*12/3-Q36+1>0,-PMT($BB36/4,$B$16*12/3-Q36+1,BC36),0) -> 4774.332 | BE36: =BC36*($BB36/4) -> 2724.594 | BF36: =BD36-BE36 -> 2049.738 | BG36: =AT36+AY36+BD36 -> 6487.5558 | BH36: =INDEX(cpi!B:B,MATCH($L36,cpi!A:A)) -> 106.1 | BI36: =100*BH36/BH$3 -> 125.41371 | BJ36: =100*AC36/AC$3 -> 162.39941 | BK36: =100*AD36/AD$3 -> 161.23548 | BL36: =BJ36*GlobalPortfolio+BK36*AusPortfolio -> 162.05023 | BM36: =100*AE36/$AE$3 -> 297.76275 | BN36: =100*AR36/AR$3 -> 141.23077 | BO36: =100*AX36/AX$3 -> 120.33123
A37: Average maint + reno spending (% home value) | B37: {=AVERAGE(_xlfn._xlws.FILTER($AZ$3:$AZ$82,ISNUMBER($AZ$3:$AZ$82)))} -> 0.013441077 | C37: 0.011405453 | L37: =DATE(YEAR(L36),MONTH(L36)+3,1) -> 41883 | M37: =AP37 -> 251060.79 | N37: =AX37-BC37 -> 158718.59 | O37: =M37/N37 -> 1.5817983 | P37: =X37/BG37 -> 0.78317564 | Q37: 35 | R37: =EOMONTH(L37,0)-EOMONTH(L37,-3) -> 92 | T37: =IF($B$10="3BR_H", INDEX('3BR_H-processed'!$E:$E,MATCH($L37,'3BR_H-processed'!$B:$B,0),MATCH(Council_Area,'3BR_H-processed'!$E$1:$E$1,0)), INDEX('2BR_F-processed'!$E:$E,MATCH($L37,'2BR_F-processed'!$B:$B,0),MATCH(Council_Area,'2BR_F-processed'!$E$1:$E$1,0))) -> 372.53435 | U37: =IF(MOD(Q37,4)=1,T37,U36) -> 376.5327 | V37: =U37*(R37)/7 -> 4948.7155 | W37: =$B$53/4*BH37/_xlfn.XLOOKUP(Q_end,cpi!A:A,cpi!B:B) -> 146.92467 | X37: =V37+W37 -> 5095.6402 | Y37: =BG37-X37 -> 1410.7422 | Z37: =Y37*$B$47 -> 0 | AA37: {=(Y37+Z37)*eff_invest} -> 1410.7422 | AB37: =AA37*(_xlfn.XLOOKUP(Q_end,cpi!A:A,cpi!B:B)/BH37) -> 1920.3612 | AC37: {=INDEX('msci-indices'!C:C,MATCH($L37,'msci-indices'!$B:$B)-2)} -> 1282.9431 | AD37: {=INDEX('msci-indices'!D:D,MATCH($L37,'msci-indices'!$B:$B)-2)} -> 1158.3053 | AE37: =AI36+AA37 -> 256725.73 | AF37: {=INDEX('msci-indices'!C:C,MATCH($L37,'msci-indices'!$B:$B)+1)} -> 1247.2922 | AG37: {=INDEX('msci-indices'!D:D,MATCH($L37,'msci-indices'!$B:$B)+1)} -> 1150.6246 | AH37: =(InvestFees/4)*AE37 -> 160.45358 | AI37: =((AF37/AC37)*GlobalPortfolio+(AG37/AD37)*AusPortfolio)*AE37-AH37 -> 251060.79 | AJ37: =AJ36+AA37 -> 166184.02 | AK37: =AI37-AJ37 -> 84876.767 | AL37: =AJ37*(_xlfn.XLOOKUP(Q_end,cpi!A:A,cpi!B:B)/BH37) -> 226216.63 | AM37: {=SUMPRODUCT($AA$3:AA37,_xlfn.SORTBY($BH$3:BH37,_xlfn.SEQUENCE(ROWS($BH$3:BH37)),-1)/$BH$3)} -> 199951.7 | AN37: =AI37-AM37 -> 51109.093 | AO37: =IF($B$49="Real gains",MAX($B$50*AN37,0),IF($B$49="Discounted nominal gains",MAX($B$50*AK37/2,0),0)) -> 0 | AP37: =AI37-AO37 -> 251060.79 | AR37: =IF($B$10="3BR_H", INDEX('ns-combined'!$C:$D,MATCH($L37,'ns-combined'!$B:$B,0),MATCH(Council_Area,'ns-combined'!$C$1:$D$1,0))*1000, INDEX('s-combined'!$C:$D,MATCH($L37,'s-combined'!$B:$B,0),MATCH(Council_Area,'s-combined'!$C$1:$D$1,0))*1000) -> 451000 | AS37: =AS36+$AS$3 -> 28437.5 | AT37: 0 | AU37: =SUM($B$28:$B$29)*AR37 -> 9020 | AV37: =AR37*$B$15/4 -> 1296.625 | AW37: =SUM($AV$3:AV37) -> 42338.688 | AX37: =AR37-AS37-AU37-AW37 -> 371203.81 | AY37: =$B$36*V37 -> 1732.0504 | AZ37: =SUM(AY37:AY37)*4/AR37 -> 0.015361866 | BA37: =SUM(AY37:AY37)/V37 -> 0.35 | BB37: =IF(MortgageRate="Discounted",_xlfn.XLOOKUP(L37,'mortgage-rates'!$A:$A,'mortgage-rates'!$E:$E)/100,_xlfn.XLOOKUP(L37,'mortgage-rates'!$A:$A,'mortgage-rates'!$D:$D)/100) -> 0.0508 | BC37: =BC36-BF36 -> 212485.22 | BD37: =IF($B$16*12/3-Q37+1>0,-PMT($BB37/4,$B$16*12/3-Q37+1,BC37),0) -> 4774.332 | BE37: =BC37*($BB37/4) -> 2698.5623 | BF37: =BD37-BE37 -> 2075.7696 | BG37: =AT37+AY37+BD37 -> 6506.3824 | BH37: =INDEX(cpi!B:B,MATCH($L37,cpi!A:A)) -> 106.3 | BI37: =100*BH37/BH$3 -> 125.65012 | BJ37: =100*AC37/AC$3 -> 169.95334 | BK37: =100*AD37/AD$3 -> 162.46513 | BL37: =BJ37*GlobalPortfolio+BK37*AusPortfolio -> 167.70687 | BM37: =100*AE37/$AE$3 -> 309.6547 | BN37: =100*AR37/AR$3 -> 138.76923 | BO37: =100*AX37/AX$3 -> 117.19026
A38: Average maint + reno spending (% rents) | B38: {=AVERAGE(_xlfn._xlws.FILTER($BA$3:$BA$82,ISNUMBER($BA$3:$BA$82)))} -> 0.35 | C38: 0.35 | L38: =DATE(YEAR(L37),MONTH(L37)+3,1) -> 41974 | M38: =AP38 -> 256516.76 | N38: =AX38-BC38 -> 174319.23 | O38: =M38/N38 -> 1.4715344 | P38: =X38/BG38 -> 0.78321812 | Q38: 36 | R38: =EOMONTH(L38,0)-EOMONTH(L38,-3) -> 92 | T38: =IF($B$10="3BR_H", INDEX('3BR_H-processed'!$E:$E,MATCH($L38,'3BR_H-processed'!$B:$B,0),MATCH(Council_Area,'3BR_H-processed'!$E$1:$E$1,0)), INDEX('2BR_F-processed'!$E:$E,MATCH($L38,'2BR_F-processed'!$B:$B,0),MATCH(Council_Area,'2BR_F-processed'!$E$1:$E$1,0))) -> 375.41411 | U38: =IF(MOD(Q38,4)=1,T38,U37) -> 376.5327 | V38: =U38*(R38)/7 -> 4948.7155 | W38: =$B$53/4*BH38/_xlfn.XLOOKUP(Q_end,cpi!A:A,cpi!B:B) -> 147.20111 | X38: =V38+W38 -> 5095.9166 | Y38: =BG38-X38 -> 1410.4658 | Z38: =Y38*$B$47 -> 0 | AA38: {=(Y38+Z38)*eff_invest} -> 1410.4658 | AB38: =AA38*(_xlfn.XLOOKUP(Q_end,cpi!A:A,cpi!B:B)/BH38) -> 1916.3793 | AC38: {=INDEX('msci-indices'!C:C,MATCH($L38,'msci-indices'!$B:$B)-2)} -> 1247.2922 | AD38: {=INDEX('msci-indices'!D:D,MATCH($L38,'msci-indices'!$B:$B)-2)} -> 1150.6246 | AE38: =AI37+AA38 -> 252471.26 | AF38: {=INDEX('msci-indices'!C:C,MATCH($L38,'msci-indices'!$B:$B)+1)} -> 1262.6926 | AG38: {=INDEX('msci-indices'!D:D,MATCH($L38,'msci-indices'!$B:$B)+1)} -> 1181.3297 | AH38: =(InvestFees/4)*AE38 -> 157.79454 | AI38: =((AF38/AC38)*GlobalPortfolio+(AG38/AD38)*AusPortfolio)*AE38-AH38 -> 256516.76 | AJ38: =AJ37+AA38 -> 167594.49 | AK38: =AI38-AJ38 -> 88922.268 | AL38: =AJ38*(_xlfn.XLOOKUP(Q_end,cpi!A:A,cpi!B:B)/BH38) -> 227708.19 | AM38: {=SUMPRODUCT($AA$3:AA38,_xlfn.SORTBY($BH$3:BH38,_xlfn.SEQUENCE(ROWS($BH$3:BH38)),-1)/$BH$3)} -> 202181.28 | AN38: =AI38-AM38 -> 54335.479 | AO38: =IF($B$49="Real gains",MAX($B$50*AN38,0),IF($B$49="Discounted nominal gains",MAX($B$50*AK38/2,0),0)) -> 0 | AP38: =AI38-AO38 -> 256516.76 | AR38: =IF($B$10="3BR_H", INDEX('ns-combined'!$C:$D,MATCH($L38,'ns-combined'!$B:$B,0),MATCH(Council_Area,'ns-combined'!$C$1:$D$1,0))*1000, INDEX('s-combined'!$C:$D,MATCH($L38,'s-combined'!$B:$B,0),MATCH(Council_Area,'s-combined'!$C$1:$D$1,0))*1000) -> 467000 | AS38: =AS37+$AS$3 -> 29250 | AT38: 0 | AU38: =SUM($B$28:$B$29)*AR38 -> 9340 | AV38: =AR38*$B$15/4 -> 1342.625 | AW38: =SUM($AV$3:AV38) -> 43681.312 | AX38: =AR38-AS38-AU38-AW38 -> 384728.69 | AY38: =$B$36*V38 -> 1732.0504 | AZ38: =SUM(AY38:AY38)*4/AR38 -> 0.01483555 | BA38: =SUM(AY38:AY38)/V38 -> 0.35 | BB38: =IF(MortgageRate="Discounted",_xlfn.XLOOKUP(L38,'mortgage-rates'!$A:$A,'mortgage-rates'!$E:$E)/100,_xlfn.XLOOKUP(L38,'mortgage-rates'!$A:$A,'mortgage-rates'!$D:$D)/100) -> 0.0508 | BC38: =BC37-BF37 -> 210409.45 | BD38: =IF($B$16*12/3-Q38+1>0,-PMT($BB38/4,$B$16*12/3-Q38+1,BC38),0) -> 4774.332 | BE38: =BC38*($BB38/4) -> 2672.2001 | BF38: =BD38-BE38 -> 2102.1319 | BG38: =AT38+AY38+BD38 -> 6506.3824 | BH38: =INDEX(cpi!B:B,MATCH($L38,cpi!A:A)) -> 106.5 | BI38: =100*BH38/BH$3 -> 125.88652 | BJ38: =100*AC38/AC$3 -> 165.23062 | BK38: =100*AD38/AD$3 -> 161.38783 | BL38: =BJ38*GlobalPortfolio+BK38*AusPortfolio -> 164.07778 | BM38: =100*AE38/$AE$3 -> 304.52308 | BN38: =100*AR38/AR$3 -> 143.69231 | BO38: =100*AX38/AX$3 -> 121.46011
L39: =DATE(YEAR(L38),MONTH(L38)+3,1) -> 42064 | M39: =AP39 -> 270259.26 | N39: =AX39-BC39 -> 170162.32 | O39: =M39/N39 -> 1.5882439 | P39: =X39/BG39 -> 0.79503562 | Q39: 37 | R39: =EOMONTH(L39,0)-EOMONTH(L39,-3) -> 90 | T39: =IF($B$10="3BR_H", INDEX('3BR_H-processed'!$E:$E,MATCH($L39,'3BR_H-processed'!$B:$B,0),MATCH(Council_Area,'3BR_H-processed'!$E$1:$E$1,0)), INDEX('2BR_F-processed'!$E:$E,MATCH($L39,'2BR_F-processed'!$B:$B,0),MATCH(Council_Area,'2BR_F-processed'!$E$1:$E$1,0))) -> 385.76419 | U39: =IF(MOD(Q39,4)=1,T39,U38) -> 385.76419 | V39: =U39*(R39)/7 -> 4959.8252 | W39: =$B$53/4*BH39/_xlfn.XLOOKUP(Q_end,cpi!A:A,cpi!B:B) -> 147.61576 | X39: =V39+W39 -> 5107.441 | Y39: =BG39-X39 -> 1316.7253 | Z39: =Y39*$B$47 -> 0 | AA39: {=(Y39+Z39)*eff_invest} -> 1316.7253 | AB39: =AA39*(_xlfn.XLOOKUP(Q_end,cpi!A:A,cpi!B:B)/BH39) -> 1783.9902 | AC39: {=INDEX('msci-indices'!C:C,MATCH($L39,'msci-indices'!$B:$B)-2)} -> 1262.6926 | AD39: {=INDEX('msci-indices'!D:D,MATCH($L39,'msci-indices'!$B:$B)-2)} -> 1181.3297 | AE39: =AI38+AA39 -> 257833.48 | AF39: {=INDEX('msci-indices'!C:C,MATCH($L39,'msci-indices'!$B:$B)+1)} -> 1295.5073 | AG39: {=INDEX('msci-indices'!D:D,MATCH($L39,'msci-indices'!$B:$B)+1)} -> 1301.9298 | AH39: =(InvestFees/4)*AE39 -> 161.14593 | AI39: =((AF39/AC39)*GlobalPortfolio+(AG39/AD39)*AusPortfolio)*AE39-AH39 -> 270259.26 | AJ39: =AJ38+AA39 -> 168911.21 | AK39: =AI39-AJ39 -> 101348.04 | AL39: =AJ39*(_xlfn.XLOOKUP(Q_end,cpi!A:A,cpi!B:B)/BH39) -> 228852.55 | AM39: {=SUMPRODUCT($AA$3:AA39,_xlfn.SORTBY($BH$3:BH39,_xlfn.SEQUENCE(ROWS($BH$3:BH39)),-1)/$BH$3)} -> 204411.44 | AN39: =AI39-AM39 -> 65847.815 | AO39: =IF($B$49="Real gains",MAX($B$50*AN39,0),IF($B$49="Discounted nominal gains",MAX($B$50*AK39/2,0),0)) -> 0 | AP39: =AI39-AO39 -> 270259.26 | AR39: =IF($B$10="3BR_H", INDEX('ns-combined'!$C:$D,MATCH($L39,'ns-combined'!$B:$B,0),MATCH(Council_Area,'ns-combined'!$C$1:$D$1,0))*1000, INDEX('s-combined'!$C:$D,MATCH($L39,'s-combined'!$B:$B,0),MATCH(Council_Area,'s-combined'!$C$1:$D$1,0))*1000) -> 462800 | AS39: =AS38+$AS$3 -> 30062.5 | AT39: 0 | AU39: =SUM($B$28:$B$29)*AR39 -> 9256 | AV39: =AR39*$B$15/4 -> 1330.55 | AW39: =SUM($AV$3:AV39) -> 45011.863 | AX39: =AR39-AS39-AU39-AW39 -> 378469.64 | AY39: =$B$36*V39 -> 1735.9388 | AZ39: =SUM(AY39:AY39)*4/AR39 -> 0.015003793 | BA39: =SUM(AY39:AY39)/V39 -> 0.35 | BB39: =IF(MortgageRate="Discounted",_xlfn.XLOOKUP(L39,'mortgage-rates'!$A:$A,'mortgage-rates'!$E:$E)/100,_xlfn.XLOOKUP(L39,'mortgage-rates'!$A:$A,'mortgage-rates'!$D:$D)/100) -> 0.0482 | BC39: =BC38-BF38 -> 208307.32 | BD39: =IF($B$16*12/3-Q39+1>0,-PMT($BB39/4,$B$16*12/3-Q39+1,BC39),0) -> 4688.2274 | BE39: =BC39*($BB39/4) -> 2510.1032 | BF39: =BD39-BE39 -> 2178.1242 | BG39: =AT39+AY39+BD39 -> 6424.1663 | BH39: =INDEX(cpi!B:B,MATCH($L39,cpi!A:A)) -> 106.8 | BI39: =100*BH39/BH$3 -> 126.24113 | BJ39: =100*AC39/AC$3 -> 167.27073 | BK39: =100*AD39/AD$3 -> 165.69455 | BL39: =BJ39*GlobalPortfolio+BK39*AusPortfolio -> 166.79788 | BM39: =100*AE39/$AE$3 -> 310.99083 | BN39: =100*AR39/AR$3 -> 142.4 | BO39: =100*AX39/AX$3 -> 119.48411
A40: Renter investment parameters | L40: =DATE(YEAR(L39),MONTH(L39)+3,1) -> 42156 | M40: =AP40 -> 266772.88 | N40: =AX40-BC40 -> 172347.06 | O40: =M40/N40 -> 1.5478818 | P40: =X40/BG40 -> 0.80749603 | Q40: 38 | R40: =EOMONTH(L40,0)-EOMONTH(L40,-3) -> 91 | T40: =IF($B$10="3BR_H", INDEX('3BR_H-processed'!$E:$E,MATCH($L40,'3BR_H-processed'!$B:$B,0),MATCH(Council_Area,'3BR_H-processed'!$E$1:$E$1,0)), INDEX('2BR_F-processed'!$E:$E,MATCH($L40,'2BR_F-processed'!$B:$B,0),MATCH(Council_Area,'2BR_F-processed'!$E$1:$E$1,0))) -> 377.69062 | U40: =IF(MOD(Q40,4)=1,T40,U39) -> 385.76419 | V40: =U40*(R40)/7 -> 5014.9344 | W40: =$B$53/4*BH40/_xlfn.XLOOKUP(Q_end,cpi!A:A,cpi!B:B) -> 148.85971 | X40: =V40+W40 -> 5163.7941 | Y40: =BG40-X40 -> 1231.0288 | Z40: =Y40*$B$47 -> 0 | AA40: {=(Y40+Z40)*eff_invest} -> 1231.0288 | AB40: =AA40*(_xlfn.XLOOKUP(Q_end,cpi!A:A,cpi!B:B)/BH40) -> 1653.9449 | AC40: {=INDEX('msci-indices'!C:C,MATCH($L40,'msci-indices'!$B:$B)-2)} -> 1295.5073 | AD40: {=INDEX('msci-indices'!D:D,MATCH($L40,'msci-indices'!$B:$B)-2)} -> 1301.9298 | AE40: =AI39+AA40 -> 271490.28 | AF40: {=INDEX('msci-indices'!C:C,MATCH($L40,'msci-indices'!$B:$B)+1)} -> 1301.507 | AG40: {=INDEX('msci-indices'!D:D,MATCH($L40,'msci-indices'!$B:$B)+1)} -> 1215.1659 | AH40: =(InvestFees/4)*AE40 -> 169.68143 | AI40: =((AF40/AC40)*GlobalPortfolio+(AG40/AD40)*AusPortfolio)*AE40-AH40 -> 266772.88 | AJ40: =AJ39+AA40 -> 170142.24 | AK40: =AI40-AJ40 -> 96630.641 | AL40: =AJ40*(_xlfn.XLOOKUP(Q_end,cpi!A:A,cpi!B:B)/BH40) -> 228594.08 | AM40: {=SUMPRODUCT($AA$3:AA40,_xlfn.SORTBY($BH$3:BH40,_xlfn.SEQUENCE(ROWS($BH$3:BH40)),-1)/$BH$3)} -> 207133.48 | AN40: =AI40-AM40 -> 59639.408 | AO40: =IF($B$49="Real gains",MAX($B$50*AN40,0),IF($B$49="Discounted nominal gains",MAX($B$50*AK40/2,0),0)) -> 0 | AP40: =AI40-AO40 -> 266772.88 | AR40: =IF($B$10="3BR_H", INDEX('ns-combined'!$C:$D,MATCH($L40,'ns-combined'!$B:$B,0),MATCH(Council_Area,'ns-combined'!$C$1:$D$1,0))*1000, INDEX('s-combined'!$C:$D,MATCH($L40,'s-combined'!$B:$B,0),MATCH(Council_Area,'s-combined'!$C$1:$D$1,0))*1000) -> 465000 | AS40: =AS39+$AS$3 -> 30875 | AT40: 0 | AU40: =SUM($B$28:$B$29)*AR40 -> 9300 | AV40: =AR40*$B$15/4 -> 1336.875 | AW40: =SUM($AV$3:AV40) -> 46348.738 | AX40: =AR40-AS40-AU40-AW40 -> 378476.26 | AY40: =$B$36*V40 -> 1755.227 | AZ40: =SUM(AY40:AY40)*4/AR40 -> 0.015098727 | BA40: =SUM(AY40:AY40)/V40 -> 0.35 | BB40: =IF(MortgageRate="Discounted",_xlfn.XLOOKUP(L40,'mortgage-rates'!$A:$A,'mortgage-rates'!$E:$E)/100,_xlfn.XLOOKUP(L40,'mortgage-rates'!$A:$A,'mortgage-rates'!$D:$D)/100) -> 0.0467 | BC40: =BC39-BF39 -> 206129.2 | BD40: =IF($B$16*12/3-Q40+1>0,-PMT($BB40/4,$B$16*12/3-Q40+1,BC40),0) -> 4639.5959 | BE40: =BC40*($BB40/4) -> 2406.5584 | BF40: =BD40-BE40 -> 2233.0375 | BG40: =AT40+AY40+BD40 -> 6394.8229 | BH40: =INDEX(cpi!B:B,MATCH($L40,cpi!A:A)) -> 107.7 | BI40: =100*BH40/BH$3 -> 127.30496 | BJ40: =100*AC40/AC$3 -> 171.61773 | BK40: =100*AD40/AD$3 -> 182.61006 | BL40: =BJ40*GlobalPortfolio+BK40*AusPortfolio -> 174.91543 | BM40: =100*AE40/$AE$3 -> 327.46325 | BN40: =100*AR40/AR$3 -> 143.07692 | BO40: =100*AX40/AX$3 -> 119.4862
A41: % of portfolio in global equities | B41: 0.7 | C41: 0.7 | L41: =DATE(YEAR(L40),MONTH(L40)+3,1) -> 42248 | M41: =AP41 -> 246071.01 | N41: =AX41-BC41 -> 182201.98 | O41: =M41/N41 -> 1.3505398 | P41: =X41/BG41 -> 0.81408585 | Q41: 39 | R41: =EOMONTH(L41,0)-EOMONTH(L41,-3) -> 92 | T41: =IF($B$10="3BR_H", INDEX('3BR_H-processed'!$E:$E,MATCH($L41,'3BR_H-processed'!$B:$B,0),MATCH(Council_Area,'3BR_H-processed'!$E$1:$E$1,0)), INDEX('2BR_F-processed'!$E:$E,MATCH($L41,'2BR_F-processed'!$B:$B,0),MATCH(Council_Area,'2BR_F-processed'!$E$1:$E$1,0))) -> 379.11857 | U41: =IF(MOD(Q41,4)=1,T41,U40) -> 385.76419 | V41: =U41*(R41)/7 -> 5070.0436 | W41: =$B$53/4*BH41/_xlfn.XLOOKUP(Q_end,cpi!A:A,cpi!B:B) -> 148.99793 | X41: =V41+W41 -> 5219.0415 | Y41: =BG41-X41 -> 1191.8813 | Z41: =Y41*$B$47 -> 0 | AA41: {=(Y41+Z41)*eff_invest} -> 1191.8813 | AB41: =AA41*(_xlfn.XLOOKUP(Q_end,cpi!A:A,cpi!B:B)/BH41) -> 1599.8629 | AC41: {=INDEX('msci-indices'!C:C,MATCH($L41,'msci-indices'!$B:$B)-2)} -> 1301.507 | AD41: {=INDEX('msci-indices'!D:D,MATCH($L41,'msci-indices'!$B:$B)-2)} -> 1215.1659 | AE41: =AI40+AA41 -> 267964.77 | AF41: {=INDEX('msci-indices'!C:C,MATCH($L41,'msci-indices'!$B:$B)+1)} -> 1189.2855 | AG41: {=INDEX('msci-indices'!D:D,MATCH($L41,'msci-indices'!$B:$B)+1)} -> 1131.2309 | AH41: =(InvestFees/4)*AE41 -> 167.47798 | AI41: =((AF41/AC41)*GlobalPortfolio+(AG41/AD41)*AusPortfolio)*AE41-AH41 -> 246071.01 | AJ41: =AJ40+AA41 -> 171334.12 | AK41: =AI41-AJ41 -> 74736.889 | AL41: =AJ41*(_xlfn.XLOOKUP(Q_end,cpi!A:A,cpi!B:B)/BH41) -> 229981.89 | AM41: {=SUMPRODUCT($AA$3:AA41,_xlfn.SORTBY($BH$3:BH41,_xlfn.SEQUENCE(ROWS($BH$3:BH41)),-1)/$BH$3)} -> 209050.46 | AN41: =AI41-AM41 -> 37020.558 | AO41: =IF($B$49="Real gains",MAX($B$50*AN41,0),IF($B$49="Discounted nominal gains",MAX($B$50*AK41/2,0),0)) -> 0 | AP41: =AI41-AO41 -> 246071.01 | AR41: =IF($B$10="3BR_H", INDEX('ns-combined'!$C:$D,MATCH($L41,'ns-combined'!$B:$B,0),MATCH(Council_Area,'ns-combined'!$C$1:$D$1,0))*1000, INDEX('s-combined'!$C:$D,MATCH($L41,'s-combined'!$B:$B,0),MATCH(Council_Area,'s-combined'!$C$1:$D$1,0))*1000) -> 475000 | AS41: =AS40+$AS$3 -> 31687.5 | AT41: 0 | AU41: =SUM($B$28:$B$29)*AR41 -> 9500 | AV41: =AR41*$B$15/4 -> 1365.625 | AW41: =SUM($AV$3:AV41) -> 47714.363 | AX41: =AR41-AS41-AU41-AW41 -> 386098.14 | AY41: =$B$36*V41 -> 1774.5153 | AZ41: =SUM(AY41:AY41)*4/AR41 -> 0.014943286 | BA41: =SUM(AY41:AY41)/V41 -> 0.35 | BB41: =IF(MortgageRate="Discounted",_xlfn.XLOOKUP(L41,'mortgage-rates'!$A:$A,'mortgage-rates'!$E:$E)/100,_xlfn.XLOOKUP(L41,'mortgage-rates'!$A:$A,'mortgage-rates'!$D:$D)/100) -> 0.0466 | BC41: =BC40-BF40 -> 203896.16 | BD41: =IF($B$16*12/3-Q41+1>0,-PMT($BB41/4,$B$16*12/3-Q41+1,BC41),0) -> 4636.4075 | BE41: =BC41*($BB41/4) -> 2375.3903 | BF41: =BD41-BE41 -> 2261.0173 | BG41: =AT41+AY41+BD41 -> 6410.9228 | BH41: =INDEX(cpi!B:B,MATCH($L41,cpi!A:A)) -> 107.8 | BI41: =100*BH41/BH$3 -> 127.42317 | BJ41: =100*AC41/AC$3 -> 172.41252 | BK41: =100*AD41/AD$3 -> 170.44046 | BL41: =BJ41*GlobalPortfolio+BK41*AusPortfolio -> 171.8209 | BM41: =100*AE41/$AE$3 -> 323.21088 | BN41: =100*AR41/AR$3 -> 146.15385 | BO41: =100*AX41/AX$3 -> 121.89245
A42: % of portfolio in Australian equities | B42: =1-GlobalPortfolio -> 0.3 | C42: 0.3 | L42: =DATE(YEAR(L41),MONTH(L41)+3,1) -> 42339 | M42: =AP42 -> 261168.07 | N42: =AX42-BC42 -> 196941.74 | O42: =M42/N42 -> 1.3261184 | P42: =X42/BG42 -> 0.8074406 | Q42: 40 | R42: =EOMONTH(L42,0)-EOMONTH(L42,-3) -> 92 | T42: =IF($B$10="3BR_H", INDEX('3BR_H-processed'!$E:$E,MATCH($L42,'3BR_H-processed'!$B:$B,0),MATCH(Council_Area,'3BR_H-processed'!$E$1:$E$1,0)), INDEX('2BR_F-processed'!$E:$E,MATCH($L42,'2BR_F-processed'!$B:$B,0),MATCH(Council_Area,'2BR_F-processed'!$E$1:$E$1,0))) -> 380.03408 | U42: =IF(MOD(Q42,4)=1,T42,U41) -> 385.76419 | V42: =U42*(R42)/7 -> 5070.0436 | W42: =$B$53/4*BH42/_xlfn.XLOOKUP(Q_end,cpi!A:A,cpi!B:B) -> 149.68901 | X42: =V42+W42 -> 5219.7326 | Y42: =BG42-X42 -> 1244.808 | Z42: =Y42*$B$47 -> 0 | AA42: {=(Y42+Z42)*eff_invest} -> 1244.808 | AB42: =AA42*(_xlfn.XLOOKUP(Q_end,cpi!A:A,cpi!B:B)/BH42) -> 1663.1923 | AC42: {=INDEX('msci-indices'!C:C,MATCH($L42,'msci-indices'!$B:$B)-2)} -> 1189.2855 | AD42: {=INDEX('msci-indices'!D:D,MATCH($L42,'msci-indices'!$B:$B)-2)} -> 1131.2309 | AE42: =AI41+AA42 -> 247315.82 | AF42: {=INDEX('msci-indices'!C:C,MATCH($L42,'msci-indices'!$B:$B)+1)} -> 1252.6491 | AG42: {=INDEX('msci-indices'!D:D,MATCH($L42,'msci-indices'!$B:$B)+1)} -> 1204.1585 | AH42: =(InvestFees/4)*AE42 -> 154.57239 | AI42: =((AF42/AC42)*GlobalPortfolio+(AG42/AD42)*AusPortfolio)*AE42-AH42 -> 261168.07 | AJ42: =AJ41+AA42 -> 172578.93 | AK42: =AI42-AJ42 -> 88589.136 | AL42: =AJ42*(_xlfn.XLOOKUP(Q_end,cpi!A:A,cpi!B:B)/BH42) -> 230583.3 | AM42: {=SUMPRODUCT($AA$3:AA42,_xlfn.SORTBY($BH$3:BH42,_xlfn.SEQUENCE(ROWS($BH$3:BH42)),-1)/$BH$3)} -> 211406.31 | AN42: =AI42-AM42 -> 49761.761 | AO42: =IF($B$49="Real gains",MAX($B$50*AN42,0),IF($B$49="Discounted nominal gains",MAX($B$50*AK42/2,0),0)) -> 0 | AP42: =AI42-AO42 -> 261168.07 | AR42: =IF($B$10="3BR_H", INDEX('ns-combined'!$C:$D,MATCH($L42,'ns-combined'!$B:$B,0),MATCH(Council_Area,'ns-combined'!$C$1:$D$1,0))*1000, INDEX('s-combined'!$C:$D,MATCH($L42,'s-combined'!$B:$B,0),MATCH(Council_Area,'s-combined'!$C$1:$D$1,0))*1000) -> 490000 | AS42: =AS41+$AS$3 -> 32500 | AT42: 0 | AU42: =SUM($B$28:$B$29)*AR42 -> 9800 | AV42: =AR42*$B$15/4 -> 1408.75 | AW42: =SUM($AV$3:AV42) -> 49123.113 | AX42: =AR42-AS42-AU42-AW42 -> 398576.89 | AY42: =$B$36*V42 -> 1774.5153 | AZ42: =SUM(AY42:AY42)*4/AR42 -> 0.014485839 | BA42: =SUM(AY42:AY42)/V42 -> 0.35 | BB42: =IF(MortgageRate="Discounted",_xlfn.XLOOKUP(L42,'mortgage-rates'!$A:$A,'mortgage-rates'!$E:$E)/100,_xlfn.XLOOKUP(L42,'mortgage-rates'!$A:$A,'mortgage-rates'!$D:$D)/100) -> 0.0483 | BC42: =BC41-BF41 -> 201635.14 | BD42: =IF($B$16*12/3-Q42+1>0,-PMT($BB42/4,$B$16*12/3-Q42+1,BC42),0) -> 4690.0254 | BE42: =BC42*($BB42/4) -> 2434.7444 | BF42: =BD42-BE42 -> 2255.281 | BG42: =AT42+AY42+BD42 -> 6464.5406 | BH42: =INDEX(cpi!B:B,MATCH($L42,cpi!A:A)) -> 108.3 | BI42: =100*BH42/BH$3 -> 128.01418 | BJ42: =100*AC42/AC$3 -> 157.54638 | BK42: =100*AD42/AD$3 -> 158.66765 | BL42: =BJ42*GlobalPortfolio+BK42*AusPortfolio -> 157.88276 | BM42: =100*AE42/$AE$3 -> 298.30475 | BN42: =100*AR42/AR$3 -> 150.76923 | BO42: =100*AX42/AX$3 -> 125.83203
A43: Investment fees (% of investment value per year) | B43: 0.0025 | C43: 0.0025 | L43: =DATE(YEAR(L42),MONTH(L42)+3,1) -> 42430 | M43: =AP43 -> 259671.35 | N43: =AX43-BC43 -> 190624.46 | O43: =M43/N43 -> 1.3622142 | P43: =X43/BG43 -> 0.8111604 | Q43: 41 | R43: =EOMONTH(L43,0)-EOMONTH(L43,-3) -> 91 | T43: =IF($B$10="3BR_H", INDEX('3BR_H-processed'!$E:$E,MATCH($L43,'3BR_H-processed'!$B:$B,0),MATCH(Council_Area,'3BR_H-processed'!$E$1:$E$1,0)), INDEX('2BR_F-processed'!$E:$E,MATCH($L43,'2BR_F-processed'!$B:$B,0),MATCH(Council_Area,'2BR_F-processed'!$E$1:$E$1,0))) -> 392.60131 | U43: =IF(MOD(Q43,4)=1,T43,U42) -> 392.60131 | V43: =U43*(R43)/7 -> 5103.817 | W43: =$B$53/4*BH43/_xlfn.XLOOKUP(Q_end,cpi!A:A,cpi!B:B) -> 149.55079 | X43: =V43+W43 -> 5253.3678 | Y43: =BG43-X43 -> 1222.9935 | Z43: =Y43*$B$47 -> 0 | AA43: {=(Y43+Z43)*eff_invest} -> 1222.9935 | AB43: =AA43*(_xlfn.XLOOKUP(Q_end,cpi!A:A,cpi!B:B)/BH43) -> 1635.556 | AC43: {=INDEX('msci-indices'!C:C,MATCH($L43,'msci-indices'!$B:$B)-2)} -> 1252.6491 | AD43: {=INDEX('msci-indices'!D:D,MATCH($L43,'msci-indices'!$B:$B)-2)} -> 1204.1585 | AE43: =AI42+AA43 -> 262391.06 | AF43: {=INDEX('msci-indices'!C:C,MATCH($L43,'msci-indices'!$B:$B)+1)} -> 1249.9269 | AG43: {=INDEX('msci-indices'!D:D,MATCH($L43,'msci-indices'!$B:$B)+1)} -> 1171.169 | AH43: =(InvestFees/4)*AE43 -> 163.99441 | AI43: =((AF43/AC43)*GlobalPortfolio+(AG43/AD43)*AusPortfolio)*AE43-AH43 -> 259671.35 | AJ43: =AJ42+AA43 -> 173801.93 | AK43: =AI43-AJ43 -> 85869.423 | AL43: =AJ43*(_xlfn.XLOOKUP(Q_end,cpi!A:A,cpi!B:B)/BH43) -> 232431.97 | AM43: {=SUMPRODUCT($AA$3:AA43,_xlfn.SORTBY($BH$3:BH43,_xlfn.SEQUENCE(ROWS($BH$3:BH43)),-1)/$BH$3)} -> 213161.65 | AN43: =AI43-AM43 -> 46509.698 | AO43: =IF($B$49="Real gains",MAX($B$50*AN43,0),IF($B$49="Discounted nominal gains",MAX($B$50*AK43/2,0),0)) -> 0 | AP43: =AI43-AO43 -> 259671.35 | AR43: =IF($B$10="3BR_H", INDEX('ns-combined'!$C:$D,MATCH($L43,'ns-combined'!$B:$B,0),MATCH(Council_Area,'ns-combined'!$C$1:$D$1,0))*1000, INDEX('s-combined'!$C:$D,MATCH($L43,'s-combined'!$B:$B,0),MATCH(Council_Area,'s-combined'!$C$1:$D$1,0))*1000) -> 483500 | AS43: =AS42+$AS$3 -> 33312.5 | AT43: 0 | AU43: =SUM($B$28:$B$29)*AR43 -> 9670 | AV43: =AR43*$B$15/4 -> 1390.0625 | AW43: =SUM($AV$3:AV43) -> 50513.175 | AX43: =AR43-AS43-AU43-AW43 -> 390004.33 | AY43: =$B$36*V43 -> 1786.336 | AZ43: =SUM(AY43:AY43)*4/AR43 -> 0.014778374 | BA43: =SUM(AY43:AY43)/V43 -> 0.35 | BB43: =IF(MortgageRate="Discounted",_xlfn.XLOOKUP(L43,'mortgage-rates'!$A:$A,'mortgage-rates'!$E:$E)/100,_xlfn.XLOOKUP(L43,'mortgage-rates'!$A:$A,'mortgage-rates'!$D:$D)/100) -> 0.0483 | BC43: =BC42-BF42 -> 199379.86 | BD43: =IF($B$16*12/3-Q43+1>0,-PMT($BB43/4,$B$16*12/3-Q43+1,BC43),0) -> 4690.0254 | BE43: =BC43*($BB43/4) -> 2407.5118 | BF43: =BD43-BE43 -> 2282.5135 | BG43: =AT43+AY43+BD43 -> 6476.3613 | BH43: =INDEX(cpi!B:B,MATCH($L43,cpi!A:A)) -> 108.2 | BI43: =100*BH43/BH$3 -> 127.89598 | BJ43: =100*AC43/AC$3 -> 165.94025 | BK43: =100*AD43/AD$3 -> 168.89654 | BL43: =BJ43*GlobalPortfolio+BK43*AusPortfolio -> 166.82714 | BM43: =100*AE43/$AE$3 -> 316.48804 | BN43: =100*AR43/AR$3 -> 148.76923 | BO43: =100*AX43/AX$3 -> 123.12564
A44: Investing through superannuation? | B44: No | C44: No | L44: =DATE(YEAR(L43),MONTH(L43)+3,1) -> 42522 | M44: =AP44 -> 265803.29 | N44: =AX44-BC44 -> 201941.35 | O44: =M44/N44 -> 1.3162401 | P44: =X44/BG44 -> 0.82059996 | Q44: 42 | R44: =EOMONTH(L44,0)-EOMONTH(L44,-3) -> 91 | T44: =IF($B$10="3BR_H", INDEX('3BR_H-processed'!$E:$E,MATCH($L44,'3BR_H-processed'!$B:$B,0),MATCH(Council_Area,'3BR_H-processed'!$E$1:$E$1,0)), INDEX('2BR_F-processed'!$E:$E,MATCH($L44,'2BR_F-processed'!$B:$B,0),MATCH(Council_Area,'2BR_F-processed'!$E$1:$E$1,0))) -> 378.64815 | U44: =IF(MOD(Q44,4)=1,T44,U43) -> 392.60131 | V44: =U44*(R44)/7 -> 5103.817 | W44: =$B$53/4*BH44/_xlfn.XLOOKUP(Q_end,cpi!A:A,cpi!B:B) -> 150.3801 | X44: =V44+W44 -> 5254.1971 | Y44: =BG44-X44 -> 1148.6756 | Z44: =Y44*$B$47 -> 0 | AA44: {=(Y44+Z44)*eff_invest} -> 1148.6756 | AB44: =AA44*(_xlfn.XLOOKUP(Q_end,cpi!A:A,cpi!B:B)/BH44) -> 1527.6963 | AC44: {=INDEX('msci-indices'!C:C,MATCH($L44,'msci-indices'!$B:$B)-2)} -> 1249.9269 | AD44: {=INDEX('msci-indices'!D:D,MATCH($L44,'msci-indices'!$B:$B)-2)} -> 1171.169 | AE44: =AI43+AA44 -> 260820.02 | AF44: {=INDEX('msci-indices'!C:C,MATCH($L44,'msci-indices'!$B:$B)+1)} -> 1263.5195 | AG44: {=INDEX('msci-indices'!D:D,MATCH($L44,'msci-indices'!$B:$B)+1)} -> 1218.4798 | AH44: =(InvestFees/4)*AE44 -> 163.01252 | AI44: =((AF44/AC44)*GlobalPortfolio+(AG44/AD44)*AusPortfolio)*AE44-AH44 -> 265803.29 | AJ44: =AJ43+AA44 -> 174950.6 | AK44: =AI44-AJ44 -> 90852.693 | AL44: =AJ44*(_xlfn.XLOOKUP(Q_end,cpi!A:A,cpi!B:B)/BH44) -> 232677.87 | AM44: {=SUMPRODUCT($AA$3:AA44,_xlfn.SORTBY($BH$3:BH44,_xlfn.SEQUENCE(ROWS($BH$3:BH44)),-1)/$BH$3)} -> 215504.49 | AN44: =AI44-AM44 -> 50298.809 | AO44: =IF($B$49="Real gains",MAX($B$50*AN44,0),IF($B$49="Discounted nominal gains",MAX($B$50*AK44/2,0),0)) -> 0 | AP44: =AI44-AO44 -> 265803.29 | AR44: =IF($B$10="3BR_H", INDEX('ns-combined'!$C:$D,MATCH($L44,'ns-combined'!$B:$B,0),MATCH(Council_Area,'ns-combined'!$C$1:$D$1,0))*1000, INDEX('s-combined'!$C:$D,MATCH($L44,'s-combined'!$B:$B,0),MATCH(Council_Area,'s-combined'!$C$1:$D$1,0))*1000) -> 495000 | AS44: =AS43+$AS$3 -> 34125 | AT44: 0 | AU44: =SUM($B$28:$B$29)*AR44 -> 9900 | AV44: =AR44*$B$15/4 -> 1423.125 | AW44: =SUM($AV$3:AV44) -> 51936.3 | AX44: =AR44-AS44-AU44-AW44 -> 399038.7 | AY44: =$B$36*V44 -> 1786.336 | AZ44: =SUM(AY44:AY44)*4/AR44 -> 0.014435038 | BA44: =SUM(AY44:AY44)/V44 -> 0.35 | BB44: =IF(MortgageRate="Discounted",_xlfn.XLOOKUP(L44,'mortgage-rates'!$A:$A,'mortgage-rates'!$E:$E)/100,_xlfn.XLOOKUP(L44,'mortgage-rates'!$A:$A,'mortgage-rates'!$D:$D)/100) -> 0.0459 | BC44: =BC43-BF43 -> 197097.35 | BD44: =IF($B$16*12/3-Q44+1>0,-PMT($BB44/4,$B$16*12/3-Q44+1,BC44),0) -> 4616.5368 | BE44: =BC44*($BB44/4) -> 2261.6921 | BF44: =BD44-BE44 -> 2354.8447 | BG44: =AT44+AY44+BD44 -> 6402.8727 | BH44: =INDEX(cpi!B:B,MATCH($L44,cpi!A:A)) -> 108.8 | BI44: =100*BH44/BH$3 -> 128.6052 | BJ44: =100*AC44/AC$3 -> 165.57963 | BK44: =100*AD44/AD$3 -> 164.26941 | BL44: =BJ44*GlobalPortfolio+BK44*AusPortfolio -> 165.18657 | BM44: =100*AE44/$AE$3 -> 314.59311 | BN44: =100*AR44/AR$3 -> 152.30769 | BO44: =100*AX44/AX$3 -> 125.97783
A45: Marginal income tax rate (including Medicare levy) | B45: 0.32 | C45: 0.32 | L45: =DATE(YEAR(L44),MONTH(L44)+3,1) -> 42614 | M45: =AP45 -> 280746.56 | N45: =AX45-BC45 -> 206946.2 | O45: =M45/N45 -> 1.3566162 | P45: =X45/BG45 -> 0.83003328 | Q45: 43 | R45: =EOMONTH(L45,0)-EOMONTH(L45,-3) -> 92 | T45: =IF($B$10="3BR_H", INDEX('3BR_H-processed'!$E:$E,MATCH($L45,'3BR_H-processed'!$B:$B,0),MATCH(Council_Area,'3BR_H-processed'!$E$1:$E$1,0)), INDEX('2BR_F-processed'!$E:$E,MATCH($L45,'2BR_F-processed'!$B:$B,0),MATCH(Council_Area,'2BR_F-processed'!$E$1:$E$1,0))) -> 385.78684 | U45: =IF(MOD(Q45,4)=1,T45,U44) -> 392.60131 | V45: =U45*(R45)/7 -> 5159.9029 | W45: =$B$53/4*BH45/_xlfn.XLOOKUP(Q_end,cpi!A:A,cpi!B:B) -> 151.07118 | X45: =V45+W45 -> 5310.9741 | Y45: =BG45-X45 -> 1087.5333 | Z45: =Y45*$B$47 -> 0 | AA45: {=(Y45+Z45)*eff_invest} -> 1087.5333 | AB45: =AA45*(_xlfn.XLOOKUP(Q_end,cpi!A:A,cpi!B:B)/BH45) -> 1439.7627 | AC45: {=INDEX('msci-indices'!C:C,MATCH($L45,'msci-indices'!$B:$B)-2)} -> 1263.5195 | AD45: {=INDEX('msci-indices'!D:D,MATCH($L45,'msci-indices'!$B:$B)-2)} -> 1218.4798 | AE45: =AI44+AA45 -> 266890.83 | AF45: {=INDEX('msci-indices'!C:C,MATCH($L45,'msci-indices'!$B:$B)+1)} -> 1329.0259 | AG45: {=INDEX('msci-indices'!D:D,MATCH($L45,'msci-indices'!$B:$B)+1)} -> 1284.478 | AH45: =(InvestFees/4)*AE45 -> 166.80677 | AI45: =((AF45/AC45)*GlobalPortfolio+(AG45/AD45)*AusPortfolio)*AE45-AH45 -> 280746.56 | AJ45: =AJ44+AA45 -> 176038.14 | AK45: =AI45-AJ45 -> 104708.43 | AL45: =AJ45*(_xlfn.XLOOKUP(Q_end,cpi!A:A,cpi!B:B)/BH45) -> 233053.23 | AM45: {=SUMPRODUCT($AA$3:AA45,_xlfn.SORTBY($BH$3:BH45,_xlfn.SEQUENCE(ROWS($BH$3:BH45)),-1)/$BH$3)} -> 217684.6 | AN45: =AI45-AM45 -> 63061.96 | AO45: =IF($B$49="Real gains",MAX($B$50*AN45,0),IF($B$49="Discounted nominal gains",MAX($B$50*AK45/2,0),0)) -> 0 | AP45: =AI45-AO45 -> 280746.56 | AR45: =IF($B$10="3BR_H", INDEX('ns-combined'!$C:$D,MATCH($L45,'ns-combined'!$B:$B,0),MATCH(Council_Area,'ns-combined'!$C$1:$D$1,0))*1000, INDEX('s-combined'!$C:$D,MATCH($L45,'s-combined'!$B:$B,0),MATCH(Council_Area,'s-combined'!$C$1:$D$1,0))*1000) -> 500000 | AS45: =AS44+$AS$3 -> 34937.5 | AT45: 0 | AU45: =SUM($B$28:$B$29)*AR45 -> 10000 | AV45: =AR45*$B$15/4 -> 1437.5 | AW45: =SUM($AV$3:AV45) -> 53373.8 | AX45: =AR45-AS45-AU45-AW45 -> 401688.7 | AY45: =$B$36*V45 -> 1805.966 | AZ45: =SUM(AY45:AY45)*4/AR45 -> 0.014447728 | BA45: =SUM(AY45:AY45)/V45 -> 0.35 | BB45: =IF(MortgageRate="Discounted",_xlfn.XLOOKUP(L45,'mortgage-rates'!$A:$A,'mortgage-rates'!$E:$E)/100,_xlfn.XLOOKUP(L45,'mortgage-rates'!$A:$A,'mortgage-rates'!$D:$D)/100) -> 0.0451 | BC45: =BC44-BF44 -> 194742.5 | BD45: =IF($B$16*12/3-Q45+1>0,-PMT($BB45/4,$B$16*12/3-Q45+1,BC45),0) -> 4592.5414 | BE45: =BC45*($BB45/4) -> 2195.7217 | BF45: =BD45-BE45 -> 2396.8196 | BG45: =AT45+AY45+BD45 -> 6398.5074 | BH45: =INDEX(cpi!B:B,MATCH($L45,cpi!A:A)) -> 109.3 | BI45: =100*BH45/BH$3 -> 129.19622 | BJ45: =100*AC45/AC$3 -> 167.38027 | BK45: =100*AD45/AD$3 -> 170.90526 | BL45: =BJ45*GlobalPortfolio+BK45*AusPortfolio -> 168.43777 | BM45: =100*AE45/$AE$3 -> 321.91552 | BN45: =100*AR45/AR$3 -> 153.84615 | BO45: =100*AX45/AX$3 -> 126.81444
A46: Concessional super contributions tax rate | B46: 0.15 | C46: 0.15 | L46: =DATE(YEAR(L45),MONTH(L45)+3,1) -> 42705 | M46: =AP46 -> 290289.08 | N46: =AX46-BC46 -> 221749.89 | O46: =M46/N46 -> 1.3090833 | P46: =X46/BG46 -> 0.83014129 | Q46: 44 | R46: =EOMONTH(L46,0)-EOMONTH(L46,-3) -> 92 | T46: =IF($B$10="3BR_H", INDEX('3BR_H-processed'!$E:$E,MATCH($L46,'3BR_H-processed'!$B:$B,0),MATCH(Council_Area,'3BR_H-processed'!$E$1:$E$1,0)), INDEX('2BR_F-processed'!$E:$E,MATCH($L46,'2BR_F-processed'!$B:$B,0),MATCH(Council_Area,'2BR_F-processed'!$E$1:$E$1,0))) -> 381.60815 | U46: =IF(MOD(Q46,4)=1,T46,U45) -> 392.60131 | V46: =U46*(R46)/7 -> 5159.9029 | W46: =$B$53/4*BH46/_xlfn.XLOOKUP(Q_end,cpi!A:A,cpi!B:B) -> 151.76227 | X46: =V46+W46 -> 5311.6652 | Y46: =BG46-X46 -> 1086.8422 | Z46: =Y46*$B$47 -> 0 | AA46: {=(Y46+Z46)*eff_invest} -> 1086.8422 | AB46: =AA46*(_xlfn.XLOOKUP(Q_end,cpi!A:A,cpi!B:B)/BH46) -> 1432.2957 | AC46: {=INDEX('msci-indices'!C:C,MATCH($L46,'msci-indices'!$B:$B)-2)} -> 1329.0259 | AD46: {=INDEX('msci-indices'!D:D,MATCH($L46,'msci-indices'!$B:$B)-2)} -> 1284.478 | AE46: =AI45+AA46 -> 281833.41 | AF46: {=INDEX('msci-indices'!C:C,MATCH($L46,'msci-indices'!$B:$B)+1)} -> 1355.3009 | AG46: {=INDEX('msci-indices'!D:D,MATCH($L46,'msci-indices'!$B:$B)+1)} -> 1356.3585 | AH46: =(InvestFees/4)*AE46 -> 176.14588 | AI46: =((AF46/AC46)*GlobalPortfolio+(AG46/AD46)*AusPortfolio)*AE46-AH46 -> 290289.08 | AJ46: =AJ45+AA46 -> 177124.98 | AK46: =AI46-AJ46 -> 113164.1 | AL46: =AJ46*(_xlfn.XLOOKUP(Q_end,cpi!A:A,cpi!B:B)/BH46) -> 233424.26 | AM46: {=SUMPRODUCT($AA$3:AA46,_xlfn.SORTBY($BH$3:BH46,_xlfn.SEQUENCE(ROWS($BH$3:BH46)),-1)/$BH$3)} -> 219857.97 | AN46: =AI46-AM46 -> 70431.104 | AO46: =IF($B$49="Real gains",MAX($B$50*AN46,0),IF($B$49="Discounted nominal gains",MAX($B$50*AK46/2,0),0)) -> 0 | AP46: =AI46-AO46 -> 290289.08 | AR46: =IF($B$10="3BR_H", INDEX('ns-combined'!$C:$D,MATCH($L46,'ns-combined'!$B:$B,0),MATCH(Council_Area,'ns-combined'!$C$1:$D$1,0))*1000, INDEX('s-combined'!$C:$D,MATCH($L46,'s-combined'!$B:$B,0),MATCH(Council_Area,'s-combined'!$C$1:$D$1,0))*1000) -> 515000 | AS46: =AS45+$AS$3 -> 35750 | AT46: 0 | AU46: =SUM($B$28:$B$29)*AR46 -> 10300 | AV46: =AR46*$B$15/4 -> 1480.625 | AW46: =SUM($AV$3:AV46) -> 54854.425 | AX46: =AR46-AS46-AU46-AW46 -> 414095.58 | AY46: =$B$36*V46 -> 1805.966 | AZ46: =SUM(AY46:AY46)*4/AR46 -> 0.014026921 | BA46: =SUM(AY46:AY46)/V46 -> 0.35 | BB46: =IF(MortgageRate="Discounted",_xlfn.XLOOKUP(L46,'mortgage-rates'!$A:$A,'mortgage-rates'!$E:$E)/100,_xlfn.XLOOKUP(L46,'mortgage-rates'!$A:$A,'mortgage-rates'!$D:$D)/100) -> 0.0451 | BC46: =BC45-BF45 -> 192345.68 | BD46: =IF($B$16*12/3-Q46+1>0,-PMT($BB46/4,$B$16*12/3-Q46+1,BC46),0) -> 4592.5414 | BE46: =BC46*($BB46/4) -> 2168.6976 | BF46: =BD46-BE46 -> 2423.8438 | BG46: =AT46+AY46+BD46 -> 6398.5074 | BH46: =INDEX(cpi!B:B,MATCH($L46,cpi!A:A)) -> 109.8 | BI46: =100*BH46/BH$3 -> 129.78723 | BJ46: =100*AC46/AC$3 -> 176.05799 | BK46: =100*AD46/AD$3 -> 180.16225 | BL46: =BJ46*GlobalPortfolio+BK46*AusPortfolio -> 177.28927 | BM46: =100*AE46/$AE$3 -> 339.9388 | BN46: =100*AR46/AR$3 -> 158.46154 | BO46: =100*AX46/AX$3 -> 130.73133
A47: Tax concessions on contributions (0% if not investing through super) | B47: =IF(B44="Yes",B45-B46,0) -> 0 | C47: 0 | L47: =DATE(YEAR(L46),MONTH(L46)+3,1) -> 42795 | M47: =AP47 -> 308301.51 | N47: =AX47-BC47 -> 216994.98 | O47: =M47/N47 -> 1.4207771 | P47: =X47/BG47 -> 0.82148626 | Q47: 45 | R47: =EOMONTH(L47,0)-EOMONTH(L47,-3) -> 90 | T47: =IF($B$10="3BR_H", INDEX('3BR_H-processed'!$E:$E,MATCH($L47,'3BR_H-processed'!$B:$B,0),MATCH(Council_Area,'3BR_H-processed'!$E$1:$E$1,0)), INDEX('2BR_F-processed'!$E:$E,MATCH($L47,'2BR_F-processed'!$B:$B,0),MATCH(Council_Area,'2BR_F-processed'!$E$1:$E$1,0))) -> 395.69597 | U47: =IF(MOD(Q47,4)=1,T47,U46) -> 395.69597 | V47: =U47*(R47)/7 -> 5087.5196 | W47: =$B$53/4*BH47/_xlfn.XLOOKUP(Q_end,cpi!A:A,cpi!B:B) -> 152.72979 | X47: =V47+W47 -> 5240.2493 | Y47: =BG47-X47 -> 1138.7366 | Z47: =Y47*$B$47 -> 0 | AA47: {=(Y47+Z47)*eff_invest} -> 1138.7366 | AB47: =AA47*(_xlfn.XLOOKUP(Q_end,cpi!A:A,cpi!B:B)/BH47) -> 1491.1782 | AC47: {=INDEX('msci-indices'!C:C,MATCH($L47,'msci-indices'!$B:$B)-2)} -> 1355.3009 | AD47: {=INDEX('msci-indices'!D:D,MATCH($L47,'msci-indices'!$B:$B)-2)} -> 1356.3585 | AE47: =AI46+AA47 -> 291427.81 | AF47: {=INDEX('msci-indices'!C:C,MATCH($L47,'msci-indices'!$B:$B)+1)} -> 1439.618 | AG47: {=INDEX('msci-indices'!D:D,MATCH($L47,'msci-indices'!$B:$B)+1)} -> 1424.0685 | AH47: =(InvestFees/4)*AE47 -> 182.14238 | AI47: =((AF47/AC47)*GlobalPortfolio+(AG47/AD47)*AusPortfolio)*AE47-AH47 -> 308301.51 | AJ47: =AJ46+AA47 -> 178263.71 | AK47: =AI47-AJ47 -> 130037.8 | AL47: =AJ47*(_xlfn.XLOOKUP(Q_end,cpi!A:A,cpi!B:B)/BH47) -> 233436.74 | AM47: {=SUMPRODUCT($AA$3:AA47,_xlfn.SORTBY($BH$3:BH47,_xlfn.SEQUENCE(ROWS($BH$3:BH47)),-1)/$BH$3)} -> 222280.74 | AN47: =AI47-AM47 -> 86020.777 | AO47: =IF($B$49="Real gains",MAX($B$50*AN47,0),IF($B$49="Discounted nominal gains",MAX($B$50*AK47/2,0),0)) -> 0 | AP47: =AI47-AO47 -> 308301.51 | AR47: =IF($B$10="3BR_H", INDEX('ns-combined'!$C:$D,MATCH($L47,'ns-combined'!$B:$B,0),MATCH(Council_Area,'ns-combined'!$C$1:$D$1,0))*1000, INDEX('s-combined'!$C:$D,MATCH($L47,'s-combined'!$B:$B,0),MATCH(Council_Area,'s-combined'!$C$1:$D$1,0))*1000) -> 510000 | AS47: =AS46+$AS$3 -> 36562.5 | AT47: 0 | AU47: =SUM($B$28:$B$29)*AR47 -> 10200 | AV47: =AR47*$B$15/4 -> 1466.25 | AW47: =SUM($AV$3:AV47) -> 56320.675 | AX47: =AR47-AS47-AU47-AW47 -> 406916.83 | AY47: =$B$36*V47 -> 1780.6318 | AZ47: =SUM(AY47:AY47)*4/AR47 -> 0.01396574 | BA47: =SUM(AY47:AY47)/V47 -> 0.35 | BB47: =IF(MortgageRate="Discounted",_xlfn.XLOOKUP(L47,'mortgage-rates'!$A:$A,'mortgage-rates'!$E:$E)/100,_xlfn.XLOOKUP(L47,'mortgage-rates'!$A:$A,'mortgage-rates'!$D:$D)/100) -> 0.0453 | BC47: =BC46-BF46 -> 189921.84 | BD47: =IF($B$16*12/3-Q47+1>0,-PMT($BB47/4,$B$16*12/3-Q47+1,BC47),0) -> 4598.3541 | BE47: =BC47*($BB47/4) -> 2150.8648 | BF47: =BD47-BE47 -> 2447.4893 | BG47: =AT47+AY47+BD47 -> 6378.9859 | BH47: =INDEX(cpi!B:B,MATCH($L47,cpi!A:A)) -> 110.5 | BI47: =100*BH47/BH$3 -> 130.61466 | BJ47: =100*AC47/AC$3 -> 179.53868 | BK47: =100*AD47/AD$3 -> 190.24428 | BL47: =BJ47*GlobalPortfolio+BK47*AusPortfolio -> 182.75036 | BM47: =100*AE47/$AE$3 -> 351.51128 | BN47: =100*AR47/AR$3 -> 156.92308 | BO47: =100*AX47/AX$3 -> 128.46498
A48: Marginal income tax rate on withdrawal | B48: 0.32 | C48: 0.32 | L48: =DATE(YEAR(L47),MONTH(L47)+3,1) -> 42887 | M48: =AP48 -> 316203.65 | N48: =AX48-BC48 -> 224980.72 | O48: =M48/N48 -> 1.40547 | P48: =X48/BG48 -> 0.82972094 | Q48: 46 | R48: =EOMONTH(L48,0)-EOMONTH(L48,-3) -> 91 | T48: =IF($B$10="3BR_H", INDEX('3BR_H-processed'!$E:$E,MATCH($L48,'3BR_H-processed'!$B:$B,0),MATCH(Council_Area,'3BR_H-processed'!$E$1:$E$1,0)), INDEX('2BR_F-processed'!$E:$E,MATCH($L48,'2BR_F-processed'!$B:$B,0),MATCH(Council_Area,'2BR_F-processed'!$E$1:$E$1,0))) -> 381.18279 | U48: =IF(MOD(Q48,4)=1,T48,U47) -> 395.69597 | V48: =U48*(R48)/7 -> 5144.0475 | W48: =$B$53/4*BH48/_xlfn.XLOOKUP(Q_end,cpi!A:A,cpi!B:B) -> 153.28265 | X48: =V48+W48 -> 5297.3302 | Y48: =BG48-X48 -> 1087.1419 | Z48: =Y48*$B$47 -> 0 | AA48: {=(Y48+Z48)*eff_invest} -> 1087.1419 | AB48: =AA48*(_xlfn.XLOOKUP(Q_end,cpi!A:A,cpi!B:B)/BH48) -> 1418.4801 | AC48: {=INDEX('msci-indices'!C:C,MATCH($L48,'msci-indices'!$B:$B)-2)} -> 1439.618 | AD48: {=INDEX('msci-indices'!D:D,MATCH($L48,'msci-indices'!$B:$B)-2)} -> 1424.0685 | AE48: =AI47+AA48 -> 309388.66 | AF48: {=INDEX('msci-indices'!C:C,MATCH($L48,'msci-indices'!$B:$B)+1)} -> 1498.0163 | AG48: {=INDEX('msci-indices'!D:D,MATCH($L48,'msci-indices'!$B:$B)+1)} -> 1396.8057 | AH48: =(InvestFees/4)*AE48 -> 193.36791 | AI48: =((AF48/AC48)*GlobalPortfolio+(AG48/AD48)*AusPortfolio)*AE48-AH48 -> 316203.65 | AJ48: =AJ47+AA48 -> 179350.86 | AK48: =AI48-AJ48 -> 136852.8 | AL48: =AJ48*(_xlfn.XLOOKUP(Q_end,cpi!A:A,cpi!B:B)/BH48) -> 234013.24 | AM48: {=SUMPRODUCT($AA$3:AA48,_xlfn.SORTBY($BH$3:BH48,_xlfn.SEQUENCE(ROWS($BH$3:BH48)),-1)/$BH$3)} -> 224376.45 | AN48: =AI48-AM48 -> 91827.205 | AO48: =IF($B$49="Real gains",MAX($B$50*AN48,0),IF($B$49="Discounted nominal gains",MAX($B$50*AK48/2,0),0)) -> 0 | AP48: =AI48-AO48 -> 316203.65 | AR48: =IF($B$10="3BR_H", INDEX('ns-combined'!$C:$D,MATCH($L48,'ns-combined'!$B:$B,0),MATCH(Council_Area,'ns-combined'!$C$1:$D$1,0))*1000, INDEX('s-combined'!$C:$D,MATCH($L48,'s-combined'!$B:$B,0),MATCH(Council_Area,'s-combined'!$C$1:$D$1,0))*1000) -> 518000 | AS48: =AS47+$AS$3 -> 37375 | AT48: 0 | AU48: =SUM($B$28:$B$29)*AR48 -> 10360 | AV48: =AR48*$B$15/4 -> 1489.25 | AW48: =SUM($AV$3:AV48) -> 57809.925 | AX48: =AR48-AS48-AU48-AW48 -> 412455.08 | AY48: =$B$36*V48 -> 1800.4166 | AZ48: =SUM(AY48:AY48)*4/AR48 -> 0.013902831 | BA48: =SUM(AY48:AY48)/V48 -> 0.35 | BB48: =IF(MortgageRate="Discounted",_xlfn.XLOOKUP(L48,'mortgage-rates'!$A:$A,'mortgage-rates'!$E:$E)/100,_xlfn.XLOOKUP(L48,'mortgage-rates'!$A:$A,'mortgage-rates'!$D:$D)/100) -> 0.0448 | BC48: =BC47-BF47 -> 187474.35 | BD48: =IF($B$16*12/3-Q48+1>0,-PMT($BB48/4,$B$16*12/3-Q48+1,BC48),0) -> 4584.0555 | BE48: =BC48*($BB48/4) -> 2099.7127 | BF48: =BD48-BE48 -> 2484.3428 | BG48: =AT48+AY48+BD48 -> 6384.4721 | BH48: =INDEX(cpi!B:B,MATCH($L48,cpi!A:A)) -> 110.9 | BI48: =100*BH48/BH$3 -> 131.08747 | BJ48: =100*AC48/AC$3 -> 190.70829 | BK48: =100*AD48/AD$3 -> 199.74136 | BL48: =BJ48*GlobalPortfolio+BK48*AusPortfolio -> 193.41821 | BM48: =100*AE48/$AE$3 -> 373.1751 | BN48: =100*AR48/AR$3 -> 159.38462 | BO48: =100*AX48/AX$3 -> 130.21342
A49: Consider CGT? Note: Unlikely to reflect realistic tax liabilities | B49: No | C49: No | L49: =DATE(YEAR(L48),MONTH(L48)+3,1) -> 42979 | M49: =AP49 -> 329185.58 | N49: =AX49-BC49 -> 232003.19 | O49: =M49/N49 -> 1.4188839 | P49: =X49/BG49 -> 0.8364378 | Q49: 47 | R49: =EOMONTH(L49,0)-EOMONTH(L49,-3) -> 92 | T49: =IF($B$10="3BR_H", INDEX('3BR_H-processed'!$E:$E,MATCH($L49,'3BR_H-processed'!$B:$B,0),MATCH(Council_Area,'3BR_H-processed'!$E$1:$E$1,0)), INDEX('2BR_F-processed'!$E:$E,MATCH($L49,'2BR_F-processed'!$B:$B,0),MATCH(Council_Area,'2BR_F-processed'!$E$1:$E$1,0))) -> 382.14948 | U49: =IF(MOD(Q49,4)=1,T49,U48) -> 395.69597 | V49: =U49*(R49)/7 -> 5200.5755 | W49: =$B$53/4*BH49/_xlfn.XLOOKUP(Q_end,cpi!A:A,cpi!B:B) -> 153.83552 | X49: =V49+W49 -> 5354.4111 | Y49: =BG49-X49 -> 1047.0345 | Z49: =Y49*$B$47 -> 0 | AA49: {=(Y49+Z49)*eff_invest} -> 1047.0345 | AB49: =AA49*(_xlfn.XLOOKUP(Q_end,cpi!A:A,cpi!B:B)/BH49) -> 1361.239 | AC49: {=INDEX('msci-indices'!C:C,MATCH($L49,'msci-indices'!$B:$B)-2)} -> 1498.0163 | AD49: {=INDEX('msci-indices'!D:D,MATCH($L49,'msci-indices'!$B:$B)-2)} -> 1396.8057 | AE49: =AI48+AA49 -> 317250.69 | AF49: {=INDEX('msci-indices'!C:C,MATCH($L49,'msci-indices'!$B:$B)+1)} -> 1573.3489 | AG49: {=INDEX('msci-indices'!D:D,MATCH($L49,'msci-indices'!$B:$B)+1)} -> 1410.974 | AH49: =(InvestFees/4)*AE49 -> 198.28168 | AI49: =((AF49/AC49)*GlobalPortfolio+(AG49/AD49)*AusPortfolio)*AE49-AH49 -> 329185.58 | AJ49: =AJ48+AA49 -> 180397.89 | AK49: =AI49-AJ49 -> 148787.69 | AL49: =AJ49*(_xlfn.XLOOKUP(Q_end,cpi!A:A,cpi!B:B)/BH49) -> 234533.47 | AM49: {=SUMPRODUCT($AA$3:AA49,_xlfn.SORTBY($BH$3:BH49,_xlfn.SEQUENCE(ROWS($BH$3:BH49)),-1)/$BH$3)} -> 226436.63 | AN49: =AI49-AM49 -> 102748.95 | AO49: =IF($B$49="Real gains",MAX($B$50*AN49,0),IF($B$49="Discounted nominal gains",MAX($B$50*AK49/2,0),0)) -> 0 | AP49: =AI49-AO49 -> 329185.58 | AR49: =IF($B$10="3BR_H", INDEX('ns-combined'!$C:$D,MATCH($L49,'ns-combined'!$B:$B,0),MATCH(Council_Area,'ns-combined'!$C$1:$D$1,0))*1000, INDEX('s-combined'!$C:$D,MATCH($L49,'s-combined'!$B:$B,0),MATCH(Council_Area,'s-combined'!$C$1:$D$1,0))*1000) -> 525000 | AS49: =AS48+$AS$3 -> 38187.5 | AT49: 0 | AU49: =SUM($B$28:$B$29)*AR49 -> 10500 | AV49: =AR49*$B$15/4 -> 1509.375 | AW49: =SUM($AV$3:AV49) -> 59319.3 | AX49: =AR49-AS49-AU49-AW49 -> 416993.2 | AY49: =$B$36*V49 -> 1820.2014 | AZ49: =SUM(AY49:AY49)*4/AR49 -> 0.013868201 | BA49: =SUM(AY49:AY49)/V49 -> 0.35 | BB49: =IF(MortgageRate="Discounted",_xlfn.XLOOKUP(L49,'mortgage-rates'!$A:$A,'mortgage-rates'!$E:$E)/100,_xlfn.XLOOKUP(L49,'mortgage-rates'!$A:$A,'mortgage-rates'!$D:$D)/100) -> 0.0447 | BC49: =BC48-BF48 -> 184990.01 | BD49: =IF($B$16*12/3-Q49+1>0,-PMT($BB49/4,$B$16*12/3-Q49+1,BC49),0) -> 4581.2441 | BE49: =BC49*($BB49/4) -> 2067.2633 | BF49: =BD49-BE49 -> 2513.9808 | BG49: =AT49+AY49+BD49 -> 6401.4456 | BH49: =INDEX(cpi!B:B,MATCH($L49,cpi!A:A)) -> 111.3 | BI49: =100*BH49/BH$3 -> 131.56028 | BJ49: =100*AC49/AC$3 -> 198.4444 | BK49: =100*AD49/AD$3 -> 195.91744 | BL49: =BJ49*GlobalPortfolio+BK49*AusPortfolio -> 197.68631 | BM49: =100*AE49/$AE$3 -> 382.65804 | BN49: =100*AR49/AR$3 -> 161.53846 | BO49: =100*AX49/AX$3 -> 131.64612
A50: Marginal CGT & dividend income tax rate (0% if investing through super) | B50: =IF(OR(B44="Yes",B49="No"),0,MAX(0.3,B48)) -> 0 | C50: 0 | L50: =DATE(YEAR(L49),MONTH(L49)+3,1) -> 43070 | M50: =AP50 -> 350435.47 | N50: =AX50-BC50 -> 241966.55 | O50: =M50/N50 -> 1.4482807 | P50: =X50/BG50 -> 0.83516642 | Q50: 48 | R50: =EOMONTH(L50,0)-EOMONTH(L50,-3) -> 92 | T50: =IF($B$10="3BR_H", INDEX('3BR_H-processed'!$E:$E,MATCH($L50,'3BR_H-processed'!$B:$B,0),MATCH(Council_Area,'3BR_H-processed'!$E$1:$E$1,0)), INDEX('2BR_F-processed'!$E:$E,MATCH($L50,'2BR_F-processed'!$B:$B,0),MATCH(Council_Area,'2BR_F-processed'!$E$1:$E$1,0))) -> 382.47985 | U50: =IF(MOD(Q50,4)=1,T50,U49) -> 395.69597 | V50: =U50*(R50)/7 -> 5200.5755 | W50: =$B$53/4*BH50/_xlfn.XLOOKUP(Q_end,cpi!A:A,cpi!B:B) -> 154.94126 | X50: =V50+W50 -> 5355.5168 | Y50: =BG50-X50 -> 1056.9977 | Z50: =Y50*$B$47 -> 0 | AA50: {=(Y50+Z50)*eff_invest} -> 1056.9977 | AB50: =AA50*(_xlfn.XLOOKUP(Q_end,cpi!A:A,cpi!B:B)/BH50) -> 1364.3851 | AC50: {=INDEX('msci-indices'!C:C,MATCH($L50,'msci-indices'!$B:$B)-2)} -> 1573.3489 | AD50: {=INDEX('msci-indices'!D:D,MATCH($L50,'msci-indices'!$B:$B)-2)} -> 1410.974 | AE50: =AI49+AA50 -> 330242.58 | AF50: {=INDEX('msci-indices'!C:C,MATCH($L50,'msci-indices'!$B:$B)+1)} -> 1659.3666 | AG50: {=INDEX('msci-indices'!D:D,MATCH($L50,'msci-indices'!$B:$B)+1)} -> 1521.5021 | AH50: =(InvestFees/4)*AE50 -> 206.40161 | AI50: =((AF50/AC50)*GlobalPortfolio+(AG50/AD50)*AusPortfolio)*AE50-AH50 -> 350435.47 | AJ50: =AJ49+AA50 -> 181454.89 | AK50: =AI50-AJ50 -> 168980.58 | AL50: =AJ50*(_xlfn.XLOOKUP(Q_end,cpi!A:A,cpi!B:B)/BH50) -> 234224.11 | AM50: {=SUMPRODUCT($AA$3:AA50,_xlfn.SORTBY($BH$3:BH50,_xlfn.SEQUENCE(ROWS($BH$3:BH50)),-1)/$BH$3)} -> 228903.57 | AN50: =AI50-AM50 -> 121531.9 | AO50: =IF($B$49="Real gains",MAX($B$50*AN50,0),IF($B$49="Discounted nominal gains",MAX($B$50*AK50/2,0),0)) -> 0 | AP50: =AI50-AO50 -> 350435.47 | AR50: =IF($B$10="3BR_H", INDEX('ns-combined'!$C:$D,MATCH($L50,'ns-combined'!$B:$B,0),MATCH(Council_Area,'ns-combined'!$C$1:$D$1,0))*1000, INDEX('s-combined'!$C:$D,MATCH($L50,'s-combined'!$B:$B,0),MATCH(Council_Area,'s-combined'!$C$1:$D$1,0))*1000) -> 535000 | AS50: =AS49+$AS$3 -> 39000 | AT50: 0 | AU50: =SUM($B$28:$B$29)*AR50 -> 10700 | AV50: =AR50*$B$15/4 -> 1538.125 | AW50: =SUM($AV$3:AV50) -> 60857.425 | AX50: =AR50-AS50-AU50-AW50 -> 424442.58 | AY50: =$B$36*V50 -> 1820.2014 | AZ50: =SUM(AY50:AY50)*4/AR50 -> 0.013608983 | BA50: =SUM(AY50:AY50)/V50 -> 0.35 | BB50: =IF(MortgageRate="Discounted",_xlfn.XLOOKUP(L50,'mortgage-rates'!$A:$A,'mortgage-rates'!$E:$E)/100,_xlfn.XLOOKUP(L50,'mortgage-rates'!$A:$A,'mortgage-rates'!$D:$D)/100) -> 0.0451 | BC50: =BC49-BF49 -> 182476.03 | BD50: =IF($B$16*12/3-Q50+1>0,-PMT($BB50/4,$B$16*12/3-Q50+1,BC50),0) -> 4592.3131 | BE50: =BC50*($BB50/4) -> 2057.4172 | BF50: =BD50-BE50 -> 2534.8958 | BG50: =AT50+AY50+BD50 -> 6412.5145 | BH50: =INDEX(cpi!B:B,MATCH($L50,cpi!A:A)) -> 112.1 | BI50: =100*BH50/BH$3 -> 132.50591 | BJ50: =100*AC50/AC$3 -> 208.42381 | BK50: =100*AD50/AD$3 -> 197.90471 | BL50: =BJ50*GlobalPortfolio+BK50*AusPortfolio -> 205.26808 | BM50: =100*AE50/$AE$3 -> 398.32846 | BN50: =100*AR50/AR$3 -> 164.61538 | BO50: =100*AX50/AX$3 -> 133.99791
L51: =DATE(YEAR(L50),MONTH(L50)+3,1) -> 43160 | M51: =AP51 -> 344244.29 | N51: =AX51-BC51 -> 233356.69 | O51: =M51/N51 -> 1.475185 | P51: =X51/BG51 -> 0.82176832 | Q51: 49 | R51: =EOMONTH(L51,0)-EOMONTH(L51,-3) -> 90 | T51: =IF($B$10="3BR_H", INDEX('3BR_H-processed'!$E:$E,MATCH($L51,'3BR_H-processed'!$B:$B,0),MATCH(Council_Area,'3BR_H-processed'!$E$1:$E$1,0)), INDEX('2BR_F-processed'!$E:$E,MATCH($L51,'2BR_F-processed'!$B:$B,0),MATCH(Council_Area,'2BR_F-processed'!$E$1:$E$1,0))) -> 395.01841 | U51: =IF(MOD(Q51,4)=1,T51,U50) -> 395.01841 | V51: =U51*(R51)/7 -> 5078.8081 | W51: =$B$53/4*BH51/_xlfn.XLOOKUP(Q_end,cpi!A:A,cpi!B:B) -> 155.77056 | X51: =V51+W51 -> 5234.5786 | Y51: =BG51-X51 -> 1135.3172 | Z51: =Y51*$B$47 -> 0 | AA51: {=(Y51+Z51)*eff_invest} -> 1135.3172 | AB51: =AA51*(_xlfn.XLOOKUP(Q_end,cpi!A:A,cpi!B:B)/BH51) -> 1457.6788 | AC51: {=INDEX('msci-indices'!C:C,MATCH($L51,'msci-indices'!$B:$B)-2)} -> 1659.3666 | AD51: {=INDEX('msci-indices'!D:D,MATCH($L51,'msci-indices'!$B:$B)-2)} -> 1521.5021 | AE51: =AI50+AA51 -> 351570.79 | AF51: {=INDEX('msci-indices'!C:C,MATCH($L51,'msci-indices'!$B:$B)+1)} -> 1639.7569 | AG51: {=INDEX('msci-indices'!D:D,MATCH($L51,'msci-indices'!$B:$B)+1)} -> 1460.9363 | AH51: =(InvestFees/4)*AE51 -> 219.73174 | AI51: =((AF51/AC51)*GlobalPortfolio+(AG51/AD51)*AusPortfolio)*AE51-AH51 -> 344244.29 | AJ51: =AJ50+AA51 -> 182590.21 | AK51: =AI51-AJ51 -> 161654.08 | AL51: =AJ51*(_xlfn.XLOOKUP(Q_end,cpi!A:A,cpi!B:B)/BH51) -> 234434.81 | AM51: {=SUMPRODUCT($AA$3:AA51,_xlfn.SORTBY($BH$3:BH51,_xlfn.SEQUENCE(ROWS($BH$3:BH51)),-1)/$BH$3)} -> 231265.05 | AN51: =AI51-AM51 -> 112979.23 | AO51: =IF($B$49="Real gains",MAX($B$50*AN51,0),IF($B$49="Discounted nominal gains",MAX($B$50*AK51/2,0),0)) -> 0 | AP51: =AI51-AO51 -> 344244.29 | AR51: =IF($B$10="3BR_H", INDEX('ns-combined'!$C:$D,MATCH($L51,'ns-combined'!$B:$B,0),MATCH(Council_Area,'ns-combined'!$C$1:$D$1,0))*1000, INDEX('s-combined'!$C:$D,MATCH($L51,'s-combined'!$B:$B,0),MATCH(Council_Area,'s-combined'!$C$1:$D$1,0))*1000) -> 526000 | AS51: =AS50+$AS$3 -> 39812.5 | AT51: 0 | AU51: =SUM($B$28:$B$29)*AR51 -> 10520 | AV51: =AR51*$B$15/4 -> 1512.25 | AW51: =SUM($AV$3:AV51) -> 62369.675 | AX51: =AR51-AS51-AU51-AW51 -> 413297.83 | AY51: =$B$36*V51 -> 1777.5828 | AZ51: =SUM(AY51:AY51)*4/AR51 -> 0.01351774 | BA51: =SUM(AY51:AY51)/V51 -> 0.35 | BB51: =IF(MortgageRate="Discounted",_xlfn.XLOOKUP(L51,'mortgage-rates'!$A:$A,'mortgage-rates'!$E:$E)/100,_xlfn.XLOOKUP(L51,'mortgage-rates'!$A:$A,'mortgage-rates'!$D:$D)/100) -> 0.0451 | BC51: =BC50-BF50 -> 179941.13 | BD51: =IF($B$16*12/3-Q51+1>0,-PMT($BB51/4,$B$16*12/3-Q51+1,BC51),0) -> 4592.3131 | BE51: =BC51*($BB51/4) -> 2028.8363 | BF51: =BD51-BE51 -> 2563.4768 | BG51: =AT51+AY51+BD51 -> 6369.8959 | BH51: =INDEX(cpi!B:B,MATCH($L51,cpi!A:A)) -> 112.7 | BI51: =100*BH51/BH$3 -> 133.21513 | BJ51: =100*AC51/AC$3 -> 219.81871 | BK51: =100*AD51/AD$3 -> 213.4075 | BL51: =BJ51*GlobalPortfolio+BK51*AusPortfolio -> 217.89535 | BM51: =100*AE51/$AE$3 -> 424.05389 | BN51: =100*AR51/AR$3 -> 161.84615 | BO51: =100*AX51/AX$3 -> 130.47948
A52: Other renter parameters | L52: =DATE(YEAR(L51),MONTH(L51)+3,1) -> 43252 | M52: =AP52 -> 359028.95 | N52: =AX52-BC52 -> 239458.17 | O52: =M52/N52 -> 1.4993389 | P52: =X52/BG52 -> 0.82816799 | Q52: 50 | R52: =EOMONTH(L52,0)-EOMONTH(L52,-3) -> 91 | T52: =IF($B$10="3BR_H", INDEX('3BR_H-processed'!$E:$E,MATCH($L52,'3BR_H-processed'!$B:$B,0),MATCH(Council_Area,'3BR_H-processed'!$E$1:$E$1,0)), INDEX('2BR_F-processed'!$E:$E,MATCH($L52,'2BR_F-processed'!$B:$B,0),MATCH(Council_Area,'2BR_F-processed'!$E$1:$E$1,0))) -> 384.39705 | U52: =IF(MOD(Q52,4)=1,T52,U51) -> 395.01841 | V52: =U52*(R52)/7 -> 5135.2393 | W52: =$B$53/4*BH52/_xlfn.XLOOKUP(Q_end,cpi!A:A,cpi!B:B) -> 156.46164 | X52: =V52+W52 -> 5291.7009 | Y52: =BG52-X52 -> 1097.9459 | Z52: =Y52*$B$47 -> 0 | AA52: {=(Y52+Z52)*eff_invest} -> 1097.9459 | AB52: =AA52*(_xlfn.XLOOKUP(Q_end,cpi!A:A,cpi!B:B)/BH52) -> 1403.4697 | AC52: {=INDEX('msci-indices'!C:C,MATCH($L52,'msci-indices'!$B:$B)-2)} -> 1639.7569 | AD52: {=INDEX('msci-indices'!D:D,MATCH($L52,'msci-indices'!$B:$B)-2)} -> 1460.9363 | AE52: =AI51+AA52 -> 345342.24 | AF52: {=INDEX('msci-indices'!C:C,MATCH($L52,'msci-indices'!$B:$B)+1)} -> 1671.605 | AG52: {=INDEX('msci-indices'!D:D,MATCH($L52,'msci-indices'!$B:$B)+1)} -> 1590.7725 | AH52: =(InvestFees/4)*AE52 -> 215.8389 | AI52: =((AF52/AC52)*GlobalPortfolio+(AG52/AD52)*AusPortfolio)*AE52-AH52 -> 359028.95 | AJ52: =AJ51+AA52 -> 183688.15 | AK52: =AI52-AJ52 -> 175340.8 | AL52: =AJ52*(_xlfn.XLOOKUP(Q_end,cpi!A:A,cpi!B:B)/BH52) -> 234802.79 | AM52: {=SUMPRODUCT($AA$3:AA52,_xlfn.SORTBY($BH$3:BH52,_xlfn.SEQUENCE(ROWS($BH$3:BH52)),-1)/$BH$3)} -> 233504.61 | AN52: =AI52-AM52 -> 125524.35 | AO52: =IF($B$49="Real gains",MAX($B$50*AN52,0),IF($B$49="Discounted nominal gains",MAX($B$50*AK52/2,0),0)) -> 0 | AP52: =AI52-AO52 -> 359028.95 | AR52: =IF($B$10="3BR_H", INDEX('ns-combined'!$C:$D,MATCH($L52,'ns-combined'!$B:$B,0),MATCH(Council_Area,'ns-combined'!$C$1:$D$1,0))*1000, INDEX('s-combined'!$C:$D,MATCH($L52,'s-combined'!$B:$B,0),MATCH(Council_Area,'s-combined'!$C$1:$D$1,0))*1000) -> 532000 | AS52: =AS51+$AS$3 -> 40625 | AT52: 0 | AU52: =SUM($B$28:$B$29)*AR52 -> 10640 | AV52: =AR52*$B$15/4 -> 1529.5 | AW52: =SUM($AV$3:AV52) -> 63899.175 | AX52: =AR52-AS52-AU52-AW52 -> 416835.83 | AY52: =$B$36*V52 -> 1797.3337 | AZ52: =SUM(AY52:AY52)*4/AR52 -> 0.013513788 | BA52: =SUM(AY52:AY52)/V52 -> 0.35 | BB52: =IF(MortgageRate="Discounted",_xlfn.XLOOKUP(L52,'mortgage-rates'!$A:$A,'mortgage-rates'!$E:$E)/100,_xlfn.XLOOKUP(L52,'mortgage-rates'!$A:$A,'mortgage-rates'!$D:$D)/100) -> 0.0451 | BC52: =BC51-BF51 -> 177377.65 | BD52: =IF($B$16*12/3-Q52+1>0,-PMT($BB52/4,$B$16*12/3-Q52+1,BC52),0) -> 4592.3131 | BE52: =BC52*($BB52/4) -> 1999.9331 | BF52: =BD52-BE52 -> 2592.38 | BG52: =AT52+AY52+BD52 -> 6389.6468 | BH52: =INDEX(cpi!B:B,MATCH($L52,cpi!A:A)) -> 113.2 | BI52: =100*BH52/BH$3 -> 133.80615 | BJ52: =100*AC52/AC$3 -> 217.22098 | BK52: =100*AD52/AD$3 -> 204.91247 | BL52: =BJ52*GlobalPortfolio+BK52*AusPortfolio -> 213.52842 | BM52: =100*AE52/$AE$3 -> 416.5412 | BN52: =100*AR52/AR$3 -> 163.69231 | BO52: =100*AX52/AX$3 -> 131.59644
A53: Renter's insurance and other costs ($ per year, end-quarter dollars) | B53: 800 | C53: 800 | L53: =DATE(YEAR(L52),MONTH(L52)+3,1) -> 43344 | M53: =AP53 -> 372712.94 | N53: =AX53-BC53 -> 247525.55 | O53: =M53/N53 -> 1.5057554 | P53: =X53/BG53 -> 0.83072684 | Q53: 51 | R53: =EOMONTH(L53,0)-EOMONTH(L53,-3) -> 92 | T53: =IF($B$10="3BR_H", INDEX('3BR_H-processed'!$E:$E,MATCH($L53,'3BR_H-processed'!$B:$B,0),MATCH(Council_Area,'3BR_H-processed'!$E$1:$E$1,0)), INDEX('2BR_F-processed'!$E:$E,MATCH($L53,'2BR_F-processed'!$B:$B,0),MATCH(Council_Area,'2BR_F-processed'!$E$1:$E$1,0))) -> 385.65233 | U53: =IF(MOD(Q53,4)=1,T53,U52) -> 395.01841 | V53: =U53*(R53)/7 -> 5191.6705 | W53: =$B$53/4*BH53/_xlfn.XLOOKUP(Q_end,cpi!A:A,cpi!B:B) -> 156.8763 | X53: =V53+W53 -> 5348.5468 | Y53: =BG53-X53 -> 1089.8473 | Z53: =Y53*$B$47 -> 0 | AA53: {=(Y53+Z53)*eff_invest} -> 1089.8473 | AB53: =AA53*(_xlfn.XLOOKUP(Q_end,cpi!A:A,cpi!B:B)/BH53) -> 1389.4353 | AC53: {=INDEX('msci-indices'!C:C,MATCH($L53,'msci-indices'!$B:$B)-2)} -> 1671.605 | AD53: {=INDEX('msci-indices'!D:D,MATCH($L53,'msci-indices'!$B:$B)-2)} -> 1590.7725 | AE53: =AI52+AA53 -> 360118.8 | AF53: {=INDEX('msci-indices'!C:C,MATCH($L53,'msci-indices'!$B:$B)+1)} -> 1747.8373 | AG53: {=INDEX('msci-indices'!D:D,MATCH($L53,'msci-indices'!$B:$B)+1)} -> 1610.2553 | AH53: =(InvestFees/4)*AE53 -> 225.07425 | AI53: =((AF53/AC53)*GlobalPortfolio+(AG53/AD53)*AusPortfolio)*AE53-AH53 -> 372712.94 | AJ53: =AJ52+AA53 -> 184778 | AK53: =AI53-AJ53 -> 187934.95 | AL53: =AJ53*(_xlfn.XLOOKUP(Q_end,cpi!A:A,cpi!B:B)/BH53) -> 235571.6 | AM53: {=SUMPRODUCT($AA$3:AA53,_xlfn.SORTBY($BH$3:BH53,_xlfn.SEQUENCE(ROWS($BH$3:BH53)),-1)/$BH$3)} -> 235548.78 | AN53: =AI53-AM53 -> 137164.17 | AO53: =IF($B$49="Real gains",MAX($B$50*AN53,0),IF($B$49="Discounted nominal gains",MAX($B$50*AK53/2,0),0)) -> 0 | AP53: =AI53-AO53 -> 372712.94 | AR53: =IF($B$10="3BR_H", INDEX('ns-combined'!$C:$D,MATCH($L53,'ns-combined'!$B:$B,0),MATCH(Council_Area,'ns-combined'!$C$1:$D$1,0))*1000, INDEX('s-combined'!$C:$D,MATCH($L53,'s-combined'!$B:$B,0),MATCH(Council_Area,'s-combined'!$C$1:$D$1,0))*1000) -> 540000 | AS53: =AS52+$AS$3 -> 41437.5 | AT53: 0 | AU53: =SUM($B$28:$B$29)*AR53 -> 10800 | AV53: =AR53*$B$15/4 -> 1552.5 | AW53: =SUM($AV$3:AV53) -> 65451.675 | AX53: =AR53-AS53-AU53-AW53 -> 422310.83 | AY53: =$B$36*V53 -> 1817.0847 | AZ53: =SUM(AY53:AY53)*4/AR53 -> 0.013459886 | BA53: =SUM(AY53:AY53)/V53 -> 0.35 | BB53: =IF(MortgageRate="Discounted",_xlfn.XLOOKUP(L53,'mortgage-rates'!$A:$A,'mortgage-rates'!$E:$E)/100,_xlfn.XLOOKUP(L53,'mortgage-rates'!$A:$A,'mortgage-rates'!$D:$D)/100) -> 0.0462 | BC53: =BC52-BF52 -> 174785.27 | BD53: =IF($B$16*12/3-Q53+1>0,-PMT($BB53/4,$B$16*12/3-Q53+1,BC53),0) -> 4621.3094 | BE53: =BC53*($BB53/4) -> 2018.7699 | BF53: =BD53-BE53 -> 2602.5395 | BG53: =AT53+AY53+BD53 -> 6438.3941 | BH53: =INDEX(cpi!B:B,MATCH($L53,cpi!A:A)) -> 113.5 | BI53: =100*BH53/BH$3 -> 134.16076 | BJ53: =100*AC53/AC$3 -> 221.43995 | BK53: =100*AD53/AD$3 -> 223.12345 | BL53: =BJ53*GlobalPortfolio+BK53*AusPortfolio -> 221.945 | BM53: =100*AE53/$AE$3 -> 434.36424 | BN53: =100*AR53/AR$3 -> 166.15385 | BO53: =100*AX53/AX$3 -> 133.32491
A54: Investment efficiency | B54: 1 | C54: 1 | L54: =DATE(YEAR(L53),MONTH(L53)+3,1) -> 43435 | M54: =AP54 -> 327740.87 | N54: =AX54-BC54 -> 247763.09 | O54: =M54/N54 -> 1.3227994 | P54: =X54/BG54 -> 0.82983054 | Q54: 52 | R54: =EOMONTH(L54,0)-EOMONTH(L54,-3) -> 92 | T54: =IF($B$10="3BR_H", INDEX('3BR_H-processed'!$E:$E,MATCH($L54,'3BR_H-processed'!$B:$B,0),MATCH(Council_Area,'3BR_H-processed'!$E$1:$E$1,0)), INDEX('2BR_F-processed'!$E:$E,MATCH($L54,'2BR_F-processed'!$B:$B,0),MATCH(Council_Area,'2BR_F-processed'!$E$1:$E$1,0))) -> 388.4104 | U54: =IF(MOD(Q54,4)=1,T54,U53) -> 395.01841 | V54: =U54*(R54)/7 -> 5191.6705 | W54: =$B$53/4*BH54/_xlfn.XLOOKUP(Q_end,cpi!A:A,cpi!B:B) -> 157.56738 | X54: =V54+W54 -> 5349.2379 | Y54: =BG54-X54 -> 1096.9431 | Z54: =Y54*$B$47 -> 0 | AA54: {=(Y54+Z54)*eff_invest} -> 1096.9431 | AB54: =AA54*(_xlfn.XLOOKUP(Q_end,cpi!A:A,cpi!B:B)/BH54) -> 1392.348 | AC54: {=INDEX('msci-indices'!C:C,MATCH($L54,'msci-indices'!$B:$B)-2)} -> 1747.8373 | AD54: {=INDEX('msci-indices'!D:D,MATCH($L54,'msci-indices'!$B:$B)-2)} -> 1610.2553 | AE54: =AI53+AA54 -> 373809.89 | AF54: {=INDEX('msci-indices'!C:C,MATCH($L54,'msci-indices'!$B:$B)+1)} -> 1503.1568 | AG54: {=INDEX('msci-indices'!D:D,MATCH($L54,'msci-indices'!$B:$B)+1)} -> 1478.0882 | AH54: =(InvestFees/4)*AE54 -> 233.63118 | AI54: =((AF54/AC54)*GlobalPortfolio+(AG54/AD54)*AusPortfolio)*AE54-AH54 -> 327740.87 | AJ54: =AJ53+AA54 -> 185874.94 | AK54: =AI54-AJ54 -> 141865.93 | AL54: =AJ54*(_xlfn.XLOOKUP(Q_end,cpi!A:A,cpi!B:B)/BH54) -> 235930.74 | AM54: {=SUMPRODUCT($AA$3:AA54,_xlfn.SORTBY($BH$3:BH54,_xlfn.SEQUENCE(ROWS($BH$3:BH54)),-1)/$BH$3)} -> 237798.44 | AN54: =AI54-AM54 -> 89942.431 | AO54: =IF($B$49="Real gains",MAX($B$50*AN54,0),IF($B$49="Discounted nominal gains",MAX($B$50*AK54/2,0),0)) -> 0 | AP54: =AI54-AO54 -> 327740.87 | AR54: =IF($B$10="3BR_H", INDEX('ns-combined'!$C:$D,MATCH($L54,'ns-combined'!$B:$B,0),MATCH(Council_Area,'ns-combined'!$C$1:$D$1,0))*1000, INDEX('s-combined'!$C:$D,MATCH($L54,'s-combined'!$B:$B,0),MATCH(Council_Area,'s-combined'!$C$1:$D$1,0))*1000) -> 540000 | AS54: =AS53+$AS$3 -> 42250 | AT54: 0 | AU54: =SUM($B$28:$B$29)*AR54 -> 10800 | AV54: =AR54*$B$15/4 -> 1552.5 | AW54: =SUM($AV$3:AV54) -> 67004.175 | AX54: =AR54-AS54-AU54-AW54 -> 419945.83 | AY54: =$B$36*V54 -> 1817.0847 | AZ54: =SUM(AY54:AY54)*4/AR54 -> 0.013459886 | BA54: =SUM(AY54:AY54)/V54 -> 0.35 | BB54: =IF(MortgageRate="Discounted",_xlfn.XLOOKUP(L54,'mortgage-rates'!$A:$A,'mortgage-rates'!$E:$E)/100,_xlfn.XLOOKUP(L54,'mortgage-rates'!$A:$A,'mortgage-rates'!$D:$D)/100) -> 0.0465 | BC54: =BC53-BF53 -> 172182.74 | BD54: =IF($B$16*12/3-Q54+1>0,-PMT($BB54/4,$B$16*12/3-Q54+1,BC54),0) -> 4629.0963 | BE54: =BC54*($BB54/4) -> 2001.6243 | BF54: =BD54-BE54 -> 2627.472 | BG54: =AT54+AY54+BD54 -> 6446.181 | BH54: =INDEX(cpi!B:B,MATCH($L54,cpi!A:A)) -> 114 | BI54: =100*BH54/BH$3 -> 134.75177 | BJ54: =100*AC54/AC$3 -> 231.53855 | BK54: =100*AD54/AD$3 -> 225.85612 | BL54: =BJ54*GlobalPortfolio+BK54*AusPortfolio -> 229.83382 | BM54: =100*AE54/$AE$3 -> 450.87801 | BN54: =100*AR54/AR$3 -> 166.15385 | BO54: =100*AX54/AX$3 -> 132.57827
L55: =DATE(YEAR(L54),MONTH(L54)+3,1) -> 43525 | M55: =AP55 -> 368401.93 | N55: =AX55-BC55 -> 241185.69 | O55: =M55/N55 -> 1.5274618 | P55: =X55/BG55 -> 0.82436297 | Q55: 53 | R55: =EOMONTH(L55,0)-EOMONTH(L55,-3) -> 90 | T55: =IF($B$10="3BR_H", INDEX('3BR_H-processed'!$E:$E,MATCH($L55,'3BR_H-processed'!$B:$B,0),MATCH(Council_Area,'3BR_H-processed'!$E$1:$E$1,0)), INDEX('2BR_F-processed'!$E:$E,MATCH($L55,'2BR_F-processed'!$B:$B,0),MATCH(Council_Area,'2BR_F-processed'!$E$1:$E$1,0))) -> 400.61834 | U55: =IF(MOD(Q55,4)=1,T55,U54) -> 400.61834 | V55: =U55*(R55)/7 -> 5150.8072 | W55: =$B$53/4*BH55/_xlfn.XLOOKUP(Q_end,cpi!A:A,cpi!B:B) -> 157.7056 | X55: =V55+W55 -> 5308.5128 | Y55: =BG55-X55 -> 1131.0205 | Z55: =Y55*$B$47 -> 0 | AA55: {=(Y55+Z55)*eff_invest} -> 1131.0205 | AB55: =AA55*(_xlfn.XLOOKUP(Q_end,cpi!A:A,cpi!B:B)/BH55) -> 1434.3442 | AC55: {=INDEX('msci-indices'!C:C,MATCH($L55,'msci-indices'!$B:$B)-2)} -> 1503.1568 | AD55: {=INDEX('msci-indices'!D:D,MATCH($L55,'msci-indices'!$B:$B)-2)} -> 1478.0882 | AE55: =AI54+AA55 -> 328871.89 | AF55: {=INDEX('msci-indices'!C:C,MATCH($L55,'msci-indices'!$B:$B)+1)} -> 1693.1497 | AG55: {=INDEX('msci-indices'!D:D,MATCH($L55,'msci-indices'!$B:$B)+1)} -> 1637.4592 | AH55: =(InvestFees/4)*AE55 -> 205.54493 | AI55: =((AF55/AC55)*GlobalPortfolio+(AG55/AD55)*AusPortfolio)*AE55-AH55 -> 368401.93 | AJ55: =AJ54+AA55 -> 187005.96 | AK55: =AI55-AJ55 -> 181395.97 | AL55: =AJ55*(_xlfn.XLOOKUP(Q_end,cpi!A:A,cpi!B:B)/BH55) -> 237158.31 | AM55: {=SUMPRODUCT($AA$3:AA55,_xlfn.SORTBY($BH$3:BH55,_xlfn.SEQUENCE(ROWS($BH$3:BH55)),-1)/$BH$3)} -> 239701.09 | AN55: =AI55-AM55 -> 128700.84 | AO55: =IF($B$49="Real gains",MAX($B$50*AN55,0),IF($B$49="Discounted nominal gains",MAX($B$50*AK55/2,0),0)) -> 0 | AP55: =AI55-AO55 -> 368401.93 | AR55: =IF($B$10="3BR_H", INDEX('ns-combined'!$C:$D,MATCH($L55,'ns-combined'!$B:$B,0),MATCH(Council_Area,'ns-combined'!$C$1:$D$1,0))*1000, INDEX('s-combined'!$C:$D,MATCH($L55,'s-combined'!$B:$B,0),MATCH(Council_Area,'s-combined'!$C$1:$D$1,0))*1000) -> 533000 | AS55: =AS54+$AS$3 -> 43062.5 | AT55: 0 | AU55: =SUM($B$28:$B$29)*AR55 -> 10660 | AV55: =AR55*$B$15/4 -> 1532.375 | AW55: =SUM($AV$3:AV55) -> 68536.55 | AX55: =AR55-AS55-AU55-AW55 -> 410740.95 | AY55: =$B$36*V55 -> 1802.7825 | AZ55: =SUM(AY55:AY55)*4/AR55 -> 0.013529325 | BA55: =SUM(AY55:AY55)/V55 -> 0.35 | BB55: =IF(MortgageRate="Discounted",_xlfn.XLOOKUP(L55,'mortgage-rates'!$A:$A,'mortgage-rates'!$E:$E)/100,_xlfn.XLOOKUP(L55,'mortgage-rates'!$A:$A,'mortgage-rates'!$D:$D)/100) -> 0.0468 | BC55: =BC54-BF54 -> 169555.26 | BD55: =IF($B$16*12/3-Q55+1>0,-PMT($BB55/4,$B$16*12/3-Q55+1,BC55),0) -> 4636.7508 | BE55: =BC55*($BB55/4) -> 1983.7966 | BF55: =BD55-BE55 -> 2652.9542 | BG55: =AT55+AY55+BD55 -> 6439.5333 | BH55: =INDEX(cpi!B:B,MATCH($L55,cpi!A:A)) -> 114.1 | BI55: =100*BH55/BH$3 -> 134.86998 | BJ55: =100*AC55/AC$3 -> 199.12537 | BK55: =100*AD55/AD$3 -> 207.31821 | BL55: =BJ55*GlobalPortfolio+BK55*AusPortfolio -> 201.58322 | BM55: =100*AE55/$AE$3 -> 396.67518 | BN55: =100*AR55/AR$3 -> 164 | BO55: =100*AX55/AX$3 -> 129.67226
L56: =DATE(YEAR(L55),MONTH(L55)+3,1) -> 43617 | M56: =AP56 -> 387781.56 | N56: =AX56-BC56 -> 246379.39 | O56: =M56/N56 -> 1.5739204 | P56: =X56/BG56 -> 0.83796483 | Q56: 54 | R56: =EOMONTH(L56,0)-EOMONTH(L56,-3) -> 91 | T56: =IF($B$10="3BR_H", INDEX('3BR_H-processed'!$E:$E,MATCH($L56,'3BR_H-processed'!$B:$B,0),MATCH(Council_Area,'3BR_H-processed'!$E$1:$E$1,0)), INDEX('2BR_F-processed'!$E:$E,MATCH($L56,'2BR_F-processed'!$B:$B,0),MATCH(Council_Area,'2BR_F-processed'!$E$1:$E$1,0))) -> 387.90105 | U56: =IF(MOD(Q56,4)=1,T56,U55) -> 400.61834 | V56: =U56*(R56)/7 -> 5208.0384 | W56: =$B$53/4*BH56/_xlfn.XLOOKUP(Q_end,cpi!A:A,cpi!B:B) -> 158.81133 | X56: =V56+W56 -> 5366.8497 | Y56: =BG56-X56 -> 1037.7744 | Z56: =Y56*$B$47 -> 0 | AA56: {=(Y56+Z56)*eff_invest} -> 1037.7744 | AB56: =AA56*(_xlfn.XLOOKUP(Q_end,cpi!A:A,cpi!B:B)/BH56) -> 1306.9274 | AC56: {=INDEX('msci-indices'!C:C,MATCH($L56,'msci-indices'!$B:$B)-2)} -> 1693.1497 | AD56: {=INDEX('msci-indices'!D:D,MATCH($L56,'msci-indices'!$B:$B)-2)} -> 1637.4592 | AE56: =AI55+AA56 -> 369439.7 | AF56: {=INDEX('msci-indices'!C:C,MATCH($L56,'msci-indices'!$B:$B)+1)} -> 1756.4484 | AG56: {=INDEX('msci-indices'!D:D,MATCH($L56,'msci-indices'!$B:$B)+1)} -> 1769.0189 | AH56: =(InvestFees/4)*AE56 -> 230.89981 | AI56: =((AF56/AC56)*GlobalPortfolio+(AG56/AD56)*AusPortfolio)*AE56-AH56 -> 387781.56 | AJ56: =AJ55+AA56 -> 188043.74 | AK56: =AI56-AJ56 -> 199737.82 | AL56: =AJ56*(_xlfn.XLOOKUP(Q_end,cpi!A:A,cpi!B:B)/BH56) -> 236814 | AM56: {=SUMPRODUCT($AA$3:AA56,_xlfn.SORTBY($BH$3:BH56,_xlfn.SEQUENCE(ROWS($BH$3:BH56)),-1)/$BH$3)} -> 242183.38 | AN56: =AI56-AM56 -> 145598.17 | AO56: =IF($B$49="Real gains",MAX($B$50*AN56,0),IF($B$49="Discounted nominal gains",MAX($B$50*AK56/2,0),0)) -> 0 | AP56: =AI56-AO56 -> 387781.56 | AR56: =IF($B$10="3BR_H", INDEX('ns-combined'!$C:$D,MATCH($L56,'ns-combined'!$B:$B,0),MATCH(Council_Area,'ns-combined'!$C$1:$D$1,0))*1000, INDEX('s-combined'!$C:$D,MATCH($L56,'s-combined'!$B:$B,0),MATCH(Council_Area,'s-combined'!$C$1:$D$1,0))*1000) -> 538000 | AS56: =AS55+$AS$3 -> 43875 | AT56: 0 | AU56: =SUM($B$28:$B$29)*AR56 -> 10760 | AV56: =AR56*$B$15/4 -> 1546.75 | AW56: =SUM($AV$3:AV56) -> 70083.3 | AX56: =AR56-AS56-AU56-AW56 -> 413281.7 | AY56: =$B$36*V56 -> 1822.8134 | AZ56: =SUM(AY56:AY56)*4/AR56 -> 0.013552516 | BA56: =SUM(AY56:AY56)/V56 -> 0.35 | BB56: =IF(MortgageRate="Discounted",_xlfn.XLOOKUP(L56,'mortgage-rates'!$A:$A,'mortgage-rates'!$E:$E)/100,_xlfn.XLOOKUP(L56,'mortgage-rates'!$A:$A,'mortgage-rates'!$D:$D)/100) -> 0.0446 | BC56: =BC55-BF55 -> 166902.31 | BD56: =IF($B$16*12/3-Q56+1>0,-PMT($BB56/4,$B$16*12/3-Q56+1,BC56),0) -> 4581.8107 | BE56: =BC56*($BB56/4) -> 1860.9607 | BF56: =BD56-BE56 -> 2720.8499 | BG56: =AT56+AY56+BD56 -> 6404.6241 | BH56: =INDEX(cpi!B:B,MATCH($L56,cpi!A:A)) -> 114.9 | BI56: =100*BH56/BH$3 -> 135.8156 | BJ56: =100*AC56/AC$3 -> 224.294 | BK56: =100*AD56/AD$3 -> 229.67177 | BL56: =BJ56*GlobalPortfolio+BK56*AusPortfolio -> 225.90733 | BM56: =100*AE56/$AE$3 -> 445.60683 | BN56: =100*AR56/AR$3 -> 165.53846 | BO56: =100*AX56/AX$3 -> 130.47439
L57: =DATE(YEAR(L56),MONTH(L56)+3,1) -> 43709 | M57: =AP57 -> 392677.53 | N57: =AX57-BC57 -> 248695.24 | O57: =M57/N57 -> 1.5789507 | P57: =X57/BG57 -> 0.85113879 | Q57: 55 | R57: =EOMONTH(L57,0)-EOMONTH(L57,-3) -> 92 | T57: =IF($B$10="3BR_H", INDEX('3BR_H-processed'!$E:$E,MATCH($L57,'3BR_H-processed'!$B:$B,0),MATCH(Council_Area,'3BR_H-processed'!$E$1:$E$1,0)), INDEX('2BR_F-processed'!$E:$E,MATCH($L57,'2BR_F-processed'!$B:$B,0),MATCH(Council_Area,'2BR_F-processed'!$E$1:$E$1,0))) -> 387.72017 | U57: =IF(MOD(Q57,4)=1,T57,U56) -> 400.61834 | V57: =U57*(R57)/7 -> 5265.2696 | W57: =$B$53/4*BH57/_xlfn.XLOOKUP(Q_end,cpi!A:A,cpi!B:B) -> 159.50242 | X57: =V57+W57 -> 5424.772 | Y57: =BG57-X57 -> 948.77373 | Z57: =Y57*$B$47 -> 0 | AA57: {=(Y57+Z57)*eff_invest} -> 948.77373 | AB57: =AA57*(_xlfn.XLOOKUP(Q_end,cpi!A:A,cpi!B:B)/BH57) -> 1189.6669 | AC57: {=INDEX('msci-indices'!C:C,MATCH($L57,'msci-indices'!$B:$B)-2)} -> 1756.4484 | AD57: {=INDEX('msci-indices'!D:D,MATCH($L57,'msci-indices'!$B:$B)-2)} -> 1769.0189 | AE57: =AI56+AA57 -> 388730.33 | AF57: {=INDEX('msci-indices'!C:C,MATCH($L57,'msci-indices'!$B:$B)+1)} -> 1762.7547 | AG57: {=INDEX('msci-indices'!D:D,MATCH($L57,'msci-indices'!$B:$B)+1)} -> 1817.7602 | AH57: =(InvestFees/4)*AE57 -> 242.95646 | AI57: =((AF57/AC57)*GlobalPortfolio+(AG57/AD57)*AusPortfolio)*AE57-AH57 -> 392677.53 | AJ57: =AJ56+AA57 -> 188992.51 | AK57: =AI57-AJ57 -> 203685.02 | AL57: =AJ57*(_xlfn.XLOOKUP(Q_end,cpi!A:A,cpi!B:B)/BH57) -> 236977.61 | AM57: {=SUMPRODUCT($AA$3:AA57,_xlfn.SORTBY($BH$3:BH57,_xlfn.SEQUENCE(ROWS($BH$3:BH57)),-1)/$BH$3)} -> 244300.75 | AN57: =AI57-AM57 -> 148376.77 | AO57: =IF($B$49="Real gains",MAX($B$50*AN57,0),IF($B$49="Discounted nominal gains",MAX($B$50*AK57/2,0),0)) -> 0 | AP57: =AI57-AO57 -> 392677.53 | AR57: =IF($B$10="3BR_H", INDEX('ns-combined'!$C:$D,MATCH($L57,'ns-combined'!$B:$B,0),MATCH(Council_Area,'ns-combined'!$C$1:$D$1,0))*1000, INDEX('s-combined'!$C:$D,MATCH($L57,'s-combined'!$B:$B,0),MATCH(Council_Area,'s-combined'!$C$1:$D$1,0))*1000) -> 540000 | AS57: =AS56+$AS$3 -> 44687.5 | AT57: 0 | AU57: =SUM($B$28:$B$29)*AR57 -> 10800 | AV57: =AR57*$B$15/4 -> 1552.5 | AW57: =SUM($AV$3:AV57) -> 71635.8 | AX57: =AR57-AS57-AU57-AW57 -> 412876.7 | AY57: =$B$36*V57 -> 1842.8444 | AZ57: =SUM(AY57:AY57)*4/AR57 -> 0.013650699 | BA57: =SUM(AY57:AY57)/V57 -> 0.35 | BB57: =IF(MortgageRate="Discounted",_xlfn.XLOOKUP(L57,'mortgage-rates'!$A:$A,'mortgage-rates'!$E:$E)/100,_xlfn.XLOOKUP(L57,'mortgage-rates'!$A:$A,'mortgage-rates'!$D:$D)/100) -> 0.0425 | BC57: =BC56-BF56 -> 164181.46 | BD57: =IF($B$16*12/3-Q57+1>0,-PMT($BB57/4,$B$16*12/3-Q57+1,BC57),0) -> 4530.7014 | BE57: =BC57*($BB57/4) -> 1744.428 | BF57: =BD57-BE57 -> 2786.2734 | BG57: =AT57+AY57+BD57 -> 6373.5457 | BH57: =INDEX(cpi!B:B,MATCH($L57,cpi!A:A)) -> 115.4 | BI57: =100*BH57/BH$3 -> 136.40662 | BJ57: =100*AC57/AC$3 -> 232.67928 | BK57: =100*AD57/AD$3 -> 248.12447 | BL57: =BJ57*GlobalPortfolio+BK57*AusPortfolio -> 237.31283 | BM57: =100*AE57/$AE$3 -> 468.87459 | BN57: =100*AR57/AR$3 -> 166.15385 | BO57: =100*AX57/AX$3 -> 130.34653
L58: =DATE(YEAR(L57),MONTH(L57)+3,1) -> 43800 | M58: =AP58 -> 417460.7 | N58: =AX58-BC58 -> 258887.76 | O58: =M58/N58 -> 1.6125162 | P58: =X58/BG58 -> 0.85447477 | Q58: 56 | R58: =EOMONTH(L58,0)-EOMONTH(L58,-3) -> 92 | T58: =IF($B$10="3BR_H", INDEX('3BR_H-processed'!$E:$E,MATCH($L58,'3BR_H-processed'!$B:$B,0),MATCH(Council_Area,'3BR_H-processed'!$E$1:$E$1,0)), INDEX('2BR_F-processed'!$E:$E,MATCH($L58,'2BR_F-processed'!$B:$B,0),MATCH(Council_Area,'2BR_F-processed'!$E$1:$E$1,0))) -> 397.23078 | U58: =IF(MOD(Q58,4)=1,T58,U57) -> 400.61834 | V58: =U58*(R58)/7 -> 5265.2696 | W58: =$B$53/4*BH58/_xlfn.XLOOKUP(Q_end,cpi!A:A,cpi!B:B) -> 160.46994 | X58: =V58+W58 -> 5425.7395 | Y58: =BG58-X58 -> 924.05538 | Z58: =Y58*$B$47 -> 0 | AA58: {=(Y58+Z58)*eff_invest} -> 924.05538 | AB58: =AA58*(_xlfn.XLOOKUP(Q_end,cpi!A:A,cpi!B:B)/BH58) -> 1151.6866 | AC58: {=INDEX('msci-indices'!C:C,MATCH($L58,'msci-indices'!$B:$B)-2)} -> 1762.7547 | AD58: {=INDEX('msci-indices'!D:D,MATCH($L58,'msci-indices'!$B:$B)-2)} -> 1817.7602 | AE58: =AI57+AA58 -> 393601.58 | AF58: {=INDEX('msci-indices'!C:C,MATCH($L58,'msci-indices'!$B:$B)+1)} -> 1916.2448 | AG58: {=INDEX('msci-indices'!D:D,MATCH($L58,'msci-indices'!$B:$B)+1)} -> 1819.5212 | AH58: =(InvestFees/4)*AE58 -> 246.00099 | AI58: =((AF58/AC58)*GlobalPortfolio+(AG58/AD58)*AusPortfolio)*AE58-AH58 -> 417460.7 | AJ58: =AJ57+AA58 -> 189916.57 | AK58: =AI58-AJ58 -> 227544.14 | AL58: =AJ58*(_xlfn.XLOOKUP(Q_end,cpi!A:A,cpi!B:B)/BH58) -> 236700.49 | AM58: {=SUMPRODUCT($AA$3:AA58,_xlfn.SORTBY($BH$3:BH58,_xlfn.SEQUENCE(ROWS($BH$3:BH58)),-1)/$BH$3)} -> 246585.15 | AN58: =AI58-AM58 -> 170875.55 | AO58: =IF($B$49="Real gains",MAX($B$50*AN58,0),IF($B$49="Discounted nominal gains",MAX($B$50*AK58/2,0),0)) -> 0 | AP58: =AI58-AO58 -> 417460.7 | AR58: =IF($B$10="3BR_H", INDEX('ns-combined'!$C:$D,MATCH($L58,'ns-combined'!$B:$B,0),MATCH(Council_Area,'ns-combined'!$C$1:$D$1,0))*1000, INDEX('s-combined'!$C:$D,MATCH($L58,'s-combined'!$B:$B,0),MATCH(Council_Area,'s-combined'!$C$1:$D$1,0))*1000) -> 550000 | AS58: =AS57+$AS$3 -> 45500 | AT58: 0 | AU58: =SUM($B$28:$B$29)*AR58 -> 11000 | AV58: =AR58*$B$15/4 -> 1581.25 | AW58: =SUM($AV$3:AV58) -> 73217.05 | AX58: =AR58-AS58-AU58-AW58 -> 420282.95 | AY58: =$B$36*V58 -> 1842.8444 | AZ58: =SUM(AY58:AY58)*4/AR58 -> 0.013402504 | BA58: =SUM(AY58:AY58)/V58 -> 0.35 | BB58: =IF(MortgageRate="Discounted",_xlfn.XLOOKUP(L58,'mortgage-rates'!$A:$A,'mortgage-rates'!$E:$E)/100,_xlfn.XLOOKUP(L58,'mortgage-rates'!$A:$A,'mortgage-rates'!$D:$D)/100) -> 0.0415 | BC58: =BC57-BF57 -> 161395.19 | BD58: =IF($B$16*12/3-Q58+1>0,-PMT($BB58/4,$B$16*12/3-Q58+1,BC58),0) -> 4506.9506 | BE58: =BC58*($BB58/4) -> 1674.4751 | BF58: =BD58-BE58 -> 2832.4755 | BG58: =AT58+AY58+BD58 -> 6349.7949 | BH58: =INDEX(cpi!B:B,MATCH($L58,cpi!A:A)) -> 116.1 | BI58: =100*BH58/BH$3 -> 137.23404 | BJ58: =100*AC58/AC$3 -> 233.51468 | BK58: =100*AD58/AD$3 -> 254.96098 | BL58: =BJ58*GlobalPortfolio+BK58*AusPortfolio -> 239.94857 | BM58: =100*AE58/$AE$3 -> 474.75015 | BN58: =100*AR58/AR$3 -> 169.23077 | BO58: =100*AX58/AX$3 -> 132.68471
L59: =DATE(YEAR(L58),MONTH(L58)+3,1) -> 43891 | M59: =AP59 -> 323152.78 | N59: =AX59-BC59 -> 249555.24 | O59: =M59/N59 -> 1.2949148 | P59: =X59/BG59 -> 0.86105467 | Q59: 57 | R59: =EOMONTH(L59,0)-EOMONTH(L59,-3) -> 91 | T59: =IF($B$10="3BR_H", INDEX('3BR_H-processed'!$E:$E,MATCH($L59,'3BR_H-processed'!$B:$B,0),MATCH(Council_Area,'3BR_H-processed'!$E$1:$E$1,0)), INDEX('2BR_F-processed'!$E:$E,MATCH($L59,'2BR_F-processed'!$B:$B,0),MATCH(Council_Area,'2BR_F-processed'!$E$1:$E$1,0))) -> 404.26059 | U59: =IF(MOD(Q59,4)=1,T59,U58) -> 404.26059 | V59: =U59*(R59)/7 -> 5255.3877 | W59: =$B$53/4*BH59/_xlfn.XLOOKUP(Q_end,cpi!A:A,cpi!B:B) -> 161.29924 | X59: =V59+W59 -> 5416.6869 | Y59: =BG59-X59 -> 874.07149 | Z59: =Y59*$B$47 -> 0 | AA59: {=(Y59+Z59)*eff_invest} -> 874.07149 | AB59: =AA59*(_xlfn.XLOOKUP(Q_end,cpi!A:A,cpi!B:B)/BH59) -> 1083.7887 | AC59: {=INDEX('msci-indices'!C:C,MATCH($L59,'msci-indices'!$B:$B)-2)} -> 1916.2448 | AD59: {=INDEX('msci-indices'!D:D,MATCH($L59,'msci-indices'!$B:$B)-2)} -> 1819.5212 | AE59: =AI58+AA59 -> 418334.77 | AF59: {=INDEX('msci-indices'!C:C,MATCH($L59,'msci-indices'!$B:$B)+1)} -> 1491.4482 | AG59: {=INDEX('msci-indices'!D:D,MATCH($L59,'msci-indices'!$B:$B)+1)} -> 1384.5123 | AH59: =(InvestFees/4)*AE59 -> 261.45923 | AI59: =((AF59/AC59)*GlobalPortfolio+(AG59/AD59)*AusPortfolio)*AE59-AH59 -> 323152.78 | AJ59: =AJ58+AA59 -> 190790.64 | AK59: =AI59-AJ59 -> 132362.15 | AL59: =AJ59*(_xlfn.XLOOKUP(Q_end,cpi!A:A,cpi!B:B)/BH59) -> 236567.31 | AM59: {=SUMPRODUCT($AA$3:AA59,_xlfn.SORTBY($BH$3:BH59,_xlfn.SEQUENCE(ROWS($BH$3:BH59)),-1)/$BH$3)} -> 248735.19 | AN59: =AI59-AM59 -> 74417.598 | AO59: =IF($B$49="Real gains",MAX($B$50*AN59,0),IF($B$49="Discounted nominal gains",MAX($B$50*AK59/2,0),0)) -> 0 | AP59: =AI59-AO59 -> 323152.78 | AR59: =IF($B$10="3BR_H", INDEX('ns-combined'!$C:$D,MATCH($L59,'ns-combined'!$B:$B,0),MATCH(Council_Area,'ns-combined'!$C$1:$D$1,0))*1000, INDEX('s-combined'!$C:$D,MATCH($L59,'s-combined'!$B:$B,0),MATCH(Council_Area,'s-combined'!$C$1:$D$1,0))*1000) -> 540000 | AS59: =AS58+$AS$3 -> 46312.5 | AT59: 0 | AU59: =SUM($B$28:$B$29)*AR59 -> 10800 | AV59: =AR59*$B$15/4 -> 1552.5 | AW59: =SUM($AV$3:AV59) -> 74769.55 | AX59: =AR59-AS59-AU59-AW59 -> 408117.95 | AY59: =$B$36*V59 -> 1839.3857 | AZ59: =SUM(AY59:AY59)*4/AR59 -> 0.013625079 | BA59: =SUM(AY59:AY59)/V59 -> 0.35 | BB59: =IF(MortgageRate="Discounted",_xlfn.XLOOKUP(L59,'mortgage-rates'!$A:$A,'mortgage-rates'!$E:$E)/100,_xlfn.XLOOKUP(L59,'mortgage-rates'!$A:$A,'mortgage-rates'!$D:$D)/100) -> 0.0391 | BC59: =BC58-BF58 -> 158562.71 | BD59: =IF($B$16*12/3-Q59+1>0,-PMT($BB59/4,$B$16*12/3-Q59+1,BC59),0) -> 4451.3727 | BE59: =BC59*($BB59/4) -> 1549.9505 | BF59: =BD59-BE59 -> 2901.4222 | BG59: =AT59+AY59+BD59 -> 6290.7584 | BH59: =INDEX(cpi!B:B,MATCH($L59,cpi!A:A)) -> 116.7 | BI59: =100*BH59/BH$3 -> 137.94326 | BJ59: =100*AC59/AC$3 -> 253.84774 | BK59: =100*AD59/AD$3 -> 255.20797 | BL59: =BJ59*GlobalPortfolio+BK59*AusPortfolio -> 254.25581 | BM59: =100*AE59/$AE$3 -> 504.58256 | BN59: =100*AR59/AR$3 -> 166.15385 | BO59: =100*AX59/AX$3 -> 128.84417
L60: =DATE(YEAR(L59),MONTH(L59)+3,1) -> 43983 | M60: =AP60 -> 385625.92 | N60: =AX60-BC60 -> 256931.54 | O60: =M60/N60 -> 1.5008898 | P60: =X60/BG60 -> 0.86865337 | Q60: 58 | R60: =EOMONTH(L60,0)-EOMONTH(L60,-3) -> 91 | T60: =IF($B$10="3BR_H", INDEX('3BR_H-processed'!$E:$E,MATCH($L60,'3BR_H-processed'!$B:$B,0),MATCH(Council_Area,'3BR_H-processed'!$E$1:$E$1,0)), INDEX('2BR_F-processed'!$E:$E,MATCH($L60,'2BR_F-processed'!$B:$B,0),MATCH(Council_Area,'2BR_F-processed'!$E$1:$E$1,0))) -> 388.74625 | U60: =IF(MOD(Q60,4)=1,T60,U59) -> 404.26059 | V60: =U60*(R60)/7 -> 5255.3877 | W60: =$B$53/4*BH60/_xlfn.XLOOKUP(Q_end,cpi!A:A,cpi!B:B) -> 158.25847 | X60: =V60+W60 -> 5413.6461 | Y60: =BG60-X60 -> 818.58218 | Z60: =Y60*$B$47 -> 0 | AA60: {=(Y60+Z60)*eff_invest} -> 818.58218 | AB60: =AA60*(_xlfn.XLOOKUP(Q_end,cpi!A:A,cpi!B:B)/BH60) -> 1034.4877 | AC60: {=INDEX('msci-indices'!C:C,MATCH($L60,'msci-indices'!$B:$B)-2)} -> 1491.4482 | AD60: {=INDEX('msci-indices'!D:D,MATCH($L60,'msci-indices'!$B:$B)-2)} -> 1384.5123 | AE60: =AI59+AA60 -> 323971.37 | AF60: {=INDEX('msci-indices'!C:C,MATCH($L60,'msci-indices'!$B:$B)+1)} -> 1788.7914 | AG60: {=INDEX('msci-indices'!D:D,MATCH($L60,'msci-indices'!$B:$B)+1)} -> 1621.6232 | AH60: =(InvestFees/4)*AE60 -> 202.4821 | AI60: =((AF60/AC60)*GlobalPortfolio+(AG60/AD60)*AusPortfolio)*AE60-AH60 -> 385625.92 | AJ60: =AJ59+AA60 -> 191609.22 | AK60: =AI60-AJ60 -> 194016.7 | AL60: =AJ60*(_xlfn.XLOOKUP(Q_end,cpi!A:A,cpi!B:B)/BH60) -> 242147.2 | AM60: {=SUMPRODUCT($AA$3:AA60,_xlfn.SORTBY($BH$3:BH60,_xlfn.SEQUENCE(ROWS($BH$3:BH60)),-1)/$BH$3)} -> 248094.16 | AN60: =AI60-AM60 -> 137531.76 | AO60: =IF($B$49="Real gains",MAX($B$50*AN60,0),IF($B$49="Discounted nominal gains",MAX($B$50*AK60/2,0),0)) -> 0 | AP60: =AI60-AO60 -> 385625.92 | AR60: =IF($B$10="3BR_H", INDEX('ns-combined'!$C:$D,MATCH($L60,'ns-combined'!$B:$B,0),MATCH(Council_Area,'ns-combined'!$C$1:$D$1,0))*1000, INDEX('s-combined'!$C:$D,MATCH($L60,'s-combined'!$B:$B,0),MATCH(Council_Area,'s-combined'!$C$1:$D$1,0))*1000) -> 547000 | AS60: =AS59+$AS$3 -> 47125 | AT60: 0 | AU60: =SUM($B$28:$B$29)*AR60 -> 10940 | AV60: =AR60*$B$15/4 -> 1572.625 | AW60: =SUM($AV$3:AV60) -> 76342.175 | AX60: =AR60-AS60-AU60-AW60 -> 412592.83 | AY60: =$B$36*V60 -> 1839.3857 | AZ60: =SUM(AY60:AY60)*4/AR60 -> 0.013450718 | BA60: =SUM(AY60:AY60)/V60 -> 0.35 | BB60: =IF(MortgageRate="Discounted",_xlfn.XLOOKUP(L60,'mortgage-rates'!$A:$A,'mortgage-rates'!$E:$E)/100,_xlfn.XLOOKUP(L60,'mortgage-rates'!$A:$A,'mortgage-rates'!$D:$D)/100) -> 0.0365 | BC60: =BC59-BF59 -> 155661.29 | BD60: =IF($B$16*12/3-Q60+1>0,-PMT($BB60/4,$B$16*12/3-Q60+1,BC60),0) -> 4392.8426 | BE60: =BC60*($BB60/4) -> 1420.4093 | BF60: =BD60-BE60 -> 2972.4334 | BG60: =AT60+AY60+BD60 -> 6232.2283 | BH60: =INDEX(cpi!B:B,MATCH($L60,cpi!A:A)) -> 114.5 | BI60: =100*BH60/BH$3 -> 135.34279 | BJ60: =100*AC60/AC$3 -> 197.57431 | BK60: =100*AD60/AD$3 -> 194.19317 | BL60: =BJ60*GlobalPortfolio+BK60*AusPortfolio -> 196.55997 | BM60: =100*AE60/$AE$3 -> 390.76432 | BN60: =100*AR60/AR$3 -> 168.30769 | BO60: =100*AX60/AX$3 -> 130.25691
L61: =DATE(YEAR(L60),MONTH(L60)+3,1) -> 44075 | M61: =AP61 -> 407414.87 | N61: =AX61-BC61 -> 265335.85 | O61: =M61/N61 -> 1.5354687 | P61: =X61/BG61 -> 0.87545761 | Q61: 59 | R61: =EOMONTH(L61,0)-EOMONTH(L61,-3) -> 92 | T61: =IF($B$10="3BR_H", INDEX('3BR_H-processed'!$E:$E,MATCH($L61,'3BR_H-processed'!$B:$B,0),MATCH(Council_Area,'3BR_H-processed'!$E$1:$E$1,0)), INDEX('2BR_F-processed'!$E:$E,MATCH($L61,'2BR_F-processed'!$B:$B,0),MATCH(Council_Area,'2BR_F-processed'!$E$1:$E$1,0))) -> 402.53277 | U61: =IF(MOD(Q61,4)=1,T61,U60) -> 404.26059 | V61: =U61*(R61)/7 -> 5313.1392 | W61: =$B$53/4*BH61/_xlfn.XLOOKUP(Q_end,cpi!A:A,cpi!B:B) -> 160.60815 | X61: =V61+W61 -> 5473.7473 | Y61: =BG61-X61 -> 778.69401 | Z61: =Y61*$B$47 -> 0 | AA61: {=(Y61+Z61)*eff_invest} -> 778.69401 | AB61: =AA61*(_xlfn.XLOOKUP(Q_end,cpi!A:A,cpi!B:B)/BH61) -> 969.68178 | AC61: {=INDEX('msci-indices'!C:C,MATCH($L61,'msci-indices'!$B:$B)-2)} -> 1788.7914 | AD61: {=INDEX('msci-indices'!D:D,MATCH($L61,'msci-indices'!$B:$B)-2)} -> 1621.6232 | AE61: =AI60+AA61 -> 386404.61 | AF61: {=INDEX('msci-indices'!C:C,MATCH($L61,'msci-indices'!$B:$B)+1)} -> 1929.6384 | AG61: {=INDEX('msci-indices'!D:D,MATCH($L61,'msci-indices'!$B:$B)+1)} -> 1620.9838 | AH61: =(InvestFees/4)*AE61 -> 241.50288 | AI61: =((AF61/AC61)*GlobalPortfolio+(AG61/AD61)*AusPortfolio)*AE61-AH61 -> 407414.87 | AJ61: =AJ60+AA61 -> 192387.91 | AK61: =AI61-AJ61 -> 215026.96 | AL61: =AJ61*(_xlfn.XLOOKUP(Q_end,cpi!A:A,cpi!B:B)/BH61) -> 239574.28 | AM61: {=SUMPRODUCT($AA$3:AA61,_xlfn.SORTBY($BH$3:BH61,_xlfn.SEQUENCE(ROWS($BH$3:BH61)),-1)/$BH$3)} -> 251129.52 | AN61: =AI61-AM61 -> 156285.36 | AO61: =IF($B$49="Real gains",MAX($B$50*AN61,0),IF($B$49="Discounted nominal gains",MAX($B$50*AK61/2,0),0)) -> 0 | AP61: =AI61-AO61 -> 407414.87 | AR61: =IF($B$10="3BR_H", INDEX('ns-combined'!$C:$D,MATCH($L61,'ns-combined'!$B:$B,0),MATCH(Council_Area,'ns-combined'!$C$1:$D$1,0))*1000, INDEX('s-combined'!$C:$D,MATCH($L61,'s-combined'!$B:$B,0),MATCH(Council_Area,'s-combined'!$C$1:$D$1,0))*1000) -> 555000 | AS61: =AS60+$AS$3 -> 47937.5 | AT61: 0 | AU61: =SUM($B$28:$B$29)*AR61 -> 11100 | AV61: =AR61*$B$15/4 -> 1595.625 | AW61: =SUM($AV$3:AV61) -> 77937.8 | AX61: =AR61-AS61-AU61-AW61 -> 418024.7 | AY61: =$B$36*V61 -> 1859.5987 | AZ61: =SUM(AY61:AY61)*4/AR61 -> 0.013402513 | BA61: =SUM(AY61:AY61)/V61 -> 0.35 | BB61: =IF(MortgageRate="Discounted",_xlfn.XLOOKUP(L61,'mortgage-rates'!$A:$A,'mortgage-rates'!$E:$E)/100,_xlfn.XLOOKUP(L61,'mortgage-rates'!$A:$A,'mortgage-rates'!$D:$D)/100) -> 0.0365 | BC61: =BC60-BF60 -> 152688.85 | BD61: =IF($B$16*12/3-Q61+1>0,-PMT($BB61/4,$B$16*12/3-Q61+1,BC61),0) -> 4392.8426 | BE61: =BC61*($BB61/4) -> 1393.2858 | BF61: =BD61-BE61 -> 2999.5568 | BG61: =AT61+AY61+BD61 -> 6252.4413 | BH61: =INDEX(cpi!B:B,MATCH($L61,cpi!A:A)) -> 116.2 | BI61: =100*BH61/BH$3 -> 137.35225 | BJ61: =100*AC61/AC$3 -> 236.9638 | BK61: =100*AD61/AD$3 -> 227.4506 | BL61: =BJ61*GlobalPortfolio+BK61*AusPortfolio -> 234.10984 | BM61: =100*AE61/$AE$3 -> 466.06938 | BN61: =100*AR61/AR$3 -> 170.76923 | BO61: =100*AX61/AX$3 -> 131.97177
L62: =DATE(YEAR(L61),MONTH(L61)+3,1) -> 44166 | M62: =AP62 -> 468338.4 | N62: =AX62-BC62 -> 285469.78 | O62: =M62/N62 -> 1.6405884 | P62: =X62/BG62 -> 0.87567867 | Q62: 60 | R62: =EOMONTH(L62,0)-EOMONTH(L62,-3) -> 92 | T62: =IF($B$10="3BR_H", INDEX('3BR_H-processed'!$E:$E,MATCH($L62,'3BR_H-processed'!$B:$B,0),MATCH(Council_Area,'3BR_H-processed'!$E$1:$E$1,0)), INDEX('2BR_F-processed'!$E:$E,MATCH($L62,'2BR_F-processed'!$B:$B,0),MATCH(Council_Area,'2BR_F-processed'!$E$1:$E$1,0))) -> 411.12757 | U62: =IF(MOD(Q62,4)=1,T62,U61) -> 404.26059 | V62: =U62*(R62)/7 -> 5313.1392 | W62: =$B$53/4*BH62/_xlfn.XLOOKUP(Q_end,cpi!A:A,cpi!B:B) -> 161.99032 | X62: =V62+W62 -> 5475.1295 | Y62: =BG62-X62 -> 777.31184 | Z62: =Y62*$B$47 -> 0 | AA62: {=(Y62+Z62)*eff_invest} -> 777.31184 | AB62: =AA62*(_xlfn.XLOOKUP(Q_end,cpi!A:A,cpi!B:B)/BH62) -> 959.70156 | AC62: {=INDEX('msci-indices'!C:C,MATCH($L62,'msci-indices'!$B:$B)-2)} -> 1929.6384 | AD62: {=INDEX('msci-indices'!D:D,MATCH($L62,'msci-indices'!$B:$B)-2)} -> 1620.9838 | AE62: =AI61+AA62 -> 408192.18 | AF62: {=INDEX('msci-indices'!C:C,MATCH($L62,'msci-indices'!$B:$B)+1)} -> 2220.9403 | AG62: {=INDEX('msci-indices'!D:D,MATCH($L62,'msci-indices'!$B:$B)+1)} -> 1849.5395 | AH62: =(InvestFees/4)*AE62 -> 255.12012 | AI62: =((AF62/AC62)*GlobalPortfolio+(AG62/AD62)*AusPortfolio)*AE62-AH62 -> 468338.4 | AJ62: =AJ61+AA62 -> 193165.23 | AK62: =AI62-AJ62 -> 275173.17 | AL62: =AJ62*(_xlfn.XLOOKUP(Q_end,cpi!A:A,cpi!B:B)/BH62) -> 238489.83 | AM62: {=SUMPRODUCT($AA$3:AA62,_xlfn.SORTBY($BH$3:BH62,_xlfn.SEQUENCE(ROWS($BH$3:BH62)),-1)/$BH$3)} -> 253519.12 | AN62: =AI62-AM62 -> 214819.28 | AO62: =IF($B$49="Real gains",MAX($B$50*AN62,0),IF($B$49="Discounted nominal gains",MAX($B$50*AK62/2,0),0)) -> 0 | AP62: =AI62-AO62 -> 468338.4 | AR62: =IF($B$10="3BR_H", INDEX('ns-combined'!$C:$D,MATCH($L62,'ns-combined'!$B:$B,0),MATCH(Council_Area,'ns-combined'!$C$1:$D$1,0))*1000, INDEX('s-combined'!$C:$D,MATCH($L62,'s-combined'!$B:$B,0),MATCH(Council_Area,'s-combined'!$C$1:$D$1,0))*1000) -> 575000 | AS62: =AS61+$AS$3 -> 48750 | AT62: 0 | AU62: =SUM($B$28:$B$29)*AR62 -> 11500 | AV62: =AR62*$B$15/4 -> 1653.125 | AW62: =SUM($AV$3:AV62) -> 79590.925 | AX62: =AR62-AS62-AU62-AW62 -> 435159.08 | AY62: =$B$36*V62 -> 1859.5987 | AZ62: =SUM(AY62:AY62)*4/AR62 -> 0.012936339 | BA62: =SUM(AY62:AY62)/V62 -> 0.35 | BB62: =IF(MortgageRate="Discounted",_xlfn.XLOOKUP(L62,'mortgage-rates'!$A:$A,'mortgage-rates'!$E:$E)/100,_xlfn.XLOOKUP(L62,'mortgage-rates'!$A:$A,'mortgage-rates'!$D:$D)/100) -> 0.0365 | BC62: =BC61-BF61 -> 149689.3 | BD62: =IF($B$16*12/3-Q62+1>0,-PMT($BB62/4,$B$16*12/3-Q62+1,BC62),0) -> 4392.8426 | BE62: =BC62*($BB62/4) -> 1365.9148 | BF62: =BD62-BE62 -> 3026.9278 | BG62: =AT62+AY62+BD62 -> 6252.4413 | BH62: =INDEX(cpi!B:B,MATCH($L62,cpi!A:A)) -> 117.2 | BI62: =100*BH62/BH$3 -> 138.53428 | BJ62: =100*AC62/AC$3 -> 255.622 | BK62: =100*AD62/AD$3 -> 227.36091 | BL62: =BJ62*GlobalPortfolio+BK62*AusPortfolio -> 247.14367 | BM62: =100*AE62/$AE$3 -> 492.34888 | BN62: =100*AR62/AR$3 -> 176.92308 | BO62: =100*AX62/AX$3 -> 137.38115
L63: =DATE(YEAR(L62),MONTH(L62)+3,1) -> 44256 | M63: =AP63 -> 492894.93 | N63: =AX63-BC63 -> 310459.2 | O63: =M63/N63 -> 1.5876319 | P63: =X63/BG63 -> 0.89208244 | Q63: 61 | R63: =EOMONTH(L63,0)-EOMONTH(L63,-3) -> 90 | T63: =IF($B$10="3BR_H", INDEX('3BR_H-processed'!$E:$E,MATCH($L63,'3BR_H-processed'!$B:$B,0),MATCH(Council_Area,'3BR_H-processed'!$E$1:$E$1,0)), INDEX('2BR_F-processed'!$E:$E,MATCH($L63,'2BR_F-processed'!$B:$B,0),MATCH(Council_Area,'2BR_F-processed'!$E$1:$E$1,0))) -> 424.74896 | U63: =IF(MOD(Q63,4)=1,T63,U62) -> 424.74896 | V63: =U63*(R63)/7 -> 5461.0581 | W63: =$B$53/4*BH63/_xlfn.XLOOKUP(Q_end,cpi!A:A,cpi!B:B) -> 162.81963 | X63: =V63+W63 -> 5623.8777 | Y63: =BG63-X63 -> 680.33525 | Z63: =Y63*$B$47 -> 0 | AA63: {=(Y63+Z63)*eff_invest} -> 680.33525 | AB63: =AA63*(_xlfn.XLOOKUP(Q_end,cpi!A:A,cpi!B:B)/BH63) -> 835.69194 | AC63: {=INDEX('msci-indices'!C:C,MATCH($L63,'msci-indices'!$B:$B)-2)} -> 2220.9403 | AD63: {=INDEX('msci-indices'!D:D,MATCH($L63,'msci-indices'!$B:$B)-2)} -> 1849.5395 | AE63: =AI62+AA63 -> 469018.74 | AF63: {=INDEX('msci-indices'!C:C,MATCH($L63,'msci-indices'!$B:$B)+1)} -> 2342.5855 | AG63: {=INDEX('msci-indices'!D:D,MATCH($L63,'msci-indices'!$B:$B)+1)} -> 1930.8659 | AH63: =(InvestFees/4)*AE63 -> 293.13671 | AI63: =((AF63/AC63)*GlobalPortfolio+(AG63/AD63)*AusPortfolio)*AE63-AH63 -> 492894.93 | AJ63: =AJ62+AA63 -> 193845.56 | AK63: =AI63-AJ63 -> 299049.37 | AL63: =AJ63*(_xlfn.XLOOKUP(Q_end,cpi!A:A,cpi!B:B)/BH63) -> 238110.8 | AM63: {=SUMPRODUCT($AA$3:AA63,_xlfn.SORTBY($BH$3:BH63,_xlfn.SEQUENCE(ROWS($BH$3:BH63)),-1)/$BH$3)} -> 255438.46 | AN63: =AI63-AM63 -> 237456.47 | AO63: =IF($B$49="Real gains",MAX($B$50*AN63,0),IF($B$49="Discounted nominal gains",MAX($B$50*AK63/2,0),0)) -> 0 | AP63: =AI63-AO63 -> 492894.93 | AR63: =IF($B$10="3BR_H", INDEX('ns-combined'!$C:$D,MATCH($L63,'ns-combined'!$B:$B,0),MATCH(Council_Area,'ns-combined'!$C$1:$D$1,0))*1000, INDEX('s-combined'!$C:$D,MATCH($L63,'s-combined'!$B:$B,0),MATCH(Council_Area,'s-combined'!$C$1:$D$1,0))*1000) -> 600000 | AS63: =AS62+$AS$3 -> 49562.5 | AT63: 0 | AU63: =SUM($B$28:$B$29)*AR63 -> 12000 | AV63: =AR63*$B$15/4 -> 1725 | AW63: =SUM($AV$3:AV63) -> 81315.925 | AX63: =AR63-AS63-AU63-AW63 -> 457121.58 | AY63: =$B$36*V63 -> 1911.3703 | AZ63: =SUM(AY63:AY63)*4/AR63 -> 0.012742469 | BA63: =SUM(AY63:AY63)/V63 -> 0.35 | BB63: =IF(MortgageRate="Discounted",_xlfn.XLOOKUP(L63,'mortgage-rates'!$A:$A,'mortgage-rates'!$E:$E)/100,_xlfn.XLOOKUP(L63,'mortgage-rates'!$A:$A,'mortgage-rates'!$D:$D)/100) -> 0.0365 | BC63: =BC62-BF62 -> 146662.37 | BD63: =IF($B$16*12/3-Q63+1>0,-PMT($BB63/4,$B$16*12/3-Q63+1,BC63),0) -> 4392.8426 | BE63: =BC63*($BB63/4) -> 1338.2941 | BF63: =BD63-BE63 -> 3054.5485 | BG63: =AT63+AY63+BD63 -> 6304.213 | BH63: =INDEX(cpi!B:B,MATCH($L63,cpi!A:A)) -> 117.8 | BI63: =100*BH63/BH$3 -> 139.2435 | BJ63: =100*AC63/AC$3 -> 294.21119 | BK63: =100*AD63/AD$3 -> 259.41837 | BL63: =BJ63*GlobalPortfolio+BK63*AusPortfolio -> 283.77335 | BM63: =100*AE63/$AE$3 -> 565.716 | BN63: =100*AR63/AR$3 -> 184.61538 | BO63: =100*AX63/AX$3 -> 144.31478
L64: =DATE(YEAR(L63),MONTH(L63)+3,1) -> 44348 | M64: =AP64 -> 531321.86 | N64: =AX64-BC64 -> 340290 | O64: =M64/N64 -> 1.5613796 | P64: =X64/BG64 -> 0.90064982 | Q64: 62 | R64: =EOMONTH(L64,0)-EOMONTH(L64,-3) -> 91 | T64: =IF($B$10="3BR_H", INDEX('3BR_H-processed'!$E:$E,MATCH($L64,'3BR_H-processed'!$B:$B,0),MATCH(Council_Area,'3BR_H-processed'!$E$1:$E$1,0)), INDEX('2BR_F-processed'!$E:$E,MATCH($L64,'2BR_F-processed'!$B:$B,0),MATCH(Council_Area,'2BR_F-processed'!$E$1:$E$1,0))) -> 427.69645 | U64: =IF(MOD(Q64,4)=1,T64,U63) -> 424.74896 | V64: =U64*(R64)/7 -> 5521.7365 | W64: =$B$53/4*BH64/_xlfn.XLOOKUP(Q_end,cpi!A:A,cpi!B:B) -> 164.2018 | X64: =V64+W64 -> 5685.9383 | Y64: =BG64-X64 -> 627.2127 | Z64: =Y64*$B$47 -> 0 | AA64: {=(Y64+Z64)*eff_invest} -> 627.2127 | AB64: =AA64*(_xlfn.XLOOKUP(Q_end,cpi!A:A,cpi!B:B)/BH64) -> 763.95352 | AC64: {=INDEX('msci-indices'!C:C,MATCH($L64,'msci-indices'!$B:$B)-2)} -> 2342.5855 | AD64: {=INDEX('msci-indices'!D:D,MATCH($L64,'msci-indices'!$B:$B)-2)} -> 1930.8659 | AE64: =AI63+AA64 -> 493522.14 | AF64: {=INDEX('msci-indices'!C:C,MATCH($L64,'msci-indices'!$B:$B)+1)} -> 2515.6062 | AG64: {=INDEX('msci-indices'!D:D,MATCH($L64,'msci-indices'!$B:$B)+1)} -> 2095.0894 | AH64: =(InvestFees/4)*AE64 -> 308.45134 | AI64: =((AF64/AC64)*GlobalPortfolio+(AG64/AD64)*AusPortfolio)*AE64-AH64 -> 531321.86 | AJ64: =AJ63+AA64 -> 194472.77 | AK64: =AI64-AJ64 -> 336849.09 | AL64: =AJ64*(_xlfn.XLOOKUP(Q_end,cpi!A:A,cpi!B:B)/BH64) -> 236870.46 | AM64: {=SUMPRODUCT($AA$3:AA64,_xlfn.SORTBY($BH$3:BH64,_xlfn.SEQUENCE(ROWS($BH$3:BH64)),-1)/$BH$3)} -> 257713.67 | AN64: =AI64-AM64 -> 273608.19 | AO64: =IF($B$49="Real gains",MAX($B$50*AN64,0),IF($B$49="Discounted nominal gains",MAX($B$50*AK64/2,0),0)) -> 0 | AP64: =AI64-AO64 -> 531321.86 | AR64: =IF($B$10="3BR_H", INDEX('ns-combined'!$C:$D,MATCH($L64,'ns-combined'!$B:$B,0),MATCH(Council_Area,'ns-combined'!$C$1:$D$1,0))*1000, INDEX('s-combined'!$C:$D,MATCH($L64,'s-combined'!$B:$B,0),MATCH(Council_Area,'s-combined'!$C$1:$D$1,0))*1000) -> 630000 | AS64: =AS63+$AS$3 -> 50375 | AT64: 0 | AU64: =SUM($B$28:$B$29)*AR64 -> 12600 | AV64: =AR64*$B$15/4 -> 1811.25 | AW64: =SUM($AV$3:AV64) -> 83127.175 | AX64: =AR64-AS64-AU64-AW64 -> 483897.83 | AY64: =$B$36*V64 -> 1932.6078 | AZ64: =SUM(AY64:AY64)*4/AR64 -> 0.012270526 | BA64: =SUM(AY64:AY64)/V64 -> 0.35 | BB64: =IF(MortgageRate="Discounted",_xlfn.XLOOKUP(L64,'mortgage-rates'!$A:$A,'mortgage-rates'!$E:$E)/100,_xlfn.XLOOKUP(L64,'mortgage-rates'!$A:$A,'mortgage-rates'!$D:$D)/100) -> 0.0359 | BC64: =BC63-BF63 -> 143607.82 | BD64: =IF($B$16*12/3-Q64+1>0,-PMT($BB64/4,$B$16*12/3-Q64+1,BC64),0) -> 4380.5432 | BE64: =BC64*($BB64/4) -> 1288.8802 | BF64: =BD64-BE64 -> 3091.663 | BG64: =AT64+AY64+BD64 -> 6313.151 | BH64: =INDEX(cpi!B:B,MATCH($L64,cpi!A:A)) -> 118.8 | BI64: =100*BH64/BH$3 -> 140.42553 | BJ64: =100*AC64/AC$3 -> 310.3257 | BK64: =100*AD64/AD$3 -> 270.8253 | BL64: =BJ64*GlobalPortfolio+BK64*AusPortfolio -> 298.47558 | BM64: =100*AE64/$AE$3 -> 595.27126 | BN64: =100*AR64/AR$3 -> 193.84615 | BO64: =100*AX64/AX$3 -> 152.76813
