Workbook
Name A83728543L: 'ABS-total-value-dwellings'!$AF$1:$AF$10,'ABS-total-value-dwellings'!$AF$11:$AF$106
Name A83728543L_Data: 'ABS-total-value-dwellings'!$AF$11:$AF$106
Name A83728543L_Latest: 'ABS-total-value-dwellings'!$AF$106
Name A83728544R: 'ABS-total-value-dwellings'!$AU$1:$AU$10,'ABS-total-value-dwellings'!$AU$17:$AU$106
Name A83728544R_Data: 'ABS-total-value-dwellings'!$AU$17:$AU$106
Name A83728544R_Latest: 'ABS-total-value-dwellings'!$AU$106
Name A83728545T: 'ABS-total-value-dwellings'!$B$1:$B$10,'ABS-total-value-dwellings'!$B$11:$B$106
Name A83728545T_Data: 'ABS-total-value-dwellings'!$B$11:$B$106
Name A83728545T_Latest: 'ABS-total-value-dwellings'!$B$106
Name A83728546V: 'ABS-total-value-dwellings'!$Q$1:$Q$10,'ABS-total-value-dwellings'!$Q$17:$Q$106
Name A83728546V_Data: 'ABS-total-value-dwellings'!$Q$17:$Q$106
Name A83728546V_Latest: 'ABS-total-value-dwellings'!$Q$106
Name A83728547W: 'ABS-total-value-dwellings'!$AH$1:$AH$10,'ABS-total-value-dwellings'!$AH$11:$AH$106
Name A83728547W_Data: 'ABS-total-value-dwellings'!$AH$11:$AH$106
Name A83728547W_Latest: 'ABS-total-value-dwellings'!$AH$106
Name A83728548X: 'ABS-total-value-dwellings'!$AW$1:$AW$10,'ABS-total-value-dwellings'!$AW$17:$AW$106
Name A83728548X_Data: 'ABS-total-value-dwellings'!$AW$17:$AW$106
Name A83728548X_Latest: 'ABS-total-value-dwellings'!$AW$106
Name A83728549A: 'ABS-total-value-dwellings'!$D$1:$D$10,'ABS-total-value-dwellings'!$D$11:$D$106
Name A83728549A_Data: 'ABS-total-value-dwellings'!$D$11:$D$106
Name A83728549A_Latest: 'ABS-total-value-dwellings'!$D$106
Name A83728550K: 'ABS-total-value-dwellings'!$S$1:$S$10,'ABS-total-value-dwellings'!$S$17:$S$106
Name A83728550K_Data: 'ABS-total-value-dwellings'!$S$17:$S$106
Name A83728550K_Latest: 'ABS-total-value-dwellings'!$S$106
Name A83728551L: 'ABS-total-value-dwellings'!$AJ$1:$AJ$10,'ABS-total-value-dwellings'!$AJ$11:$AJ$106
Name A83728551L_Data: 'ABS-total-value-dwellings'!$AJ$11:$AJ$106
Name A83728551L_Latest: 'ABS-total-value-dwellings'!$AJ$106
Name A83728552R: 'ABS-total-value-dwellings'!$AY$1:$AY$10,'ABS-total-value-dwellings'!$AY$17:$AY$106
Name A83728552R_Data: 'ABS-total-value-dwellings'!$AY$17:$AY$106
Name A83728552R_Latest: 'ABS-total-value-dwellings'!$AY$106
Name A83728553T: 'ABS-total-value-dwellings'!$F$1:$F$10,'ABS-total-value-dwellings'!$F$11:$F$106
Name A83728553T_Data: 'ABS-total-value-dwellings'!$F$11:$F$106
Name A83728553T_Latest: 'ABS-total-value-dwellings'!$F$106
Name A83728554V: 'ABS-total-value-dwellings'!$U$1:$U$10,'ABS-total-value-dwellings'!$U$17:$U$106
Name A83728554V_Data: 'ABS-total-value-dwellings'!$U$17:$U$106
Name A83728554V_Latest: 'ABS-total-value-dwellings'!$U$106
Name A83728555W: 'ABS-total-value-dwellings'!$AL$1:$AL$10,'ABS-total-value-dwellings'!$AL$11:$AL$106
Name A83728555W_Data: 'ABS-total-value-dwellings'!$AL$11:$AL$106
Name A83728555W_Latest: 'ABS-total-value-dwellings'!$AL$106
Name A83728556X: 'ABS-total-value-dwellings'!$BA$1:$BA$10,'ABS-total-value-dwellings'!$BA$17:$BA$106
Name A83728556X_Data: 'ABS-total-value-dwellings'!$BA$17:$BA$106
Name A83728556X_Latest: 'ABS-total-value-dwellings'!$BA$106
Name A83728557A: 'ABS-total-value-dwellings'!$H$1:$H$10,'ABS-total-value-dwellings'!$H$11:$H$106
Name A83728557A_Data: 'ABS-total-value-dwellings'!$H$11:$H$106
Name A83728557A_Latest: 'ABS-total-value-dwellings'!$H$106
Name A83728558C: 'ABS-total-value-dwellings'!$W$1:$W$10,'ABS-total-value-dwellings'!$W$17:$W$106
Name A83728558C_Data: 'ABS-total-value-dwellings'!$W$17:$W$106
Name A83728558C_Latest: 'ABS-total-value-dwellings'!$W$106
Name A83728559F: 'ABS-total-value-dwellings'!$AN$1:$AN$10,'ABS-total-value-dwellings'!$AN$11:$AN$106
Name A83728559F_Data: 'ABS-total-value-dwellings'!$AN$11:$AN$106
Name A83728559F_Latest: 'ABS-total-value-dwellings'!$AN$106
Name A83728560R: 'ABS-total-value-dwellings'!$BC$1:$BC$10,'ABS-total-value-dwellings'!$BC$17:$BC$106
Name A83728560R_Data: 'ABS-total-value-dwellings'!$BC$17:$BC$106
Name A83728560R_Latest: 'ABS-total-value-dwellings'!$BC$106
Name A83728561T: 'ABS-total-value-dwellings'!$J$1:$J$10,'ABS-total-value-dwellings'!$J$11:$J$106
Name A83728561T_Data: 'ABS-total-value-dwellings'!$J$11:$J$106
Name A83728561T_Latest: 'ABS-total-value-dwellings'!$J$106
Name A83728562V: 'ABS-total-value-dwellings'!$Y$1:$Y$10,'ABS-total-value-dwellings'!$Y$17:$Y$106
Name A83728562V_Data: 'ABS-total-value-dwellings'!$Y$17:$Y$106
Name A83728562V_Latest: 'ABS-total-value-dwellings'!$Y$106

Sheet analysis
A1: Rent vs buy analysis - Sydney | B1: Set values | C1: Default values | T1: Renter calcs >> | X1: {=SUM(_xlfn._xlws.FILTER(X3:X82,ISNUMBER(X3:X82)))} -> 495610.31 | AI1: CGT calcs | AR1: Buyer calcs >> | AY1: Maintenance and renovation | BB1: Mortgage | BG1: {=SUM(_xlfn._xlws.FILTER(BG3:BG82,ISNUMBER(BG3:BG82)))} -> 847025.77 | BH1: Comparison vs inflation
A2: Ending renter-to-owner wealth ratio | B2: =_xlfn.XLOOKUP(Q_end,L:L,O:O) -> 1.5721835 | E2: ="Renter vs owner wealth, "&IF(Council_Area="Greater Sydney","Sydney",Council_Area)&IF(B10="2BR_F"," 2-bedroom flat"," 3-bedroom house") -> Renter vs owner wealth, Sydney 3-bedroom house | L2: Quarter ending | M2: Renter's portfolio | N2: Owner's home equity | O2: Renter-to-owner wealth ratio | P2: Renter-to-owner cash needs | Q2: Quarter of analysis | R2: Days in quarter | T2: Median weekly rents, new bonds | U2: Renter's rents | V2: Quarterly rent | W2: Other renter costs | X2: Renter's cashflow costs | Y2: Renter additional cashflow | Z2: Tax concessions | AA2: Renter investment contributions | AB2: Contributions (CPI-adjusted to Q_end) | AC2: MSCI World index, start Q | AD2: MSCI Aus index, start Q | AE2: Portfolio, start Q | AF2: MSCI World index, end Q | AG2: MSCI Aus index, end Q | AH2: Investment fees | AI2: Portfolio, end Q, before CGT | AJ2: Cost base (nominal) | AK2: Nominal gains ($) | AL2: Cost base (CPI-adjusted to Q_end) | AM2: Cost base + CPI to current quarter | AN2: Real gains ($) | AO2: CGT on withdrawals | AP2: Portfolio, end Q | AR2: Median home price | AS2: Depreciation | AT2: Home purchase costs | AU2: Home sale costs | AV2: Renovation | AW2: Renovation, cumulative | AX2: Adjusted home price | AY2: Maintenance | AZ2: Total p.a. as % of home value | BA2: Total p.a. as % of rent | BB2: Mortgage rates | BC2: Loan balance | BD2: Mortgage payment | BE2: Mortgage interest | BF2: Mortgage - principal component | BG2: Owner's cashflow costs | BH2: CPI | BI2: CPI (Q_st art = 100) | BJ2: MSCI World (Q_start=100) | BK2: MSCI Aus (Q_start=100) | BL2: Portfolio index (Q_start=100) | BM2: Portfolio (Q_start=100) | BN2: Median home price (Q_start = 100) | BO2: Adjusted home price (Q_start = 100)
A3: Average renter-to-owner cashflow needs excl. home purchase costs | B3: {=SUM(_xlfn._xlws.FILTER($X$3:$X$82,ISNUMBER($X$3:$X$82)))/(SUM(_xlfn._xlws.FILTER($BG$3:$BG$82,ISNUMBER($BG$3:$BG$82)))-AT3)} -> 0.67712268 | L3: =Q_start -> 38777 | M3: =AP3 -> 171246 | N3: =AX3-BC3 -> 80327.5 | O3: =M3/N3 -> 2.1318478 | P3: =X3/BG3 -> 0.028454399 | Q3: 1 | R3: =EOMONTH(L3,0)-EOMONTH(L3,-3) -> 90 | T3: =IF($B$10="3BR_H", INDEX('3BR_H-combined'!$C:$BH,MATCH($L3,'3BR_H-combined'!$B:$B,0),MATCH(Council_Area,'3BR_H-combined'!$C$1:$BH$1,0)), INDEX('2BR_F-combined'!$C:$BH,MATCH($L3,'2BR_F-combined'!$B:$B,0),MATCH(Council_Area,'2BR_F-combined'!$C$1:$BH$1,0))) -> 265 | U3: =IF(MOD(Q3,4)=1,T3,U2) -> 265 | V3: =U3*(R3)/7 -> 3407.1429 | W3: =$B$53/4*BH3/_xlfn.XLOOKUP(Q_end,cpi!A:A,cpi!B:B) -> 116.93158 | X3: =V3+W3 -> 3524.0744 | Y3: =BG3-X3 -> 120325.83 | Z3: =MAX(0,Y3*$B$47) -> 38504.264 | AA3: =(Y3+Z3)*eff_invest -> 158830.09 | AB3: =AA3*(_xlfn.XLOOKUP(Q_end,cpi!A:A,cpi!B:B)/BH3) -> 271663.29 | AC3: {=INDEX('msci-indices'!C:C,MATCH($L3,'msci-indices'!$B:$B)-2)} -> 754.87961 | AD3: {=INDEX('msci-indices'!D:D,MATCH($L3,'msci-indices'!$B:$B)-2)} -> 712.95625 | AE3: =AA3 -> 158830.09 | AF3: {=INDEX('msci-indices'!C:C,MATCH($L3,'msci-indices'!$B:$B)+1)} -> 809.32012 | AG3: {=INDEX('msci-indices'!D:D,MATCH($L3,'msci-indices'!$B:$B)+1)} -> 780.24347 | AH3: =(InvestFees/4)*AE3 -> 99.268806 | AI3: =((AF3/AC3)*GlobalPortfolio+(AG3/AD3)*AusPortfolio)*AE3-AH3 -> 171246 | AJ3: =AA3 -> 158830.09 | AK3: =AI3-AJ3 -> 12415.911 | AL3: =AJ3*(_xlfn.XLOOKUP(Q_end,cpi!A:A,cpi!B:B)/BH3) -> 271663.29 | AM3: =AA3 -> 158830.09 | AN3: =AI3-AM3 -> 12415.911 | AO3: =IF($B$49="Real gains",MAX($B$50*AN3,0),IF($B$49="Discounted nominal gains",MAX($B$50*AK3/2,0),0)) -> 0 | AP3: =AI3-AO3 -> 171246 | AR3: =IF($B$10="3BR_H", INDEX('ns-combined'!$C:$BH,MATCH($L3,'ns-combined'!$B:$B,0),MATCH(Council_Area,'ns-combined'!$C$1:$BH$1,0))*1000, INDEX('s-combined'!$C:$BH,MATCH($L3,'s-combined'!$B:$B,0),MATCH(Council_Area,'s-combined'!$C$1:$BH$1,0))*1000) -> 460000 | AS3: =AR3*$B$14/4 -> 1150 | AT3: =SUM(B20:B26)*AR3 -> 115090 | AU3: =SUM($B$28:$B$29)*AR3 -> 9200 | AV3: =AR3*$B$15/4 -> 1322.5 | AW3: =SUM($AV$3:AV3) -> 1322.5 | AX3: =AR3-AS3-AU3-AW3 -> 448327.5 | AY3: =$B$36*V3 -> 1192.5 | AZ3: =SUM(AY3:AY3)*4/AR3 -> 0.010369565 | BA3: =SUM(AY3:AY3)/V3 -> 0.35 | BB3: =IF(MortgageRate="Discounted",_xlfn.XLOOKUP(L3,'mortgage-rates'!$A:$A,'mortgage-rates'!$E:$E)/100,_xlfn.XLOOKUP(L3,'mortgage-rates'!$A:$A,'mortgage-rates'!$D:$D)/100) -> 0.0664 | BC3: =(1-B20)*AR3 -> 368000 | BD3: =IF($B$16*12/3-Q3+1>0,-PMT($BB3/4,$B$16*12/3-Q3+1,BC3),0) -> 7567.3998 | BE3: =BC3*($BB3/4) -> 6108.8 | BF3: =BD3-BE3 -> 1458.5998 | BG3: =AT3+AY3+BD3 -> 123849.9 | BH3: =INDEX(cpi!B:B,MATCH($L3,cpi!A:A)) -> 84.6 | BI3: =100*BH3/BH$3 -> 100 | BJ3: =100*AC3/AC$3 -> 100 | BK3: =100*AD3/AD$3 -> 100 | BL3: =BJ3*GlobalPortfolio+BK3*AusPortfolio -> 100 | BM3: =100*AE3/$AE$3 -> 100 | BN3: =100*AR3/AR$3 -> 100 | BO3: =100*AX3/AX$3 -> 100
A4: Median home price growth p.a. | B4: =((_xlfn.XLOOKUP(Q_end,L:L,AR:AR)/_xlfn.XLOOKUP(Q_start,L:L,AR:AR))^(1/YEARFRAC(EOMONTH(Q_start,-3)+1,EOMONTH(Q_end,0))))-1 -> 0.063057079 | L4: =IF(DATE(YEAR(L3),MONTH(L3)+3,1)<=Q_end,DATE(YEAR(L3),MONTH(L3)+3,1),"") -> 38869 | M4: =AP4 -> 177232.23 | N4: =AX4-BC4 -> 103741.72 | O4: =M4/N4 -> 1.7083988 | P4: =X4/BG4 -> 0.39708887 | Q4: 2 | R4: =EOMONTH(L4,0)-EOMONTH(L4,-3) -> 91 | T4: =IF($B$10="3BR_H", INDEX('3BR_H-combined'!$C:$BH,MATCH($L4,'3BR_H-combined'!$B:$B,0),MATCH(Council_Area,'3BR_H-combined'!$C$1:$BH$1,0)), INDEX('2BR_F-combined'!$C:$BH,MATCH($L4,'2BR_F-combined'!$B:$B,0),MATCH(Council_Area,'2BR_F-combined'!$C$1:$BH$1,0))) -> 265 | U4: =IF(MOD(Q4,4)=1,T4,U3) -> 265 | V4: =U4*(R4)/7 -> 3445 | W4: =$B$53/4*BH4/_xlfn.XLOOKUP(Q_end,cpi!A:A,cpi!B:B) -> 118.7284 | X4: =V4+W4 -> 3563.7284 | Y4: =BG4-X4 -> 5410.9084 | Z4: =Y4*$B$47 -> 1731.4907 | AA4: =(Y4+Z4)*eff_invest -> 7142.3991 | AB4: =AA4*(_xlfn.XLOOKUP(Q_end,cpi!A:A,cpi!B:B)/BH4) -> 12031.492 | AC4: {=INDEX('msci-indices'!C:C,MATCH($L4,'msci-indices'!$B:$B)-2)} -> 809.32012 | AD4: {=INDEX('msci-indices'!D:D,MATCH($L4,'msci-indices'!$B:$B)-2)} -> 780.24347 | AE4: =AI3+AA4 -> 178388.4 | AF4: {=INDEX('msci-indices'!C:C,MATCH($L4,'msci-indices'!$B:$B)+1)} -> 802.64573 | AG4: {=INDEX('msci-indices'!D:D,MATCH($L4,'msci-indices'!$B:$B)+1)} -> 780.02674 | AH4: =(InvestFees/4)*AE4 -> 111.49275 | AI4: =((AF4/AC4)*GlobalPortfolio+(AG4/AD4)*AusPortfolio)*AE4-AH4 -> 177232.23 | AJ4: =AJ3+AA4 -> 165972.49 | AK4: =AI4-AJ4 -> 11259.746 | AL4: =AJ4*(_xlfn.XLOOKUP(Q_end,cpi!A:A,cpi!B:B)/BH4) -> 279583.46 | AM4: {=SUMPRODUCT($AA$3:AA4,_xlfn.SORTBY($BH$3:BH4,_xlfn.SEQUENCE(ROWS($BH$3:BH4)),-1)/$BH$3)} -> 168413.14 | AN4: =AI4-AM4 -> 8819.0946 | AO4: =IF($B$49="Real gains",MAX($B$50*AN4,0),IF($B$49="Discounted nominal gains",MAX($B$50*AK4/2,0),0)) -> 0 | AP4: =AI4-AO4 -> 177232.23 | AR4: =IF($B$10="3BR_H", INDEX('ns-combined'!$C:$BH,MATCH($L4,'ns-combined'!$B:$B,0),MATCH(Council_Area,'ns-combined'!$C$1:$BH$1,0))*1000, INDEX('s-combined'!$C:$BH,MATCH($L4,'s-combined'!$B:$B,0),MATCH(Council_Area,'s-combined'!$C$1:$BH$1,0))*1000) -> 485000 | AS4: =AS3+$AS$3 -> 2300 | AT4: 0 | AU4: =SUM($B$28:$B$29)*AR4 -> 9700 | AV4: =AR4*$B$15/4 -> 1394.375 | AW4: =SUM($AV$3:AV4) -> 2716.875 | AX4: =AR4-AS4-AU4-AW4 -> 470283.12 | AY4: =$B$36*V4 -> 1205.75 | AZ4: =SUM(AY4:AY4)*4/AR4 -> 0.0099443299 | BA4: =SUM(AY4:AY4)/V4 -> 0.35 | BB4: =IF(MortgageRate="Discounted",_xlfn.XLOOKUP(L4,'mortgage-rates'!$A:$A,'mortgage-rates'!$E:$E)/100,_xlfn.XLOOKUP(L4,'mortgage-rates'!$A:$A,'mortgage-rates'!$D:$D)/100) -> 0.0693 | BC4: =BC3-BF3 -> 366541.4 | BD4: =IF($B$16*12/3-Q4+1>0,-PMT($BB4/4,$B$16*12/3-Q4+1,BC4),0) -> 7768.8868 | BE4: =BC4*($BB4/4) -> 6350.3298 | BF4: =BD4-BE4 -> 1418.557 | BG4: =AT4+AY4+BD4 -> 8974.6368 | BH4: =INDEX(cpi!B:B,MATCH($L4,cpi!A:A)) -> 85.9 | BI4: =100*BH4/BH$3 -> 101.53664 | BJ4: =100*AC4/AC$3 -> 107.21181 | BK4: =100*AD4/AD$3 -> 109.43778 | BL4: =BJ4*GlobalPortfolio+BK4*AusPortfolio -> 107.8796 | BM4: =100*AE4/$AE$3 -> 112.31398 | BN4: =100*AR4/AR$3 -> 105.43478 | BO4: =100*AX4/AX$3 -> 104.89723
A5: Adjusted home price growth p.a. | B5: =((_xlfn.XLOOKUP(Q_end,L:L,AX:AX)/_xlfn.XLOOKUP(Q_start,L:L,AX:AX))^(1/YEARFRAC(EOMONTH(Q_start,-3)+1,EOMONTH(Q_end,0))))-1 -> 0.052061806 | L5: =DATE(YEAR(L4),MONTH(L4)+3,1) -> 38961 | M5: =AP5 -> 191229.57 | N5: =AX5-BC5 -> 89913.282 | O5: =M5/N5 -> 2.1268222 | P5: =X5/BG5 -> 0.39199261 | Q5: 3 | R5: =EOMONTH(L5,0)-EOMONTH(L5,-3) -> 92 | T5: =IF($B$10="3BR_H", INDEX('3BR_H-combined'!$C:$BH,MATCH($L5,'3BR_H-combined'!$B:$B,0),MATCH(Council_Area,'3BR_H-combined'!$C$1:$BH$1,0)), INDEX('2BR_F-combined'!$C:$BH,MATCH($L5,'2BR_F-combined'!$B:$B,0),MATCH(Council_Area,'2BR_F-combined'!$C$1:$BH$1,0))) -> 270 | U5: =IF(MOD(Q5,4)=1,T5,U4) -> 265 | V5: =U5*(R5)/7 -> 3482.8571 | W5: =$B$53/4*BH5/_xlfn.XLOOKUP(Q_end,cpi!A:A,cpi!B:B) -> 119.69592 | X5: =V5+W5 -> 3602.5531 | Y5: =BG5-X5 -> 5587.8065 | Z5: =Y5*$B$47 -> 1788.0981 | AA5: =(Y5+Z5)*eff_invest -> 7375.9046 | AB5: =AA5*(_xlfn.XLOOKUP(Q_end,cpi!A:A,cpi!B:B)/BH5) -> 12324.404 | AC5: {=INDEX('msci-indices'!C:C,MATCH($L5,'msci-indices'!$B:$B)-2)} -> 802.64573 | AD5: {=INDEX('msci-indices'!D:D,MATCH($L5,'msci-indices'!$B:$B)-2)} -> 780.02674 | AE5: =AI4+AA5 -> 184608.14 | AF5: {=INDEX('msci-indices'!C:C,MATCH($L5,'msci-indices'!$B:$B)+1)} -> 835.13401 | AG5: {=INDEX('msci-indices'!D:D,MATCH($L5,'msci-indices'!$B:$B)+1)} -> 801.24067 | AH5: =(InvestFees/4)*AE5 -> 115.38009 | AI5: =((AF5/AC5)*GlobalPortfolio+(AG5/AD5)*AusPortfolio)*AE5-AH5 -> 191229.57 | AJ5: =AJ4+AA5 -> 173348.39 | AK5: =AI5-AJ5 -> 17881.172 | AL5: =AJ5*(_xlfn.XLOOKUP(Q_end,cpi!A:A,cpi!B:B)/BH5) -> 289647.95 | AM5: {=SUMPRODUCT($AA$3:AA5,_xlfn.SORTBY($BH$3:BH5,_xlfn.SEQUENCE(ROWS($BH$3:BH5)),-1)/$BH$3)} -> 177212.99 | AN5: =AI5-AM5 -> 14016.571 | AO5: =IF($B$49="Real gains",MAX($B$50*AN5,0),IF($B$49="Discounted nominal gains",MAX($B$50*AK5/2,0),0)) -> 0 | AP5: =AI5-AO5 -> 191229.57 | AR5: =IF($B$10="3BR_H", INDEX('ns-combined'!$C:$BH,MATCH($L5,'ns-combined'!$B:$B,0),MATCH(Council_Area,'ns-combined'!$C$1:$BH$1,0))*1000, INDEX('s-combined'!$C:$BH,MATCH($L5,'s-combined'!$B:$B,0),MATCH(Council_Area,'s-combined'!$C$1:$BH$1,0))*1000) -> 472000 | AS5: =AS4+$AS$3 -> 3450 | AT5: 0 | AU5: =SUM($B$28:$B$29)*AR5 -> 9440 | AV5: =AR5*$B$15/4 -> 1357 | AW5: =SUM($AV$3:AV5) -> 4073.875 | AX5: =AR5-AS5-AU5-AW5 -> 455036.12 | AY5: =$B$36*V5 -> 1219 | AZ5: =SUM(AY5:AY5)*4/AR5 -> 0.010330508 | BA5: =SUM(AY5:AY5)/V5 -> 0.35 | BB5: =IF(MortgageRate="Discounted",_xlfn.XLOOKUP(L5,'mortgage-rates'!$A:$A,'mortgage-rates'!$E:$E)/100,_xlfn.XLOOKUP(L5,'mortgage-rates'!$A:$A,'mortgage-rates'!$D:$D)/100) -> 0.0722 | BC5: =BC4-BF4 -> 365122.84 | BD5: =IF($B$16*12/3-Q5+1>0,-PMT($BB5/4,$B$16*12/3-Q5+1,BC5),0) -> 7971.3596 | BE5: =BC5*($BB5/4) -> 6590.4673 | BF5: =BD5-BE5 -> 1380.8922 | BG5: =AT5+AY5+BD5 -> 9190.3596 | BH5: =INDEX(cpi!B:B,MATCH($L5,cpi!A:A)) -> 86.6 | BI5: =100*BH5/BH$3 -> 102.36407 | BJ5: =100*AC5/AC$3 -> 106.32765 | BK5: =100*AD5/AD$3 -> 109.40738 | BL5: =BJ5*GlobalPortfolio+BK5*AusPortfolio -> 107.25157 | BM5: =100*AE5/$AE$3 -> 116.22995 | BN5: =100*AR5/AR$3 -> 102.6087 | BO5: =100*AX5/AX$3 -> 101.49637
A6: Rent growth p.a. | B6: =((_xlfn.XLOOKUP(Q_end,L:L,U:U)/_xlfn.XLOOKUP(Q_start,L:L,U:U))^(1/YEARFRAC(EOMONTH(Q_start,-3)+1,EOMONTH(Q_end,0))))-1 -> 0.049766255 | L6: =DATE(YEAR(L5),MONTH(L5)+3,1) -> 39052 | M6: =AP6 -> 216879.36 | N6: =AX6-BC6 -> 109306.8 | O6: =M6/N6 -> 1.9841342 | P6: =X6/BG6 -> 0.3846743 | Q6: 4 | R6: =EOMONTH(L6,0)-EOMONTH(L6,-3) -> 92 | T6: =IF($B$10="3BR_H", INDEX('3BR_H-combined'!$C:$BH,MATCH($L6,'3BR_H-combined'!$B:$B,0),MATCH(Council_Area,'3BR_H-combined'!$C$1:$BH$1,0)), INDEX('2BR_F-combined'!$C:$BH,MATCH($L6,'2BR_F-combined'!$B:$B,0),MATCH(Council_Area,'2BR_F-combined'!$C$1:$BH$1,0))) -> 275 | U6: =IF(MOD(Q6,4)=1,T6,U5) -> 265 | V6: =U6*(R6)/7 -> 3482.8571 | W6: =$B$53/4*BH6/_xlfn.XLOOKUP(Q_end,cpi!A:A,cpi!B:B) -> 119.83414 | X6: =V6+W6 -> 3602.6913 | Y6: =BG6-X6 -> 5762.8713 | Z6: =Y6*$B$47 -> 1844.1188 | AA6: =(Y6+Z6)*eff_invest -> 7606.9901 | AB6: =AA6*(_xlfn.XLOOKUP(Q_end,cpi!A:A,cpi!B:B)/BH6) -> 12695.865 | AC6: {=INDEX('msci-indices'!C:C,MATCH($L6,'msci-indices'!$B:$B)-2)} -> 835.13401 | AD6: {=INDEX('msci-indices'!D:D,MATCH($L6,'msci-indices'!$B:$B)-2)} -> 801.24067 | AE6: =AI5+AA6 -> 198836.56 | AF6: {=INDEX('msci-indices'!C:C,MATCH($L6,'msci-indices'!$B:$B)+1)} -> 906.58022 | AG6: {=INDEX('msci-indices'!D:D,MATCH($L6,'msci-indices'!$B:$B)+1)} -> 885.32149 | AH6: =(InvestFees/4)*AE6 -> 124.27285 | AI6: =((AF6/AC6)*GlobalPortfolio+(AG6/AD6)*AusPortfolio)*AE6-AH6 -> 216879.36 | AJ6: =AJ5+AA6 -> 180955.38 | AK6: =AI6-AJ6 -> 35923.979 | AL6: =AJ6*(_xlfn.XLOOKUP(Q_end,cpi!A:A,cpi!B:B)/BH6) -> 302009.73 | AM6: {=SUMPRODUCT($AA$3:AA6,_xlfn.SORTBY($BH$3:BH6,_xlfn.SEQUENCE(ROWS($BH$3:BH6)),-1)/$BH$3)} -> 185180.17 | AN6: =AI6-AM6 -> 31699.196 | AO6: =IF($B$49="Real gains",MAX($B$50*AN6,0),IF($B$49="Discounted nominal gains",MAX($B$50*AK6/2,0),0)) -> 0 | AP6: =AI6-AO6 -> 216879.36 | AR6: =IF($B$10="3BR_H", INDEX('ns-combined'!$C:$BH,MATCH($L6,'ns-combined'!$B:$B,0),MATCH(Council_Area,'ns-combined'!$C$1:$BH$1,0))*1000, INDEX('s-combined'!$C:$BH,MATCH($L6,'s-combined'!$B:$B,0),MATCH(Council_Area,'s-combined'!$C$1:$BH$1,0))*1000) -> 493000 | AS6: =AS5+$AS$3 -> 4600 | AT6: 0 | AU6: =SUM($B$28:$B$29)*AR6 -> 9860 | AV6: =AR6*$B$15/4 -> 1417.375 | AW6: =SUM($AV$3:AV6) -> 5491.25 | AX6: =AR6-AS6-AU6-AW6 -> 473048.75 | AY6: =$B$36*V6 -> 1219 | AZ6: =SUM(AY6:AY6)*4/AR6 -> 0.0098904665 | BA6: =SUM(AY6:AY6)/V6 -> 0.35 | BB6: =IF(MortgageRate="Discounted",_xlfn.XLOOKUP(L6,'mortgage-rates'!$A:$A,'mortgage-rates'!$E:$E)/100,_xlfn.XLOOKUP(L6,'mortgage-rates'!$A:$A,'mortgage-rates'!$D:$D)/100) -> 0.0747 | BC6: =BC5-BF5 -> 363741.95 | BD6: =IF($B$16*12/3-Q6+1>0,-PMT($BB6/4,$B$16*12/3-Q6+1,BC6),0) -> 8146.5626 | BE6: =BC6*($BB6/4) -> 6792.8809 | BF6: =BD6-BE6 -> 1353.6817 | BG6: =AT6+AY6+BD6 -> 9365.5626 | BH6: =INDEX(cpi!B:B,MATCH($L6,cpi!A:A)) -> 86.7 | BI6: =100*BH6/BH$3 -> 102.48227 | BJ6: =100*AC6/AC$3 -> 110.63142 | BK6: =100*AD6/AD$3 -> 112.38287 | BL6: =BJ6*GlobalPortfolio+BK6*AusPortfolio -> 111.15685 | BM6: =100*AE6/$AE$3 -> 125.18822 | BN6: =100*AR6/AR$3 -> 107.17391 | BO6: =100*AX6/AX$3 -> 105.51411
A7: Investment index (country-weighted) growth p.a. | B7: =((_xlfn.XLOOKUP(Q_end,L:L,BL:BL)/_xlfn.XLOOKUP(Q_start,L:L,BL:BL))^(1/YEARFRAC(EOMONTH(Q_start,-3)+1,EOMONTH(Q_end,0))))-1 -> 0.080631422 | L7: =DATE(YEAR(L6),MONTH(L6)+3,1) -> 39142 | M7: =AP7 -> 233286.98 | N7: =AX7-BC7 -> 87573.481 | O7: =M7/N7 -> 2.6638999 | P7: =X7/BG7 -> 0.39545095 | Q7: 5 | R7: =EOMONTH(L7,0)-EOMONTH(L7,-3) -> 90 | T7: =IF($B$10="3BR_H", INDEX('3BR_H-combined'!$C:$BH,MATCH($L7,'3BR_H-combined'!$B:$B,0),MATCH(Council_Area,'3BR_H-combined'!$C$1:$BH$1,0)), INDEX('2BR_F-combined'!$C:$BH,MATCH($L7,'2BR_F-combined'!$B:$B,0),MATCH(Council_Area,'2BR_F-combined'!$C$1:$BH$1,0))) -> 280 | U7: =IF(MOD(Q7,4)=1,T7,U6) -> 280 | V7: =U7*(R7)/7 -> 3600 | W7: =$B$53/4*BH7/_xlfn.XLOOKUP(Q_end,cpi!A:A,cpi!B:B) -> 119.83414 | X7: =V7+W7 -> 3719.8341 | Y7: =BG7-X7 -> 5686.7285 | Z7: =Y7*$B$47 -> 1819.7531 | AA7: =(Y7+Z7)*eff_invest -> 7506.4816 | AB7: =AA7*(_xlfn.XLOOKUP(Q_end,cpi!A:A,cpi!B:B)/BH7) -> 12528.119 | AC7: {=INDEX('msci-indices'!C:C,MATCH($L7,'msci-indices'!$B:$B)-2)} -> 906.58022 | AD7: {=INDEX('msci-indices'!D:D,MATCH($L7,'msci-indices'!$B:$B)-2)} -> 885.32149 | AE7: =AI6+AA7 -> 224385.84 | AF7: {=INDEX('msci-indices'!C:C,MATCH($L7,'msci-indices'!$B:$B)+1)} -> 932.09759 | AG7: {=INDEX('msci-indices'!D:D,MATCH($L7,'msci-indices'!$B:$B)+1)} -> 946.08734 | AH7: =(InvestFees/4)*AE7 -> 140.24115 | AI7: =((AF7/AC7)*GlobalPortfolio+(AG7/AD7)*AusPortfolio)*AE7-AH7 -> 233286.98 | AJ7: =AJ6+AA7 -> 188461.86 | AK7: =AI7-AJ7 -> 44825.12 | AL7: =AJ7*(_xlfn.XLOOKUP(Q_end,cpi!A:A,cpi!B:B)/BH7) -> 314537.85 | AM7: {=SUMPRODUCT($AA$3:AA7,_xlfn.SORTBY($BH$3:BH7,_xlfn.SEQUENCE(ROWS($BH$3:BH7)),-1)/$BH$3)} -> 192873.01 | AN7: =AI7-AM7 -> 40413.972 | AO7: =IF($B$49="Real gains",MAX($B$50*AN7,0),IF($B$49="Discounted nominal gains",MAX($B$50*AK7/2,0),0)) -> 0 | AP7: =AI7-AO7 -> 233286.98 | AR7: =IF($B$10="3BR_H", INDEX('ns-combined'!$C:$BH,MATCH($L7,'ns-combined'!$B:$B,0),MATCH(Council_Area,'ns-combined'!$C$1:$BH$1,0))*1000, INDEX('s-combined'!$C:$BH,MATCH($L7,'s-combined'!$B:$B,0),MATCH(Council_Area,'s-combined'!$C$1:$BH$1,0))*1000) -> 472000 | AS7: =AS6+$AS$3 -> 5750 | AT7: 0 | AU7: =SUM($B$28:$B$29)*AR7 -> 9440 | AV7: =AR7*$B$15/4 -> 1357 | AW7: =SUM($AV$3:AV7) -> 6848.25 | AX7: =AR7-AS7-AU7-AW7 -> 449961.75 | AY7: =$B$36*V7 -> 1260 | AZ7: =SUM(AY7:AY7)*4/AR7 -> 0.010677966 | BA7: =SUM(AY7:AY7)/V7 -> 0.35 | BB7: =IF(MortgageRate="Discounted",_xlfn.XLOOKUP(L7,'mortgage-rates'!$A:$A,'mortgage-rates'!$E:$E)/100,_xlfn.XLOOKUP(L7,'mortgage-rates'!$A:$A,'mortgage-rates'!$D:$D)/100) -> 0.0747 | BC7: =BC6-BF6 -> 362388.27 | BD7: =IF($B$16*12/3-Q7+1>0,-PMT($BB7/4,$B$16*12/3-Q7+1,BC7),0) -> 8146.5626 | BE7: =BC7*($BB7/4) -> 6767.6009 | BF7: =BD7-BE7 -> 1378.9617 | BG7: =AT7+AY7+BD7 -> 9406.5626 | BH7: =INDEX(cpi!B:B,MATCH($L7,cpi!A:A)) -> 86.7 | BI7: =100*BH7/BH$3 -> 102.48227 | BJ7: =100*AC7/AC$3 -> 120.096 | BK7: =100*AD7/AD$3 -> 124.17613 | BL7: =BJ7*GlobalPortfolio+BK7*AusPortfolio -> 121.32004 | BM7: =100*AE7/$AE$3 -> 141.27414 | BN7: =100*AR7/AR$3 -> 102.6087 | BO7: =100*AX7/AX$3 -> 100.36452
A8: CPI growth p.a. | B8: =((_xlfn.XLOOKUP(Q_end,L:L,BI:BI)/_xlfn.XLOOKUP(Q_start,L:L,BI:BI))^(1/YEARFRAC(EOMONTH(Q_start,-3)+1,EOMONTH(Q_end,0))))-1 -> 0.027199758 | L8: =DATE(YEAR(L7),MONTH(L7)+3,1) -> 39234 | M8: =AP8 -> 255575.37 | N8: =AX8-BC8 -> 113804.94 | O8: =M8/N8 -> 2.2457317 | P8: =X8/BG8 -> 0.39925602 | Q8: 6 | R8: =EOMONTH(L8,0)-EOMONTH(L8,-3) -> 91 | T8: =IF($B$10="3BR_H", INDEX('3BR_H-combined'!$C:$BH,MATCH($L8,'3BR_H-combined'!$B:$B,0),MATCH(Council_Area,'3BR_H-combined'!$C$1:$BH$1,0)), INDEX('2BR_F-combined'!$C:$BH,MATCH($L8,'2BR_F-combined'!$B:$B,0),MATCH(Council_Area,'2BR_F-combined'!$C$1:$BH$1,0))) -> 280 | U8: =IF(MOD(Q8,4)=1,T8,U7) -> 280 | V8: =U8*(R8)/7 -> 3640 | W8: =$B$53/4*BH8/_xlfn.XLOOKUP(Q_end,cpi!A:A,cpi!B:B) -> 121.21631 | X8: =V8+W8 -> 3761.2163 | Y8: =BG8-X8 -> 5659.3463 | Z8: =Y8*$B$47 -> 1810.9908 | AA8: =(Y8+Z8)*eff_invest -> 7470.3371 | AB8: =AA8*(_xlfn.XLOOKUP(Q_end,cpi!A:A,cpi!B:B)/BH8) -> 12325.63 | AC8: {=INDEX('msci-indices'!C:C,MATCH($L8,'msci-indices'!$B:$B)-2)} -> 932.09759 | AD8: {=INDEX('msci-indices'!D:D,MATCH($L8,'msci-indices'!$B:$B)-2)} -> 946.08734 | AE8: =AI7+AA8 -> 240757.32 | AF8: {=INDEX('msci-indices'!C:C,MATCH($L8,'msci-indices'!$B:$B)+1)} -> 991.70582 | AG8: {=INDEX('msci-indices'!D:D,MATCH($L8,'msci-indices'!$B:$B)+1)} -> 1000.9831 | AH8: =(InvestFees/4)*AE8 -> 150.47333 | AI8: =((AF8/AC8)*GlobalPortfolio+(AG8/AD8)*AusPortfolio)*AE8-AH8 -> 255575.37 | AJ8: =AJ7+AA8 -> 195932.2 | AK8: =AI8-AJ8 -> 59643.165 | AL8: =AJ8*(_xlfn.XLOOKUP(Q_end,cpi!A:A,cpi!B:B)/BH8) -> 323276.96 | AM8: {=SUMPRODUCT($AA$3:AA8,_xlfn.SORTBY($BH$3:BH8,_xlfn.SEQUENCE(ROWS($BH$3:BH8)),-1)/$BH$3)} -> 202407.78 | AN8: =AI8-AM8 -> 53167.584 | AO8: =IF($B$49="Real gains",MAX($B$50*AN8,0),IF($B$49="Discounted nominal gains",MAX($B$50*AK8/2,0),0)) -> 0 | AP8: =AI8-AO8 -> 255575.37 | AR8: =IF($B$10="3BR_H", INDEX('ns-combined'!$C:$BH,MATCH($L8,'ns-combined'!$B:$B,0),MATCH(Council_Area,'ns-combined'!$C$1:$BH$1,0))*1000, INDEX('s-combined'!$C:$BH,MATCH($L8,'s-combined'!$B:$B,0),MATCH(Council_Area,'s-combined'!$C$1:$BH$1,0))*1000) -> 500000 | AS8: =AS7+$AS$3 -> 6900 | AT8: 0 | AU8: =SUM($B$28:$B$29)*AR8 -> 10000 | AV8: =AR8*$B$15/4 -> 1437.5 | AW8: =SUM($AV$3:AV8) -> 8285.75 | AX8: =AR8-AS8-AU8-AW8 -> 474814.25 | AY8: =$B$36*V8 -> 1274 | AZ8: =SUM(AY8:AY8)*4/AR8 -> 0.010192 | BA8: =SUM(AY8:AY8)/V8 -> 0.35 | BB8: =IF(MortgageRate="Discounted",_xlfn.XLOOKUP(L8,'mortgage-rates'!$A:$A,'mortgage-rates'!$E:$E)/100,_xlfn.XLOOKUP(L8,'mortgage-rates'!$A:$A,'mortgage-rates'!$D:$D)/100) -> 0.0747 | BC8: =BC7-BF7 -> 361009.31 | BD8: =IF($B$16*12/3-Q8+1>0,-PMT($BB8/4,$B$16*12/3-Q8+1,BC8),0) -> 8146.5626 | BE8: =BC8*($BB8/4) -> 6741.8488 | BF8: =BD8-BE8 -> 1404.7138 | BG8: =AT8+AY8+BD8 -> 9420.5626 | BH8: =INDEX(cpi!B:B,MATCH($L8,cpi!A:A)) -> 87.7 | BI8: =100*BH8/BH$3 -> 103.6643 | BJ8: =100*AC8/AC$3 -> 123.47632 | BK8: =100*AD8/AD$3 -> 132.69921 | BL8: =BJ8*GlobalPortfolio+BK8*AusPortfolio -> 126.24319 | BM8: =100*AE8/$AE$3 -> 151.58168 | BN8: =100*AR8/AR$3 -> 108.69565 | BO8: =100*AX8/AX$3 -> 105.9079
L9: =DATE(YEAR(L8),MONTH(L8)+3,1) -> 39326 | M9: =AP9 -> 271190.09 | N9: =AX9-BC9 -> 113599.28 | O9: =M9/N9 -> 2.3872518 | P9: =X9/BG9 -> 0.39570697 | Q9: 7 | R9: =EOMONTH(L9,0)-EOMONTH(L9,-3) -> 92 | T9: =IF($B$10="3BR_H", INDEX('3BR_H-combined'!$C:$BH,MATCH($L9,'3BR_H-combined'!$B:$B,0),MATCH(Council_Area,'3BR_H-combined'!$C$1:$BH$1,0)), INDEX('2BR_F-combined'!$C:$BH,MATCH($L9,'2BR_F-combined'!$B:$B,0),MATCH(Council_Area,'2BR_F-combined'!$C$1:$BH$1,0))) -> 295 | U9: =IF(MOD(Q9,4)=1,T9,U8) -> 280 | V9: =U9*(R9)/7 -> 3680 | W9: =$B$53/4*BH9/_xlfn.XLOOKUP(Q_end,cpi!A:A,cpi!B:B) -> 121.90739 | X9: =V9+W9 -> 3801.9074 | Y9: =BG9-X9 -> 5805.9784 | Z9: =Y9*$B$47 -> 1857.9131 | AA9: =(Y9+Z9)*eff_invest -> 7663.8914 | AB9: =AA9*(_xlfn.XLOOKUP(Q_end,cpi!A:A,cpi!B:B)/BH9) -> 12573.3 | AC9: {=INDEX('msci-indices'!C:C,MATCH($L9,'msci-indices'!$B:$B)-2)} -> 991.70582 | AD9: {=INDEX('msci-indices'!D:D,MATCH($L9,'msci-indices'!$B:$B)-2)} -> 1000.9831 | AE9: =AI8+AA9 -> 263239.26 | AF9: {=INDEX('msci-indices'!C:C,MATCH($L9,'msci-indices'!$B:$B)+1)} -> 1009.8701 | AG9: {=INDEX('msci-indices'!D:D,MATCH($L9,'msci-indices'!$B:$B)+1)} -> 1061.067 | AH9: =(InvestFees/4)*AE9 -> 164.52454 | AI9: =((AF9/AC9)*GlobalPortfolio+(AG9/AD9)*AusPortfolio)*AE9-AH9 -> 271190.09 | AJ9: =AJ8+AA9 -> 203596.09 | AK9: =AI9-AJ9 -> 67593.998 | AL9: =AJ9*(_xlfn.XLOOKUP(Q_end,cpi!A:A,cpi!B:B)/BH9) -> 334017.63 | AM9: {=SUMPRODUCT($AA$3:AA9,_xlfn.SORTBY($BH$3:BH9,_xlfn.SEQUENCE(ROWS($BH$3:BH9)),-1)/$BH$3)} -> 211280.71 | AN9: =AI9-AM9 -> 59909.385 | AO9: =IF($B$49="Real gains",MAX($B$50*AN9,0),IF($B$49="Discounted nominal gains",MAX($B$50*AK9/2,0),0)) -> 0 | AP9: =AI9-AO9 -> 271190.09 | AR9: =IF($B$10="3BR_H", INDEX('ns-combined'!$C:$BH,MATCH($L9,'ns-combined'!$B:$B,0),MATCH(Council_Area,'ns-combined'!$C$1:$BH$1,0))*1000, INDEX('s-combined'!$C:$BH,MATCH($L9,'s-combined'!$B:$B,0),MATCH(Council_Area,'s-combined'!$C$1:$BH$1,0))*1000) -> 501000 | AS9: =AS8+$AS$3 -> 8050 | AT9: 0 | AU9: =SUM($B$28:$B$29)*AR9 -> 10020 | AV9: =AR9*$B$15/4 -> 1440.375 | AW9: =SUM($AV$3:AV9) -> 9726.125 | AX9: =AR9-AS9-AU9-AW9 -> 473203.88 | AY9: =$B$36*V9 -> 1288 | AZ9: =SUM(AY9:AY9)*4/AR9 -> 0.010283433 | BA9: =SUM(AY9:AY9)/V9 -> 0.35 | BB9: =IF(MortgageRate="Discounted",_xlfn.XLOOKUP(L9,'mortgage-rates'!$A:$A,'mortgage-rates'!$E:$E)/100,_xlfn.XLOOKUP(L9,'mortgage-rates'!$A:$A,'mortgage-rates'!$D:$D)/100) -> 0.0772 | BC9: =BC8-BF8 -> 359604.59 | BD9: =IF($B$16*12/3-Q9+1>0,-PMT($BB9/4,$B$16*12/3-Q9+1,BC9),0) -> 8319.8858 | BE9: =BC9*($BB9/4) -> 6940.3687 | BF9: =BD9-BE9 -> 1379.5171 | BG9: =AT9+AY9+BD9 -> 9607.8858 | BH9: =INDEX(cpi!B:B,MATCH($L9,cpi!A:A)) -> 88.2 | BI9: =100*BH9/BH$3 -> 104.25532 | BJ9: =100*AC9/AC$3 -> 131.37271 | BK9: =100*AD9/AD$3 -> 140.39895 | BL9: =BJ9*GlobalPortfolio+BK9*AusPortfolio -> 134.08059 | BM9: =100*AE9/$AE$3 -> 165.73639 | BN9: =100*AR9/AR$3 -> 108.91304 | BO9: =100*AX9/AX$3 -> 105.54871
A10: Dwelling type (3br house, 3BR_H; or 2br flat, 2BR_F) | B10: 3BR_H | C10: 3BR_H | L10: =DATE(YEAR(L9),MONTH(L9)+3,1) -> 39417 | M10: =AP10 -> 271364.42 | N10: =AX10-BC10 -> 140725.05 | O10: =M10/N10 -> 1.9283306 | P10: =X10/BG10 -> 0.38883535 | Q10: 8 | R10: =EOMONTH(L10,0)-EOMONTH(L10,-3) -> 92 | T10: =IF($B$10="3BR_H", INDEX('3BR_H-combined'!$C:$BH,MATCH($L10,'3BR_H-combined'!$B:$B,0),MATCH(Council_Area,'3BR_H-combined'!$C$1:$BH$1,0)), INDEX('2BR_F-combined'!$C:$BH,MATCH($L10,'2BR_F-combined'!$B:$B,0),MATCH(Council_Area,'2BR_F-combined'!$C$1:$BH$1,0))) -> 310 | U10: =IF(MOD(Q10,4)=1,T10,U9) -> 280 | V10: =U10*(R10)/7 -> 3680 | W10: =$B$53/4*BH10/_xlfn.XLOOKUP(Q_end,cpi!A:A,cpi!B:B) -> 123.42778 | X10: =V10+W10 -> 3803.4278 | Y10: =BG10-X10 -> 5978.1617 | Z10: =Y10*$B$47 -> 1913.0117 | AA10: =(Y10+Z10)*eff_invest -> 7891.1734 | AB10: =AA10*(_xlfn.XLOOKUP(Q_end,cpi!A:A,cpi!B:B)/BH10) -> 12786.705 | AC10: {=INDEX('msci-indices'!C:C,MATCH($L10,'msci-indices'!$B:$B)-2)} -> 1009.8701 | AD10: {=INDEX('msci-indices'!D:D,MATCH($L10,'msci-indices'!$B:$B)-2)} -> 1061.067 | AE10: =AI9+AA10 -> 279081.26 | AF10: {=INDEX('msci-indices'!C:C,MATCH($L10,'msci-indices'!$B:$B)+1)} -> 983.50383 | AG10: {=INDEX('msci-indices'!D:D,MATCH($L10,'msci-indices'!$B:$B)+1)} -> 1030.1196 | AH10: =(InvestFees/4)*AE10 -> 174.42579 | AI10: =((AF10/AC10)*GlobalPortfolio+(AG10/AD10)*AusPortfolio)*AE10-AH10 -> 271364.42 | AJ10: =AJ9+AA10 -> 211487.27 | AK10: =AI10-AJ10 -> 59877.149 | AL10: =AJ10*(_xlfn.XLOOKUP(Q_end,cpi!A:A,cpi!B:B)/BH10) -> 342689.89 | AM10: {=SUMPRODUCT($AA$3:AA10,_xlfn.SORTBY($BH$3:BH10,_xlfn.SEQUENCE(ROWS($BH$3:BH10)),-1)/$BH$3)} -> 221554.9 | AN10: =AI10-AM10 -> 49809.52 | AO10: =IF($B$49="Real gains",MAX($B$50*AN10,0),IF($B$49="Discounted nominal gains",MAX($B$50*AK10/2,0),0)) -> 0 | AP10: =AI10-AO10 -> 271364.42 | AR10: =IF($B$10="3BR_H", INDEX('ns-combined'!$C:$BH,MATCH($L10,'ns-combined'!$B:$B,0),MATCH(Council_Area,'ns-combined'!$C$1:$BH$1,0))*1000, INDEX('s-combined'!$C:$BH,MATCH($L10,'s-combined'!$B:$B,0),MATCH(Council_Area,'s-combined'!$C$1:$BH$1,0))*1000) -> 530000 | AS10: =AS9+$AS$3 -> 9200 | AT10: 0 | AU10: =SUM($B$28:$B$29)*AR10 -> 10600 | AV10: =AR10*$B$15/4 -> 1523.75 | AW10: =SUM($AV$3:AV10) -> 11249.875 | AX10: =AR10-AS10-AU10-AW10 -> 498950.12 | AY10: =$B$36*V10 -> 1288 | AZ10: =SUM(AY10:AY10)*4/AR10 -> 0.0097207547 | BA10: =SUM(AY10:AY10)/V10 -> 0.35 | BB10: =IF(MortgageRate="Discounted",_xlfn.XLOOKUP(L10,'mortgage-rates'!$A:$A,'mortgage-rates'!$E:$E)/100,_xlfn.XLOOKUP(L10,'mortgage-rates'!$A:$A,'mortgage-rates'!$D:$D)/100) -> 0.0797 | BC10: =BC9-BF9 -> 358225.08 | BD10: =IF($B$16*12/3-Q10+1>0,-PMT($BB10/4,$B$16*12/3-Q10+1,BC10),0) -> 8493.5894 | BE10: =BC10*($BB10/4) -> 7137.6347 | BF10: =BD10-BE10 -> 1355.9548 | BG10: =AT10+AY10+BD10 -> 9781.5894 | BH10: =INDEX(cpi!B:B,MATCH($L10,cpi!A:A)) -> 89.3 | BI10: =100*BH10/BH$3 -> 105.55556 | BJ10: =100*AC10/AC$3 -> 133.77897 | BK10: =100*AD10/AD$3 -> 148.82639 | BL10: =BJ10*GlobalPortfolio+BK10*AusPortfolio -> 138.29319 | BM10: =100*AE10/$AE$3 -> 175.71058 | BN10: =100*AR10/AR$3 -> 115.21739 | BO10: =100*AX10/AX$3 -> 111.29144
A11: Analysis start quarter | B11: 38777 | C11: 38777 | L11: =DATE(YEAR(L10),MONTH(L10)+3,1) -> 39508 | M11: =AP11 -> 249614.15 | N11: =AX11-BC11 -> 95436.628 | O11: =M11/N11 -> 2.6154964 | P11: =X11/BG11 -> 0.40957642 | Q11: 9 | R11: =EOMONTH(L11,0)-EOMONTH(L11,-3) -> 91 | T11: =IF($B$10="3BR_H", INDEX('3BR_H-combined'!$C:$BH,MATCH($L11,'3BR_H-combined'!$B:$B,0),MATCH(Council_Area,'3BR_H-combined'!$C$1:$BH$1,0)), INDEX('2BR_F-combined'!$C:$BH,MATCH($L11,'2BR_F-combined'!$B:$B,0),MATCH(Council_Area,'2BR_F-combined'!$C$1:$BH$1,0))) -> 320 | U11: =IF(MOD(Q11,4)=1,T11,U10) -> 320 | V11: =U11*(R11)/7 -> 4160 | W11: =$B$53/4*BH11/_xlfn.XLOOKUP(Q_end,cpi!A:A,cpi!B:B) -> 124.94817 | X11: =V11+W11 -> 4284.9482 | Y11: =BG11-X11 -> 6176.9534 | Z11: =Y11*$B$47 -> 1976.6251 | AA11: =(Y11+Z11)*eff_invest -> 8153.5784 | AB11: =AA11*(_xlfn.XLOOKUP(Q_end,cpi!A:A,cpi!B:B)/BH11) -> 13051.137 | AC11: {=INDEX('msci-indices'!C:C,MATCH($L11,'msci-indices'!$B:$B)-2)} -> 983.50383 | AD11: {=INDEX('msci-indices'!D:D,MATCH($L11,'msci-indices'!$B:$B)-2)} -> 1030.1196 | AE11: =AI10+AA11 -> 279517.99 | AF11: {=INDEX('msci-indices'!C:C,MATCH($L11,'msci-indices'!$B:$B)+1)} -> 894.99836 | AG11: {=INDEX('msci-indices'!D:D,MATCH($L11,'msci-indices'!$B:$B)+1)} -> 881.21373 | AH11: =(InvestFees/4)*AE11 -> 174.69875 | AI11: =((AF11/AC11)*GlobalPortfolio+(AG11/AD11)*AusPortfolio)*AE11-AH11 -> 249614.15 | AJ11: =AJ10+AA11 -> 219640.85 | AK11: =AI11-AJ11 -> 29973.31 | AL11: =AJ11*(_xlfn.XLOOKUP(Q_end,cpi!A:A,cpi!B:B)/BH11) -> 351571.13 | AM11: {=SUMPRODUCT($AA$3:AA11,_xlfn.SORTBY($BH$3:BH11,_xlfn.SEQUENCE(ROWS($BH$3:BH11)),-1)/$BH$3)} -> 232193.52 | AN11: =AI11-AM11 -> 17420.634 | AO11: =IF($B$49="Real gains",MAX($B$50*AN11,0),IF($B$49="Discounted nominal gains",MAX($B$50*AK11/2,0),0)) -> 0 | AP11: =AI11-AO11 -> 249614.15 | AR11: =IF($B$10="3BR_H", INDEX('ns-combined'!$C:$BH,MATCH($L11,'ns-combined'!$B:$B,0),MATCH(Council_Area,'ns-combined'!$C$1:$BH$1,0))*1000, INDEX('s-combined'!$C:$BH,MATCH($L11,'s-combined'!$B:$B,0),MATCH(Council_Area,'s-combined'!$C$1:$BH$1,0))*1000) -> 485000 | AS11: =AS10+$AS$3 -> 10350 | AT11: 0 | AU11: =SUM($B$28:$B$29)*AR11 -> 9700 | AV11: =AR11*$B$15/4 -> 1394.375 | AW11: =SUM($AV$3:AV11) -> 12644.25 | AX11: =AR11-AS11-AU11-AW11 -> 452305.75 | AY11: =$B$36*V11 -> 1456 | AZ11: =SUM(AY11:AY11)*4/AR11 -> 0.012008247 | BA11: =SUM(AY11:AY11)/V11 -> 0.35 | BB11: =IF(MortgageRate="Discounted",_xlfn.XLOOKUP(L11,'mortgage-rates'!$A:$A,'mortgage-rates'!$E:$E)/100,_xlfn.XLOOKUP(L11,'mortgage-rates'!$A:$A,'mortgage-rates'!$D:$D)/100) -> 0.087 | BC11: =BC10-BF10 -> 356869.12 | BD11: =IF($B$16*12/3-Q11+1>0,-PMT($BB11/4,$B$16*12/3-Q11+1,BC11),0) -> 9005.9015 | BE11: =BC11*($BB11/4) -> 7761.9034 | BF11: =BD11-BE11 -> 1243.9981 | BG11: =AT11+AY11+BD11 -> 10461.902 | BH11: =INDEX(cpi!B:B,MATCH($L11,cpi!A:A)) -> 90.4 | BI11: =100*BH11/BH$3 -> 106.85579 | BJ11: =100*AC11/AC$3 -> 130.28618 | BK11: =100*AD11/AD$3 -> 144.48568 | BL11: =BJ11*GlobalPortfolio+BK11*AusPortfolio -> 134.54603 | BM11: =100*AE11/$AE$3 -> 175.98554 | BN11: =100*AR11/AR$3 -> 105.43478 | BO11: =100*AX11/AX$3 -> 100.88735
A12: Analysis end quarter | B12: 45992 | C12: 45992 | L12: =DATE(YEAR(L11),MONTH(L11)+3,1) -> 39600 | M12: =AP12 -> 253859.37 | N12: =AX12-BC12 -> 107816 | O12: =M12/N12 -> 2.3545612 | P12: =X12/BG12 -> 0.40589362 | Q12: 10 | R12: =EOMONTH(L12,0)-EOMONTH(L12,-3) -> 91 | T12: =IF($B$10="3BR_H", INDEX('3BR_H-combined'!$C:$BH,MATCH($L12,'3BR_H-combined'!$B:$B,0),MATCH(Council_Area,'3BR_H-combined'!$C$1:$BH$1,0)), INDEX('2BR_F-combined'!$C:$BH,MATCH($L12,'2BR_F-combined'!$B:$B,0),MATCH(Council_Area,'2BR_F-combined'!$C$1:$BH$1,0))) -> 330 | U12: =IF(MOD(Q12,4)=1,T12,U11) -> 320 | V12: =U12*(R12)/7 -> 4160 | W12: =$B$53/4*BH12/_xlfn.XLOOKUP(Q_end,cpi!A:A,cpi!B:B) -> 126.60677 | X12: =V12+W12 -> 4286.6068 | Y12: =BG12-X12 -> 6274.3051 | Z12: =Y12*$B$47 -> 2007.7776 | AA12: =(Y12+Z12)*eff_invest -> 8282.0827 | AB12: =AA12*(_xlfn.XLOOKUP(Q_end,cpi!A:A,cpi!B:B)/BH12) -> 13083.159 | AC12: {=INDEX('msci-indices'!C:C,MATCH($L12,'msci-indices'!$B:$B)-2)} -> 894.99836 | AD12: {=INDEX('msci-indices'!D:D,MATCH($L12,'msci-indices'!$B:$B)-2)} -> 881.21373 | AE12: =AI11+AA12 -> 257896.24 | AF12: {=INDEX('msci-indices'!C:C,MATCH($L12,'msci-indices'!$B:$B)+1)} -> 881.79174 | AG12: {=INDEX('msci-indices'!D:D,MATCH($L12,'msci-indices'!$B:$B)+1)} -> 867.41147 | AH12: =(InvestFees/4)*AE12 -> 161.18515 | AI12: =((AF12/AC12)*GlobalPortfolio+(AG12/AD12)*AusPortfolio)*AE12-AH12 -> 253859.37 | AJ12: =AJ11+AA12 -> 227922.93 | AK12: =AI12-AJ12 -> 25936.445 | AL12: =AJ12*(_xlfn.XLOOKUP(Q_end,cpi!A:A,cpi!B:B)/BH12) -> 360048.56 | AM12: {=SUMPRODUCT($AA$3:AA12,_xlfn.SORTBY($BH$3:BH12,_xlfn.SEQUENCE(ROWS($BH$3:BH12)),-1)/$BH$3)} -> 243250.62 | AN12: =AI12-AM12 -> 10608.756 | AO12: =IF($B$49="Real gains",MAX($B$50*AN12,0),IF($B$49="Discounted nominal gains",MAX($B$50*AK12/2,0),0)) -> 0 | AP12: =AI12-AO12 -> 253859.37 | AR12: =IF($B$10="3BR_H", INDEX('ns-combined'!$C:$BH,MATCH($L12,'ns-combined'!$B:$B,0),MATCH(Council_Area,'ns-combined'!$C$1:$BH$1,0))*1000, INDEX('s-combined'!$C:$BH,MATCH($L12,'s-combined'!$B:$B,0),MATCH(Council_Area,'s-combined'!$C$1:$BH$1,0))*1000) -> 499000 | AS12: =AS11+$AS$3 -> 11500 | AT12: 0 | AU12: =SUM($B$28:$B$29)*AR12 -> 9980 | AV12: =AR12*$B$15/4 -> 1434.625 | AW12: =SUM($AV$3:AV12) -> 14078.875 | AX12: =AR12-AS12-AU12-AW12 -> 463441.12 | AY12: =$B$36*V12 -> 1456 | AZ12: =SUM(AY12:AY12)*4/AR12 -> 0.011671343 | BA12: =SUM(AY12:AY12)/V12 -> 0.35 | BB12: =IF(MortgageRate="Discounted",_xlfn.XLOOKUP(L12,'mortgage-rates'!$A:$A,'mortgage-rates'!$E:$E)/100,_xlfn.XLOOKUP(L12,'mortgage-rates'!$A:$A,'mortgage-rates'!$D:$D)/100) -> 0.0884 | BC12: =BC11-BF11 -> 355625.12 | BD12: =IF($B$16*12/3-Q12+1>0,-PMT($BB12/4,$B$16*12/3-Q12+1,BC12),0) -> 9104.9118 | BE12: =BC12*($BB12/4) -> 7859.3152 | BF12: =BD12-BE12 -> 1245.5966 | BG12: =AT12+AY12+BD12 -> 10560.912 | BH12: =INDEX(cpi!B:B,MATCH($L12,cpi!A:A)) -> 91.6 | BI12: =100*BH12/BH$3 -> 108.27423 | BJ12: =100*AC12/AC$3 -> 118.56173 | BK12: =100*AD12/AD$3 -> 123.59997 | BL12: =BJ12*GlobalPortfolio+BK12*AusPortfolio -> 120.07321 | BM12: =100*AE12/$AE$3 -> 162.37241 | BN12: =100*AR12/AR$3 -> 108.47826 | BO12: =100*AX12/AX$3 -> 103.37111
A13: Council/Area | B13: Greater Sydney | C13: Greater Sydney | L13: =DATE(YEAR(L12),MONTH(L12)+3,1) -> 39692 | M13: =AP13 -> 225654.89 | N13: =AX13-BC13 -> 78140.348 | O13: =M13/N13 -> 2.8878153 | P13: =X13/BG13 -> 0.41192349 | Q13: 11 | R13: =EOMONTH(L13,0)-EOMONTH(L13,-3) -> 92 | T13: =IF($B$10="3BR_H", INDEX('3BR_H-combined'!$C:$BH,MATCH($L13,'3BR_H-combined'!$B:$B,0),MATCH(Council_Area,'3BR_H-combined'!$C$1:$BH$1,0)), INDEX('2BR_F-combined'!$C:$BH,MATCH($L13,'2BR_F-combined'!$B:$B,0),MATCH(Council_Area,'2BR_F-combined'!$C$1:$BH$1,0))) -> 347.5 | U13: =IF(MOD(Q13,4)=1,T13,U12) -> 320 | V13: =U13*(R13)/7 -> 4205.7143 | W13: =$B$53/4*BH13/_xlfn.XLOOKUP(Q_end,cpi!A:A,cpi!B:B) -> 127.98894 | X13: =V13+W13 -> 4333.7032 | Y13: =BG13-X13 -> 6186.9476 | Z13: =Y13*$B$47 -> 1979.8232 | AA13: =(Y13+Z13)*eff_invest -> 8166.7708 | AB13: =AA13*(_xlfn.XLOOKUP(Q_end,cpi!A:A,cpi!B:B)/BH13) -> 12761.682 | AC13: {=INDEX('msci-indices'!C:C,MATCH($L13,'msci-indices'!$B:$B)-2)} -> 881.79174 | AD13: {=INDEX('msci-indices'!D:D,MATCH($L13,'msci-indices'!$B:$B)-2)} -> 867.41147 | AE13: =AI12+AA13 -> 262026.14 | AF13: {=INDEX('msci-indices'!C:C,MATCH($L13,'msci-indices'!$B:$B)+1)} -> 747.65998 | AG13: {=INDEX('msci-indices'!D:D,MATCH($L13,'msci-indices'!$B:$B)+1)} -> 775.74397 | AH13: =(InvestFees/4)*AE13 -> 163.76634 | AI13: =((AF13/AC13)*GlobalPortfolio+(AG13/AD13)*AusPortfolio)*AE13-AH13 -> 225654.89 | AJ13: =AJ12+AA13 -> 236089.7 | AK13: =AI13-AJ13 -> -10434.809 | AL13: =AJ13*(_xlfn.XLOOKUP(Q_end,cpi!A:A,cpi!B:B)/BH13) -> 368922.02 | AM13: {=SUMPRODUCT($AA$3:AA13,_xlfn.SORTBY($BH$3:BH13,_xlfn.SEQUENCE(ROWS($BH$3:BH13)),-1)/$BH$3)} -> 253927.66 | AN13: =AI13-AM13 -> -28272.77 | AO13: =IF($B$49="Real gains",MAX($B$50*AN13,0),IF($B$49="Discounted nominal gains",MAX($B$50*AK13/2,0),0)) -> 0 | AP13: =AI13-AO13 -> 225654.89 | AR13: =IF($B$10="3BR_H", INDEX('ns-combined'!$C:$BH,MATCH($L13,'ns-combined'!$B:$B,0),MATCH(Council_Area,'ns-combined'!$C$1:$BH$1,0))*1000, INDEX('s-combined'!$C:$BH,MATCH($L13,'s-combined'!$B:$B,0),MATCH(Council_Area,'s-combined'!$C$1:$BH$1,0))*1000) -> 470000 | AS13: =AS12+$AS$3 -> 12650 | AT13: 0 | AU13: =SUM($B$28:$B$29)*AR13 -> 9400 | AV13: =AR13*$B$15/4 -> 1351.25 | AW13: =SUM($AV$3:AV13) -> 15430.125 | AX13: =AR13-AS13-AU13-AW13 -> 432519.88 | AY13: =$B$36*V13 -> 1472 | AZ13: =SUM(AY13:AY13)*4/AR13 -> 0.01252766 | BA13: =SUM(AY13:AY13)/V13 -> 0.35 | BB13: =IF(MortgageRate="Discounted",_xlfn.XLOOKUP(L13,'mortgage-rates'!$A:$A,'mortgage-rates'!$E:$E)/100,_xlfn.XLOOKUP(L13,'mortgage-rates'!$A:$A,'mortgage-rates'!$D:$D)/100) -> 0.0876 | BC13: =BC12-BF12 -> 354379.53 | BD13: =IF($B$16*12/3-Q13+1>0,-PMT($BB13/4,$B$16*12/3-Q13+1,BC13),0) -> 9048.6508 | BE13: =BC13*($BB13/4) -> 7760.9116 | BF13: =BD13-BE13 -> 1287.7392 | BG13: =AT13+AY13+BD13 -> 10520.651 | BH13: =INDEX(cpi!B:B,MATCH($L13,cpi!A:A)) -> 92.6 | BI13: =100*BH13/BH$3 -> 109.45626 | BJ13: =100*AC13/AC$3 -> 116.81223 | BK13: =100*AD13/AD$3 -> 121.66405 | BL13: =BJ13*GlobalPortfolio+BK13*AusPortfolio -> 118.26778 | BM13: =100*AE13/$AE$3 -> 164.97261 | BN13: =100*AR13/AR$3 -> 102.17391 | BO13: =100*AX13/AX$3 -> 96.47409
A14: Depreciation (% of initial home value per year) | B14: 0.01 | C14: 0.01 | L14: =DATE(YEAR(L13),MONTH(L13)+3,1) -> 39783 | M14: =AP14 -> 182515.55 | N14: =AX14-BC14 -> 66178.462 | O14: =M14/N14 -> 2.7579298 | P14: =X14/BG14 -> 0.49178915 | Q14: 12 | R14: =EOMONTH(L14,0)-EOMONTH(L14,-3) -> 92 | T14: =IF($B$10="3BR_H", INDEX('3BR_H-combined'!$C:$BH,MATCH($L14,'3BR_H-combined'!$B:$B,0),MATCH(Council_Area,'3BR_H-combined'!$C$1:$BH$1,0)), INDEX('2BR_F-combined'!$C:$BH,MATCH($L14,'2BR_F-combined'!$B:$B,0),MATCH(Council_Area,'2BR_F-combined'!$C$1:$BH$1,0))) -> 350 | U14: =IF(MOD(Q14,4)=1,T14,U13) -> 320 | V14: =U14*(R14)/7 -> 4205.7143 | W14: =$B$53/4*BH14/_xlfn.XLOOKUP(Q_end,cpi!A:A,cpi!B:B) -> 127.98894 | X14: =V14+W14 -> 4333.7032 | Y14: =BG14-X14 -> 4478.4132 | Z14: =Y14*$B$47 -> 1433.0922 | AA14: =(Y14+Z14)*eff_invest -> 5911.5054 | AB14: =AA14*(_xlfn.XLOOKUP(Q_end,cpi!A:A,cpi!B:B)/BH14) -> 9237.5253 | AC14: {=INDEX('msci-indices'!C:C,MATCH($L14,'msci-indices'!$B:$B)-2)} -> 747.65998 | AD14: {=INDEX('msci-indices'!D:D,MATCH($L14,'msci-indices'!$B:$B)-2)} -> 775.74397 | AE14: =AI13+AA14 -> 231566.39 | AF14: {=INDEX('msci-indices'!C:C,MATCH($L14,'msci-indices'!$B:$B)+1)} -> 582.01082 | AG14: {=INDEX('msci-indices'!D:D,MATCH($L14,'msci-indices'!$B:$B)+1)} -> 630.6613 | AH14: =(InvestFees/4)*AE14 -> 144.729 | AI14: =((AF14/AC14)*GlobalPortfolio+(AG14/AD14)*AusPortfolio)*AE14-AH14 -> 182515.55 | AJ14: =AJ13+AA14 -> 242001.2 | AK14: =AI14-AJ14 -> -59485.653 | AL14: =AJ14*(_xlfn.XLOOKUP(Q_end,cpi!A:A,cpi!B:B)/BH14) -> 378159.55 | AM14: {=SUMPRODUCT($AA$3:AA14,_xlfn.SORTBY($BH$3:BH14,_xlfn.SEQUENCE(ROWS($BH$3:BH14)),-1)/$BH$3)} -> 260563.12 | AN14: =AI14-AM14 -> -78047.573 | AO14: =IF($B$49="Real gains",MAX($B$50*AN14,0),IF($B$49="Discounted nominal gains",MAX($B$50*AK14/2,0),0)) -> 0 | AP14: =AI14-AO14 -> 182515.55 | AR14: =IF($B$10="3BR_H", INDEX('ns-combined'!$C:$BH,MATCH($L14,'ns-combined'!$B:$B,0),MATCH(Council_Area,'ns-combined'!$C$1:$BH$1,0))*1000, INDEX('s-combined'!$C:$BH,MATCH($L14,'s-combined'!$B:$B,0),MATCH(Council_Area,'s-combined'!$C$1:$BH$1,0))*1000) -> 459000 | AS14: =AS13+$AS$3 -> 13800 | AT14: 0 | AU14: =SUM($B$28:$B$29)*AR14 -> 9180 | AV14: =AR14*$B$15/4 -> 1319.625 | AW14: =SUM($AV$3:AV14) -> 16749.75 | AX14: =AR14-AS14-AU14-AW14 -> 419270.25 | AY14: =$B$36*V14 -> 1472 | AZ14: =SUM(AY14:AY14)*4/AR14 -> 0.012827887 | BA14: =SUM(AY14:AY14)/V14 -> 0.35 | BB14: =IF(MortgageRate="Discounted",_xlfn.XLOOKUP(L14,'mortgage-rates'!$A:$A,'mortgage-rates'!$E:$E)/100,_xlfn.XLOOKUP(L14,'mortgage-rates'!$A:$A,'mortgage-rates'!$D:$D)/100) -> 0.062 | BC14: =BC13-BF13 -> 353091.79 | BD14: =IF($B$16*12/3-Q14+1>0,-PMT($BB14/4,$B$16*12/3-Q14+1,BC14),0) -> 7340.1164 | BE14: =BC14*($BB14/4) -> 5472.9227 | BF14: =BD14-BE14 -> 1867.1937 | BG14: =AT14+AY14+BD14 -> 8812.1164 | BH14: =INDEX(cpi!B:B,MATCH($L14,cpi!A:A)) -> 92.6 | BI14: =100*BH14/BH$3 -> 109.45626 | BJ14: =100*AC14/AC$3 -> 99.043605 | BK14: =100*AD14/AD$3 -> 108.80667 | BL14: =BJ14*GlobalPortfolio+BK14*AusPortfolio -> 101.97253 | BM14: =100*AE14/$AE$3 -> 145.79504 | BN14: =100*AR14/AR$3 -> 99.782609 | BO14: =100*AX14/AX$3 -> 93.518745
A15: Renovations, alterations, and additions (% of current home value per year) | B15: 0.0115 | C15: 0.0115 | L15: =DATE(YEAR(L14),MONTH(L14)+3,1) -> 39873 | M15: =AP15 -> 170999.66 | N15: =AX15-BC15 -> 47010.656 | O15: =M15/N15 -> 3.6374659 | P15: =X15/BG15 -> 0.55848576 | Q15: 13 | R15: =EOMONTH(L15,0)-EOMONTH(L15,-3) -> 90 | T15: =IF($B$10="3BR_H", INDEX('3BR_H-combined'!$C:$BH,MATCH($L15,'3BR_H-combined'!$B:$B,0),MATCH(Council_Area,'3BR_H-combined'!$C$1:$BH$1,0)), INDEX('2BR_F-combined'!$C:$BH,MATCH($L15,'2BR_F-combined'!$B:$B,0),MATCH(Council_Area,'2BR_F-combined'!$C$1:$BH$1,0))) -> 350 | U15: =IF(MOD(Q15,4)=1,T15,U14) -> 350 | V15: =U15*(R15)/7 -> 4500 | W15: =$B$53/4*BH15/_xlfn.XLOOKUP(Q_end,cpi!A:A,cpi!B:B) -> 127.85073 | X15: =V15+W15 -> 4627.8507 | Y15: =BG15-X15 -> 3658.575 | Z15: =Y15*$B$47 -> 1170.744 | AA15: =(Y15+Z15)*eff_invest -> 4829.319 | AB15: =AA15*(_xlfn.XLOOKUP(Q_end,cpi!A:A,cpi!B:B)/BH15) -> 7554.6212 | AC15: {=INDEX('msci-indices'!C:C,MATCH($L15,'msci-indices'!$B:$B)-2)} -> 582.01082 | AD15: {=INDEX('msci-indices'!D:D,MATCH($L15,'msci-indices'!$B:$B)-2)} -> 630.6613 | AE15: =AI14+AA15 -> 187344.87 | AF15: {=INDEX('msci-indices'!C:C,MATCH($L15,'msci-indices'!$B:$B)+1)} -> 513.55423 | AG15: {=INDEX('msci-indices'!D:D,MATCH($L15,'msci-indices'!$B:$B)+1)} -> 621.64895 | AH15: =(InvestFees/4)*AE15 -> 117.09054 | AI15: =((AF15/AC15)*GlobalPortfolio+(AG15/AD15)*AusPortfolio)*AE15-AH15 -> 170999.66 | AJ15: =AJ14+AA15 -> 246830.52 | AK15: =AI15-AJ15 -> -75830.867 | AL15: =AJ15*(_xlfn.XLOOKUP(Q_end,cpi!A:A,cpi!B:B)/BH15) -> 386122.99 | AM15: {=SUMPRODUCT($AA$3:AA15,_xlfn.SORTBY($BH$3:BH15,_xlfn.SEQUENCE(ROWS($BH$3:BH15)),-1)/$BH$3)} -> 265901.29 | AN15: =AI15-AM15 -> -94901.639 | AO15: =IF($B$49="Real gains",MAX($B$50*AN15,0),IF($B$49="Discounted nominal gains",MAX($B$50*AK15/2,0),0)) -> 0 | AP15: =AI15-AO15 -> 170999.66 | AR15: =IF($B$10="3BR_H", INDEX('ns-combined'!$C:$BH,MATCH($L15,'ns-combined'!$B:$B,0),MATCH(Council_Area,'ns-combined'!$C$1:$BH$1,0))*1000, INDEX('s-combined'!$C:$BH,MATCH($L15,'s-combined'!$B:$B,0),MATCH(Council_Area,'s-combined'!$C$1:$BH$1,0))*1000) -> 440000 | AS15: =AS14+$AS$3 -> 14950 | AT15: 0 | AU15: =SUM($B$28:$B$29)*AR15 -> 8800 | AV15: =AR15*$B$15/4 -> 1265 | AW15: =SUM($AV$3:AV15) -> 18014.75 | AX15: =AR15-AS15-AU15-AW15 -> 398235.25 | AY15: =$B$36*V15 -> 1575 | AZ15: =SUM(AY15:AY15)*4/AR15 -> 0.014318182 | BA15: =SUM(AY15:AY15)/V15 -> 0.35 | BB15: =IF(MortgageRate="Discounted",_xlfn.XLOOKUP(L15,'mortgage-rates'!$A:$A,'mortgage-rates'!$E:$E)/100,_xlfn.XLOOKUP(L15,'mortgage-rates'!$A:$A,'mortgage-rates'!$D:$D)/100) -> 0.0518 | BC15: =BC14-BF14 -> 351224.59 | BD15: =IF($B$16*12/3-Q15+1>0,-PMT($BB15/4,$B$16*12/3-Q15+1,BC15),0) -> 6711.4257 | BE15: =BC15*($BB15/4) -> 4548.3585 | BF15: =BD15-BE15 -> 2163.0672 | BG15: =AT15+AY15+BD15 -> 8286.4257 | BH15: =INDEX(cpi!B:B,MATCH($L15,cpi!A:A)) -> 92.5 | BI15: =100*BH15/BH$3 -> 109.33806 | BJ15: =100*AC15/AC$3 -> 77.099819 | BK15: =100*AD15/AD$3 -> 88.457223 | BL15: =BJ15*GlobalPortfolio+BK15*AusPortfolio -> 80.50704 | BM15: =100*AE15/$AE$3 -> 117.95301 | BN15: =100*AR15/AR$3 -> 95.652174 | BO15: =100*AX15/AX$3 -> 88.826862
A16: Loan term (years) | B16: 25 | C16: 25 | L16: =DATE(YEAR(L15),MONTH(L15)+3,1) -> 39965 | M16: =AP16 -> 208361.68 | N16: =AX16-BC16 -> 90729.348 | O16: =M16/N16 -> 2.2965191 | P16: =X16/BG16 -> 0.56503703 | Q16: 14 | R16: =EOMONTH(L16,0)-EOMONTH(L16,-3) -> 91 | T16: =IF($B$10="3BR_H", INDEX('3BR_H-combined'!$C:$BH,MATCH($L16,'3BR_H-combined'!$B:$B,0),MATCH(Council_Area,'3BR_H-combined'!$C$1:$BH$1,0)), INDEX('2BR_F-combined'!$C:$BH,MATCH($L16,'2BR_F-combined'!$B:$B,0),MATCH(Council_Area,'2BR_F-combined'!$C$1:$BH$1,0))) -> 350 | U16: =IF(MOD(Q16,4)=1,T16,U15) -> 350 | V16: =U16*(R16)/7 -> 4550 | W16: =$B$53/4*BH16/_xlfn.XLOOKUP(Q_end,cpi!A:A,cpi!B:B) -> 128.54181 | X16: =V16+W16 -> 4678.5418 | Y16: =BG16-X16 -> 3601.5205 | Z16: =Y16*$B$47 -> 1152.4866 | AA16: =(Y16+Z16)*eff_invest -> 4754.0071 | AB16: =AA16*(_xlfn.XLOOKUP(Q_end,cpi!A:A,cpi!B:B)/BH16) -> 7396.8261 | AC16: {=INDEX('msci-indices'!C:C,MATCH($L16,'msci-indices'!$B:$B)-2)} -> 513.55423 | AD16: {=INDEX('msci-indices'!D:D,MATCH($L16,'msci-indices'!$B:$B)-2)} -> 621.64895 | AE16: =AI15+AA16 -> 175753.66 | AF16: {=INDEX('msci-indices'!C:C,MATCH($L16,'msci-indices'!$B:$B)+1)} -> 624.35598 | AG16: {=INDEX('msci-indices'!D:D,MATCH($L16,'msci-indices'!$B:$B)+1)} -> 694.44245 | AH16: =(InvestFees/4)*AE16 -> 109.84604 | AI16: =((AF16/AC16)*GlobalPortfolio+(AG16/AD16)*AusPortfolio)*AE16-AH16 -> 208361.68 | AJ16: =AJ15+AA16 -> 251584.53 | AK16: =AI16-AJ16 -> -43222.845 | AL16: =AJ16*(_xlfn.XLOOKUP(Q_end,cpi!A:A,cpi!B:B)/BH16) -> 391443.89 | AM16: {=SUMPRODUCT($AA$3:AA16,_xlfn.SORTBY($BH$3:BH16,_xlfn.SEQUENCE(ROWS($BH$3:BH16)),-1)/$BH$3)} -> 272254.54 | AN16: =AI16-AM16 -> -63892.852 | AO16: =IF($B$49="Real gains",MAX($B$50*AN16,0),IF($B$49="Discounted nominal gains",MAX($B$50*AK16/2,0),0)) -> 0 | AP16: =AI16-AO16 -> 208361.68 | AR16: =IF($B$10="3BR_H", INDEX('ns-combined'!$C:$BH,MATCH($L16,'ns-combined'!$B:$B,0),MATCH(Council_Area,'ns-combined'!$C$1:$BH$1,0))*1000, INDEX('s-combined'!$C:$BH,MATCH($L16,'s-combined'!$B:$B,0),MATCH(Council_Area,'s-combined'!$C$1:$BH$1,0))*1000) -> 485000 | AS16: =AS15+$AS$3 -> 16100 | AT16: 0 | AU16: =SUM($B$28:$B$29)*AR16 -> 9700 | AV16: =AR16*$B$15/4 -> 1394.375 | AW16: =SUM($AV$3:AV16) -> 19409.125 | AX16: =AR16-AS16-AU16-AW16 -> 439790.88 | AY16: =$B$36*V16 -> 1592.5 | AZ16: =SUM(AY16:AY16)*4/AR16 -> 0.013134021 | BA16: =SUM(AY16:AY16)/V16 -> 0.35 | BB16: =IF(MortgageRate="Discounted",_xlfn.XLOOKUP(L16,'mortgage-rates'!$A:$A,'mortgage-rates'!$E:$E)/100,_xlfn.XLOOKUP(L16,'mortgage-rates'!$A:$A,'mortgage-rates'!$D:$D)/100) -> 0.0514 | BC16: =BC15-BF15 -> 349061.53 | BD16: =IF($B$16*12/3-Q16+1>0,-PMT($BB16/4,$B$16*12/3-Q16+1,BC16),0) -> 6687.5624 | BE16: =BC16*($BB16/4) -> 4485.4406 | BF16: =BD16-BE16 -> 2202.1217 | BG16: =AT16+AY16+BD16 -> 8280.0624 | BH16: =INDEX(cpi!B:B,MATCH($L16,cpi!A:A)) -> 93 | BI16: =100*BH16/BH$3 -> 109.92908 | BJ16: =100*AC16/AC$3 -> 68.031276 | BK16: =100*AD16/AD$3 -> 87.193142 | BL16: =BJ16*GlobalPortfolio+BK16*AusPortfolio -> 73.779836 | BM16: =100*AE16/$AE$3 -> 110.65514 | BN16: =100*AR16/AR$3 -> 105.43478 | BO16: =100*AX16/AX$3 -> 98.095895
L17: =DATE(YEAR(L16),MONTH(L16)+3,1) -> 40057 | M17: =AP17 -> 254076.64 | N17: =AX17-BC17 -> 98204.095 | O17: =M17/N17 -> 2.5872306 | P17: =X17/BG17 -> 0.5699878 | Q17: 15 | R17: =EOMONTH(L17,0)-EOMONTH(L17,-3) -> 92 | T17: =IF($B$10="3BR_H", INDEX('3BR_H-combined'!$C:$BH,MATCH($L17,'3BR_H-combined'!$B:$B,0),MATCH(Council_Area,'3BR_H-combined'!$C$1:$BH$1,0)), INDEX('2BR_F-combined'!$C:$BH,MATCH($L17,'2BR_F-combined'!$B:$B,0),MATCH(Council_Area,'2BR_F-combined'!$C$1:$BH$1,0))) -> 360 | U17: =IF(MOD(Q17,4)=1,T17,U16) -> 350 | V17: =U17*(R17)/7 -> 4600 | W17: =$B$53/4*BH17/_xlfn.XLOOKUP(Q_end,cpi!A:A,cpi!B:B) -> 129.50933 | X17: =V17+W17 -> 4729.5093 | Y17: =BG17-X17 -> 3568.053 | Z17: =Y17*$B$47 -> 1141.777 | AA17: =(Y17+Z17)*eff_invest -> 4709.83 | AB17: =AA17*(_xlfn.XLOOKUP(Q_end,cpi!A:A,cpi!B:B)/BH17) -> 7273.3447 | AC17: {=INDEX('msci-indices'!C:C,MATCH($L17,'msci-indices'!$B:$B)-2)} -> 624.35598 | AD17: {=INDEX('msci-indices'!D:D,MATCH($L17,'msci-indices'!$B:$B)-2)} -> 694.44245 | AE17: =AI16+AA17 -> 213071.51 | AF17: {=INDEX('msci-indices'!C:C,MATCH($L17,'msci-indices'!$B:$B)+1)} -> 736.86333 | AG17: {=INDEX('msci-indices'!D:D,MATCH($L17,'msci-indices'!$B:$B)+1)} -> 849.38296 | AH17: =(InvestFees/4)*AE17 -> 133.1697 | AI17: =((AF17/AC17)*GlobalPortfolio+(AG17/AD17)*AusPortfolio)*AE17-AH17 -> 254076.64 | AJ17: =AJ16+AA17 -> 256294.36 | AK17: =AI17-AJ17 -> -2217.7222 | AL17: =AJ17*(_xlfn.XLOOKUP(Q_end,cpi!A:A,cpi!B:B)/BH17) -> 395792.89 | AM17: {=SUMPRODUCT($AA$3:AA17,_xlfn.SORTBY($BH$3:BH17,_xlfn.SEQUENCE(ROWS($BH$3:BH17)),-1)/$BH$3)} -> 278975.09 | AN17: =AI17-AM17 -> -24898.448 | AO17: =IF($B$49="Real gains",MAX($B$50*AN17,0),IF($B$49="Discounted nominal gains",MAX($B$50*AK17/2,0),0)) -> 0 | AP17: =AI17-AO17 -> 254076.64 | AR17: =IF($B$10="3BR_H", INDEX('ns-combined'!$C:$BH,MATCH($L17,'ns-combined'!$B:$B,0),MATCH(Council_Area,'ns-combined'!$C$1:$BH$1,0))*1000, INDEX('s-combined'!$C:$BH,MATCH($L17,'s-combined'!$B:$B,0),MATCH(Council_Area,'s-combined'!$C$1:$BH$1,0))*1000) -> 493000 | AS17: =AS16+$AS$3 -> 17250 | AT17: 0 | AU17: =SUM($B$28:$B$29)*AR17 -> 9860 | AV17: =AR17*$B$15/4 -> 1417.375 | AW17: =SUM($AV$3:AV17) -> 20826.5 | AX17: =AR17-AS17-AU17-AW17 -> 445063.5 | AY17: =$B$36*V17 -> 1610 | AZ17: =SUM(AY17:AY17)*4/AR17 -> 0.01306288 | BA17: =SUM(AY17:AY17)/V17 -> 0.35 | BB17: =IF(MortgageRate="Discounted",_xlfn.XLOOKUP(L17,'mortgage-rates'!$A:$A,'mortgage-rates'!$E:$E)/100,_xlfn.XLOOKUP(L17,'mortgage-rates'!$A:$A,'mortgage-rates'!$D:$D)/100) -> 0.0514 | BC17: =BC16-BF16 -> 346859.41 | BD17: =IF($B$16*12/3-Q17+1>0,-PMT($BB17/4,$B$16*12/3-Q17+1,BC17),0) -> 6687.5624 | BE17: =BC17*($BB17/4) -> 4457.1434 | BF17: =BD17-BE17 -> 2230.419 | BG17: =AT17+AY17+BD17 -> 8297.5624 | BH17: =INDEX(cpi!B:B,MATCH($L17,cpi!A:A)) -> 93.7 | BI17: =100*BH17/BH$3 -> 110.7565 | BJ17: =100*AC17/AC$3 -> 82.709345 | BK17: =100*AD17/AD$3 -> 97.403235 | BL17: =BJ17*GlobalPortfolio+BK17*AusPortfolio -> 87.117512 | BM17: =100*AE17/$AE$3 -> 134.1506 | BN17: =100*AR17/AR$3 -> 107.17391 | BO17: =100*AX17/AX$3 -> 99.271961
A18: Mortgage | L18: =DATE(YEAR(L17),MONTH(L17)+3,1) -> 40148 | M18: =AP18 -> 269071.98 | N18: =AX18-BC18 -> 180922.76 | O18: =M18/N18 -> 1.4872201 | P18: =X18/BG18 -> 0.53691924 | Q18: 16 | R18: =EOMONTH(L18,0)-EOMONTH(L18,-3) -> 92 | T18: =IF($B$10="3BR_H", INDEX('3BR_H-combined'!$C:$BH,MATCH($L18,'3BR_H-combined'!$B:$B,0),MATCH(Council_Area,'3BR_H-combined'!$C$1:$BH$1,0)), INDEX('2BR_F-combined'!$C:$BH,MATCH($L18,'2BR_F-combined'!$B:$B,0),MATCH(Council_Area,'2BR_F-combined'!$C$1:$BH$1,0))) -> 370 | U18: =IF(MOD(Q18,4)=1,T18,U17) -> 350 | V18: =U18*(R18)/7 -> 4600 | W18: =$B$53/4*BH18/_xlfn.XLOOKUP(Q_end,cpi!A:A,cpi!B:B) -> 130.61507 | X18: =V18+W18 -> 4730.6151 | Y18: =BG18-X18 -> 4080.0491 | Z18: =Y18*$B$47 -> 1305.6157 | AA18: =(Y18+Z18)*eff_invest -> 5385.6648 | AB18: =AA18*(_xlfn.XLOOKUP(Q_end,cpi!A:A,cpi!B:B)/BH18) -> 8246.6211 | AC18: {=INDEX('msci-indices'!C:C,MATCH($L18,'msci-indices'!$B:$B)-2)} -> 736.86333 | AD18: {=INDEX('msci-indices'!D:D,MATCH($L18,'msci-indices'!$B:$B)-2)} -> 849.38296 | AE18: =AI17+AA18 -> 259462.3 | AF18: {=INDEX('msci-indices'!C:C,MATCH($L18,'msci-indices'!$B:$B)+1)} -> 765.74116 | AG18: {=INDEX('msci-indices'!D:D,MATCH($L18,'msci-indices'!$B:$B)+1)} -> 878.3433 | AH18: =(InvestFees/4)*AE18 -> 162.16394 | AI18: =((AF18/AC18)*GlobalPortfolio+(AG18/AD18)*AusPortfolio)*AE18-AH18 -> 269071.98 | AJ18: =AJ17+AA18 -> 261680.02 | AK18: =AI18-AJ18 -> 7391.9501 | AL18: =AJ18*(_xlfn.XLOOKUP(Q_end,cpi!A:A,cpi!B:B)/BH18) -> 400688.88 | AM18: {=SUMPRODUCT($AA$3:AA18,_xlfn.SORTBY($BH$3:BH18,_xlfn.SEQUENCE(ROWS($BH$3:BH18)),-1)/$BH$3)} -> 286624.92 | AN18: =AI18-AM18 -> -17552.943 | AO18: =IF($B$49="Real gains",MAX($B$50*AN18,0),IF($B$49="Discounted nominal gains",MAX($B$50*AK18/2,0),0)) -> 0 | AP18: =AI18-AO18 -> 269071.98 | AR18: =IF($B$10="3BR_H", INDEX('ns-combined'!$C:$BH,MATCH($L18,'ns-combined'!$B:$B,0),MATCH(Council_Area,'ns-combined'!$C$1:$BH$1,0))*1000, INDEX('s-combined'!$C:$BH,MATCH($L18,'s-combined'!$B:$B,0),MATCH(Council_Area,'s-combined'!$C$1:$BH$1,0))*1000) -> 578000 | AS18: =AS17+$AS$3 -> 18400 | AT18: 0 | AU18: =SUM($B$28:$B$29)*AR18 -> 11560 | AV18: =AR18*$B$15/4 -> 1661.75 | AW18: =SUM($AV$3:AV18) -> 22488.25 | AX18: =AR18-AS18-AU18-AW18 -> 525551.75 | AY18: =$B$36*V18 -> 1610 | AZ18: =SUM(AY18:AY18)*4/AR18 -> 0.011141869 | BA18: =SUM(AY18:AY18)/V18 -> 0.35 | BB18: =IF(MortgageRate="Discounted",_xlfn.XLOOKUP(L18,'mortgage-rates'!$A:$A,'mortgage-rates'!$E:$E)/100,_xlfn.XLOOKUP(L18,'mortgage-rates'!$A:$A,'mortgage-rates'!$D:$D)/100) -> 0.06 | BC18: =BC17-BF17 -> 344628.99 | BD18: =IF($B$16*12/3-Q18+1>0,-PMT($BB18/4,$B$16*12/3-Q18+1,BC18),0) -> 7200.6642 | BE18: =BC18*($BB18/4) -> 5169.4348 | BF18: =BD18-BE18 -> 2031.2294 | BG18: =AT18+AY18+BD18 -> 8810.6642 | BH18: =INDEX(cpi!B:B,MATCH($L18,cpi!A:A)) -> 94.5 | BI18: =100*BH18/BH$3 -> 111.70213 | BJ18: =100*AC18/AC$3 -> 97.613357 | BK18: =100*AD18/AD$3 -> 119.13536 | BL18: =BJ18*GlobalPortfolio+BK18*AusPortfolio -> 104.06996 | BM18: =100*AE18/$AE$3 -> 163.35841 | BN18: =100*AR18/AR$3 -> 125.65217 | BO18: =100*AX18/AX$3 -> 117.22496
A19: Mortgage rates (Standard/Discounted) | B19: Discounted | C19: Discounted | L19: =DATE(YEAR(L18),MONTH(L18)+3,1) -> 40238 | M19: =AP19 -> 282918.25 | N19: =AX19-BC19 -> 168416.74 | O19: =M19/N19 -> 1.6798701 | P19: =X19/BG19 -> 0.55366017 | Q19: 17 | R19: =EOMONTH(L19,0)-EOMONTH(L19,-3) -> 90 | T19: =IF($B$10="3BR_H", INDEX('3BR_H-combined'!$C:$BH,MATCH($L19,'3BR_H-combined'!$B:$B,0),MATCH(Council_Area,'3BR_H-combined'!$C$1:$BH$1,0)), INDEX('2BR_F-combined'!$C:$BH,MATCH($L19,'2BR_F-combined'!$B:$B,0),MATCH(Council_Area,'2BR_F-combined'!$C$1:$BH$1,0))) -> 380 | U19: =IF(MOD(Q19,4)=1,T19,U18) -> 380 | V19: =U19*(R19)/7 -> 4885.7143 | W19: =$B$53/4*BH19/_xlfn.XLOOKUP(Q_end,cpi!A:A,cpi!B:B) -> 131.58258 | X19: =V19+W19 -> 5017.2969 | Y19: =BG19-X19 -> 4044.7544 | Z19: =Y19*$B$47 -> 1294.3214 | AA19: =(Y19+Z19)*eff_invest -> 5339.0758 | AB19: =AA19*(_xlfn.XLOOKUP(Q_end,cpi!A:A,cpi!B:B)/BH19) -> 8115.1708 | AC19: {=INDEX('msci-indices'!C:C,MATCH($L19,'msci-indices'!$B:$B)-2)} -> 765.74116 | AD19: {=INDEX('msci-indices'!D:D,MATCH($L19,'msci-indices'!$B:$B)-2)} -> 878.3433 | AE19: =AI18+AA19 -> 274411.05 | AF19: {=INDEX('msci-indices'!C:C,MATCH($L19,'msci-indices'!$B:$B)+1)} -> 794.63718 | AG19: {=INDEX('msci-indices'!D:D,MATCH($L19,'msci-indices'!$B:$B)+1)} -> 893.60148 | AH19: =(InvestFees/4)*AE19 -> 171.50691 | AI19: =((AF19/AC19)*GlobalPortfolio+(AG19/AD19)*AusPortfolio)*AE19-AH19 -> 282918.25 | AJ19: =AJ18+AA19 -> 267019.1 | AK19: =AI19-AJ19 -> 15899.151 | AL19: =AJ19*(_xlfn.XLOOKUP(Q_end,cpi!A:A,cpi!B:B)/BH19) -> 405857.81 | AM19: {=SUMPRODUCT($AA$3:AA19,_xlfn.SORTBY($BH$3:BH19,_xlfn.SEQUENCE(ROWS($BH$3:BH19)),-1)/$BH$3)} -> 294104.56 | AN19: =AI19-AM19 -> -11186.31 | AO19: =IF($B$49="Real gains",MAX($B$50*AN19,0),IF($B$49="Discounted nominal gains",MAX($B$50*AK19/2,0),0)) -> 0 | AP19: =AI19-AO19 -> 282918.25 | AR19: =IF($B$10="3BR_H", INDEX('ns-combined'!$C:$BH,MATCH($L19,'ns-combined'!$B:$B,0),MATCH(Council_Area,'ns-combined'!$C$1:$BH$1,0))*1000, INDEX('s-combined'!$C:$BH,MATCH($L19,'s-combined'!$B:$B,0),MATCH(Council_Area,'s-combined'!$C$1:$BH$1,0))*1000) -> 566000 | AS19: =AS18+$AS$3 -> 19550 | AT19: 0 | AU19: =SUM($B$28:$B$29)*AR19 -> 11320 | AV19: =AR19*$B$15/4 -> 1627.25 | AW19: =SUM($AV$3:AV19) -> 24115.5 | AX19: =AR19-AS19-AU19-AW19 -> 511014.5 | AY19: =$B$36*V19 -> 1710 | AZ19: =SUM(AY19:AY19)*4/AR19 -> 0.012084806 | BA19: =SUM(AY19:AY19)/V19 -> 0.35 | BB19: =IF(MortgageRate="Discounted",_xlfn.XLOOKUP(L19,'mortgage-rates'!$A:$A,'mortgage-rates'!$E:$E)/100,_xlfn.XLOOKUP(L19,'mortgage-rates'!$A:$A,'mortgage-rates'!$D:$D)/100) -> 0.0625 | BC19: =BC18-BF18 -> 342597.76 | BD19: =IF($B$16*12/3-Q19+1>0,-PMT($BB19/4,$B$16*12/3-Q19+1,BC19),0) -> 7352.0512 | BE19: =BC19*($BB19/4) -> 5353.09 | BF19: =BD19-BE19 -> 1998.9613 | BG19: =AT19+AY19+BD19 -> 9062.0512 | BH19: =INDEX(cpi!B:B,MATCH($L19,cpi!A:A)) -> 95.2 | BI19: =100*BH19/BH$3 -> 112.52955 | BJ19: =100*AC19/AC$3 -> 101.43885 | BK19: =100*AD19/AD$3 -> 123.19736 | BL19: =BJ19*GlobalPortfolio+BK19*AusPortfolio -> 107.9664 | BM19: =100*AE19/$AE$3 -> 172.77019 | BN19: =100*AR19/AR$3 -> 123.04348 | BO19: =100*AX19/AX$3 -> 113.98241
A20: Deposit (% of home purchase price) | B20: 0.2 | C20: 0.2 | L20: =DATE(YEAR(L19),MONTH(L19)+3,1) -> 40330 | M20: =AP20 -> 253048.61 | N20: =AX20-BC20 -> 195975.08 | O20: =M20/N20 -> 1.2912285 | P20: =X20/BG20 -> 0.54043853 | Q20: 18 | R20: =EOMONTH(L20,0)-EOMONTH(L20,-3) -> 91 | T20: =IF($B$10="3BR_H", INDEX('3BR_H-combined'!$C:$BH,MATCH($L20,'3BR_H-combined'!$B:$B,0),MATCH(Council_Area,'3BR_H-combined'!$C$1:$BH$1,0)), INDEX('2BR_F-combined'!$C:$BH,MATCH($L20,'2BR_F-combined'!$B:$B,0),MATCH(Council_Area,'2BR_F-combined'!$C$1:$BH$1,0))) -> 380 | U20: =IF(MOD(Q20,4)=1,T20,U19) -> 380 | V20: =U20*(R20)/7 -> 4940 | W20: =$B$53/4*BH20/_xlfn.XLOOKUP(Q_end,cpi!A:A,cpi!B:B) -> 132.41189 | X20: =V20+W20 -> 5072.4119 | Y20: =BG20-X20 -> 4313.3214 | Z20: =Y20*$B$47 -> 1380.2628 | AA20: =(Y20+Z20)*eff_invest -> 5693.5843 | AB20: =AA20*(_xlfn.XLOOKUP(Q_end,cpi!A:A,cpi!B:B)/BH20) -> 8599.8084 | AC20: {=INDEX('msci-indices'!C:C,MATCH($L20,'msci-indices'!$B:$B)-2)} -> 794.63718 | AD20: {=INDEX('msci-indices'!D:D,MATCH($L20,'msci-indices'!$B:$B)-2)} -> 893.60148 | AE20: =AI19+AA20 -> 288611.84 | AF20: {=INDEX('msci-indices'!C:C,MATCH($L20,'msci-indices'!$B:$B)+1)} -> 696.18018 | AG20: {=INDEX('msci-indices'!D:D,MATCH($L20,'msci-indices'!$B:$B)+1)} -> 786.77037 | AH20: =(InvestFees/4)*AE20 -> 180.3824 | AI20: =((AF20/AC20)*GlobalPortfolio+(AG20/AD20)*AusPortfolio)*AE20-AH20 -> 253048.61 | AJ20: =AJ19+AA20 -> 272712.68 | AK20: =AI20-AJ20 -> -19664.07 | AL20: =AJ20*(_xlfn.XLOOKUP(Q_end,cpi!A:A,cpi!B:B)/BH20) -> 411915.72 | AM20: {=SUMPRODUCT($AA$3:AA20,_xlfn.SORTBY($BH$3:BH20,_xlfn.SEQUENCE(ROWS($BH$3:BH20)),-1)/$BH$3)} -> 301798.92 | AN20: =AI20-AM20 -> -48750.306 | AO20: =IF($B$49="Real gains",MAX($B$50*AN20,0),IF($B$49="Discounted nominal gains",MAX($B$50*AK20/2,0),0)) -> 0 | AP20: =AI20-AO20 -> 253048.61 | AR20: =IF($B$10="3BR_H", INDEX('ns-combined'!$C:$BH,MATCH($L20,'ns-combined'!$B:$B,0),MATCH(Council_Area,'ns-combined'!$C$1:$BH$1,0))*1000, INDEX('s-combined'!$C:$BH,MATCH($L20,'s-combined'!$B:$B,0),MATCH(Council_Area,'s-combined'!$C$1:$BH$1,0))*1000) -> 595000 | AS20: =AS19+$AS$3 -> 20700 | AT20: 0 | AU20: =SUM($B$28:$B$29)*AR20 -> 11900 | AV20: =AR20*$B$15/4 -> 1710.625 | AW20: =SUM($AV$3:AV20) -> 25826.125 | AX20: =AR20-AS20-AU20-AW20 -> 536573.88 | AY20: =$B$36*V20 -> 1729 | AZ20: =SUM(AY20:AY20)*4/AR20 -> 0.011623529 | BA20: =SUM(AY20:AY20)/V20 -> 0.35 | BB20: =IF(MortgageRate="Discounted",_xlfn.XLOOKUP(L20,'mortgage-rates'!$A:$A,'mortgage-rates'!$E:$E)/100,_xlfn.XLOOKUP(L20,'mortgage-rates'!$A:$A,'mortgage-rates'!$D:$D)/100) -> 0.0675 | BC20: =BC19-BF19 -> 340598.8 | BD20: =IF($B$16*12/3-Q20+1>0,-PMT($BB20/4,$B$16*12/3-Q20+1,BC20),0) -> 7656.7333 | BE20: =BC20*($BB20/4) -> 5747.6047 | BF20: =BD20-BE20 -> 1909.1286 | BG20: =AT20+AY20+BD20 -> 9385.7333 | BH20: =INDEX(cpi!B:B,MATCH($L20,cpi!A:A)) -> 95.8 | BI20: =100*BH20/BH$3 -> 113.23877 | BJ20: =100*AC20/AC$3 -> 105.26674 | BK20: =100*AD20/AD$3 -> 125.33749 | BL20: =BJ20*GlobalPortfolio+BK20*AusPortfolio -> 111.28797 | BM20: =100*AE20/$AE$3 -> 181.71106 | BN20: =100*AR20/AR$3 -> 129.34783 | BO20: =100*AX20/AX$3 -> 119.68346
A21: Lenders' mortgage insurance (% of home purchase price) | B21: 0 | C21: 0 | L21: =DATE(YEAR(L20),MONTH(L20)+3,1) -> 40422 | M21: =AP21 -> 290505.19 | N21: =AX21-BC21 -> 177435.33 | O21: =M21/N21 -> 1.6372454 | P21: =X21/BG21 -> 0.54520705 | Q21: 19 | R21: =EOMONTH(L21,0)-EOMONTH(L21,-3) -> 92 | T21: =IF($B$10="3BR_H", INDEX('3BR_H-combined'!$C:$BH,MATCH($L21,'3BR_H-combined'!$B:$B,0),MATCH(Council_Area,'3BR_H-combined'!$C$1:$BH$1,0)), INDEX('2BR_F-combined'!$C:$BH,MATCH($L21,'2BR_F-combined'!$B:$B,0),MATCH(Council_Area,'2BR_F-combined'!$C$1:$BH$1,0))) -> 390 | U21: =IF(MOD(Q21,4)=1,T21,U20) -> 380 | V21: =U21*(R21)/7 -> 4994.2857 | W21: =$B$53/4*BH21/_xlfn.XLOOKUP(Q_end,cpi!A:A,cpi!B:B) -> 133.24119 | X21: =V21+W21 -> 5127.5269 | Y21: =BG21-X21 -> 4277.2064 | Z21: =Y21*$B$47 -> 1368.706 | AA21: =(Y21+Z21)*eff_invest -> 5645.9124 | AB21: =AA21*(_xlfn.XLOOKUP(Q_end,cpi!A:A,cpi!B:B)/BH21) -> 8474.7254 | AC21: {=INDEX('msci-indices'!C:C,MATCH($L21,'msci-indices'!$B:$B)-2)} -> 696.18018 | AD21: {=INDEX('msci-indices'!D:D,MATCH($L21,'msci-indices'!$B:$B)-2)} -> 786.77037 | AE21: =AI20+AA21 -> 258694.53 | AF21: {=INDEX('msci-indices'!C:C,MATCH($L21,'msci-indices'!$B:$B)+1)} -> 792.86986 | AG21: {=INDEX('msci-indices'!D:D,MATCH($L21,'msci-indices'!$B:$B)+1)} -> 855.9299 | AH21: =(InvestFees/4)*AE21 -> 161.68408 | AI21: =((AF21/AC21)*GlobalPortfolio+(AG21/AD21)*AusPortfolio)*AE21-AH21 -> 290505.19 | AJ21: =AJ20+AA21 -> 278358.6 | AK21: =AI21-AJ21 -> 12146.592 | AL21: =AJ21*(_xlfn.XLOOKUP(Q_end,cpi!A:A,cpi!B:B)/BH21) -> 417826.65 | AM21: {=SUMPRODUCT($AA$3:AA21,_xlfn.SORTBY($BH$3:BH21,_xlfn.SEQUENCE(ROWS($BH$3:BH21)),-1)/$BH$3)} -> 309471.78 | AN21: =AI21-AM21 -> -18966.594 | AO21: =IF($B$49="Real gains",MAX($B$50*AN21,0),IF($B$49="Discounted nominal gains",MAX($B$50*AK21/2,0),0)) -> 0 | AP21: =AI21-AO21 -> 290505.19 | AR21: =IF($B$10="3BR_H", INDEX('ns-combined'!$C:$BH,MATCH($L21,'ns-combined'!$B:$B,0),MATCH(Council_Area,'ns-combined'!$C$1:$BH$1,0))*1000, INDEX('s-combined'!$C:$BH,MATCH($L21,'s-combined'!$B:$B,0),MATCH(Council_Area,'s-combined'!$C$1:$BH$1,0))*1000) -> 577000 | AS21: =AS20+$AS$3 -> 21850 | AT21: 0 | AU21: =SUM($B$28:$B$29)*AR21 -> 11540 | AV21: =AR21*$B$15/4 -> 1658.875 | AW21: =SUM($AV$3:AV21) -> 27485 | AX21: =AR21-AS21-AU21-AW21 -> 516125 | AY21: =$B$36*V21 -> 1748 | AZ21: =SUM(AY21:AY21)*4/AR21 -> 0.012117851 | BA21: =SUM(AY21:AY21)/V21 -> 0.35 | BB21: =IF(MortgageRate="Discounted",_xlfn.XLOOKUP(L21,'mortgage-rates'!$A:$A,'mortgage-rates'!$E:$E)/100,_xlfn.XLOOKUP(L21,'mortgage-rates'!$A:$A,'mortgage-rates'!$D:$D)/100) -> 0.0675 | BC21: =BC20-BF20 -> 338689.67 | BD21: =IF($B$16*12/3-Q21+1>0,-PMT($BB21/4,$B$16*12/3-Q21+1,BC21),0) -> 7656.7333 | BE21: =BC21*($BB21/4) -> 5715.3881 | BF21: =BD21-BE21 -> 1941.3452 | BG21: =AT21+AY21+BD21 -> 9404.7333 | BH21: =INDEX(cpi!B:B,MATCH($L21,cpi!A:A)) -> 96.4 | BI21: =100*BH21/BH$3 -> 113.94799 | BJ21: =100*AC21/AC$3 -> 92.224001 | BK21: =100*AD21/AD$3 -> 110.35325 | BL21: =BJ21*GlobalPortfolio+BK21*AusPortfolio -> 97.662775 | BM21: =100*AE21/$AE$3 -> 162.87501 | BN21: =100*AR21/AR$3 -> 125.43478 | BO21: =100*AX21/AX$3 -> 115.12232
L22: =DATE(YEAR(L21),MONTH(L21)+3,1) -> 40513 | M22: =AP22 -> 320357.57 | N22: =AX22-BC22 -> 199041.68 | O22: =M22/N22 -> 1.6094999 | P22: =X22/BG22 -> 0.53152259 | Q22: 20 | R22: =EOMONTH(L22,0)-EOMONTH(L22,-3) -> 92 | T22: =IF($B$10="3BR_H", INDEX('3BR_H-combined'!$C:$BH,MATCH($L22,'3BR_H-combined'!$B:$B,0),MATCH(Council_Area,'3BR_H-combined'!$C$1:$BH$1,0)), INDEX('2BR_F-combined'!$C:$BH,MATCH($L22,'2BR_F-combined'!$B:$B,0),MATCH(Council_Area,'2BR_F-combined'!$C$1:$BH$1,0))) -> 400 | U22: =IF(MOD(Q22,4)=1,T22,U21) -> 380 | V22: =U22*(R22)/7 -> 4994.2857 | W22: =$B$53/4*BH22/_xlfn.XLOOKUP(Q_end,cpi!A:A,cpi!B:B) -> 134.07049 | X22: =V22+W22 -> 5128.3562 | Y22: =BG22-X22 -> 4520.0696 | Z22: =Y22*$B$47 -> 1446.4223 | AA22: =(Y22+Z22)*eff_invest -> 5966.4918 | AB22: =AA22*(_xlfn.XLOOKUP(Q_end,cpi!A:A,cpi!B:B)/BH22) -> 8900.5295 | AC22: {=INDEX('msci-indices'!C:C,MATCH($L22,'msci-indices'!$B:$B)-2)} -> 792.86986 | AD22: {=INDEX('msci-indices'!D:D,MATCH($L22,'msci-indices'!$B:$B)-2)} -> 855.9299 | AE22: =AI21+AA22 -> 296471.68 | AF22: {=INDEX('msci-indices'!C:C,MATCH($L22,'msci-indices'!$B:$B)+1)} -> 869.42368 | AG22: {=INDEX('msci-indices'!D:D,MATCH($L22,'msci-indices'!$B:$B)+1)} -> 894.74694 | AH22: =(InvestFees/4)*AE22 -> 185.2948 | AI22: =((AF22/AC22)*GlobalPortfolio+(AG22/AD22)*AusPortfolio)*AE22-AH22 -> 320357.57 | AJ22: =AJ21+AA22 -> 284325.09 | AK22: =AI22-AJ22 -> 36032.481 | AL22: =AJ22*(_xlfn.XLOOKUP(Q_end,cpi!A:A,cpi!B:B)/BH22) -> 424142.68 | AM22: {=SUMPRODUCT($AA$3:AA22,_xlfn.SORTBY($BH$3:BH22,_xlfn.SEQUENCE(ROWS($BH$3:BH22)),-1)/$BH$3)} -> 317476.74 | AN22: =AI22-AM22 -> 2880.8291 | AO22: =IF($B$49="Real gains",MAX($B$50*AN22,0),IF($B$49="Discounted nominal gains",MAX($B$50*AK22/2,0),0)) -> 0 | AP22: =AI22-AO22 -> 320357.57 | AR22: =IF($B$10="3BR_H", INDEX('ns-combined'!$C:$BH,MATCH($L22,'ns-combined'!$B:$B,0),MATCH(Council_Area,'ns-combined'!$C$1:$BH$1,0))*1000, INDEX('s-combined'!$C:$BH,MATCH($L22,'s-combined'!$B:$B,0),MATCH(Council_Area,'s-combined'!$C$1:$BH$1,0))*1000) -> 600000 | AS22: =AS21+$AS$3 -> 23000 | AT22: 0 | AU22: =SUM($B$28:$B$29)*AR22 -> 12000 | AV22: =AR22*$B$15/4 -> 1725 | AW22: =SUM($AV$3:AV22) -> 29210 | AX22: =AR22-AS22-AU22-AW22 -> 535790 | AY22: =$B$36*V22 -> 1748 | AZ22: =SUM(AY22:AY22)*4/AR22 -> 0.011653333 | BA22: =SUM(AY22:AY22)/V22 -> 0.35 | BB22: =IF(MortgageRate="Discounted",_xlfn.XLOOKUP(L22,'mortgage-rates'!$A:$A,'mortgage-rates'!$E:$E)/100,_xlfn.XLOOKUP(L22,'mortgage-rates'!$A:$A,'mortgage-rates'!$D:$D)/100) -> 0.0715 | BC22: =BC21-BF21 -> 336748.32 | BD22: =IF($B$16*12/3-Q22+1>0,-PMT($BB22/4,$B$16*12/3-Q22+1,BC22),0) -> 7900.4258 | BE22: =BC22*($BB22/4) -> 6019.3763 | BF22: =BD22-BE22 -> 1881.0495 | BG22: =AT22+AY22+BD22 -> 9648.4258 | BH22: =INDEX(cpi!B:B,MATCH($L22,cpi!A:A)) -> 97 | BI22: =100*BH22/BH$3 -> 114.65721 | BJ22: =100*AC22/AC$3 -> 105.03262 | BK22: =100*AD22/AD$3 -> 120.05364 | BL22: =BJ22*GlobalPortfolio+BK22*AusPortfolio -> 109.53893 | BM22: =100*AE22/$AE$3 -> 186.65964 | BN22: =100*AR22/AR$3 -> 130.43478 | BO22: =100*AX22/AX$3 -> 119.50862
A23: Home transaction costs (% of home value) | L23: =DATE(YEAR(L22),MONTH(L22)+3,1) -> 40603 | M23: =AP23 -> 340622.03 | N23: =AX23-BC23 -> 149191.48 | O23: =M23/N23 -> 2.2831199 | P23: =X23/BG23 -> 0.54555644 | Q23: 21 | R23: =EOMONTH(L23,0)-EOMONTH(L23,-3) -> 90 | T23: =IF($B$10="3BR_H", INDEX('3BR_H-combined'!$C:$BH,MATCH($L23,'3BR_H-combined'!$B:$B,0),MATCH(Council_Area,'3BR_H-combined'!$C$1:$BH$1,0)), INDEX('2BR_F-combined'!$C:$BH,MATCH($L23,'2BR_F-combined'!$B:$B,0),MATCH(Council_Area,'2BR_F-combined'!$C$1:$BH$1,0))) -> 400 | U23: =IF(MOD(Q23,4)=1,T23,U22) -> 400 | V23: =U23*(R23)/7 -> 5142.8571 | W23: =$B$53/4*BH23/_xlfn.XLOOKUP(Q_end,cpi!A:A,cpi!B:B) -> 136.00553 | X23: =V23+W23 -> 5278.8627 | Y23: =BG23-X23 -> 4397.2447 | Z23: =Y23*$B$47 -> 1407.1183 | AA23: =(Y23+Z23)*eff_invest -> 5804.363 | AB23: =AA23*(_xlfn.XLOOKUP(Q_end,cpi!A:A,cpi!B:B)/BH23) -> 8535.481 | AC23: {=INDEX('msci-indices'!C:C,MATCH($L23,'msci-indices'!$B:$B)-2)} -> 869.42368 | AD23: {=INDEX('msci-indices'!D:D,MATCH($L23,'msci-indices'!$B:$B)-2)} -> 894.74694 | AE23: =AI22+AA23 -> 326161.93 | AF23: {=INDEX('msci-indices'!C:C,MATCH($L23,'msci-indices'!$B:$B)+1)} -> 912.83804 | AG23: {=INDEX('msci-indices'!D:D,MATCH($L23,'msci-indices'!$B:$B)+1)} -> 924.58629 | AH23: =(InvestFees/4)*AE23 -> 203.85121 | AI23: =((AF23/AC23)*GlobalPortfolio+(AG23/AD23)*AusPortfolio)*AE23-AH23 -> 340622.03 | AJ23: =AJ22+AA23 -> 290129.45 | AK23: =AI23-AJ23 -> 50492.576 | AL23: =AJ23*(_xlfn.XLOOKUP(Q_end,cpi!A:A,cpi!B:B)/BH23) -> 426643.62 | AM23: {=SUMPRODUCT($AA$3:AA23,_xlfn.SORTBY($BH$3:BH23,_xlfn.SEQUENCE(ROWS($BH$3:BH23)),-1)/$BH$3)} -> 326841.2 | AN23: =AI23-AM23 -> 13780.831 | AO23: =IF($B$49="Real gains",MAX($B$50*AN23,0),IF($B$49="Discounted nominal gains",MAX($B$50*AK23/2,0),0)) -> 0 | AP23: =AI23-AO23 -> 340622.03 | AR23: =IF($B$10="3BR_H", INDEX('ns-combined'!$C:$BH,MATCH($L23,'ns-combined'!$B:$B,0),MATCH(Council_Area,'ns-combined'!$C$1:$BH$1,0))*1000, INDEX('s-combined'!$C:$BH,MATCH($L23,'s-combined'!$B:$B,0),MATCH(Council_Area,'s-combined'!$C$1:$BH$1,0))*1000) -> 550000 | AS23: =AS22+$AS$3 -> 24150 | AT23: 0 | AU23: =SUM($B$28:$B$29)*AR23 -> 11000 | AV23: =AR23*$B$15/4 -> 1581.25 | AW23: =SUM($AV$3:AV23) -> 30791.25 | AX23: =AR23-AS23-AU23-AW23 -> 484058.75 | AY23: =$B$36*V23 -> 1800 | AZ23: =SUM(AY23:AY23)*4/AR23 -> 0.013090909 | BA23: =SUM(AY23:AY23)/V23 -> 0.35 | BB23: =IF(MortgageRate="Discounted",_xlfn.XLOOKUP(L23,'mortgage-rates'!$A:$A,'mortgage-rates'!$E:$E)/100,_xlfn.XLOOKUP(L23,'mortgage-rates'!$A:$A,'mortgage-rates'!$D:$D)/100) -> 0.0711 | BC23: =BC22-BF22 -> 334867.27 | BD23: =IF($B$16*12/3-Q23+1>0,-PMT($BB23/4,$B$16*12/3-Q23+1,BC23),0) -> 7876.1074 | BE23: =BC23*($BB23/4) -> 5952.2658 | BF23: =BD23-BE23 -> 1923.8416 | BG23: =AT23+AY23+BD23 -> 9676.1074 | BH23: =INDEX(cpi!B:B,MATCH($L23,cpi!A:A)) -> 98.4 | BI23: =100*BH23/BH$3 -> 116.31206 | BJ23: =100*AC23/AC$3 -> 115.17382 | BK23: =100*AD23/AD$3 -> 125.49816 | BL23: =BJ23*GlobalPortfolio+BK23*AusPortfolio -> 118.27112 | BM23: =100*AE23/$AE$3 -> 205.35274 | BN23: =100*AR23/AR$3 -> 119.56522 | BO23: =100*AX23/AX$3 -> 107.9699
A24: When buying the house (cashflow costs) | L24: =DATE(YEAR(L23),MONTH(L23)+3,1) -> 40695 | M24: =AP24 -> 342345.35 | N24: =AX24-BC24 -> 197240.32 | O24: =M24/N24 -> 1.7356763 | P24: =X24/BG24 -> 0.55285277 | Q24: 22 | R24: =EOMONTH(L24,0)-EOMONTH(L24,-3) -> 91 | T24: =IF($B$10="3BR_H", INDEX('3BR_H-combined'!$C:$BH,MATCH($L24,'3BR_H-combined'!$B:$B,0),MATCH(Council_Area,'3BR_H-combined'!$C$1:$BH$1,0)), INDEX('2BR_F-combined'!$C:$BH,MATCH($L24,'2BR_F-combined'!$B:$B,0),MATCH(Council_Area,'2BR_F-combined'!$C$1:$BH$1,0))) -> 400 | U24: =IF(MOD(Q24,4)=1,T24,U23) -> 400 | V24: =U24*(R24)/7 -> 5200 | W24: =$B$53/4*BH24/_xlfn.XLOOKUP(Q_end,cpi!A:A,cpi!B:B) -> 137.24948 | X24: =V24+W24 -> 5337.2495 | Y24: =BG24-X24 -> 4316.7664 | Z24: =Y24*$B$47 -> 1381.3653 | AA24: =(Y24+Z24)*eff_invest -> 5698.1317 | AB24: =AA24*(_xlfn.XLOOKUP(Q_end,cpi!A:A,cpi!B:B)/BH24) -> 8303.3198 | AC24: {=INDEX('msci-indices'!C:C,MATCH($L24,'msci-indices'!$B:$B)-2)} -> 912.83804 | AD24: {=INDEX('msci-indices'!D:D,MATCH($L24,'msci-indices'!$B:$B)-2)} -> 924.58629 | AE24: =AI23+AA24 -> 346320.16 | AF24: {=INDEX('msci-indices'!C:C,MATCH($L24,'msci-indices'!$B:$B)+1)} -> 915.80494 | AG24: {=INDEX('msci-indices'!D:D,MATCH($L24,'msci-indices'!$B:$B)+1)} -> 884.12823 | AH24: =(InvestFees/4)*AE24 -> 216.4501 | AI24: =((AF24/AC24)*GlobalPortfolio+(AG24/AD24)*AusPortfolio)*AE24-AH24 -> 342345.35 | AJ24: =AJ23+AA24 -> 295827.58 | AK24: =AI24-AJ24 -> 46517.767 | AL24: =AJ24*(_xlfn.XLOOKUP(Q_end,cpi!A:A,cpi!B:B)/BH24) -> 431080.07 | AM24: {=SUMPRODUCT($AA$3:AA24,_xlfn.SORTBY($BH$3:BH24,_xlfn.SEQUENCE(ROWS($BH$3:BH24)),-1)/$BH$3)} -> 335246.28 | AN24: =AI24-AM24 -> 7099.0674 | AO24: =IF($B$49="Real gains",MAX($B$50*AN24,0),IF($B$49="Discounted nominal gains",MAX($B$50*AK24/2,0),0)) -> 0 | AP24: =AI24-AO24 -> 342345.35 | AR24: =IF($B$10="3BR_H", INDEX('ns-combined'!$C:$BH,MATCH($L24,'ns-combined'!$B:$B,0),MATCH(Council_Area,'ns-combined'!$C$1:$BH$1,0))*1000, INDEX('s-combined'!$C:$BH,MATCH($L24,'s-combined'!$B:$B,0),MATCH(Council_Area,'s-combined'!$C$1:$BH$1,0))*1000) -> 600000 | AS24: =AS23+$AS$3 -> 25300 | AT24: 0 | AU24: =SUM($B$28:$B$29)*AR24 -> 12000 | AV24: =AR24*$B$15/4 -> 1725 | AW24: =SUM($AV$3:AV24) -> 32516.25 | AX24: =AR24-AS24-AU24-AW24 -> 530183.75 | AY24: =$B$36*V24 -> 1820 | AZ24: =SUM(AY24:AY24)*4/AR24 -> 0.012133333 | BA24: =SUM(AY24:AY24)/V24 -> 0.35 | BB24: =IF(MortgageRate="Discounted",_xlfn.XLOOKUP(L24,'mortgage-rates'!$A:$A,'mortgage-rates'!$E:$E)/100,_xlfn.XLOOKUP(L24,'mortgage-rates'!$A:$A,'mortgage-rates'!$D:$D)/100) -> 0.0704 | BC24: =BC23-BF23 -> 332943.43 | BD24: =IF($B$16*12/3-Q24+1>0,-PMT($BB24/4,$B$16*12/3-Q24+1,BC24),0) -> 7834.0159 | BE24: =BC24*($BB24/4) -> 5859.8044 | BF24: =BD24-BE24 -> 1974.2115 | BG24: =AT24+AY24+BD24 -> 9654.0159 | BH24: =INDEX(cpi!B:B,MATCH($L24,cpi!A:A)) -> 99.3 | BI24: =100*BH24/BH$3 -> 117.37589 | BJ24: =100*AC24/AC$3 -> 120.92498 | BK24: =100*AD24/AD$3 -> 129.68345 | BL24: =BJ24*GlobalPortfolio+BK24*AusPortfolio -> 123.55252 | BM24: =100*AE24/$AE$3 -> 218.04443 | BN24: =100*AR24/AR$3 -> 130.43478 | BO24: =100*AX24/AX$3 -> 118.25814
A25: Real estate agent commissions (purchase) | B25: 0.015 | C25: 0.015 | L25: =DATE(YEAR(L24),MONTH(L24)+3,1) -> 40787 | M25: =AP25 -> 293257.75 | N25: =AX25-BC25 -> 147483.28 | O25: =M25/N25 -> 1.9884135 | P25: =X25/BG25 -> 0.55801697 | Q25: 23 | R25: =EOMONTH(L25,0)-EOMONTH(L25,-3) -> 92 | T25: =IF($B$10="3BR_H", INDEX('3BR_H-combined'!$C:$BH,MATCH($L25,'3BR_H-combined'!$B:$B,0),MATCH(Council_Area,'3BR_H-combined'!$C$1:$BH$1,0)), INDEX('2BR_F-combined'!$C:$BH,MATCH($L25,'2BR_F-combined'!$B:$B,0),MATCH(Council_Area,'2BR_F-combined'!$C$1:$BH$1,0))) -> 400 | U25: =IF(MOD(Q25,4)=1,T25,U24) -> 400 | V25: =U25*(R25)/7 -> 5257.1429 | W25: =$B$53/4*BH25/_xlfn.XLOOKUP(Q_end,cpi!A:A,cpi!B:B) -> 137.80235 | X25: =V25+W25 -> 5394.9452 | Y25: =BG25-X25 -> 4273.1213 | Z25: =Y25*$B$47 -> 1367.3988 | AA25: =(Y25+Z25)*eff_invest -> 5640.5202 | AB25: =AA25*(_xlfn.XLOOKUP(Q_end,cpi!A:A,cpi!B:B)/BH25) -> 8186.3919 | AC25: {=INDEX('msci-indices'!C:C,MATCH($L25,'msci-indices'!$B:$B)-2)} -> 915.80494 | AD25: {=INDEX('msci-indices'!D:D,MATCH($L25,'msci-indices'!$B:$B)-2)} -> 884.12823 | AE25: =AI24+AA25 -> 347985.87 | AF25: {=INDEX('msci-indices'!C:C,MATCH($L25,'msci-indices'!$B:$B)+1)} -> 758.74852 | AG25: {=INDEX('msci-indices'!D:D,MATCH($L25,'msci-indices'!$B:$B)+1)} -> 776.26676 | AH25: =(InvestFees/4)*AE25 -> 217.49117 | AI25: =((AF25/AC25)*GlobalPortfolio+(AG25/AD25)*AusPortfolio)*AE25-AH25 -> 293257.75 | AJ25: =AJ24+AA25 -> 301468.1 | AK25: =AI25-AJ25 -> -8210.3581 | AL25: =AJ25*(_xlfn.XLOOKUP(Q_end,cpi!A:A,cpi!B:B)/BH25) -> 437536.96 | AM25: {=SUMPRODUCT($AA$3:AA25,_xlfn.SORTBY($BH$3:BH25,_xlfn.SEQUENCE(ROWS($BH$3:BH25)),-1)/$BH$3)} -> 342738.06 | AN25: =AI25-AM25 -> -49480.309 | AO25: =IF($B$49="Real gains",MAX($B$50*AN25,0),IF($B$49="Discounted nominal gains",MAX($B$50*AK25/2,0),0)) -> 0 | AP25: =AI25-AO25 -> 293257.75 | AR25: =IF($B$10="3BR_H", INDEX('ns-combined'!$C:$BH,MATCH($L25,'ns-combined'!$B:$B,0),MATCH(Council_Area,'ns-combined'!$C$1:$BH$1,0))*1000, INDEX('s-combined'!$C:$BH,MATCH($L25,'s-combined'!$B:$B,0),MATCH(Council_Area,'s-combined'!$C$1:$BH$1,0))*1000) -> 550000 | AS25: =AS24+$AS$3 -> 26450 | AT25: 0 | AU25: =SUM($B$28:$B$29)*AR25 -> 11000 | AV25: =AR25*$B$15/4 -> 1581.25 | AW25: =SUM($AV$3:AV25) -> 34097.5 | AX25: =AR25-AS25-AU25-AW25 -> 478452.5 | AY25: =$B$36*V25 -> 1840 | AZ25: =SUM(AY25:AY25)*4/AR25 -> 0.013381818 | BA25: =SUM(AY25:AY25)/V25 -> 0.35 | BB25: =IF(MortgageRate="Discounted",_xlfn.XLOOKUP(L25,'mortgage-rates'!$A:$A,'mortgage-rates'!$E:$E)/100,_xlfn.XLOOKUP(L25,'mortgage-rates'!$A:$A,'mortgage-rates'!$D:$D)/100) -> 0.0703 | BC25: =BC24-BF24 -> 330969.22 | BD25: =IF($B$16*12/3-Q25+1>0,-PMT($BB25/4,$B$16*12/3-Q25+1,BC25),0) -> 7828.0665 | BE25: =BC25*($BB25/4) -> 5816.784 | BF25: =BD25-BE25 -> 2011.2825 | BG25: =AT25+AY25+BD25 -> 9668.0665 | BH25: =INDEX(cpi!B:B,MATCH($L25,cpi!A:A)) -> 99.7 | BI25: =100*BH25/BH$3 -> 117.8487 | BJ25: =100*AC25/AC$3 -> 121.31801 | BK25: =100*AD25/AD$3 -> 124.00876 | BL25: =BJ25*GlobalPortfolio+BK25*AusPortfolio -> 122.12524 | BM25: =100*AE25/$AE$3 -> 219.09317 | BN25: =100*AR25/AR$3 -> 119.56522 | BO25: =100*AX25/AX$3 -> 106.71942
A26: Stamp duty (purchase) | B26: =(8990+(4.5/100)*(AR3-300000))/AR3 -> 0.035195652 | L26: =DATE(YEAR(L25),MONTH(L25)+3,1) -> 40878 | M26: =AP26 -> 316011.3 | N26: =AX26-BC26 -> 117449.56 | O26: =M26/N26 -> 2.6906128 | P26: =X26/BG26 -> 0.57506581 | Q26: 24 | R26: =EOMONTH(L26,0)-EOMONTH(L26,-3) -> 92 | T26: =IF($B$10="3BR_H", INDEX('3BR_H-combined'!$C:$BH,MATCH($L26,'3BR_H-combined'!$B:$B,0),MATCH(Council_Area,'3BR_H-combined'!$C$1:$BH$1,0)), INDEX('2BR_F-combined'!$C:$BH,MATCH($L26,'2BR_F-combined'!$B:$B,0),MATCH(Council_Area,'2BR_F-combined'!$C$1:$BH$1,0))) -> 420 | U26: =IF(MOD(Q26,4)=1,T26,U25) -> 400 | V26: =U26*(R26)/7 -> 5257.1429 | W26: =$B$53/4*BH26/_xlfn.XLOOKUP(Q_end,cpi!A:A,cpi!B:B) -> 138.07878 | X26: =V26+W26 -> 5395.2216 | Y26: =BG26-X26 -> 3986.6988 | Z26: =Y26*$B$47 -> 1275.7436 | AA26: =(Y26+Z26)*eff_invest -> 5262.4424 | AB26: =AA26*(_xlfn.XLOOKUP(Q_end,cpi!A:A,cpi!B:B)/BH26) -> 7622.3765 | AC26: {=INDEX('msci-indices'!C:C,MATCH($L26,'msci-indices'!$B:$B)-2)} -> 758.74852 | AD26: {=INDEX('msci-indices'!D:D,MATCH($L26,'msci-indices'!$B:$B)-2)} -> 776.26676 | AE26: =AI25+AA26 -> 298520.19 | AF26: {=INDEX('msci-indices'!C:C,MATCH($L26,'msci-indices'!$B:$B)+1)} -> 816.9754 | AG26: {=INDEX('msci-indices'!D:D,MATCH($L26,'msci-indices'!$B:$B)+1)} -> 790.49635 | AH26: =(InvestFees/4)*AE26 -> 186.57512 | AI26: =((AF26/AC26)*GlobalPortfolio+(AG26/AD26)*AusPortfolio)*AE26-AH26 -> 316011.3 | AJ26: =AJ25+AA26 -> 306730.55 | AK26: =AI26-AJ26 -> 9280.7539 | AL26: =AJ26*(_xlfn.XLOOKUP(Q_end,cpi!A:A,cpi!B:B)/BH26) -> 444283.38 | AM26: {=SUMPRODUCT($AA$3:AA26,_xlfn.SORTBY($BH$3:BH26,_xlfn.SEQUENCE(ROWS($BH$3:BH26)),-1)/$BH$3)} -> 349530.4 | AN26: =AI26-AM26 -> -33519.096 | AO26: =IF($B$49="Real gains",MAX($B$50*AN26,0),IF($B$49="Discounted nominal gains",MAX($B$50*AK26/2,0),0)) -> 0 | AP26: =AI26-AO26 -> 316011.3 | AR26: =IF($B$10="3BR_H", INDEX('ns-combined'!$C:$BH,MATCH($L26,'ns-combined'!$B:$B,0),MATCH(Council_Area,'ns-combined'!$C$1:$BH$1,0))*1000, INDEX('s-combined'!$C:$BH,MATCH($L26,'s-combined'!$B:$B,0),MATCH(Council_Area,'s-combined'!$C$1:$BH$1,0))*1000) -> 520000 | AS26: =AS25+$AS$3 -> 27600 | AT26: 0 | AU26: =SUM($B$28:$B$29)*AR26 -> 10400 | AV26: =AR26*$B$15/4 -> 1495 | AW26: =SUM($AV$3:AV26) -> 35592.5 | AX26: =AR26-AS26-AU26-AW26 -> 446407.5 | AY26: =$B$36*V26 -> 1840 | AZ26: =SUM(AY26:AY26)*4/AR26 -> 0.014153846 | BA26: =SUM(AY26:AY26)/V26 -> 0.35 | BB26: =IF(MortgageRate="Discounted",_xlfn.XLOOKUP(L26,'mortgage-rates'!$A:$A,'mortgage-rates'!$E:$E)/100,_xlfn.XLOOKUP(L26,'mortgage-rates'!$A:$A,'mortgage-rates'!$D:$D)/100) -> 0.0654 | BC26: =BC25-BF25 -> 328957.94 | BD26: =IF($B$16*12/3-Q26+1>0,-PMT($BB26/4,$B$16*12/3-Q26+1,BC26),0) -> 7541.9204 | BE26: =BC26*($BB26/4) -> 5378.4623 | BF26: =BD26-BE26 -> 2163.4582 | BG26: =AT26+AY26+BD26 -> 9381.9204 | BH26: =INDEX(cpi!B:B,MATCH($L26,cpi!A:A)) -> 99.9 | BI26: =100*BH26/BH$3 -> 118.08511 | BJ26: =100*AC26/AC$3 -> 100.51252 | BK26: =100*AD26/AD$3 -> 108.88 | BL26: =BJ26*GlobalPortfolio+BK26*AusPortfolio -> 103.02276 | BM26: =100*AE26/$AE$3 -> 187.94939 | BN26: =100*AR26/AR$3 -> 113.04348 | BO26: =100*AX26/AX$3 -> 99.571742
A27: When selling the house (derating of home value) | L27: =DATE(YEAR(L26),MONTH(L26)+3,1) -> 40969 | M27: =AP27 -> 355912.97 | N27: =AX27-BC27 -> 183412.52 | O27: =M27/N27 -> 1.9405053 | P27: =X27/BG27 -> 0.58614696 | Q27: 25 | R27: =EOMONTH(L27,0)-EOMONTH(L27,-3) -> 91 | T27: =IF($B$10="3BR_H", INDEX('3BR_H-combined'!$C:$BH,MATCH($L27,'3BR_H-combined'!$B:$B,0),MATCH(Council_Area,'3BR_H-combined'!$C$1:$BH$1,0)), INDEX('2BR_F-combined'!$C:$BH,MATCH($L27,'2BR_F-combined'!$B:$B,0),MATCH(Council_Area,'2BR_F-combined'!$C$1:$BH$1,0))) -> 420 | U27: =IF(MOD(Q27,4)=1,T27,U26) -> 420 | V27: =U27*(R27)/7 -> 5460 | W27: =$B$53/4*BH27/_xlfn.XLOOKUP(Q_end,cpi!A:A,cpi!B:B) -> 138.07878 | X27: =V27+W27 -> 5598.0788 | Y27: =BG27-X27 -> 3952.5615 | Z27: =Y27*$B$47 -> 1264.8197 | AA27: =(Y27+Z27)*eff_invest -> 5217.3812 | AB27: =AA27*(_xlfn.XLOOKUP(Q_end,cpi!A:A,cpi!B:B)/BH27) -> 7557.1076 | AC27: {=INDEX('msci-indices'!C:C,MATCH($L27,'msci-indices'!$B:$B)-2)} -> 816.9754 | AD27: {=INDEX('msci-indices'!D:D,MATCH($L27,'msci-indices'!$B:$B)-2)} -> 790.49635 | AE27: =AI26+AA27 -> 321228.68 | AF27: {=INDEX('msci-indices'!C:C,MATCH($L27,'msci-indices'!$B:$B)+1)} -> 913.58723 | AG27: {=INDEX('msci-indices'!D:D,MATCH($L27,'msci-indices'!$B:$B)+1)} -> 858.5317 | AH27: =(InvestFees/4)*AE27 -> 200.76793 | AI27: =((AF27/AC27)*GlobalPortfolio+(AG27/AD27)*AusPortfolio)*AE27-AH27 -> 355912.97 | AJ27: =AJ26+AA27 -> 311947.93 | AK27: =AI27-AJ27 -> 43965.046 | AL27: =AJ27*(_xlfn.XLOOKUP(Q_end,cpi!A:A,cpi!B:B)/BH27) -> 451840.49 | AM27: {=SUMPRODUCT($AA$3:AA27,_xlfn.SORTBY($BH$3:BH27,_xlfn.SEQUENCE(ROWS($BH$3:BH27)),-1)/$BH$3)} -> 355924.25 | AN27: =AI27-AM27 -> -11.275898 | AO27: =IF($B$49="Real gains",MAX($B$50*AN27,0),IF($B$49="Discounted nominal gains",MAX($B$50*AK27/2,0),0)) -> 0 | AP27: =AI27-AO27 -> 355912.97 | AR27: =IF($B$10="3BR_H", INDEX('ns-combined'!$C:$BH,MATCH($L27,'ns-combined'!$B:$B,0),MATCH(Council_Area,'ns-combined'!$C$1:$BH$1,0))*1000, INDEX('s-combined'!$C:$BH,MATCH($L27,'s-combined'!$B:$B,0),MATCH(Council_Area,'s-combined'!$C$1:$BH$1,0))*1000) -> 588000 | AS27: =AS26+$AS$3 -> 28750 | AT27: 0 | AU27: =SUM($B$28:$B$29)*AR27 -> 11760 | AV27: =AR27*$B$15/4 -> 1690.5 | AW27: =SUM($AV$3:AV27) -> 37283 | AX27: =AR27-AS27-AU27-AW27 -> 510207 | AY27: =$B$36*V27 -> 1911 | AZ27: =SUM(AY27:AY27)*4/AR27 -> 0.013 | BA27: =SUM(AY27:AY27)/V27 -> 0.35 | BB27: =IF(MortgageRate="Discounted",_xlfn.XLOOKUP(L27,'mortgage-rates'!$A:$A,'mortgage-rates'!$E:$E)/100,_xlfn.XLOOKUP(L27,'mortgage-rates'!$A:$A,'mortgage-rates'!$D:$D)/100) -> 0.0671 | BC27: =BC26-BF26 -> 326794.48 | BD27: =IF($B$16*12/3-Q27+1>0,-PMT($BB27/4,$B$16*12/3-Q27+1,BC27),0) -> 7639.6403 | BE27: =BC27*($BB27/4) -> 5481.9774 | BF27: =BD27-BE27 -> 2157.6629 | BG27: =AT27+AY27+BD27 -> 9550.6403 | BH27: =INDEX(cpi!B:B,MATCH($L27,cpi!A:A)) -> 99.9 | BI27: =100*BH27/BH$3 -> 118.08511 | BJ27: =100*AC27/AC$3 -> 108.22592 | BK27: =100*AD27/AD$3 -> 110.87586 | BL27: =BJ27*GlobalPortfolio+BK27*AusPortfolio -> 109.0209 | BM27: =100*AE27/$AE$3 -> 202.24674 | BN27: =100*AR27/AR$3 -> 127.82609 | BO27: =100*AX27/AX$3 -> 113.8023
A28: Real estate agent commissions (sale) | B28: 0.015 | C28: 0.015 | L28: =DATE(YEAR(L27),MONTH(L27)+3,1) -> 41061 | M28: =AP28 -> 341539.28 | N28: =AX28-BC28 -> 187615.31 | O28: =M28/N28 -> 1.8204233 | P28: =X28/BG28 -> 0.60705542 | Q28: 26 | R28: =EOMONTH(L28,0)-EOMONTH(L28,-3) -> 91 | T28: =IF($B$10="3BR_H", INDEX('3BR_H-combined'!$C:$BH,MATCH($L28,'3BR_H-combined'!$B:$B,0),MATCH(Council_Area,'3BR_H-combined'!$C$1:$BH$1,0)), INDEX('2BR_F-combined'!$C:$BH,MATCH($L28,'2BR_F-combined'!$B:$B,0),MATCH(Council_Area,'2BR_F-combined'!$C$1:$BH$1,0))) -> 420 | U28: =IF(MOD(Q28,4)=1,T28,U27) -> 420 | V28: =U28*(R28)/7 -> 5460 | W28: =$B$53/4*BH28/_xlfn.XLOOKUP(Q_end,cpi!A:A,cpi!B:B) -> 138.90809 | X28: =V28+W28 -> 5598.9081 | Y28: =BG28-X28 -> 3624.1511 | Z28: =Y28*$B$47 -> 1159.7284 | AA28: =(Y28+Z28)*eff_invest -> 4783.8795 | AB28: =AA28*(_xlfn.XLOOKUP(Q_end,cpi!A:A,cpi!B:B)/BH28) -> 6887.8345 | AC28: {=INDEX('msci-indices'!C:C,MATCH($L28,'msci-indices'!$B:$B)-2)} -> 913.58723 | AD28: {=INDEX('msci-indices'!D:D,MATCH($L28,'msci-indices'!$B:$B)-2)} -> 858.5317 | AE28: =AI27+AA28 -> 360696.85 | AF28: {=INDEX('msci-indices'!C:C,MATCH($L28,'msci-indices'!$B:$B)+1)} -> 865.80589 | AG28: {=INDEX('msci-indices'!D:D,MATCH($L28,'msci-indices'!$B:$B)+1)} -> 813.09506 | AH28: =(InvestFees/4)*AE28 -> 225.43553 | AI28: =((AF28/AC28)*GlobalPortfolio+(AG28/AD28)*AusPortfolio)*AE28-AH28 -> 341539.28 | AJ28: =AJ27+AA28 -> 316731.81 | AK28: =AI28-AJ28 -> 24807.478 | AL28: =AJ28*(_xlfn.XLOOKUP(Q_end,cpi!A:A,cpi!B:B)/BH28) -> 456030.77 | AM28: {=SUMPRODUCT($AA$3:AA28,_xlfn.SORTBY($BH$3:BH28,_xlfn.SEQUENCE(ROWS($BH$3:BH28)),-1)/$BH$3)} -> 362998.29 | AN28: =AI28-AM28 -> -21459.006 | AO28: =IF($B$49="Real gains",MAX($B$50*AN28,0),IF($B$49="Discounted nominal gains",MAX($B$50*AK28/2,0),0)) -> 0 | AP28: =AI28-AO28 -> 341539.28 | AR28: =IF($B$10="3BR_H", INDEX('ns-combined'!$C:$BH,MATCH($L28,'ns-combined'!$B:$B,0),MATCH(Council_Area,'ns-combined'!$C$1:$BH$1,0))*1000, INDEX('s-combined'!$C:$BH,MATCH($L28,'s-combined'!$B:$B,0),MATCH(Council_Area,'s-combined'!$C$1:$BH$1,0))*1000) -> 593000 | AS28: =AS27+$AS$3 -> 29900 | AT28: 0 | AU28: =SUM($B$28:$B$29)*AR28 -> 11860 | AV28: =AR28*$B$15/4 -> 1704.875 | AW28: =SUM($AV$3:AV28) -> 38987.875 | AX28: =AR28-AS28-AU28-AW28 -> 512252.12 | AY28: =$B$36*V28 -> 1911 | AZ28: =SUM(AY28:AY28)*4/AR28 -> 0.012890388 | BA28: =SUM(AY28:AY28)/V28 -> 0.35 | BB28: =IF(MortgageRate="Discounted",_xlfn.XLOOKUP(L28,'mortgage-rates'!$A:$A,'mortgage-rates'!$E:$E)/100,_xlfn.XLOOKUP(L28,'mortgage-rates'!$A:$A,'mortgage-rates'!$D:$D)/100) -> 0.0613 | BC28: =BC27-BF27 -> 324636.82 | BD28: =IF($B$16*12/3-Q28+1>0,-PMT($BB28/4,$B$16*12/3-Q28+1,BC28),0) -> 7312.0592 | BE28: =BC28*($BB28/4) -> 4975.0592 | BF28: =BD28-BE28 -> 2337 | BG28: =AT28+AY28+BD28 -> 9223.0592 | BH28: =INDEX(cpi!B:B,MATCH($L28,cpi!A:A)) -> 100.5 | BI28: =100*BH28/BH$3 -> 118.79433 | BJ28: =100*AC28/AC$3 -> 121.02423 | BK28: =100*AD28/AD$3 -> 120.41857 | BL28: =BJ28*GlobalPortfolio+BK28*AusPortfolio -> 120.84253 | BM28: =100*AE28/$AE$3 -> 227.09605 | BN28: =100*AR28/AR$3 -> 128.91304 | BO28: =100*AX28/AX$3 -> 114.25847
A29: Other selling costs | B29: 0.005 | C29: 0.005 | L29: =DATE(YEAR(L28),MONTH(L28)+3,1) -> 41153 | M29: =AP29 -> 371251.95 | N29: =AX29-BC29 -> 162669.31 | O29: =M29/N29 -> 2.2822495 | P29: =X29/BG29 -> 0.61416604 | Q29: 27 | R29: =EOMONTH(L29,0)-EOMONTH(L29,-3) -> 92 | T29: =IF($B$10="3BR_H", INDEX('3BR_H-combined'!$C:$BH,MATCH($L29,'3BR_H-combined'!$B:$B,0),MATCH(Council_Area,'3BR_H-combined'!$C$1:$BH$1,0)), INDEX('2BR_F-combined'!$C:$BH,MATCH($L29,'2BR_F-combined'!$B:$B,0),MATCH(Council_Area,'2BR_F-combined'!$C$1:$BH$1,0))) -> 420 | U29: =IF(MOD(Q29,4)=1,T29,U28) -> 420 | V29: =U29*(R29)/7 -> 5520 | W29: =$B$53/4*BH29/_xlfn.XLOOKUP(Q_end,cpi!A:A,cpi!B:B) -> 140.42847 | X29: =V29+W29 -> 5660.4285 | Y29: =BG29-X29 -> 3556.0181 | Z29: =Y29*$B$47 -> 1137.9258 | AA29: =(Y29+Z29)*eff_invest -> 4693.9439 | AB29: =AA29*(_xlfn.XLOOKUP(Q_end,cpi!A:A,cpi!B:B)/BH29) -> 6685.1741 | AC29: {=INDEX('msci-indices'!C:C,MATCH($L29,'msci-indices'!$B:$B)-2)} -> 865.80589 | AD29: {=INDEX('msci-indices'!D:D,MATCH($L29,'msci-indices'!$B:$B)-2)} -> 813.09506 | AE29: =AI28+AA29 -> 346233.23 | AF29: {=INDEX('msci-indices'!C:C,MATCH($L29,'msci-indices'!$B:$B)+1)} -> 923.8995 | AG29: {=INDEX('msci-indices'!D:D,MATCH($L29,'msci-indices'!$B:$B)+1)} -> 883.33647 | AH29: =(InvestFees/4)*AE29 -> 216.39577 | AI29: =((AF29/AC29)*GlobalPortfolio+(AG29/AD29)*AusPortfolio)*AE29-AH29 -> 371251.95 | AJ29: =AJ28+AA29 -> 321425.75 | AK29: =AI29-AJ29 -> 49826.195 | AL29: =AJ29*(_xlfn.XLOOKUP(Q_end,cpi!A:A,cpi!B:B)/BH29) -> 457778.6 | AM29: {=SUMPRODUCT($AA$3:AA29,_xlfn.SORTBY($BH$3:BH29,_xlfn.SEQUENCE(ROWS($BH$3:BH29)),-1)/$BH$3)} -> 370945.74 | AN29: =AI29-AM29 -> 306.20472 | AO29: =IF($B$49="Real gains",MAX($B$50*AN29,0),IF($B$49="Discounted nominal gains",MAX($B$50*AK29/2,0),0)) -> 0 | AP29: =AI29-AO29 -> 371251.95 | AR29: =IF($B$10="3BR_H", INDEX('ns-combined'!$C:$BH,MATCH($L29,'ns-combined'!$B:$B,0),MATCH(Council_Area,'ns-combined'!$C$1:$BH$1,0))*1000, INDEX('s-combined'!$C:$BH,MATCH($L29,'s-combined'!$B:$B,0),MATCH(Council_Area,'s-combined'!$C$1:$BH$1,0))*1000) -> 568000 | AS29: =AS28+$AS$3 -> 31050 | AT29: 0 | AU29: =SUM($B$28:$B$29)*AR29 -> 11360 | AV29: =AR29*$B$15/4 -> 1633 | AW29: =SUM($AV$3:AV29) -> 40620.875 | AX29: =AR29-AS29-AU29-AW29 -> 484969.12 | AY29: =$B$36*V29 -> 1932 | AZ29: =SUM(AY29:AY29)*4/AR29 -> 0.013605634 | BA29: =SUM(AY29:AY29)/V29 -> 0.35 | BB29: =IF(MortgageRate="Discounted",_xlfn.XLOOKUP(L29,'mortgage-rates'!$A:$A,'mortgage-rates'!$E:$E)/100,_xlfn.XLOOKUP(L29,'mortgage-rates'!$A:$A,'mortgage-rates'!$D:$D)/100) -> 0.0608 | BC29: =BC28-BF28 -> 322299.82 | BD29: =IF($B$16*12/3-Q29+1>0,-PMT($BB29/4,$B$16*12/3-Q29+1,BC29),0) -> 7284.4466 | BE29: =BC29*($BB29/4) -> 4898.9572 | BF29: =BD29-BE29 -> 2385.4894 | BG29: =AT29+AY29+BD29 -> 9216.4466 | BH29: =INDEX(cpi!B:B,MATCH($L29,cpi!A:A)) -> 101.6 | BI29: =100*BH29/BH$3 -> 120.09456 | BJ29: =100*AC29/AC$3 -> 114.69457 | BK29: =100*AD29/AD$3 -> 114.04558 | BL29: =BJ29*GlobalPortfolio+BK29*AusPortfolio -> 114.49987 | BM29: =100*AE29/$AE$3 -> 217.9897 | BN29: =100*AR29/AR$3 -> 123.47826 | BO29: =100*AX29/AX$3 -> 108.17296
L30: =DATE(YEAR(L29),MONTH(L29)+3,1) -> 41244 | M30: =AP30 -> 390027.83 | N30: =AX30-BC30 -> 213082.3 | O30: =M30/N30 -> 1.8304093 | P30: =X30/BG30 -> 0.62901395 | Q30: 28 | R30: =EOMONTH(L30,0)-EOMONTH(L30,-3) -> 92 | T30: =IF($B$10="3BR_H", INDEX('3BR_H-combined'!$C:$BH,MATCH($L30,'3BR_H-combined'!$B:$B,0),MATCH(Council_Area,'3BR_H-combined'!$C$1:$BH$1,0)), INDEX('2BR_F-combined'!$C:$BH,MATCH($L30,'2BR_F-combined'!$B:$B,0),MATCH(Council_Area,'2BR_F-combined'!$C$1:$BH$1,0))) -> 420 | U30: =IF(MOD(Q30,4)=1,T30,U29) -> 420 | V30: =U30*(R30)/7 -> 5520 | W30: =$B$53/4*BH30/_xlfn.XLOOKUP(Q_end,cpi!A:A,cpi!B:B) -> 140.98134 | X30: =V30+W30 -> 5660.9813 | Y30: =BG30-X30 -> 3338.7894 | Z30: =Y30*$B$47 -> 1068.4126 | AA30: =(Y30+Z30)*eff_invest -> 4407.202 | AB30: =AA30*(_xlfn.XLOOKUP(Q_end,cpi!A:A,cpi!B:B)/BH30) -> 6252.1778 | AC30: {=INDEX('msci-indices'!C:C,MATCH($L30,'msci-indices'!$B:$B)-2)} -> 923.8995 | AD30: {=INDEX('msci-indices'!D:D,MATCH($L30,'msci-indices'!$B:$B)-2)} -> 883.33647 | AE30: =AI29+AA30 -> 375659.15 | AF30: {=INDEX('msci-indices'!C:C,MATCH($L30,'msci-indices'!$B:$B)+1)} -> 948.15111 | AG30: {=INDEX('msci-indices'!D:D,MATCH($L30,'msci-indices'!$B:$B)+1)} -> 943.69729 | AH30: =(InvestFees/4)*AE30 -> 234.78697 | AI30: =((AF30/AC30)*GlobalPortfolio+(AG30/AD30)*AusPortfolio)*AE30-AH30 -> 390027.83 | AJ30: =AJ29+AA30 -> 325832.95 | AK30: =AI30-AJ30 -> 64194.876 | AL30: =AJ30*(_xlfn.XLOOKUP(Q_end,cpi!A:A,cpi!B:B)/BH30) -> 462235.57 | AM30: {=SUMPRODUCT($AA$3:AA30,_xlfn.SORTBY($BH$3:BH30,_xlfn.SEQUENCE(ROWS($BH$3:BH30)),-1)/$BH$3)} -> 377362.81 | AN30: =AI30-AM30 -> 12665.02 | AO30: =IF($B$49="Real gains",MAX($B$50*AN30,0),IF($B$49="Discounted nominal gains",MAX($B$50*AK30/2,0),0)) -> 0 | AP30: =AI30-AO30 -> 390027.83 | AR30: =IF($B$10="3BR_H", INDEX('ns-combined'!$C:$BH,MATCH($L30,'ns-combined'!$B:$B,0),MATCH(Council_Area,'ns-combined'!$C$1:$BH$1,0))*1000, INDEX('s-combined'!$C:$BH,MATCH($L30,'s-combined'!$B:$B,0),MATCH(Council_Area,'s-combined'!$C$1:$BH$1,0))*1000) -> 620000 | AS30: =AS29+$AS$3 -> 32200 | AT30: 0 | AU30: =SUM($B$28:$B$29)*AR30 -> 12400 | AV30: =AR30*$B$15/4 -> 1782.5 | AW30: =SUM($AV$3:AV30) -> 42403.375 | AX30: =AR30-AS30-AU30-AW30 -> 532996.62 | AY30: =$B$36*V30 -> 1932 | AZ30: =SUM(AY30:AY30)*4/AR30 -> 0.012464516 | BA30: =SUM(AY30:AY30)/V30 -> 0.35 | BB30: =IF(MortgageRate="Discounted",_xlfn.XLOOKUP(L30,'mortgage-rates'!$A:$A,'mortgage-rates'!$E:$E)/100,_xlfn.XLOOKUP(L30,'mortgage-rates'!$A:$A,'mortgage-rates'!$D:$D)/100) -> 0.0568 | BC30: =BC29-BF29 -> 319914.33 | BD30: =IF($B$16*12/3-Q30+1>0,-PMT($BB30/4,$B$16*12/3-Q30+1,BC30),0) -> 7067.7708 | BE30: =BC30*($BB30/4) -> 4542.7834 | BF30: =BD30-BE30 -> 2524.9873 | BG30: =AT30+AY30+BD30 -> 8999.7708 | BH30: =INDEX(cpi!B:B,MATCH($L30,cpi!A:A)) -> 102 | BI30: =100*BH30/BH$3 -> 120.56738 | BJ30: =100*AC30/AC$3 -> 122.39031 | BK30: =100*AD30/AD$3 -> 123.89771 | BL30: =BJ30*GlobalPortfolio+BK30*AusPortfolio -> 122.84253 | BM30: =100*AE30/$AE$3 -> 236.51636 | BN30: =100*AR30/AR$3 -> 134.78261 | BO30: =100*AX30/AX$3 -> 118.88555
A31: Home ownership running costs (% of gross rents) | L31: =DATE(YEAR(L30),MONTH(L30)+3,1) -> 41334 | M31: =AP31 -> 426191.29 | N31: =AX31-BC31 -> 193132.29 | O31: =M31/N31 -> 2.2067325 | P31: =X31/BG31 -> 0.63205442 | Q31: 29 | R31: =EOMONTH(L31,0)-EOMONTH(L31,-3) -> 90 | T31: =IF($B$10="3BR_H", INDEX('3BR_H-combined'!$C:$BH,MATCH($L31,'3BR_H-combined'!$B:$B,0),MATCH(Council_Area,'3BR_H-combined'!$C$1:$BH$1,0)), INDEX('2BR_F-combined'!$C:$BH,MATCH($L31,'2BR_F-combined'!$B:$B,0),MATCH(Council_Area,'2BR_F-combined'!$C$1:$BH$1,0))) -> 430 | U31: =IF(MOD(Q31,4)=1,T31,U30) -> 430 | V31: =U31*(R31)/7 -> 5528.5714 | W31: =$B$53/4*BH31/_xlfn.XLOOKUP(Q_end,cpi!A:A,cpi!B:B) -> 141.53421 | X31: =V31+W31 -> 5670.1056 | Y31: =BG31-X31 -> 3300.8081 | Z31: =Y31*$B$47 -> 1056.2586 | AA31: =(Y31+Z31)*eff_invest -> 4357.0667 | AB31: =AA31*(_xlfn.XLOOKUP(Q_end,cpi!A:A,cpi!B:B)/BH31) -> 6156.9097 | AC31: {=INDEX('msci-indices'!C:C,MATCH($L31,'msci-indices'!$B:$B)-2)} -> 948.15111 | AD31: {=INDEX('msci-indices'!D:D,MATCH($L31,'msci-indices'!$B:$B)-2)} -> 943.69729 | AE31: =AI30+AA31 -> 394384.9 | AF31: {=INDEX('msci-indices'!C:C,MATCH($L31,'msci-indices'!$B:$B)+1)} -> 1024.7053 | AG31: {=INDEX('msci-indices'!D:D,MATCH($L31,'msci-indices'!$B:$B)+1)} -> 1021.5673 | AH31: =(InvestFees/4)*AE31 -> 246.49056 | AI31: =((AF31/AC31)*GlobalPortfolio+(AG31/AD31)*AusPortfolio)*AE31-AH31 -> 426191.29 | AJ31: =AJ30+AA31 -> 330190.02 | AK31: =AI31-AJ31 -> 96001.266 | AL31: =AJ31*(_xlfn.XLOOKUP(Q_end,cpi!A:A,cpi!B:B)/BH31) -> 466586.87 | AM31: {=SUMPRODUCT($AA$3:AA31,_xlfn.SORTBY($BH$3:BH31,_xlfn.SEQUENCE(ROWS($BH$3:BH31)),-1)/$BH$3)} -> 383743.92 | AN31: =AI31-AM31 -> 42447.37 | AO31: =IF($B$49="Real gains",MAX($B$50*AN31,0),IF($B$49="Discounted nominal gains",MAX($B$50*AK31/2,0),0)) -> 0 | AP31: =AI31-AO31 -> 426191.29 | AR31: =IF($B$10="3BR_H", INDEX('ns-combined'!$C:$BH,MATCH($L31,'ns-combined'!$B:$B,0),MATCH(Council_Area,'ns-combined'!$C$1:$BH$1,0))*1000, INDEX('s-combined'!$C:$BH,MATCH($L31,'s-combined'!$B:$B,0),MATCH(Council_Area,'s-combined'!$C$1:$BH$1,0))*1000) -> 600000 | AS31: =AS30+$AS$3 -> 33350 | AT31: 0 | AU31: =SUM($B$28:$B$29)*AR31 -> 12000 | AV31: =AR31*$B$15/4 -> 1725 | AW31: =SUM($AV$3:AV31) -> 44128.375 | AX31: =AR31-AS31-AU31-AW31 -> 510521.62 | AY31: =$B$36*V31 -> 1935 | AZ31: =SUM(AY31:AY31)*4/AR31 -> 0.0129 | BA31: =SUM(AY31:AY31)/V31 -> 0.35 | BB31: =IF(MortgageRate="Discounted",_xlfn.XLOOKUP(L31,'mortgage-rates'!$A:$A,'mortgage-rates'!$E:$E)/100,_xlfn.XLOOKUP(L31,'mortgage-rates'!$A:$A,'mortgage-rates'!$D:$D)/100) -> 0.0562 | BC31: =BC30-BF30 -> 317389.34 | BD31: =IF($B$16*12/3-Q31+1>0,-PMT($BB31/4,$B$16*12/3-Q31+1,BC31),0) -> 7035.9137 | BE31: =BC31*($BB31/4) -> 4459.3202 | BF31: =BD31-BE31 -> 2576.5935 | BG31: =AT31+AY31+BD31 -> 8970.9137 | BH31: =INDEX(cpi!B:B,MATCH($L31,cpi!A:A)) -> 102.4 | BI31: =100*BH31/BH$3 -> 121.04019 | BJ31: =100*AC31/AC$3 -> 125.60296 | BK31: =100*AD31/AD$3 -> 132.36398 | BL31: =BJ31*GlobalPortfolio+BK31*AusPortfolio -> 127.63126 | BM31: =100*AE31/$AE$3 -> 248.30616 | BN31: =100*AR31/AR$3 -> 130.43478 | BO31: =100*AX31/AX$3 -> 113.87248
A32: Council rates | B32: 0.07 | C32: 0.07 | L32: =DATE(YEAR(L31),MONTH(L31)+3,1) -> 41426 | M32: =AP32 -> 427558.07 | N32: =AX32-BC32 -> 222147.63 | O32: =M32/N32 -> 1.9246574 | P32: =X32/BG32 -> 0.64721459 | Q32: 30 | R32: =EOMONTH(L32,0)-EOMONTH(L32,-3) -> 91 | T32: =IF($B$10="3BR_H", INDEX('3BR_H-combined'!$C:$BH,MATCH($L32,'3BR_H-combined'!$B:$B,0),MATCH(Council_Area,'3BR_H-combined'!$C$1:$BH$1,0)), INDEX('2BR_F-combined'!$C:$BH,MATCH($L32,'2BR_F-combined'!$B:$B,0),MATCH(Council_Area,'2BR_F-combined'!$C$1:$BH$1,0))) -> 420 | U32: =IF(MOD(Q32,4)=1,T32,U31) -> 430 | V32: =U32*(R32)/7 -> 5590 | W32: =$B$53/4*BH32/_xlfn.XLOOKUP(Q_end,cpi!A:A,cpi!B:B) -> 142.22529 | X32: =V32+W32 -> 5732.2253 | Y32: =BG32-X32 -> 3124.5363 | Z32: =Y32*$B$47 -> 999.85162 | AA32: =(Y32+Z32)*eff_invest -> 4124.3879 | AB32: =AA32*(_xlfn.XLOOKUP(Q_end,cpi!A:A,cpi!B:B)/BH32) -> 5799.7953 | AC32: {=INDEX('msci-indices'!C:C,MATCH($L32,'msci-indices'!$B:$B)-2)} -> 1024.7053 | AD32: {=INDEX('msci-indices'!D:D,MATCH($L32,'msci-indices'!$B:$B)-2)} -> 1021.5673 | AE32: =AI31+AA32 -> 430315.67 | AF32: {=INDEX('msci-indices'!C:C,MATCH($L32,'msci-indices'!$B:$B)+1)} -> 1030.5184 | AG32: {=INDEX('msci-indices'!D:D,MATCH($L32,'msci-indices'!$B:$B)+1)} -> 988.35138 | AH32: =(InvestFees/4)*AE32 -> 268.9473 | AI32: =((AF32/AC32)*GlobalPortfolio+(AG32/AD32)*AusPortfolio)*AE32-AH32 -> 427558.07 | AJ32: =AJ31+AA32 -> 334314.41 | AK32: =AI32-AJ32 -> 93243.664 | AL32: =AJ32*(_xlfn.XLOOKUP(Q_end,cpi!A:A,cpi!B:B)/BH32) -> 470119.48 | AM32: {=SUMPRODUCT($AA$3:AA32,_xlfn.SORTBY($BH$3:BH32,_xlfn.SEQUENCE(ROWS($BH$3:BH32)),-1)/$BH$3)} -> 390096.41 | AN32: =AI32-AM32 -> 37461.657 | AO32: =IF($B$49="Real gains",MAX($B$50*AN32,0),IF($B$49="Discounted nominal gains",MAX($B$50*AK32/2,0),0)) -> 0 | AP32: =AI32-AO32 -> 427558.07 | AR32: =IF($B$10="3BR_H", INDEX('ns-combined'!$C:$BH,MATCH($L32,'ns-combined'!$B:$B,0),MATCH(Council_Area,'ns-combined'!$C$1:$BH$1,0))*1000, INDEX('s-combined'!$C:$BH,MATCH($L32,'s-combined'!$B:$B,0),MATCH(Council_Area,'s-combined'!$C$1:$BH$1,0))*1000) -> 630000 | AS32: =AS31+$AS$3 -> 34500 | AT32: 0 | AU32: =SUM($B$28:$B$29)*AR32 -> 12600 | AV32: =AR32*$B$15/4 -> 1811.25 | AW32: =SUM($AV$3:AV32) -> 45939.625 | AX32: =AR32-AS32-AU32-AW32 -> 536960.38 | AY32: =$B$36*V32 -> 1956.5 | AZ32: =SUM(AY32:AY32)*4/AR32 -> 0.012422222 | BA32: =SUM(AY32:AY32)/V32 -> 0.35 | BB32: =IF(MortgageRate="Discounted",_xlfn.XLOOKUP(L32,'mortgage-rates'!$A:$A,'mortgage-rates'!$E:$E)/100,_xlfn.XLOOKUP(L32,'mortgage-rates'!$A:$A,'mortgage-rates'!$D:$D)/100) -> 0.0536 | BC32: =BC31-BF31 -> 314812.75 | BD32: =IF($B$16*12/3-Q32+1>0,-PMT($BB32/4,$B$16*12/3-Q32+1,BC32),0) -> 6900.2616 | BE32: =BC32*($BB32/4) -> 4218.4908 | BF32: =BD32-BE32 -> 2681.7708 | BG32: =AT32+AY32+BD32 -> 8856.7616 | BH32: =INDEX(cpi!B:B,MATCH($L32,cpi!A:A)) -> 102.9 | BI32: =100*BH32/BH$3 -> 121.63121 | BJ32: =100*AC32/AC$3 -> 135.7442 | BK32: =100*AD32/AD$3 -> 143.28611 | BL32: =BJ32*GlobalPortfolio+BK32*AusPortfolio -> 138.00677 | BM32: =100*AE32/$AE$3 -> 270.92831 | BN32: =100*AR32/AR$3 -> 136.95652 | BO32: =100*AX32/AX$3 -> 119.76967
A33: Maintenance incl. body corporate fees | B33: 0.16 | C33: 0.16 | L33: =DATE(YEAR(L32),MONTH(L32)+3,1) -> 41518 | M33: =AP33 -> 470338.25 | N33: =AX33-BC33 -> 241410.65 | O33: =M33/N33 -> 1.9482912 | P33: =X33/BG33 -> 0.66339705 | Q33: 31 | R33: =EOMONTH(L33,0)-EOMONTH(L33,-3) -> 92 | T33: =IF($B$10="3BR_H", INDEX('3BR_H-combined'!$C:$BH,MATCH($L33,'3BR_H-combined'!$B:$B,0),MATCH(Council_Area,'3BR_H-combined'!$C$1:$BH$1,0)), INDEX('2BR_F-combined'!$C:$BH,MATCH($L33,'2BR_F-combined'!$B:$B,0),MATCH(Council_Area,'2BR_F-combined'!$C$1:$BH$1,0))) -> 430 | U33: =IF(MOD(Q33,4)=1,T33,U32) -> 430 | V33: =U33*(R33)/7 -> 5651.4286 | W33: =$B$53/4*BH33/_xlfn.XLOOKUP(Q_end,cpi!A:A,cpi!B:B) -> 143.60746 | X33: =V33+W33 -> 5795.036 | Y33: =BG33-X33 -> 2940.3602 | Z33: =Y33*$B$47 -> 940.91525 | AA33: =(Y33+Z33)*eff_invest -> 3881.2754 | AB33: =AA33*(_xlfn.XLOOKUP(Q_end,cpi!A:A,cpi!B:B)/BH33) -> 5405.3951 | AC33: {=INDEX('msci-indices'!C:C,MATCH($L33,'msci-indices'!$B:$B)-2)} -> 1030.5184 | AD33: {=INDEX('msci-indices'!D:D,MATCH($L33,'msci-indices'!$B:$B)-2)} -> 988.35138 | AE33: =AI32+AA33 -> 431439.35 | AF33: {=INDEX('msci-indices'!C:C,MATCH($L33,'msci-indices'!$B:$B)+1)} -> 1119.4371 | AG33: {=INDEX('msci-indices'!D:D,MATCH($L33,'msci-indices'!$B:$B)+1)} -> 1088.4582 | AH33: =(InvestFees/4)*AE33 -> 269.64959 | AI33: =((AF33/AC33)*GlobalPortfolio+(AG33/AD33)*AusPortfolio)*AE33-AH33 -> 470338.25 | AJ33: =AJ32+AA33 -> 338195.68 | AK33: =AI33-AJ33 -> 132142.57 | AL33: =AJ33*(_xlfn.XLOOKUP(Q_end,cpi!A:A,cpi!B:B)/BH33) -> 471000.15 | AM33: {=SUMPRODUCT($AA$3:AA33,_xlfn.SORTBY($BH$3:BH33,_xlfn.SEQUENCE(ROWS($BH$3:BH33)),-1)/$BH$3)} -> 397153.38 | AN33: =AI33-AM33 -> 73184.876 | AO33: =IF($B$49="Real gains",MAX($B$50*AN33,0),IF($B$49="Discounted nominal gains",MAX($B$50*AK33/2,0),0)) -> 0 | AP33: =AI33-AO33 -> 470338.25 | AR33: =IF($B$10="3BR_H", INDEX('ns-combined'!$C:$BH,MATCH($L33,'ns-combined'!$B:$B,0),MATCH(Council_Area,'ns-combined'!$C$1:$BH$1,0))*1000, INDEX('s-combined'!$C:$BH,MATCH($L33,'s-combined'!$B:$B,0),MATCH(Council_Area,'s-combined'!$C$1:$BH$1,0))*1000) -> 650000 | AS33: =AS32+$AS$3 -> 35650 | AT33: 0 | AU33: =SUM($B$28:$B$29)*AR33 -> 13000 | AV33: =AR33*$B$15/4 -> 1868.75 | AW33: =SUM($AV$3:AV33) -> 47808.375 | AX33: =AR33-AS33-AU33-AW33 -> 553541.62 | AY33: =$B$36*V33 -> 1978 | AZ33: =SUM(AY33:AY33)*4/AR33 -> 0.012172308 | BA33: =SUM(AY33:AY33)/V33 -> 0.35 | BB33: =IF(MortgageRate="Discounted",_xlfn.XLOOKUP(L33,'mortgage-rates'!$A:$A,'mortgage-rates'!$E:$E)/100,_xlfn.XLOOKUP(L33,'mortgage-rates'!$A:$A,'mortgage-rates'!$D:$D)/100) -> 0.0508 | BC33: =BC32-BF32 -> 312130.97 | BD33: =IF($B$16*12/3-Q33+1>0,-PMT($BB33/4,$B$16*12/3-Q33+1,BC33),0) -> 6757.3962 | BE33: =BC33*($BB33/4) -> 3964.0634 | BF33: =BD33-BE33 -> 2793.3328 | BG33: =AT33+AY33+BD33 -> 8735.3962 | BH33: =INDEX(cpi!B:B,MATCH($L33,cpi!A:A)) -> 103.9 | BI33: =100*BH33/BH$3 -> 122.81324 | BJ33: =100*AC33/AC$3 -> 136.51427 | BK33: =100*AD33/AD$3 -> 138.62721 | BL33: =BJ33*GlobalPortfolio+BK33*AusPortfolio -> 137.14815 | BM33: =100*AE33/$AE$3 -> 271.63578 | BN33: =100*AR33/AR$3 -> 141.30435 | BO33: =100*AX33/AX$3 -> 123.46814
A34: Plant depreciation | B34: 0.07 | C34: 0.07 | L34: =DATE(YEAR(L33),MONTH(L33)+3,1) -> 41609 | M34: =AP34 -> 504975.39 | N34: =AX34-BC34 -> 311538.23 | O34: =M34/N34 -> 1.6209098 | P34: =X34/BG34 -> 0.66276251 | Q34: 32 | R34: =EOMONTH(L34,0)-EOMONTH(L34,-3) -> 92 | T34: =IF($B$10="3BR_H", INDEX('3BR_H-combined'!$C:$BH,MATCH($L34,'3BR_H-combined'!$B:$B,0),MATCH(Council_Area,'3BR_H-combined'!$C$1:$BH$1,0)), INDEX('2BR_F-combined'!$C:$BH,MATCH($L34,'2BR_F-combined'!$B:$B,0),MATCH(Council_Area,'2BR_F-combined'!$C$1:$BH$1,0))) -> 440 | U34: =IF(MOD(Q34,4)=1,T34,U33) -> 430 | V34: =U34*(R34)/7 -> 5651.4286 | W34: =$B$53/4*BH34/_xlfn.XLOOKUP(Q_end,cpi!A:A,cpi!B:B) -> 144.7132 | X34: =V34+W34 -> 5796.1418 | Y34: =BG34-X34 -> 2949.2862 | Z34: =Y34*$B$47 -> 943.77159 | AA34: =(Y34+Z34)*eff_invest -> 3893.0578 | AB34: =AA34*(_xlfn.XLOOKUP(Q_end,cpi!A:A,cpi!B:B)/BH34) -> 5380.3769 | AC34: {=INDEX('msci-indices'!C:C,MATCH($L34,'msci-indices'!$B:$B)-2)} -> 1119.4371 | AD34: {=INDEX('msci-indices'!D:D,MATCH($L34,'msci-indices'!$B:$B)-2)} -> 1088.4582 | AE34: =AI33+AA34 -> 474231.31 | AF34: {=INDEX('msci-indices'!C:C,MATCH($L34,'msci-indices'!$B:$B)+1)} -> 1208.1074 | AG34: {=INDEX('msci-indices'!D:D,MATCH($L34,'msci-indices'!$B:$B)+1)} -> 1124.7671 | AH34: =(InvestFees/4)*AE34 -> 296.39457 | AI34: =((AF34/AC34)*GlobalPortfolio+(AG34/AD34)*AusPortfolio)*AE34-AH34 -> 504975.39 | AJ34: =AJ33+AA34 -> 342088.74 | AK34: =AI34-AJ34 -> 162886.65 | AL34: =AJ34*(_xlfn.XLOOKUP(Q_end,cpi!A:A,cpi!B:B)/BH34) -> 472781.67 | AM34: {=SUMPRODUCT($AA$3:AA34,_xlfn.SORTBY($BH$3:BH34,_xlfn.SEQUENCE(ROWS($BH$3:BH34)),-1)/$BH$3)} -> 403878.62 | AN34: =AI34-AM34 -> 101096.77 | AO34: =IF($B$49="Real gains",MAX($B$50*AN34,0),IF($B$49="Discounted nominal gains",MAX($B$50*AK34/2,0),0)) -> 0 | AP34: =AI34-AO34 -> 504975.39 | AR34: =IF($B$10="3BR_H", INDEX('ns-combined'!$C:$BH,MATCH($L34,'ns-combined'!$B:$B,0),MATCH(Council_Area,'ns-combined'!$C$1:$BH$1,0))*1000, INDEX('s-combined'!$C:$BH,MATCH($L34,'s-combined'!$B:$B,0),MATCH(Council_Area,'s-combined'!$C$1:$BH$1,0))*1000) -> 722000 | AS34: =AS33+$AS$3 -> 36800 | AT34: 0 | AU34: =SUM($B$28:$B$29)*AR34 -> 14440 | AV34: =AR34*$B$15/4 -> 2075.75 | AW34: =SUM($AV$3:AV34) -> 49884.125 | AX34: =AR34-AS34-AU34-AW34 -> 620875.88 | AY34: =$B$36*V34 -> 1978 | AZ34: =SUM(AY34:AY34)*4/AR34 -> 0.010958449 | BA34: =SUM(AY34:AY34)/V34 -> 0.35 | BB34: =IF(MortgageRate="Discounted",_xlfn.XLOOKUP(L34,'mortgage-rates'!$A:$A,'mortgage-rates'!$E:$E)/100,_xlfn.XLOOKUP(L34,'mortgage-rates'!$A:$A,'mortgage-rates'!$D:$D)/100) -> 0.051 | BC34: =BC33-BF33 -> 309337.64 | BD34: =IF($B$16*12/3-Q34+1>0,-PMT($BB34/4,$B$16*12/3-Q34+1,BC34),0) -> 6767.428 | BE34: =BC34*($BB34/4) -> 3944.0549 | BF34: =BD34-BE34 -> 2823.373 | BG34: =AT34+AY34+BD34 -> 8745.428 | BH34: =INDEX(cpi!B:B,MATCH($L34,cpi!A:A)) -> 104.7 | BI34: =100*BH34/BH$3 -> 123.75887 | BJ34: =100*AC34/AC$3 -> 148.29346 | BK34: =100*AD34/AD$3 -> 152.6683 | BL34: =BJ34*GlobalPortfolio+BK34*AusPortfolio -> 149.60591 | BM34: =100*AE34/$AE$3 -> 298.57775 | BN34: =100*AR34/AR$3 -> 156.95652 | BO34: =100*AX34/AX$3 -> 138.48713
A35: Other expenses | B35: 0.05 | C35: 0.05 | L35: =DATE(YEAR(L34),MONTH(L34)+3,1) -> 41699 | M35: =AP35 -> 517032.83 | N35: =AX35-BC35 -> 270096.61 | O35: =M35/N35 -> 1.9142515 | P35: =X35/BG35 -> 0.67536398 | Q35: 33 | R35: =EOMONTH(L35,0)-EOMONTH(L35,-3) -> 90 | T35: =IF($B$10="3BR_H", INDEX('3BR_H-combined'!$C:$BH,MATCH($L35,'3BR_H-combined'!$B:$B,0),MATCH(Council_Area,'3BR_H-combined'!$C$1:$BH$1,0)), INDEX('2BR_F-combined'!$C:$BH,MATCH($L35,'2BR_F-combined'!$B:$B,0),MATCH(Council_Area,'2BR_F-combined'!$C$1:$BH$1,0))) -> 450 | U35: =IF(MOD(Q35,4)=1,T35,U34) -> 450 | V35: =U35*(R35)/7 -> 5785.7143 | W35: =$B$53/4*BH35/_xlfn.XLOOKUP(Q_end,cpi!A:A,cpi!B:B) -> 145.68072 | X35: =V35+W35 -> 5931.395 | Y35: =BG35-X35 -> 2851.121 | Z35: =Y35*$B$47 -> 912.35873 | AA35: =(Y35+Z35)*eff_invest -> 3763.4798 | AB35: =AA35*(_xlfn.XLOOKUP(Q_end,cpi!A:A,cpi!B:B)/BH35) -> 5166.7507 | AC35: {=INDEX('msci-indices'!C:C,MATCH($L35,'msci-indices'!$B:$B)-2)} -> 1208.1074 | AD35: {=INDEX('msci-indices'!D:D,MATCH($L35,'msci-indices'!$B:$B)-2)} -> 1124.7671 | AE35: =AI34+AA35 -> 508738.87 | AF35: {=INDEX('msci-indices'!C:C,MATCH($L35,'msci-indices'!$B:$B)+1)} -> 1225.92 | AG35: {=INDEX('msci-indices'!D:D,MATCH($L35,'msci-indices'!$B:$B)+1)} -> 1149.5384 | AH35: =(InvestFees/4)*AE35 -> 317.96179 | AI35: =((AF35/AC35)*GlobalPortfolio+(AG35/AD35)*AusPortfolio)*AE35-AH35 -> 517032.83 | AJ35: =AJ34+AA35 -> 345852.22 | AK35: =AI35-AJ35 -> 171180.61 | AL35: =AJ35*(_xlfn.XLOOKUP(Q_end,cpi!A:A,cpi!B:B)/BH35) -> 474808.5 | AM35: {=SUMPRODUCT($AA$3:AA35,_xlfn.SORTBY($BH$3:BH35,_xlfn.SEQUENCE(ROWS($BH$3:BH35)),-1)/$BH$3)} -> 410309.86 | AN35: =AI35-AM35 -> 106722.97 | AO35: =IF($B$49="Real gains",MAX($B$50*AN35,0),IF($B$49="Discounted nominal gains",MAX($B$50*AK35/2,0),0)) -> 0 | AP35: =AI35-AO35 -> 517032.83 | AR35: =IF($B$10="3BR_H", INDEX('ns-combined'!$C:$BH,MATCH($L35,'ns-combined'!$B:$B,0),MATCH(Council_Area,'ns-combined'!$C$1:$BH$1,0))*1000, INDEX('s-combined'!$C:$BH,MATCH($L35,'s-combined'!$B:$B,0),MATCH(Council_Area,'s-combined'!$C$1:$BH$1,0))*1000) -> 680000 | AS35: =AS34+$AS$3 -> 37950 | AT35: 0 | AU35: =SUM($B$28:$B$29)*AR35 -> 13600 | AV35: =AR35*$B$15/4 -> 1955 | AW35: =SUM($AV$3:AV35) -> 51839.125 | AX35: =AR35-AS35-AU35-AW35 -> 576610.88 | AY35: =$B$36*V35 -> 2025 | AZ35: =SUM(AY35:AY35)*4/AR35 -> 0.011911765 | BA35: =SUM(AY35:AY35)/V35 -> 0.35 | BB35: =IF(MortgageRate="Discounted",_xlfn.XLOOKUP(L35,'mortgage-rates'!$A:$A,'mortgage-rates'!$E:$E)/100,_xlfn.XLOOKUP(L35,'mortgage-rates'!$A:$A,'mortgage-rates'!$D:$D)/100) -> 0.0508 | BC35: =BC34-BF34 -> 306514.27 | BD35: =IF($B$16*12/3-Q35+1>0,-PMT($BB35/4,$B$16*12/3-Q35+1,BC35),0) -> 6757.516 | BE35: =BC35*($BB35/4) -> 3892.7312 | BF35: =BD35-BE35 -> 2864.7848 | BG35: =AT35+AY35+BD35 -> 8782.516 | BH35: =INDEX(cpi!B:B,MATCH($L35,cpi!A:A)) -> 105.4 | BI35: =100*BH35/BH$3 -> 124.58629 | BJ35: =100*AC35/AC$3 -> 160.03975 | BK35: =100*AD35/AD$3 -> 157.76103 | BL35: =BJ35*GlobalPortfolio+BK35*AusPortfolio -> 159.35613 | BM35: =100*AE35/$AE$3 -> 320.30384 | BN35: =100*AR35/AR$3 -> 147.82609 | BO35: =100*AX35/AX$3 -> 128.61376
A36: Total home ownership running costs | B36: =SUM(B32:B35) -> 0.35 | L36: =DATE(YEAR(L35),MONTH(L35)+3,1) -> 41791 | M36: =AP36 -> 538561.2 | N36: =AX36-BC36 -> 318712.64 | O36: =M36/N36 -> 1.6898018 | P36: =X36/BG36 -> 0.6810491 | Q36: 34 | R36: =EOMONTH(L36,0)-EOMONTH(L36,-3) -> 91 | T36: =IF($B$10="3BR_H", INDEX('3BR_H-combined'!$C:$BH,MATCH($L36,'3BR_H-combined'!$B:$B,0),MATCH(Council_Area,'3BR_H-combined'!$C$1:$BH$1,0)), INDEX('2BR_F-combined'!$C:$BH,MATCH($L36,'2BR_F-combined'!$B:$B,0),MATCH(Council_Area,'2BR_F-combined'!$C$1:$BH$1,0))) -> 450 | U36: =IF(MOD(Q36,4)=1,T36,U35) -> 450 | V36: =U36*(R36)/7 -> 5850 | W36: =$B$53/4*BH36/_xlfn.XLOOKUP(Q_end,cpi!A:A,cpi!B:B) -> 146.64824 | X36: =V36+W36 -> 5996.6482 | Y36: =BG36-X36 -> 2808.3678 | Z36: =Y36*$B$47 -> 898.67769 | AA36: =(Y36+Z36)*eff_invest -> 3707.0455 | AB36: =AA36*(_xlfn.XLOOKUP(Q_end,cpi!A:A,cpi!B:B)/BH36) -> 5055.6973 | AC36: {=INDEX('msci-indices'!C:C,MATCH($L36,'msci-indices'!$B:$B)-2)} -> 1225.92 | AD36: {=INDEX('msci-indices'!D:D,MATCH($L36,'msci-indices'!$B:$B)-2)} -> 1149.5384 | AE36: =AI35+AA36 -> 520739.88 | AF36: {=INDEX('msci-indices'!C:C,MATCH($L36,'msci-indices'!$B:$B)+1)} -> 1282.9431 | AG36: {=INDEX('msci-indices'!D:D,MATCH($L36,'msci-indices'!$B:$B)+1)} -> 1158.3053 | AH36: =(InvestFees/4)*AE36 -> 325.46242 | AI36: =((AF36/AC36)*GlobalPortfolio+(AG36/AD36)*AusPortfolio)*AE36-AH36 -> 538561.2 | AJ36: =AJ35+AA36 -> 349559.27 | AK36: =AI36-AJ36 -> 189001.93 | AL36: =AJ36*(_xlfn.XLOOKUP(Q_end,cpi!A:A,cpi!B:B)/BH36) -> 476731.63 | AM36: {=SUMPRODUCT($AA$3:AA36,_xlfn.SORTBY($BH$3:BH36,_xlfn.SEQUENCE(ROWS($BH$3:BH36)),-1)/$BH$3)} -> 416722.05 | AN36: =AI36-AM36 -> 121839.15 | AO36: =IF($B$49="Real gains",MAX($B$50*AN36,0),IF($B$49="Discounted nominal gains",MAX($B$50*AK36/2,0),0)) -> 0 | AP36: =AI36-AO36 -> 538561.2 | AR36: =IF($B$10="3BR_H", INDEX('ns-combined'!$C:$BH,MATCH($L36,'ns-combined'!$B:$B,0),MATCH(Council_Area,'ns-combined'!$C$1:$BH$1,0))*1000, INDEX('s-combined'!$C:$BH,MATCH($L36,'s-combined'!$B:$B,0),MATCH(Council_Area,'s-combined'!$C$1:$BH$1,0))*1000) -> 730000 | AS36: =AS35+$AS$3 -> 39100 | AT36: 0 | AU36: =SUM($B$28:$B$29)*AR36 -> 14600 | AV36: =AR36*$B$15/4 -> 2098.75 | AW36: =SUM($AV$3:AV36) -> 53937.875 | AX36: =AR36-AS36-AU36-AW36 -> 622362.12 | AY36: =$B$36*V36 -> 2047.5 | AZ36: =SUM(AY36:AY36)*4/AR36 -> 0.011219178 | BA36: =SUM(AY36:AY36)/V36 -> 0.35 | BB36: =IF(MortgageRate="Discounted",_xlfn.XLOOKUP(L36,'mortgage-rates'!$A:$A,'mortgage-rates'!$E:$E)/100,_xlfn.XLOOKUP(L36,'mortgage-rates'!$A:$A,'mortgage-rates'!$D:$D)/100) -> 0.0508 | BC36: =BC35-BF35 -> 303649.48 | BD36: =IF($B$16*12/3-Q36+1>0,-PMT($BB36/4,$B$16*12/3-Q36+1,BC36),0) -> 6757.516 | BE36: =BC36*($BB36/4) -> 3856.3484 | BF36: =BD36-BE36 -> 2901.1676 | BG36: =AT36+AY36+BD36 -> 8805.016 | BH36: =INDEX(cpi!B:B,MATCH($L36,cpi!A:A)) -> 106.1 | BI36: =100*BH36/BH$3 -> 125.41371 | BJ36: =100*AC36/AC$3 -> 162.39941 | BK36: =100*AD36/AD$3 -> 161.23548 | BL36: =BJ36*GlobalPortfolio+BK36*AusPortfolio -> 162.05023 | BM36: =100*AE36/$AE$3 -> 327.85971 | BN36: =100*AR36/AR$3 -> 158.69565 | BO36: =100*AX36/AX$3 -> 138.81864
A37: Average maint + reno spending (% home value) | B37: {=AVERAGE(_xlfn._xlws.FILTER($AZ$3:$AZ$82,ISNUMBER($AZ$3:$AZ$82)))} -> 0.010213382 | L37: =DATE(YEAR(L36),MONTH(L36)+3,1) -> 41883 | M37: =AP37 -> 530248.19 | N37: =AX37-BC37 -> 321296.43 | O37: =M37/N37 -> 1.6503395 | P37: =X37/BG37 -> 0.68662695 | Q37: 35 | R37: =EOMONTH(L37,0)-EOMONTH(L37,-3) -> 92 | T37: =IF($B$10="3BR_H", INDEX('3BR_H-combined'!$C:$BH,MATCH($L37,'3BR_H-combined'!$B:$B,0),MATCH(Council_Area,'3BR_H-combined'!$C$1:$BH$1,0)), INDEX('2BR_F-combined'!$C:$BH,MATCH($L37,'2BR_F-combined'!$B:$B,0),MATCH(Council_Area,'2BR_F-combined'!$C$1:$BH$1,0))) -> 450 | U37: =IF(MOD(Q37,4)=1,T37,U36) -> 450 | V37: =U37*(R37)/7 -> 5914.2857 | W37: =$B$53/4*BH37/_xlfn.XLOOKUP(Q_end,cpi!A:A,cpi!B:B) -> 146.92467 | X37: =V37+W37 -> 6061.2104 | Y37: =BG37-X37 -> 2766.3056 | Z37: =Y37*$B$47 -> 885.21781 | AA37: =(Y37+Z37)*eff_invest -> 3651.5234 | AB37: =AA37*(_xlfn.XLOOKUP(Q_end,cpi!A:A,cpi!B:B)/BH37) -> 4970.6062 | AC37: {=INDEX('msci-indices'!C:C,MATCH($L37,'msci-indices'!$B:$B)-2)} -> 1282.9431 | AD37: {=INDEX('msci-indices'!D:D,MATCH($L37,'msci-indices'!$B:$B)-2)} -> 1158.3053 | AE37: =AI36+AA37 -> 542212.72 | AF37: {=INDEX('msci-indices'!C:C,MATCH($L37,'msci-indices'!$B:$B)+1)} -> 1247.2922 | AG37: {=INDEX('msci-indices'!D:D,MATCH($L37,'msci-indices'!$B:$B)+1)} -> 1150.6246 | AH37: =(InvestFees/4)*AE37 -> 338.88295 | AI37: =((AF37/AC37)*GlobalPortfolio+(AG37/AD37)*AusPortfolio)*AE37-AH37 -> 530248.19 | AJ37: =AJ36+AA37 -> 353210.79 | AK37: =AI37-AJ37 -> 177037.4 | AL37: =AJ37*(_xlfn.XLOOKUP(Q_end,cpi!A:A,cpi!B:B)/BH37) -> 480805.28 | AM37: {=SUMPRODUCT($AA$3:AA37,_xlfn.SORTBY($BH$3:BH37,_xlfn.SEQUENCE(ROWS($BH$3:BH37)),-1)/$BH$3)} -> 422187.31 | AN37: =AI37-AM37 -> 108060.88 | AO37: =IF($B$49="Real gains",MAX($B$50*AN37,0),IF($B$49="Discounted nominal gains",MAX($B$50*AK37/2,0),0)) -> 0 | AP37: =AI37-AO37 -> 530248.19 | AR37: =IF($B$10="3BR_H", INDEX('ns-combined'!$C:$BH,MATCH($L37,'ns-combined'!$B:$B,0),MATCH(Council_Area,'ns-combined'!$C$1:$BH$1,0))*1000, INDEX('s-combined'!$C:$BH,MATCH($L37,'s-combined'!$B:$B,0),MATCH(Council_Area,'s-combined'!$C$1:$BH$1,0))*1000) -> 733000 | AS37: =AS36+$AS$3 -> 40250 | AT37: 0 | AU37: =SUM($B$28:$B$29)*AR37 -> 14660 | AV37: =AR37*$B$15/4 -> 2107.375 | AW37: =SUM($AV$3:AV37) -> 56045.25 | AX37: =AR37-AS37-AU37-AW37 -> 622044.75 | AY37: =$B$36*V37 -> 2070 | AZ37: =SUM(AY37:AY37)*4/AR37 -> 0.011296044 | BA37: =SUM(AY37:AY37)/V37 -> 0.35 | BB37: =IF(MortgageRate="Discounted",_xlfn.XLOOKUP(L37,'mortgage-rates'!$A:$A,'mortgage-rates'!$E:$E)/100,_xlfn.XLOOKUP(L37,'mortgage-rates'!$A:$A,'mortgage-rates'!$D:$D)/100) -> 0.0508 | BC37: =BC36-BF36 -> 300748.32 | BD37: =IF($B$16*12/3-Q37+1>0,-PMT($BB37/4,$B$16*12/3-Q37+1,BC37),0) -> 6757.516 | BE37: =BC37*($BB37/4) -> 3819.5036 | BF37: =BD37-BE37 -> 2938.0124 | BG37: =AT37+AY37+BD37 -> 8827.516 | BH37: =INDEX(cpi!B:B,MATCH($L37,cpi!A:A)) -> 106.3 | BI37: =100*BH37/BH$3 -> 125.65012 | BJ37: =100*AC37/AC$3 -> 169.95334 | BK37: =100*AD37/AD$3 -> 162.46513 | BL37: =BJ37*GlobalPortfolio+BK37*AusPortfolio -> 167.70687 | BM37: =100*AE37/$AE$3 -> 341.3791 | BN37: =100*AR37/AR$3 -> 159.34783 | BO37: =100*AX37/AX$3 -> 138.74785
A38: Average maint + reno spending (% rents) | B38: {=AVERAGE(_xlfn._xlws.FILTER($BA$3:$BA$82,ISNUMBER($BA$3:$BA$82)))} -> 0.35 | L38: =DATE(YEAR(L37),MONTH(L37)+3,1) -> 41974 | M38: =AP38 -> 542454.34 | N38: =AX38-BC38 -> 401101.32 | O38: =M38/N38 -> 1.3524123 | P38: =X38/BG38 -> 0.68665826 | Q38: 36 | R38: =EOMONTH(L38,0)-EOMONTH(L38,-3) -> 92 | T38: =IF($B$10="3BR_H", INDEX('3BR_H-combined'!$C:$BH,MATCH($L38,'3BR_H-combined'!$B:$B,0),MATCH(Council_Area,'3BR_H-combined'!$C$1:$BH$1,0)), INDEX('2BR_F-combined'!$C:$BH,MATCH($L38,'2BR_F-combined'!$B:$B,0),MATCH(Council_Area,'2BR_F-combined'!$C$1:$BH$1,0))) -> 450 | U38: =IF(MOD(Q38,4)=1,T38,U37) -> 450 | V38: =U38*(R38)/7 -> 5914.2857 | W38: =$B$53/4*BH38/_xlfn.XLOOKUP(Q_end,cpi!A:A,cpi!B:B) -> 147.20111 | X38: =V38+W38 -> 6061.4868 | Y38: =BG38-X38 -> 2766.0292 | Z38: =Y38*$B$47 -> 885.12935 | AA38: =(Y38+Z38)*eff_invest -> 3651.1586 | AB38: =AA38*(_xlfn.XLOOKUP(Q_end,cpi!A:A,cpi!B:B)/BH38) -> 4960.776 | AC38: {=INDEX('msci-indices'!C:C,MATCH($L38,'msci-indices'!$B:$B)-2)} -> 1247.2922 | AD38: {=INDEX('msci-indices'!D:D,MATCH($L38,'msci-indices'!$B:$B)-2)} -> 1150.6246 | AE38: =AI37+AA38 -> 533899.35 | AF38: {=INDEX('msci-indices'!C:C,MATCH($L38,'msci-indices'!$B:$B)+1)} -> 1262.6926 | AG38: {=INDEX('msci-indices'!D:D,MATCH($L38,'msci-indices'!$B:$B)+1)} -> 1181.3297 | AH38: =(InvestFees/4)*AE38 -> 333.68709 | AI38: =((AF38/AC38)*GlobalPortfolio+(AG38/AD38)*AusPortfolio)*AE38-AH38 -> 542454.34 | AJ38: =AJ37+AA38 -> 356861.95 | AK38: =AI38-AJ38 -> 185592.4 | AL38: =AJ38*(_xlfn.XLOOKUP(Q_end,cpi!A:A,cpi!B:B)/BH38) -> 484863.14 | AM38: {=SUMPRODUCT($AA$3:AA38,_xlfn.SORTBY($BH$3:BH38,_xlfn.SEQUENCE(ROWS($BH$3:BH38)),-1)/$BH$3)} -> 427669.36 | AN38: =AI38-AM38 -> 114784.98 | AO38: =IF($B$49="Real gains",MAX($B$50*AN38,0),IF($B$49="Discounted nominal gains",MAX($B$50*AK38/2,0),0)) -> 0 | AP38: =AI38-AO38 -> 542454.34 | AR38: =IF($B$10="3BR_H", INDEX('ns-combined'!$C:$BH,MATCH($L38,'ns-combined'!$B:$B,0),MATCH(Council_Area,'ns-combined'!$C$1:$BH$1,0))*1000, INDEX('s-combined'!$C:$BH,MATCH($L38,'s-combined'!$B:$B,0),MATCH(Council_Area,'s-combined'!$C$1:$BH$1,0))*1000) -> 815000 | AS38: =AS37+$AS$3 -> 41400 | AT38: 0 | AU38: =SUM($B$28:$B$29)*AR38 -> 16300 | AV38: =AR38*$B$15/4 -> 2343.125 | AW38: =SUM($AV$3:AV38) -> 58388.375 | AX38: =AR38-AS38-AU38-AW38 -> 698911.62 | AY38: =$B$36*V38 -> 2070 | AZ38: =SUM(AY38:AY38)*4/AR38 -> 0.010159509 | BA38: =SUM(AY38:AY38)/V38 -> 0.35 | BB38: =IF(MortgageRate="Discounted",_xlfn.XLOOKUP(L38,'mortgage-rates'!$A:$A,'mortgage-rates'!$E:$E)/100,_xlfn.XLOOKUP(L38,'mortgage-rates'!$A:$A,'mortgage-rates'!$D:$D)/100) -> 0.0508 | BC38: =BC37-BF37 -> 297810.3 | BD38: =IF($B$16*12/3-Q38+1>0,-PMT($BB38/4,$B$16*12/3-Q38+1,BC38),0) -> 6757.516 | BE38: =BC38*($BB38/4) -> 3782.1909 | BF38: =BD38-BE38 -> 2975.3252 | BG38: =AT38+AY38+BD38 -> 8827.516 | BH38: =INDEX(cpi!B:B,MATCH($L38,cpi!A:A)) -> 106.5 | BI38: =100*BH38/BH$3 -> 125.88652 | BJ38: =100*AC38/AC$3 -> 165.23062 | BK38: =100*AD38/AD$3 -> 161.38783 | BL38: =BJ38*GlobalPortfolio+BK38*AusPortfolio -> 164.07778 | BM38: =100*AE38/$AE$3 -> 336.14497 | BN38: =100*AR38/AR$3 -> 177.17391 | BO38: =100*AX38/AX$3 -> 155.8931
L39: =DATE(YEAR(L38),MONTH(L38)+3,1) -> 42064 | M39: =AP39 -> 572370.41 | N39: =AX39-BC39 -> 361498.52 | O39: =M39/N39 -> 1.5833271 | P39: =X39/BG39 -> 0.68509101 | Q39: 37 | R39: =EOMONTH(L39,0)-EOMONTH(L39,-3) -> 90 | T39: =IF($B$10="3BR_H", INDEX('3BR_H-combined'!$C:$BH,MATCH($L39,'3BR_H-combined'!$B:$B,0),MATCH(Council_Area,'3BR_H-combined'!$C$1:$BH$1,0)), INDEX('2BR_F-combined'!$C:$BH,MATCH($L39,'2BR_F-combined'!$B:$B,0),MATCH(Council_Area,'2BR_F-combined'!$C$1:$BH$1,0))) -> 450 | U39: =IF(MOD(Q39,4)=1,T39,U38) -> 450 | V39: =U39*(R39)/7 -> 5785.7143 | W39: =$B$53/4*BH39/_xlfn.XLOOKUP(Q_end,cpi!A:A,cpi!B:B) -> 147.61576 | X39: =V39+W39 -> 5933.33 | Y39: =BG39-X39 -> 2727.315 | Z39: =Y39*$B$47 -> 872.74079 | AA39: =(Y39+Z39)*eff_invest -> 3600.0557 | AB39: =AA39*(_xlfn.XLOOKUP(Q_end,cpi!A:A,cpi!B:B)/BH39) -> 4877.6036 | AC39: {=INDEX('msci-indices'!C:C,MATCH($L39,'msci-indices'!$B:$B)-2)} -> 1262.6926 | AD39: {=INDEX('msci-indices'!D:D,MATCH($L39,'msci-indices'!$B:$B)-2)} -> 1181.3297 | AE39: =AI38+AA39 -> 546054.4 | AF39: {=INDEX('msci-indices'!C:C,MATCH($L39,'msci-indices'!$B:$B)+1)} -> 1295.5073 | AG39: {=INDEX('msci-indices'!D:D,MATCH($L39,'msci-indices'!$B:$B)+1)} -> 1301.9298 | AH39: =(InvestFees/4)*AE39 -> 341.284 | AI39: =((AF39/AC39)*GlobalPortfolio+(AG39/AD39)*AusPortfolio)*AE39-AH39 -> 572370.41 | AJ39: =AJ38+AA39 -> 360462 | AK39: =AI39-AJ39 -> 211908.4 | AL39: =AJ39*(_xlfn.XLOOKUP(Q_end,cpi!A:A,cpi!B:B)/BH39) -> 488378.76 | AM39: {=SUMPRODUCT($AA$3:AA39,_xlfn.SORTBY($BH$3:BH39,_xlfn.SEQUENCE(ROWS($BH$3:BH39)),-1)/$BH$3)} -> 433289.05 | AN39: =AI39-AM39 -> 139081.35 | AO39: =IF($B$49="Real gains",MAX($B$50*AN39,0),IF($B$49="Discounted nominal gains",MAX($B$50*AK39/2,0),0)) -> 0 | AP39: =AI39-AO39 -> 572370.41 | AR39: =IF($B$10="3BR_H", INDEX('ns-combined'!$C:$BH,MATCH($L39,'ns-combined'!$B:$B,0),MATCH(Council_Area,'ns-combined'!$C$1:$BH$1,0))*1000, INDEX('s-combined'!$C:$BH,MATCH($L39,'s-combined'!$B:$B,0),MATCH(Council_Area,'s-combined'!$C$1:$BH$1,0))*1000) -> 775000 | AS39: =AS38+$AS$3 -> 42550 | AT39: 0 | AU39: =SUM($B$28:$B$29)*AR39 -> 15500 | AV39: =AR39*$B$15/4 -> 2228.125 | AW39: =SUM($AV$3:AV39) -> 60616.5 | AX39: =AR39-AS39-AU39-AW39 -> 656333.5 | AY39: =$B$36*V39 -> 2025 | AZ39: =SUM(AY39:AY39)*4/AR39 -> 0.010451613 | BA39: =SUM(AY39:AY39)/V39 -> 0.35 | BB39: =IF(MortgageRate="Discounted",_xlfn.XLOOKUP(L39,'mortgage-rates'!$A:$A,'mortgage-rates'!$E:$E)/100,_xlfn.XLOOKUP(L39,'mortgage-rates'!$A:$A,'mortgage-rates'!$D:$D)/100) -> 0.0482 | BC39: =BC38-BF38 -> 294834.98 | BD39: =IF($B$16*12/3-Q39+1>0,-PMT($BB39/4,$B$16*12/3-Q39+1,BC39),0) -> 6635.645 | BE39: =BC39*($BB39/4) -> 3552.7615 | BF39: =BD39-BE39 -> 3082.8835 | BG39: =AT39+AY39+BD39 -> 8660.645 | BH39: =INDEX(cpi!B:B,MATCH($L39,cpi!A:A)) -> 106.8 | BI39: =100*BH39/BH$3 -> 126.24113 | BJ39: =100*AC39/AC$3 -> 167.27073 | BK39: =100*AD39/AD$3 -> 165.69455 | BL39: =BJ39*GlobalPortfolio+BK39*AusPortfolio -> 166.79788 | BM39: =100*AE39/$AE$3 -> 343.79783 | BN39: =100*AR39/AR$3 -> 168.47826 | BO39: =100*AX39/AX$3 -> 146.39599
A40: Renter investment parameters | L40: =DATE(YEAR(L39),MONTH(L39)+3,1) -> 42156 | M40: =AP40 -> 565817.34 | N40: =AX40-BC40 -> 454030.15 | O40: =M40/N40 -> 1.2462109 | P40: =X40/BG40 -> 0.69638286 | Q40: 38 | R40: =EOMONTH(L40,0)-EOMONTH(L40,-3) -> 91 | T40: =IF($B$10="3BR_H", INDEX('3BR_H-combined'!$C:$BH,MATCH($L40,'3BR_H-combined'!$B:$B,0),MATCH(Council_Area,'3BR_H-combined'!$C$1:$BH$1,0)), INDEX('2BR_F-combined'!$C:$BH,MATCH($L40,'2BR_F-combined'!$B:$B,0),MATCH(Council_Area,'2BR_F-combined'!$C$1:$BH$1,0))) -> 460 | U40: =IF(MOD(Q40,4)=1,T40,U39) -> 450 | V40: =U40*(R40)/7 -> 5850 | W40: =$B$53/4*BH40/_xlfn.XLOOKUP(Q_end,cpi!A:A,cpi!B:B) -> 148.85971 | X40: =V40+W40 -> 5998.8597 | Y40: =BG40-X40 -> 2615.4529 | Z40: =Y40*$B$47 -> 836.94494 | AA40: =(Y40+Z40)*eff_invest -> 3452.3979 | AB40: =AA40*(_xlfn.XLOOKUP(Q_end,cpi!A:A,cpi!B:B)/BH40) -> 4638.4584 | AC40: {=INDEX('msci-indices'!C:C,MATCH($L40,'msci-indices'!$B:$B)-2)} -> 1295.5073 | AD40: {=INDEX('msci-indices'!D:D,MATCH($L40,'msci-indices'!$B:$B)-2)} -> 1301.9298 | AE40: =AI39+AA40 -> 575822.81 | AF40: {=INDEX('msci-indices'!C:C,MATCH($L40,'msci-indices'!$B:$B)+1)} -> 1301.507 | AG40: {=INDEX('msci-indices'!D:D,MATCH($L40,'msci-indices'!$B:$B)+1)} -> 1215.1659 | AH40: =(InvestFees/4)*AE40 -> 359.88925 | AI40: =((AF40/AC40)*GlobalPortfolio+(AG40/AD40)*AusPortfolio)*AE40-AH40 -> 565817.34 | AJ40: =AJ39+AA40 -> 363914.4 | AK40: =AI40-AJ40 -> 201902.94 | AL40: =AJ40*(_xlfn.XLOOKUP(Q_end,cpi!A:A,cpi!B:B)/BH40) -> 488936.06 | AM40: {=SUMPRODUCT($AA$3:AA40,_xlfn.SORTBY($BH$3:BH40,_xlfn.SEQUENCE(ROWS($BH$3:BH40)),-1)/$BH$3)} -> 439874.31 | AN40: =AI40-AM40 -> 125943.03 | AO40: =IF($B$49="Real gains",MAX($B$50*AN40,0),IF($B$49="Discounted nominal gains",MAX($B$50*AK40/2,0),0)) -> 0 | AP40: =AI40-AO40 -> 565817.34 | AR40: =IF($B$10="3BR_H", INDEX('ns-combined'!$C:$BH,MATCH($L40,'ns-combined'!$B:$B,0),MATCH(Council_Area,'ns-combined'!$C$1:$BH$1,0))*1000, INDEX('s-combined'!$C:$BH,MATCH($L40,'s-combined'!$B:$B,0),MATCH(Council_Area,'s-combined'!$C$1:$BH$1,0))*1000) -> 870000 | AS40: =AS39+$AS$3 -> 43700 | AT40: 0 | AU40: =SUM($B$28:$B$29)*AR40 -> 17400 | AV40: =AR40*$B$15/4 -> 2501.25 | AW40: =SUM($AV$3:AV40) -> 63117.75 | AX40: =AR40-AS40-AU40-AW40 -> 745782.25 | AY40: =$B$36*V40 -> 2047.5 | AZ40: =SUM(AY40:AY40)*4/AR40 -> 0.0094137931 | BA40: =SUM(AY40:AY40)/V40 -> 0.35 | BB40: =IF(MortgageRate="Discounted",_xlfn.XLOOKUP(L40,'mortgage-rates'!$A:$A,'mortgage-rates'!$E:$E)/100,_xlfn.XLOOKUP(L40,'mortgage-rates'!$A:$A,'mortgage-rates'!$D:$D)/100) -> 0.0467 | BC40: =BC39-BF39 -> 291752.1 | BD40: =IF($B$16*12/3-Q40+1>0,-PMT($BB40/4,$B$16*12/3-Q40+1,BC40),0) -> 6566.8126 | BE40: =BC40*($BB40/4) -> 3406.2057 | BF40: =BD40-BE40 -> 3160.6069 | BG40: =AT40+AY40+BD40 -> 8614.3126 | BH40: =INDEX(cpi!B:B,MATCH($L40,cpi!A:A)) -> 107.7 | BI40: =100*BH40/BH$3 -> 127.30496 | BJ40: =100*AC40/AC$3 -> 171.61773 | BK40: =100*AD40/AD$3 -> 182.61006 | BL40: =BJ40*GlobalPortfolio+BK40*AusPortfolio -> 174.91543 | BM40: =100*AE40/$AE$3 -> 362.54013 | BN40: =100*AR40/AR$3 -> 189.13043 | BO40: =100*AX40/AX$3 -> 166.34765
A41: % of portfolio in global equities | B41: 0.7 | C41: 0.7 | L41: =DATE(YEAR(L40),MONTH(L40)+3,1) -> 42248 | M41: =AP41 -> 522701.92 | N41: =AX41-BC41 -> 473082.01 | O41: =M41/N41 -> 1.1048865 | P41: =X41/BG41 -> 0.70239492 | Q41: 39 | R41: =EOMONTH(L41,0)-EOMONTH(L41,-3) -> 92 | T41: =IF($B$10="3BR_H", INDEX('3BR_H-combined'!$C:$BH,MATCH($L41,'3BR_H-combined'!$B:$B,0),MATCH(Council_Area,'3BR_H-combined'!$C$1:$BH$1,0)), INDEX('2BR_F-combined'!$C:$BH,MATCH($L41,'2BR_F-combined'!$B:$B,0),MATCH(Council_Area,'2BR_F-combined'!$C$1:$BH$1,0))) -> 460 | U41: =IF(MOD(Q41,4)=1,T41,U40) -> 450 | V41: =U41*(R41)/7 -> 5914.2857 | W41: =$B$53/4*BH41/_xlfn.XLOOKUP(Q_end,cpi!A:A,cpi!B:B) -> 148.99793 | X41: =V41+W41 -> 6063.2836 | Y41: =BG41-X41 -> 2569.0163 | Z41: =Y41*$B$47 -> 822.0852 | AA41: =(Y41+Z41)*eff_invest -> 3391.1015 | AB41: =AA41*(_xlfn.XLOOKUP(Q_end,cpi!A:A,cpi!B:B)/BH41) -> 4551.8774 | AC41: {=INDEX('msci-indices'!C:C,MATCH($L41,'msci-indices'!$B:$B)-2)} -> 1301.507 | AD41: {=INDEX('msci-indices'!D:D,MATCH($L41,'msci-indices'!$B:$B)-2)} -> 1215.1659 | AE41: =AI40+AA41 -> 569208.44 | AF41: {=INDEX('msci-indices'!C:C,MATCH($L41,'msci-indices'!$B:$B)+1)} -> 1189.2855 | AG41: {=INDEX('msci-indices'!D:D,MATCH($L41,'msci-indices'!$B:$B)+1)} -> 1131.2309 | AH41: =(InvestFees/4)*AE41 -> 355.75528 | AI41: =((AF41/AC41)*GlobalPortfolio+(AG41/AD41)*AusPortfolio)*AE41-AH41 -> 522701.92 | AJ41: =AJ40+AA41 -> 367305.5 | AK41: =AI41-AJ41 -> 155396.42 | AL41: =AJ41*(_xlfn.XLOOKUP(Q_end,cpi!A:A,cpi!B:B)/BH41) -> 493034.38 | AM41: {=SUMPRODUCT($AA$3:AA41,_xlfn.SORTBY($BH$3:BH41,_xlfn.SEQUENCE(ROWS($BH$3:BH41)),-1)/$BH$3)} -> 444941.77 | AN41: =AI41-AM41 -> 77760.155 | AO41: =IF($B$49="Real gains",MAX($B$50*AN41,0),IF($B$49="Discounted nominal gains",MAX($B$50*AK41/2,0),0)) -> 0 | AP41: =AI41-AO41 -> 522701.92 | AR41: =IF($B$10="3BR_H", INDEX('ns-combined'!$C:$BH,MATCH($L41,'ns-combined'!$B:$B,0),MATCH(Council_Area,'ns-combined'!$C$1:$BH$1,0))*1000, INDEX('s-combined'!$C:$BH,MATCH($L41,'s-combined'!$B:$B,0),MATCH(Council_Area,'s-combined'!$C$1:$BH$1,0))*1000) -> 890000 | AS41: =AS40+$AS$3 -> 44850 | AT41: 0 | AU41: =SUM($B$28:$B$29)*AR41 -> 17800 | AV41: =AR41*$B$15/4 -> 2558.75 | AW41: =SUM($AV$3:AV41) -> 65676.5 | AX41: =AR41-AS41-AU41-AW41 -> 761673.5 | AY41: =$B$36*V41 -> 2070 | AZ41: =SUM(AY41:AY41)*4/AR41 -> 0.0093033708 | BA41: =SUM(AY41:AY41)/V41 -> 0.35 | BB41: =IF(MortgageRate="Discounted",_xlfn.XLOOKUP(L41,'mortgage-rates'!$A:$A,'mortgage-rates'!$E:$E)/100,_xlfn.XLOOKUP(L41,'mortgage-rates'!$A:$A,'mortgage-rates'!$D:$D)/100) -> 0.0466 | BC41: =BC40-BF40 -> 288591.49 | BD41: =IF($B$16*12/3-Q41+1>0,-PMT($BB41/4,$B$16*12/3-Q41+1,BC41),0) -> 6562.2999 | BE41: =BC41*($BB41/4) -> 3362.0908 | BF41: =BD41-BE41 -> 3200.2091 | BG41: =AT41+AY41+BD41 -> 8632.2999 | BH41: =INDEX(cpi!B:B,MATCH($L41,cpi!A:A)) -> 107.8 | BI41: =100*BH41/BH$3 -> 127.42317 | BJ41: =100*AC41/AC$3 -> 172.41252 | BK41: =100*AD41/AD$3 -> 170.44046 | BL41: =BJ41*GlobalPortfolio+BK41*AusPortfolio -> 171.8209 | BM41: =100*AE41/$AE$3 -> 358.3757 | BN41: =100*AR41/AR$3 -> 193.47826 | BO41: =100*AX41/AX$3 -> 169.89221
A42: % of portfolio in Australian equities | B42: =1-GlobalPortfolio -> 0.3 | C42: 0.3 | L42: =DATE(YEAR(L41),MONTH(L41)+3,1) -> 42339 | M42: =AP42 -> 555664.5 | N42: =AX42-BC42 -> 492115.97 | O42: =M42/N42 -> 1.1291332 | P42: =X42/BG42 -> 0.69635308 | Q42: 40 | R42: =EOMONTH(L42,0)-EOMONTH(L42,-3) -> 92 | T42: =IF($B$10="3BR_H", INDEX('3BR_H-combined'!$C:$BH,MATCH($L42,'3BR_H-combined'!$B:$B,0),MATCH(Council_Area,'3BR_H-combined'!$C$1:$BH$1,0)), INDEX('2BR_F-combined'!$C:$BH,MATCH($L42,'2BR_F-combined'!$B:$B,0),MATCH(Council_Area,'2BR_F-combined'!$C$1:$BH$1,0))) -> 460 | U42: =IF(MOD(Q42,4)=1,T42,U41) -> 450 | V42: =U42*(R42)/7 -> 5914.2857 | W42: =$B$53/4*BH42/_xlfn.XLOOKUP(Q_end,cpi!A:A,cpi!B:B) -> 149.68901 | X42: =V42+W42 -> 6063.9747 | Y42: =BG42-X42 -> 2644.215 | Z42: =Y42*$B$47 -> 846.14881 | AA42: =(Y42+Z42)*eff_invest -> 3490.3638 | AB42: =AA42*(_xlfn.XLOOKUP(Q_end,cpi!A:A,cpi!B:B)/BH42) -> 4663.4871 | AC42: {=INDEX('msci-indices'!C:C,MATCH($L42,'msci-indices'!$B:$B)-2)} -> 1189.2855 | AD42: {=INDEX('msci-indices'!D:D,MATCH($L42,'msci-indices'!$B:$B)-2)} -> 1131.2309 | AE42: =AI41+AA42 -> 526192.29 | AF42: {=INDEX('msci-indices'!C:C,MATCH($L42,'msci-indices'!$B:$B)+1)} -> 1252.6491 | AG42: {=INDEX('msci-indices'!D:D,MATCH($L42,'msci-indices'!$B:$B)+1)} -> 1204.1585 | AH42: =(InvestFees/4)*AE42 -> 328.87018 | AI42: =((AF42/AC42)*GlobalPortfolio+(AG42/AD42)*AusPortfolio)*AE42-AH42 -> 555664.5 | AJ42: =AJ41+AA42 -> 370795.87 | AK42: =AI42-AJ42 -> 184868.64 | AL42: =AJ42*(_xlfn.XLOOKUP(Q_end,cpi!A:A,cpi!B:B)/BH42) -> 495421.62 | AM42: {=SUMPRODUCT($AA$3:AA42,_xlfn.SORTBY($BH$3:BH42,_xlfn.SEQUENCE(ROWS($BH$3:BH42)),-1)/$BH$3)} -> 450846.39 | AN42: =AI42-AM42 -> 104818.12 | AO42: =IF($B$49="Real gains",MAX($B$50*AN42,0),IF($B$49="Discounted nominal gains",MAX($B$50*AK42/2,0),0)) -> 0 | AP42: =AI42-AO42 -> 555664.5 | AR42: =IF($B$10="3BR_H", INDEX('ns-combined'!$C:$BH,MATCH($L42,'ns-combined'!$B:$B,0),MATCH(Council_Area,'ns-combined'!$C$1:$BH$1,0))*1000, INDEX('s-combined'!$C:$BH,MATCH($L42,'s-combined'!$B:$B,0),MATCH(Council_Area,'s-combined'!$C$1:$BH$1,0))*1000) -> 910000 | AS42: =AS41+$AS$3 -> 46000 | AT42: 0 | AU42: =SUM($B$28:$B$29)*AR42 -> 18200 | AV42: =AR42*$B$15/4 -> 2616.25 | AW42: =SUM($AV$3:AV42) -> 68292.75 | AX42: =AR42-AS42-AU42-AW42 -> 777507.25 | AY42: =$B$36*V42 -> 2070 | AZ42: =SUM(AY42:AY42)*4/AR42 -> 0.0090989011 | BA42: =SUM(AY42:AY42)/V42 -> 0.35 | BB42: =IF(MortgageRate="Discounted",_xlfn.XLOOKUP(L42,'mortgage-rates'!$A:$A,'mortgage-rates'!$E:$E)/100,_xlfn.XLOOKUP(L42,'mortgage-rates'!$A:$A,'mortgage-rates'!$D:$D)/100) -> 0.0483 | BC42: =BC41-BF41 -> 285391.28 | BD42: =IF($B$16*12/3-Q42+1>0,-PMT($BB42/4,$B$16*12/3-Q42+1,BC42),0) -> 6638.1898 | BE42: =BC42*($BB42/4) -> 3446.0997 | BF42: =BD42-BE42 -> 3192.0901 | BG42: =AT42+AY42+BD42 -> 8708.1898 | BH42: =INDEX(cpi!B:B,MATCH($L42,cpi!A:A)) -> 108.3 | BI42: =100*BH42/BH$3 -> 128.01418 | BJ42: =100*AC42/AC$3 -> 157.54638 | BK42: =100*AD42/AD$3 -> 158.66765 | BL42: =BJ42*GlobalPortfolio+BK42*AusPortfolio -> 157.88276 | BM42: =100*AE42/$AE$3 -> 331.29257 | BN42: =100*AR42/AR$3 -> 197.82609 | BO42: =100*AX42/AX$3 -> 173.42395
A43: Investment fees (% of investment value per year) | B43: 0.0025 | C43: 0.0025 | L43: =DATE(YEAR(L42),MONTH(L42)+3,1) -> 42430 | M43: =AP43 -> 553082.78 | N43: =AX43-BC43 -> 432914.31 | O43: =M43/N43 -> 1.2775803 | P43: =X43/BG43 -> 0.72425905 | Q43: 41 | R43: =EOMONTH(L43,0)-EOMONTH(L43,-3) -> 91 | T43: =IF($B$10="3BR_H", INDEX('3BR_H-combined'!$C:$BH,MATCH($L43,'3BR_H-combined'!$B:$B,0),MATCH(Council_Area,'3BR_H-combined'!$C$1:$BH$1,0)), INDEX('2BR_F-combined'!$C:$BH,MATCH($L43,'2BR_F-combined'!$B:$B,0),MATCH(Council_Area,'2BR_F-combined'!$C$1:$BH$1,0))) -> 480 | U43: =IF(MOD(Q43,4)=1,T43,U42) -> 480 | V43: =U43*(R43)/7 -> 6240 | W43: =$B$53/4*BH43/_xlfn.XLOOKUP(Q_end,cpi!A:A,cpi!B:B) -> 149.55079 | X43: =V43+W43 -> 6389.5508 | Y43: =BG43-X43 -> 2432.639 | Z43: =Y43*$B$47 -> 778.44447 | AA43: =(Y43+Z43)*eff_invest -> 3211.0834 | AB43: =AA43*(_xlfn.XLOOKUP(Q_end,cpi!A:A,cpi!B:B)/BH43) -> 4294.3047 | AC43: {=INDEX('msci-indices'!C:C,MATCH($L43,'msci-indices'!$B:$B)-2)} -> 1252.6491 | AD43: {=INDEX('msci-indices'!D:D,MATCH($L43,'msci-indices'!$B:$B)-2)} -> 1204.1585 | AE43: =AI42+AA43 -> 558875.59 | AF43: {=INDEX('msci-indices'!C:C,MATCH($L43,'msci-indices'!$B:$B)+1)} -> 1249.9269 | AG43: {=INDEX('msci-indices'!D:D,MATCH($L43,'msci-indices'!$B:$B)+1)} -> 1171.169 | AH43: =(InvestFees/4)*AE43 -> 349.29724 | AI43: =((AF43/AC43)*GlobalPortfolio+(AG43/AD43)*AusPortfolio)*AE43-AH43 -> 553082.78 | AJ43: =AJ42+AA43 -> 374006.95 | AK43: =AI43-AJ43 -> 179075.83 | AL43: =AJ43*(_xlfn.XLOOKUP(Q_end,cpi!A:A,cpi!B:B)/BH43) -> 500173.81 | AM43: {=SUMPRODUCT($AA$3:AA43,_xlfn.SORTBY($BH$3:BH43,_xlfn.SEQUENCE(ROWS($BH$3:BH43)),-1)/$BH$3)} -> 455365.58 | AN43: =AI43-AM43 -> 97717.194 | AO43: =IF($B$49="Real gains",MAX($B$50*AN43,0),IF($B$49="Discounted nominal gains",MAX($B$50*AK43/2,0),0)) -> 0 | AP43: =AI43-AO43 -> 553082.78 | AR43: =IF($B$10="3BR_H", INDEX('ns-combined'!$C:$BH,MATCH($L43,'ns-combined'!$B:$B,0),MATCH(Council_Area,'ns-combined'!$C$1:$BH$1,0))*1000, INDEX('s-combined'!$C:$BH,MATCH($L43,'s-combined'!$B:$B,0),MATCH(Council_Area,'s-combined'!$C$1:$BH$1,0))*1000) -> 850000 | AS43: =AS42+$AS$3 -> 47150 | AT43: 0 | AU43: =SUM($B$28:$B$29)*AR43 -> 17000 | AV43: =AR43*$B$15/4 -> 2443.75 | AW43: =SUM($AV$3:AV43) -> 70736.5 | AX43: =AR43-AS43-AU43-AW43 -> 715113.5 | AY43: =$B$36*V43 -> 2184 | AZ43: =SUM(AY43:AY43)*4/AR43 -> 0.010277647 | BA43: =SUM(AY43:AY43)/V43 -> 0.35 | BB43: =IF(MortgageRate="Discounted",_xlfn.XLOOKUP(L43,'mortgage-rates'!$A:$A,'mortgage-rates'!$E:$E)/100,_xlfn.XLOOKUP(L43,'mortgage-rates'!$A:$A,'mortgage-rates'!$D:$D)/100) -> 0.0483 | BC43: =BC42-BF42 -> 282199.19 | BD43: =IF($B$16*12/3-Q43+1>0,-PMT($BB43/4,$B$16*12/3-Q43+1,BC43),0) -> 6638.1898 | BE43: =BC43*($BB43/4) -> 3407.5552 | BF43: =BD43-BE43 -> 3230.6345 | BG43: =AT43+AY43+BD43 -> 8822.1898 | BH43: =INDEX(cpi!B:B,MATCH($L43,cpi!A:A)) -> 108.2 | BI43: =100*BH43/BH$3 -> 127.89598 | BJ43: =100*AC43/AC$3 -> 165.94025 | BK43: =100*AD43/AD$3 -> 168.89654 | BL43: =BJ43*GlobalPortfolio+BK43*AusPortfolio -> 166.82714 | BM43: =100*AE43/$AE$3 -> 351.8701 | BN43: =100*AR43/AR$3 -> 184.78261 | BO43: =100*AX43/AX$3 -> 159.50695
A44: Investing through superannuation? | B44: Yes | C44: No | L44: =DATE(YEAR(L43),MONTH(L43)+3,1) -> 42522 | M44: =AP44 -> 566781.46 | N44: =AX44-BC44 -> 466750.57 | O44: =M44/N44 -> 1.2143134 | P44: =X44/BG44 -> 0.73299515 | Q44: 42 | R44: =EOMONTH(L44,0)-EOMONTH(L44,-3) -> 91 | T44: =IF($B$10="3BR_H", INDEX('3BR_H-combined'!$C:$BH,MATCH($L44,'3BR_H-combined'!$B:$B,0),MATCH(Council_Area,'3BR_H-combined'!$C$1:$BH$1,0)), INDEX('2BR_F-combined'!$C:$BH,MATCH($L44,'2BR_F-combined'!$B:$B,0),MATCH(Council_Area,'2BR_F-combined'!$C$1:$BH$1,0))) -> 470 | U44: =IF(MOD(Q44,4)=1,T44,U43) -> 480 | V44: =U44*(R44)/7 -> 6240 | W44: =$B$53/4*BH44/_xlfn.XLOOKUP(Q_end,cpi!A:A,cpi!B:B) -> 150.3801 | X44: =V44+W44 -> 6390.3801 | Y44: =BG44-X44 -> 2327.795 | Z44: =Y44*$B$47 -> 744.8944 | AA44: =(Y44+Z44)*eff_invest -> 3072.6894 | AB44: =AA44*(_xlfn.XLOOKUP(Q_end,cpi!A:A,cpi!B:B)/BH44) -> 4086.5639 | AC44: {=INDEX('msci-indices'!C:C,MATCH($L44,'msci-indices'!$B:$B)-2)} -> 1249.9269 | AD44: {=INDEX('msci-indices'!D:D,MATCH($L44,'msci-indices'!$B:$B)-2)} -> 1171.169 | AE44: =AI43+AA44 -> 556155.47 | AF44: {=INDEX('msci-indices'!C:C,MATCH($L44,'msci-indices'!$B:$B)+1)} -> 1263.5195 | AG44: {=INDEX('msci-indices'!D:D,MATCH($L44,'msci-indices'!$B:$B)+1)} -> 1218.4798 | AH44: =(InvestFees/4)*AE44 -> 347.59717 | AI44: =((AF44/AC44)*GlobalPortfolio+(AG44/AD44)*AusPortfolio)*AE44-AH44 -> 566781.46 | AJ44: =AJ43+AA44 -> 377079.64 | AK44: =AI44-AJ44 -> 189701.82 | AL44: =AJ44*(_xlfn.XLOOKUP(Q_end,cpi!A:A,cpi!B:B)/BH44) -> 501502.06 | AM44: {=SUMPRODUCT($AA$3:AA44,_xlfn.SORTBY($BH$3:BH44,_xlfn.SEQUENCE(ROWS($BH$3:BH44)),-1)/$BH$3)} -> 461010.95 | AN44: =AI44-AM44 -> 105770.51 | AO44: =IF($B$49="Real gains",MAX($B$50*AN44,0),IF($B$49="Discounted nominal gains",MAX($B$50*AK44/2,0),0)) -> 0 | AP44: =AI44-AO44 -> 566781.46 | AR44: =IF($B$10="3BR_H", INDEX('ns-combined'!$C:$BH,MATCH($L44,'ns-combined'!$B:$B,0),MATCH(Council_Area,'ns-combined'!$C$1:$BH$1,0))*1000, INDEX('s-combined'!$C:$BH,MATCH($L44,'s-combined'!$B:$B,0),MATCH(Council_Area,'s-combined'!$C$1:$BH$1,0))*1000) -> 885000 | AS44: =AS43+$AS$3 -> 48300 | AT44: 0 | AU44: =SUM($B$28:$B$29)*AR44 -> 17700 | AV44: =AR44*$B$15/4 -> 2544.375 | AW44: =SUM($AV$3:AV44) -> 73280.875 | AX44: =AR44-AS44-AU44-AW44 -> 745719.12 | AY44: =$B$36*V44 -> 2184 | AZ44: =SUM(AY44:AY44)*4/AR44 -> 0.0098711864 | BA44: =SUM(AY44:AY44)/V44 -> 0.35 | BB44: =IF(MortgageRate="Discounted",_xlfn.XLOOKUP(L44,'mortgage-rates'!$A:$A,'mortgage-rates'!$E:$E)/100,_xlfn.XLOOKUP(L44,'mortgage-rates'!$A:$A,'mortgage-rates'!$D:$D)/100) -> 0.0459 | BC44: =BC43-BF43 -> 278968.55 | BD44: =IF($B$16*12/3-Q44+1>0,-PMT($BB44/4,$B$16*12/3-Q44+1,BC44),0) -> 6534.1751 | BE44: =BC44*($BB44/4) -> 3201.1642 | BF44: =BD44-BE44 -> 3333.0109 | BG44: =AT44+AY44+BD44 -> 8718.1751 | BH44: =INDEX(cpi!B:B,MATCH($L44,cpi!A:A)) -> 108.8 | BI44: =100*BH44/BH$3 -> 128.6052 | BJ44: =100*AC44/AC$3 -> 165.57963 | BK44: =100*AD44/AD$3 -> 164.26941 | BL44: =BJ44*GlobalPortfolio+BK44*AusPortfolio -> 165.18657 | BM44: =100*AE44/$AE$3 -> 350.1575 | BN44: =100*AR44/AR$3 -> 192.3913 | BO44: =100*AX44/AX$3 -> 166.33357
A45: Marginal income tax rate (including Medicare levy) | B45: 0.47 | C45: 0.32 | L45: =DATE(YEAR(L44),MONTH(L44)+3,1) -> 42614 | M45: =AP45 -> 599328.34 | N45: =AX45-BC45 -> 466389.21 | O45: =M45/N45 -> 1.285039 | P45: =X45/BG45 -> 0.74178744 | Q45: 43 | R45: =EOMONTH(L45,0)-EOMONTH(L45,-3) -> 92 | T45: =IF($B$10="3BR_H", INDEX('3BR_H-combined'!$C:$BH,MATCH($L45,'3BR_H-combined'!$B:$B,0),MATCH(Council_Area,'3BR_H-combined'!$C$1:$BH$1,0)), INDEX('2BR_F-combined'!$C:$BH,MATCH($L45,'2BR_F-combined'!$B:$B,0),MATCH(Council_Area,'2BR_F-combined'!$C$1:$BH$1,0))) -> 470 | U45: =IF(MOD(Q45,4)=1,T45,U44) -> 480 | V45: =U45*(R45)/7 -> 6308.5714 | W45: =$B$53/4*BH45/_xlfn.XLOOKUP(Q_end,cpi!A:A,cpi!B:B) -> 151.07118 | X45: =V45+W45 -> 6459.6426 | Y45: =BG45-X45 -> 2248.5698 | Z45: =Y45*$B$47 -> 719.54234 | AA45: =(Y45+Z45)*eff_invest -> 2968.1121 | AB45: =AA45*(_xlfn.XLOOKUP(Q_end,cpi!A:A,cpi!B:B)/BH45) -> 3929.422 | AC45: {=INDEX('msci-indices'!C:C,MATCH($L45,'msci-indices'!$B:$B)-2)} -> 1263.5195 | AD45: {=INDEX('msci-indices'!D:D,MATCH($L45,'msci-indices'!$B:$B)-2)} -> 1218.4798 | AE45: =AI44+AA45 -> 569749.58 | AF45: {=INDEX('msci-indices'!C:C,MATCH($L45,'msci-indices'!$B:$B)+1)} -> 1329.0259 | AG45: {=INDEX('msci-indices'!D:D,MATCH($L45,'msci-indices'!$B:$B)+1)} -> 1284.478 | AH45: =(InvestFees/4)*AE45 -> 356.09349 | AI45: =((AF45/AC45)*GlobalPortfolio+(AG45/AD45)*AusPortfolio)*AE45-AH45 -> 599328.34 | AJ45: =AJ44+AA45 -> 380047.75 | AK45: =AI45-AJ45 -> 219280.59 | AL45: =AJ45*(_xlfn.XLOOKUP(Q_end,cpi!A:A,cpi!B:B)/BH45) -> 503137.33 | AM45: {=SUMPRODUCT($AA$3:AA45,_xlfn.SORTBY($BH$3:BH45,_xlfn.SEQUENCE(ROWS($BH$3:BH45)),-1)/$BH$3)} -> 466364.97 | AN45: =AI45-AM45 -> 132963.37 | AO45: =IF($B$49="Real gains",MAX($B$50*AN45,0),IF($B$49="Discounted nominal gains",MAX($B$50*AK45/2,0),0)) -> 0 | AP45: =AI45-AO45 -> 599328.34 | AR45: =IF($B$10="3BR_H", INDEX('ns-combined'!$C:$BH,MATCH($L45,'ns-combined'!$B:$B,0),MATCH(Council_Area,'ns-combined'!$C$1:$BH$1,0))*1000, INDEX('s-combined'!$C:$BH,MATCH($L45,'s-combined'!$B:$B,0),MATCH(Council_Area,'s-combined'!$C$1:$BH$1,0))*1000) -> 885000 | AS45: =AS44+$AS$3 -> 49450 | AT45: 0 | AU45: =SUM($B$28:$B$29)*AR45 -> 17700 | AV45: =AR45*$B$15/4 -> 2544.375 | AW45: =SUM($AV$3:AV45) -> 75825.25 | AX45: =AR45-AS45-AU45-AW45 -> 742024.75 | AY45: =$B$36*V45 -> 2208 | AZ45: =SUM(AY45:AY45)*4/AR45 -> 0.009979661 | BA45: =SUM(AY45:AY45)/V45 -> 0.35 | BB45: =IF(MortgageRate="Discounted",_xlfn.XLOOKUP(L45,'mortgage-rates'!$A:$A,'mortgage-rates'!$E:$E)/100,_xlfn.XLOOKUP(L45,'mortgage-rates'!$A:$A,'mortgage-rates'!$D:$D)/100) -> 0.0451 | BC45: =BC44-BF44 -> 275635.54 | BD45: =IF($B$16*12/3-Q45+1>0,-PMT($BB45/4,$B$16*12/3-Q45+1,BC45),0) -> 6500.2124 | BE45: =BC45*($BB45/4) -> 3107.7908 | BF45: =BD45-BE45 -> 3392.4217 | BG45: =AT45+AY45+BD45 -> 8708.2124 | BH45: =INDEX(cpi!B:B,MATCH($L45,cpi!A:A)) -> 109.3 | BI45: =100*BH45/BH$3 -> 129.19622 | BJ45: =100*AC45/AC$3 -> 167.38027 | BK45: =100*AD45/AD$3 -> 170.90526 | BL45: =BJ45*GlobalPortfolio+BK45*AusPortfolio -> 168.43777 | BM45: =100*AE45/$AE$3 -> 358.7164 | BN45: =100*AR45/AR$3 -> 192.3913 | BO45: =100*AX45/AX$3 -> 165.50953
A46: Concessional super contributions tax rate | B46: 0.15 | C46: 0.15 | L46: =DATE(YEAR(L45),MONTH(L45)+3,1) -> 42705 | M46: =AP46 -> 620365.83 | N46: =AX46-BC46 -> 552074.25 | O46: =M46/N46 -> 1.1237 | P46: =X46/BG46 -> 0.7418668 | Q46: 44 | R46: =EOMONTH(L46,0)-EOMONTH(L46,-3) -> 92 | T46: =IF($B$10="3BR_H", INDEX('3BR_H-combined'!$C:$BH,MATCH($L46,'3BR_H-combined'!$B:$B,0),MATCH(Council_Area,'3BR_H-combined'!$C$1:$BH$1,0)), INDEX('2BR_F-combined'!$C:$BH,MATCH($L46,'2BR_F-combined'!$B:$B,0),MATCH(Council_Area,'2BR_F-combined'!$C$1:$BH$1,0))) -> 480 | U46: =IF(MOD(Q46,4)=1,T46,U45) -> 480 | V46: =U46*(R46)/7 -> 6308.5714 | W46: =$B$53/4*BH46/_xlfn.XLOOKUP(Q_end,cpi!A:A,cpi!B:B) -> 151.76227 | X46: =V46+W46 -> 6460.3337 | Y46: =BG46-X46 -> 2247.8787 | Z46: =Y46*$B$47 -> 719.32119 | AA46: =(Y46+Z46)*eff_invest -> 2967.1999 | AB46: =AA46*(_xlfn.XLOOKUP(Q_end,cpi!A:A,cpi!B:B)/BH46) -> 3910.3263 | AC46: {=INDEX('msci-indices'!C:C,MATCH($L46,'msci-indices'!$B:$B)-2)} -> 1329.0259 | AD46: {=INDEX('msci-indices'!D:D,MATCH($L46,'msci-indices'!$B:$B)-2)} -> 1284.478 | AE46: =AI45+AA46 -> 602295.54 | AF46: {=INDEX('msci-indices'!C:C,MATCH($L46,'msci-indices'!$B:$B)+1)} -> 1355.3009 | AG46: {=INDEX('msci-indices'!D:D,MATCH($L46,'msci-indices'!$B:$B)+1)} -> 1356.3585 | AH46: =(InvestFees/4)*AE46 -> 376.43471 | AI46: =((AF46/AC46)*GlobalPortfolio+(AG46/AD46)*AusPortfolio)*AE46-AH46 -> 620365.83 | AJ46: =AJ45+AA46 -> 383014.95 | AK46: =AI46-AJ46 -> 237350.88 | AL46: =AJ46*(_xlfn.XLOOKUP(Q_end,cpi!A:A,cpi!B:B)/BH46) -> 504756.5 | AM46: {=SUMPRODUCT($AA$3:AA46,_xlfn.SORTBY($BH$3:BH46,_xlfn.SEQUENCE(ROWS($BH$3:BH46)),-1)/$BH$3)} -> 471716.26 | AN46: =AI46-AM46 -> 148649.56 | AO46: =IF($B$49="Real gains",MAX($B$50*AN46,0),IF($B$49="Discounted nominal gains",MAX($B$50*AK46/2,0),0)) -> 0 | AP46: =AI46-AO46 -> 620365.83 | AR46: =IF($B$10="3BR_H", INDEX('ns-combined'!$C:$BH,MATCH($L46,'ns-combined'!$B:$B,0),MATCH(Council_Area,'ns-combined'!$C$1:$BH$1,0))*1000, INDEX('s-combined'!$C:$BH,MATCH($L46,'s-combined'!$B:$B,0),MATCH(Council_Area,'s-combined'!$C$1:$BH$1,0))*1000) -> 973000 | AS46: =AS45+$AS$3 -> 50600 | AT46: 0 | AU46: =SUM($B$28:$B$29)*AR46 -> 19460 | AV46: =AR46*$B$15/4 -> 2797.375 | AW46: =SUM($AV$3:AV46) -> 78622.625 | AX46: =AR46-AS46-AU46-AW46 -> 824317.38 | AY46: =$B$36*V46 -> 2208 | AZ46: =SUM(AY46:AY46)*4/AR46 -> 0.0090770812 | BA46: =SUM(AY46:AY46)/V46 -> 0.35 | BB46: =IF(MortgageRate="Discounted",_xlfn.XLOOKUP(L46,'mortgage-rates'!$A:$A,'mortgage-rates'!$E:$E)/100,_xlfn.XLOOKUP(L46,'mortgage-rates'!$A:$A,'mortgage-rates'!$D:$D)/100) -> 0.0451 | BC46: =BC45-BF45 -> 272243.12 | BD46: =IF($B$16*12/3-Q46+1>0,-PMT($BB46/4,$B$16*12/3-Q46+1,BC46),0) -> 6500.2124 | BE46: =BC46*($BB46/4) -> 3069.5412 | BF46: =BD46-BE46 -> 3430.6712 | BG46: =AT46+AY46+BD46 -> 8708.2124 | BH46: =INDEX(cpi!B:B,MATCH($L46,cpi!A:A)) -> 109.8 | BI46: =100*BH46/BH$3 -> 129.78723 | BJ46: =100*AC46/AC$3 -> 176.05799 | BK46: =100*AD46/AD$3 -> 180.16225 | BL46: =BJ46*GlobalPortfolio+BK46*AusPortfolio -> 177.28927 | BM46: =100*AE46/$AE$3 -> 379.20745 | BN46: =100*AR46/AR$3 -> 211.52174 | BO46: =100*AX46/AX$3 -> 183.865
A47: Tax concessions on contributions (0% if not investing through super) | B47: =IF(B44="Yes",B45-B46,0) -> 0.32 | L47: =DATE(YEAR(L46),MONTH(L46)+3,1) -> 42795 | M47: =AP47 -> 659442 | N47: =AX47-BC47 -> 480227.42 | O47: =M47/N47 -> 1.3731869 | P47: =X47/BG47 -> 0.74054909 | Q47: 45 | R47: =EOMONTH(L47,0)-EOMONTH(L47,-3) -> 90 | T47: =IF($B$10="3BR_H", INDEX('3BR_H-combined'!$C:$BH,MATCH($L47,'3BR_H-combined'!$B:$B,0),MATCH(Council_Area,'3BR_H-combined'!$C$1:$BH$1,0)), INDEX('2BR_F-combined'!$C:$BH,MATCH($L47,'2BR_F-combined'!$B:$B,0),MATCH(Council_Area,'2BR_F-combined'!$C$1:$BH$1,0))) -> 490 | U47: =IF(MOD(Q47,4)=1,T47,U46) -> 490 | V47: =U47*(R47)/7 -> 6300 | W47: =$B$53/4*BH47/_xlfn.XLOOKUP(Q_end,cpi!A:A,cpi!B:B) -> 152.72979 | X47: =V47+W47 -> 6452.7298 | Y47: =BG47-X47 -> 2260.7099 | Z47: =Y47*$B$47 -> 723.42716 | AA47: =(Y47+Z47)*eff_invest -> 2984.137 | AB47: =AA47*(_xlfn.XLOOKUP(Q_end,cpi!A:A,cpi!B:B)/BH47) -> 3907.7342 | AC47: {=INDEX('msci-indices'!C:C,MATCH($L47,'msci-indices'!$B:$B)-2)} -> 1355.3009 | AD47: {=INDEX('msci-indices'!D:D,MATCH($L47,'msci-indices'!$B:$B)-2)} -> 1356.3585 | AE47: =AI46+AA47 -> 623349.96 | AF47: {=INDEX('msci-indices'!C:C,MATCH($L47,'msci-indices'!$B:$B)+1)} -> 1439.618 | AG47: {=INDEX('msci-indices'!D:D,MATCH($L47,'msci-indices'!$B:$B)+1)} -> 1424.0685 | AH47: =(InvestFees/4)*AE47 -> 389.59373 | AI47: =((AF47/AC47)*GlobalPortfolio+(AG47/AD47)*AusPortfolio)*AE47-AH47 -> 659442 | AJ47: =AJ46+AA47 -> 385999.09 | AK47: =AI47-AJ47 -> 273442.91 | AL47: =AJ47*(_xlfn.XLOOKUP(Q_end,cpi!A:A,cpi!B:B)/BH47) -> 505466.68 | AM47: {=SUMPRODUCT($AA$3:AA47,_xlfn.SORTBY($BH$3:BH47,_xlfn.SEQUENCE(ROWS($BH$3:BH47)),-1)/$BH$3)} -> 477468.06 | AN47: =AI47-AM47 -> 181973.94 | AO47: =IF($B$49="Real gains",MAX($B$50*AN47,0),IF($B$49="Discounted nominal gains",MAX($B$50*AK47/2,0),0)) -> 0 | AP47: =AI47-AO47 -> 659442 | AR47: =IF($B$10="3BR_H", INDEX('ns-combined'!$C:$BH,MATCH($L47,'ns-combined'!$B:$B,0),MATCH(Council_Area,'ns-combined'!$C$1:$BH$1,0))*1000, INDEX('s-combined'!$C:$BH,MATCH($L47,'s-combined'!$B:$B,0),MATCH(Council_Area,'s-combined'!$C$1:$BH$1,0))*1000) -> 900000 | AS47: =AS46+$AS$3 -> 51750 | AT47: 0 | AU47: =SUM($B$28:$B$29)*AR47 -> 18000 | AV47: =AR47*$B$15/4 -> 2587.5 | AW47: =SUM($AV$3:AV47) -> 81210.125 | AX47: =AR47-AS47-AU47-AW47 -> 749039.88 | AY47: =$B$36*V47 -> 2205 | AZ47: =SUM(AY47:AY47)*4/AR47 -> 0.0098 | BA47: =SUM(AY47:AY47)/V47 -> 0.35 | BB47: =IF(MortgageRate="Discounted",_xlfn.XLOOKUP(L47,'mortgage-rates'!$A:$A,'mortgage-rates'!$E:$E)/100,_xlfn.XLOOKUP(L47,'mortgage-rates'!$A:$A,'mortgage-rates'!$D:$D)/100) -> 0.0453 | BC47: =BC46-BF46 -> 268812.45 | BD47: =IF($B$16*12/3-Q47+1>0,-PMT($BB47/4,$B$16*12/3-Q47+1,BC47),0) -> 6508.4397 | BE47: =BC47*($BB47/4) -> 3044.301 | BF47: =BD47-BE47 -> 3464.1387 | BG47: =AT47+AY47+BD47 -> 8713.4397 | BH47: =INDEX(cpi!B:B,MATCH($L47,cpi!A:A)) -> 110.5 | BI47: =100*BH47/BH$3 -> 130.61466 | BJ47: =100*AC47/AC$3 -> 179.53868 | BK47: =100*AD47/AD$3 -> 190.24428 | BL47: =BJ47*GlobalPortfolio+BK47*AusPortfolio -> 182.75036 | BM47: =100*AE47/$AE$3 -> 392.4634 | BN47: =100*AR47/AR$3 -> 195.65217 | BO47: =100*AX47/AX$3 -> 167.07426
A48: Marginal income tax rate on withdrawal | B48: 0.32 | C48: 0.32 | L48: =DATE(YEAR(L47),MONTH(L47)+3,1) -> 42887 | M48: =AP48 -> 676928.16 | N48: =AX48-BC48 -> 650950.94 | O48: =M48/N48 -> 1.0399066 | P48: =X48/BG48 -> 0.7482801 | Q48: 46 | R48: =EOMONTH(L48,0)-EOMONTH(L48,-3) -> 91 | T48: =IF($B$10="3BR_H", INDEX('3BR_H-combined'!$C:$BH,MATCH($L48,'3BR_H-combined'!$B:$B,0),MATCH(Council_Area,'3BR_H-combined'!$C$1:$BH$1,0)), INDEX('2BR_F-combined'!$C:$BH,MATCH($L48,'2BR_F-combined'!$B:$B,0),MATCH(Council_Area,'2BR_F-combined'!$C$1:$BH$1,0))) -> 485 | U48: =IF(MOD(Q48,4)=1,T48,U47) -> 490 | V48: =U48*(R48)/7 -> 6370 | W48: =$B$53/4*BH48/_xlfn.XLOOKUP(Q_end,cpi!A:A,cpi!B:B) -> 153.28265 | X48: =V48+W48 -> 6523.2827 | Y48: =BG48-X48 -> 2194.419 | Z48: =Y48*$B$47 -> 702.21407 | AA48: =(Y48+Z48)*eff_invest -> 2896.633 | AB48: =AA48*(_xlfn.XLOOKUP(Q_end,cpi!A:A,cpi!B:B)/BH48) -> 3779.4662 | AC48: {=INDEX('msci-indices'!C:C,MATCH($L48,'msci-indices'!$B:$B)-2)} -> 1439.618 | AD48: {=INDEX('msci-indices'!D:D,MATCH($L48,'msci-indices'!$B:$B)-2)} -> 1424.0685 | AE48: =AI47+AA48 -> 662338.63 | AF48: {=INDEX('msci-indices'!C:C,MATCH($L48,'msci-indices'!$B:$B)+1)} -> 1498.0163 | AG48: {=INDEX('msci-indices'!D:D,MATCH($L48,'msci-indices'!$B:$B)+1)} -> 1396.8057 | AH48: =(InvestFees/4)*AE48 -> 413.96164 | AI48: =((AF48/AC48)*GlobalPortfolio+(AG48/AD48)*AusPortfolio)*AE48-AH48 -> 676928.16 | AJ48: =AJ47+AA48 -> 388895.72 | AK48: =AI48-AJ48 -> 288032.44 | AL48: =AJ48*(_xlfn.XLOOKUP(Q_end,cpi!A:A,cpi!B:B)/BH48) -> 507423 | AM48: {=SUMPRODUCT($AA$3:AA48,_xlfn.SORTBY($BH$3:BH48,_xlfn.SEQUENCE(ROWS($BH$3:BH48)),-1)/$BH$3)} -> 482608.08 | AN48: =AI48-AM48 -> 194320.09 | AO48: =IF($B$49="Real gains",MAX($B$50*AN48,0),IF($B$49="Discounted nominal gains",MAX($B$50*AK48/2,0),0)) -> 0 | AP48: =AI48-AO48 -> 676928.16 | AR48: =IF($B$10="3BR_H", INDEX('ns-combined'!$C:$BH,MATCH($L48,'ns-combined'!$B:$B,0),MATCH(Council_Area,'ns-combined'!$C$1:$BH$1,0))*1000, INDEX('s-combined'!$C:$BH,MATCH($L48,'s-combined'!$B:$B,0),MATCH(Council_Area,'s-combined'!$C$1:$BH$1,0))*1000) -> 1075000 | AS48: =AS47+$AS$3 -> 52900 | AT48: 0 | AU48: =SUM($B$28:$B$29)*AR48 -> 21500 | AV48: =AR48*$B$15/4 -> 3090.625 | AW48: =SUM($AV$3:AV48) -> 84300.75 | AX48: =AR48-AS48-AU48-AW48 -> 916299.25 | AY48: =$B$36*V48 -> 2229.5 | AZ48: =SUM(AY48:AY48)*4/AR48 -> 0.008295814 | BA48: =SUM(AY48:AY48)/V48 -> 0.35 | BB48: =IF(MortgageRate="Discounted",_xlfn.XLOOKUP(L48,'mortgage-rates'!$A:$A,'mortgage-rates'!$E:$E)/100,_xlfn.XLOOKUP(L48,'mortgage-rates'!$A:$A,'mortgage-rates'!$D:$D)/100) -> 0.0448 | BC48: =BC47-BF47 -> 265348.31 | BD48: =IF($B$16*12/3-Q48+1>0,-PMT($BB48/4,$B$16*12/3-Q48+1,BC48),0) -> 6488.2016 | BE48: =BC48*($BB48/4) -> 2971.9011 | BF48: =BD48-BE48 -> 3516.3005 | BG48: =AT48+AY48+BD48 -> 8717.7016 | BH48: =INDEX(cpi!B:B,MATCH($L48,cpi!A:A)) -> 110.9 | BI48: =100*BH48/BH$3 -> 131.08747 | BJ48: =100*AC48/AC$3 -> 190.70829 | BK48: =100*AD48/AD$3 -> 199.74136 | BL48: =BJ48*GlobalPortfolio+BK48*AusPortfolio -> 193.41821 | BM48: =100*AE48/$AE$3 -> 417.0108 | BN48: =100*AR48/AR$3 -> 233.69565 | BO48: =100*AX48/AX$3 -> 204.38167
A49: Consider CGT? Note: Unlikely to reflect realistic tax liabilities | B49: No | C49: No | L49: =DATE(YEAR(L48),MONTH(L48)+3,1) -> 42979 | M49: =AP49 -> 705331.11 | N49: =AX49-BC49 -> 528085.99 | O49: =M49/N49 -> 1.3356369 | P49: =X49/BG49 -> 0.75459689 | Q49: 47 | R49: =EOMONTH(L49,0)-EOMONTH(L49,-3) -> 92 | T49: =IF($B$10="3BR_H", INDEX('3BR_H-combined'!$C:$BH,MATCH($L49,'3BR_H-combined'!$B:$B,0),MATCH(Council_Area,'3BR_H-combined'!$C$1:$BH$1,0)), INDEX('2BR_F-combined'!$C:$BH,MATCH($L49,'2BR_F-combined'!$B:$B,0),MATCH(Council_Area,'2BR_F-combined'!$C$1:$BH$1,0))) -> 490 | U49: =IF(MOD(Q49,4)=1,T49,U48) -> 490 | V49: =U49*(R49)/7 -> 6440 | W49: =$B$53/4*BH49/_xlfn.XLOOKUP(Q_end,cpi!A:A,cpi!B:B) -> 153.83552 | X49: =V49+W49 -> 6593.8355 | Y49: =BG49-X49 -> 2144.387 | Z49: =Y49*$B$47 -> 686.20383 | AA49: =(Y49+Z49)*eff_invest -> 2830.5908 | AB49: =AA49*(_xlfn.XLOOKUP(Q_end,cpi!A:A,cpi!B:B)/BH49) -> 3680.0224 | AC49: {=INDEX('msci-indices'!C:C,MATCH($L49,'msci-indices'!$B:$B)-2)} -> 1498.0163 | AD49: {=INDEX('msci-indices'!D:D,MATCH($L49,'msci-indices'!$B:$B)-2)} -> 1396.8057 | AE49: =AI48+AA49 -> 679758.76 | AF49: {=INDEX('msci-indices'!C:C,MATCH($L49,'msci-indices'!$B:$B)+1)} -> 1573.3489 | AG49: {=INDEX('msci-indices'!D:D,MATCH($L49,'msci-indices'!$B:$B)+1)} -> 1410.974 | AH49: =(InvestFees/4)*AE49 -> 424.84922 | AI49: =((AF49/AC49)*GlobalPortfolio+(AG49/AD49)*AusPortfolio)*AE49-AH49 -> 705331.11 | AJ49: =AJ48+AA49 -> 391726.31 | AK49: =AI49-AJ49 -> 313604.8 | AL49: =AJ49*(_xlfn.XLOOKUP(Q_end,cpi!A:A,cpi!B:B)/BH49) -> 509279.4 | AM49: {=SUMPRODUCT($AA$3:AA49,_xlfn.SORTBY($BH$3:BH49,_xlfn.SEQUENCE(ROWS($BH$3:BH49)),-1)/$BH$3)} -> 487696.96 | AN49: =AI49-AM49 -> 217634.16 | AO49: =IF($B$49="Real gains",MAX($B$50*AN49,0),IF($B$49="Discounted nominal gains",MAX($B$50*AK49/2,0),0)) -> 0 | AP49: =AI49-AO49 -> 705331.11 | AR49: =IF($B$10="3BR_H", INDEX('ns-combined'!$C:$BH,MATCH($L49,'ns-combined'!$B:$B,0),MATCH(Council_Area,'ns-combined'!$C$1:$BH$1,0))*1000, INDEX('s-combined'!$C:$BH,MATCH($L49,'s-combined'!$B:$B,0),MATCH(Council_Area,'s-combined'!$C$1:$BH$1,0))*1000) -> 950000 | AS49: =AS48+$AS$3 -> 54050 | AT49: 0 | AU49: =SUM($B$28:$B$29)*AR49 -> 19000 | AV49: =AR49*$B$15/4 -> 2731.25 | AW49: =SUM($AV$3:AV49) -> 87032 | AX49: =AR49-AS49-AU49-AW49 -> 789918 | AY49: =$B$36*V49 -> 2254 | AZ49: =SUM(AY49:AY49)*4/AR49 -> 0.0094905263 | BA49: =SUM(AY49:AY49)/V49 -> 0.35 | BB49: =IF(MortgageRate="Discounted",_xlfn.XLOOKUP(L49,'mortgage-rates'!$A:$A,'mortgage-rates'!$E:$E)/100,_xlfn.XLOOKUP(L49,'mortgage-rates'!$A:$A,'mortgage-rates'!$D:$D)/100) -> 0.0447 | BC49: =BC48-BF48 -> 261832.01 | BD49: =IF($B$16*12/3-Q49+1>0,-PMT($BB49/4,$B$16*12/3-Q49+1,BC49),0) -> 6484.2225 | BE49: =BC49*($BB49/4) -> 2925.9727 | BF49: =BD49-BE49 -> 3558.2498 | BG49: =AT49+AY49+BD49 -> 8738.2225 | BH49: =INDEX(cpi!B:B,MATCH($L49,cpi!A:A)) -> 111.3 | BI49: =100*BH49/BH$3 -> 131.56028 | BJ49: =100*AC49/AC$3 -> 198.4444 | BK49: =100*AD49/AD$3 -> 195.91744 | BL49: =BJ49*GlobalPortfolio+BK49*AusPortfolio -> 197.68631 | BM49: =100*AE49/$AE$3 -> 427.97858 | BN49: =100*AR49/AR$3 -> 206.52174 | BO49: =100*AX49/AX$3 -> 176.19218
A50: Marginal CGT & dividend income tax rate (0% if investing through super) | B50: =IF(OR(B44="Yes",B49="No"),0,MAX(0.3,B48)) -> 0 | L50: =DATE(YEAR(L49),MONTH(L49)+3,1) -> 43070 | M50: =AP50 -> 751483.09 | N50: =AX50-BC50 -> 615704.24 | O50: =M50/N50 -> 1.2205261 | P50: =X50/BG50 -> 0.75337271 | Q50: 48 | R50: =EOMONTH(L50,0)-EOMONTH(L50,-3) -> 92 | T50: =IF($B$10="3BR_H", INDEX('3BR_H-combined'!$C:$BH,MATCH($L50,'3BR_H-combined'!$B:$B,0),MATCH(Council_Area,'3BR_H-combined'!$C$1:$BH$1,0)), INDEX('2BR_F-combined'!$C:$BH,MATCH($L50,'2BR_F-combined'!$B:$B,0),MATCH(Council_Area,'2BR_F-combined'!$C$1:$BH$1,0))) -> 500 | U50: =IF(MOD(Q50,4)=1,T50,U49) -> 490 | V50: =U50*(R50)/7 -> 6440 | W50: =$B$53/4*BH50/_xlfn.XLOOKUP(Q_end,cpi!A:A,cpi!B:B) -> 154.94126 | X50: =V50+W50 -> 6594.9413 | Y50: =BG50-X50 -> 2158.948 | Z50: =Y50*$B$47 -> 690.86336 | AA50: =(Y50+Z50)*eff_invest -> 2849.8114 | AB50: =AA50*(_xlfn.XLOOKUP(Q_end,cpi!A:A,cpi!B:B)/BH50) -> 3678.57 | AC50: {=INDEX('msci-indices'!C:C,MATCH($L50,'msci-indices'!$B:$B)-2)} -> 1573.3489 | AD50: {=INDEX('msci-indices'!D:D,MATCH($L50,'msci-indices'!$B:$B)-2)} -> 1410.974 | AE50: =AI49+AA50 -> 708180.93 | AF50: {=INDEX('msci-indices'!C:C,MATCH($L50,'msci-indices'!$B:$B)+1)} -> 1659.3666 | AG50: {=INDEX('msci-indices'!D:D,MATCH($L50,'msci-indices'!$B:$B)+1)} -> 1521.5021 | AH50: =(InvestFees/4)*AE50 -> 442.61308 | AI50: =((AF50/AC50)*GlobalPortfolio+(AG50/AD50)*AusPortfolio)*AE50-AH50 -> 751483.09 | AJ50: =AJ49+AA50 -> 394576.12 | AK50: =AI50-AJ50 -> 356906.97 | AL50: =AJ50*(_xlfn.XLOOKUP(Q_end,cpi!A:A,cpi!B:B)/BH50) -> 509323.51 | AM50: {=SUMPRODUCT($AA$3:AA50,_xlfn.SORTBY($BH$3:BH50,_xlfn.SEQUENCE(ROWS($BH$3:BH50)),-1)/$BH$3)} -> 493568.27 | AN50: =AI50-AM50 -> 257914.83 | AO50: =IF($B$49="Real gains",MAX($B$50*AN50,0),IF($B$49="Discounted nominal gains",MAX($B$50*AK50/2,0),0)) -> 0 | AP50: =AI50-AO50 -> 751483.09 | AR50: =IF($B$10="3BR_H", INDEX('ns-combined'!$C:$BH,MATCH($L50,'ns-combined'!$B:$B,0),MATCH(Council_Area,'ns-combined'!$C$1:$BH$1,0))*1000, INDEX('s-combined'!$C:$BH,MATCH($L50,'s-combined'!$B:$B,0),MATCH(Council_Area,'s-combined'!$C$1:$BH$1,0))*1000) -> 1040000 | AS50: =AS49+$AS$3 -> 55200 | AT50: 0 | AU50: =SUM($B$28:$B$29)*AR50 -> 20800 | AV50: =AR50*$B$15/4 -> 2990 | AW50: =SUM($AV$3:AV50) -> 90022 | AX50: =AR50-AS50-AU50-AW50 -> 873978 | AY50: =$B$36*V50 -> 2254 | AZ50: =SUM(AY50:AY50)*4/AR50 -> 0.0086692308 | BA50: =SUM(AY50:AY50)/V50 -> 0.35 | BB50: =IF(MortgageRate="Discounted",_xlfn.XLOOKUP(L50,'mortgage-rates'!$A:$A,'mortgage-rates'!$E:$E)/100,_xlfn.XLOOKUP(L50,'mortgage-rates'!$A:$A,'mortgage-rates'!$D:$D)/100) -> 0.0451 | BC50: =BC49-BF49 -> 258273.76 | BD50: =IF($B$16*12/3-Q50+1>0,-PMT($BB50/4,$B$16*12/3-Q50+1,BC50),0) -> 6499.8893 | BE50: =BC50*($BB50/4) -> 2912.0367 | BF50: =BD50-BE50 -> 3587.8526 | BG50: =AT50+AY50+BD50 -> 8753.8893 | BH50: =INDEX(cpi!B:B,MATCH($L50,cpi!A:A)) -> 112.1 | BI50: =100*BH50/BH$3 -> 132.50591 | BJ50: =100*AC50/AC$3 -> 208.42381 | BK50: =100*AD50/AD$3 -> 197.90471 | BL50: =BJ50*GlobalPortfolio+BK50*AusPortfolio -> 205.26808 | BM50: =100*AE50/$AE$3 -> 445.87328 | BN50: =100*AR50/AR$3 -> 226.08696 | BO50: =100*AX50/AX$3 -> 194.94187
L51: =DATE(YEAR(L50),MONTH(L50)+3,1) -> 43160 | M51: =AP51 -> 738621.65 | N51: =AX51-BC51 -> 516462.47 | O51: =M51/N51 -> 1.4301555 | P51: =X51/BG51 -> 0.75250575 | Q51: 49 | R51: =EOMONTH(L51,0)-EOMONTH(L51,-3) -> 90 | T51: =IF($B$10="3BR_H", INDEX('3BR_H-combined'!$C:$BH,MATCH($L51,'3BR_H-combined'!$B:$B,0),MATCH(Council_Area,'3BR_H-combined'!$C$1:$BH$1,0)), INDEX('2BR_F-combined'!$C:$BH,MATCH($L51,'2BR_F-combined'!$B:$B,0),MATCH(Council_Area,'2BR_F-combined'!$C$1:$BH$1,0))) -> 500 | U51: =IF(MOD(Q51,4)=1,T51,U50) -> 500 | V51: =U51*(R51)/7 -> 6428.5714 | W51: =$B$53/4*BH51/_xlfn.XLOOKUP(Q_end,cpi!A:A,cpi!B:B) -> 155.77056 | X51: =V51+W51 -> 6584.342 | Y51: =BG51-X51 -> 2165.5473 | Z51: =Y51*$B$47 -> 692.97512 | AA51: =(Y51+Z51)*eff_invest -> 2858.5224 | AB51: =AA51*(_xlfn.XLOOKUP(Q_end,cpi!A:A,cpi!B:B)/BH51) -> 3670.1703 | AC51: {=INDEX('msci-indices'!C:C,MATCH($L51,'msci-indices'!$B:$B)-2)} -> 1659.3666 | AD51: {=INDEX('msci-indices'!D:D,MATCH($L51,'msci-indices'!$B:$B)-2)} -> 1521.5021 | AE51: =AI50+AA51 -> 754341.62 | AF51: {=INDEX('msci-indices'!C:C,MATCH($L51,'msci-indices'!$B:$B)+1)} -> 1639.7569 | AG51: {=INDEX('msci-indices'!D:D,MATCH($L51,'msci-indices'!$B:$B)+1)} -> 1460.9363 | AH51: =(InvestFees/4)*AE51 -> 471.46351 | AI51: =((AF51/AC51)*GlobalPortfolio+(AG51/AD51)*AusPortfolio)*AE51-AH51 -> 738621.65 | AJ51: =AJ50+AA51 -> 397434.65 | AK51: =AI51-AJ51 -> 341187 | AL51: =AJ51*(_xlfn.XLOOKUP(Q_end,cpi!A:A,cpi!B:B)/BH51) -> 510282.11 | AM51: {=SUMPRODUCT($AA$3:AA51,_xlfn.SORTBY($BH$3:BH51,_xlfn.SEQUENCE(ROWS($BH$3:BH51)),-1)/$BH$3)} -> 499105.28 | AN51: =AI51-AM51 -> 239516.36 | AO51: =IF($B$49="Real gains",MAX($B$50*AN51,0),IF($B$49="Discounted nominal gains",MAX($B$50*AK51/2,0),0)) -> 0 | AP51: =AI51-AO51 -> 738621.65 | AR51: =IF($B$10="3BR_H", INDEX('ns-combined'!$C:$BH,MATCH($L51,'ns-combined'!$B:$B,0),MATCH(Council_Area,'ns-combined'!$C$1:$BH$1,0))*1000, INDEX('s-combined'!$C:$BH,MATCH($L51,'s-combined'!$B:$B,0),MATCH(Council_Area,'s-combined'!$C$1:$BH$1,0))*1000) -> 939000 | AS51: =AS50+$AS$3 -> 56350 | AT51: 0 | AU51: =SUM($B$28:$B$29)*AR51 -> 18780 | AV51: =AR51*$B$15/4 -> 2699.625 | AW51: =SUM($AV$3:AV51) -> 92721.625 | AX51: =AR51-AS51-AU51-AW51 -> 771148.38 | AY51: =$B$36*V51 -> 2250 | AZ51: =SUM(AY51:AY51)*4/AR51 -> 0.0095846645 | BA51: =SUM(AY51:AY51)/V51 -> 0.35 | BB51: =IF(MortgageRate="Discounted",_xlfn.XLOOKUP(L51,'mortgage-rates'!$A:$A,'mortgage-rates'!$E:$E)/100,_xlfn.XLOOKUP(L51,'mortgage-rates'!$A:$A,'mortgage-rates'!$D:$D)/100) -> 0.0451 | BC51: =BC50-BF50 -> 254685.91 | BD51: =IF($B$16*12/3-Q51+1>0,-PMT($BB51/4,$B$16*12/3-Q51+1,BC51),0) -> 6499.8893 | BE51: =BC51*($BB51/4) -> 2871.5836 | BF51: =BD51-BE51 -> 3628.3056 | BG51: =AT51+AY51+BD51 -> 8749.8893 | BH51: =INDEX(cpi!B:B,MATCH($L51,cpi!A:A)) -> 112.7 | BI51: =100*BH51/BH$3 -> 133.21513 | BJ51: =100*AC51/AC$3 -> 219.81871 | BK51: =100*AD51/AD$3 -> 213.4075 | BL51: =BJ51*GlobalPortfolio+BK51*AusPortfolio -> 217.89535 | BM51: =100*AE51/$AE$3 -> 474.93622 | BN51: =100*AR51/AR$3 -> 204.13043 | BO51: =100*AX51/AX$3 -> 172.00559
A52: Other renter parameters | L52: =DATE(YEAR(L51),MONTH(L51)+3,1) -> 43252 | M52: =AP52 -> 770802.09 | N52: =AX52-BC52 -> 526989.52 | O52: =M52/N52 -> 1.4626517 | P52: =X52/BG52 -> 0.7585807 | Q52: 50 | R52: =EOMONTH(L52,0)-EOMONTH(L52,-3) -> 91 | T52: =IF($B$10="3BR_H", INDEX('3BR_H-combined'!$C:$BH,MATCH($L52,'3BR_H-combined'!$B:$B,0),MATCH(Council_Area,'3BR_H-combined'!$C$1:$BH$1,0)), INDEX('2BR_F-combined'!$C:$BH,MATCH($L52,'2BR_F-combined'!$B:$B,0),MATCH(Council_Area,'2BR_F-combined'!$C$1:$BH$1,0))) -> 495 | U52: =IF(MOD(Q52,4)=1,T52,U51) -> 500 | V52: =U52*(R52)/7 -> 6500 | W52: =$B$53/4*BH52/_xlfn.XLOOKUP(Q_end,cpi!A:A,cpi!B:B) -> 156.46164 | X52: =V52+W52 -> 6656.4616 | Y52: =BG52-X52 -> 2118.4276 | Z52: =Y52*$B$47 -> 677.89683 | AA52: =(Y52+Z52)*eff_invest -> 2796.3244 | AB52: =AA52*(_xlfn.XLOOKUP(Q_end,cpi!A:A,cpi!B:B)/BH52) -> 3574.4536 | AC52: {=INDEX('msci-indices'!C:C,MATCH($L52,'msci-indices'!$B:$B)-2)} -> 1639.7569 | AD52: {=INDEX('msci-indices'!D:D,MATCH($L52,'msci-indices'!$B:$B)-2)} -> 1460.9363 | AE52: =AI51+AA52 -> 741417.97 | AF52: {=INDEX('msci-indices'!C:C,MATCH($L52,'msci-indices'!$B:$B)+1)} -> 1671.605 | AG52: {=INDEX('msci-indices'!D:D,MATCH($L52,'msci-indices'!$B:$B)+1)} -> 1590.7725 | AH52: =(InvestFees/4)*AE52 -> 463.38623 | AI52: =((AF52/AC52)*GlobalPortfolio+(AG52/AD52)*AusPortfolio)*AE52-AH52 -> 770802.09 | AJ52: =AJ51+AA52 -> 400230.97 | AK52: =AI52-AJ52 -> 370571.12 | AL52: =AJ52*(_xlfn.XLOOKUP(Q_end,cpi!A:A,cpi!B:B)/BH52) -> 511602.66 | AM52: {=SUMPRODUCT($AA$3:AA52,_xlfn.SORTBY($BH$3:BH52,_xlfn.SEQUENCE(ROWS($BH$3:BH52)),-1)/$BH$3)} -> 504419.85 | AN52: =AI52-AM52 -> 266382.24 | AO52: =IF($B$49="Real gains",MAX($B$50*AN52,0),IF($B$49="Discounted nominal gains",MAX($B$50*AK52/2,0),0)) -> 0 | AP52: =AI52-AO52 -> 770802.09 | AR52: =IF($B$10="3BR_H", INDEX('ns-combined'!$C:$BH,MATCH($L52,'ns-combined'!$B:$B,0),MATCH(Council_Area,'ns-combined'!$C$1:$BH$1,0))*1000, INDEX('s-combined'!$C:$BH,MATCH($L52,'s-combined'!$B:$B,0),MATCH(Council_Area,'s-combined'!$C$1:$BH$1,0))*1000) -> 950000 | AS52: =AS51+$AS$3 -> 57500 | AT52: 0 | AU52: =SUM($B$28:$B$29)*AR52 -> 19000 | AV52: =AR52*$B$15/4 -> 2731.25 | AW52: =SUM($AV$3:AV52) -> 95452.875 | AX52: =AR52-AS52-AU52-AW52 -> 778047.12 | AY52: =$B$36*V52 -> 2275 | AZ52: =SUM(AY52:AY52)*4/AR52 -> 0.0095789474 | BA52: =SUM(AY52:AY52)/V52 -> 0.35 | BB52: =IF(MortgageRate="Discounted",_xlfn.XLOOKUP(L52,'mortgage-rates'!$A:$A,'mortgage-rates'!$E:$E)/100,_xlfn.XLOOKUP(L52,'mortgage-rates'!$A:$A,'mortgage-rates'!$D:$D)/100) -> 0.0451 | BC52: =BC51-BF51 -> 251057.6 | BD52: =IF($B$16*12/3-Q52+1>0,-PMT($BB52/4,$B$16*12/3-Q52+1,BC52),0) -> 6499.8893 | BE52: =BC52*($BB52/4) -> 2830.6745 | BF52: =BD52-BE52 -> 3669.2148 | BG52: =AT52+AY52+BD52 -> 8774.8893 | BH52: =INDEX(cpi!B:B,MATCH($L52,cpi!A:A)) -> 113.2 | BI52: =100*BH52/BH$3 -> 133.80615 | BJ52: =100*AC52/AC$3 -> 217.22098 | BK52: =100*AD52/AD$3 -> 204.91247 | BL52: =BJ52*GlobalPortfolio+BK52*AusPortfolio -> 213.52842 | BM52: =100*AE52/$AE$3 -> 466.79944 | BN52: =100*AR52/AR$3 -> 206.52174 | BO52: =100*AX52/AX$3 -> 173.54437
A53: Renter's insurance and other costs ($ per year, end-quarter dollars) | B53: 800 | C53: 800 | L53: =DATE(YEAR(L52),MONTH(L52)+3,1) -> 43344 | M53: =AP53 -> 800644.92 | N53: =AX53-BC53 -> 477921.24 | O53: =M53/N53 -> 1.6752654 | P53: =X53/BG53 -> 0.76104038 | Q53: 51 | R53: =EOMONTH(L53,0)-EOMONTH(L53,-3) -> 92 | T53: =IF($B$10="3BR_H", INDEX('3BR_H-combined'!$C:$BH,MATCH($L53,'3BR_H-combined'!$B:$B,0),MATCH(Council_Area,'3BR_H-combined'!$C$1:$BH$1,0)), INDEX('2BR_F-combined'!$C:$BH,MATCH($L53,'2BR_F-combined'!$B:$B,0),MATCH(Council_Area,'2BR_F-combined'!$C$1:$BH$1,0))) -> 500 | U53: =IF(MOD(Q53,4)=1,T53,U52) -> 500 | V53: =U53*(R53)/7 -> 6571.4286 | W53: =$B$53/4*BH53/_xlfn.XLOOKUP(Q_end,cpi!A:A,cpi!B:B) -> 156.8763 | X53: =V53+W53 -> 6728.3049 | Y53: =BG53-X53 -> 2112.6253 | Z53: =Y53*$B$47 -> 676.04011 | AA53: =(Y53+Z53)*eff_invest -> 2788.6655 | AB53: =AA53*(_xlfn.XLOOKUP(Q_end,cpi!A:A,cpi!B:B)/BH53) -> 3555.2413 | AC53: {=INDEX('msci-indices'!C:C,MATCH($L53,'msci-indices'!$B:$B)-2)} -> 1671.605 | AD53: {=INDEX('msci-indices'!D:D,MATCH($L53,'msci-indices'!$B:$B)-2)} -> 1590.7725 | AE53: =AI52+AA53 -> 773590.76 | AF53: {=INDEX('msci-indices'!C:C,MATCH($L53,'msci-indices'!$B:$B)+1)} -> 1747.8373 | AG53: {=INDEX('msci-indices'!D:D,MATCH($L53,'msci-indices'!$B:$B)+1)} -> 1610.2553 | AH53: =(InvestFees/4)*AE53 -> 483.49422 | AI53: =((AF53/AC53)*GlobalPortfolio+(AG53/AD53)*AusPortfolio)*AE53-AH53 -> 800644.92 | AJ53: =AJ52+AA53 -> 403019.64 | AK53: =AI53-AJ53 -> 397625.29 | AL53: =AJ53*(_xlfn.XLOOKUP(Q_end,cpi!A:A,cpi!B:B)/BH53) -> 513805.65 | AM53: {=SUMPRODUCT($AA$3:AA53,_xlfn.SORTBY($BH$3:BH53,_xlfn.SEQUENCE(ROWS($BH$3:BH53)),-1)/$BH$3)} -> 509366.69 | AN53: =AI53-AM53 -> 291278.24 | AO53: =IF($B$49="Real gains",MAX($B$50*AN53,0),IF($B$49="Discounted nominal gains",MAX($B$50*AK53/2,0),0)) -> 0 | AP53: =AI53-AO53 -> 800644.92 | AR53: =IF($B$10="3BR_H", INDEX('ns-combined'!$C:$BH,MATCH($L53,'ns-combined'!$B:$B,0),MATCH(Council_Area,'ns-combined'!$C$1:$BH$1,0))*1000, INDEX('s-combined'!$C:$BH,MATCH($L53,'s-combined'!$B:$B,0),MATCH(Council_Area,'s-combined'!$C$1:$BH$1,0))*1000) -> 900000 | AS53: =AS52+$AS$3 -> 58650 | AT53: 0 | AU53: =SUM($B$28:$B$29)*AR53 -> 18000 | AV53: =AR53*$B$15/4 -> 2587.5 | AW53: =SUM($AV$3:AV53) -> 98040.375 | AX53: =AR53-AS53-AU53-AW53 -> 725309.62 | AY53: =$B$36*V53 -> 2300 | AZ53: =SUM(AY53:AY53)*4/AR53 -> 0.010222222 | BA53: =SUM(AY53:AY53)/V53 -> 0.35 | BB53: =IF(MortgageRate="Discounted",_xlfn.XLOOKUP(L53,'mortgage-rates'!$A:$A,'mortgage-rates'!$E:$E)/100,_xlfn.XLOOKUP(L53,'mortgage-rates'!$A:$A,'mortgage-rates'!$D:$D)/100) -> 0.0462 | BC53: =BC52-BF52 -> 247388.39 | BD53: =IF($B$16*12/3-Q53+1>0,-PMT($BB53/4,$B$16*12/3-Q53+1,BC53),0) -> 6540.9302 | BE53: =BC53*($BB53/4) -> 2857.3359 | BF53: =BD53-BE53 -> 3683.5943 | BG53: =AT53+AY53+BD53 -> 8840.9302 | BH53: =INDEX(cpi!B:B,MATCH($L53,cpi!A:A)) -> 113.5 | BI53: =100*BH53/BH$3 -> 134.16076 | BJ53: =100*AC53/AC$3 -> 221.43995 | BK53: =100*AD53/AD$3 -> 223.12345 | BL53: =BJ53*GlobalPortfolio+BK53*AusPortfolio -> 221.945 | BM53: =100*AE53/$AE$3 -> 487.05555 | BN53: =100*AR53/AR$3 -> 195.65217 | BO53: =100*AX53/AX$3 -> 161.7812
A54: Investment efficiency | B54: 1 | C54: 1 | L54: =DATE(YEAR(L53),MONTH(L53)+3,1) -> 43435 | M54: =AP54 -> 704428.92 | N54: =AX54-BC54 -> 525746.46 | O54: =M54/N54 -> 1.3398643 | P54: =X54/BG54 -> 0.76017088 | Q54: 52 | R54: =EOMONTH(L54,0)-EOMONTH(L54,-3) -> 92 | T54: =IF($B$10="3BR_H", INDEX('3BR_H-combined'!$C:$BH,MATCH($L54,'3BR_H-combined'!$B:$B,0),MATCH(Council_Area,'3BR_H-combined'!$C$1:$BH$1,0)), INDEX('2BR_F-combined'!$C:$BH,MATCH($L54,'2BR_F-combined'!$B:$B,0),MATCH(Council_Area,'2BR_F-combined'!$C$1:$BH$1,0))) -> 500 | U54: =IF(MOD(Q54,4)=1,T54,U53) -> 500 | V54: =U54*(R54)/7 -> 6571.4286 | W54: =$B$53/4*BH54/_xlfn.XLOOKUP(Q_end,cpi!A:A,cpi!B:B) -> 157.56738 | X54: =V54+W54 -> 6728.996 | Y54: =BG54-X54 -> 2122.9558 | Z54: =Y54*$B$47 -> 679.34585 | AA54: =(Y54+Z54)*eff_invest -> 2802.3016 | AB54: =AA54*(_xlfn.XLOOKUP(Q_end,cpi!A:A,cpi!B:B)/BH54) -> 3556.9565 | AC54: {=INDEX('msci-indices'!C:C,MATCH($L54,'msci-indices'!$B:$B)-2)} -> 1747.8373 | AD54: {=INDEX('msci-indices'!D:D,MATCH($L54,'msci-indices'!$B:$B)-2)} -> 1610.2553 | AE54: =AI53+AA54 -> 803447.22 | AF54: {=INDEX('msci-indices'!C:C,MATCH($L54,'msci-indices'!$B:$B)+1)} -> 1503.1568 | AG54: {=INDEX('msci-indices'!D:D,MATCH($L54,'msci-indices'!$B:$B)+1)} -> 1478.0882 | AH54: =(InvestFees/4)*AE54 -> 502.15451 | AI54: =((AF54/AC54)*GlobalPortfolio+(AG54/AD54)*AusPortfolio)*AE54-AH54 -> 704428.92 | AJ54: =AJ53+AA54 -> 405821.94 | AK54: =AI54-AJ54 -> 298606.98 | AL54: =AJ54*(_xlfn.XLOOKUP(Q_end,cpi!A:A,cpi!B:B)/BH54) -> 515109.07 | AM54: {=SUMPRODUCT($AA$3:AA54,_xlfn.SORTBY($BH$3:BH54,_xlfn.SEQUENCE(ROWS($BH$3:BH54)),-1)/$BH$3)} -> 514711.5 | AN54: =AI54-AM54 -> 189717.41 | AO54: =IF($B$49="Real gains",MAX($B$50*AN54,0),IF($B$49="Discounted nominal gains",MAX($B$50*AK54/2,0),0)) -> 0 | AP54: =AI54-AO54 -> 704428.92 | AR54: =IF($B$10="3BR_H", INDEX('ns-combined'!$C:$BH,MATCH($L54,'ns-combined'!$B:$B,0),MATCH(Council_Area,'ns-combined'!$C$1:$BH$1,0))*1000, INDEX('s-combined'!$C:$BH,MATCH($L54,'s-combined'!$B:$B,0),MATCH(Council_Area,'s-combined'!$C$1:$BH$1,0))*1000) -> 949000 | AS54: =AS53+$AS$3 -> 59800 | AT54: 0 | AU54: =SUM($B$28:$B$29)*AR54 -> 18980 | AV54: =AR54*$B$15/4 -> 2728.375 | AW54: =SUM($AV$3:AV54) -> 100768.75 | AX54: =AR54-AS54-AU54-AW54 -> 769451.25 | AY54: =$B$36*V54 -> 2300 | AZ54: =SUM(AY54:AY54)*4/AR54 -> 0.0096944152 | BA54: =SUM(AY54:AY54)/V54 -> 0.35 | BB54: =IF(MortgageRate="Discounted",_xlfn.XLOOKUP(L54,'mortgage-rates'!$A:$A,'mortgage-rates'!$E:$E)/100,_xlfn.XLOOKUP(L54,'mortgage-rates'!$A:$A,'mortgage-rates'!$D:$D)/100) -> 0.0465 | BC54: =BC53-BF53 -> 243704.79 | BD54: =IF($B$16*12/3-Q54+1>0,-PMT($BB54/4,$B$16*12/3-Q54+1,BC54),0) -> 6551.9517 | BE54: =BC54*($BB54/4) -> 2833.0682 | BF54: =BD54-BE54 -> 3718.8835 | BG54: =AT54+AY54+BD54 -> 8851.9517 | BH54: =INDEX(cpi!B:B,MATCH($L54,cpi!A:A)) -> 114 | BI54: =100*BH54/BH$3 -> 134.75177 | BJ54: =100*AC54/AC$3 -> 231.53855 | BK54: =100*AD54/AD$3 -> 225.85612 | BL54: =BJ54*GlobalPortfolio+BK54*AusPortfolio -> 229.83382 | BM54: =100*AE54/$AE$3 -> 505.85328 | BN54: =100*AR54/AR$3 -> 206.30435 | BO54: =100*AX54/AX$3 -> 171.62705
L55: =DATE(YEAR(L54),MONTH(L54)+3,1) -> 43525 | M55: =AP55 -> 792454.53 | N55: =AX55-BC55 -> 443508.46 | O55: =M55/N55 -> 1.7867856 | P55: =X55/BG55 -> 0.74195441 | Q55: 53 | R55: =EOMONTH(L55,0)-EOMONTH(L55,-3) -> 90 | T55: =IF($B$10="3BR_H", INDEX('3BR_H-combined'!$C:$BH,MATCH($L55,'3BR_H-combined'!$B:$B,0),MATCH(Council_Area,'3BR_H-combined'!$C$1:$BH$1,0)), INDEX('2BR_F-combined'!$C:$BH,MATCH($L55,'2BR_F-combined'!$B:$B,0),MATCH(Council_Area,'2BR_F-combined'!$C$1:$BH$1,0))) -> 495 | U55: =IF(MOD(Q55,4)=1,T55,U54) -> 495 | V55: =U55*(R55)/7 -> 6364.2857 | W55: =$B$53/4*BH55/_xlfn.XLOOKUP(Q_end,cpi!A:A,cpi!B:B) -> 157.7056 | X55: =V55+W55 -> 6521.9913 | Y55: =BG55-X55 -> 2268.2944 | Z55: =Y55*$B$47 -> 725.85422 | AA55: =(Y55+Z55)*eff_invest -> 2994.1487 | AB55: =AA55*(_xlfn.XLOOKUP(Q_end,cpi!A:A,cpi!B:B)/BH55) -> 3797.1368 | AC55: {=INDEX('msci-indices'!C:C,MATCH($L55,'msci-indices'!$B:$B)-2)} -> 1503.1568 | AD55: {=INDEX('msci-indices'!D:D,MATCH($L55,'msci-indices'!$B:$B)-2)} -> 1478.0882 | AE55: =AI54+AA55 -> 707423.07 | AF55: {=INDEX('msci-indices'!C:C,MATCH($L55,'msci-indices'!$B:$B)+1)} -> 1693.1497 | AG55: {=INDEX('msci-indices'!D:D,MATCH($L55,'msci-indices'!$B:$B)+1)} -> 1637.4592 | AH55: =(InvestFees/4)*AE55 -> 442.13942 | AI55: =((AF55/AC55)*GlobalPortfolio+(AG55/AD55)*AusPortfolio)*AE55-AH55 -> 792454.53 | AJ55: =AJ54+AA55 -> 408816.09 | AK55: =AI55-AJ55 -> 383638.44 | AL55: =AJ55*(_xlfn.XLOOKUP(Q_end,cpi!A:A,cpi!B:B)/BH55) -> 518454.76 | AM55: {=SUMPRODUCT($AA$3:AA55,_xlfn.SORTBY($BH$3:BH55,_xlfn.SEQUENCE(ROWS($BH$3:BH55)),-1)/$BH$3)} -> 519521.07 | AN55: =AI55-AM55 -> 272933.46 | AO55: =IF($B$49="Real gains",MAX($B$50*AN55,0),IF($B$49="Discounted nominal gains",MAX($B$50*AK55/2,0),0)) -> 0 | AP55: =AI55-AO55 -> 792454.53 | AR55: =IF($B$10="3BR_H", INDEX('ns-combined'!$C:$BH,MATCH($L55,'ns-combined'!$B:$B,0),MATCH(Council_Area,'ns-combined'!$C$1:$BH$1,0))*1000, INDEX('s-combined'!$C:$BH,MATCH($L55,'s-combined'!$B:$B,0),MATCH(Council_Area,'s-combined'!$C$1:$BH$1,0))*1000) -> 865000 | AS55: =AS54+$AS$3 -> 60950 | AT55: 0 | AU55: =SUM($B$28:$B$29)*AR55 -> 17300 | AV55: =AR55*$B$15/4 -> 2486.875 | AW55: =SUM($AV$3:AV55) -> 103255.62 | AX55: =AR55-AS55-AU55-AW55 -> 683494.38 | AY55: =$B$36*V55 -> 2227.5 | AZ55: =SUM(AY55:AY55)*4/AR55 -> 0.010300578 | BA55: =SUM(AY55:AY55)/V55 -> 0.35 | BB55: =IF(MortgageRate="Discounted",_xlfn.XLOOKUP(L55,'mortgage-rates'!$A:$A,'mortgage-rates'!$E:$E)/100,_xlfn.XLOOKUP(L55,'mortgage-rates'!$A:$A,'mortgage-rates'!$D:$D)/100) -> 0.0468 | BC55: =BC54-BF54 -> 239985.91 | BD55: =IF($B$16*12/3-Q55+1>0,-PMT($BB55/4,$B$16*12/3-Q55+1,BC55),0) -> 6562.7858 | BE55: =BC55*($BB55/4) -> 2807.8352 | BF55: =BD55-BE55 -> 3754.9506 | BG55: =AT55+AY55+BD55 -> 8790.2858 | BH55: =INDEX(cpi!B:B,MATCH($L55,cpi!A:A)) -> 114.1 | BI55: =100*BH55/BH$3 -> 134.86998 | BJ55: =100*AC55/AC$3 -> 199.12537 | BK55: =100*AD55/AD$3 -> 207.31821 | BL55: =BJ55*GlobalPortfolio+BK55*AusPortfolio -> 201.58322 | BM55: =100*AE55/$AE$3 -> 445.39613 | BN55: =100*AR55/AR$3 -> 188.04348 | BO55: =100*AX55/AX$3 -> 152.45426
L56: =DATE(YEAR(L55),MONTH(L55)+3,1) -> 43617 | M56: =AP56 -> 834767.97 | N56: =AX56-BC56 -> 477825.91 | O56: =M56/N56 -> 1.7470128 | P56: =X56/BG56 -> 0.75467601 | Q56: 54 | R56: =EOMONTH(L56,0)-EOMONTH(L56,-3) -> 91 | T56: =IF($B$10="3BR_H", INDEX('3BR_H-combined'!$C:$BH,MATCH($L56,'3BR_H-combined'!$B:$B,0),MATCH(Council_Area,'3BR_H-combined'!$C$1:$BH$1,0)), INDEX('2BR_F-combined'!$C:$BH,MATCH($L56,'2BR_F-combined'!$B:$B,0),MATCH(Council_Area,'2BR_F-combined'!$C$1:$BH$1,0))) -> 480 | U56: =IF(MOD(Q56,4)=1,T56,U55) -> 495 | V56: =U56*(R56)/7 -> 6435 | W56: =$B$53/4*BH56/_xlfn.XLOOKUP(Q_end,cpi!A:A,cpi!B:B) -> 158.81133 | X56: =V56+W56 -> 6593.8113 | Y56: =BG56-X56 -> 2143.463 | Z56: =Y56*$B$47 -> 685.90816 | AA56: =(Y56+Z56)*eff_invest -> 2829.3712 | AB56: =AA56*(_xlfn.XLOOKUP(Q_end,cpi!A:A,cpi!B:B)/BH56) -> 3563.1855 | AC56: {=INDEX('msci-indices'!C:C,MATCH($L56,'msci-indices'!$B:$B)-2)} -> 1693.1497 | AD56: {=INDEX('msci-indices'!D:D,MATCH($L56,'msci-indices'!$B:$B)-2)} -> 1637.4592 | AE56: =AI55+AA56 -> 795283.9 | AF56: {=INDEX('msci-indices'!C:C,MATCH($L56,'msci-indices'!$B:$B)+1)} -> 1756.4484 | AG56: {=INDEX('msci-indices'!D:D,MATCH($L56,'msci-indices'!$B:$B)+1)} -> 1769.0189 | AH56: =(InvestFees/4)*AE56 -> 497.05244 | AI56: =((AF56/AC56)*GlobalPortfolio+(AG56/AD56)*AusPortfolio)*AE56-AH56 -> 834767.97 | AJ56: =AJ55+AA56 -> 411645.46 | AK56: =AI56-AJ56 -> 423122.51 | AL56: =AJ56*(_xlfn.XLOOKUP(Q_end,cpi!A:A,cpi!B:B)/BH56) -> 518408.16 | AM56: {=SUMPRODUCT($AA$3:AA56,_xlfn.SORTBY($BH$3:BH56,_xlfn.SEQUENCE(ROWS($BH$3:BH56)),-1)/$BH$3)} -> 525456.79 | AN56: =AI56-AM56 -> 309311.18 | AO56: =IF($B$49="Real gains",MAX($B$50*AN56,0),IF($B$49="Discounted nominal gains",MAX($B$50*AK56/2,0),0)) -> 0 | AP56: =AI56-AO56 -> 834767.97 | AR56: =IF($B$10="3BR_H", INDEX('ns-combined'!$C:$BH,MATCH($L56,'ns-combined'!$B:$B,0),MATCH(Council_Area,'ns-combined'!$C$1:$BH$1,0))*1000, INDEX('s-combined'!$C:$BH,MATCH($L56,'s-combined'!$B:$B,0),MATCH(Council_Area,'s-combined'!$C$1:$BH$1,0))*1000) -> 900000 | AS56: =AS55+$AS$3 -> 62100 | AT56: 0 | AU56: =SUM($B$28:$B$29)*AR56 -> 18000 | AV56: =AR56*$B$15/4 -> 2587.5 | AW56: =SUM($AV$3:AV56) -> 105843.12 | AX56: =AR56-AS56-AU56-AW56 -> 714056.88 | AY56: =$B$36*V56 -> 2252.25 | AZ56: =SUM(AY56:AY56)*4/AR56 -> 0.01001 | BA56: =SUM(AY56:AY56)/V56 -> 0.35 | BB56: =IF(MortgageRate="Discounted",_xlfn.XLOOKUP(L56,'mortgage-rates'!$A:$A,'mortgage-rates'!$E:$E)/100,_xlfn.XLOOKUP(L56,'mortgage-rates'!$A:$A,'mortgage-rates'!$D:$D)/100) -> 0.0446 | BC56: =BC55-BF55 -> 236230.96 | BD56: =IF($B$16*12/3-Q56+1>0,-PMT($BB56/4,$B$16*12/3-Q56+1,BC56),0) -> 6485.0243 | BE56: =BC56*($BB56/4) -> 2633.9752 | BF56: =BD56-BE56 -> 3851.0491 | BG56: =AT56+AY56+BD56 -> 8737.2743 | BH56: =INDEX(cpi!B:B,MATCH($L56,cpi!A:A)) -> 114.9 | BI56: =100*BH56/BH$3 -> 135.8156 | BJ56: =100*AC56/AC$3 -> 224.294 | BK56: =100*AD56/AD$3 -> 229.67177 | BL56: =BJ56*GlobalPortfolio+BK56*AusPortfolio -> 225.90733 | BM56: =100*AE56/$AE$3 -> 500.71363 | BN56: =100*AR56/AR$3 -> 195.65217 | BO56: =100*AX56/AX$3 -> 159.27126
L57: =DATE(YEAR(L56),MONTH(L56)+3,1) -> 43709 | M57: =AP57 -> 845943.7 | N57: =AX57-BC57 -> 492596.34 | O57: =M57/N57 -> 1.7173163 | P57: =X57/BG57 -> 0.76702627 | Q57: 55 | R57: =EOMONTH(L57,0)-EOMONTH(L57,-3) -> 92 | T57: =IF($B$10="3BR_H", INDEX('3BR_H-combined'!$C:$BH,MATCH($L57,'3BR_H-combined'!$B:$B,0),MATCH(Council_Area,'3BR_H-combined'!$C$1:$BH$1,0)), INDEX('2BR_F-combined'!$C:$BH,MATCH($L57,'2BR_F-combined'!$B:$B,0),MATCH(Council_Area,'2BR_F-combined'!$C$1:$BH$1,0))) -> 485 | U57: =IF(MOD(Q57,4)=1,T57,U56) -> 495 | V57: =U57*(R57)/7 -> 6505.7143 | W57: =$B$53/4*BH57/_xlfn.XLOOKUP(Q_end,cpi!A:A,cpi!B:B) -> 159.50242 | X57: =V57+W57 -> 6665.2167 | Y57: =BG57-X57 -> 2024.4683 | Z57: =Y57*$B$47 -> 647.82986 | AA57: =(Y57+Z57)*eff_invest -> 2672.2982 | AB57: =AA57*(_xlfn.XLOOKUP(Q_end,cpi!A:A,cpi!B:B)/BH57) -> 3350.7933 | AC57: {=INDEX('msci-indices'!C:C,MATCH($L57,'msci-indices'!$B:$B)-2)} -> 1756.4484 | AD57: {=INDEX('msci-indices'!D:D,MATCH($L57,'msci-indices'!$B:$B)-2)} -> 1769.0189 | AE57: =AI56+AA57 -> 837440.27 | AF57: {=INDEX('msci-indices'!C:C,MATCH($L57,'msci-indices'!$B:$B)+1)} -> 1762.7547 | AG57: {=INDEX('msci-indices'!D:D,MATCH($L57,'msci-indices'!$B:$B)+1)} -> 1817.7602 | AH57: =(InvestFees/4)*AE57 -> 523.40017 | AI57: =((AF57/AC57)*GlobalPortfolio+(AG57/AD57)*AusPortfolio)*AE57-AH57 -> 845943.7 | AJ57: =AJ56+AA57 -> 414317.76 | AK57: =AI57-AJ57 -> 431625.94 | AL57: =AJ57*(_xlfn.XLOOKUP(Q_end,cpi!A:A,cpi!B:B)/BH57) -> 519512.82 | AM57: {=SUMPRODUCT($AA$3:AA57,_xlfn.SORTBY($BH$3:BH57,_xlfn.SEQUENCE(ROWS($BH$3:BH57)),-1)/$BH$3)} -> 530711.48 | AN57: =AI57-AM57 -> 315232.22 | AO57: =IF($B$49="Real gains",MAX($B$50*AN57,0),IF($B$49="Discounted nominal gains",MAX($B$50*AK57/2,0),0)) -> 0 | AP57: =AI57-AO57 -> 845943.7 | AR57: =IF($B$10="3BR_H", INDEX('ns-combined'!$C:$BH,MATCH($L57,'ns-combined'!$B:$B,0),MATCH(Council_Area,'ns-combined'!$C$1:$BH$1,0))*1000, INDEX('s-combined'!$C:$BH,MATCH($L57,'s-combined'!$B:$B,0),MATCH(Council_Area,'s-combined'!$C$1:$BH$1,0))*1000) -> 915000 | AS57: =AS56+$AS$3 -> 63250 | AT57: 0 | AU57: =SUM($B$28:$B$29)*AR57 -> 18300 | AV57: =AR57*$B$15/4 -> 2630.625 | AW57: =SUM($AV$3:AV57) -> 108473.75 | AX57: =AR57-AS57-AU57-AW57 -> 724976.25 | AY57: =$B$36*V57 -> 2277 | AZ57: =SUM(AY57:AY57)*4/AR57 -> 0.0099540984 | BA57: =SUM(AY57:AY57)/V57 -> 0.35 | BB57: =IF(MortgageRate="Discounted",_xlfn.XLOOKUP(L57,'mortgage-rates'!$A:$A,'mortgage-rates'!$E:$E)/100,_xlfn.XLOOKUP(L57,'mortgage-rates'!$A:$A,'mortgage-rates'!$D:$D)/100) -> 0.0425 | BC57: =BC56-BF56 -> 232379.91 | BD57: =IF($B$16*12/3-Q57+1>0,-PMT($BB57/4,$B$16*12/3-Q57+1,BC57),0) -> 6412.685 | BE57: =BC57*($BB57/4) -> 2469.0366 | BF57: =BD57-BE57 -> 3943.6485 | BG57: =AT57+AY57+BD57 -> 8689.685 | BH57: =INDEX(cpi!B:B,MATCH($L57,cpi!A:A)) -> 115.4 | BI57: =100*BH57/BH$3 -> 136.40662 | BJ57: =100*AC57/AC$3 -> 232.67928 | BK57: =100*AD57/AD$3 -> 248.12447 | BL57: =BJ57*GlobalPortfolio+BK57*AusPortfolio -> 237.31283 | BM57: =100*AE57/$AE$3 -> 527.25543 | BN57: =100*AR57/AR$3 -> 198.91304 | BO57: =100*AX57/AX$3 -> 161.70684
L58: =DATE(YEAR(L57),MONTH(L57)+3,1) -> 43800 | M58: =AP58 -> 900008.5 | N58: =AX58-BC58 -> 590471.86 | O58: =M58/N58 -> 1.5242191 | P58: =X58/BG58 -> 0.77011685 | Q58: 56 | R58: =EOMONTH(L58,0)-EOMONTH(L58,-3) -> 92 | T58: =IF($B$10="3BR_H", INDEX('3BR_H-combined'!$C:$BH,MATCH($L58,'3BR_H-combined'!$B:$B,0),MATCH(Council_Area,'3BR_H-combined'!$C$1:$BH$1,0)), INDEX('2BR_F-combined'!$C:$BH,MATCH($L58,'2BR_F-combined'!$B:$B,0),MATCH(Council_Area,'2BR_F-combined'!$C$1:$BH$1,0))) -> 490 | U58: =IF(MOD(Q58,4)=1,T58,U57) -> 495 | V58: =U58*(R58)/7 -> 6505.7143 | W58: =$B$53/4*BH58/_xlfn.XLOOKUP(Q_end,cpi!A:A,cpi!B:B) -> 160.46994 | X58: =V58+W58 -> 6666.1842 | Y58: =BG58-X58 -> 1989.8843 | Z58: =Y58*$B$47 -> 636.76296 | AA58: =(Y58+Z58)*eff_invest -> 2626.6472 | AB58: =AA58*(_xlfn.XLOOKUP(Q_end,cpi!A:A,cpi!B:B)/BH58) -> 3273.6938 | AC58: {=INDEX('msci-indices'!C:C,MATCH($L58,'msci-indices'!$B:$B)-2)} -> 1762.7547 | AD58: {=INDEX('msci-indices'!D:D,MATCH($L58,'msci-indices'!$B:$B)-2)} -> 1817.7602 | AE58: =AI57+AA58 -> 848570.35 | AF58: {=INDEX('msci-indices'!C:C,MATCH($L58,'msci-indices'!$B:$B)+1)} -> 1916.2448 | AG58: {=INDEX('msci-indices'!D:D,MATCH($L58,'msci-indices'!$B:$B)+1)} -> 1819.5212 | AH58: =(InvestFees/4)*AE58 -> 530.35647 | AI58: =((AF58/AC58)*GlobalPortfolio+(AG58/AD58)*AusPortfolio)*AE58-AH58 -> 900008.5 | AJ58: =AJ57+AA58 -> 416944.4 | AK58: =AI58-AJ58 -> 483064.1 | AL58: =AJ58*(_xlfn.XLOOKUP(Q_end,cpi!A:A,cpi!B:B)/BH58) -> 519654.22 | AM58: {=SUMPRODUCT($AA$3:AA58,_xlfn.SORTBY($BH$3:BH58,_xlfn.SEQUENCE(ROWS($BH$3:BH58)),-1)/$BH$3)} -> 536290.57 | AN58: =AI58-AM58 -> 363717.93 | AO58: =IF($B$49="Real gains",MAX($B$50*AN58,0),IF($B$49="Discounted nominal gains",MAX($B$50*AK58/2,0),0)) -> 0 | AP58: =AI58-AO58 -> 900008.5 | AR58: =IF($B$10="3BR_H", INDEX('ns-combined'!$C:$BH,MATCH($L58,'ns-combined'!$B:$B,0),MATCH(Council_Area,'ns-combined'!$C$1:$BH$1,0))*1000, INDEX('s-combined'!$C:$BH,MATCH($L58,'s-combined'!$B:$B,0),MATCH(Council_Area,'s-combined'!$C$1:$BH$1,0))*1000) -> 1015000 | AS58: =AS57+$AS$3 -> 64400 | AT58: 0 | AU58: =SUM($B$28:$B$29)*AR58 -> 20300 | AV58: =AR58*$B$15/4 -> 2918.125 | AW58: =SUM($AV$3:AV58) -> 111391.88 | AX58: =AR58-AS58-AU58-AW58 -> 818908.12 | AY58: =$B$36*V58 -> 2277 | AZ58: =SUM(AY58:AY58)*4/AR58 -> 0.008973399 | BA58: =SUM(AY58:AY58)/V58 -> 0.35 | BB58: =IF(MortgageRate="Discounted",_xlfn.XLOOKUP(L58,'mortgage-rates'!$A:$A,'mortgage-rates'!$E:$E)/100,_xlfn.XLOOKUP(L58,'mortgage-rates'!$A:$A,'mortgage-rates'!$D:$D)/100) -> 0.0415 | BC58: =BC57-BF57 -> 228436.26 | BD58: =IF($B$16*12/3-Q58+1>0,-PMT($BB58/4,$B$16*12/3-Q58+1,BC58),0) -> 6379.0685 | BE58: =BC58*($BB58/4) -> 2370.0262 | BF58: =BD58-BE58 -> 4009.0422 | BG58: =AT58+AY58+BD58 -> 8656.0685 | BH58: =INDEX(cpi!B:B,MATCH($L58,cpi!A:A)) -> 116.1 | BI58: =100*BH58/BH$3 -> 137.23404 | BJ58: =100*AC58/AC$3 -> 233.51468 | BK58: =100*AD58/AD$3 -> 254.96098 | BL58: =BJ58*GlobalPortfolio+BK58*AusPortfolio -> 239.94857 | BM58: =100*AE58/$AE$3 -> 534.26297 | BN58: =100*AR58/AR$3 -> 220.65217 | BO58: =100*AX58/AX$3 -> 182.65846
L59: =DATE(YEAR(L58),MONTH(L58)+3,1) -> 43891 | M59: =AP59 -> 697271.18 | N59: =AX59-BC59 -> 557190.53 | O59: =M59/N59 -> 1.2514053 | P59: =X59/BG59 -> 0.7656943 | Q59: 57 | R59: =EOMONTH(L59,0)-EOMONTH(L59,-3) -> 91 | T59: =IF($B$10="3BR_H", INDEX('3BR_H-combined'!$C:$BH,MATCH($L59,'3BR_H-combined'!$B:$B,0),MATCH(Council_Area,'3BR_H-combined'!$C$1:$BH$1,0)), INDEX('2BR_F-combined'!$C:$BH,MATCH($L59,'2BR_F-combined'!$B:$B,0),MATCH(Council_Area,'2BR_F-combined'!$C$1:$BH$1,0))) -> 490 | U59: =IF(MOD(Q59,4)=1,T59,U58) -> 490 | V59: =U59*(R59)/7 -> 6370 | W59: =$B$53/4*BH59/_xlfn.XLOOKUP(Q_end,cpi!A:A,cpi!B:B) -> 161.29924 | X59: =V59+W59 -> 6531.2992 | Y59: =BG59-X59 -> 1998.6052 | Z59: =Y59*$B$47 -> 639.55367 | AA59: =(Y59+Z59)*eff_invest -> 2638.1589 | AB59: =AA59*(_xlfn.XLOOKUP(Q_end,cpi!A:A,cpi!B:B)/BH59) -> 3271.1362 | AC59: {=INDEX('msci-indices'!C:C,MATCH($L59,'msci-indices'!$B:$B)-2)} -> 1916.2448 | AD59: {=INDEX('msci-indices'!D:D,MATCH($L59,'msci-indices'!$B:$B)-2)} -> 1819.5212 | AE59: =AI58+AA59 -> 902646.66 | AF59: {=INDEX('msci-indices'!C:C,MATCH($L59,'msci-indices'!$B:$B)+1)} -> 1491.4482 | AG59: {=INDEX('msci-indices'!D:D,MATCH($L59,'msci-indices'!$B:$B)+1)} -> 1384.5123 | AH59: =(InvestFees/4)*AE59 -> 564.15416 | AI59: =((AF59/AC59)*GlobalPortfolio+(AG59/AD59)*AusPortfolio)*AE59-AH59 -> 697271.18 | AJ59: =AJ58+AA59 -> 419582.56 | AK59: =AI59-AJ59 -> 277688.62 | AL59: =AJ59*(_xlfn.XLOOKUP(Q_end,cpi!A:A,cpi!B:B)/BH59) -> 520253.61 | AM59: {=SUMPRODUCT($AA$3:AA59,_xlfn.SORTBY($BH$3:BH59,_xlfn.SEQUENCE(ROWS($BH$3:BH59)),-1)/$BH$3)} -> 541724.74 | AN59: =AI59-AM59 -> 155546.45 | AO59: =IF($B$49="Real gains",MAX($B$50*AN59,0),IF($B$49="Discounted nominal gains",MAX($B$50*AK59/2,0),0)) -> 0 | AP59: =AI59-AO59 -> 697271.18 | AR59: =IF($B$10="3BR_H", INDEX('ns-combined'!$C:$BH,MATCH($L59,'ns-combined'!$B:$B,0),MATCH(Council_Area,'ns-combined'!$C$1:$BH$1,0))*1000, INDEX('s-combined'!$C:$BH,MATCH($L59,'s-combined'!$B:$B,0),MATCH(Council_Area,'s-combined'!$C$1:$BH$1,0))*1000) -> 981000 | AS59: =AS58+$AS$3 -> 65550 | AT59: 0 | AU59: =SUM($B$28:$B$29)*AR59 -> 19620 | AV59: =AR59*$B$15/4 -> 2820.375 | AW59: =SUM($AV$3:AV59) -> 114212.25 | AX59: =AR59-AS59-AU59-AW59 -> 781617.75 | AY59: =$B$36*V59 -> 2229.5 | AZ59: =SUM(AY59:AY59)*4/AR59 -> 0.0090907238 | BA59: =SUM(AY59:AY59)/V59 -> 0.35 | BB59: =IF(MortgageRate="Discounted",_xlfn.XLOOKUP(L59,'mortgage-rates'!$A:$A,'mortgage-rates'!$E:$E)/100,_xlfn.XLOOKUP(L59,'mortgage-rates'!$A:$A,'mortgage-rates'!$D:$D)/100) -> 0.0391 | BC59: =BC58-BF58 -> 224427.22 | BD59: =IF($B$16*12/3-Q59+1>0,-PMT($BB59/4,$B$16*12/3-Q59+1,BC59),0) -> 6300.4045 | BE59: =BC59*($BB59/4) -> 2193.7761 | BF59: =BD59-BE59 -> 4106.6284 | BG59: =AT59+AY59+BD59 -> 8529.9045 | BH59: =INDEX(cpi!B:B,MATCH($L59,cpi!A:A)) -> 116.7 | BI59: =100*BH59/BH$3 -> 137.94326 | BJ59: =100*AC59/AC$3 -> 253.84774 | BK59: =100*AD59/AD$3 -> 255.20797 | BL59: =BJ59*GlobalPortfolio+BK59*AusPortfolio -> 254.25581 | BM59: =100*AE59/$AE$3 -> 568.30961 | BN59: =100*AR59/AR$3 -> 213.26087 | BO59: =100*AX59/AX$3 -> 174.3408
L60: =DATE(YEAR(L59),MONTH(L59)+3,1) -> 43983 | M60: =AP60 -> 832982.76 | N60: =AX60-BC60 -> 556349.66 | O60: =M60/N60 -> 1.4972289 | P60: =X60/BG60 -> 0.77284369 | Q60: 58 | R60: =EOMONTH(L60,0)-EOMONTH(L60,-3) -> 91 | T60: =IF($B$10="3BR_H", INDEX('3BR_H-combined'!$C:$BH,MATCH($L60,'3BR_H-combined'!$B:$B,0),MATCH(Council_Area,'3BR_H-combined'!$C$1:$BH$1,0)), INDEX('2BR_F-combined'!$C:$BH,MATCH($L60,'2BR_F-combined'!$B:$B,0),MATCH(Council_Area,'2BR_F-combined'!$C$1:$BH$1,0))) -> 480 | U60: =IF(MOD(Q60,4)=1,T60,U59) -> 490 | V60: =U60*(R60)/7 -> 6370 | W60: =$B$53/4*BH60/_xlfn.XLOOKUP(Q_end,cpi!A:A,cpi!B:B) -> 158.25847 | X60: =V60+W60 -> 6528.2585 | Y60: =BG60-X60 -> 1918.8034 | Z60: =Y60*$B$47 -> 614.01709 | AA60: =(Y60+Z60)*eff_invest -> 2532.8205 | AB60: =AA60*(_xlfn.XLOOKUP(Q_end,cpi!A:A,cpi!B:B)/BH60) -> 3200.8657 | AC60: {=INDEX('msci-indices'!C:C,MATCH($L60,'msci-indices'!$B:$B)-2)} -> 1491.4482 | AD60: {=INDEX('msci-indices'!D:D,MATCH($L60,'msci-indices'!$B:$B)-2)} -> 1384.5123 | AE60: =AI59+AA60 -> 699804 | AF60: {=INDEX('msci-indices'!C:C,MATCH($L60,'msci-indices'!$B:$B)+1)} -> 1788.7914 | AG60: {=INDEX('msci-indices'!D:D,MATCH($L60,'msci-indices'!$B:$B)+1)} -> 1621.6232 | AH60: =(InvestFees/4)*AE60 -> 437.3775 | AI60: =((AF60/AC60)*GlobalPortfolio+(AG60/AD60)*AusPortfolio)*AE60-AH60 -> 832982.76 | AJ60: =AJ59+AA60 -> 422115.38 | AK60: =AI60-AJ60 -> 410867.38 | AL60: =AJ60*(_xlfn.XLOOKUP(Q_end,cpi!A:A,cpi!B:B)/BH60) -> 533450.62 | AM60: {=SUMPRODUCT($AA$3:AA60,_xlfn.SORTBY($BH$3:BH60,_xlfn.SEQUENCE(ROWS($BH$3:BH60)),-1)/$BH$3)} -> 541819.73 | AN60: =AI60-AM60 -> 291163.03 | AO60: =IF($B$49="Real gains",MAX($B$50*AN60,0),IF($B$49="Discounted nominal gains",MAX($B$50*AK60/2,0),0)) -> 0 | AP60: =AI60-AO60 -> 832982.76 | AR60: =IF($B$10="3BR_H", INDEX('ns-combined'!$C:$BH,MATCH($L60,'ns-combined'!$B:$B,0),MATCH(Council_Area,'ns-combined'!$C$1:$BH$1,0))*1000, INDEX('s-combined'!$C:$BH,MATCH($L60,'s-combined'!$B:$B,0),MATCH(Council_Area,'s-combined'!$C$1:$BH$1,0))*1000) -> 980000 | AS60: =AS59+$AS$3 -> 66700 | AT60: 0 | AU60: =SUM($B$28:$B$29)*AR60 -> 19600 | AV60: =AR60*$B$15/4 -> 2817.5 | AW60: =SUM($AV$3:AV60) -> 117029.75 | AX60: =AR60-AS60-AU60-AW60 -> 776670.25 | AY60: =$B$36*V60 -> 2229.5 | AZ60: =SUM(AY60:AY60)*4/AR60 -> 0.0091 | BA60: =SUM(AY60:AY60)/V60 -> 0.35 | BB60: =IF(MortgageRate="Discounted",_xlfn.XLOOKUP(L60,'mortgage-rates'!$A:$A,'mortgage-rates'!$E:$E)/100,_xlfn.XLOOKUP(L60,'mortgage-rates'!$A:$A,'mortgage-rates'!$D:$D)/100) -> 0.0365 | BC60: =BC59-BF59 -> 220320.59 | BD60: =IF($B$16*12/3-Q60+1>0,-PMT($BB60/4,$B$16*12/3-Q60+1,BC60),0) -> 6217.5619 | BE60: =BC60*($BB60/4) -> 2010.4254 | BF60: =BD60-BE60 -> 4207.1365 | BG60: =AT60+AY60+BD60 -> 8447.0619 | BH60: =INDEX(cpi!B:B,MATCH($L60,cpi!A:A)) -> 114.5 | BI60: =100*BH60/BH$3 -> 135.34279 | BJ60: =100*AC60/AC$3 -> 197.57431 | BK60: =100*AD60/AD$3 -> 194.19317 | BL60: =BJ60*GlobalPortfolio+BK60*AusPortfolio -> 196.55997 | BM60: =100*AE60/$AE$3 -> 440.59914 | BN60: =100*AR60/AR$3 -> 213.04348 | BO60: =100*AX60/AX$3 -> 173.23725
L61: =DATE(YEAR(L60),MONTH(L60)+3,1) -> 44075 | M61: =AP61 -> 880879.08 | N61: =AX61-BC61 -> 576131.79 | O61: =M61/N61 -> 1.5289541 | P61: =X61/BG61 -> 0.7791489 | Q61: 59 | R61: =EOMONTH(L61,0)-EOMONTH(L61,-3) -> 92 | T61: =IF($B$10="3BR_H", INDEX('3BR_H-combined'!$C:$BH,MATCH($L61,'3BR_H-combined'!$B:$B,0),MATCH(Council_Area,'3BR_H-combined'!$C$1:$BH$1,0)), INDEX('2BR_F-combined'!$C:$BH,MATCH($L61,'2BR_F-combined'!$B:$B,0),MATCH(Council_Area,'2BR_F-combined'!$C$1:$BH$1,0))) -> 500 | U61: =IF(MOD(Q61,4)=1,T61,U60) -> 490 | V61: =U61*(R61)/7 -> 6440 | W61: =$B$53/4*BH61/_xlfn.XLOOKUP(Q_end,cpi!A:A,cpi!B:B) -> 160.60815 | X61: =V61+W61 -> 6600.6082 | Y61: =BG61-X61 -> 1870.9537 | Z61: =Y61*$B$47 -> 598.70519 | AA61: =(Y61+Z61)*eff_invest -> 2469.6589 | AB61: =AA61*(_xlfn.XLOOKUP(Q_end,cpi!A:A,cpi!B:B)/BH61) -> 3075.3842 | AC61: {=INDEX('msci-indices'!C:C,MATCH($L61,'msci-indices'!$B:$B)-2)} -> 1788.7914 | AD61: {=INDEX('msci-indices'!D:D,MATCH($L61,'msci-indices'!$B:$B)-2)} -> 1621.6232 | AE61: =AI60+AA61 -> 835452.42 | AF61: {=INDEX('msci-indices'!C:C,MATCH($L61,'msci-indices'!$B:$B)+1)} -> 1929.6384 | AG61: {=INDEX('msci-indices'!D:D,MATCH($L61,'msci-indices'!$B:$B)+1)} -> 1620.9838 | AH61: =(InvestFees/4)*AE61 -> 522.15776 | AI61: =((AF61/AC61)*GlobalPortfolio+(AG61/AD61)*AusPortfolio)*AE61-AH61 -> 880879.08 | AJ61: =AJ60+AA61 -> 424585.04 | AK61: =AI61-AJ61 -> 456294.04 | AL61: =AJ61*(_xlfn.XLOOKUP(Q_end,cpi!A:A,cpi!B:B)/BH61) -> 528721.65 | AM61: {=SUMPRODUCT($AA$3:AA61,_xlfn.SORTBY($BH$3:BH61,_xlfn.SEQUENCE(ROWS($BH$3:BH61)),-1)/$BH$3)} -> 548949.81 | AN61: =AI61-AM61 -> 331929.27 | AO61: =IF($B$49="Real gains",MAX($B$50*AN61,0),IF($B$49="Discounted nominal gains",MAX($B$50*AK61/2,0),0)) -> 0 | AP61: =AI61-AO61 -> 880879.08 | AR61: =IF($B$10="3BR_H", INDEX('ns-combined'!$C:$BH,MATCH($L61,'ns-combined'!$B:$B,0),MATCH(Council_Area,'ns-combined'!$C$1:$BH$1,0))*1000, INDEX('s-combined'!$C:$BH,MATCH($L61,'s-combined'!$B:$B,0),MATCH(Council_Area,'s-combined'!$C$1:$BH$1,0))*1000) -> 1000000 | AS61: =AS60+$AS$3 -> 67850 | AT61: 0 | AU61: =SUM($B$28:$B$29)*AR61 -> 20000 | AV61: =AR61*$B$15/4 -> 2875 | AW61: =SUM($AV$3:AV61) -> 119904.75 | AX61: =AR61-AS61-AU61-AW61 -> 792245.25 | AY61: =$B$36*V61 -> 2254 | AZ61: =SUM(AY61:AY61)*4/AR61 -> 0.009016 | BA61: =SUM(AY61:AY61)/V61 -> 0.35 | BB61: =IF(MortgageRate="Discounted",_xlfn.XLOOKUP(L61,'mortgage-rates'!$A:$A,'mortgage-rates'!$E:$E)/100,_xlfn.XLOOKUP(L61,'mortgage-rates'!$A:$A,'mortgage-rates'!$D:$D)/100) -> 0.0365 | BC61: =BC60-BF60 -> 216113.46 | BD61: =IF($B$16*12/3-Q61+1>0,-PMT($BB61/4,$B$16*12/3-Q61+1,BC61),0) -> 6217.5619 | BE61: =BC61*($BB61/4) -> 1972.0353 | BF61: =BD61-BE61 -> 4245.5266 | BG61: =AT61+AY61+BD61 -> 8471.5619 | BH61: =INDEX(cpi!B:B,MATCH($L61,cpi!A:A)) -> 116.2 | BI61: =100*BH61/BH$3 -> 137.35225 | BJ61: =100*AC61/AC$3 -> 236.9638 | BK61: =100*AD61/AD$3 -> 227.4506 | BL61: =BJ61*GlobalPortfolio+BK61*AusPortfolio -> 234.10984 | BM61: =100*AE61/$AE$3 -> 526.00387 | BN61: =100*AR61/AR$3 -> 217.3913 | BO61: =100*AX61/AX$3 -> 176.71128
L62: =DATE(YEAR(L61),MONTH(L61)+3,1) -> 44166 | M62: =AP62 -> 1013506.1 | N62: =AX62-BC62 -> 644751.07 | O62: =M62/N62 -> 1.571934 | P62: =X62/BG62 -> 0.77931206 | Q62: 60 | R62: =EOMONTH(L62,0)-EOMONTH(L62,-3) -> 92 | T62: =IF($B$10="3BR_H", INDEX('3BR_H-combined'!$C:$BH,MATCH($L62,'3BR_H-combined'!$B:$B,0),MATCH(Council_Area,'3BR_H-combined'!$C$1:$BH$1,0)), INDEX('2BR_F-combined'!$C:$BH,MATCH($L62,'2BR_F-combined'!$B:$B,0),MATCH(Council_Area,'2BR_F-combined'!$C$1:$BH$1,0))) -> 510 | U62: =IF(MOD(Q62,4)=1,T62,U61) -> 490 | V62: =U62*(R62)/7 -> 6440 | W62: =$B$53/4*BH62/_xlfn.XLOOKUP(Q_end,cpi!A:A,cpi!B:B) -> 161.99032 | X62: =V62+W62 -> 6601.9903 | Y62: =BG62-X62 -> 1869.5716 | Z62: =Y62*$B$47 -> 598.2629 | AA62: =(Y62+Z62)*eff_invest -> 2467.8345 | AB62: =AA62*(_xlfn.XLOOKUP(Q_end,cpi!A:A,cpi!B:B)/BH62) -> 3046.8912 | AC62: {=INDEX('msci-indices'!C:C,MATCH($L62,'msci-indices'!$B:$B)-2)} -> 1929.6384 | AD62: {=INDEX('msci-indices'!D:D,MATCH($L62,'msci-indices'!$B:$B)-2)} -> 1620.9838 | AE62: =AI61+AA62 -> 883346.91 | AF62: {=INDEX('msci-indices'!C:C,MATCH($L62,'msci-indices'!$B:$B)+1)} -> 2220.9403 | AG62: {=INDEX('msci-indices'!D:D,MATCH($L62,'msci-indices'!$B:$B)+1)} -> 1849.5395 | AH62: =(InvestFees/4)*AE62 -> 552.09182 | AI62: =((AF62/AC62)*GlobalPortfolio+(AG62/AD62)*AusPortfolio)*AE62-AH62 -> 1013506.1 | AJ62: =AJ61+AA62 -> 427052.88 | AK62: =AI62-AJ62 -> 586453.25 | AL62: =AJ62*(_xlfn.XLOOKUP(Q_end,cpi!A:A,cpi!B:B)/BH62) -> 527257.26 | AM62: {=SUMPRODUCT($AA$3:AA62,_xlfn.SORTBY($BH$3:BH62,_xlfn.SEQUENCE(ROWS($BH$3:BH62)),-1)/$BH$3)} -> 554864.25 | AN62: =AI62-AM62 -> 458641.87 | AO62: =IF($B$49="Real gains",MAX($B$50*AN62,0),IF($B$49="Discounted nominal gains",MAX($B$50*AK62/2,0),0)) -> 0 | AP62: =AI62-AO62 -> 1013506.1 | AR62: =IF($B$10="3BR_H", INDEX('ns-combined'!$C:$BH,MATCH($L62,'ns-combined'!$B:$B,0),MATCH(Council_Area,'ns-combined'!$C$1:$BH$1,0))*1000, INDEX('s-combined'!$C:$BH,MATCH($L62,'s-combined'!$B:$B,0),MATCH(Council_Area,'s-combined'!$C$1:$BH$1,0))*1000) -> 1070000 | AS62: =AS61+$AS$3 -> 69000 | AT62: 0 | AU62: =SUM($B$28:$B$29)*AR62 -> 21400 | AV62: =AR62*$B$15/4 -> 3076.25 | AW62: =SUM($AV$3:AV62) -> 122981 | AX62: =AR62-AS62-AU62-AW62 -> 856619 | AY62: =$B$36*V62 -> 2254 | AZ62: =SUM(AY62:AY62)*4/AR62 -> 0.0084261682 | BA62: =SUM(AY62:AY62)/V62 -> 0.35 | BB62: =IF(MortgageRate="Discounted",_xlfn.XLOOKUP(L62,'mortgage-rates'!$A:$A,'mortgage-rates'!$E:$E)/100,_xlfn.XLOOKUP(L62,'mortgage-rates'!$A:$A,'mortgage-rates'!$D:$D)/100) -> 0.0365 | BC62: =BC61-BF61 -> 211867.93 | BD62: =IF($B$16*12/3-Q62+1>0,-PMT($BB62/4,$B$16*12/3-Q62+1,BC62),0) -> 6217.5619 | BE62: =BC62*($BB62/4) -> 1933.2949 | BF62: =BD62-BE62 -> 4284.267 | BG62: =AT62+AY62+BD62 -> 8471.5619 | BH62: =INDEX(cpi!B:B,MATCH($L62,cpi!A:A)) -> 117.2 | BI62: =100*BH62/BH$3 -> 138.53428 | BJ62: =100*AC62/AC$3 -> 255.622 | BK62: =100*AD62/AD$3 -> 227.36091 | BL62: =BJ62*GlobalPortfolio+BK62*AusPortfolio -> 247.14367 | BM62: =100*AE62/$AE$3 -> 556.15842 | BN62: =100*AR62/AR$3 -> 232.6087 | BO62: =100*AX62/AX$3 -> 191.06992
L63: =DATE(YEAR(L62),MONTH(L62)+3,1) -> 44256 | M63: =AP63 -> 1067413.2 | N63: =AX63-BC63 -> 683894.09 | O63: =M63/N63 -> 1.5607872 | P63: =X63/BG63 -> 0.80568412 | Q63: 61 | R63: =EOMONTH(L63,0)-EOMONTH(L63,-3) -> 90 | T63: =IF($B$10="3BR_H", INDEX('3BR_H-combined'!$C:$BH,MATCH($L63,'3BR_H-combined'!$B:$B,0),MATCH(Council_Area,'3BR_H-combined'!$C$1:$BH$1,0)), INDEX('2BR_F-combined'!$C:$BH,MATCH($L63,'2BR_F-combined'!$B:$B,0),MATCH(Council_Area,'2BR_F-combined'!$C$1:$BH$1,0))) -> 525 | U63: =IF(MOD(Q63,4)=1,T63,U62) -> 525 | V63: =U63*(R63)/7 -> 6750 | W63: =$B$53/4*BH63/_xlfn.XLOOKUP(Q_end,cpi!A:A,cpi!B:B) -> 162.81963 | X63: =V63+W63 -> 6912.8196 | Y63: =BG63-X63 -> 1667.2423 | Z63: =Y63*$B$47 -> 533.51752 | AA63: =(Y63+Z63)*eff_invest -> 2200.7598 | AB63: =AA63*(_xlfn.XLOOKUP(Q_end,cpi!A:A,cpi!B:B)/BH63) -> 2703.3102 | AC63: {=INDEX('msci-indices'!C:C,MATCH($L63,'msci-indices'!$B:$B)-2)} -> 2220.9403 | AD63: {=INDEX('msci-indices'!D:D,MATCH($L63,'msci-indices'!$B:$B)-2)} -> 1849.5395 | AE63: =AI62+AA63 -> 1015706.9 | AF63: {=INDEX('msci-indices'!C:C,MATCH($L63,'msci-indices'!$B:$B)+1)} -> 2342.5855 | AG63: {=INDEX('msci-indices'!D:D,MATCH($L63,'msci-indices'!$B:$B)+1)} -> 1930.8659 | AH63: =(InvestFees/4)*AE63 -> 634.8168 | AI63: =((AF63/AC63)*GlobalPortfolio+(AG63/AD63)*AusPortfolio)*AE63-AH63 -> 1067413.2 | AJ63: =AJ62+AA63 -> 429253.64 | AK63: =AI63-AJ63 -> 638159.53 | AL63: =AJ63*(_xlfn.XLOOKUP(Q_end,cpi!A:A,cpi!B:B)/BH63) -> 527275.05 | AM63: {=SUMPRODUCT($AA$3:AA63,_xlfn.SORTBY($BH$3:BH63,_xlfn.SEQUENCE(ROWS($BH$3:BH63)),-1)/$BH$3)} -> 559807.61 | AN63: =AI63-AM63 -> 507605.56 | AO63: =IF($B$49="Real gains",MAX($B$50*AN63,0),IF($B$49="Discounted nominal gains",MAX($B$50*AK63/2,0),0)) -> 0 | AP63: =AI63-AO63 -> 1067413.2 | AR63: =IF($B$10="3BR_H", INDEX('ns-combined'!$C:$BH,MATCH($L63,'ns-combined'!$B:$B,0),MATCH(Council_Area,'ns-combined'!$C$1:$BH$1,0))*1000, INDEX('s-combined'!$C:$BH,MATCH($L63,'s-combined'!$B:$B,0),MATCH(Council_Area,'s-combined'!$C$1:$BH$1,0))*1000) -> 1110000 | AS63: =AS62+$AS$3 -> 70150 | AT63: 0 | AU63: =SUM($B$28:$B$29)*AR63 -> 22200 | AV63: =AR63*$B$15/4 -> 3191.25 | AW63: =SUM($AV$3:AV63) -> 126172.25 | AX63: =AR63-AS63-AU63-AW63 -> 891477.75 | AY63: =$B$36*V63 -> 2362.5 | AZ63: =SUM(AY63:AY63)*4/AR63 -> 0.0085135135 | BA63: =SUM(AY63:AY63)/V63 -> 0.35 | BB63: =IF(MortgageRate="Discounted",_xlfn.XLOOKUP(L63,'mortgage-rates'!$A:$A,'mortgage-rates'!$E:$E)/100,_xlfn.XLOOKUP(L63,'mortgage-rates'!$A:$A,'mortgage-rates'!$D:$D)/100) -> 0.0365 | BC63: =BC62-BF62 -> 207583.66 | BD63: =IF($B$16*12/3-Q63+1>0,-PMT($BB63/4,$B$16*12/3-Q63+1,BC63),0) -> 6217.5619 | BE63: =BC63*($BB63/4) -> 1894.2009 | BF63: =BD63-BE63 -> 4323.361 | BG63: =AT63+AY63+BD63 -> 8580.0619 | BH63: =INDEX(cpi!B:B,MATCH($L63,cpi!A:A)) -> 117.8 | BI63: =100*BH63/BH$3 -> 139.2435 | BJ63: =100*AC63/AC$3 -> 294.21119 | BK63: =100*AD63/AD$3 -> 259.41837 | BL63: =BJ63*GlobalPortfolio+BK63*AusPortfolio -> 283.77335 | BM63: =100*AE63/$AE$3 -> 639.49274 | BN63: =100*AR63/AR$3 -> 241.30435 | BO63: =100*AX63/AX$3 -> 198.84521
L64: =DATE(YEAR(L63),MONTH(L63)+3,1) -> 44348 | M64: =AP64 -> 1151441.5 | N64: =AX64-BC64 -> 830444.95 | O64: =M64/N64 -> 1.3865357 | P64: =X64/BG64 -> 0.81374786 | Q64: 62 | R64: =EOMONTH(L64,0)-EOMONTH(L64,-3) -> 91 | T64: =IF($B$10="3BR_H", INDEX('3BR_H-combined'!$C:$BH,MATCH($L64,'3BR_H-combined'!$B:$B,0),MATCH(Council_Area,'3BR_H-combined'!$C$1:$BH$1,0)), INDEX('2BR_F-combined'!$C:$BH,MATCH($L64,'2BR_F-combined'!$B:$B,0),MATCH(Council_Area,'2BR_F-combined'!$C$1:$BH$1,0))) -> 520 | U64: =IF(MOD(Q64,4)=1,T64,U63) -> 525 | V64: =U64*(R64)/7 -> 6825 | W64: =$B$53/4*BH64/_xlfn.XLOOKUP(Q_end,cpi!A:A,cpi!B:B) -> 164.2018 | X64: =V64+W64 -> 6989.2018 | Y64: =BG64-X64 -> 1599.7017 | Z64: =Y64*$B$47 -> 511.90454 | AA64: =(Y64+Z64)*eff_invest -> 2111.6062 | AB64: =AA64*(_xlfn.XLOOKUP(Q_end,cpi!A:A,cpi!B:B)/BH64) -> 2571.9648 | AC64: {=INDEX('msci-indices'!C:C,MATCH($L64,'msci-indices'!$B:$B)-2)} -> 2342.5855 | AD64: {=INDEX('msci-indices'!D:D,MATCH($L64,'msci-indices'!$B:$B)-2)} -> 1930.8659 | AE64: =AI63+AA64 -> 1069524.8 | AF64: {=INDEX('msci-indices'!C:C,MATCH($L64,'msci-indices'!$B:$B)+1)} -> 2515.6062 | AG64: {=INDEX('msci-indices'!D:D,MATCH($L64,'msci-indices'!$B:$B)+1)} -> 2095.0894 | AH64: =(InvestFees/4)*AE64 -> 668.45298 | AI64: =((AF64/AC64)*GlobalPortfolio+(AG64/AD64)*AusPortfolio)*AE64-AH64 -> 1151441.5 | AJ64: =AJ63+AA64 -> 431365.24 | AK64: =AI64-AJ64 -> 720076.3 | AL64: =AJ64*(_xlfn.XLOOKUP(Q_end,cpi!A:A,cpi!B:B)/BH64) -> 525408.67 | AM64: {=SUMPRODUCT($AA$3:AA64,_xlfn.SORTBY($BH$3:BH64,_xlfn.SEQUENCE(ROWS($BH$3:BH64)),-1)/$BH$3)} -> 565447.12 | AN64: =AI64-AM64 -> 585994.42 | AO64: =IF($B$49="Real gains",MAX($B$50*AN64,0),IF($B$49="Discounted nominal gains",MAX($B$50*AK64/2,0),0)) -> 0 | AP64: =AI64-AO64 -> 1151441.5 | AR64: =IF($B$10="3BR_H", INDEX('ns-combined'!$C:$BH,MATCH($L64,'ns-combined'!$B:$B,0),MATCH(Council_Area,'ns-combined'!$C$1:$BH$1,0))*1000, INDEX('s-combined'!$C:$BH,MATCH($L64,'s-combined'!$B:$B,0),MATCH(Council_Area,'s-combined'!$C$1:$BH$1,0))*1000) -> 1260000 | AS64: =AS63+$AS$3 -> 71300 | AT64: 0 | AU64: =SUM($B$28:$B$29)*AR64 -> 25200 | AV64: =AR64*$B$15/4 -> 3622.5 | AW64: =SUM($AV$3:AV64) -> 129794.75 | AX64: =AR64-AS64-AU64-AW64 -> 1033705.2 | AY64: =$B$36*V64 -> 2388.75 | AZ64: =SUM(AY64:AY64)*4/AR64 -> 0.0075833333 | BA64: =SUM(AY64:AY64)/V64 -> 0.35 | BB64: =IF(MortgageRate="Discounted",_xlfn.XLOOKUP(L64,'mortgage-rates'!$A:$A,'mortgage-rates'!$E:$E)/100,_xlfn.XLOOKUP(L64,'mortgage-rates'!$A:$A,'mortgage-rates'!$D:$D)/100) -> 0.0359 | BC64: =BC63-BF63 -> 203260.3 | BD64: =IF($B$16*12/3-Q64+1>0,-PMT($BB64/4,$B$16*12/3-Q64+1,BC64),0) -> 6200.1535 | BE64: =BC64*($BB64/4) -> 1824.2612 | BF64: =BD64-BE64 -> 4375.8923 | BG64: =AT64+AY64+BD64 -> 8588.9035 | BH64: =INDEX(cpi!B:B,MATCH($L64,cpi!A:A)) -> 118.8 | BI64: =100*BH64/BH$3 -> 140.42553 | BJ64: =100*AC64/AC$3 -> 310.3257 | BK64: =100*AD64/AD$3 -> 270.8253 | BL64: =BJ64*GlobalPortfolio+BK64*AusPortfolio -> 298.47558 | BM64: =100*AE64/$AE$3 -> 673.37667 | BN64: =100*AR64/AR$3 -> 273.91304 | BO64: =100*AX64/AX$3 -> 230.56923
