Workbook
Name A83728543L: 'ABS-total-value-dwellings'!$AF$1:$AF$10,'ABS-total-value-dwellings'!$AF$11:$AF$106
Name A83728543L_Data: 'ABS-total-value-dwellings'!$AF$11:$AF$106
Name A83728543L_Latest: 'ABS-total-value-dwellings'!$AF$106
Name A83728544R: 'ABS-total-value-dwellings'!$AU$1:$AU$10,'ABS-total-value-dwellings'!$AU$17:$AU$106
Name A83728544R_Data: 'ABS-total-value-dwellings'!$AU$17:$AU$106
Name A83728544R_Latest: 'ABS-total-value-dwellings'!$AU$106
Name A83728545T: 'ABS-total-value-dwellings'!$B$1:$B$10,'ABS-total-value-dwellings'!$B$11:$B$106
Name A83728545T_Data: 'ABS-total-value-dwellings'!$B$11:$B$106
Name A83728545T_Latest: 'ABS-total-value-dwellings'!$B$106
Name A83728546V: 'ABS-total-value-dwellings'!$Q$1:$Q$10,'ABS-total-value-dwellings'!$Q$17:$Q$106
Name A83728546V_Data: 'ABS-total-value-dwellings'!$Q$17:$Q$106
Name A83728546V_Latest: 'ABS-total-value-dwellings'!$Q$106
Name A83728547W: 'ABS-total-value-dwellings'!$AH$1:$AH$10,'ABS-total-value-dwellings'!$AH$11:$AH$106
Name A83728547W_Data: 'ABS-total-value-dwellings'!$AH$11:$AH$106
Name A83728547W_Latest: 'ABS-total-value-dwellings'!$AH$106
Name A83728548X: 'ABS-total-value-dwellings'!$AW$1:$AW$10,'ABS-total-value-dwellings'!$AW$17:$AW$106
Name A83728548X_Data: 'ABS-total-value-dwellings'!$AW$17:$AW$106
Name A83728548X_Latest: 'ABS-total-value-dwellings'!$AW$106
Name A83728549A: 'ABS-total-value-dwellings'!$D$1:$D$10,'ABS-total-value-dwellings'!$D$11:$D$106
Name A83728549A_Data: 'ABS-total-value-dwellings'!$D$11:$D$106
Name A83728549A_Latest: 'ABS-total-value-dwellings'!$D$106
Name A83728550K: 'ABS-total-value-dwellings'!$S$1:$S$10,'ABS-total-value-dwellings'!$S$17:$S$106
Name A83728550K_Data: 'ABS-total-value-dwellings'!$S$17:$S$106
Name A83728550K_Latest: 'ABS-total-value-dwellings'!$S$106
Name A83728551L: 'ABS-total-value-dwellings'!$AJ$1:$AJ$10,'ABS-total-value-dwellings'!$AJ$11:$AJ$106
Name A83728551L_Data: 'ABS-total-value-dwellings'!$AJ$11:$AJ$106
Name A83728551L_Latest: 'ABS-total-value-dwellings'!$AJ$106
Name A83728552R: 'ABS-total-value-dwellings'!$AY$1:$AY$10,'ABS-total-value-dwellings'!$AY$17:$AY$106
Name A83728552R_Data: 'ABS-total-value-dwellings'!$AY$17:$AY$106
Name A83728552R_Latest: 'ABS-total-value-dwellings'!$AY$106
Name A83728553T: 'ABS-total-value-dwellings'!$F$1:$F$10,'ABS-total-value-dwellings'!$F$11:$F$106
Name A83728553T_Data: 'ABS-total-value-dwellings'!$F$11:$F$106
Name A83728553T_Latest: 'ABS-total-value-dwellings'!$F$106
Name A83728554V: 'ABS-total-value-dwellings'!$U$1:$U$10,'ABS-total-value-dwellings'!$U$17:$U$106
Name A83728554V_Data: 'ABS-total-value-dwellings'!$U$17:$U$106
Name A83728554V_Latest: 'ABS-total-value-dwellings'!$U$106
Name A83728555W: 'ABS-total-value-dwellings'!$AL$1:$AL$10,'ABS-total-value-dwellings'!$AL$11:$AL$106
Name A83728555W_Data: 'ABS-total-value-dwellings'!$AL$11:$AL$106
Name A83728555W_Latest: 'ABS-total-value-dwellings'!$AL$106
Name A83728556X: 'ABS-total-value-dwellings'!$BA$1:$BA$10,'ABS-total-value-dwellings'!$BA$17:$BA$106
Name A83728556X_Data: 'ABS-total-value-dwellings'!$BA$17:$BA$106
Name A83728556X_Latest: 'ABS-total-value-dwellings'!$BA$106
Name A83728557A: 'ABS-total-value-dwellings'!$H$1:$H$10,'ABS-total-value-dwellings'!$H$11:$H$106
Name A83728557A_Data: 'ABS-total-value-dwellings'!$H$11:$H$106
Name A83728557A_Latest: 'ABS-total-value-dwellings'!$H$106
Name A83728558C: 'ABS-total-value-dwellings'!$W$1:$W$10,'ABS-total-value-dwellings'!$W$17:$W$106
Name A83728558C_Data: 'ABS-total-value-dwellings'!$W$17:$W$106
Name A83728558C_Latest: 'ABS-total-value-dwellings'!$W$106
Name A83728559F: 'ABS-total-value-dwellings'!$AN$1:$AN$10,'ABS-total-value-dwellings'!$AN$11:$AN$106
Name A83728559F_Data: 'ABS-total-value-dwellings'!$AN$11:$AN$106
Name A83728559F_Latest: 'ABS-total-value-dwellings'!$AN$106
Name A83728560R: 'ABS-total-value-dwellings'!$BC$1:$BC$10,'ABS-total-value-dwellings'!$BC$17:$BC$106
Name A83728560R_Data: 'ABS-total-value-dwellings'!$BC$17:$BC$106
Name A83728560R_Latest: 'ABS-total-value-dwellings'!$BC$106
Name A83728561T: 'ABS-total-value-dwellings'!$J$1:$J$10,'ABS-total-value-dwellings'!$J$11:$J$106
Name A83728561T_Data: 'ABS-total-value-dwellings'!$J$11:$J$106
Name A83728561T_Latest: 'ABS-total-value-dwellings'!$J$106
Name A83728562V: 'ABS-total-value-dwellings'!$Y$1:$Y$10,'ABS-total-value-dwellings'!$Y$17:$Y$106
Name A83728562V_Data: 'ABS-total-value-dwellings'!$Y$17:$Y$106
Name A83728562V_Latest: 'ABS-total-value-dwellings'!$Y$106

Sheet analysis
A1: Rent vs buy analysis - Adelaide | B1: Set values | C1: Default values | T1: Renter calcs >> | X1: {=SUM(_xlfn._xlws.FILTER(X3:X82,ISNUMBER(X3:X82)))} -> 393021.7 | AI1: CGT calcs | AR1: Buyer calcs >> | AY1: Maintenance and renovation | BB1: Mortgage | BG1: {=SUM(_xlfn._xlws.FILTER(BG3:BG82,ISNUMBER(BG3:BG82)))} -> 546411.05 | BH1: Comparison vs inflation
A2: Ending renter-to-owner wealth ratio | B2: =_xlfn.XLOOKUP(Q_end,L:L,O:O) -> 0.94039311 | E2: ="Renter vs owner wealth, "&Council_Area&IF(B10="2BR_F"," 2-bedroom flat"," 3-bedroom house") -> Renter vs owner wealth, Adelaide 3-bedroom house | L2: Quarter ending | M2: Renter's portfolio | N2: Owner's home equity | O2: Renter-to-owner wealth ratio | P2: Renter-to-owner cash needs | Q2: Quarter of analysis | R2: Days in quarter | T2: Median weekly rents, new bonds | U2: Renter's rents | V2: Quarterly rent | W2: Other renter costs | X2: Renter's cashflow costs | Y2: Renter additional cashflow | Z2: Tax concessions | AA2: Renter investment contributions | AB2: Contributions (CPI-adjusted to Q_end) | AC2: MSCI World index, start Q | AD2: MSCI Aus index, start Q | AE2: Portfolio, start Q | AF2: MSCI World index, end Q | AG2: MSCI Aus index, end Q | AH2: Investment fees | AI2: Portfolio, end Q, before CGT | AJ2: Cost base (nominal) | AK2: Nominal gains ($) | AL2: Cost base (CPI-adjusted to Q_end) | AM2: Cost base + CPI to current quarter | AN2: Real gains ($) | AO2: CGT on withdrawals | AP2: Portfolio, end Q | AR2: Median home price | AS2: Depreciation | AT2: Home purchase costs | AU2: Home sale costs | AV2: Renovation | AW2: Renovation, cumulative | AX2: Adjusted home price | AY2: Maintenance | AZ2: Total p.a. as % of home value | BA2: Total p.a. as % of rent | BB2: Mortgage rates | BC2: Loan balance | BD2: Mortgage payment | BE2: Mortgage interest | BF2: Mortgage - principal component | BG2: Owner's cashflow costs | BH2: CPI | BI2: CPI (Q_st art = 100) | BJ2: MSCI World (Q_start=100) | BK2: MSCI Aus (Q_start=100) | BL2: Portfolio index (Q_start=100) | BM2: Portfolio (Q_start=100) | BN2: Median home price (Q_start = 100) | BO2: Adjusted home price (Q_start = 100)
A3: Average renter-to-owner cashflow needs excl. home purchase costs | B3: {=SUM(_xlfn._xlws.FILTER($X$3:$X$82,ISNUMBER($X$3:$X$82)))/(SUM(_xlfn._xlws.FILTER($BG$3:$BG$82,ISNUMBER($BG$3:$BG$82)))-AT3)} -> 0.82596899 | L3: =Q_start -> 38777 | M3: =AP3 -> 78787.253 | N3: =AX3-BC3 -> 48895 | O3: =M3/N3 -> 1.611356 | P3: =X3/BG3 -> 0.041768055 | Q3: 1 | R3: =EOMONTH(L3,0)-EOMONTH(L3,-3) -> 90 | T3: =IF($B$10="3BR_H", INDEX('3BR_H-processed'!$E:$F,MATCH($L3,'3BR_H-processed'!$B:$B,0),MATCH(Council_Area,'3BR_H-processed'!$E$1:$F$1,0)), INDEX('2BR_F-processed'!$E:$F,MATCH($L3,'2BR_F-processed'!$B:$B,0),MATCH(Council_Area,'2BR_F-processed'!$E$1:$F$1,0))) -> 238.64607 | U3: =IF(MOD(Q3,4)=1,T3,U2) -> 238.64607 | V3: =U3*(R3)/7 -> 3068.3066 | W3: =$B$53/4*BH3/_xlfn.XLOOKUP(Q_end,cpi!A:A,cpi!B:B) -> 116.93158 | X3: =V3+W3 -> 3185.2382 | Y3: =BG3-X3 -> 73074.912 | Z3: =MAX(0,Y3*$B$47) -> 0 | AA3: {=(Y3+Z3)*eff_invest} -> 73074.912 | AB3: =AA3*(_xlfn.XLOOKUP(Q_end,cpi!A:A,cpi!B:B)/BH3) -> 124987.47 | AC3: {=INDEX('msci-indices'!C:C,MATCH($L3,'msci-indices'!$B:$B)-2)} -> 754.87961 | AD3: {=INDEX('msci-indices'!D:D,MATCH($L3,'msci-indices'!$B:$B)-2)} -> 712.95625 | AE3: =AA3 -> 73074.912 | AF3: {=INDEX('msci-indices'!C:C,MATCH($L3,'msci-indices'!$B:$B)+1)} -> 809.32012 | AG3: {=INDEX('msci-indices'!D:D,MATCH($L3,'msci-indices'!$B:$B)+1)} -> 780.24347 | AH3: =(InvestFees/4)*AE3 -> 45.67182 | AI3: =((AF3/AC3)*GlobalPortfolio+(AG3/AD3)*AusPortfolio)*AE3-AH3 -> 78787.253 | AJ3: =AA3 -> 73074.912 | AK3: =AI3-AJ3 -> 5712.3407 | AL3: =AJ3*(_xlfn.XLOOKUP(Q_end,cpi!A:A,cpi!B:B)/BH3) -> 124987.47 | AM3: =AA3 -> 73074.912 | AN3: =AI3-AM3 -> 5712.3407 | AO3: =IF($B$49="Real gains",MAX($B$50*AN3,0),IF($B$49="Discounted nominal gains",MAX($B$50*AK3/2,0),0)) -> 0 | AP3: =AI3-AO3 -> 78787.253 | AR3: =IF($B$10="3BR_H", INDEX('ns-combined'!$C:$D,MATCH($L3,'ns-combined'!$B:$B,0),MATCH(Council_Area,'ns-combined'!$C$1:$D$1,0))*1000, INDEX('s-combined'!$C:$D,MATCH($L3,'s-combined'!$B:$B,0),MATCH(Council_Area,'s-combined'!$C$1:$D$1,0))*1000) -> 280000 | AS3: =AR3*$B$14/4 -> 700 | AT3: =SUM(B20:B26)*AR3 -> 70580 | AU3: =SUM($B$28:$B$29)*AR3 -> 5600 | AV3: =AR3*$B$15/4 -> 805 | AW3: =SUM($AV$3:AV3) -> 805 | AX3: =AR3-AS3-AU3-AW3 -> 272895 | AY3: =$B$36*V3 -> 1073.9073 | AZ3: =SUM(AY3:AY3)*4/AR3 -> 0.015341533 | BA3: =SUM(AY3:AY3)/V3 -> 0.35 | BB3: =IF(MortgageRate="Discounted",_xlfn.XLOOKUP(L3,'mortgage-rates'!$A:$A,'mortgage-rates'!$E:$E)/100,_xlfn.XLOOKUP(L3,'mortgage-rates'!$A:$A,'mortgage-rates'!$D:$D)/100) -> 0.0664 | BC3: =(1-B20)*AR3 -> 224000 | BD3: =IF($B$16*12/3-Q3+1>0,-PMT($BB3/4,$B$16*12/3-Q3+1,BC3),0) -> 4606.2433 | BE3: =BC3*($BB3/4) -> 3718.4 | BF3: =BD3-BE3 -> 887.84334 | BG3: =AT3+AY3+BD3 -> 76260.151 | BH3: =INDEX(cpi!B:B,MATCH($L3,cpi!A:A)) -> 84.6 | BI3: =100*BH3/BH$3 -> 100 | BJ3: =100*AC3/AC$3 -> 100 | BK3: =100*AD3/AD$3 -> 100 | BL3: =BJ3*GlobalPortfolio+BK3*AusPortfolio -> 100 | BM3: =100*AE3/$AE$3 -> 100 | BN3: =100*AR3/AR$3 -> 100 | BO3: =100*AX3/AX$3 -> 100
A4: Median home price growth p.a. | B4: =((_xlfn.XLOOKUP(Q_end,L:L,AR:AR)/_xlfn.XLOOKUP(Q_start,L:L,AR:AR))^(1/YEARFRAC(EOMONTH(Q_start,-3)+1,EOMONTH(Q_end,0))))-1 -> 0.062987797 | L4: =IF(DATE(YEAR(L3),MONTH(L3)+3,1)<=Q_end,DATE(YEAR(L3),MONTH(L3)+3,1),"") -> 38869 | M4: =AP4 -> 80853.41 | N4: =AX4-BC4 -> 54140.593 | O4: =M4/N4 -> 1.4933972 | P4: =X4/BG4 -> 0.55396017 | Q4: 2 | R4: =EOMONTH(L4,0)-EOMONTH(L4,-3) -> 91 | T4: =IF($B$10="3BR_H", INDEX('3BR_H-processed'!$E:$F,MATCH($L4,'3BR_H-processed'!$B:$B,0),MATCH(Council_Area,'3BR_H-processed'!$E$1:$F$1,0)), INDEX('2BR_F-processed'!$E:$F,MATCH($L4,'2BR_F-processed'!$B:$B,0),MATCH(Council_Area,'2BR_F-processed'!$E$1:$F$1,0))) -> 238.64607 | U4: =IF(MOD(Q4,4)=1,T4,U3) -> 238.64607 | V4: =U4*(R4)/7 -> 3102.3989 | W4: =$B$53/4*BH4/_xlfn.XLOOKUP(Q_end,cpi!A:A,cpi!B:B) -> 118.7284 | X4: =V4+W4 -> 3221.1273 | Y4: =BG4-X4 -> 2593.5999 | Z4: =Y4*$B$47 -> 0 | AA4: {=(Y4+Z4)*eff_invest} -> 2593.5999 | AB4: =AA4*(_xlfn.XLOOKUP(Q_end,cpi!A:A,cpi!B:B)/BH4) -> 4368.9629 | AC4: {=INDEX('msci-indices'!C:C,MATCH($L4,'msci-indices'!$B:$B)-2)} -> 809.32012 | AD4: {=INDEX('msci-indices'!D:D,MATCH($L4,'msci-indices'!$B:$B)-2)} -> 780.24347 | AE4: =AI3+AA4 -> 81380.853 | AF4: {=INDEX('msci-indices'!C:C,MATCH($L4,'msci-indices'!$B:$B)+1)} -> 802.64573 | AG4: {=INDEX('msci-indices'!D:D,MATCH($L4,'msci-indices'!$B:$B)+1)} -> 780.02674 | AH4: =(InvestFees/4)*AE4 -> 50.863033 | AI4: =((AF4/AC4)*GlobalPortfolio+(AG4/AD4)*AusPortfolio)*AE4-AH4 -> 80853.41 | AJ4: =AJ3+AA4 -> 75668.512 | AK4: =AI4-AJ4 -> 5184.898 | AL4: =AJ4*(_xlfn.XLOOKUP(Q_end,cpi!A:A,cpi!B:B)/BH4) -> 127464.89 | AM4: {=SUMPRODUCT($AA$3:AA4,_xlfn.SORTBY($BH$3:BH4,_xlfn.SEQUENCE(ROWS($BH$3:BH4)),-1)/$BH$3)} -> 76791.413 | AN4: =AI4-AM4 -> 4061.9975 | AO4: =IF($B$49="Real gains",MAX($B$50*AN4,0),IF($B$49="Discounted nominal gains",MAX($B$50*AK4/2,0),0)) -> 0 | AP4: =AI4-AO4 -> 80853.41 | AR4: =IF($B$10="3BR_H", INDEX('ns-combined'!$C:$D,MATCH($L4,'ns-combined'!$B:$B,0),MATCH(Council_Area,'ns-combined'!$C$1:$D$1,0))*1000, INDEX('s-combined'!$C:$D,MATCH($L4,'s-combined'!$B:$B,0),MATCH(Council_Area,'s-combined'!$C$1:$D$1,0))*1000) -> 286000 | AS4: =AS3+$AS$3 -> 1400 | AT4: 0 | AU4: =SUM($B$28:$B$29)*AR4 -> 5720 | AV4: =AR4*$B$15/4 -> 822.25 | AW4: =SUM($AV$3:AV4) -> 1627.25 | AX4: =AR4-AS4-AU4-AW4 -> 277252.75 | AY4: =$B$36*V4 -> 1085.8396 | AZ4: =SUM(AY4:AY4)*4/AR4 -> 0.015186568 | BA4: =SUM(AY4:AY4)/V4 -> 0.35 | BB4: =IF(MortgageRate="Discounted",_xlfn.XLOOKUP(L4,'mortgage-rates'!$A:$A,'mortgage-rates'!$E:$E)/100,_xlfn.XLOOKUP(L4,'mortgage-rates'!$A:$A,'mortgage-rates'!$D:$D)/100) -> 0.0693 | BC4: =BC3-BF3 -> 223112.16 | BD4: =IF($B$16*12/3-Q4+1>0,-PMT($BB4/4,$B$16*12/3-Q4+1,BC4),0) -> 4728.8876 | BE4: =BC4*($BB4/4) -> 3865.4181 | BF4: =BD4-BE4 -> 863.4695 | BG4: =AT4+AY4+BD4 -> 5814.7272 | BH4: =INDEX(cpi!B:B,MATCH($L4,cpi!A:A)) -> 85.9 | BI4: =100*BH4/BH$3 -> 101.53664 | BJ4: =100*AC4/AC$3 -> 107.21181 | BK4: =100*AD4/AD$3 -> 109.43778 | BL4: =BJ4*GlobalPortfolio+BK4*AusPortfolio -> 107.8796 | BM4: =100*AE4/$AE$3 -> 111.36634 | BN4: =100*AR4/AR$3 -> 102.14286 | BO4: =100*AX4/AX$3 -> 101.59686
A5: Adjusted home price growth p.a. | B5: =((_xlfn.XLOOKUP(Q_end,L:L,AX:AX)/_xlfn.XLOOKUP(Q_start,L:L,AX:AX))^(1/YEARFRAC(EOMONTH(Q_start,-3)+1,EOMONTH(Q_end,0))))-1 -> 0.052745728 | L5: =DATE(YEAR(L4),MONTH(L4)+3,1) -> 38961 | M5: =AP5 -> 86543.751 | N5: =AX5-BC5 -> 57390.313 | O5: =M5/N5 -> 1.5079853 | P5: =X5/BG5 -> 0.54726718 | Q5: 3 | R5: =EOMONTH(L5,0)-EOMONTH(L5,-3) -> 92 | T5: =IF($B$10="3BR_H", INDEX('3BR_H-processed'!$E:$F,MATCH($L5,'3BR_H-processed'!$B:$B,0),MATCH(Council_Area,'3BR_H-processed'!$E$1:$F$1,0)), INDEX('2BR_F-processed'!$E:$F,MATCH($L5,'2BR_F-processed'!$B:$B,0),MATCH(Council_Area,'2BR_F-processed'!$E$1:$F$1,0))) -> 238.64607 | U5: =IF(MOD(Q5,4)=1,T5,U4) -> 238.64607 | V5: =U5*(R5)/7 -> 3136.4912 | W5: =$B$53/4*BH5/_xlfn.XLOOKUP(Q_end,cpi!A:A,cpi!B:B) -> 119.69592 | X5: =V5+W5 -> 3256.1871 | Y5: =BG5-X5 -> 2693.7167 | Z5: =Y5*$B$47 -> 0 | AA5: {=(Y5+Z5)*eff_invest} -> 2693.7167 | AB5: =AA5*(_xlfn.XLOOKUP(Q_end,cpi!A:A,cpi!B:B)/BH5) -> 4500.9331 | AC5: {=INDEX('msci-indices'!C:C,MATCH($L5,'msci-indices'!$B:$B)-2)} -> 802.64573 | AD5: {=INDEX('msci-indices'!D:D,MATCH($L5,'msci-indices'!$B:$B)-2)} -> 780.02674 | AE5: =AI4+AA5 -> 83547.127 | AF5: {=INDEX('msci-indices'!C:C,MATCH($L5,'msci-indices'!$B:$B)+1)} -> 835.13401 | AG5: {=INDEX('msci-indices'!D:D,MATCH($L5,'msci-indices'!$B:$B)+1)} -> 801.24067 | AH5: =(InvestFees/4)*AE5 -> 52.216954 | AI5: =((AF5/AC5)*GlobalPortfolio+(AG5/AD5)*AusPortfolio)*AE5-AH5 -> 86543.751 | AJ5: =AJ4+AA5 -> 78362.229 | AK5: =AI5-AJ5 -> 8181.5218 | AL5: =AJ5*(_xlfn.XLOOKUP(Q_end,cpi!A:A,cpi!B:B)/BH5) -> 130935.5 | AM5: {=SUMPRODUCT($AA$3:AA5,_xlfn.SORTBY($BH$3:BH5,_xlfn.SEQUENCE(ROWS($BH$3:BH5)),-1)/$BH$3)} -> 80129.623 | AN5: =AI5-AM5 -> 6414.1281 | AO5: =IF($B$49="Real gains",MAX($B$50*AN5,0),IF($B$49="Discounted nominal gains",MAX($B$50*AK5/2,0),0)) -> 0 | AP5: =AI5-AO5 -> 86543.751 | AR5: =IF($B$10="3BR_H", INDEX('ns-combined'!$C:$D,MATCH($L5,'ns-combined'!$B:$B,0),MATCH(Council_Area,'ns-combined'!$C$1:$D$1,0))*1000, INDEX('s-combined'!$C:$D,MATCH($L5,'s-combined'!$B:$B,0),MATCH(Council_Area,'s-combined'!$C$1:$D$1,0))*1000) -> 290000 | AS5: =AS4+$AS$3 -> 2100 | AT5: 0 | AU5: =SUM($B$28:$B$29)*AR5 -> 5800 | AV5: =AR5*$B$15/4 -> 833.75 | AW5: =SUM($AV$3:AV5) -> 2461 | AX5: =AR5-AS5-AU5-AW5 -> 279639 | AY5: =$B$36*V5 -> 1097.7719 | AZ5: =SUM(AY5:AY5)*4/AR5 -> 0.015141682 | BA5: =SUM(AY5:AY5)/V5 -> 0.35 | BB5: =IF(MortgageRate="Discounted",_xlfn.XLOOKUP(L5,'mortgage-rates'!$A:$A,'mortgage-rates'!$E:$E)/100,_xlfn.XLOOKUP(L5,'mortgage-rates'!$A:$A,'mortgage-rates'!$D:$D)/100) -> 0.0722 | BC5: =BC4-BF4 -> 222248.69 | BD5: =IF($B$16*12/3-Q5+1>0,-PMT($BB5/4,$B$16*12/3-Q5+1,BC5),0) -> 4852.1319 | BE5: =BC5*($BB5/4) -> 4011.5888 | BF5: =BD5-BE5 -> 840.54311 | BG5: =AT5+AY5+BD5 -> 5949.9038 | BH5: =INDEX(cpi!B:B,MATCH($L5,cpi!A:A)) -> 86.6 | BI5: =100*BH5/BH$3 -> 102.36407 | BJ5: =100*AC5/AC$3 -> 106.32765 | BK5: =100*AD5/AD$3 -> 109.40738 | BL5: =BJ5*GlobalPortfolio+BK5*AusPortfolio -> 107.25157 | BM5: =100*AE5/$AE$3 -> 114.33079 | BN5: =100*AR5/AR$3 -> 103.57143 | BO5: =100*AX5/AX$3 -> 102.47128
A6: Rent growth p.a. | B6: =((_xlfn.XLOOKUP(Q_end,L:L,U:U)/_xlfn.XLOOKUP(Q_start,L:L,U:U))^(1/YEARFRAC(EOMONTH(Q_start,-3)+1,EOMONTH(Q_end,0))))-1 -> 0.046296774 | L6: =DATE(YEAR(L5),MONTH(L5)+3,1) -> 39052 | M6: =AP6 -> 97451.217 | N6: =AX6-BC6 -> 66468.356 | O6: =M6/N6 -> 1.4661295 | P6: =X6/BG6 -> 0.53765358 | Q6: 4 | R6: =EOMONTH(L6,0)-EOMONTH(L6,-3) -> 92 | T6: =IF($B$10="3BR_H", INDEX('3BR_H-processed'!$E:$F,MATCH($L6,'3BR_H-processed'!$B:$B,0),MATCH(Council_Area,'3BR_H-processed'!$E$1:$F$1,0)), INDEX('2BR_F-processed'!$E:$F,MATCH($L6,'2BR_F-processed'!$B:$B,0),MATCH(Council_Area,'2BR_F-processed'!$E$1:$F$1,0))) -> 238.64607 | U6: =IF(MOD(Q6,4)=1,T6,U5) -> 238.64607 | V6: =U6*(R6)/7 -> 3136.4912 | W6: =$B$53/4*BH6/_xlfn.XLOOKUP(Q_end,cpi!A:A,cpi!B:B) -> 119.83414 | X6: =V6+W6 -> 3256.3253 | Y6: =BG6-X6 -> 2800.2238 | Z6: =Y6*$B$47 -> 0 | AA6: {=(Y6+Z6)*eff_invest} -> 2800.2238 | AB6: =AA6*(_xlfn.XLOOKUP(Q_end,cpi!A:A,cpi!B:B)/BH6) -> 4673.4993 | AC6: {=INDEX('msci-indices'!C:C,MATCH($L6,'msci-indices'!$B:$B)-2)} -> 835.13401 | AD6: {=INDEX('msci-indices'!D:D,MATCH($L6,'msci-indices'!$B:$B)-2)} -> 801.24067 | AE6: =AI5+AA6 -> 89343.975 | AF6: {=INDEX('msci-indices'!C:C,MATCH($L6,'msci-indices'!$B:$B)+1)} -> 906.58022 | AG6: {=INDEX('msci-indices'!D:D,MATCH($L6,'msci-indices'!$B:$B)+1)} -> 885.32149 | AH6: =(InvestFees/4)*AE6 -> 55.839984 | AI6: =((AF6/AC6)*GlobalPortfolio+(AG6/AD6)*AusPortfolio)*AE6-AH6 -> 97451.217 | AJ6: =AJ5+AA6 -> 81162.453 | AK6: =AI6-AJ6 -> 16288.764 | AL6: =AJ6*(_xlfn.XLOOKUP(Q_end,cpi!A:A,cpi!B:B)/BH6) -> 135457.98 | AM6: {=SUMPRODUCT($AA$3:AA6,_xlfn.SORTBY($BH$3:BH6,_xlfn.SEQUENCE(ROWS($BH$3:BH6)),-1)/$BH$3)} -> 83079.076 | AN6: =AI6-AM6 -> 14372.14 | AO6: =IF($B$49="Real gains",MAX($B$50*AN6,0),IF($B$49="Discounted nominal gains",MAX($B$50*AK6/2,0),0)) -> 0 | AP6: =AI6-AO6 -> 97451.217 | AR6: =IF($B$10="3BR_H", INDEX('ns-combined'!$C:$D,MATCH($L6,'ns-combined'!$B:$B,0),MATCH(Council_Area,'ns-combined'!$C$1:$D$1,0))*1000, INDEX('s-combined'!$C:$D,MATCH($L6,'s-combined'!$B:$B,0),MATCH(Council_Area,'s-combined'!$C$1:$D$1,0))*1000) -> 300000 | AS6: =AS5+$AS$3 -> 2800 | AT6: 0 | AU6: =SUM($B$28:$B$29)*AR6 -> 6000 | AV6: =AR6*$B$15/4 -> 862.5 | AW6: =SUM($AV$3:AV6) -> 3323.5 | AX6: =AR6-AS6-AU6-AW6 -> 287876.5 | AY6: =$B$36*V6 -> 1097.7719 | AZ6: =SUM(AY6:AY6)*4/AR6 -> 0.014636959 | BA6: =SUM(AY6:AY6)/V6 -> 0.35 | BB6: =IF(MortgageRate="Discounted",_xlfn.XLOOKUP(L6,'mortgage-rates'!$A:$A,'mortgage-rates'!$E:$E)/100,_xlfn.XLOOKUP(L6,'mortgage-rates'!$A:$A,'mortgage-rates'!$D:$D)/100) -> 0.0747 | BC6: =BC5-BF5 -> 221408.14 | BD6: =IF($B$16*12/3-Q6+1>0,-PMT($BB6/4,$B$16*12/3-Q6+1,BC6),0) -> 4958.7772 | BE6: =BC6*($BB6/4) -> 4134.7971 | BF6: =BD6-BE6 -> 823.98014 | BG6: =AT6+AY6+BD6 -> 6056.5492 | BH6: =INDEX(cpi!B:B,MATCH($L6,cpi!A:A)) -> 86.7 | BI6: =100*BH6/BH$3 -> 102.48227 | BJ6: =100*AC6/AC$3 -> 110.63142 | BK6: =100*AD6/AD$3 -> 112.38287 | BL6: =BJ6*GlobalPortfolio+BK6*AusPortfolio -> 111.15685 | BM6: =100*AE6/$AE$3 -> 122.26354 | BN6: =100*AR6/AR$3 -> 107.14286 | BO6: =100*AX6/AX$3 -> 105.48984
A7: Investment index (country-weighted) growth p.a. | B7: =((_xlfn.XLOOKUP(Q_end,L:L,BL:BL)/_xlfn.XLOOKUP(Q_start,L:L,BL:BL))^(1/YEARFRAC(EOMONTH(Q_start,-3)+1,EOMONTH(Q_end,0))))-1 -> 0.080631422 | L7: =DATE(YEAR(L6),MONTH(L6)+3,1) -> 39142 | M7: =AP7 -> 104138.17 | N7: =AX7-BC7 -> 70615.461 | O7: =M7/N7 -> 1.474722 | P7: =X7/BG7 -> 0.55539464 | Q7: 5 | R7: =EOMONTH(L7,0)-EOMONTH(L7,-3) -> 90 | T7: =IF($B$10="3BR_H", INDEX('3BR_H-processed'!$E:$F,MATCH($L7,'3BR_H-processed'!$B:$B,0),MATCH(Council_Area,'3BR_H-processed'!$E$1:$F$1,0)), INDEX('2BR_F-processed'!$E:$F,MATCH($L7,'2BR_F-processed'!$B:$B,0),MATCH(Council_Area,'2BR_F-processed'!$E$1:$F$1,0))) -> 254.32303 | U7: =IF(MOD(Q7,4)=1,T7,U6) -> 254.32303 | V7: =U7*(R7)/7 -> 3269.8676 | W7: =$B$53/4*BH7/_xlfn.XLOOKUP(Q_end,cpi!A:A,cpi!B:B) -> 119.83414 | X7: =V7+W7 -> 3389.7017 | Y7: =BG7-X7 -> 2713.5292 | Z7: =Y7*$B$47 -> 0 | AA7: {=(Y7+Z7)*eff_invest} -> 2713.5292 | AB7: =AA7*(_xlfn.XLOOKUP(Q_end,cpi!A:A,cpi!B:B)/BH7) -> 4528.8082 | AC7: {=INDEX('msci-indices'!C:C,MATCH($L7,'msci-indices'!$B:$B)-2)} -> 906.58022 | AD7: {=INDEX('msci-indices'!D:D,MATCH($L7,'msci-indices'!$B:$B)-2)} -> 885.32149 | AE7: =AI6+AA7 -> 100164.75 | AF7: {=INDEX('msci-indices'!C:C,MATCH($L7,'msci-indices'!$B:$B)+1)} -> 932.09759 | AG7: {=INDEX('msci-indices'!D:D,MATCH($L7,'msci-indices'!$B:$B)+1)} -> 946.08734 | AH7: =(InvestFees/4)*AE7 -> 62.602966 | AI7: =((AF7/AC7)*GlobalPortfolio+(AG7/AD7)*AusPortfolio)*AE7-AH7 -> 104138.17 | AJ7: =AJ6+AA7 -> 83875.982 | AK7: =AI7-AJ7 -> 20262.189 | AL7: =AJ7*(_xlfn.XLOOKUP(Q_end,cpi!A:A,cpi!B:B)/BH7) -> 139986.79 | AM7: {=SUMPRODUCT($AA$3:AA7,_xlfn.SORTBY($BH$3:BH7,_xlfn.SEQUENCE(ROWS($BH$3:BH7)),-1)/$BH$3)} -> 85860.989 | AN7: =AI7-AM7 -> 18277.182 | AO7: =IF($B$49="Real gains",MAX($B$50*AN7,0),IF($B$49="Discounted nominal gains",MAX($B$50*AK7/2,0),0)) -> 0 | AP7: =AI7-AO7 -> 104138.17 | AR7: =IF($B$10="3BR_H", INDEX('ns-combined'!$C:$D,MATCH($L7,'ns-combined'!$B:$B,0),MATCH(Council_Area,'ns-combined'!$C$1:$D$1,0))*1000, INDEX('s-combined'!$C:$D,MATCH($L7,'s-combined'!$B:$B,0),MATCH(Council_Area,'s-combined'!$C$1:$D$1,0))*1000) -> 305000 | AS7: =AS6+$AS$3 -> 3500 | AT7: 0 | AU7: =SUM($B$28:$B$29)*AR7 -> 6100 | AV7: =AR7*$B$15/4 -> 876.875 | AW7: =SUM($AV$3:AV7) -> 4200.375 | AX7: =AR7-AS7-AU7-AW7 -> 291199.62 | AY7: =$B$36*V7 -> 1144.4537 | AZ7: =SUM(AY7:AY7)*4/AR7 -> 0.015009228 | BA7: =SUM(AY7:AY7)/V7 -> 0.35 | BB7: =IF(MortgageRate="Discounted",_xlfn.XLOOKUP(L7,'mortgage-rates'!$A:$A,'mortgage-rates'!$E:$E)/100,_xlfn.XLOOKUP(L7,'mortgage-rates'!$A:$A,'mortgage-rates'!$D:$D)/100) -> 0.0747 | BC7: =BC6-BF6 -> 220584.16 | BD7: =IF($B$16*12/3-Q7+1>0,-PMT($BB7/4,$B$16*12/3-Q7+1,BC7),0) -> 4958.7772 | BE7: =BC7*($BB7/4) -> 4119.4093 | BF7: =BD7-BE7 -> 839.36797 | BG7: =AT7+AY7+BD7 -> 6103.2309 | BH7: =INDEX(cpi!B:B,MATCH($L7,cpi!A:A)) -> 86.7 | BI7: =100*BH7/BH$3 -> 102.48227 | BJ7: =100*AC7/AC$3 -> 120.096 | BK7: =100*AD7/AD$3 -> 124.17613 | BL7: =BJ7*GlobalPortfolio+BK7*AusPortfolio -> 121.32004 | BM7: =100*AE7/$AE$3 -> 137.07132 | BN7: =100*AR7/AR$3 -> 108.92857 | BO7: =100*AX7/AX$3 -> 106.70757
A8: CPI growth p.a. | B8: =((_xlfn.XLOOKUP(Q_end,L:L,BI:BI)/_xlfn.XLOOKUP(Q_start,L:L,BI:BI))^(1/YEARFRAC(EOMONTH(Q_start,-3)+1,EOMONTH(Q_end,0))))-1 -> 0.027199758 | L8: =DATE(YEAR(L7),MONTH(L7)+3,1) -> 39234 | M8: =AP8 -> 113401.63 | N8: =AX8-BC8 -> 79649.204 | O8: =M8/N8 -> 1.4237636 | P8: =X8/BG8 -> 0.56040638 | Q8: 6 | R8: =EOMONTH(L8,0)-EOMONTH(L8,-3) -> 91 | T8: =IF($B$10="3BR_H", INDEX('3BR_H-processed'!$E:$F,MATCH($L8,'3BR_H-processed'!$B:$B,0),MATCH(Council_Area,'3BR_H-processed'!$E$1:$F$1,0)), INDEX('2BR_F-processed'!$E:$F,MATCH($L8,'2BR_F-processed'!$B:$B,0),MATCH(Council_Area,'2BR_F-processed'!$E$1:$F$1,0))) -> 254.32303 | U8: =IF(MOD(Q8,4)=1,T8,U7) -> 254.32303 | V8: =U8*(R8)/7 -> 3306.1995 | W8: =$B$53/4*BH8/_xlfn.XLOOKUP(Q_end,cpi!A:A,cpi!B:B) -> 121.21631 | X8: =V8+W8 -> 3427.4158 | Y8: =BG8-X8 -> 2688.5313 | Z8: =Y8*$B$47 -> 0 | AA8: {=(Y8+Z8)*eff_invest} -> 2688.5313 | AB8: =AA8*(_xlfn.XLOOKUP(Q_end,cpi!A:A,cpi!B:B)/BH8) -> 4435.9233 | AC8: {=INDEX('msci-indices'!C:C,MATCH($L8,'msci-indices'!$B:$B)-2)} -> 932.09759 | AD8: {=INDEX('msci-indices'!D:D,MATCH($L8,'msci-indices'!$B:$B)-2)} -> 946.08734 | AE8: =AI7+AA8 -> 106826.7 | AF8: {=INDEX('msci-indices'!C:C,MATCH($L8,'msci-indices'!$B:$B)+1)} -> 991.70582 | AG8: {=INDEX('msci-indices'!D:D,MATCH($L8,'msci-indices'!$B:$B)+1)} -> 1000.9831 | AH8: =(InvestFees/4)*AE8 -> 66.766689 | AI8: =((AF8/AC8)*GlobalPortfolio+(AG8/AD8)*AusPortfolio)*AE8-AH8 -> 113401.63 | AJ8: =AJ7+AA8 -> 86564.513 | AK8: =AI8-AJ8 -> 26837.121 | AL8: =AJ8*(_xlfn.XLOOKUP(Q_end,cpi!A:A,cpi!B:B)/BH8) -> 142826.51 | AM8: {=SUMPRODUCT($AA$3:AA8,_xlfn.SORTBY($BH$3:BH8,_xlfn.SEQUENCE(ROWS($BH$3:BH8)),-1)/$BH$3)} -> 89481.341 | AN8: =AI8-AM8 -> 23920.293 | AO8: =IF($B$49="Real gains",MAX($B$50*AN8,0),IF($B$49="Discounted nominal gains",MAX($B$50*AK8/2,0),0)) -> 0 | AP8: =AI8-AO8 -> 113401.63 | AR8: =IF($B$10="3BR_H", INDEX('ns-combined'!$C:$D,MATCH($L8,'ns-combined'!$B:$B,0),MATCH(Council_Area,'ns-combined'!$C$1:$D$1,0))*1000, INDEX('s-combined'!$C:$D,MATCH($L8,'s-combined'!$B:$B,0),MATCH(Council_Area,'s-combined'!$C$1:$D$1,0))*1000) -> 315000 | AS8: =AS7+$AS$3 -> 4200 | AT8: 0 | AU8: =SUM($B$28:$B$29)*AR8 -> 6300 | AV8: =AR8*$B$15/4 -> 905.625 | AW8: =SUM($AV$3:AV8) -> 5106 | AX8: =AR8-AS8-AU8-AW8 -> 299394 | AY8: =$B$36*V8 -> 1157.1698 | AZ8: =SUM(AY8:AY8)*4/AR8 -> 0.01469422 | BA8: =SUM(AY8:AY8)/V8 -> 0.35 | BB8: =IF(MortgageRate="Discounted",_xlfn.XLOOKUP(L8,'mortgage-rates'!$A:$A,'mortgage-rates'!$E:$E)/100,_xlfn.XLOOKUP(L8,'mortgage-rates'!$A:$A,'mortgage-rates'!$D:$D)/100) -> 0.0747 | BC8: =BC7-BF7 -> 219744.8 | BD8: =IF($B$16*12/3-Q8+1>0,-PMT($BB8/4,$B$16*12/3-Q8+1,BC8),0) -> 4958.7772 | BE8: =BC8*($BB8/4) -> 4103.7341 | BF8: =BD8-BE8 -> 855.04317 | BG8: =AT8+AY8+BD8 -> 6115.947 | BH8: =INDEX(cpi!B:B,MATCH($L8,cpi!A:A)) -> 87.7 | BI8: =100*BH8/BH$3 -> 103.6643 | BJ8: =100*AC8/AC$3 -> 123.47632 | BK8: =100*AD8/AD$3 -> 132.69921 | BL8: =BJ8*GlobalPortfolio+BK8*AusPortfolio -> 126.24319 | BM8: =100*AE8/$AE$3 -> 146.18793 | BN8: =100*AR8/AR$3 -> 112.5 | BO8: =100*AX8/AX$3 -> 109.71033
L9: =DATE(YEAR(L8),MONTH(L8)+3,1) -> 39326 | M9: =AP9 -> 119680.18 | N9: =AX9-BC9 -> 98441.122 | O9: =M9/N9 -> 1.2157539 | P9: =X9/BG9 -> 0.55571823 | Q9: 7 | R9: =EOMONTH(L9,0)-EOMONTH(L9,-3) -> 92 | T9: =IF($B$10="3BR_H", INDEX('3BR_H-processed'!$E:$F,MATCH($L9,'3BR_H-processed'!$B:$B,0),MATCH(Council_Area,'3BR_H-processed'!$E$1:$F$1,0)), INDEX('2BR_F-processed'!$E:$F,MATCH($L9,'2BR_F-processed'!$B:$B,0),MATCH(Council_Area,'2BR_F-processed'!$E$1:$F$1,0))) -> 254.32303 | U9: =IF(MOD(Q9,4)=1,T9,U8) -> 254.32303 | V9: =U9*(R9)/7 -> 3342.5313 | W9: =$B$53/4*BH9/_xlfn.XLOOKUP(Q_end,cpi!A:A,cpi!B:B) -> 121.90739 | X9: =V9+W9 -> 3464.4387 | Y9: =BG9-X9 -> 2769.7255 | Z9: =Y9*$B$47 -> 0 | AA9: {=(Y9+Z9)*eff_invest} -> 2769.7255 | AB9: =AA9*(_xlfn.XLOOKUP(Q_end,cpi!A:A,cpi!B:B)/BH9) -> 4543.9828 | AC9: {=INDEX('msci-indices'!C:C,MATCH($L9,'msci-indices'!$B:$B)-2)} -> 991.70582 | AD9: {=INDEX('msci-indices'!D:D,MATCH($L9,'msci-indices'!$B:$B)-2)} -> 1000.9831 | AE9: =AI8+AA9 -> 116171.36 | AF9: {=INDEX('msci-indices'!C:C,MATCH($L9,'msci-indices'!$B:$B)+1)} -> 1009.8701 | AG9: {=INDEX('msci-indices'!D:D,MATCH($L9,'msci-indices'!$B:$B)+1)} -> 1061.067 | AH9: =(InvestFees/4)*AE9 -> 72.6071 | AI9: =((AF9/AC9)*GlobalPortfolio+(AG9/AD9)*AusPortfolio)*AE9-AH9 -> 119680.18 | AJ9: =AJ8+AA9 -> 89334.239 | AK9: =AI9-AJ9 -> 30345.941 | AL9: =AJ9*(_xlfn.XLOOKUP(Q_end,cpi!A:A,cpi!B:B)/BH9) -> 146560.82 | AM9: {=SUMPRODUCT($AA$3:AA9,_xlfn.SORTBY($BH$3:BH9,_xlfn.SEQUENCE(ROWS($BH$3:BH9)),-1)/$BH$3)} -> 92780.684 | AN9: =AI9-AM9 -> 26899.495 | AO9: =IF($B$49="Real gains",MAX($B$50*AN9,0),IF($B$49="Discounted nominal gains",MAX($B$50*AK9/2,0),0)) -> 0 | AP9: =AI9-AO9 -> 119680.18 | AR9: =IF($B$10="3BR_H", INDEX('ns-combined'!$C:$D,MATCH($L9,'ns-combined'!$B:$B,0),MATCH(Council_Area,'ns-combined'!$C$1:$D$1,0))*1000, INDEX('s-combined'!$C:$D,MATCH($L9,'s-combined'!$B:$B,0),MATCH(Council_Area,'s-combined'!$C$1:$D$1,0))*1000) -> 335000 | AS9: =AS8+$AS$3 -> 4900 | AT9: 0 | AU9: =SUM($B$28:$B$29)*AR9 -> 6700 | AV9: =AR9*$B$15/4 -> 963.125 | AW9: =SUM($AV$3:AV9) -> 6069.125 | AX9: =AR9-AS9-AU9-AW9 -> 317330.88 | AY9: =$B$36*V9 -> 1169.886 | AZ9: =SUM(AY9:AY9)*4/AR9 -> 0.013968788 | BA9: =SUM(AY9:AY9)/V9 -> 0.35 | BB9: =IF(MortgageRate="Discounted",_xlfn.XLOOKUP(L9,'mortgage-rates'!$A:$A,'mortgage-rates'!$E:$E)/100,_xlfn.XLOOKUP(L9,'mortgage-rates'!$A:$A,'mortgage-rates'!$D:$D)/100) -> 0.0772 | BC9: =BC8-BF8 -> 218889.75 | BD9: =IF($B$16*12/3-Q9+1>0,-PMT($BB9/4,$B$16*12/3-Q9+1,BC9),0) -> 5064.2783 | BE9: =BC9*($BB9/4) -> 4224.5722 | BF9: =BD9-BE9 -> 839.70606 | BG9: =AT9+AY9+BD9 -> 6234.1642 | BH9: =INDEX(cpi!B:B,MATCH($L9,cpi!A:A)) -> 88.2 | BI9: =100*BH9/BH$3 -> 104.25532 | BJ9: =100*AC9/AC$3 -> 131.37271 | BK9: =100*AD9/AD$3 -> 140.39895 | BL9: =BJ9*GlobalPortfolio+BK9*AusPortfolio -> 134.08059 | BM9: =100*AE9/$AE$3 -> 158.97571 | BN9: =100*AR9/AR$3 -> 119.64286 | BO9: =100*AX9/AX$3 -> 116.28314
A10: Dwelling type (3br house, 3BR_H; or 2br flat, 2BR_F) | B10: 3BR_H | C10: 3BR_H | L10: =DATE(YEAR(L9),MONTH(L9)+3,1) -> 39417 | M10: =AP10 -> 119165.39 | N10: =AX10-BC10 -> 120091.58 | O10: =M10/N10 -> 0.99228761 | P10: =X10/BG10 -> 0.54669013 | Q10: 8 | R10: =EOMONTH(L10,0)-EOMONTH(L10,-3) -> 92 | T10: =IF($B$10="3BR_H", INDEX('3BR_H-processed'!$E:$F,MATCH($L10,'3BR_H-processed'!$B:$B,0),MATCH(Council_Area,'3BR_H-processed'!$E$1:$F$1,0)), INDEX('2BR_F-processed'!$E:$F,MATCH($L10,'2BR_F-processed'!$B:$B,0),MATCH(Council_Area,'2BR_F-processed'!$E$1:$F$1,0))) -> 254.32303 | U10: =IF(MOD(Q10,4)=1,T10,U9) -> 254.32303 | V10: =U10*(R10)/7 -> 3342.5313 | W10: =$B$53/4*BH10/_xlfn.XLOOKUP(Q_end,cpi!A:A,cpi!B:B) -> 123.42778 | X10: =V10+W10 -> 3465.9591 | Y10: =BG10-X10 -> 2873.9378 | Z10: =Y10*$B$47 -> 0 | AA10: {=(Y10+Z10)*eff_invest} -> 2873.9378 | AB10: =AA10*(_xlfn.XLOOKUP(Q_end,cpi!A:A,cpi!B:B)/BH10) -> 4656.8735 | AC10: {=INDEX('msci-indices'!C:C,MATCH($L10,'msci-indices'!$B:$B)-2)} -> 1009.8701 | AD10: {=INDEX('msci-indices'!D:D,MATCH($L10,'msci-indices'!$B:$B)-2)} -> 1061.067 | AE10: =AI9+AA10 -> 122554.12 | AF10: {=INDEX('msci-indices'!C:C,MATCH($L10,'msci-indices'!$B:$B)+1)} -> 983.50383 | AG10: {=INDEX('msci-indices'!D:D,MATCH($L10,'msci-indices'!$B:$B)+1)} -> 1030.1196 | AH10: =(InvestFees/4)*AE10 -> 76.596323 | AI10: =((AF10/AC10)*GlobalPortfolio+(AG10/AD10)*AusPortfolio)*AE10-AH10 -> 119165.39 | AJ10: =AJ9+AA10 -> 92208.177 | AK10: =AI10-AJ10 -> 26957.209 | AL10: =AJ10*(_xlfn.XLOOKUP(Q_end,cpi!A:A,cpi!B:B)/BH10) -> 149412.35 | AM10: {=SUMPRODUCT($AA$3:AA10,_xlfn.SORTBY($BH$3:BH10,_xlfn.SEQUENCE(ROWS($BH$3:BH10)),-1)/$BH$3)} -> 96719.952 | AN10: =AI10-AM10 -> 22445.434 | AO10: =IF($B$49="Real gains",MAX($B$50*AN10,0),IF($B$49="Discounted nominal gains",MAX($B$50*AK10/2,0),0)) -> 0 | AP10: =AI10-AO10 -> 119165.39 | AR10: =IF($B$10="3BR_H", INDEX('ns-combined'!$C:$D,MATCH($L10,'ns-combined'!$B:$B,0),MATCH(Council_Area,'ns-combined'!$C$1:$D$1,0))*1000, INDEX('s-combined'!$C:$D,MATCH($L10,'s-combined'!$B:$B,0),MATCH(Council_Area,'s-combined'!$C$1:$D$1,0))*1000) -> 358000 | AS10: =AS9+$AS$3 -> 5600 | AT10: 0 | AU10: =SUM($B$28:$B$29)*AR10 -> 7160 | AV10: =AR10*$B$15/4 -> 1029.25 | AW10: =SUM($AV$3:AV10) -> 7098.375 | AX10: =AR10-AS10-AU10-AW10 -> 338141.62 | AY10: =$B$36*V10 -> 1169.886 | AZ10: =SUM(AY10:AY10)*4/AR10 -> 0.013071352 | BA10: =SUM(AY10:AY10)/V10 -> 0.35 | BB10: =IF(MortgageRate="Discounted",_xlfn.XLOOKUP(L10,'mortgage-rates'!$A:$A,'mortgage-rates'!$E:$E)/100,_xlfn.XLOOKUP(L10,'mortgage-rates'!$A:$A,'mortgage-rates'!$D:$D)/100) -> 0.0797 | BC10: =BC9-BF9 -> 218050.05 | BD10: =IF($B$16*12/3-Q10+1>0,-PMT($BB10/4,$B$16*12/3-Q10+1,BC10),0) -> 5170.011 | BE10: =BC10*($BB10/4) -> 4344.6472 | BF10: =BD10-BE10 -> 825.36378 | BG10: =AT10+AY10+BD10 -> 6339.8969 | BH10: =INDEX(cpi!B:B,MATCH($L10,cpi!A:A)) -> 89.3 | BI10: =100*BH10/BH$3 -> 105.55556 | BJ10: =100*AC10/AC$3 -> 133.77897 | BK10: =100*AD10/AD$3 -> 148.82639 | BL10: =BJ10*GlobalPortfolio+BK10*AusPortfolio -> 138.29319 | BM10: =100*AE10/$AE$3 -> 167.71025 | BN10: =100*AR10/AR$3 -> 127.85714 | BO10: =100*AX10/AX$3 -> 123.90906
A11: Analysis start quarter | B11: 38777 | C11: 38777 | L11: =DATE(YEAR(L10),MONTH(L10)+3,1) -> 39508 | M11: =AP11 -> 109163.03 | N11: =AX11-BC11 -> 121141.94 | O11: =M11/N11 -> 0.90111674 | P11: =X11/BG11 -> 0.54169253 | Q11: 9 | R11: =EOMONTH(L11,0)-EOMONTH(L11,-3) -> 91 | T11: =IF($B$10="3BR_H", INDEX('3BR_H-processed'!$E:$F,MATCH($L11,'3BR_H-processed'!$B:$B,0),MATCH(Council_Area,'3BR_H-processed'!$E$1:$F$1,0)), INDEX('2BR_F-processed'!$E:$F,MATCH($L11,'2BR_F-processed'!$B:$B,0),MATCH(Council_Area,'2BR_F-processed'!$E$1:$F$1,0))) -> 270 | U11: =IF(MOD(Q11,4)=1,T11,U10) -> 270 | V11: =U11*(R11)/7 -> 3510 | W11: =$B$53/4*BH11/_xlfn.XLOOKUP(Q_end,cpi!A:A,cpi!B:B) -> 124.94817 | X11: =V11+W11 -> 3634.9482 | Y11: =BG11-X11 -> 3075.4049 | Z11: =Y11*$B$47 -> 0 | AA11: {=(Y11+Z11)*eff_invest} -> 3075.4049 | AB11: =AA11*(_xlfn.XLOOKUP(Q_end,cpi!A:A,cpi!B:B)/BH11) -> 4922.6891 | AC11: {=INDEX('msci-indices'!C:C,MATCH($L11,'msci-indices'!$B:$B)-2)} -> 983.50383 | AD11: {=INDEX('msci-indices'!D:D,MATCH($L11,'msci-indices'!$B:$B)-2)} -> 1030.1196 | AE11: =AI10+AA11 -> 122240.79 | AF11: {=INDEX('msci-indices'!C:C,MATCH($L11,'msci-indices'!$B:$B)+1)} -> 894.99836 | AG11: {=INDEX('msci-indices'!D:D,MATCH($L11,'msci-indices'!$B:$B)+1)} -> 881.21373 | AH11: =(InvestFees/4)*AE11 -> 76.400494 | AI11: =((AF11/AC11)*GlobalPortfolio+(AG11/AD11)*AusPortfolio)*AE11-AH11 -> 109163.03 | AJ11: =AJ10+AA11 -> 95283.582 | AK11: =AI11-AJ11 -> 13879.45 | AL11: =AJ11*(_xlfn.XLOOKUP(Q_end,cpi!A:A,cpi!B:B)/BH11) -> 152516.97 | AM11: {=SUMPRODUCT($AA$3:AA11,_xlfn.SORTBY($BH$3:BH11,_xlfn.SEQUENCE(ROWS($BH$3:BH11)),-1)/$BH$3)} -> 100898.5 | AN11: =AI11-AM11 -> 8264.528 | AO11: =IF($B$49="Real gains",MAX($B$50*AN11,0),IF($B$49="Discounted nominal gains",MAX($B$50*AK11/2,0),0)) -> 0 | AP11: =AI11-AO11 -> 109163.03 | AR11: =IF($B$10="3BR_H", INDEX('ns-combined'!$C:$D,MATCH($L11,'ns-combined'!$B:$B,0),MATCH(Council_Area,'ns-combined'!$C$1:$D$1,0))*1000, INDEX('s-combined'!$C:$D,MATCH($L11,'s-combined'!$B:$B,0),MATCH(Council_Area,'s-combined'!$C$1:$D$1,0))*1000) -> 360000 | AS11: =AS10+$AS$3 -> 6300 | AT11: 0 | AU11: =SUM($B$28:$B$29)*AR11 -> 7200 | AV11: =AR11*$B$15/4 -> 1035 | AW11: =SUM($AV$3:AV11) -> 8133.375 | AX11: =AR11-AS11-AU11-AW11 -> 338366.62 | AY11: =$B$36*V11 -> 1228.5 | AZ11: =SUM(AY11:AY11)*4/AR11 -> 0.01365 | BA11: =SUM(AY11:AY11)/V11 -> 0.35 | BB11: =IF(MortgageRate="Discounted",_xlfn.XLOOKUP(L11,'mortgage-rates'!$A:$A,'mortgage-rates'!$E:$E)/100,_xlfn.XLOOKUP(L11,'mortgage-rates'!$A:$A,'mortgage-rates'!$D:$D)/100) -> 0.087 | BC11: =BC10-BF10 -> 217224.68 | BD11: =IF($B$16*12/3-Q11+1>0,-PMT($BB11/4,$B$16*12/3-Q11+1,BC11),0) -> 5481.8531 | BE11: =BC11*($BB11/4) -> 4724.6369 | BF11: =BD11-BE11 -> 757.21625 | BG11: =AT11+AY11+BD11 -> 6710.3531 | BH11: =INDEX(cpi!B:B,MATCH($L11,cpi!A:A)) -> 90.4 | BI11: =100*BH11/BH$3 -> 106.85579 | BJ11: =100*AC11/AC$3 -> 130.28618 | BK11: =100*AD11/AD$3 -> 144.48568 | BL11: =BJ11*GlobalPortfolio+BK11*AusPortfolio -> 134.54603 | BM11: =100*AE11/$AE$3 -> 167.28147 | BN11: =100*AR11/AR$3 -> 128.57143 | BO11: =100*AX11/AX$3 -> 123.99151
A12: Analysis end quarter | B12: 45992 | C12: 45992 | L12: =DATE(YEAR(L11),MONTH(L11)+3,1) -> 39600 | M12: =AP12 -> 110539.25 | N12: =AX12-BC12 -> 125049.78 | O12: =M12/N12 -> 0.88396197 | P12: =X12/BG12 -> 0.53711575 | Q12: 10 | R12: =EOMONTH(L12,0)-EOMONTH(L12,-3) -> 91 | T12: =IF($B$10="3BR_H", INDEX('3BR_H-processed'!$E:$F,MATCH($L12,'3BR_H-processed'!$B:$B,0),MATCH(Council_Area,'3BR_H-processed'!$E$1:$F$1,0)), INDEX('2BR_F-processed'!$E:$F,MATCH($L12,'2BR_F-processed'!$B:$B,0),MATCH(Council_Area,'2BR_F-processed'!$E$1:$F$1,0))) -> 270 | U12: =IF(MOD(Q12,4)=1,T12,U11) -> 270 | V12: =U12*(R12)/7 -> 3510 | W12: =$B$53/4*BH12/_xlfn.XLOOKUP(Q_end,cpi!A:A,cpi!B:B) -> 126.60677 | X12: =V12+W12 -> 3636.6068 | Y12: =BG12-X12 -> 3134.0135 | Z12: =Y12*$B$47 -> 0 | AA12: {=(Y12+Z12)*eff_invest} -> 3134.0135 | AB12: =AA12*(_xlfn.XLOOKUP(Q_end,cpi!A:A,cpi!B:B)/BH12) -> 4950.7833 | AC12: {=INDEX('msci-indices'!C:C,MATCH($L12,'msci-indices'!$B:$B)-2)} -> 894.99836 | AD12: {=INDEX('msci-indices'!D:D,MATCH($L12,'msci-indices'!$B:$B)-2)} -> 881.21373 | AE12: =AI11+AA12 -> 112297.04 | AF12: {=INDEX('msci-indices'!C:C,MATCH($L12,'msci-indices'!$B:$B)+1)} -> 881.79174 | AG12: {=INDEX('msci-indices'!D:D,MATCH($L12,'msci-indices'!$B:$B)+1)} -> 867.41147 | AH12: =(InvestFees/4)*AE12 -> 70.185653 | AI12: =((AF12/AC12)*GlobalPortfolio+(AG12/AD12)*AusPortfolio)*AE12-AH12 -> 110539.25 | AJ12: =AJ11+AA12 -> 98417.595 | AK12: =AI12-AJ12 -> 12121.658 | AL12: =AJ12*(_xlfn.XLOOKUP(Q_end,cpi!A:A,cpi!B:B)/BH12) -> 155469.72 | AM12: {=SUMPRODUCT($AA$3:AA12,_xlfn.SORTBY($BH$3:BH12,_xlfn.SEQUENCE(ROWS($BH$3:BH12)),-1)/$BH$3)} -> 105260.72 | AN12: =AI12-AM12 -> 5278.5284 | AO12: =IF($B$49="Real gains",MAX($B$50*AN12,0),IF($B$49="Discounted nominal gains",MAX($B$50*AK12/2,0),0)) -> 0 | AP12: =AI12-AO12 -> 110539.25 | AR12: =IF($B$10="3BR_H", INDEX('ns-combined'!$C:$D,MATCH($L12,'ns-combined'!$B:$B,0),MATCH(Council_Area,'ns-combined'!$C$1:$D$1,0))*1000, INDEX('s-combined'!$C:$D,MATCH($L12,'s-combined'!$B:$B,0),MATCH(Council_Area,'s-combined'!$C$1:$D$1,0))*1000) -> 365000 | AS12: =AS11+$AS$3 -> 7000 | AT12: 0 | AU12: =SUM($B$28:$B$29)*AR12 -> 7300 | AV12: =AR12*$B$15/4 -> 1049.375 | AW12: =SUM($AV$3:AV12) -> 9182.75 | AX12: =AR12-AS12-AU12-AW12 -> 341517.25 | AY12: =$B$36*V12 -> 1228.5 | AZ12: =SUM(AY12:AY12)*4/AR12 -> 0.013463014 | BA12: =SUM(AY12:AY12)/V12 -> 0.35 | BB12: =IF(MortgageRate="Discounted",_xlfn.XLOOKUP(L12,'mortgage-rates'!$A:$A,'mortgage-rates'!$E:$E)/100,_xlfn.XLOOKUP(L12,'mortgage-rates'!$A:$A,'mortgage-rates'!$D:$D)/100) -> 0.0884 | BC12: =BC11-BF11 -> 216467.47 | BD12: =IF($B$16*12/3-Q12+1>0,-PMT($BB12/4,$B$16*12/3-Q12+1,BC12),0) -> 5542.1202 | BE12: =BC12*($BB12/4) -> 4783.931 | BF12: =BD12-BE12 -> 758.18923 | BG12: =AT12+AY12+BD12 -> 6770.6202 | BH12: =INDEX(cpi!B:B,MATCH($L12,cpi!A:A)) -> 91.6 | BI12: =100*BH12/BH$3 -> 108.27423 | BJ12: =100*AC12/AC$3 -> 118.56173 | BK12: =100*AD12/AD$3 -> 123.59997 | BL12: =BJ12*GlobalPortfolio+BK12*AusPortfolio -> 120.07321 | BM12: =100*AE12/$AE$3 -> 153.67387 | BN12: =100*AR12/AR$3 -> 130.35714 | BO12: =100*AX12/AX$3 -> 125.14603
A13: Council/Area | B13: Adelaide | C13: Adelaide | L13: =DATE(YEAR(L12),MONTH(L12)+3,1) -> 39692 | M13: =AP13 -> 97842.264 | N13: =AX13-BC13 -> 119172.97 | O13: =M13/N13 -> 0.82101052 | P13: =X13/BG13 -> 0.54468574 | Q13: 11 | R13: =EOMONTH(L13,0)-EOMONTH(L13,-3) -> 92 | T13: =IF($B$10="3BR_H", INDEX('3BR_H-processed'!$E:$F,MATCH($L13,'3BR_H-processed'!$B:$B,0),MATCH(Council_Area,'3BR_H-processed'!$E$1:$F$1,0)), INDEX('2BR_F-processed'!$E:$F,MATCH($L13,'2BR_F-processed'!$B:$B,0),MATCH(Council_Area,'2BR_F-processed'!$E$1:$F$1,0))) -> 280 | U13: =IF(MOD(Q13,4)=1,T13,U12) -> 270 | V13: =U13*(R13)/7 -> 3548.5714 | W13: =$B$53/4*BH13/_xlfn.XLOOKUP(Q_end,cpi!A:A,cpi!B:B) -> 127.98894 | X13: =V13+W13 -> 3676.5604 | Y13: =BG13-X13 -> 3073.314 | Z13: =Y13*$B$47 -> 0 | AA13: {=(Y13+Z13)*eff_invest} -> 3073.314 | AB13: =AA13*(_xlfn.XLOOKUP(Q_end,cpi!A:A,cpi!B:B)/BH13) -> 4802.468 | AC13: {=INDEX('msci-indices'!C:C,MATCH($L13,'msci-indices'!$B:$B)-2)} -> 881.79174 | AD13: {=INDEX('msci-indices'!D:D,MATCH($L13,'msci-indices'!$B:$B)-2)} -> 867.41147 | AE13: =AI12+AA13 -> 113612.57 | AF13: {=INDEX('msci-indices'!C:C,MATCH($L13,'msci-indices'!$B:$B)+1)} -> 747.65998 | AG13: {=INDEX('msci-indices'!D:D,MATCH($L13,'msci-indices'!$B:$B)+1)} -> 775.74397 | AH13: =(InvestFees/4)*AE13 -> 71.007854 | AI13: =((AF13/AC13)*GlobalPortfolio+(AG13/AD13)*AusPortfolio)*AE13-AH13 -> 97842.264 | AJ13: =AJ12+AA13 -> 101490.91 | AK13: =AI13-AJ13 -> -3648.6448 | AL13: =AJ13*(_xlfn.XLOOKUP(Q_end,cpi!A:A,cpi!B:B)/BH13) -> 158593.25 | AM13: {=SUMPRODUCT($AA$3:AA13,_xlfn.SORTBY($BH$3:BH13,_xlfn.SEQUENCE(ROWS($BH$3:BH13)),-1)/$BH$3)} -> 109430.85 | AN13: =AI13-AM13 -> -11588.585 | AO13: =IF($B$49="Real gains",MAX($B$50*AN13,0),IF($B$49="Discounted nominal gains",MAX($B$50*AK13/2,0),0)) -> 0 | AP13: =AI13-AO13 -> 97842.264 | AR13: =IF($B$10="3BR_H", INDEX('ns-combined'!$C:$D,MATCH($L13,'ns-combined'!$B:$B,0),MATCH(Council_Area,'ns-combined'!$C$1:$D$1,0))*1000, INDEX('s-combined'!$C:$D,MATCH($L13,'s-combined'!$B:$B,0),MATCH(Council_Area,'s-combined'!$C$1:$D$1,0))*1000) -> 360000 | AS13: =AS12+$AS$3 -> 7700 | AT13: 0 | AU13: =SUM($B$28:$B$29)*AR13 -> 7200 | AV13: =AR13*$B$15/4 -> 1035 | AW13: =SUM($AV$3:AV13) -> 10217.75 | AX13: =AR13-AS13-AU13-AW13 -> 334882.25 | AY13: =$B$36*V13 -> 1242 | AZ13: =SUM(AY13:AY13)*4/AR13 -> 0.0138 | BA13: =SUM(AY13:AY13)/V13 -> 0.35 | BB13: =IF(MortgageRate="Discounted",_xlfn.XLOOKUP(L13,'mortgage-rates'!$A:$A,'mortgage-rates'!$E:$E)/100,_xlfn.XLOOKUP(L13,'mortgage-rates'!$A:$A,'mortgage-rates'!$D:$D)/100) -> 0.0876 | BC13: =BC12-BF12 -> 215709.28 | BD13: =IF($B$16*12/3-Q13+1>0,-PMT($BB13/4,$B$16*12/3-Q13+1,BC13),0) -> 5507.8744 | BE13: =BC13*($BB13/4) -> 4724.0332 | BF13: =BD13-BE13 -> 783.84123 | BG13: =AT13+AY13+BD13 -> 6749.8744 | BH13: =INDEX(cpi!B:B,MATCH($L13,cpi!A:A)) -> 92.6 | BI13: =100*BH13/BH$3 -> 109.45626 | BJ13: =100*AC13/AC$3 -> 116.81223 | BK13: =100*AD13/AD$3 -> 121.66405 | BL13: =BJ13*GlobalPortfolio+BK13*AusPortfolio -> 118.26778 | BM13: =100*AE13/$AE$3 -> 155.47411 | BN13: =100*AR13/AR$3 -> 128.57143 | BO13: =100*AX13/AX$3 -> 122.71469
A14: Depreciation (% of initial home value per year) | B14: 0.01 | C14: 0.01 | L14: =DATE(YEAR(L13),MONTH(L13)+3,1) -> 39783 | M14: =AP14 -> 78719.757 | N14: =AX14-BC14 -> 113336.19 | O14: =M14/N14 -> 0.69456859 | P14: =X14/BG14 -> 0.64389259 | Q14: 12 | R14: =EOMONTH(L14,0)-EOMONTH(L14,-3) -> 92 | T14: =IF($B$10="3BR_H", INDEX('3BR_H-processed'!$E:$F,MATCH($L14,'3BR_H-processed'!$B:$B,0),MATCH(Council_Area,'3BR_H-processed'!$E$1:$F$1,0)), INDEX('2BR_F-processed'!$E:$F,MATCH($L14,'2BR_F-processed'!$B:$B,0),MATCH(Council_Area,'2BR_F-processed'!$E$1:$F$1,0))) -> 280 | U14: =IF(MOD(Q14,4)=1,T14,U13) -> 270 | V14: =U14*(R14)/7 -> 3548.5714 | W14: =$B$53/4*BH14/_xlfn.XLOOKUP(Q_end,cpi!A:A,cpi!B:B) -> 127.98894 | X14: =V14+W14 -> 3676.5604 | Y14: =BG14-X14 -> 2033.3366 | Z14: =Y14*$B$47 -> 0 | AA14: {=(Y14+Z14)*eff_invest} -> 2033.3366 | AB14: =AA14*(_xlfn.XLOOKUP(Q_end,cpi!A:A,cpi!B:B)/BH14) -> 3177.3629 | AC14: {=INDEX('msci-indices'!C:C,MATCH($L14,'msci-indices'!$B:$B)-2)} -> 747.65998 | AD14: {=INDEX('msci-indices'!D:D,MATCH($L14,'msci-indices'!$B:$B)-2)} -> 775.74397 | AE14: =AI13+AA14 -> 99875.601 | AF14: {=INDEX('msci-indices'!C:C,MATCH($L14,'msci-indices'!$B:$B)+1)} -> 582.01082 | AG14: {=INDEX('msci-indices'!D:D,MATCH($L14,'msci-indices'!$B:$B)+1)} -> 630.6613 | AH14: =(InvestFees/4)*AE14 -> 62.422251 | AI14: =((AF14/AC14)*GlobalPortfolio+(AG14/AD14)*AusPortfolio)*AE14-AH14 -> 78719.757 | AJ14: =AJ13+AA14 -> 103524.25 | AK14: =AI14-AJ14 -> -24804.489 | AL14: =AJ14*(_xlfn.XLOOKUP(Q_end,cpi!A:A,cpi!B:B)/BH14) -> 161770.61 | AM14: {=SUMPRODUCT($AA$3:AA14,_xlfn.SORTBY($BH$3:BH14,_xlfn.SEQUENCE(ROWS($BH$3:BH14)),-1)/$BH$3)} -> 111730.17 | AN14: =AI14-AM14 -> -33010.409 | AO14: =IF($B$49="Real gains",MAX($B$50*AN14,0),IF($B$49="Discounted nominal gains",MAX($B$50*AK14/2,0),0)) -> 0 | AP14: =AI14-AO14 -> 78719.757 | AR14: =IF($B$10="3BR_H", INDEX('ns-combined'!$C:$D,MATCH($L14,'ns-combined'!$B:$B,0),MATCH(Council_Area,'ns-combined'!$C$1:$D$1,0))*1000, INDEX('s-combined'!$C:$D,MATCH($L14,'s-combined'!$B:$B,0),MATCH(Council_Area,'s-combined'!$C$1:$D$1,0))*1000) -> 355000 | AS14: =AS13+$AS$3 -> 8400 | AT14: 0 | AU14: =SUM($B$28:$B$29)*AR14 -> 7100 | AV14: =AR14*$B$15/4 -> 1020.625 | AW14: =SUM($AV$3:AV14) -> 11238.375 | AX14: =AR14-AS14-AU14-AW14 -> 328261.62 | AY14: =$B$36*V14 -> 1242 | AZ14: =SUM(AY14:AY14)*4/AR14 -> 0.013994366 | BA14: =SUM(AY14:AY14)/V14 -> 0.35 | BB14: =IF(MortgageRate="Discounted",_xlfn.XLOOKUP(L14,'mortgage-rates'!$A:$A,'mortgage-rates'!$E:$E)/100,_xlfn.XLOOKUP(L14,'mortgage-rates'!$A:$A,'mortgage-rates'!$D:$D)/100) -> 0.062 | BC14: =BC13-BF13 -> 214925.44 | BD14: =IF($B$16*12/3-Q14+1>0,-PMT($BB14/4,$B$16*12/3-Q14+1,BC14),0) -> 4467.897 | BE14: =BC14*($BB14/4) -> 3331.3443 | BF14: =BD14-BE14 -> 1136.5527 | BG14: =AT14+AY14+BD14 -> 5709.897 | BH14: =INDEX(cpi!B:B,MATCH($L14,cpi!A:A)) -> 92.6 | BI14: =100*BH14/BH$3 -> 109.45626 | BJ14: =100*AC14/AC$3 -> 99.043605 | BK14: =100*AD14/AD$3 -> 108.80667 | BL14: =BJ14*GlobalPortfolio+BK14*AusPortfolio -> 101.97253 | BM14: =100*AE14/$AE$3 -> 136.67564 | BN14: =100*AR14/AR$3 -> 126.78571 | BO14: =100*AX14/AX$3 -> 120.28862
A15: Renovations, alterations, and additions (% of current home value per year) | B15: 0.0115 | C15: 0.0115 | L15: =DATE(YEAR(L14),MONTH(L14)+3,1) -> 39873 | M15: =AP15 -> 73251.696 | N15: =AX15-BC15 -> 111286.43 | O15: =M15/N15 -> 0.65822668 | P15: =X15/BG15 -> 0.71544858 | Q15: 13 | R15: =EOMONTH(L15,0)-EOMONTH(L15,-3) -> 90 | T15: =IF($B$10="3BR_H", INDEX('3BR_H-processed'!$E:$F,MATCH($L15,'3BR_H-processed'!$B:$B,0),MATCH(Council_Area,'3BR_H-processed'!$E$1:$F$1,0)), INDEX('2BR_F-processed'!$E:$F,MATCH($L15,'2BR_F-processed'!$B:$B,0),MATCH(Council_Area,'2BR_F-processed'!$E$1:$F$1,0))) -> 290 | U15: =IF(MOD(Q15,4)=1,T15,U14) -> 290 | V15: =U15*(R15)/7 -> 3728.5714 | W15: =$B$53/4*BH15/_xlfn.XLOOKUP(Q_end,cpi!A:A,cpi!B:B) -> 127.85073 | X15: =V15+W15 -> 3856.4222 | Y15: =BG15-X15 -> 1533.7935 | Z15: =Y15*$B$47 -> 0 | AA15: {=(Y15+Z15)*eff_invest} -> 1533.7935 | AB15: =AA15*(_xlfn.XLOOKUP(Q_end,cpi!A:A,cpi!B:B)/BH15) -> 2399.3505 | AC15: {=INDEX('msci-indices'!C:C,MATCH($L15,'msci-indices'!$B:$B)-2)} -> 582.01082 | AD15: {=INDEX('msci-indices'!D:D,MATCH($L15,'msci-indices'!$B:$B)-2)} -> 630.6613 | AE15: =AI14+AA15 -> 80253.551 | AF15: {=INDEX('msci-indices'!C:C,MATCH($L15,'msci-indices'!$B:$B)+1)} -> 513.55423 | AG15: {=INDEX('msci-indices'!D:D,MATCH($L15,'msci-indices'!$B:$B)+1)} -> 621.64895 | AH15: =(InvestFees/4)*AE15 -> 50.158469 | AI15: =((AF15/AC15)*GlobalPortfolio+(AG15/AD15)*AusPortfolio)*AE15-AH15 -> 73251.696 | AJ15: =AJ14+AA15 -> 105058.04 | AK15: =AI15-AJ15 -> -31806.343 | AL15: =AJ15*(_xlfn.XLOOKUP(Q_end,cpi!A:A,cpi!B:B)/BH15) -> 164344.85 | AM15: {=SUMPRODUCT($AA$3:AA15,_xlfn.SORTBY($BH$3:BH15,_xlfn.SEQUENCE(ROWS($BH$3:BH15)),-1)/$BH$3)} -> 113430.1 | AN15: =AI15-AM15 -> -40178.405 | AO15: =IF($B$49="Real gains",MAX($B$50*AN15,0),IF($B$49="Discounted nominal gains",MAX($B$50*AK15/2,0),0)) -> 0 | AP15: =AI15-AO15 -> 73251.696 | AR15: =IF($B$10="3BR_H", INDEX('ns-combined'!$C:$D,MATCH($L15,'ns-combined'!$B:$B,0),MATCH(Council_Area,'ns-combined'!$C$1:$D$1,0))*1000, INDEX('s-combined'!$C:$D,MATCH($L15,'s-combined'!$B:$B,0),MATCH(Council_Area,'s-combined'!$C$1:$D$1,0))*1000) -> 353500 | AS15: =AS14+$AS$3 -> 9100 | AT15: 0 | AU15: =SUM($B$28:$B$29)*AR15 -> 7070 | AV15: =AR15*$B$15/4 -> 1016.3125 | AW15: =SUM($AV$3:AV15) -> 12254.688 | AX15: =AR15-AS15-AU15-AW15 -> 325075.31 | AY15: =$B$36*V15 -> 1305 | AZ15: =SUM(AY15:AY15)*4/AR15 -> 0.01476662 | BA15: =SUM(AY15:AY15)/V15 -> 0.35 | BB15: =IF(MortgageRate="Discounted",_xlfn.XLOOKUP(L15,'mortgage-rates'!$A:$A,'mortgage-rates'!$E:$E)/100,_xlfn.XLOOKUP(L15,'mortgage-rates'!$A:$A,'mortgage-rates'!$D:$D)/100) -> 0.0518 | BC15: =BC14-BF14 -> 213788.88 | BD15: =IF($B$16*12/3-Q15+1>0,-PMT($BB15/4,$B$16*12/3-Q15+1,BC15),0) -> 4085.2157 | BE15: =BC15*($BB15/4) -> 2768.566 | BF15: =BD15-BE15 -> 1316.6496 | BG15: =AT15+AY15+BD15 -> 5390.2157 | BH15: =INDEX(cpi!B:B,MATCH($L15,cpi!A:A)) -> 92.5 | BI15: =100*BH15/BH$3 -> 109.33806 | BJ15: =100*AC15/AC$3 -> 77.099819 | BK15: =100*AD15/AD$3 -> 88.457223 | BL15: =BJ15*GlobalPortfolio+BK15*AusPortfolio -> 80.50704 | BM15: =100*AE15/$AE$3 -> 109.82367 | BN15: =100*AR15/AR$3 -> 126.25 | BO15: =100*AX15/AX$3 -> 119.12102
A16: Loan term (years) | B16: 25 | C16: 25 | L16: =DATE(YEAR(L15),MONTH(L15)+3,1) -> 39965 | M16: =AP16 -> 88610.666 | N16: =AX16-BC16 -> 120169.45 | O16: =M16/N16 -> 0.73738095 | P16: =X16/BG16 -> 0.7232661 | Q16: 14 | R16: =EOMONTH(L16,0)-EOMONTH(L16,-3) -> 91 | T16: =IF($B$10="3BR_H", INDEX('3BR_H-processed'!$E:$F,MATCH($L16,'3BR_H-processed'!$B:$B,0),MATCH(Council_Area,'3BR_H-processed'!$E$1:$F$1,0)), INDEX('2BR_F-processed'!$E:$F,MATCH($L16,'2BR_F-processed'!$B:$B,0),MATCH(Council_Area,'2BR_F-processed'!$E$1:$F$1,0))) -> 290 | U16: =IF(MOD(Q16,4)=1,T16,U15) -> 290 | V16: =U16*(R16)/7 -> 3770 | W16: =$B$53/4*BH16/_xlfn.XLOOKUP(Q_end,cpi!A:A,cpi!B:B) -> 128.54181 | X16: =V16+W16 -> 3898.5418 | Y16: =BG16-X16 -> 1491.6483 | Z16: =Y16*$B$47 -> 0 | AA16: {=(Y16+Z16)*eff_invest} -> 1491.6483 | AB16: =AA16*(_xlfn.XLOOKUP(Q_end,cpi!A:A,cpi!B:B)/BH16) -> 2320.8765 | AC16: {=INDEX('msci-indices'!C:C,MATCH($L16,'msci-indices'!$B:$B)-2)} -> 513.55423 | AD16: {=INDEX('msci-indices'!D:D,MATCH($L16,'msci-indices'!$B:$B)-2)} -> 621.64895 | AE16: =AI15+AA16 -> 74743.344 | AF16: {=INDEX('msci-indices'!C:C,MATCH($L16,'msci-indices'!$B:$B)+1)} -> 624.35598 | AG16: {=INDEX('msci-indices'!D:D,MATCH($L16,'msci-indices'!$B:$B)+1)} -> 694.44245 | AH16: =(InvestFees/4)*AE16 -> 46.71459 | AI16: =((AF16/AC16)*GlobalPortfolio+(AG16/AD16)*AusPortfolio)*AE16-AH16 -> 88610.666 | AJ16: =AJ15+AA16 -> 106549.69 | AK16: =AI16-AJ16 -> -17939.021 | AL16: =AJ16*(_xlfn.XLOOKUP(Q_end,cpi!A:A,cpi!B:B)/BH16) -> 165782.15 | AM16: {=SUMPRODUCT($AA$3:AA16,_xlfn.SORTBY($BH$3:BH16,_xlfn.SEQUENCE(ROWS($BH$3:BH16)),-1)/$BH$3)} -> 115590.49 | AN16: =AI16-AM16 -> -26979.826 | AO16: =IF($B$49="Real gains",MAX($B$50*AN16,0),IF($B$49="Discounted nominal gains",MAX($B$50*AK16/2,0),0)) -> 0 | AP16: =AI16-AO16 -> 88610.666 | AR16: =IF($B$10="3BR_H", INDEX('ns-combined'!$C:$D,MATCH($L16,'ns-combined'!$B:$B,0),MATCH(Council_Area,'ns-combined'!$C$1:$D$1,0))*1000, INDEX('s-combined'!$C:$D,MATCH($L16,'s-combined'!$B:$B,0),MATCH(Council_Area,'s-combined'!$C$1:$D$1,0))*1000) -> 363000 | AS16: =AS15+$AS$3 -> 9800 | AT16: 0 | AU16: =SUM($B$28:$B$29)*AR16 -> 7260 | AV16: =AR16*$B$15/4 -> 1043.625 | AW16: =SUM($AV$3:AV16) -> 13298.312 | AX16: =AR16-AS16-AU16-AW16 -> 332641.69 | AY16: =$B$36*V16 -> 1319.5 | AZ16: =SUM(AY16:AY16)*4/AR16 -> 0.014539945 | BA16: =SUM(AY16:AY16)/V16 -> 0.35 | BB16: =IF(MortgageRate="Discounted",_xlfn.XLOOKUP(L16,'mortgage-rates'!$A:$A,'mortgage-rates'!$E:$E)/100,_xlfn.XLOOKUP(L16,'mortgage-rates'!$A:$A,'mortgage-rates'!$D:$D)/100) -> 0.0514 | BC16: =BC15-BF15 -> 212472.23 | BD16: =IF($B$16*12/3-Q16+1>0,-PMT($BB16/4,$B$16*12/3-Q16+1,BC16),0) -> 4070.6901 | BE16: =BC16*($BB16/4) -> 2730.2682 | BF16: =BD16-BE16 -> 1340.4219 | BG16: =AT16+AY16+BD16 -> 5390.1901 | BH16: =INDEX(cpi!B:B,MATCH($L16,cpi!A:A)) -> 93 | BI16: =100*BH16/BH$3 -> 109.92908 | BJ16: =100*AC16/AC$3 -> 68.031276 | BK16: =100*AD16/AD$3 -> 87.193142 | BL16: =BJ16*GlobalPortfolio+BK16*AusPortfolio -> 73.779836 | BM16: =100*AE16/$AE$3 -> 102.28318 | BN16: =100*AR16/AR$3 -> 129.64286 | BO16: =100*AX16/AX$3 -> 121.89365
L17: =DATE(YEAR(L16),MONTH(L16)+3,1) -> 40057 | M17: =AP17 -> 107409.03 | N17: =AX17-BC17 -> 126606.13 | O17: =M17/N17 -> 0.84837154 | P17: =X17/BG17 -> 0.72917 | Q17: 15 | R17: =EOMONTH(L17,0)-EOMONTH(L17,-3) -> 92 | T17: =IF($B$10="3BR_H", INDEX('3BR_H-processed'!$E:$F,MATCH($L17,'3BR_H-processed'!$B:$B,0),MATCH(Council_Area,'3BR_H-processed'!$E$1:$F$1,0)), INDEX('2BR_F-processed'!$E:$F,MATCH($L17,'2BR_F-processed'!$B:$B,0),MATCH(Council_Area,'2BR_F-processed'!$E$1:$F$1,0))) -> 295 | U17: =IF(MOD(Q17,4)=1,T17,U16) -> 290 | V17: =U17*(R17)/7 -> 3811.4286 | W17: =$B$53/4*BH17/_xlfn.XLOOKUP(Q_end,cpi!A:A,cpi!B:B) -> 129.50933 | X17: =V17+W17 -> 3940.9379 | Y17: =BG17-X17 -> 1463.7522 | Z17: =Y17*$B$47 -> 0 | AA17: {=(Y17+Z17)*eff_invest} -> 1463.7522 | AB17: =AA17*(_xlfn.XLOOKUP(Q_end,cpi!A:A,cpi!B:B)/BH17) -> 2260.4584 | AC17: {=INDEX('msci-indices'!C:C,MATCH($L17,'msci-indices'!$B:$B)-2)} -> 624.35598 | AD17: {=INDEX('msci-indices'!D:D,MATCH($L17,'msci-indices'!$B:$B)-2)} -> 694.44245 | AE17: =AI16+AA17 -> 90074.419 | AF17: {=INDEX('msci-indices'!C:C,MATCH($L17,'msci-indices'!$B:$B)+1)} -> 736.86333 | AG17: {=INDEX('msci-indices'!D:D,MATCH($L17,'msci-indices'!$B:$B)+1)} -> 849.38296 | AH17: =(InvestFees/4)*AE17 -> 56.296512 | AI17: =((AF17/AC17)*GlobalPortfolio+(AG17/AD17)*AusPortfolio)*AE17-AH17 -> 107409.03 | AJ17: =AJ16+AA17 -> 108013.44 | AK17: =AI17-AJ17 -> -604.40635 | AL17: =AJ17*(_xlfn.XLOOKUP(Q_end,cpi!A:A,cpi!B:B)/BH17) -> 166804.11 | AM17: {=SUMPRODUCT($AA$3:AA17,_xlfn.SORTBY($BH$3:BH17,_xlfn.SEQUENCE(ROWS($BH$3:BH17)),-1)/$BH$3)} -> 117907.86 | AN17: =AI17-AM17 -> -10498.822 | AO17: =IF($B$49="Real gains",MAX($B$50*AN17,0),IF($B$49="Discounted nominal gains",MAX($B$50*AK17/2,0),0)) -> 0 | AP17: =AI17-AO17 -> 107409.03 | AR17: =IF($B$10="3BR_H", INDEX('ns-combined'!$C:$D,MATCH($L17,'ns-combined'!$B:$B,0),MATCH(Council_Area,'ns-combined'!$C$1:$D$1,0))*1000, INDEX('s-combined'!$C:$D,MATCH($L17,'s-combined'!$B:$B,0),MATCH(Council_Area,'s-combined'!$C$1:$D$1,0))*1000) -> 370000 | AS17: =AS16+$AS$3 -> 10500 | AT17: 0 | AU17: =SUM($B$28:$B$29)*AR17 -> 7400 | AV17: =AR17*$B$15/4 -> 1063.75 | AW17: =SUM($AV$3:AV17) -> 14362.062 | AX17: =AR17-AS17-AU17-AW17 -> 337737.94 | AY17: =$B$36*V17 -> 1334 | AZ17: =SUM(AY17:AY17)*4/AR17 -> 0.014421622 | BA17: =SUM(AY17:AY17)/V17 -> 0.35 | BB17: =IF(MortgageRate="Discounted",_xlfn.XLOOKUP(L17,'mortgage-rates'!$A:$A,'mortgage-rates'!$E:$E)/100,_xlfn.XLOOKUP(L17,'mortgage-rates'!$A:$A,'mortgage-rates'!$D:$D)/100) -> 0.0514 | BC17: =BC16-BF16 -> 211131.81 | BD17: =IF($B$16*12/3-Q17+1>0,-PMT($BB17/4,$B$16*12/3-Q17+1,BC17),0) -> 4070.6901 | BE17: =BC17*($BB17/4) -> 2713.0438 | BF17: =BD17-BE17 -> 1357.6463 | BG17: =AT17+AY17+BD17 -> 5404.6901 | BH17: =INDEX(cpi!B:B,MATCH($L17,cpi!A:A)) -> 93.7 | BI17: =100*BH17/BH$3 -> 110.7565 | BJ17: =100*AC17/AC$3 -> 82.709345 | BK17: =100*AD17/AD$3 -> 97.403235 | BL17: =BJ17*GlobalPortfolio+BK17*AusPortfolio -> 87.117512 | BM17: =100*AE17/$AE$3 -> 123.26312 | BN17: =100*AR17/AR$3 -> 132.14286 | BO17: =100*AX17/AX$3 -> 123.76113
A18: Mortgage | L18: =DATE(YEAR(L17),MONTH(L17)+3,1) -> 40148 | M18: =AP18 -> 113227.84 | N18: =AX18-BC18 -> 154341.22 | O18: =M18/N18 -> 0.73362019 | P18: =X18/BG18 -> 0.68952855 | Q18: 16 | R18: =EOMONTH(L18,0)-EOMONTH(L18,-3) -> 92 | T18: =IF($B$10="3BR_H", INDEX('3BR_H-processed'!$E:$F,MATCH($L18,'3BR_H-processed'!$B:$B,0),MATCH(Council_Area,'3BR_H-processed'!$E$1:$F$1,0)), INDEX('2BR_F-processed'!$E:$F,MATCH($L18,'2BR_F-processed'!$B:$B,0),MATCH(Council_Area,'2BR_F-processed'!$E$1:$F$1,0))) -> 300 | U18: =IF(MOD(Q18,4)=1,T18,U17) -> 290 | V18: =U18*(R18)/7 -> 3811.4286 | W18: =$B$53/4*BH18/_xlfn.XLOOKUP(Q_end,cpi!A:A,cpi!B:B) -> 130.61507 | X18: =V18+W18 -> 3942.0436 | Y18: =BG18-X18 -> 1774.9693 | Z18: =Y18*$B$47 -> 0 | AA18: {=(Y18+Z18)*eff_invest} -> 1774.9693 | AB18: =AA18*(_xlfn.XLOOKUP(Q_end,cpi!A:A,cpi!B:B)/BH18) -> 2717.8631 | AC18: {=INDEX('msci-indices'!C:C,MATCH($L18,'msci-indices'!$B:$B)-2)} -> 736.86333 | AD18: {=INDEX('msci-indices'!D:D,MATCH($L18,'msci-indices'!$B:$B)-2)} -> 849.38296 | AE18: =AI17+AA18 -> 109184 | AF18: {=INDEX('msci-indices'!C:C,MATCH($L18,'msci-indices'!$B:$B)+1)} -> 765.74116 | AG18: {=INDEX('msci-indices'!D:D,MATCH($L18,'msci-indices'!$B:$B)+1)} -> 878.3433 | AH18: =(InvestFees/4)*AE18 -> 68.240002 | AI18: =((AF18/AC18)*GlobalPortfolio+(AG18/AD18)*AusPortfolio)*AE18-AH18 -> 113227.84 | AJ18: =AJ17+AA18 -> 109788.41 | AK18: =AI18-AJ18 -> 3439.4277 | AL18: =AJ18*(_xlfn.XLOOKUP(Q_end,cpi!A:A,cpi!B:B)/BH18) -> 168109.87 | AM18: {=SUMPRODUCT($AA$3:AA18,_xlfn.SORTBY($BH$3:BH18,_xlfn.SEQUENCE(ROWS($BH$3:BH18)),-1)/$BH$3)} -> 120647.83 | AN18: =AI18-AM18 -> -7419.9938 | AO18: =IF($B$49="Real gains",MAX($B$50*AN18,0),IF($B$49="Discounted nominal gains",MAX($B$50*AK18/2,0),0)) -> 0 | AP18: =AI18-AO18 -> 113227.84 | AR18: =IF($B$10="3BR_H", INDEX('ns-combined'!$C:$D,MATCH($L18,'ns-combined'!$B:$B,0),MATCH(Council_Area,'ns-combined'!$C$1:$D$1,0))*1000, INDEX('s-combined'!$C:$D,MATCH($L18,'s-combined'!$B:$B,0),MATCH(Council_Area,'s-combined'!$C$1:$D$1,0))*1000) -> 398800 | AS18: =AS17+$AS$3 -> 11200 | AT18: 0 | AU18: =SUM($B$28:$B$29)*AR18 -> 7976 | AV18: =AR18*$B$15/4 -> 1146.55 | AW18: =SUM($AV$3:AV18) -> 15508.612 | AX18: =AR18-AS18-AU18-AW18 -> 364115.39 | AY18: =$B$36*V18 -> 1334 | AZ18: =SUM(AY18:AY18)*4/AR18 -> 0.01338014 | BA18: =SUM(AY18:AY18)/V18 -> 0.35 | BB18: =IF(MortgageRate="Discounted",_xlfn.XLOOKUP(L18,'mortgage-rates'!$A:$A,'mortgage-rates'!$E:$E)/100,_xlfn.XLOOKUP(L18,'mortgage-rates'!$A:$A,'mortgage-rates'!$D:$D)/100) -> 0.06 | BC18: =BC17-BF17 -> 209774.17 | BD18: =IF($B$16*12/3-Q18+1>0,-PMT($BB18/4,$B$16*12/3-Q18+1,BC18),0) -> 4383.013 | BE18: =BC18*($BB18/4) -> 3146.6125 | BF18: =BD18-BE18 -> 1236.4005 | BG18: =AT18+AY18+BD18 -> 5717.013 | BH18: =INDEX(cpi!B:B,MATCH($L18,cpi!A:A)) -> 94.5 | BI18: =100*BH18/BH$3 -> 111.70213 | BJ18: =100*AC18/AC$3 -> 97.613357 | BK18: =100*AD18/AD$3 -> 119.13536 | BL18: =BJ18*GlobalPortfolio+BK18*AusPortfolio -> 104.06996 | BM18: =100*AE18/$AE$3 -> 149.4138 | BN18: =100*AR18/AR$3 -> 142.42857 | BO18: =100*AX18/AX$3 -> 133.42692
A19: Mortgage rates (Standard/Discounted) | B19: Discounted | C19: Discounted | L19: =DATE(YEAR(L18),MONTH(L18)+3,1) -> 40238 | M19: =AP19 -> 118545.3 | N19: =AX19-BC19 -> 156857.87 | O19: =M19/N19 -> 0.75574973 | P19: =X19/BG19 -> 0.70139412 | Q19: 17 | R19: =EOMONTH(L19,0)-EOMONTH(L19,-3) -> 90 | T19: =IF($B$10="3BR_H", INDEX('3BR_H-processed'!$E:$F,MATCH($L19,'3BR_H-processed'!$B:$B,0),MATCH(Council_Area,'3BR_H-processed'!$E$1:$F$1,0)), INDEX('2BR_F-processed'!$E:$F,MATCH($L19,'2BR_F-processed'!$B:$B,0),MATCH(Council_Area,'2BR_F-processed'!$E$1:$F$1,0))) -> 310 | U19: =IF(MOD(Q19,4)=1,T19,U18) -> 310 | V19: =U19*(R19)/7 -> 3985.7143 | W19: =$B$53/4*BH19/_xlfn.XLOOKUP(Q_end,cpi!A:A,cpi!B:B) -> 131.58258 | X19: =V19+W19 -> 4117.2969 | Y19: =BG19-X19 -> 1752.8647 | Z19: =Y19*$B$47 -> 0 | AA19: {=(Y19+Z19)*eff_invest} -> 1752.8647 | AB19: =AA19*(_xlfn.XLOOKUP(Q_end,cpi!A:A,cpi!B:B)/BH19) -> 2664.2808 | AC19: {=INDEX('msci-indices'!C:C,MATCH($L19,'msci-indices'!$B:$B)-2)} -> 765.74116 | AD19: {=INDEX('msci-indices'!D:D,MATCH($L19,'msci-indices'!$B:$B)-2)} -> 878.3433 | AE19: =AI18+AA19 -> 114980.7 | AF19: {=INDEX('msci-indices'!C:C,MATCH($L19,'msci-indices'!$B:$B)+1)} -> 794.63718 | AG19: {=INDEX('msci-indices'!D:D,MATCH($L19,'msci-indices'!$B:$B)+1)} -> 893.60148 | AH19: =(InvestFees/4)*AE19 -> 71.862938 | AI19: =((AF19/AC19)*GlobalPortfolio+(AG19/AD19)*AusPortfolio)*AE19-AH19 -> 118545.3 | AJ19: =AJ18+AA19 -> 111541.27 | AK19: =AI19-AJ19 -> 7004.0214 | AL19: =AJ19*(_xlfn.XLOOKUP(Q_end,cpi!A:A,cpi!B:B)/BH19) -> 169538.05 | AM19: {=SUMPRODUCT($AA$3:AA19,_xlfn.SORTBY($BH$3:BH19,_xlfn.SEQUENCE(ROWS($BH$3:BH19)),-1)/$BH$3)} -> 123303.08 | AN19: =AI19-AM19 -> -4757.7846 | AO19: =IF($B$49="Real gains",MAX($B$50*AN19,0),IF($B$49="Discounted nominal gains",MAX($B$50*AK19/2,0),0)) -> 0 | AP19: =AI19-AO19 -> 118545.3 | AR19: =IF($B$10="3BR_H", INDEX('ns-combined'!$C:$D,MATCH($L19,'ns-combined'!$B:$B,0),MATCH(Council_Area,'ns-combined'!$C$1:$D$1,0))*1000, INDEX('s-combined'!$C:$D,MATCH($L19,'s-combined'!$B:$B,0),MATCH(Council_Area,'s-combined'!$C$1:$D$1,0))*1000) -> 402000 | AS19: =AS18+$AS$3 -> 11900 | AT19: 0 | AU19: =SUM($B$28:$B$29)*AR19 -> 8040 | AV19: =AR19*$B$15/4 -> 1155.75 | AW19: =SUM($AV$3:AV19) -> 16664.362 | AX19: =AR19-AS19-AU19-AW19 -> 365395.64 | AY19: =$B$36*V19 -> 1395 | AZ19: =SUM(AY19:AY19)*4/AR19 -> 0.013880597 | BA19: =SUM(AY19:AY19)/V19 -> 0.35 | BB19: =IF(MortgageRate="Discounted",_xlfn.XLOOKUP(L19,'mortgage-rates'!$A:$A,'mortgage-rates'!$E:$E)/100,_xlfn.XLOOKUP(L19,'mortgage-rates'!$A:$A,'mortgage-rates'!$D:$D)/100) -> 0.0625 | BC19: =BC18-BF18 -> 208537.77 | BD19: =IF($B$16*12/3-Q19+1>0,-PMT($BB19/4,$B$16*12/3-Q19+1,BC19),0) -> 4475.1616 | BE19: =BC19*($BB19/4) -> 3258.4026 | BF19: =BD19-BE19 -> 1216.759 | BG19: =AT19+AY19+BD19 -> 5870.1616 | BH19: =INDEX(cpi!B:B,MATCH($L19,cpi!A:A)) -> 95.2 | BI19: =100*BH19/BH$3 -> 112.52955 | BJ19: =100*AC19/AC$3 -> 101.43885 | BK19: =100*AD19/AD$3 -> 123.19736 | BL19: =BJ19*GlobalPortfolio+BK19*AusPortfolio -> 107.9664 | BM19: =100*AE19/$AE$3 -> 157.34634 | BN19: =100*AR19/AR$3 -> 143.57143 | BO19: =100*AX19/AX$3 -> 133.89605
A20: Deposit (% of home purchase price) | B20: 0.2 | C20: 0.2 | L20: =DATE(YEAR(L19),MONTH(L19)+3,1) -> 40330 | M20: =AP20 -> 105611.46 | N20: =AX20-BC20 -> 164035.88 | O20: =M20/N20 -> 0.64383148 | P20: =X20/BG20 -> 0.68560854 | Q20: 18 | R20: =EOMONTH(L20,0)-EOMONTH(L20,-3) -> 91 | T20: =IF($B$10="3BR_H", INDEX('3BR_H-processed'!$E:$F,MATCH($L20,'3BR_H-processed'!$B:$B,0),MATCH(Council_Area,'3BR_H-processed'!$E$1:$F$1,0)), INDEX('2BR_F-processed'!$E:$F,MATCH($L20,'2BR_F-processed'!$B:$B,0),MATCH(Council_Area,'2BR_F-processed'!$E$1:$F$1,0))) -> 300 | U20: =IF(MOD(Q20,4)=1,T20,U19) -> 310 | V20: =U20*(R20)/7 -> 4030 | W20: =$B$53/4*BH20/_xlfn.XLOOKUP(Q_end,cpi!A:A,cpi!B:B) -> 132.41189 | X20: =V20+W20 -> 4162.4119 | Y20: =BG20-X20 -> 1908.7084 | Z20: =Y20*$B$47 -> 0 | AA20: {=(Y20+Z20)*eff_invest} -> 1908.7084 | AB20: =AA20*(_xlfn.XLOOKUP(Q_end,cpi!A:A,cpi!B:B)/BH20) -> 2882.9865 | AC20: {=INDEX('msci-indices'!C:C,MATCH($L20,'msci-indices'!$B:$B)-2)} -> 794.63718 | AD20: {=INDEX('msci-indices'!D:D,MATCH($L20,'msci-indices'!$B:$B)-2)} -> 893.60148 | AE20: =AI19+AA20 -> 120454 | AF20: {=INDEX('msci-indices'!C:C,MATCH($L20,'msci-indices'!$B:$B)+1)} -> 696.18018 | AG20: {=INDEX('msci-indices'!D:D,MATCH($L20,'msci-indices'!$B:$B)+1)} -> 786.77037 | AH20: =(InvestFees/4)*AE20 -> 75.283752 | AI20: =((AF20/AC20)*GlobalPortfolio+(AG20/AD20)*AusPortfolio)*AE20-AH20 -> 105611.46 | AJ20: =AJ19+AA20 -> 113449.98 | AK20: =AI20-AJ20 -> -7838.5174 | AL20: =AJ20*(_xlfn.XLOOKUP(Q_end,cpi!A:A,cpi!B:B)/BH20) -> 171359.21 | AM20: {=SUMPRODUCT($AA$3:AA20,_xlfn.SORTBY($BH$3:BH20,_xlfn.SEQUENCE(ROWS($BH$3:BH20)),-1)/$BH$3)} -> 126044.81 | AN20: =AI20-AM20 -> -20433.35 | AO20: =IF($B$49="Real gains",MAX($B$50*AN20,0),IF($B$49="Discounted nominal gains",MAX($B$50*AK20/2,0),0)) -> 0 | AP20: =AI20-AO20 -> 105611.46 | AR20: =IF($B$10="3BR_H", INDEX('ns-combined'!$C:$D,MATCH($L20,'ns-combined'!$B:$B,0),MATCH(Council_Area,'ns-combined'!$C$1:$D$1,0))*1000, INDEX('s-combined'!$C:$D,MATCH($L20,'s-combined'!$B:$B,0),MATCH(Council_Area,'s-combined'!$C$1:$D$1,0))*1000) -> 410000 | AS20: =AS19+$AS$3 -> 12600 | AT20: 0 | AU20: =SUM($B$28:$B$29)*AR20 -> 8200 | AV20: =AR20*$B$15/4 -> 1178.75 | AW20: =SUM($AV$3:AV20) -> 17843.112 | AX20: =AR20-AS20-AU20-AW20 -> 371356.89 | AY20: =$B$36*V20 -> 1410.5 | AZ20: =SUM(AY20:AY20)*4/AR20 -> 0.013760976 | BA20: =SUM(AY20:AY20)/V20 -> 0.35 | BB20: =IF(MortgageRate="Discounted",_xlfn.XLOOKUP(L20,'mortgage-rates'!$A:$A,'mortgage-rates'!$E:$E)/100,_xlfn.XLOOKUP(L20,'mortgage-rates'!$A:$A,'mortgage-rates'!$D:$D)/100) -> 0.0675 | BC20: =BC19-BF19 -> 207321.01 | BD20: =IF($B$16*12/3-Q20+1>0,-PMT($BB20/4,$B$16*12/3-Q20+1,BC20),0) -> 4660.6203 | BE20: =BC20*($BB20/4) -> 3498.542 | BF20: =BD20-BE20 -> 1162.0783 | BG20: =AT20+AY20+BD20 -> 6071.1203 | BH20: =INDEX(cpi!B:B,MATCH($L20,cpi!A:A)) -> 95.8 | BI20: =100*BH20/BH$3 -> 113.23877 | BJ20: =100*AC20/AC$3 -> 105.26674 | BK20: =100*AD20/AD$3 -> 125.33749 | BL20: =BJ20*GlobalPortfolio+BK20*AusPortfolio -> 111.28797 | BM20: =100*AE20/$AE$3 -> 164.83633 | BN20: =100*AR20/AR$3 -> 146.42857 | BO20: =100*AX20/AX$3 -> 136.0805
A21: Lenders' mortgage insurance (% of home purchase price) | B21: 0 | C21: 0 | L21: =DATE(YEAR(L20),MONTH(L20)+3,1) -> 40422 | M21: =AP21 -> 120708.25 | N21: =AX21-BC21 -> 153547.96 | O21: =M21/N21 -> 0.78612738 | P21: =X21/BG21 -> 0.69127475 | Q21: 19 | R21: =EOMONTH(L21,0)-EOMONTH(L21,-3) -> 92 | T21: =IF($B$10="3BR_H", INDEX('3BR_H-processed'!$E:$F,MATCH($L21,'3BR_H-processed'!$B:$B,0),MATCH(Council_Area,'3BR_H-processed'!$E$1:$F$1,0)), INDEX('2BR_F-processed'!$E:$F,MATCH($L21,'2BR_F-processed'!$B:$B,0),MATCH(Council_Area,'2BR_F-processed'!$E$1:$F$1,0))) -> 310 | U21: =IF(MOD(Q21,4)=1,T21,U20) -> 310 | V21: =U21*(R21)/7 -> 4074.2857 | W21: =$B$53/4*BH21/_xlfn.XLOOKUP(Q_end,cpi!A:A,cpi!B:B) -> 133.24119 | X21: =V21+W21 -> 4207.5269 | Y21: =BG21-X21 -> 1879.0934 | Z21: =Y21*$B$47 -> 0 | AA21: {=(Y21+Z21)*eff_invest} -> 1879.0934 | AB21: =AA21*(_xlfn.XLOOKUP(Q_end,cpi!A:A,cpi!B:B)/BH21) -> 2820.5893 | AC21: {=INDEX('msci-indices'!C:C,MATCH($L21,'msci-indices'!$B:$B)-2)} -> 696.18018 | AD21: {=INDEX('msci-indices'!D:D,MATCH($L21,'msci-indices'!$B:$B)-2)} -> 786.77037 | AE21: =AI20+AA21 -> 107490.56 | AF21: {=INDEX('msci-indices'!C:C,MATCH($L21,'msci-indices'!$B:$B)+1)} -> 792.86986 | AG21: {=INDEX('msci-indices'!D:D,MATCH($L21,'msci-indices'!$B:$B)+1)} -> 855.9299 | AH21: =(InvestFees/4)*AE21 -> 67.181599 | AI21: =((AF21/AC21)*GlobalPortfolio+(AG21/AD21)*AusPortfolio)*AE21-AH21 -> 120708.25 | AJ21: =AJ20+AA21 -> 115329.08 | AK21: =AI21-AJ21 -> 5379.1793 | AL21: =AJ21*(_xlfn.XLOOKUP(Q_end,cpi!A:A,cpi!B:B)/BH21) -> 173113.25 | AM21: {=SUMPRODUCT($AA$3:AA21,_xlfn.SORTBY($BH$3:BH21,_xlfn.SEQUENCE(ROWS($BH$3:BH21)),-1)/$BH$3)} -> 128764.23 | AN21: =AI21-AM21 -> -8055.9789 | AO21: =IF($B$49="Real gains",MAX($B$50*AN21,0),IF($B$49="Discounted nominal gains",MAX($B$50*AK21/2,0),0)) -> 0 | AP21: =AI21-AO21 -> 120708.25 | AR21: =IF($B$10="3BR_H", INDEX('ns-combined'!$C:$D,MATCH($L21,'ns-combined'!$B:$B,0),MATCH(Council_Area,'ns-combined'!$C$1:$D$1,0))*1000, INDEX('s-combined'!$C:$D,MATCH($L21,'s-combined'!$B:$B,0),MATCH(Council_Area,'s-combined'!$C$1:$D$1,0))*1000) -> 400000 | AS21: =AS20+$AS$3 -> 13300 | AT21: 0 | AU21: =SUM($B$28:$B$29)*AR21 -> 8000 | AV21: =AR21*$B$15/4 -> 1150 | AW21: =SUM($AV$3:AV21) -> 18993.112 | AX21: =AR21-AS21-AU21-AW21 -> 359706.89 | AY21: =$B$36*V21 -> 1426 | AZ21: =SUM(AY21:AY21)*4/AR21 -> 0.01426 | BA21: =SUM(AY21:AY21)/V21 -> 0.35 | BB21: =IF(MortgageRate="Discounted",_xlfn.XLOOKUP(L21,'mortgage-rates'!$A:$A,'mortgage-rates'!$E:$E)/100,_xlfn.XLOOKUP(L21,'mortgage-rates'!$A:$A,'mortgage-rates'!$D:$D)/100) -> 0.0675 | BC21: =BC20-BF20 -> 206158.93 | BD21: =IF($B$16*12/3-Q21+1>0,-PMT($BB21/4,$B$16*12/3-Q21+1,BC21),0) -> 4660.6203 | BE21: =BC21*($BB21/4) -> 3478.9319 | BF21: =BD21-BE21 -> 1181.6884 | BG21: =AT21+AY21+BD21 -> 6086.6203 | BH21: =INDEX(cpi!B:B,MATCH($L21,cpi!A:A)) -> 96.4 | BI21: =100*BH21/BH$3 -> 113.94799 | BJ21: =100*AC21/AC$3 -> 92.224001 | BK21: =100*AD21/AD$3 -> 110.35325 | BL21: =BJ21*GlobalPortfolio+BK21*AusPortfolio -> 97.662775 | BM21: =100*AE21/$AE$3 -> 147.09639 | BN21: =100*AR21/AR$3 -> 142.85714 | BO21: =100*AX21/AX$3 -> 131.81146
L22: =DATE(YEAR(L21),MONTH(L21)+3,1) -> 40513 | M22: =AP22 -> 132623.26 | N22: =AX22-BC22 -> 162650.9 | O22: =M22/N22 -> 0.81538594 | P22: =X22/BG22 -> 0.67496178 | Q22: 20 | R22: =EOMONTH(L22,0)-EOMONTH(L22,-3) -> 92 | T22: =IF($B$10="3BR_H", INDEX('3BR_H-processed'!$E:$F,MATCH($L22,'3BR_H-processed'!$B:$B,0),MATCH(Council_Area,'3BR_H-processed'!$E$1:$F$1,0)), INDEX('2BR_F-processed'!$E:$F,MATCH($L22,'2BR_F-processed'!$B:$B,0),MATCH(Council_Area,'2BR_F-processed'!$E$1:$F$1,0))) -> 312.5 | U22: =IF(MOD(Q22,4)=1,T22,U21) -> 310 | V22: =U22*(R22)/7 -> 4074.2857 | W22: =$B$53/4*BH22/_xlfn.XLOOKUP(Q_end,cpi!A:A,cpi!B:B) -> 134.07049 | X22: =V22+W22 -> 4208.3562 | Y22: =BG22-X22 -> 2026.5986 | Z22: =Y22*$B$47 -> 0 | AA22: {=(Y22+Z22)*eff_invest} -> 2026.5986 | AB22: =AA22*(_xlfn.XLOOKUP(Q_end,cpi!A:A,cpi!B:B)/BH22) -> 3023.1837 | AC22: {=INDEX('msci-indices'!C:C,MATCH($L22,'msci-indices'!$B:$B)-2)} -> 792.86986 | AD22: {=INDEX('msci-indices'!D:D,MATCH($L22,'msci-indices'!$B:$B)-2)} -> 855.9299 | AE22: =AI21+AA22 -> 122734.85 | AF22: {=INDEX('msci-indices'!C:C,MATCH($L22,'msci-indices'!$B:$B)+1)} -> 869.42368 | AG22: {=INDEX('msci-indices'!D:D,MATCH($L22,'msci-indices'!$B:$B)+1)} -> 894.74694 | AH22: =(InvestFees/4)*AE22 -> 76.709283 | AI22: =((AF22/AC22)*GlobalPortfolio+(AG22/AD22)*AusPortfolio)*AE22-AH22 -> 132623.26 | AJ22: =AJ21+AA22 -> 117355.67 | AK22: =AI22-AJ22 -> 15267.581 | AL22: =AJ22*(_xlfn.XLOOKUP(Q_end,cpi!A:A,cpi!B:B)/BH22) -> 175065.63 | AM22: {=SUMPRODUCT($AA$3:AA22,_xlfn.SORTBY($BH$3:BH22,_xlfn.SEQUENCE(ROWS($BH$3:BH22)),-1)/$BH$3)} -> 131630.52 | AN22: =AI22-AM22 -> 992.7379 | AO22: =IF($B$49="Real gains",MAX($B$50*AN22,0),IF($B$49="Discounted nominal gains",MAX($B$50*AK22/2,0),0)) -> 0 | AP22: =AI22-AO22 -> 132623.26 | AR22: =IF($B$10="3BR_H", INDEX('ns-combined'!$C:$D,MATCH($L22,'ns-combined'!$B:$B,0),MATCH(Council_Area,'ns-combined'!$C$1:$D$1,0))*1000, INDEX('s-combined'!$C:$D,MATCH($L22,'s-combined'!$B:$B,0),MATCH(Council_Area,'s-combined'!$C$1:$D$1,0))*1000) -> 410000 | AS22: =AS21+$AS$3 -> 14000 | AT22: 0 | AU22: =SUM($B$28:$B$29)*AR22 -> 8200 | AV22: =AR22*$B$15/4 -> 1178.75 | AW22: =SUM($AV$3:AV22) -> 20171.862 | AX22: =AR22-AS22-AU22-AW22 -> 367628.14 | AY22: =$B$36*V22 -> 1426 | AZ22: =SUM(AY22:AY22)*4/AR22 -> 0.013912195 | BA22: =SUM(AY22:AY22)/V22 -> 0.35 | BB22: =IF(MortgageRate="Discounted",_xlfn.XLOOKUP(L22,'mortgage-rates'!$A:$A,'mortgage-rates'!$E:$E)/100,_xlfn.XLOOKUP(L22,'mortgage-rates'!$A:$A,'mortgage-rates'!$D:$D)/100) -> 0.0715 | BC22: =BC21-BF21 -> 204977.24 | BD22: =IF($B$16*12/3-Q22+1>0,-PMT($BB22/4,$B$16*12/3-Q22+1,BC22),0) -> 4808.9548 | BE22: =BC22*($BB22/4) -> 3663.9682 | BF22: =BD22-BE22 -> 1144.9867 | BG22: =AT22+AY22+BD22 -> 6234.9548 | BH22: =INDEX(cpi!B:B,MATCH($L22,cpi!A:A)) -> 97 | BI22: =100*BH22/BH$3 -> 114.65721 | BJ22: =100*AC22/AC$3 -> 105.03262 | BK22: =100*AD22/AD$3 -> 120.05364 | BL22: =BJ22*GlobalPortfolio+BK22*AusPortfolio -> 109.53893 | BM22: =100*AE22/$AE$3 -> 167.95758 | BN22: =100*AR22/AR$3 -> 146.42857 | BO22: =100*AX22/AX$3 -> 134.71413
A23: Home transaction costs (% of home value) | L23: =DATE(YEAR(L22),MONTH(L22)+3,1) -> 40603 | M23: =AP23 -> 140574.8 | N23: =AX23-BC23 -> 152145.88 | O23: =M23/N23 -> 0.92394745 | P23: =X23/BG23 -> 0.68177533 | Q23: 21 | R23: =EOMONTH(L23,0)-EOMONTH(L23,-3) -> 90 | T23: =IF($B$10="3BR_H", INDEX('3BR_H-processed'!$E:$F,MATCH($L23,'3BR_H-processed'!$B:$B,0),MATCH(Council_Area,'3BR_H-processed'!$E$1:$F$1,0)), INDEX('2BR_F-processed'!$E:$F,MATCH($L23,'2BR_F-processed'!$B:$B,0),MATCH(Council_Area,'2BR_F-processed'!$E$1:$F$1,0))) -> 320 | U23: =IF(MOD(Q23,4)=1,T23,U22) -> 320 | V23: =U23*(R23)/7 -> 4114.2857 | W23: =$B$53/4*BH23/_xlfn.XLOOKUP(Q_end,cpi!A:A,cpi!B:B) -> 136.00553 | X23: =V23+W23 -> 4250.2912 | Y23: =BG23-X23 -> 1983.8611 | Z23: =Y23*$B$47 -> 0 | AA23: {=(Y23+Z23)*eff_invest} -> 1983.8611 | AB23: =AA23*(_xlfn.XLOOKUP(Q_end,cpi!A:A,cpi!B:B)/BH23) -> 2917.3242 | AC23: {=INDEX('msci-indices'!C:C,MATCH($L23,'msci-indices'!$B:$B)-2)} -> 869.42368 | AD23: {=INDEX('msci-indices'!D:D,MATCH($L23,'msci-indices'!$B:$B)-2)} -> 894.74694 | AE23: =AI22+AA23 -> 134607.12 | AF23: {=INDEX('msci-indices'!C:C,MATCH($L23,'msci-indices'!$B:$B)+1)} -> 912.83804 | AG23: {=INDEX('msci-indices'!D:D,MATCH($L23,'msci-indices'!$B:$B)+1)} -> 924.58629 | AH23: =(InvestFees/4)*AE23 -> 84.129448 | AI23: =((AF23/AC23)*GlobalPortfolio+(AG23/AD23)*AusPortfolio)*AE23-AH23 -> 140574.8 | AJ23: =AJ22+AA23 -> 119339.54 | AK23: =AI23-AJ23 -> 21235.266 | AL23: =AJ23*(_xlfn.XLOOKUP(Q_end,cpi!A:A,cpi!B:B)/BH23) -> 175492.18 | AM23: {=SUMPRODUCT($AA$3:AA23,_xlfn.SORTBY($BH$3:BH23,_xlfn.SEQUENCE(ROWS($BH$3:BH23)),-1)/$BH$3)} -> 135148.24 | AN23: =AI23-AM23 -> 5426.5588 | AO23: =IF($B$49="Real gains",MAX($B$50*AN23,0),IF($B$49="Discounted nominal gains",MAX($B$50*AK23/2,0),0)) -> 0 | AP23: =AI23-AO23 -> 140574.8 | AR23: =IF($B$10="3BR_H", INDEX('ns-combined'!$C:$D,MATCH($L23,'ns-combined'!$B:$B,0),MATCH(Council_Area,'ns-combined'!$C$1:$D$1,0))*1000, INDEX('s-combined'!$C:$D,MATCH($L23,'s-combined'!$B:$B,0),MATCH(Council_Area,'s-combined'!$C$1:$D$1,0))*1000) -> 400000 | AS23: =AS22+$AS$3 -> 14700 | AT23: 0 | AU23: =SUM($B$28:$B$29)*AR23 -> 8000 | AV23: =AR23*$B$15/4 -> 1150 | AW23: =SUM($AV$3:AV23) -> 21321.862 | AX23: =AR23-AS23-AU23-AW23 -> 355978.14 | AY23: =$B$36*V23 -> 1440 | AZ23: =SUM(AY23:AY23)*4/AR23 -> 0.0144 | BA23: =SUM(AY23:AY23)/V23 -> 0.35 | BB23: =IF(MortgageRate="Discounted",_xlfn.XLOOKUP(L23,'mortgage-rates'!$A:$A,'mortgage-rates'!$E:$E)/100,_xlfn.XLOOKUP(L23,'mortgage-rates'!$A:$A,'mortgage-rates'!$D:$D)/100) -> 0.0711 | BC23: =BC22-BF22 -> 203832.25 | BD23: =IF($B$16*12/3-Q23+1>0,-PMT($BB23/4,$B$16*12/3-Q23+1,BC23),0) -> 4794.1523 | BE23: =BC23*($BB23/4) -> 3623.1183 | BF23: =BD23-BE23 -> 1171.034 | BG23: =AT23+AY23+BD23 -> 6234.1523 | BH23: =INDEX(cpi!B:B,MATCH($L23,cpi!A:A)) -> 98.4 | BI23: =100*BH23/BH$3 -> 116.31206 | BJ23: =100*AC23/AC$3 -> 115.17382 | BK23: =100*AD23/AD$3 -> 125.49816 | BL23: =BJ23*GlobalPortfolio+BK23*AusPortfolio -> 118.27112 | BM23: =100*AE23/$AE$3 -> 184.20428 | BN23: =100*AR23/AR$3 -> 142.85714 | BO23: =100*AX23/AX$3 -> 130.44509
A24: When buying the house (cashflow costs) | L24: =DATE(YEAR(L23),MONTH(L23)+3,1) -> 40695 | M24: =AP24 -> 140866.55 | N24: =AX24-BC24 -> 146581.29 | O24: =M24/N24 -> 0.96101314 | P24: =X24/BG24 -> 0.69037317 | Q24: 22 | R24: =EOMONTH(L24,0)-EOMONTH(L24,-3) -> 91 | T24: =IF($B$10="3BR_H", INDEX('3BR_H-processed'!$E:$F,MATCH($L24,'3BR_H-processed'!$B:$B,0),MATCH(Council_Area,'3BR_H-processed'!$E$1:$F$1,0)), INDEX('2BR_F-processed'!$E:$F,MATCH($L24,'2BR_F-processed'!$B:$B,0),MATCH(Council_Area,'2BR_F-processed'!$E$1:$F$1,0))) -> 320 | U24: =IF(MOD(Q24,4)=1,T24,U23) -> 320 | V24: =U24*(R24)/7 -> 4160 | W24: =$B$53/4*BH24/_xlfn.XLOOKUP(Q_end,cpi!A:A,cpi!B:B) -> 137.24948 | X24: =V24+W24 -> 4297.2495 | Y24: =BG24-X24 -> 1927.2819 | Z24: =Y24*$B$47 -> 0 | AA24: {=(Y24+Z24)*eff_invest} -> 1927.2819 | AB24: =AA24*(_xlfn.XLOOKUP(Q_end,cpi!A:A,cpi!B:B)/BH24) -> 2808.436 | AC24: {=INDEX('msci-indices'!C:C,MATCH($L24,'msci-indices'!$B:$B)-2)} -> 912.83804 | AD24: {=INDEX('msci-indices'!D:D,MATCH($L24,'msci-indices'!$B:$B)-2)} -> 924.58629 | AE24: =AI23+AA24 -> 142502.08 | AF24: {=INDEX('msci-indices'!C:C,MATCH($L24,'msci-indices'!$B:$B)+1)} -> 915.80494 | AG24: {=INDEX('msci-indices'!D:D,MATCH($L24,'msci-indices'!$B:$B)+1)} -> 884.12823 | AH24: =(InvestFees/4)*AE24 -> 89.063802 | AI24: =((AF24/AC24)*GlobalPortfolio+(AG24/AD24)*AusPortfolio)*AE24-AH24 -> 140866.55 | AJ24: =AJ23+AA24 -> 121266.82 | AK24: =AI24-AJ24 -> 19599.732 | AL24: =AJ24*(_xlfn.XLOOKUP(Q_end,cpi!A:A,cpi!B:B)/BH24) -> 176710.05 | AM24: {=SUMPRODUCT($AA$3:AA24,_xlfn.SORTBY($BH$3:BH24,_xlfn.SEQUENCE(ROWS($BH$3:BH24)),-1)/$BH$3)} -> 138205.64 | AN24: =AI24-AM24 -> 2660.9125 | AO24: =IF($B$49="Real gains",MAX($B$50*AN24,0),IF($B$49="Discounted nominal gains",MAX($B$50*AK24/2,0),0)) -> 0 | AP24: =AI24-AO24 -> 140866.55 | AR24: =IF($B$10="3BR_H", INDEX('ns-combined'!$C:$D,MATCH($L24,'ns-combined'!$B:$B,0),MATCH(Council_Area,'ns-combined'!$C$1:$D$1,0))*1000, INDEX('s-combined'!$C:$D,MATCH($L24,'s-combined'!$B:$B,0),MATCH(Council_Area,'s-combined'!$C$1:$D$1,0))*1000) -> 395000 | AS24: =AS23+$AS$3 -> 15400 | AT24: 0 | AU24: =SUM($B$28:$B$29)*AR24 -> 7900 | AV24: =AR24*$B$15/4 -> 1135.625 | AW24: =SUM($AV$3:AV24) -> 22457.487 | AX24: =AR24-AS24-AU24-AW24 -> 349242.51 | AY24: =$B$36*V24 -> 1456 | AZ24: =SUM(AY24:AY24)*4/AR24 -> 0.014744304 | BA24: =SUM(AY24:AY24)/V24 -> 0.35 | BB24: =IF(MortgageRate="Discounted",_xlfn.XLOOKUP(L24,'mortgage-rates'!$A:$A,'mortgage-rates'!$E:$E)/100,_xlfn.XLOOKUP(L24,'mortgage-rates'!$A:$A,'mortgage-rates'!$D:$D)/100) -> 0.0704 | BC24: =BC23-BF23 -> 202661.22 | BD24: =IF($B$16*12/3-Q24+1>0,-PMT($BB24/4,$B$16*12/3-Q24+1,BC24),0) -> 4768.5314 | BE24: =BC24*($BB24/4) -> 3566.8375 | BF24: =BD24-BE24 -> 1201.694 | BG24: =AT24+AY24+BD24 -> 6224.5314 | BH24: =INDEX(cpi!B:B,MATCH($L24,cpi!A:A)) -> 99.3 | BI24: =100*BH24/BH$3 -> 117.37589 | BJ24: =100*AC24/AC$3 -> 120.92498 | BK24: =100*AD24/AD$3 -> 129.68345 | BL24: =BJ24*GlobalPortfolio+BK24*AusPortfolio -> 123.55252 | BM24: =100*AE24/$AE$3 -> 195.00822 | BN24: =100*AR24/AR$3 -> 141.07143 | BO24: =100*AX24/AX$3 -> 127.97688
A25: Real estate agent commissions (purchase) | B25: 0.015 | C25: 0.015 | L25: =DATE(YEAR(L24),MONTH(L24)+3,1) -> 40787 | M25: =AP25 -> 120307.93 | N25: =AX25-BC25 -> 141061.74 | O25: =M25/N25 -> 0.85287428 | P25: =X25/BG25 -> 0.69642124 | Q25: 23 | R25: =EOMONTH(L25,0)-EOMONTH(L25,-3) -> 92 | T25: =IF($B$10="3BR_H", INDEX('3BR_H-processed'!$E:$F,MATCH($L25,'3BR_H-processed'!$B:$B,0),MATCH(Council_Area,'3BR_H-processed'!$E$1:$F$1,0)), INDEX('2BR_F-processed'!$E:$F,MATCH($L25,'2BR_F-processed'!$B:$B,0),MATCH(Council_Area,'2BR_F-processed'!$E$1:$F$1,0))) -> 320 | U25: =IF(MOD(Q25,4)=1,T25,U24) -> 320 | V25: =U25*(R25)/7 -> 4205.7143 | W25: =$B$53/4*BH25/_xlfn.XLOOKUP(Q_end,cpi!A:A,cpi!B:B) -> 137.80235 | X25: =V25+W25 -> 4343.5166 | Y25: =BG25-X25 -> 1893.3934 | Z25: =Y25*$B$47 -> 0 | AA25: {=(Y25+Z25)*eff_invest} -> 1893.3934 | AB25: =AA25*(_xlfn.XLOOKUP(Q_end,cpi!A:A,cpi!B:B)/BH25) -> 2747.9843 | AC25: {=INDEX('msci-indices'!C:C,MATCH($L25,'msci-indices'!$B:$B)-2)} -> 915.80494 | AD25: {=INDEX('msci-indices'!D:D,MATCH($L25,'msci-indices'!$B:$B)-2)} -> 884.12823 | AE25: =AI24+AA25 -> 142759.94 | AF25: {=INDEX('msci-indices'!C:C,MATCH($L25,'msci-indices'!$B:$B)+1)} -> 758.74852 | AG25: {=INDEX('msci-indices'!D:D,MATCH($L25,'msci-indices'!$B:$B)+1)} -> 776.26676 | AH25: =(InvestFees/4)*AE25 -> 89.224964 | AI25: =((AF25/AC25)*GlobalPortfolio+(AG25/AD25)*AusPortfolio)*AE25-AH25 -> 120307.93 | AJ25: =AJ24+AA25 -> 123160.21 | AK25: =AI25-AJ25 -> -2852.2832 | AL25: =AJ25*(_xlfn.XLOOKUP(Q_end,cpi!A:A,cpi!B:B)/BH25) -> 178749.07 | AM25: {=SUMPRODUCT($AA$3:AA25,_xlfn.SORTBY($BH$3:BH25,_xlfn.SEQUENCE(ROWS($BH$3:BH25)),-1)/$BH$3)} -> 140828.06 | AN25: =AI25-AM25 -> -20520.128 | AO25: =IF($B$49="Real gains",MAX($B$50*AN25,0),IF($B$49="Discounted nominal gains",MAX($B$50*AK25/2,0),0)) -> 0 | AP25: =AI25-AO25 -> 120307.93 | AR25: =IF($B$10="3BR_H", INDEX('ns-combined'!$C:$D,MATCH($L25,'ns-combined'!$B:$B,0),MATCH(Council_Area,'ns-combined'!$C$1:$D$1,0))*1000, INDEX('s-combined'!$C:$D,MATCH($L25,'s-combined'!$B:$B,0),MATCH(Council_Area,'s-combined'!$C$1:$D$1,0))*1000) -> 390000 | AS25: =AS24+$AS$3 -> 16100 | AT25: 0 | AU25: =SUM($B$28:$B$29)*AR25 -> 7800 | AV25: =AR25*$B$15/4 -> 1121.25 | AW25: =SUM($AV$3:AV25) -> 23578.737 | AX25: =AR25-AS25-AU25-AW25 -> 342521.26 | AY25: =$B$36*V25 -> 1472 | AZ25: =SUM(AY25:AY25)*4/AR25 -> 0.015097436 | BA25: =SUM(AY25:AY25)/V25 -> 0.35 | BB25: =IF(MortgageRate="Discounted",_xlfn.XLOOKUP(L25,'mortgage-rates'!$A:$A,'mortgage-rates'!$E:$E)/100,_xlfn.XLOOKUP(L25,'mortgage-rates'!$A:$A,'mortgage-rates'!$D:$D)/100) -> 0.0703 | BC25: =BC24-BF24 -> 201459.52 | BD25: =IF($B$16*12/3-Q25+1>0,-PMT($BB25/4,$B$16*12/3-Q25+1,BC25),0) -> 4764.9101 | BE25: =BC25*($BB25/4) -> 3540.6511 | BF25: =BD25-BE25 -> 1224.2589 | BG25: =AT25+AY25+BD25 -> 6236.9101 | BH25: =INDEX(cpi!B:B,MATCH($L25,cpi!A:A)) -> 99.7 | BI25: =100*BH25/BH$3 -> 117.8487 | BJ25: =100*AC25/AC$3 -> 121.31801 | BK25: =100*AD25/AD$3 -> 124.00876 | BL25: =BJ25*GlobalPortfolio+BK25*AusPortfolio -> 122.12524 | BM25: =100*AE25/$AE$3 -> 195.36109 | BN25: =100*AR25/AR$3 -> 139.28571 | BO25: =100*AX25/AX$3 -> 125.51394
A26: Stamp duty (purchase) | B26: =IF(AR3<250000,6830+(4.25/100)*(AR3-200000),8955+(4.75/100)*(AR3-250000))/AR3 -> 0.037071429 | C26: 0.03 | L26: =DATE(YEAR(L25),MONTH(L25)+3,1) -> 40878 | M26: =AP26 -> 129176.76 | N26: =AX26-BC26 -> 135579.12 | O26: =M26/N26 -> 0.95277764 | P26: =X26/BG26 -> 0.71647427 | Q26: 24 | R26: =EOMONTH(L26,0)-EOMONTH(L26,-3) -> 92 | T26: =IF($B$10="3BR_H", INDEX('3BR_H-processed'!$E:$F,MATCH($L26,'3BR_H-processed'!$B:$B,0),MATCH(Council_Area,'3BR_H-processed'!$E$1:$F$1,0)), INDEX('2BR_F-processed'!$E:$F,MATCH($L26,'2BR_F-processed'!$B:$B,0),MATCH(Council_Area,'2BR_F-processed'!$E$1:$F$1,0))) -> 320 | U26: =IF(MOD(Q26,4)=1,T26,U25) -> 320 | V26: =U26*(R26)/7 -> 4205.7143 | W26: =$B$53/4*BH26/_xlfn.XLOOKUP(Q_end,cpi!A:A,cpi!B:B) -> 138.07878 | X26: =V26+W26 -> 4343.7931 | Y26: =BG26-X26 -> 1718.9411 | Z26: =Y26*$B$47 -> 0 | AA26: {=(Y26+Z26)*eff_invest} -> 1718.9411 | AB26: =AA26*(_xlfn.XLOOKUP(Q_end,cpi!A:A,cpi!B:B)/BH26) -> 2489.7976 | AC26: {=INDEX('msci-indices'!C:C,MATCH($L26,'msci-indices'!$B:$B)-2)} -> 758.74852 | AD26: {=INDEX('msci-indices'!D:D,MATCH($L26,'msci-indices'!$B:$B)-2)} -> 776.26676 | AE26: =AI25+AA26 -> 122026.87 | AF26: {=INDEX('msci-indices'!C:C,MATCH($L26,'msci-indices'!$B:$B)+1)} -> 816.9754 | AG26: {=INDEX('msci-indices'!D:D,MATCH($L26,'msci-indices'!$B:$B)+1)} -> 790.49635 | AH26: =(InvestFees/4)*AE26 -> 76.266793 | AI26: =((AF26/AC26)*GlobalPortfolio+(AG26/AD26)*AusPortfolio)*AE26-AH26 -> 129176.76 | AJ26: =AJ25+AA26 -> 124879.15 | AK26: =AI26-AJ26 -> 4297.6039 | AL26: =AJ26*(_xlfn.XLOOKUP(Q_end,cpi!A:A,cpi!B:B)/BH26) -> 180881.01 | AM26: {=SUMPRODUCT($AA$3:AA26,_xlfn.SORTBY($BH$3:BH26,_xlfn.SEQUENCE(ROWS($BH$3:BH26)),-1)/$BH$3)} -> 143124.66 | AN26: =AI26-AM26 -> -13947.906 | AO26: =IF($B$49="Real gains",MAX($B$50*AN26,0),IF($B$49="Discounted nominal gains",MAX($B$50*AK26/2,0),0)) -> 0 | AP26: =AI26-AO26 -> 129176.76 | AR26: =IF($B$10="3BR_H", INDEX('ns-combined'!$C:$D,MATCH($L26,'ns-combined'!$B:$B,0),MATCH(Council_Area,'ns-combined'!$C$1:$D$1,0))*1000, INDEX('s-combined'!$C:$D,MATCH($L26,'s-combined'!$B:$B,0),MATCH(Council_Area,'s-combined'!$C$1:$D$1,0))*1000) -> 385000 | AS26: =AS25+$AS$3 -> 16800 | AT26: 0 | AU26: =SUM($B$28:$B$29)*AR26 -> 7700 | AV26: =AR26*$B$15/4 -> 1106.875 | AW26: =SUM($AV$3:AV26) -> 24685.612 | AX26: =AR26-AS26-AU26-AW26 -> 335814.39 | AY26: =$B$36*V26 -> 1472 | AZ26: =SUM(AY26:AY26)*4/AR26 -> 0.015293506 | BA26: =SUM(AY26:AY26)/V26 -> 0.35 | BB26: =IF(MortgageRate="Discounted",_xlfn.XLOOKUP(L26,'mortgage-rates'!$A:$A,'mortgage-rates'!$E:$E)/100,_xlfn.XLOOKUP(L26,'mortgage-rates'!$A:$A,'mortgage-rates'!$D:$D)/100) -> 0.0654 | BC26: =BC25-BF25 -> 200235.27 | BD26: =IF($B$16*12/3-Q26+1>0,-PMT($BB26/4,$B$16*12/3-Q26+1,BC26),0) -> 4590.7342 | BE26: =BC26*($BB26/4) -> 3273.8466 | BF26: =BD26-BE26 -> 1316.8876 | BG26: =AT26+AY26+BD26 -> 6062.7342 | BH26: =INDEX(cpi!B:B,MATCH($L26,cpi!A:A)) -> 99.9 | BI26: =100*BH26/BH$3 -> 118.08511 | BJ26: =100*AC26/AC$3 -> 100.51252 | BK26: =100*AD26/AD$3 -> 108.88 | BL26: =BJ26*GlobalPortfolio+BK26*AusPortfolio -> 103.02276 | BM26: =100*AE26/$AE$3 -> 166.98873 | BN26: =100*AR26/AR$3 -> 137.5 | BO26: =100*AX26/AX$3 -> 123.05626
A27: When selling the house (derating of home value) | L27: =DATE(YEAR(L26),MONTH(L26)+3,1) -> 40969 | M27: =AP27 -> 145034.21 | N27: =AX27-BC27 -> 132157.76 | O27: =M27/N27 -> 1.0974324 | P27: =X27/BG27 -> 0.71981199 | Q27: 25 | R27: =EOMONTH(L27,0)-EOMONTH(L27,-3) -> 91 | T27: =IF($B$10="3BR_H", INDEX('3BR_H-processed'!$E:$F,MATCH($L27,'3BR_H-processed'!$B:$B,0),MATCH(Council_Area,'3BR_H-processed'!$E$1:$F$1,0)), INDEX('2BR_F-processed'!$E:$F,MATCH($L27,'2BR_F-processed'!$B:$B,0),MATCH(Council_Area,'2BR_F-processed'!$E$1:$F$1,0))) -> 330 | U27: =IF(MOD(Q27,4)=1,T27,U26) -> 330 | V27: =U27*(R27)/7 -> 4290 | W27: =$B$53/4*BH27/_xlfn.XLOOKUP(Q_end,cpi!A:A,cpi!B:B) -> 138.07878 | X27: =V27+W27 -> 4428.0788 | Y27: =BG27-X27 -> 1723.637 | Z27: =Y27*$B$47 -> 0 | AA27: {=(Y27+Z27)*eff_invest} -> 1723.637 | AB27: =AA27*(_xlfn.XLOOKUP(Q_end,cpi!A:A,cpi!B:B)/BH27) -> 2496.5994 | AC27: {=INDEX('msci-indices'!C:C,MATCH($L27,'msci-indices'!$B:$B)-2)} -> 816.9754 | AD27: {=INDEX('msci-indices'!D:D,MATCH($L27,'msci-indices'!$B:$B)-2)} -> 790.49635 | AE27: =AI26+AA27 -> 130900.39 | AF27: {=INDEX('msci-indices'!C:C,MATCH($L27,'msci-indices'!$B:$B)+1)} -> 913.58723 | AG27: {=INDEX('msci-indices'!D:D,MATCH($L27,'msci-indices'!$B:$B)+1)} -> 858.5317 | AH27: =(InvestFees/4)*AE27 -> 81.812745 | AI27: =((AF27/AC27)*GlobalPortfolio+(AG27/AD27)*AusPortfolio)*AE27-AH27 -> 145034.21 | AJ27: =AJ26+AA27 -> 126602.79 | AK27: =AI27-AJ27 -> 18431.421 | AL27: =AJ27*(_xlfn.XLOOKUP(Q_end,cpi!A:A,cpi!B:B)/BH27) -> 183377.61 | AM27: {=SUMPRODUCT($AA$3:AA27,_xlfn.SORTBY($BH$3:BH27,_xlfn.SEQUENCE(ROWS($BH$3:BH27)),-1)/$BH$3)} -> 145261.18 | AN27: =AI27-AM27 -> -226.96825 | AO27: =IF($B$49="Real gains",MAX($B$50*AN27,0),IF($B$49="Discounted nominal gains",MAX($B$50*AK27/2,0),0)) -> 0 | AP27: =AI27-AO27 -> 145034.21 | AR27: =IF($B$10="3BR_H", INDEX('ns-combined'!$C:$D,MATCH($L27,'ns-combined'!$B:$B,0),MATCH(Council_Area,'ns-combined'!$C$1:$D$1,0))*1000, INDEX('s-combined'!$C:$D,MATCH($L27,'s-combined'!$B:$B,0),MATCH(Council_Area,'s-combined'!$C$1:$D$1,0))*1000) -> 382000 | AS27: =AS26+$AS$3 -> 17500 | AT27: 0 | AU27: =SUM($B$28:$B$29)*AR27 -> 7640 | AV27: =AR27*$B$15/4 -> 1098.25 | AW27: =SUM($AV$3:AV27) -> 25783.862 | AX27: =AR27-AS27-AU27-AW27 -> 331076.14 | AY27: =$B$36*V27 -> 1501.5 | AZ27: =SUM(AY27:AY27)*4/AR27 -> 0.015722513 | BA27: =SUM(AY27:AY27)/V27 -> 0.35 | BB27: =IF(MortgageRate="Discounted",_xlfn.XLOOKUP(L27,'mortgage-rates'!$A:$A,'mortgage-rates'!$E:$E)/100,_xlfn.XLOOKUP(L27,'mortgage-rates'!$A:$A,'mortgage-rates'!$D:$D)/100) -> 0.0671 | BC27: =BC26-BF26 -> 198918.38 | BD27: =IF($B$16*12/3-Q27+1>0,-PMT($BB27/4,$B$16*12/3-Q27+1,BC27),0) -> 4650.2158 | BE27: =BC27*($BB27/4) -> 3336.8558 | BF27: =BD27-BE27 -> 1313.36 | BG27: =AT27+AY27+BD27 -> 6151.7158 | BH27: =INDEX(cpi!B:B,MATCH($L27,cpi!A:A)) -> 99.9 | BI27: =100*BH27/BH$3 -> 118.08511 | BJ27: =100*AC27/AC$3 -> 108.22592 | BK27: =100*AD27/AD$3 -> 110.87586 | BL27: =BJ27*GlobalPortfolio+BK27*AusPortfolio -> 109.0209 | BM27: =100*AE27/$AE$3 -> 179.13178 | BN27: =100*AR27/AR$3 -> 136.42857 | BO27: =100*AX27/AX$3 -> 121.31997
A28: Real estate agent commissions (sale) | B28: 0.015 | C28: 0.015 | L28: =DATE(YEAR(L27),MONTH(L27)+3,1) -> 41061 | M28: =AP28 -> 138773.56 | N28: =AX28-BC28 -> 134604.24 | O28: =M28/N28 -> 1.0309746 | P28: =X28/BG28 -> 0.74406435 | Q28: 26 | R28: =EOMONTH(L28,0)-EOMONTH(L28,-3) -> 91 | T28: =IF($B$10="3BR_H", INDEX('3BR_H-processed'!$E:$F,MATCH($L28,'3BR_H-processed'!$B:$B,0),MATCH(Council_Area,'3BR_H-processed'!$E$1:$F$1,0)), INDEX('2BR_F-processed'!$E:$F,MATCH($L28,'2BR_F-processed'!$B:$B,0),MATCH(Council_Area,'2BR_F-processed'!$E$1:$F$1,0))) -> 320 | U28: =IF(MOD(Q28,4)=1,T28,U27) -> 330 | V28: =U28*(R28)/7 -> 4290 | W28: =$B$53/4*BH28/_xlfn.XLOOKUP(Q_end,cpi!A:A,cpi!B:B) -> 138.90809 | X28: =V28+W28 -> 4428.9081 | Y28: =BG28-X28 -> 1523.4106 | Z28: =Y28*$B$47 -> 0 | AA28: {=(Y28+Z28)*eff_invest} -> 1523.4106 | AB28: =AA28*(_xlfn.XLOOKUP(Q_end,cpi!A:A,cpi!B:B)/BH28) -> 2193.4081 | AC28: {=INDEX('msci-indices'!C:C,MATCH($L28,'msci-indices'!$B:$B)-2)} -> 913.58723 | AD28: {=INDEX('msci-indices'!D:D,MATCH($L28,'msci-indices'!$B:$B)-2)} -> 858.5317 | AE28: =AI27+AA28 -> 146557.62 | AF28: {=INDEX('msci-indices'!C:C,MATCH($L28,'msci-indices'!$B:$B)+1)} -> 865.80589 | AG28: {=INDEX('msci-indices'!D:D,MATCH($L28,'msci-indices'!$B:$B)+1)} -> 813.09506 | AH28: =(InvestFees/4)*AE28 -> 91.598513 | AI28: =((AF28/AC28)*GlobalPortfolio+(AG28/AD28)*AusPortfolio)*AE28-AH28 -> 138773.56 | AJ28: =AJ27+AA28 -> 128126.2 | AK28: =AI28-AJ28 -> 10647.356 | AL28: =AJ28*(_xlfn.XLOOKUP(Q_end,cpi!A:A,cpi!B:B)/BH28) -> 184476.23 | AM28: {=SUMPRODUCT($AA$3:AA28,_xlfn.SORTBY($BH$3:BH28,_xlfn.SEQUENCE(ROWS($BH$3:BH28)),-1)/$BH$3)} -> 147710.24 | AN28: =AI28-AM28 -> -8936.687 | AO28: =IF($B$49="Real gains",MAX($B$50*AN28,0),IF($B$49="Discounted nominal gains",MAX($B$50*AK28/2,0),0)) -> 0 | AP28: =AI28-AO28 -> 138773.56 | AR28: =IF($B$10="3BR_H", INDEX('ns-combined'!$C:$D,MATCH($L28,'ns-combined'!$B:$B,0),MATCH(Council_Area,'ns-combined'!$C$1:$D$1,0))*1000, INDEX('s-combined'!$C:$D,MATCH($L28,'s-combined'!$B:$B,0),MATCH(Council_Area,'s-combined'!$C$1:$D$1,0))*1000) -> 385000 | AS28: =AS27+$AS$3 -> 18200 | AT28: 0 | AU28: =SUM($B$28:$B$29)*AR28 -> 7700 | AV28: =AR28*$B$15/4 -> 1106.875 | AW28: =SUM($AV$3:AV28) -> 26890.737 | AX28: =AR28-AS28-AU28-AW28 -> 332209.26 | AY28: =$B$36*V28 -> 1501.5 | AZ28: =SUM(AY28:AY28)*4/AR28 -> 0.0156 | BA28: =SUM(AY28:AY28)/V28 -> 0.35 | BB28: =IF(MortgageRate="Discounted",_xlfn.XLOOKUP(L28,'mortgage-rates'!$A:$A,'mortgage-rates'!$E:$E)/100,_xlfn.XLOOKUP(L28,'mortgage-rates'!$A:$A,'mortgage-rates'!$D:$D)/100) -> 0.0613 | BC28: =BC27-BF27 -> 197605.02 | BD28: =IF($B$16*12/3-Q28+1>0,-PMT($BB28/4,$B$16*12/3-Q28+1,BC28),0) -> 4450.8187 | BE28: =BC28*($BB28/4) -> 3028.2969 | BF28: =BD28-BE28 -> 1422.5217 | BG28: =AT28+AY28+BD28 -> 5952.3187 | BH28: =INDEX(cpi!B:B,MATCH($L28,cpi!A:A)) -> 100.5 | BI28: =100*BH28/BH$3 -> 118.79433 | BJ28: =100*AC28/AC$3 -> 121.02423 | BK28: =100*AD28/AD$3 -> 120.41857 | BL28: =BJ28*GlobalPortfolio+BK28*AusPortfolio -> 120.84253 | BM28: =100*AE28/$AE$3 -> 200.55805 | BN28: =100*AR28/AR$3 -> 137.5 | BO28: =100*AX28/AX$3 -> 121.7352
A29: Other selling costs | B29: 0.005 | C29: 0.005 | L29: =DATE(YEAR(L28),MONTH(L28)+3,1) -> 41153 | M29: =AP29 -> 150382.28 | N29: =AX29-BC29 -> 135197.02 | O29: =M29/N29 -> 1.1123195 | P29: =X29/BG29 -> 0.75227874 | Q29: 27 | R29: =EOMONTH(L29,0)-EOMONTH(L29,-3) -> 92 | T29: =IF($B$10="3BR_H", INDEX('3BR_H-processed'!$E:$F,MATCH($L29,'3BR_H-processed'!$B:$B,0),MATCH(Council_Area,'3BR_H-processed'!$E$1:$F$1,0)), INDEX('2BR_F-processed'!$E:$F,MATCH($L29,'2BR_F-processed'!$B:$B,0),MATCH(Council_Area,'2BR_F-processed'!$E$1:$F$1,0))) -> 320 | U29: =IF(MOD(Q29,4)=1,T29,U28) -> 330 | V29: =U29*(R29)/7 -> 4337.1429 | W29: =$B$53/4*BH29/_xlfn.XLOOKUP(Q_end,cpi!A:A,cpi!B:B) -> 140.42847 | X29: =V29+W29 -> 4477.5713 | Y29: =BG29-X29 -> 1474.4396 | Z29: =Y29*$B$47 -> 0 | AA29: {=(Y29+Z29)*eff_invest} -> 1474.4396 | AB29: =AA29*(_xlfn.XLOOKUP(Q_end,cpi!A:A,cpi!B:B)/BH29) -> 2099.9155 | AC29: {=INDEX('msci-indices'!C:C,MATCH($L29,'msci-indices'!$B:$B)-2)} -> 865.80589 | AD29: {=INDEX('msci-indices'!D:D,MATCH($L29,'msci-indices'!$B:$B)-2)} -> 813.09506 | AE29: =AI28+AA29 -> 140248 | AF29: {=INDEX('msci-indices'!C:C,MATCH($L29,'msci-indices'!$B:$B)+1)} -> 923.8995 | AG29: {=INDEX('msci-indices'!D:D,MATCH($L29,'msci-indices'!$B:$B)+1)} -> 883.33647 | AH29: =(InvestFees/4)*AE29 -> 87.654997 | AI29: =((AF29/AC29)*GlobalPortfolio+(AG29/AD29)*AusPortfolio)*AE29-AH29 -> 150382.28 | AJ29: =AJ28+AA29 -> 129600.64 | AK29: =AI29-AJ29 -> 20781.638 | AL29: =AJ29*(_xlfn.XLOOKUP(Q_end,cpi!A:A,cpi!B:B)/BH29) -> 184578.86 | AM29: {=SUMPRODUCT($AA$3:AA29,_xlfn.SORTBY($BH$3:BH29,_xlfn.SEQUENCE(ROWS($BH$3:BH29)),-1)/$BH$3)} -> 150548.75 | AN29: =AI29-AM29 -> -166.47298 | AO29: =IF($B$49="Real gains",MAX($B$50*AN29,0),IF($B$49="Discounted nominal gains",MAX($B$50*AK29/2,0),0)) -> 0 | AP29: =AI29-AO29 -> 150382.28 | AR29: =IF($B$10="3BR_H", INDEX('ns-combined'!$C:$D,MATCH($L29,'ns-combined'!$B:$B,0),MATCH(Council_Area,'ns-combined'!$C$1:$D$1,0))*1000, INDEX('s-combined'!$C:$D,MATCH($L29,'s-combined'!$B:$B,0),MATCH(Council_Area,'s-combined'!$C$1:$D$1,0))*1000) -> 386000 | AS29: =AS28+$AS$3 -> 18900 | AT29: 0 | AU29: =SUM($B$28:$B$29)*AR29 -> 7720 | AV29: =AR29*$B$15/4 -> 1109.75 | AW29: =SUM($AV$3:AV29) -> 28000.487 | AX29: =AR29-AS29-AU29-AW29 -> 331379.51 | AY29: =$B$36*V29 -> 1518 | AZ29: =SUM(AY29:AY29)*4/AR29 -> 0.01573057 | BA29: =SUM(AY29:AY29)/V29 -> 0.35 | BB29: =IF(MortgageRate="Discounted",_xlfn.XLOOKUP(L29,'mortgage-rates'!$A:$A,'mortgage-rates'!$E:$E)/100,_xlfn.XLOOKUP(L29,'mortgage-rates'!$A:$A,'mortgage-rates'!$D:$D)/100) -> 0.0608 | BC29: =BC28-BF28 -> 196182.5 | BD29: =IF($B$16*12/3-Q29+1>0,-PMT($BB29/4,$B$16*12/3-Q29+1,BC29),0) -> 4434.011 | BE29: =BC29*($BB29/4) -> 2981.9739 | BF29: =BD29-BE29 -> 1452.037 | BG29: =AT29+AY29+BD29 -> 5952.011 | BH29: =INDEX(cpi!B:B,MATCH($L29,cpi!A:A)) -> 101.6 | BI29: =100*BH29/BH$3 -> 120.09456 | BJ29: =100*AC29/AC$3 -> 114.69457 | BK29: =100*AD29/AD$3 -> 114.04558 | BL29: =BJ29*GlobalPortfolio+BK29*AusPortfolio -> 114.49987 | BM29: =100*AE29/$AE$3 -> 191.92359 | BN29: =100*AR29/AR$3 -> 137.85714 | BO29: =100*AX29/AX$3 -> 121.43114
L30: =DATE(YEAR(L29),MONTH(L29)+3,1) -> 41244 | M30: =AP30 -> 157527.61 | N30: =AX30-BC30 -> 143633.43 | O30: =M30/N30 -> 1.0967336 | P30: =X30/BG30 -> 0.76942111 | Q30: 28 | R30: =EOMONTH(L30,0)-EOMONTH(L30,-3) -> 92 | T30: =IF($B$10="3BR_H", INDEX('3BR_H-processed'!$E:$F,MATCH($L30,'3BR_H-processed'!$B:$B,0),MATCH(Council_Area,'3BR_H-processed'!$E$1:$F$1,0)), INDEX('2BR_F-processed'!$E:$F,MATCH($L30,'2BR_F-processed'!$B:$B,0),MATCH(Council_Area,'2BR_F-processed'!$E$1:$F$1,0))) -> 325 | U30: =IF(MOD(Q30,4)=1,T30,U29) -> 330 | V30: =U30*(R30)/7 -> 4337.1429 | W30: =$B$53/4*BH30/_xlfn.XLOOKUP(Q_end,cpi!A:A,cpi!B:B) -> 140.98134 | X30: =V30+W30 -> 4478.1242 | Y30: =BG30-X30 -> 1341.9971 | Z30: =Y30*$B$47 -> 0 | AA30: {=(Y30+Z30)*eff_invest} -> 1341.9971 | AB30: =AA30*(_xlfn.XLOOKUP(Q_end,cpi!A:A,cpi!B:B)/BH30) -> 1903.794 | AC30: {=INDEX('msci-indices'!C:C,MATCH($L30,'msci-indices'!$B:$B)-2)} -> 923.8995 | AD30: {=INDEX('msci-indices'!D:D,MATCH($L30,'msci-indices'!$B:$B)-2)} -> 883.33647 | AE30: =AI29+AA30 -> 151724.27 | AF30: {=INDEX('msci-indices'!C:C,MATCH($L30,'msci-indices'!$B:$B)+1)} -> 948.15111 | AG30: {=INDEX('msci-indices'!D:D,MATCH($L30,'msci-indices'!$B:$B)+1)} -> 943.69729 | AH30: =(InvestFees/4)*AE30 -> 94.827671 | AI30: =((AF30/AC30)*GlobalPortfolio+(AG30/AD30)*AusPortfolio)*AE30-AH30 -> 157527.61 | AJ30: =AJ29+AA30 -> 130942.64 | AK30: =AI30-AJ30 -> 26584.977 | AL30: =AJ30*(_xlfn.XLOOKUP(Q_end,cpi!A:A,cpi!B:B)/BH30) -> 185758.82 | AM30: {=SUMPRODUCT($AA$3:AA30,_xlfn.SORTBY($BH$3:BH30,_xlfn.SEQUENCE(ROWS($BH$3:BH30)),-1)/$BH$3)} -> 152673.72 | AN30: =AI30-AM30 -> 4853.891 | AO30: =IF($B$49="Real gains",MAX($B$50*AN30,0),IF($B$49="Discounted nominal gains",MAX($B$50*AK30/2,0),0)) -> 0 | AP30: =AI30-AO30 -> 157527.61 | AR30: =IF($B$10="3BR_H", INDEX('ns-combined'!$C:$D,MATCH($L30,'ns-combined'!$B:$B,0),MATCH(Council_Area,'ns-combined'!$C$1:$D$1,0))*1000, INDEX('s-combined'!$C:$D,MATCH($L30,'s-combined'!$B:$B,0),MATCH(Council_Area,'s-combined'!$C$1:$D$1,0))*1000) -> 395000 | AS30: =AS29+$AS$3 -> 19600 | AT30: 0 | AU30: =SUM($B$28:$B$29)*AR30 -> 7900 | AV30: =AR30*$B$15/4 -> 1135.625 | AW30: =SUM($AV$3:AV30) -> 29136.112 | AX30: =AR30-AS30-AU30-AW30 -> 338363.89 | AY30: =$B$36*V30 -> 1518 | AZ30: =SUM(AY30:AY30)*4/AR30 -> 0.015372152 | BA30: =SUM(AY30:AY30)/V30 -> 0.35 | BB30: =IF(MortgageRate="Discounted",_xlfn.XLOOKUP(L30,'mortgage-rates'!$A:$A,'mortgage-rates'!$E:$E)/100,_xlfn.XLOOKUP(L30,'mortgage-rates'!$A:$A,'mortgage-rates'!$D:$D)/100) -> 0.0568 | BC30: =BC29-BF29 -> 194730.46 | BD30: =IF($B$16*12/3-Q30+1>0,-PMT($BB30/4,$B$16*12/3-Q30+1,BC30),0) -> 4302.1213 | BE30: =BC30*($BB30/4) -> 2765.1725 | BF30: =BD30-BE30 -> 1536.9488 | BG30: =AT30+AY30+BD30 -> 5820.1213 | BH30: =INDEX(cpi!B:B,MATCH($L30,cpi!A:A)) -> 102 | BI30: =100*BH30/BH$3 -> 120.56738 | BJ30: =100*AC30/AC$3 -> 122.39031 | BK30: =100*AD30/AD$3 -> 123.89771 | BL30: =BJ30*GlobalPortfolio+BK30*AusPortfolio -> 122.84253 | BM30: =100*AE30/$AE$3 -> 207.6284 | BN30: =100*AR30/AR$3 -> 141.07143 | BO30: =100*AX30/AX$3 -> 123.9905
A31: Home ownership running costs (% of gross rents) | L31: =DATE(YEAR(L30),MONTH(L30)+3,1) -> 41334 | M31: =AP31 -> 171726.82 | N31: =AX31-BC31 -> 143334.75 | O31: =M31/N31 -> 1.1980822 | P31: =X31/BG31 -> 0.7601589 | Q31: 29 | R31: =EOMONTH(L31,0)-EOMONTH(L31,-3) -> 90 | T31: =IF($B$10="3BR_H", INDEX('3BR_H-processed'!$E:$F,MATCH($L31,'3BR_H-processed'!$B:$B,0),MATCH(Council_Area,'3BR_H-processed'!$E$1:$F$1,0)), INDEX('2BR_F-processed'!$E:$F,MATCH($L31,'2BR_F-processed'!$B:$B,0),MATCH(Council_Area,'2BR_F-processed'!$E$1:$F$1,0))) -> 330 | U31: =IF(MOD(Q31,4)=1,T31,U30) -> 330 | V31: =U31*(R31)/7 -> 4242.8571 | W31: =$B$53/4*BH31/_xlfn.XLOOKUP(Q_end,cpi!A:A,cpi!B:B) -> 141.53421 | X31: =V31+W31 -> 4384.3914 | Y31: =BG31-X31 -> 1383.3387 | Z31: =Y31*$B$47 -> 0 | AA31: {=(Y31+Z31)*eff_invest} -> 1383.3387 | AB31: =AA31*(_xlfn.XLOOKUP(Q_end,cpi!A:A,cpi!B:B)/BH31) -> 1954.7765 | AC31: {=INDEX('msci-indices'!C:C,MATCH($L31,'msci-indices'!$B:$B)-2)} -> 948.15111 | AD31: {=INDEX('msci-indices'!D:D,MATCH($L31,'msci-indices'!$B:$B)-2)} -> 943.69729 | AE31: =AI30+AA31 -> 158910.95 | AF31: {=INDEX('msci-indices'!C:C,MATCH($L31,'msci-indices'!$B:$B)+1)} -> 1024.7053 | AG31: {=INDEX('msci-indices'!D:D,MATCH($L31,'msci-indices'!$B:$B)+1)} -> 1021.5673 | AH31: =(InvestFees/4)*AE31 -> 99.319345 | AI31: =((AF31/AC31)*GlobalPortfolio+(AG31/AD31)*AusPortfolio)*AE31-AH31 -> 171726.82 | AJ31: =AJ30+AA31 -> 132325.97 | AK31: =AI31-AJ31 -> 39400.843 | AL31: =AJ31*(_xlfn.XLOOKUP(Q_end,cpi!A:A,cpi!B:B)/BH31) -> 186987.97 | AM31: {=SUMPRODUCT($AA$3:AA31,_xlfn.SORTBY($BH$3:BH31,_xlfn.SEQUENCE(ROWS($BH$3:BH31)),-1)/$BH$3)} -> 154844.35 | AN31: =AI31-AM31 -> 16882.469 | AO31: =IF($B$49="Real gains",MAX($B$50*AN31,0),IF($B$49="Discounted nominal gains",MAX($B$50*AK31/2,0),0)) -> 0 | AP31: =AI31-AO31 -> 171726.82 | AR31: =IF($B$10="3BR_H", INDEX('ns-combined'!$C:$D,MATCH($L31,'ns-combined'!$B:$B,0),MATCH(Council_Area,'ns-combined'!$C$1:$D$1,0))*1000, INDEX('s-combined'!$C:$D,MATCH($L31,'s-combined'!$B:$B,0),MATCH(Council_Area,'s-combined'!$C$1:$D$1,0))*1000) -> 395000 | AS31: =AS30+$AS$3 -> 20300 | AT31: 0 | AU31: =SUM($B$28:$B$29)*AR31 -> 7900 | AV31: =AR31*$B$15/4 -> 1135.625 | AW31: =SUM($AV$3:AV31) -> 30271.737 | AX31: =AR31-AS31-AU31-AW31 -> 336528.26 | AY31: =$B$36*V31 -> 1485 | AZ31: =SUM(AY31:AY31)*4/AR31 -> 0.015037975 | BA31: =SUM(AY31:AY31)/V31 -> 0.35 | BB31: =IF(MortgageRate="Discounted",_xlfn.XLOOKUP(L31,'mortgage-rates'!$A:$A,'mortgage-rates'!$E:$E)/100,_xlfn.XLOOKUP(L31,'mortgage-rates'!$A:$A,'mortgage-rates'!$D:$D)/100) -> 0.0562 | BC31: =BC30-BF30 -> 193193.51 | BD31: =IF($B$16*12/3-Q31+1>0,-PMT($BB31/4,$B$16*12/3-Q31+1,BC31),0) -> 4282.7301 | BE31: =BC31*($BB31/4) -> 2714.3688 | BF31: =BD31-BE31 -> 1568.3613 | BG31: =AT31+AY31+BD31 -> 5767.7301 | BH31: =INDEX(cpi!B:B,MATCH($L31,cpi!A:A)) -> 102.4 | BI31: =100*BH31/BH$3 -> 121.04019 | BJ31: =100*AC31/AC$3 -> 125.60296 | BK31: =100*AD31/AD$3 -> 132.36398 | BL31: =BJ31*GlobalPortfolio+BK31*AusPortfolio -> 127.63126 | BM31: =100*AE31/$AE$3 -> 217.46308 | BN31: =100*AR31/AR$3 -> 141.07143 | BO31: =100*AX31/AX$3 -> 123.31786
A32: Council rates | B32: 0.07 | C32: 0.07 | L32: =DATE(YEAR(L31),MONTH(L31)+3,1) -> 41426 | M32: =AP32 -> 171887.64 | N32: =AX32-BC32 -> 143067.49 | O32: =M32/N32 -> 1.2014444 | P32: =X32/BG32 -> 0.7773571 | Q32: 30 | R32: =EOMONTH(L32,0)-EOMONTH(L32,-3) -> 91 | T32: =IF($B$10="3BR_H", INDEX('3BR_H-processed'!$E:$F,MATCH($L32,'3BR_H-processed'!$B:$B,0),MATCH(Council_Area,'3BR_H-processed'!$E$1:$F$1,0)), INDEX('2BR_F-processed'!$E:$F,MATCH($L32,'2BR_F-processed'!$B:$B,0),MATCH(Council_Area,'2BR_F-processed'!$E$1:$F$1,0))) -> 320 | U32: =IF(MOD(Q32,4)=1,T32,U31) -> 330 | V32: =U32*(R32)/7 -> 4290 | W32: =$B$53/4*BH32/_xlfn.XLOOKUP(Q_end,cpi!A:A,cpi!B:B) -> 142.22529 | X32: =V32+W32 -> 4432.2253 | Y32: =BG32-X32 -> 1269.4339 | Z32: =Y32*$B$47 -> 0 | AA32: {=(Y32+Z32)*eff_invest} -> 1269.4339 | AB32: =AA32*(_xlfn.XLOOKUP(Q_end,cpi!A:A,cpi!B:B)/BH32) -> 1785.1029 | AC32: {=INDEX('msci-indices'!C:C,MATCH($L32,'msci-indices'!$B:$B)-2)} -> 1024.7053 | AD32: {=INDEX('msci-indices'!D:D,MATCH($L32,'msci-indices'!$B:$B)-2)} -> 1021.5673 | AE32: =AI31+AA32 -> 172996.25 | AF32: {=INDEX('msci-indices'!C:C,MATCH($L32,'msci-indices'!$B:$B)+1)} -> 1030.5184 | AG32: {=INDEX('msci-indices'!D:D,MATCH($L32,'msci-indices'!$B:$B)+1)} -> 988.35138 | AH32: =(InvestFees/4)*AE32 -> 108.12266 | AI32: =((AF32/AC32)*GlobalPortfolio+(AG32/AD32)*AusPortfolio)*AE32-AH32 -> 171887.64 | AJ32: =AJ31+AA32 -> 133595.41 | AK32: =AI32-AJ32 -> 38292.227 | AL32: =AJ32*(_xlfn.XLOOKUP(Q_end,cpi!A:A,cpi!B:B)/BH32) -> 187864.49 | AM32: {=SUMPRODUCT($AA$3:AA32,_xlfn.SORTBY($BH$3:BH32,_xlfn.SEQUENCE(ROWS($BH$3:BH32)),-1)/$BH$3)} -> 156993.52 | AN32: =AI32-AM32 -> 14894.12 | AO32: =IF($B$49="Real gains",MAX($B$50*AN32,0),IF($B$49="Discounted nominal gains",MAX($B$50*AK32/2,0),0)) -> 0 | AP32: =AI32-AO32 -> 171887.64 | AR32: =IF($B$10="3BR_H", INDEX('ns-combined'!$C:$D,MATCH($L32,'ns-combined'!$B:$B,0),MATCH(Council_Area,'ns-combined'!$C$1:$D$1,0))*1000, INDEX('s-combined'!$C:$D,MATCH($L32,'s-combined'!$B:$B,0),MATCH(Council_Area,'s-combined'!$C$1:$D$1,0))*1000) -> 395000 | AS32: =AS31+$AS$3 -> 21000 | AT32: 0 | AU32: =SUM($B$28:$B$29)*AR32 -> 7900 | AV32: =AR32*$B$15/4 -> 1135.625 | AW32: =SUM($AV$3:AV32) -> 31407.362 | AX32: =AR32-AS32-AU32-AW32 -> 334692.64 | AY32: =$B$36*V32 -> 1501.5 | AZ32: =SUM(AY32:AY32)*4/AR32 -> 0.015205063 | BA32: =SUM(AY32:AY32)/V32 -> 0.35 | BB32: =IF(MortgageRate="Discounted",_xlfn.XLOOKUP(L32,'mortgage-rates'!$A:$A,'mortgage-rates'!$E:$E)/100,_xlfn.XLOOKUP(L32,'mortgage-rates'!$A:$A,'mortgage-rates'!$D:$D)/100) -> 0.0536 | BC32: =BC31-BF31 -> 191625.15 | BD32: =IF($B$16*12/3-Q32+1>0,-PMT($BB32/4,$B$16*12/3-Q32+1,BC32),0) -> 4200.1592 | BE32: =BC32*($BB32/4) -> 2567.777 | BF32: =BD32-BE32 -> 1632.3822 | BG32: =AT32+AY32+BD32 -> 5701.6592 | BH32: =INDEX(cpi!B:B,MATCH($L32,cpi!A:A)) -> 102.9 | BI32: =100*BH32/BH$3 -> 121.63121 | BJ32: =100*AC32/AC$3 -> 135.7442 | BK32: =100*AD32/AD$3 -> 143.28611 | BL32: =BJ32*GlobalPortfolio+BK32*AusPortfolio -> 138.00677 | BM32: =100*AE32/$AE$3 -> 236.73823 | BN32: =100*AR32/AR$3 -> 141.07143 | BO32: =100*AX32/AX$3 -> 122.64521
A33: Maintenance incl. body corporate fees | B33: 0.16 | C33: 0.16 | L33: =DATE(YEAR(L32),MONTH(L32)+3,1) -> 41518 | M33: =AP33 -> 188639.33 | N33: =AX33-BC33 -> 142864.25 | O33: =M33/N33 -> 1.3204097 | P33: =X33/BG33 -> 0.79570112 | Q33: 31 | R33: =EOMONTH(L33,0)-EOMONTH(L33,-3) -> 92 | T33: =IF($B$10="3BR_H", INDEX('3BR_H-processed'!$E:$F,MATCH($L33,'3BR_H-processed'!$B:$B,0),MATCH(Council_Area,'3BR_H-processed'!$E$1:$F$1,0)), INDEX('2BR_F-processed'!$E:$F,MATCH($L33,'2BR_F-processed'!$B:$B,0),MATCH(Council_Area,'2BR_F-processed'!$E$1:$F$1,0))) -> 325 | U33: =IF(MOD(Q33,4)=1,T33,U32) -> 330 | V33: =U33*(R33)/7 -> 4337.1429 | W33: =$B$53/4*BH33/_xlfn.XLOOKUP(Q_end,cpi!A:A,cpi!B:B) -> 143.60746 | X33: =V33+W33 -> 4480.7503 | Y33: =BG33-X33 -> 1150.4474 | Z33: =Y33*$B$47 -> 0 | AA33: {=(Y33+Z33)*eff_invest} -> 1150.4474 | AB33: =AA33*(_xlfn.XLOOKUP(Q_end,cpi!A:A,cpi!B:B)/BH33) -> 1602.2111 | AC33: {=INDEX('msci-indices'!C:C,MATCH($L33,'msci-indices'!$B:$B)-2)} -> 1030.5184 | AD33: {=INDEX('msci-indices'!D:D,MATCH($L33,'msci-indices'!$B:$B)-2)} -> 988.35138 | AE33: =AI32+AA33 -> 173038.08 | AF33: {=INDEX('msci-indices'!C:C,MATCH($L33,'msci-indices'!$B:$B)+1)} -> 1119.4371 | AG33: {=INDEX('msci-indices'!D:D,MATCH($L33,'msci-indices'!$B:$B)+1)} -> 1088.4582 | AH33: =(InvestFees/4)*AE33 -> 108.1488 | AI33: =((AF33/AC33)*GlobalPortfolio+(AG33/AD33)*AusPortfolio)*AE33-AH33 -> 188639.33 | AJ33: =AJ32+AA33 -> 134745.86 | AK33: =AI33-AJ33 -> 53893.474 | AL33: =AJ33*(_xlfn.XLOOKUP(Q_end,cpi!A:A,cpi!B:B)/BH33) -> 187658.57 | AM33: {=SUMPRODUCT($AA$3:AA33,_xlfn.SORTBY($BH$3:BH33,_xlfn.SEQUENCE(ROWS($BH$3:BH33)),-1)/$BH$3)} -> 159455.75 | AN33: =AI33-AM33 -> 29183.582 | AO33: =IF($B$49="Real gains",MAX($B$50*AN33,0),IF($B$49="Discounted nominal gains",MAX($B$50*AK33/2,0),0)) -> 0 | AP33: =AI33-AO33 -> 188639.33 | AR33: =IF($B$10="3BR_H", INDEX('ns-combined'!$C:$D,MATCH($L33,'ns-combined'!$B:$B,0),MATCH(Council_Area,'ns-combined'!$C$1:$D$1,0))*1000, INDEX('s-combined'!$C:$D,MATCH($L33,'s-combined'!$B:$B,0),MATCH(Council_Area,'s-combined'!$C$1:$D$1,0))*1000) -> 395000 | AS33: =AS32+$AS$3 -> 21700 | AT33: 0 | AU33: =SUM($B$28:$B$29)*AR33 -> 7900 | AV33: =AR33*$B$15/4 -> 1135.625 | AW33: =SUM($AV$3:AV33) -> 32542.987 | AX33: =AR33-AS33-AU33-AW33 -> 332857.01 | AY33: =$B$36*V33 -> 1518 | AZ33: =SUM(AY33:AY33)*4/AR33 -> 0.015372152 | BA33: =SUM(AY33:AY33)/V33 -> 0.35 | BB33: =IF(MortgageRate="Discounted",_xlfn.XLOOKUP(L33,'mortgage-rates'!$A:$A,'mortgage-rates'!$E:$E)/100,_xlfn.XLOOKUP(L33,'mortgage-rates'!$A:$A,'mortgage-rates'!$D:$D)/100) -> 0.0508 | BC33: =BC32-BF32 -> 189992.77 | BD33: =IF($B$16*12/3-Q33+1>0,-PMT($BB33/4,$B$16*12/3-Q33+1,BC33),0) -> 4113.1977 | BE33: =BC33*($BB33/4) -> 2412.9081 | BF33: =BD33-BE33 -> 1700.2895 | BG33: =AT33+AY33+BD33 -> 5631.1977 | BH33: =INDEX(cpi!B:B,MATCH($L33,cpi!A:A)) -> 103.9 | BI33: =100*BH33/BH$3 -> 122.81324 | BJ33: =100*AC33/AC$3 -> 136.51427 | BK33: =100*AD33/AD$3 -> 138.62721 | BL33: =BJ33*GlobalPortfolio+BK33*AusPortfolio -> 137.14815 | BM33: =100*AE33/$AE$3 -> 236.79547 | BN33: =100*AR33/AR$3 -> 141.07143 | BO33: =100*AX33/AX$3 -> 121.97256
A34: Plant depreciation | B34: 0.07 | C34: 0.07 | L34: =DATE(YEAR(L33),MONTH(L33)+3,1) -> 41609 | M34: =AP34 -> 202099.04 | N34: =AX34-BC34 -> 159340.03 | O34: =M34/N34 -> 1.2683507 | P34: =X34/BG34 -> 0.79503537 | Q34: 32 | R34: =EOMONTH(L34,0)-EOMONTH(L34,-3) -> 92 | T34: =IF($B$10="3BR_H", INDEX('3BR_H-processed'!$E:$F,MATCH($L34,'3BR_H-processed'!$B:$B,0),MATCH(Council_Area,'3BR_H-processed'!$E$1:$F$1,0)), INDEX('2BR_F-processed'!$E:$F,MATCH($L34,'2BR_F-processed'!$B:$B,0),MATCH(Council_Area,'2BR_F-processed'!$E$1:$F$1,0))) -> 327.5 | U34: =IF(MOD(Q34,4)=1,T34,U33) -> 330 | V34: =U34*(R34)/7 -> 4337.1429 | W34: =$B$53/4*BH34/_xlfn.XLOOKUP(Q_end,cpi!A:A,cpi!B:B) -> 144.7132 | X34: =V34+W34 -> 4481.8561 | Y34: =BG34-X34 -> 1155.4479 | Z34: =Y34*$B$47 -> 0 | AA34: {=(Y34+Z34)*eff_invest} -> 1155.4479 | AB34: =AA34*(_xlfn.XLOOKUP(Q_end,cpi!A:A,cpi!B:B)/BH34) -> 1596.8798 | AC34: {=INDEX('msci-indices'!C:C,MATCH($L34,'msci-indices'!$B:$B)-2)} -> 1119.4371 | AD34: {=INDEX('msci-indices'!D:D,MATCH($L34,'msci-indices'!$B:$B)-2)} -> 1088.4582 | AE34: =AI33+AA34 -> 189794.78 | AF34: {=INDEX('msci-indices'!C:C,MATCH($L34,'msci-indices'!$B:$B)+1)} -> 1208.1074 | AG34: {=INDEX('msci-indices'!D:D,MATCH($L34,'msci-indices'!$B:$B)+1)} -> 1124.7671 | AH34: =(InvestFees/4)*AE34 -> 118.62174 | AI34: =((AF34/AC34)*GlobalPortfolio+(AG34/AD34)*AusPortfolio)*AE34-AH34 -> 202099.04 | AJ34: =AJ33+AA34 -> 135901.3 | AK34: =AI34-AJ34 -> 66197.735 | AL34: =AJ34*(_xlfn.XLOOKUP(Q_end,cpi!A:A,cpi!B:B)/BH34) -> 187821.57 | AM34: {=SUMPRODUCT($AA$3:AA34,_xlfn.SORTBY($BH$3:BH34,_xlfn.SEQUENCE(ROWS($BH$3:BH34)),-1)/$BH$3)} -> 161756.14 | AN34: =AI34-AM34 -> 40342.895 | AO34: =IF($B$49="Real gains",MAX($B$50*AN34,0),IF($B$49="Discounted nominal gains",MAX($B$50*AK34/2,0),0)) -> 0 | AP34: =AI34-AO34 -> 202099.04 | AR34: =IF($B$10="3BR_H", INDEX('ns-combined'!$C:$D,MATCH($L34,'ns-combined'!$B:$B,0),MATCH(Council_Area,'ns-combined'!$C$1:$D$1,0))*1000, INDEX('s-combined'!$C:$D,MATCH($L34,'s-combined'!$B:$B,0),MATCH(Council_Area,'s-combined'!$C$1:$D$1,0))*1000) -> 412000 | AS34: =AS33+$AS$3 -> 22400 | AT34: 0 | AU34: =SUM($B$28:$B$29)*AR34 -> 8240 | AV34: =AR34*$B$15/4 -> 1184.5 | AW34: =SUM($AV$3:AV34) -> 33727.488 | AX34: =AR34-AS34-AU34-AW34 -> 347632.51 | AY34: =$B$36*V34 -> 1518 | AZ34: =SUM(AY34:AY34)*4/AR34 -> 0.014737864 | BA34: =SUM(AY34:AY34)/V34 -> 0.35 | BB34: =IF(MortgageRate="Discounted",_xlfn.XLOOKUP(L34,'mortgage-rates'!$A:$A,'mortgage-rates'!$E:$E)/100,_xlfn.XLOOKUP(L34,'mortgage-rates'!$A:$A,'mortgage-rates'!$D:$D)/100) -> 0.051 | BC34: =BC33-BF33 -> 188292.48 | BD34: =IF($B$16*12/3-Q34+1>0,-PMT($BB34/4,$B$16*12/3-Q34+1,BC34),0) -> 4119.304 | BE34: =BC34*($BB34/4) -> 2400.7291 | BF34: =BD34-BE34 -> 1718.5749 | BG34: =AT34+AY34+BD34 -> 5637.304 | BH34: =INDEX(cpi!B:B,MATCH($L34,cpi!A:A)) -> 104.7 | BI34: =100*BH34/BH$3 -> 123.75887 | BJ34: =100*AC34/AC$3 -> 148.29346 | BK34: =100*AD34/AD$3 -> 152.6683 | BL34: =BJ34*GlobalPortfolio+BK34*AusPortfolio -> 149.60591 | BM34: =100*AE34/$AE$3 -> 259.72632 | BN34: =100*AR34/AR$3 -> 147.14286 | BO34: =100*AX34/AX$3 -> 127.38691
A35: Other expenses | B35: 0.05 | C35: 0.05 | L35: =DATE(YEAR(L34),MONTH(L34)+3,1) -> 41699 | M35: =AP35 -> 206623.31 | N35: =AX35-BC35 -> 154288.48 | O35: =M35/N35 -> 1.3392011 | P35: =X35/BG35 -> 0.78390956 | Q35: 33 | R35: =EOMONTH(L35,0)-EOMONTH(L35,-3) -> 90 | T35: =IF($B$10="3BR_H", INDEX('3BR_H-processed'!$E:$F,MATCH($L35,'3BR_H-processed'!$B:$B,0),MATCH(Council_Area,'3BR_H-processed'!$E$1:$F$1,0)), INDEX('2BR_F-processed'!$E:$F,MATCH($L35,'2BR_F-processed'!$B:$B,0),MATCH(Council_Area,'2BR_F-processed'!$E$1:$F$1,0))) -> 330 | U35: =IF(MOD(Q35,4)=1,T35,U34) -> 330 | V35: =U35*(R35)/7 -> 4242.8571 | W35: =$B$53/4*BH35/_xlfn.XLOOKUP(Q_end,cpi!A:A,cpi!B:B) -> 145.68072 | X35: =V35+W35 -> 4388.5379 | Y35: =BG35-X35 -> 1209.7328 | Z35: =Y35*$B$47 -> 0 | AA35: {=(Y35+Z35)*eff_invest} -> 1209.7328 | AB35: =AA35*(_xlfn.XLOOKUP(Q_end,cpi!A:A,cpi!B:B)/BH35) -> 1660.8001 | AC35: {=INDEX('msci-indices'!C:C,MATCH($L35,'msci-indices'!$B:$B)-2)} -> 1208.1074 | AD35: {=INDEX('msci-indices'!D:D,MATCH($L35,'msci-indices'!$B:$B)-2)} -> 1124.7671 | AE35: =AI34+AA35 -> 203308.77 | AF35: {=INDEX('msci-indices'!C:C,MATCH($L35,'msci-indices'!$B:$B)+1)} -> 1225.92 | AG35: {=INDEX('msci-indices'!D:D,MATCH($L35,'msci-indices'!$B:$B)+1)} -> 1149.5384 | AH35: =(InvestFees/4)*AE35 -> 127.06798 | AI35: =((AF35/AC35)*GlobalPortfolio+(AG35/AD35)*AusPortfolio)*AE35-AH35 -> 206623.31 | AJ35: =AJ34+AA35 -> 137111.04 | AK35: =AI35-AJ35 -> 69512.276 | AL35: =AJ35*(_xlfn.XLOOKUP(Q_end,cpi!A:A,cpi!B:B)/BH35) -> 188234.98 | AM35: {=SUMPRODUCT($AA$3:AA35,_xlfn.SORTBY($BH$3:BH35,_xlfn.SEQUENCE(ROWS($BH$3:BH35)),-1)/$BH$3)} -> 164027.94 | AN35: =AI35-AM35 -> 42595.375 | AO35: =IF($B$49="Real gains",MAX($B$50*AN35,0),IF($B$49="Discounted nominal gains",MAX($B$50*AK35/2,0),0)) -> 0 | AP35: =AI35-AO35 -> 206623.31 | AR35: =IF($B$10="3BR_H", INDEX('ns-combined'!$C:$D,MATCH($L35,'ns-combined'!$B:$B,0),MATCH(Council_Area,'ns-combined'!$C$1:$D$1,0))*1000, INDEX('s-combined'!$C:$D,MATCH($L35,'s-combined'!$B:$B,0),MATCH(Council_Area,'s-combined'!$C$1:$D$1,0))*1000) -> 407000 | AS35: =AS34+$AS$3 -> 23100 | AT35: 0 | AU35: =SUM($B$28:$B$29)*AR35 -> 8140 | AV35: =AR35*$B$15/4 -> 1170.125 | AW35: =SUM($AV$3:AV35) -> 34897.613 | AX35: =AR35-AS35-AU35-AW35 -> 340862.39 | AY35: =$B$36*V35 -> 1485 | AZ35: =SUM(AY35:AY35)*4/AR35 -> 0.014594595 | BA35: =SUM(AY35:AY35)/V35 -> 0.35 | BB35: =IF(MortgageRate="Discounted",_xlfn.XLOOKUP(L35,'mortgage-rates'!$A:$A,'mortgage-rates'!$E:$E)/100,_xlfn.XLOOKUP(L35,'mortgage-rates'!$A:$A,'mortgage-rates'!$D:$D)/100) -> 0.0508 | BC35: =BC34-BF34 -> 186573.9 | BD35: =IF($B$16*12/3-Q35+1>0,-PMT($BB35/4,$B$16*12/3-Q35+1,BC35),0) -> 4113.2706 | BE35: =BC35*($BB35/4) -> 2369.4886 | BF35: =BD35-BE35 -> 1743.7821 | BG35: =AT35+AY35+BD35 -> 5598.2706 | BH35: =INDEX(cpi!B:B,MATCH($L35,cpi!A:A)) -> 105.4 | BI35: =100*BH35/BH$3 -> 124.58629 | BJ35: =100*AC35/AC$3 -> 160.03975 | BK35: =100*AD35/AD$3 -> 157.76103 | BL35: =BJ35*GlobalPortfolio+BK35*AusPortfolio -> 159.35613 | BM35: =100*AE35/$AE$3 -> 278.21966 | BN35: =100*AR35/AR$3 -> 145.35714 | BO35: =100*AX35/AX$3 -> 124.90606
A36: Total home ownership running costs | B36: =SUM(B32:B35) -> 0.35 | C36: 0.35 | L36: =DATE(YEAR(L35),MONTH(L35)+3,1) -> 41791 | M36: =AP36 -> 214913.04 | N36: =AX36-BC36 -> 152207.89 | O36: =M36/N36 -> 1.4119704 | P36: =X36/BG36 -> 0.79017444 | Q36: 34 | R36: =EOMONTH(L36,0)-EOMONTH(L36,-3) -> 91 | T36: =IF($B$10="3BR_H", INDEX('3BR_H-processed'!$E:$F,MATCH($L36,'3BR_H-processed'!$B:$B,0),MATCH(Council_Area,'3BR_H-processed'!$E$1:$F$1,0)), INDEX('2BR_F-processed'!$E:$F,MATCH($L36,'2BR_F-processed'!$B:$B,0),MATCH(Council_Area,'2BR_F-processed'!$E$1:$F$1,0))) -> 340 | U36: =IF(MOD(Q36,4)=1,T36,U35) -> 330 | V36: =U36*(R36)/7 -> 4290 | W36: =$B$53/4*BH36/_xlfn.XLOOKUP(Q_end,cpi!A:A,cpi!B:B) -> 146.64824 | X36: =V36+W36 -> 4436.6482 | Y36: =BG36-X36 -> 1178.1224 | Z36: =Y36*$B$47 -> 0 | AA36: {=(Y36+Z36)*eff_invest} -> 1178.1224 | AB36: =AA36*(_xlfn.XLOOKUP(Q_end,cpi!A:A,cpi!B:B)/BH36) -> 1606.7324 | AC36: {=INDEX('msci-indices'!C:C,MATCH($L36,'msci-indices'!$B:$B)-2)} -> 1225.92 | AD36: {=INDEX('msci-indices'!D:D,MATCH($L36,'msci-indices'!$B:$B)-2)} -> 1149.5384 | AE36: =AI35+AA36 -> 207801.43 | AF36: {=INDEX('msci-indices'!C:C,MATCH($L36,'msci-indices'!$B:$B)+1)} -> 1282.9431 | AG36: {=INDEX('msci-indices'!D:D,MATCH($L36,'msci-indices'!$B:$B)+1)} -> 1158.3053 | AH36: =(InvestFees/4)*AE36 -> 129.8759 | AI36: =((AF36/AC36)*GlobalPortfolio+(AG36/AD36)*AusPortfolio)*AE36-AH36 -> 214913.04 | AJ36: =AJ35+AA36 -> 138289.16 | AK36: =AI36-AJ36 -> 76623.88 | AL36: =AJ36*(_xlfn.XLOOKUP(Q_end,cpi!A:A,cpi!B:B)/BH36) -> 188599.82 | AM36: {=SUMPRODUCT($AA$3:AA36,_xlfn.SORTBY($BH$3:BH36,_xlfn.SEQUENCE(ROWS($BH$3:BH36)),-1)/$BH$3)} -> 166282.35 | AN36: =AI36-AM36 -> 48630.686 | AO36: =IF($B$49="Real gains",MAX($B$50*AN36,0),IF($B$49="Discounted nominal gains",MAX($B$50*AK36/2,0),0)) -> 0 | AP36: =AI36-AO36 -> 214913.04 | AR36: =IF($B$10="3BR_H", INDEX('ns-combined'!$C:$D,MATCH($L36,'ns-combined'!$B:$B,0),MATCH(Council_Area,'ns-combined'!$C$1:$D$1,0))*1000, INDEX('s-combined'!$C:$D,MATCH($L36,'s-combined'!$B:$B,0),MATCH(Council_Area,'s-combined'!$C$1:$D$1,0))*1000) -> 405000 | AS36: =AS35+$AS$3 -> 23800 | AT36: 0 | AU36: =SUM($B$28:$B$29)*AR36 -> 8100 | AV36: =AR36*$B$15/4 -> 1164.375 | AW36: =SUM($AV$3:AV36) -> 36061.988 | AX36: =AR36-AS36-AU36-AW36 -> 337038.01 | AY36: =$B$36*V36 -> 1501.5 | AZ36: =SUM(AY36:AY36)*4/AR36 -> 0.01482963 | BA36: =SUM(AY36:AY36)/V36 -> 0.35 | BB36: =IF(MortgageRate="Discounted",_xlfn.XLOOKUP(L36,'mortgage-rates'!$A:$A,'mortgage-rates'!$E:$E)/100,_xlfn.XLOOKUP(L36,'mortgage-rates'!$A:$A,'mortgage-rates'!$D:$D)/100) -> 0.0508 | BC36: =BC35-BF35 -> 184830.12 | BD36: =IF($B$16*12/3-Q36+1>0,-PMT($BB36/4,$B$16*12/3-Q36+1,BC36),0) -> 4113.2706 | BE36: =BC36*($BB36/4) -> 2347.3425 | BF36: =BD36-BE36 -> 1765.9281 | BG36: =AT36+AY36+BD36 -> 5614.7706 | BH36: =INDEX(cpi!B:B,MATCH($L36,cpi!A:A)) -> 106.1 | BI36: =100*BH36/BH$3 -> 125.41371 | BJ36: =100*AC36/AC$3 -> 162.39941 | BK36: =100*AD36/AD$3 -> 161.23548 | BL36: =BJ36*GlobalPortfolio+BK36*AusPortfolio -> 162.05023 | BM36: =100*AE36/$AE$3 -> 284.36768 | BN36: =100*AR36/AR$3 -> 144.64286 | BO36: =100*AX36/AX$3 -> 123.50465
A37: Average maint + reno spending (% home value) | B37: {=AVERAGE(_xlfn._xlws.FILTER($AZ$3:$AZ$82,ISNUMBER($AZ$3:$AZ$82)))} -> 0.013949375 | C37: 0.011405453 | L37: =DATE(YEAR(L36),MONTH(L36)+3,1) -> 41883 | M37: =AP37 -> 211292.63 | N37: =AX37-BC37 -> 156995.07 | O37: =M37/N37 -> 1.3458552 | P37: =X37/BG37 -> 0.79627989 | Q37: 35 | R37: =EOMONTH(L37,0)-EOMONTH(L37,-3) -> 92 | T37: =IF($B$10="3BR_H", INDEX('3BR_H-processed'!$E:$F,MATCH($L37,'3BR_H-processed'!$B:$B,0),MATCH(Council_Area,'3BR_H-processed'!$E$1:$F$1,0)), INDEX('2BR_F-processed'!$E:$F,MATCH($L37,'2BR_F-processed'!$B:$B,0),MATCH(Council_Area,'2BR_F-processed'!$E$1:$F$1,0))) -> 330 | U37: =IF(MOD(Q37,4)=1,T37,U36) -> 330 | V37: =U37*(R37)/7 -> 4337.1429 | W37: =$B$53/4*BH37/_xlfn.XLOOKUP(Q_end,cpi!A:A,cpi!B:B) -> 146.92467 | X37: =V37+W37 -> 4484.0675 | Y37: =BG37-X37 -> 1147.2031 | Z37: =Y37*$B$47 -> 0 | AA37: {=(Y37+Z37)*eff_invest} -> 1147.2031 | AB37: =AA37*(_xlfn.XLOOKUP(Q_end,cpi!A:A,cpi!B:B)/BH37) -> 1561.6208 | AC37: {=INDEX('msci-indices'!C:C,MATCH($L37,'msci-indices'!$B:$B)-2)} -> 1282.9431 | AD37: {=INDEX('msci-indices'!D:D,MATCH($L37,'msci-indices'!$B:$B)-2)} -> 1158.3053 | AE37: =AI36+AA37 -> 216060.24 | AF37: {=INDEX('msci-indices'!C:C,MATCH($L37,'msci-indices'!$B:$B)+1)} -> 1247.2922 | AG37: {=INDEX('msci-indices'!D:D,MATCH($L37,'msci-indices'!$B:$B)+1)} -> 1150.6246 | AH37: =(InvestFees/4)*AE37 -> 135.03765 | AI37: =((AF37/AC37)*GlobalPortfolio+(AG37/AD37)*AusPortfolio)*AE37-AH37 -> 211292.63 | AJ37: =AJ36+AA37 -> 139436.36 | AK37: =AI37-AJ37 -> 71856.269 | AL37: =AJ37*(_xlfn.XLOOKUP(Q_end,cpi!A:A,cpi!B:B)/BH37) -> 189806.6 | AM37: {=SUMPRODUCT($AA$3:AA37,_xlfn.SORTBY($BH$3:BH37,_xlfn.SEQUENCE(ROWS($BH$3:BH37)),-1)/$BH$3)} -> 168091.65 | AN37: =AI37-AM37 -> 43200.979 | AO37: =IF($B$49="Real gains",MAX($B$50*AN37,0),IF($B$49="Discounted nominal gains",MAX($B$50*AK37/2,0),0)) -> 0 | AP37: =AI37-AO37 -> 211292.63 | AR37: =IF($B$10="3BR_H", INDEX('ns-combined'!$C:$D,MATCH($L37,'ns-combined'!$B:$B,0),MATCH(Council_Area,'ns-combined'!$C$1:$D$1,0))*1000, INDEX('s-combined'!$C:$D,MATCH($L37,'s-combined'!$B:$B,0),MATCH(Council_Area,'s-combined'!$C$1:$D$1,0))*1000) -> 410000 | AS37: =AS36+$AS$3 -> 24500 | AT37: 0 | AU37: =SUM($B$28:$B$29)*AR37 -> 8200 | AV37: =AR37*$B$15/4 -> 1178.75 | AW37: =SUM($AV$3:AV37) -> 37240.738 | AX37: =AR37-AS37-AU37-AW37 -> 340059.26 | AY37: =$B$36*V37 -> 1518 | AZ37: =SUM(AY37:AY37)*4/AR37 -> 0.014809756 | BA37: =SUM(AY37:AY37)/V37 -> 0.35 | BB37: =IF(MortgageRate="Discounted",_xlfn.XLOOKUP(L37,'mortgage-rates'!$A:$A,'mortgage-rates'!$E:$E)/100,_xlfn.XLOOKUP(L37,'mortgage-rates'!$A:$A,'mortgage-rates'!$D:$D)/100) -> 0.0508 | BC37: =BC36-BF36 -> 183064.19 | BD37: =IF($B$16*12/3-Q37+1>0,-PMT($BB37/4,$B$16*12/3-Q37+1,BC37),0) -> 4113.2706 | BE37: =BC37*($BB37/4) -> 2324.9152 | BF37: =BD37-BE37 -> 1788.3554 | BG37: =AT37+AY37+BD37 -> 5631.2706 | BH37: =INDEX(cpi!B:B,MATCH($L37,cpi!A:A)) -> 106.3 | BI37: =100*BH37/BH$3 -> 125.65012 | BJ37: =100*AC37/AC$3 -> 169.95334 | BK37: =100*AD37/AD$3 -> 162.46513 | BL37: =BJ37*GlobalPortfolio+BK37*AusPortfolio -> 167.70687 | BM37: =100*AE37/$AE$3 -> 295.66952 | BN37: =100*AR37/AR$3 -> 146.42857 | BO37: =100*AX37/AX$3 -> 124.61176
A38: Average maint + reno spending (% rents) | B38: {=AVERAGE(_xlfn._xlws.FILTER($BA$3:$BA$82,ISNUMBER($BA$3:$BA$82)))} -> 0.35 | C38: 0.35 | L38: =DATE(YEAR(L37),MONTH(L37)+3,1) -> 41974 | M38: =AP38 -> 215843.61 | N38: =AX38-BC38 -> 171561.55 | O38: =M38/N38 -> 1.2581118 | P38: =X38/BG38 -> 0.79632897 | Q38: 36 | R38: =EOMONTH(L38,0)-EOMONTH(L38,-3) -> 92 | T38: =IF($B$10="3BR_H", INDEX('3BR_H-processed'!$E:$F,MATCH($L38,'3BR_H-processed'!$B:$B,0),MATCH(Council_Area,'3BR_H-processed'!$E$1:$F$1,0)), INDEX('2BR_F-processed'!$E:$F,MATCH($L38,'2BR_F-processed'!$B:$B,0),MATCH(Council_Area,'2BR_F-processed'!$E$1:$F$1,0))) -> 330 | U38: =IF(MOD(Q38,4)=1,T38,U37) -> 330 | V38: =U38*(R38)/7 -> 4337.1429 | W38: =$B$53/4*BH38/_xlfn.XLOOKUP(Q_end,cpi!A:A,cpi!B:B) -> 147.20111 | X38: =V38+W38 -> 4484.344 | Y38: =BG38-X38 -> 1146.9267 | Z38: =Y38*$B$47 -> 0 | AA38: {=(Y38+Z38)*eff_invest} -> 1146.9267 | AB38: =AA38*(_xlfn.XLOOKUP(Q_end,cpi!A:A,cpi!B:B)/BH38) -> 1558.3126 | AC38: {=INDEX('msci-indices'!C:C,MATCH($L38,'msci-indices'!$B:$B)-2)} -> 1247.2922 | AD38: {=INDEX('msci-indices'!D:D,MATCH($L38,'msci-indices'!$B:$B)-2)} -> 1150.6246 | AE38: =AI37+AA38 -> 212439.56 | AF38: {=INDEX('msci-indices'!C:C,MATCH($L38,'msci-indices'!$B:$B)+1)} -> 1262.6926 | AG38: {=INDEX('msci-indices'!D:D,MATCH($L38,'msci-indices'!$B:$B)+1)} -> 1181.3297 | AH38: =(InvestFees/4)*AE38 -> 132.77472 | AI38: =((AF38/AC38)*GlobalPortfolio+(AG38/AD38)*AusPortfolio)*AE38-AH38 -> 215843.61 | AJ38: =AJ37+AA38 -> 140583.29 | AK38: =AI38-AJ38 -> 75260.317 | AL38: =AJ38*(_xlfn.XLOOKUP(Q_end,cpi!A:A,cpi!B:B)/BH38) -> 191008.47 | AM38: {=SUMPRODUCT($AA$3:AA38,_xlfn.SORTBY($BH$3:BH38,_xlfn.SEQUENCE(ROWS($BH$3:BH38)),-1)/$BH$3)} -> 169907.22 | AN38: =AI38-AM38 -> 45936.382 | AO38: =IF($B$49="Real gains",MAX($B$50*AN38,0),IF($B$49="Discounted nominal gains",MAX($B$50*AK38/2,0),0)) -> 0 | AP38: =AI38-AO38 -> 215843.61 | AR38: =IF($B$10="3BR_H", INDEX('ns-combined'!$C:$D,MATCH($L38,'ns-combined'!$B:$B,0),MATCH(Council_Area,'ns-combined'!$C$1:$D$1,0))*1000, INDEX('s-combined'!$C:$D,MATCH($L38,'s-combined'!$B:$B,0),MATCH(Council_Area,'s-combined'!$C$1:$D$1,0))*1000) -> 425000 | AS38: =AS37+$AS$3 -> 25200 | AT38: 0 | AU38: =SUM($B$28:$B$29)*AR38 -> 8500 | AV38: =AR38*$B$15/4 -> 1221.875 | AW38: =SUM($AV$3:AV38) -> 38462.613 | AX38: =AR38-AS38-AU38-AW38 -> 352837.39 | AY38: =$B$36*V38 -> 1518 | AZ38: =SUM(AY38:AY38)*4/AR38 -> 0.014287059 | BA38: =SUM(AY38:AY38)/V38 -> 0.35 | BB38: =IF(MortgageRate="Discounted",_xlfn.XLOOKUP(L38,'mortgage-rates'!$A:$A,'mortgage-rates'!$E:$E)/100,_xlfn.XLOOKUP(L38,'mortgage-rates'!$A:$A,'mortgage-rates'!$D:$D)/100) -> 0.0508 | BC38: =BC37-BF37 -> 181275.84 | BD38: =IF($B$16*12/3-Q38+1>0,-PMT($BB38/4,$B$16*12/3-Q38+1,BC38),0) -> 4113.2706 | BE38: =BC38*($BB38/4) -> 2302.2031 | BF38: =BD38-BE38 -> 1811.0675 | BG38: =AT38+AY38+BD38 -> 5631.2706 | BH38: =INDEX(cpi!B:B,MATCH($L38,cpi!A:A)) -> 106.5 | BI38: =100*BH38/BH$3 -> 125.88652 | BJ38: =100*AC38/AC$3 -> 165.23062 | BK38: =100*AD38/AD$3 -> 161.38783 | BL38: =BJ38*GlobalPortfolio+BK38*AusPortfolio -> 164.07778 | BM38: =100*AE38/$AE$3 -> 290.71476 | BN38: =100*AR38/AR$3 -> 151.78571 | BO38: =100*AX38/AX$3 -> 129.29419
L39: =DATE(YEAR(L38),MONTH(L38)+3,1) -> 42064 | M39: =AP39 -> 227346.41 | N39: =AX39-BC39 -> 162168.06 | O39: =M39/N39 -> 1.4019186 | P39: =X39/BG39 -> 0.81145137 | Q39: 37 | R39: =EOMONTH(L39,0)-EOMONTH(L39,-3) -> 90 | T39: =IF($B$10="3BR_H", INDEX('3BR_H-processed'!$E:$F,MATCH($L39,'3BR_H-processed'!$B:$B,0),MATCH(Council_Area,'3BR_H-processed'!$E$1:$F$1,0)), INDEX('2BR_F-processed'!$E:$F,MATCH($L39,'2BR_F-processed'!$B:$B,0),MATCH(Council_Area,'2BR_F-processed'!$E$1:$F$1,0))) -> 340 | U39: =IF(MOD(Q39,4)=1,T39,U38) -> 340 | V39: =U39*(R39)/7 -> 4371.4286 | W39: =$B$53/4*BH39/_xlfn.XLOOKUP(Q_end,cpi!A:A,cpi!B:B) -> 147.61576 | X39: =V39+W39 -> 4519.0443 | Y39: =BG39-X39 -> 1050.0439 | Z39: =Y39*$B$47 -> 0 | AA39: {=(Y39+Z39)*eff_invest} -> 1050.0439 | AB39: =AA39*(_xlfn.XLOOKUP(Q_end,cpi!A:A,cpi!B:B)/BH39) -> 1422.6719 | AC39: {=INDEX('msci-indices'!C:C,MATCH($L39,'msci-indices'!$B:$B)-2)} -> 1262.6926 | AD39: {=INDEX('msci-indices'!D:D,MATCH($L39,'msci-indices'!$B:$B)-2)} -> 1181.3297 | AE39: =AI38+AA39 -> 216893.65 | AF39: {=INDEX('msci-indices'!C:C,MATCH($L39,'msci-indices'!$B:$B)+1)} -> 1295.5073 | AG39: {=INDEX('msci-indices'!D:D,MATCH($L39,'msci-indices'!$B:$B)+1)} -> 1301.9298 | AH39: =(InvestFees/4)*AE39 -> 135.55853 | AI39: =((AF39/AC39)*GlobalPortfolio+(AG39/AD39)*AusPortfolio)*AE39-AH39 -> 227346.41 | AJ39: =AJ38+AA39 -> 141633.33 | AK39: =AI39-AJ39 -> 85713.076 | AL39: =AJ39*(_xlfn.XLOOKUP(Q_end,cpi!A:A,cpi!B:B)/BH39) -> 191894.6 | AM39: {=SUMPRODUCT($AA$3:AA39,_xlfn.SORTBY($BH$3:BH39,_xlfn.SEQUENCE(ROWS($BH$3:BH39)),-1)/$BH$3)} -> 171711.33 | AN39: =AI39-AM39 -> 55635.077 | AO39: =IF($B$49="Real gains",MAX($B$50*AN39,0),IF($B$49="Discounted nominal gains",MAX($B$50*AK39/2,0),0)) -> 0 | AP39: =AI39-AO39 -> 227346.41 | AR39: =IF($B$10="3BR_H", INDEX('ns-combined'!$C:$D,MATCH($L39,'ns-combined'!$B:$B,0),MATCH(Council_Area,'ns-combined'!$C$1:$D$1,0))*1000, INDEX('s-combined'!$C:$D,MATCH($L39,'s-combined'!$B:$B,0),MATCH(Council_Area,'s-combined'!$C$1:$D$1,0))*1000) -> 415500 | AS39: =AS38+$AS$3 -> 25900 | AT39: 0 | AU39: =SUM($B$28:$B$29)*AR39 -> 8310 | AV39: =AR39*$B$15/4 -> 1194.5625 | AW39: =SUM($AV$3:AV39) -> 39657.175 | AX39: =AR39-AS39-AU39-AW39 -> 341632.83 | AY39: =$B$36*V39 -> 1530 | AZ39: =SUM(AY39:AY39)*4/AR39 -> 0.014729242 | BA39: =SUM(AY39:AY39)/V39 -> 0.35 | BB39: =IF(MortgageRate="Discounted",_xlfn.XLOOKUP(L39,'mortgage-rates'!$A:$A,'mortgage-rates'!$E:$E)/100,_xlfn.XLOOKUP(L39,'mortgage-rates'!$A:$A,'mortgage-rates'!$D:$D)/100) -> 0.0482 | BC39: =BC38-BF38 -> 179464.77 | BD39: =IF($B$16*12/3-Q39+1>0,-PMT($BB39/4,$B$16*12/3-Q39+1,BC39),0) -> 4039.0883 | BE39: =BC39*($BB39/4) -> 2162.5505 | BF39: =BD39-BE39 -> 1876.5378 | BG39: =AT39+AY39+BD39 -> 5569.0883 | BH39: =INDEX(cpi!B:B,MATCH($L39,cpi!A:A)) -> 106.8 | BI39: =100*BH39/BH$3 -> 126.24113 | BJ39: =100*AC39/AC$3 -> 167.27073 | BK39: =100*AD39/AD$3 -> 165.69455 | BL39: =BJ39*GlobalPortfolio+BK39*AusPortfolio -> 166.79788 | BM39: =100*AE39/$AE$3 -> 296.81 | BN39: =100*AR39/AR$3 -> 148.39286 | BO39: =100*AX39/AX$3 -> 125.18838
A40: Renter investment parameters | L40: =DATE(YEAR(L39),MONTH(L39)+3,1) -> 42156 | M40: =AP40 -> 224354.43 | N40: =AX40-BC40 -> 166547.09 | O40: =M40/N40 -> 1.3470931 | P40: =X40/BG40 -> 0.82408061 | Q40: 38 | R40: =EOMONTH(L40,0)-EOMONTH(L40,-3) -> 91 | T40: =IF($B$10="3BR_H", INDEX('3BR_H-processed'!$E:$F,MATCH($L40,'3BR_H-processed'!$B:$B,0),MATCH(Council_Area,'3BR_H-processed'!$E$1:$F$1,0)), INDEX('2BR_F-processed'!$E:$F,MATCH($L40,'2BR_F-processed'!$B:$B,0),MATCH(Council_Area,'2BR_F-processed'!$E$1:$F$1,0))) -> 340 | U40: =IF(MOD(Q40,4)=1,T40,U39) -> 340 | V40: =U40*(R40)/7 -> 4420 | W40: =$B$53/4*BH40/_xlfn.XLOOKUP(Q_end,cpi!A:A,cpi!B:B) -> 148.85971 | X40: =V40+W40 -> 4568.8597 | Y40: =BG40-X40 -> 975.33059 | Z40: =Y40*$B$47 -> 0 | AA40: {=(Y40+Z40)*eff_invest} -> 975.33059 | AB40: =AA40*(_xlfn.XLOOKUP(Q_end,cpi!A:A,cpi!B:B)/BH40) -> 1310.4024 | AC40: {=INDEX('msci-indices'!C:C,MATCH($L40,'msci-indices'!$B:$B)-2)} -> 1295.5073 | AD40: {=INDEX('msci-indices'!D:D,MATCH($L40,'msci-indices'!$B:$B)-2)} -> 1301.9298 | AE40: =AI39+AA40 -> 228321.74 | AF40: {=INDEX('msci-indices'!C:C,MATCH($L40,'msci-indices'!$B:$B)+1)} -> 1301.507 | AG40: {=INDEX('msci-indices'!D:D,MATCH($L40,'msci-indices'!$B:$B)+1)} -> 1215.1659 | AH40: =(InvestFees/4)*AE40 -> 142.70109 | AI40: =((AF40/AC40)*GlobalPortfolio+(AG40/AD40)*AusPortfolio)*AE40-AH40 -> 224354.43 | AJ40: =AJ39+AA40 -> 142608.66 | AK40: =AI40-AJ40 -> 81745.771 | AL40: =AJ40*(_xlfn.XLOOKUP(Q_end,cpi!A:A,cpi!B:B)/BH40) -> 191601.43 | AM40: {=SUMPRODUCT($AA$3:AA40,_xlfn.SORTBY($BH$3:BH40,_xlfn.SEQUENCE(ROWS($BH$3:BH40)),-1)/$BH$3)} -> 173951.32 | AN40: =AI40-AM40 -> 50403.117 | AO40: =IF($B$49="Real gains",MAX($B$50*AN40,0),IF($B$49="Discounted nominal gains",MAX($B$50*AK40/2,0),0)) -> 0 | AP40: =AI40-AO40 -> 224354.43 | AR40: =IF($B$10="3BR_H", INDEX('ns-combined'!$C:$D,MATCH($L40,'ns-combined'!$B:$B,0),MATCH(Council_Area,'ns-combined'!$C$1:$D$1,0))*1000, INDEX('s-combined'!$C:$D,MATCH($L40,'s-combined'!$B:$B,0),MATCH(Council_Area,'s-combined'!$C$1:$D$1,0))*1000) -> 420000 | AS40: =AS39+$AS$3 -> 26600 | AT40: 0 | AU40: =SUM($B$28:$B$29)*AR40 -> 8400 | AV40: =AR40*$B$15/4 -> 1207.5 | AW40: =SUM($AV$3:AV40) -> 40864.675 | AX40: =AR40-AS40-AU40-AW40 -> 344135.33 | AY40: =$B$36*V40 -> 1547 | AZ40: =SUM(AY40:AY40)*4/AR40 -> 0.014733333 | BA40: =SUM(AY40:AY40)/V40 -> 0.35 | BB40: =IF(MortgageRate="Discounted",_xlfn.XLOOKUP(L40,'mortgage-rates'!$A:$A,'mortgage-rates'!$E:$E)/100,_xlfn.XLOOKUP(L40,'mortgage-rates'!$A:$A,'mortgage-rates'!$D:$D)/100) -> 0.0467 | BC40: =BC39-BF39 -> 177588.23 | BD40: =IF($B$16*12/3-Q40+1>0,-PMT($BB40/4,$B$16*12/3-Q40+1,BC40),0) -> 3997.1903 | BE40: =BC40*($BB40/4) -> 2073.3426 | BF40: =BD40-BE40 -> 1923.8477 | BG40: =AT40+AY40+BD40 -> 5544.1903 | BH40: =INDEX(cpi!B:B,MATCH($L40,cpi!A:A)) -> 107.7 | BI40: =100*BH40/BH$3 -> 127.30496 | BJ40: =100*AC40/AC$3 -> 171.61773 | BK40: =100*AD40/AD$3 -> 182.61006 | BL40: =BJ40*GlobalPortfolio+BK40*AusPortfolio -> 174.91543 | BM40: =100*AE40/$AE$3 -> 312.44887 | BN40: =100*AR40/AR$3 -> 150 | BO40: =100*AX40/AX$3 -> 126.1054
A41: % of portfolio in global equities | B41: 0.7 | C41: 0.7 | L41: =DATE(YEAR(L40),MONTH(L40)+3,1) -> 42248 | M41: =AP41 -> 206887.81 | N41: =AX41-BC41 -> 173891.88 | O41: =M41/N41 -> 1.1897497 | P41: =X41/BG41 -> 0.83073066 | Q41: 39 | R41: =EOMONTH(L41,0)-EOMONTH(L41,-3) -> 92 | T41: =IF($B$10="3BR_H", INDEX('3BR_H-processed'!$E:$F,MATCH($L41,'3BR_H-processed'!$B:$B,0),MATCH(Council_Area,'3BR_H-processed'!$E$1:$F$1,0)), INDEX('2BR_F-processed'!$E:$F,MATCH($L41,'2BR_F-processed'!$B:$B,0),MATCH(Council_Area,'2BR_F-processed'!$E$1:$F$1,0))) -> 340 | U41: =IF(MOD(Q41,4)=1,T41,U40) -> 340 | V41: =U41*(R41)/7 -> 4468.5714 | W41: =$B$53/4*BH41/_xlfn.XLOOKUP(Q_end,cpi!A:A,cpi!B:B) -> 148.99793 | X41: =V41+W41 -> 4617.5694 | Y41: =BG41-X41 -> 940.87406 | Z41: =Y41*$B$47 -> 0 | AA41: {=(Y41+Z41)*eff_invest} -> 940.87406 | AB41: =AA41*(_xlfn.XLOOKUP(Q_end,cpi!A:A,cpi!B:B)/BH41) -> 1262.9358 | AC41: {=INDEX('msci-indices'!C:C,MATCH($L41,'msci-indices'!$B:$B)-2)} -> 1301.507 | AD41: {=INDEX('msci-indices'!D:D,MATCH($L41,'msci-indices'!$B:$B)-2)} -> 1215.1659 | AE41: =AI40+AA41 -> 225295.31 | AF41: {=INDEX('msci-indices'!C:C,MATCH($L41,'msci-indices'!$B:$B)+1)} -> 1189.2855 | AG41: {=INDEX('msci-indices'!D:D,MATCH($L41,'msci-indices'!$B:$B)+1)} -> 1131.2309 | AH41: =(InvestFees/4)*AE41 -> 140.80957 | AI41: =((AF41/AC41)*GlobalPortfolio+(AG41/AD41)*AusPortfolio)*AE41-AH41 -> 206887.81 | AJ41: =AJ40+AA41 -> 143549.54 | AK41: =AI41-AJ41 -> 63338.277 | AL41: =AJ41*(_xlfn.XLOOKUP(Q_end,cpi!A:A,cpi!B:B)/BH41) -> 192686.62 | AM41: {=SUMPRODUCT($AA$3:AA41,_xlfn.SORTBY($BH$3:BH41,_xlfn.SEQUENCE(ROWS($BH$3:BH41)),-1)/$BH$3)} -> 175480.52 | AN41: =AI41-AM41 -> 31407.299 | AO41: =IF($B$49="Real gains",MAX($B$50*AN41,0),IF($B$49="Discounted nominal gains",MAX($B$50*AK41/2,0),0)) -> 0 | AP41: =AI41-AO41 -> 206887.81 | AR41: =IF($B$10="3BR_H", INDEX('ns-combined'!$C:$D,MATCH($L41,'ns-combined'!$B:$B,0),MATCH(Council_Area,'ns-combined'!$C$1:$D$1,0))*1000, INDEX('s-combined'!$C:$D,MATCH($L41,'s-combined'!$B:$B,0),MATCH(Council_Area,'s-combined'!$C$1:$D$1,0))*1000) -> 427500 | AS41: =AS40+$AS$3 -> 27300 | AT41: 0 | AU41: =SUM($B$28:$B$29)*AR41 -> 8550 | AV41: =AR41*$B$15/4 -> 1229.0625 | AW41: =SUM($AV$3:AV41) -> 42093.738 | AX41: =AR41-AS41-AU41-AW41 -> 349556.26 | AY41: =$B$36*V41 -> 1564 | AZ41: =SUM(AY41:AY41)*4/AR41 -> 0.014633918 | BA41: =SUM(AY41:AY41)/V41 -> 0.35 | BB41: =IF(MortgageRate="Discounted",_xlfn.XLOOKUP(L41,'mortgage-rates'!$A:$A,'mortgage-rates'!$E:$E)/100,_xlfn.XLOOKUP(L41,'mortgage-rates'!$A:$A,'mortgage-rates'!$D:$D)/100) -> 0.0466 | BC41: =BC40-BF40 -> 175664.38 | BD41: =IF($B$16*12/3-Q41+1>0,-PMT($BB41/4,$B$16*12/3-Q41+1,BC41),0) -> 3994.4434 | BE41: =BC41*($BB41/4) -> 2046.4901 | BF41: =BD41-BE41 -> 1947.9533 | BG41: =AT41+AY41+BD41 -> 5558.4434 | BH41: =INDEX(cpi!B:B,MATCH($L41,cpi!A:A)) -> 107.8 | BI41: =100*BH41/BH$3 -> 127.42317 | BJ41: =100*AC41/AC$3 -> 172.41252 | BK41: =100*AD41/AD$3 -> 170.44046 | BL41: =BJ41*GlobalPortfolio+BK41*AusPortfolio -> 171.8209 | BM41: =100*AE41/$AE$3 -> 308.30733 | BN41: =100*AR41/AR$3 -> 152.67857 | BO41: =100*AX41/AX$3 -> 128.09185
A42: % of portfolio in Australian equities | B42: =1-GlobalPortfolio -> 0.3 | C42: 0.3 | L42: =DATE(YEAR(L41),MONTH(L41)+3,1) -> 42339 | M42: =AP42 -> 219517.3 | N42: =AX42-BC42 -> 182216.33 | O42: =M42/N42 -> 1.204707 | P42: =X42/BG42 -> 0.82400702 | Q42: 40 | R42: =EOMONTH(L42,0)-EOMONTH(L42,-3) -> 92 | T42: =IF($B$10="3BR_H", INDEX('3BR_H-processed'!$E:$F,MATCH($L42,'3BR_H-processed'!$B:$B,0),MATCH(Council_Area,'3BR_H-processed'!$E$1:$F$1,0)), INDEX('2BR_F-processed'!$E:$F,MATCH($L42,'2BR_F-processed'!$B:$B,0),MATCH(Council_Area,'2BR_F-processed'!$E$1:$F$1,0))) -> 330 | U42: =IF(MOD(Q42,4)=1,T42,U41) -> 340 | V42: =U42*(R42)/7 -> 4468.5714 | W42: =$B$53/4*BH42/_xlfn.XLOOKUP(Q_end,cpi!A:A,cpi!B:B) -> 149.68901 | X42: =V42+W42 -> 4618.2604 | Y42: =BG42-X42 -> 986.3768 | Z42: =Y42*$B$47 -> 0 | AA42: {=(Y42+Z42)*eff_invest} -> 986.3768 | AB42: =AA42*(_xlfn.XLOOKUP(Q_end,cpi!A:A,cpi!B:B)/BH42) -> 1317.9014 | AC42: {=INDEX('msci-indices'!C:C,MATCH($L42,'msci-indices'!$B:$B)-2)} -> 1189.2855 | AD42: {=INDEX('msci-indices'!D:D,MATCH($L42,'msci-indices'!$B:$B)-2)} -> 1131.2309 | AE42: =AI41+AA42 -> 207874.19 | AF42: {=INDEX('msci-indices'!C:C,MATCH($L42,'msci-indices'!$B:$B)+1)} -> 1252.6491 | AG42: {=INDEX('msci-indices'!D:D,MATCH($L42,'msci-indices'!$B:$B)+1)} -> 1204.1585 | AH42: =(InvestFees/4)*AE42 -> 129.92137 | AI42: =((AF42/AC42)*GlobalPortfolio+(AG42/AD42)*AusPortfolio)*AE42-AH42 -> 219517.3 | AJ42: =AJ41+AA42 -> 144535.91 | AK42: =AI42-AJ42 -> 74981.384 | AL42: =AJ42*(_xlfn.XLOOKUP(Q_end,cpi!A:A,cpi!B:B)/BH42) -> 193114.93 | AM42: {=SUMPRODUCT($AA$3:AA42,_xlfn.SORTBY($BH$3:BH42,_xlfn.SEQUENCE(ROWS($BH$3:BH42)),-1)/$BH$3)} -> 177395.32 | AN42: =AI42-AM42 -> 42121.982 | AO42: =IF($B$49="Real gains",MAX($B$50*AN42,0),IF($B$49="Discounted nominal gains",MAX($B$50*AK42/2,0),0)) -> 0 | AP42: =AI42-AO42 -> 219517.3 | AR42: =IF($B$10="3BR_H", INDEX('ns-combined'!$C:$D,MATCH($L42,'ns-combined'!$B:$B,0),MATCH(Council_Area,'ns-combined'!$C$1:$D$1,0))*1000, INDEX('s-combined'!$C:$D,MATCH($L42,'s-combined'!$B:$B,0),MATCH(Council_Area,'s-combined'!$C$1:$D$1,0))*1000) -> 436000 | AS42: =AS41+$AS$3 -> 28000 | AT42: 0 | AU42: =SUM($B$28:$B$29)*AR42 -> 8720 | AV42: =AR42*$B$15/4 -> 1253.5 | AW42: =SUM($AV$3:AV42) -> 43347.238 | AX42: =AR42-AS42-AU42-AW42 -> 355932.76 | AY42: =$B$36*V42 -> 1564 | AZ42: =SUM(AY42:AY42)*4/AR42 -> 0.014348624 | BA42: =SUM(AY42:AY42)/V42 -> 0.35 | BB42: =IF(MortgageRate="Discounted",_xlfn.XLOOKUP(L42,'mortgage-rates'!$A:$A,'mortgage-rates'!$E:$E)/100,_xlfn.XLOOKUP(L42,'mortgage-rates'!$A:$A,'mortgage-rates'!$D:$D)/100) -> 0.0483 | BC42: =BC41-BF41 -> 173716.43 | BD42: =IF($B$16*12/3-Q42+1>0,-PMT($BB42/4,$B$16*12/3-Q42+1,BC42),0) -> 4040.6372 | BE42: =BC42*($BB42/4) -> 2097.6259 | BF42: =BD42-BE42 -> 1943.0113 | BG42: =AT42+AY42+BD42 -> 5604.6372 | BH42: =INDEX(cpi!B:B,MATCH($L42,cpi!A:A)) -> 108.3 | BI42: =100*BH42/BH$3 -> 128.01418 | BJ42: =100*AC42/AC$3 -> 157.54638 | BK42: =100*AD42/AD$3 -> 158.66765 | BL42: =BJ42*GlobalPortfolio+BK42*AusPortfolio -> 157.88276 | BM42: =100*AE42/$AE$3 -> 284.46725 | BN42: =100*AR42/AR$3 -> 155.71429 | BO42: =100*AX42/AX$3 -> 130.42847
A43: Investment fees (% of investment value per year) | B43: 0.0025 | C43: 0.0025 | L43: =DATE(YEAR(L42),MONTH(L42)+3,1) -> 42430 | M43: =AP43 -> 218241.15 | N43: =AX43-BC43 -> 182205.84 | O43: =M43/N43 -> 1.1977725 | P43: =X43/BG43 -> 0.81945589 | Q43: 41 | R43: =EOMONTH(L43,0)-EOMONTH(L43,-3) -> 91 | T43: =IF($B$10="3BR_H", INDEX('3BR_H-processed'!$E:$F,MATCH($L43,'3BR_H-processed'!$B:$B,0),MATCH(Council_Area,'3BR_H-processed'!$E$1:$F$1,0)), INDEX('2BR_F-processed'!$E:$F,MATCH($L43,'2BR_F-processed'!$B:$B,0),MATCH(Council_Area,'2BR_F-processed'!$E$1:$F$1,0))) -> 341 | U43: =IF(MOD(Q43,4)=1,T43,U42) -> 341 | V43: =U43*(R43)/7 -> 4433 | W43: =$B$53/4*BH43/_xlfn.XLOOKUP(Q_end,cpi!A:A,cpi!B:B) -> 149.55079 | X43: =V43+W43 -> 4582.5508 | Y43: =BG43-X43 -> 1009.6364 | Z43: =Y43*$B$47 -> 0 | AA43: {=(Y43+Z43)*eff_invest} -> 1009.6364 | AB43: =AA43*(_xlfn.XLOOKUP(Q_end,cpi!A:A,cpi!B:B)/BH43) -> 1350.2255 | AC43: {=INDEX('msci-indices'!C:C,MATCH($L43,'msci-indices'!$B:$B)-2)} -> 1252.6491 | AD43: {=INDEX('msci-indices'!D:D,MATCH($L43,'msci-indices'!$B:$B)-2)} -> 1204.1585 | AE43: =AI42+AA43 -> 220526.94 | AF43: {=INDEX('msci-indices'!C:C,MATCH($L43,'msci-indices'!$B:$B)+1)} -> 1249.9269 | AG43: {=INDEX('msci-indices'!D:D,MATCH($L43,'msci-indices'!$B:$B)+1)} -> 1171.169 | AH43: =(InvestFees/4)*AE43 -> 137.82933 | AI43: =((AF43/AC43)*GlobalPortfolio+(AG43/AD43)*AusPortfolio)*AE43-AH43 -> 218241.15 | AJ43: =AJ42+AA43 -> 145545.55 | AK43: =AI43-AJ43 -> 72695.598 | AL43: =AJ43*(_xlfn.XLOOKUP(Q_end,cpi!A:A,cpi!B:B)/BH43) -> 194643.63 | AM43: {=SUMPRODUCT($AA$3:AA43,_xlfn.SORTBY($BH$3:BH43,_xlfn.SEQUENCE(ROWS($BH$3:BH43)),-1)/$BH$3)} -> 178822.24 | AN43: =AI43-AM43 -> 39418.905 | AO43: =IF($B$49="Real gains",MAX($B$50*AN43,0),IF($B$49="Discounted nominal gains",MAX($B$50*AK43/2,0),0)) -> 0 | AP43: =AI43-AO43 -> 218241.15 | AR43: =IF($B$10="3BR_H", INDEX('ns-combined'!$C:$D,MATCH($L43,'ns-combined'!$B:$B,0),MATCH(Council_Area,'ns-combined'!$C$1:$D$1,0))*1000, INDEX('s-combined'!$C:$D,MATCH($L43,'s-combined'!$B:$B,0),MATCH(Council_Area,'s-combined'!$C$1:$D$1,0))*1000) -> 436000 | AS43: =AS42+$AS$3 -> 28700 | AT43: 0 | AU43: =SUM($B$28:$B$29)*AR43 -> 8720 | AV43: =AR43*$B$15/4 -> 1253.5 | AW43: =SUM($AV$3:AV43) -> 44600.738 | AX43: =AR43-AS43-AU43-AW43 -> 353979.26 | AY43: =$B$36*V43 -> 1551.55 | AZ43: =SUM(AY43:AY43)*4/AR43 -> 0.014234404 | BA43: =SUM(AY43:AY43)/V43 -> 0.35 | BB43: =IF(MortgageRate="Discounted",_xlfn.XLOOKUP(L43,'mortgage-rates'!$A:$A,'mortgage-rates'!$E:$E)/100,_xlfn.XLOOKUP(L43,'mortgage-rates'!$A:$A,'mortgage-rates'!$D:$D)/100) -> 0.0483 | BC43: =BC42-BF42 -> 171773.42 | BD43: =IF($B$16*12/3-Q43+1>0,-PMT($BB43/4,$B$16*12/3-Q43+1,BC43),0) -> 4040.6372 | BE43: =BC43*($BB43/4) -> 2074.164 | BF43: =BD43-BE43 -> 1966.4732 | BG43: =AT43+AY43+BD43 -> 5592.1872 | BH43: =INDEX(cpi!B:B,MATCH($L43,cpi!A:A)) -> 108.2 | BI43: =100*BH43/BH$3 -> 127.89598 | BJ43: =100*AC43/AC$3 -> 165.94025 | BK43: =100*AD43/AD$3 -> 168.89654 | BL43: =BJ43*GlobalPortfolio+BK43*AusPortfolio -> 166.82714 | BM43: =100*AE43/$AE$3 -> 301.782 | BN43: =100*AR43/AR$3 -> 155.71429 | BO43: =100*AX43/AX$3 -> 129.71262
A44: Investing through superannuation? | B44: No | C44: No | L44: =DATE(YEAR(L43),MONTH(L43)+3,1) -> 42522 | M44: =AP44 -> 223374.46 | N44: =AX44-BC44 -> 186127.32 | O44: =M44/N44 -> 1.2001165 | P44: =X44/BG44 -> 0.82898979 | Q44: 42 | R44: =EOMONTH(L44,0)-EOMONTH(L44,-3) -> 91 | T44: =IF($B$10="3BR_H", INDEX('3BR_H-processed'!$E:$F,MATCH($L44,'3BR_H-processed'!$B:$B,0),MATCH(Council_Area,'3BR_H-processed'!$E$1:$F$1,0)), INDEX('2BR_F-processed'!$E:$F,MATCH($L44,'2BR_F-processed'!$B:$B,0),MATCH(Council_Area,'2BR_F-processed'!$E$1:$F$1,0))) -> 335 | U44: =IF(MOD(Q44,4)=1,T44,U43) -> 341 | V44: =U44*(R44)/7 -> 4433 | W44: =$B$53/4*BH44/_xlfn.XLOOKUP(Q_end,cpi!A:A,cpi!B:B) -> 150.3801 | X44: =V44+W44 -> 4583.3801 | Y44: =BG44-X44 -> 945.49388 | Z44: =Y44*$B$47 -> 0 | AA44: {=(Y44+Z44)*eff_invest} -> 945.49388 | AB44: =AA44*(_xlfn.XLOOKUP(Q_end,cpi!A:A,cpi!B:B)/BH44) -> 1257.4721 | AC44: {=INDEX('msci-indices'!C:C,MATCH($L44,'msci-indices'!$B:$B)-2)} -> 1249.9269 | AD44: {=INDEX('msci-indices'!D:D,MATCH($L44,'msci-indices'!$B:$B)-2)} -> 1171.169 | AE44: =AI43+AA44 -> 219186.64 | AF44: {=INDEX('msci-indices'!C:C,MATCH($L44,'msci-indices'!$B:$B)+1)} -> 1263.5195 | AG44: {=INDEX('msci-indices'!D:D,MATCH($L44,'msci-indices'!$B:$B)+1)} -> 1218.4798 | AH44: =(InvestFees/4)*AE44 -> 136.99165 | AI44: =((AF44/AC44)*GlobalPortfolio+(AG44/AD44)*AusPortfolio)*AE44-AH44 -> 223374.46 | AJ44: =AJ43+AA44 -> 146491.04 | AK44: =AI44-AJ44 -> 76883.413 | AL44: =AJ44*(_xlfn.XLOOKUP(Q_end,cpi!A:A,cpi!B:B)/BH44) -> 194827.7 | AM44: {=SUMPRODUCT($AA$3:AA44,_xlfn.SORTBY($BH$3:BH44,_xlfn.SEQUENCE(ROWS($BH$3:BH44)),-1)/$BH$3)} -> 180771.15 | AN44: =AI44-AM44 -> 42603.303 | AO44: =IF($B$49="Real gains",MAX($B$50*AN44,0),IF($B$49="Discounted nominal gains",MAX($B$50*AK44/2,0),0)) -> 0 | AP44: =AI44-AO44 -> 223374.46 | AR44: =IF($B$10="3BR_H", INDEX('ns-combined'!$C:$D,MATCH($L44,'ns-combined'!$B:$B,0),MATCH(Council_Area,'ns-combined'!$C$1:$D$1,0))*1000, INDEX('s-combined'!$C:$D,MATCH($L44,'s-combined'!$B:$B,0),MATCH(Council_Area,'s-combined'!$C$1:$D$1,0))*1000) -> 440000 | AS44: =AS43+$AS$3 -> 29400 | AT44: 0 | AU44: =SUM($B$28:$B$29)*AR44 -> 8800 | AV44: =AR44*$B$15/4 -> 1265 | AW44: =SUM($AV$3:AV44) -> 45865.738 | AX44: =AR44-AS44-AU44-AW44 -> 355934.26 | AY44: =$B$36*V44 -> 1551.55 | AZ44: =SUM(AY44:AY44)*4/AR44 -> 0.014105 | BA44: =SUM(AY44:AY44)/V44 -> 0.35 | BB44: =IF(MortgageRate="Discounted",_xlfn.XLOOKUP(L44,'mortgage-rates'!$A:$A,'mortgage-rates'!$E:$E)/100,_xlfn.XLOOKUP(L44,'mortgage-rates'!$A:$A,'mortgage-rates'!$D:$D)/100) -> 0.0459 | BC44: =BC43-BF43 -> 169806.95 | BD44: =IF($B$16*12/3-Q44+1>0,-PMT($BB44/4,$B$16*12/3-Q44+1,BC44),0) -> 3977.324 | BE44: =BC44*($BB44/4) -> 1948.5347 | BF44: =BD44-BE44 -> 2028.7893 | BG44: =AT44+AY44+BD44 -> 5528.874 | BH44: =INDEX(cpi!B:B,MATCH($L44,cpi!A:A)) -> 108.8 | BI44: =100*BH44/BH$3 -> 128.6052 | BJ44: =100*AC44/AC$3 -> 165.57963 | BK44: =100*AD44/AD$3 -> 164.26941 | BL44: =BJ44*GlobalPortfolio+BK44*AusPortfolio -> 165.18657 | BM44: =100*AE44/$AE$3 -> 299.94787 | BN44: =100*AR44/AR$3 -> 157.14286 | BO44: =100*AX44/AX$3 -> 130.42902
A45: Marginal income tax rate (including Medicare levy) | B45: 0.32 | C45: 0.32 | L45: =DATE(YEAR(L44),MONTH(L44)+3,1) -> 42614 | M45: =AP45 -> 235909.82 | N45: =AX45-BC45 -> 191076.73 | O45: =M45/N45 -> 1.234634 | P45: =X45/BG45 -> 0.83847511 | Q45: 43 | R45: =EOMONTH(L45,0)-EOMONTH(L45,-3) -> 92 | T45: =IF($B$10="3BR_H", INDEX('3BR_H-processed'!$E:$F,MATCH($L45,'3BR_H-processed'!$B:$B,0),MATCH(Council_Area,'3BR_H-processed'!$E$1:$F$1,0)), INDEX('2BR_F-processed'!$E:$F,MATCH($L45,'2BR_F-processed'!$B:$B,0),MATCH(Council_Area,'2BR_F-processed'!$E$1:$F$1,0))) -> 340 | U45: =IF(MOD(Q45,4)=1,T45,U44) -> 341 | V45: =U45*(R45)/7 -> 4481.7143 | W45: =$B$53/4*BH45/_xlfn.XLOOKUP(Q_end,cpi!A:A,cpi!B:B) -> 151.07118 | X45: =V45+W45 -> 4632.7855 | Y45: =BG45-X45 -> 892.46557 | Z45: =Y45*$B$47 -> 0 | AA45: {=(Y45+Z45)*eff_invest} -> 892.46557 | AB45: =AA45*(_xlfn.XLOOKUP(Q_end,cpi!A:A,cpi!B:B)/BH45) -> 1181.5166 | AC45: {=INDEX('msci-indices'!C:C,MATCH($L45,'msci-indices'!$B:$B)-2)} -> 1263.5195 | AD45: {=INDEX('msci-indices'!D:D,MATCH($L45,'msci-indices'!$B:$B)-2)} -> 1218.4798 | AE45: =AI44+AA45 -> 224266.92 | AF45: {=INDEX('msci-indices'!C:C,MATCH($L45,'msci-indices'!$B:$B)+1)} -> 1329.0259 | AG45: {=INDEX('msci-indices'!D:D,MATCH($L45,'msci-indices'!$B:$B)+1)} -> 1284.478 | AH45: =(InvestFees/4)*AE45 -> 140.16683 | AI45: =((AF45/AC45)*GlobalPortfolio+(AG45/AD45)*AusPortfolio)*AE45-AH45 -> 235909.82 | AJ45: =AJ44+AA45 -> 147383.51 | AK45: =AI45-AJ45 -> 88526.314 | AL45: =AJ45*(_xlfn.XLOOKUP(Q_end,cpi!A:A,cpi!B:B)/BH45) -> 195117.97 | AM45: {=SUMPRODUCT($AA$3:AA45,_xlfn.SORTBY($BH$3:BH45,_xlfn.SEQUENCE(ROWS($BH$3:BH45)),-1)/$BH$3)} -> 182578.46 | AN45: =AI45-AM45 -> 53331.36 | AO45: =IF($B$49="Real gains",MAX($B$50*AN45,0),IF($B$49="Discounted nominal gains",MAX($B$50*AK45/2,0),0)) -> 0 | AP45: =AI45-AO45 -> 235909.82 | AR45: =IF($B$10="3BR_H", INDEX('ns-combined'!$C:$D,MATCH($L45,'ns-combined'!$B:$B,0),MATCH(Council_Area,'ns-combined'!$C$1:$D$1,0))*1000, INDEX('s-combined'!$C:$D,MATCH($L45,'s-combined'!$B:$B,0),MATCH(Council_Area,'s-combined'!$C$1:$D$1,0))*1000) -> 445000 | AS45: =AS44+$AS$3 -> 30100 | AT45: 0 | AU45: =SUM($B$28:$B$29)*AR45 -> 8900 | AV45: =AR45*$B$15/4 -> 1279.375 | AW45: =SUM($AV$3:AV45) -> 47145.113 | AX45: =AR45-AS45-AU45-AW45 -> 358854.89 | AY45: =$B$36*V45 -> 1568.6 | AZ45: =SUM(AY45:AY45)*4/AR45 -> 0.014099775 | BA45: =SUM(AY45:AY45)/V45 -> 0.35 | BB45: =IF(MortgageRate="Discounted",_xlfn.XLOOKUP(L45,'mortgage-rates'!$A:$A,'mortgage-rates'!$E:$E)/100,_xlfn.XLOOKUP(L45,'mortgage-rates'!$A:$A,'mortgage-rates'!$D:$D)/100) -> 0.0451 | BC45: =BC44-BF44 -> 167778.16 | BD45: =IF($B$16*12/3-Q45+1>0,-PMT($BB45/4,$B$16*12/3-Q45+1,BC45),0) -> 3956.651 | BE45: =BC45*($BB45/4) -> 1891.6987 | BF45: =BD45-BE45 -> 2064.9523 | BG45: =AT45+AY45+BD45 -> 5525.251 | BH45: =INDEX(cpi!B:B,MATCH($L45,cpi!A:A)) -> 109.3 | BI45: =100*BH45/BH$3 -> 129.19622 | BJ45: =100*AC45/AC$3 -> 167.38027 | BK45: =100*AD45/AD$3 -> 170.90526 | BL45: =BJ45*GlobalPortfolio+BK45*AusPortfolio -> 168.43777 | BM45: =100*AE45/$AE$3 -> 306.90002 | BN45: =100*AR45/AR$3 -> 158.92857 | BO45: =100*AX45/AX$3 -> 131.49925
A46: Concessional super contributions tax rate | B46: 0.15 | C46: 0.15 | L46: =DATE(YEAR(L45),MONTH(L45)+3,1) -> 42705 | M46: =AP46 -> 243906.21 | N46: =AX46-BC46 -> 193116.56 | O46: =M46/N46 -> 1.263 | P46: =X46/BG46 -> 0.83860019 | Q46: 44 | R46: =EOMONTH(L46,0)-EOMONTH(L46,-3) -> 92 | T46: =IF($B$10="3BR_H", INDEX('3BR_H-processed'!$E:$F,MATCH($L46,'3BR_H-processed'!$B:$B,0),MATCH(Council_Area,'3BR_H-processed'!$E$1:$F$1,0)), INDEX('2BR_F-processed'!$E:$F,MATCH($L46,'2BR_F-processed'!$B:$B,0),MATCH(Council_Area,'2BR_F-processed'!$E$1:$F$1,0))) -> 340 | U46: =IF(MOD(Q46,4)=1,T46,U45) -> 341 | V46: =U46*(R46)/7 -> 4481.7143 | W46: =$B$53/4*BH46/_xlfn.XLOOKUP(Q_end,cpi!A:A,cpi!B:B) -> 151.76227 | X46: =V46+W46 -> 4633.4766 | Y46: =BG46-X46 -> 891.77448 | Z46: =Y46*$B$47 -> 0 | AA46: {=(Y46+Z46)*eff_invest} -> 891.77448 | AB46: =AA46*(_xlfn.XLOOKUP(Q_end,cpi!A:A,cpi!B:B)/BH46) -> 1175.2256 | AC46: {=INDEX('msci-indices'!C:C,MATCH($L46,'msci-indices'!$B:$B)-2)} -> 1329.0259 | AD46: {=INDEX('msci-indices'!D:D,MATCH($L46,'msci-indices'!$B:$B)-2)} -> 1284.478 | AE46: =AI45+AA46 -> 236801.6 | AF46: {=INDEX('msci-indices'!C:C,MATCH($L46,'msci-indices'!$B:$B)+1)} -> 1355.3009 | AG46: {=INDEX('msci-indices'!D:D,MATCH($L46,'msci-indices'!$B:$B)+1)} -> 1356.3585 | AH46: =(InvestFees/4)*AE46 -> 148.001 | AI46: =((AF46/AC46)*GlobalPortfolio+(AG46/AD46)*AusPortfolio)*AE46-AH46 -> 243906.21 | AJ46: =AJ45+AA46 -> 148275.28 | AK46: =AI46-AJ46 -> 95630.922 | AL46: =AJ46*(_xlfn.XLOOKUP(Q_end,cpi!A:A,cpi!B:B)/BH46) -> 195404.68 | AM46: {=SUMPRODUCT($AA$3:AA46,_xlfn.SORTBY($BH$3:BH46,_xlfn.SEQUENCE(ROWS($BH$3:BH46)),-1)/$BH$3)} -> 184379.04 | AN46: =AI46-AM46 -> 59527.164 | AO46: =IF($B$49="Real gains",MAX($B$50*AN46,0),IF($B$49="Discounted nominal gains",MAX($B$50*AK46/2,0),0)) -> 0 | AP46: =AI46-AO46 -> 243906.21 | AR46: =IF($B$10="3BR_H", INDEX('ns-combined'!$C:$D,MATCH($L46,'ns-combined'!$B:$B,0),MATCH(Council_Area,'ns-combined'!$C$1:$D$1,0))*1000, INDEX('s-combined'!$C:$D,MATCH($L46,'s-combined'!$B:$B,0),MATCH(Council_Area,'s-combined'!$C$1:$D$1,0))*1000) -> 447000 | AS46: =AS45+$AS$3 -> 30800 | AT46: 0 | AU46: =SUM($B$28:$B$29)*AR46 -> 8940 | AV46: =AR46*$B$15/4 -> 1285.125 | AW46: =SUM($AV$3:AV46) -> 48430.238 | AX46: =AR46-AS46-AU46-AW46 -> 358829.76 | AY46: =$B$36*V46 -> 1568.6 | AZ46: =SUM(AY46:AY46)*4/AR46 -> 0.014036689 | BA46: =SUM(AY46:AY46)/V46 -> 0.35 | BB46: =IF(MortgageRate="Discounted",_xlfn.XLOOKUP(L46,'mortgage-rates'!$A:$A,'mortgage-rates'!$E:$E)/100,_xlfn.XLOOKUP(L46,'mortgage-rates'!$A:$A,'mortgage-rates'!$D:$D)/100) -> 0.0451 | BC46: =BC45-BF45 -> 165713.2 | BD46: =IF($B$16*12/3-Q46+1>0,-PMT($BB46/4,$B$16*12/3-Q46+1,BC46),0) -> 3956.651 | BE46: =BC46*($BB46/4) -> 1868.4164 | BF46: =BD46-BE46 -> 2088.2347 | BG46: =AT46+AY46+BD46 -> 5525.251 | BH46: =INDEX(cpi!B:B,MATCH($L46,cpi!A:A)) -> 109.8 | BI46: =100*BH46/BH$3 -> 129.78723 | BJ46: =100*AC46/AC$3 -> 176.05799 | BK46: =100*AD46/AD$3 -> 180.16225 | BL46: =BJ46*GlobalPortfolio+BK46*AusPortfolio -> 177.28927 | BM46: =100*AE46/$AE$3 -> 324.05321 | BN46: =100*AR46/AR$3 -> 159.64286 | BO46: =100*AX46/AX$3 -> 131.49005
A47: Tax concessions on contributions (0% if not investing through super) | B47: =IF(B44="Yes",B45-B46,0) -> 0 | C47: 0 | L47: =DATE(YEAR(L46),MONTH(L46)+3,1) -> 42795 | M47: =AP47 -> 258963.51 | N47: =AX47-BC47 -> 197421.3 | O47: =M47/N47 -> 1.3117303 | P47: =X47/BG47 -> 0.84034972 | Q47: 45 | R47: =EOMONTH(L47,0)-EOMONTH(L47,-3) -> 90 | T47: =IF($B$10="3BR_H", INDEX('3BR_H-processed'!$E:$F,MATCH($L47,'3BR_H-processed'!$B:$B,0),MATCH(Council_Area,'3BR_H-processed'!$E$1:$F$1,0)), INDEX('2BR_F-processed'!$E:$F,MATCH($L47,'2BR_F-processed'!$B:$B,0),MATCH(Council_Area,'2BR_F-processed'!$E$1:$F$1,0))) -> 350 | U47: =IF(MOD(Q47,4)=1,T47,U46) -> 350 | V47: =U47*(R47)/7 -> 4500 | W47: =$B$53/4*BH47/_xlfn.XLOOKUP(Q_end,cpi!A:A,cpi!B:B) -> 152.72979 | X47: =V47+W47 -> 4652.7298 | Y47: =BG47-X47 -> 883.92914 | Z47: =Y47*$B$47 -> 0 | AA47: {=(Y47+Z47)*eff_invest} -> 883.92914 | AB47: =AA47*(_xlfn.XLOOKUP(Q_end,cpi!A:A,cpi!B:B)/BH47) -> 1157.5072 | AC47: {=INDEX('msci-indices'!C:C,MATCH($L47,'msci-indices'!$B:$B)-2)} -> 1355.3009 | AD47: {=INDEX('msci-indices'!D:D,MATCH($L47,'msci-indices'!$B:$B)-2)} -> 1356.3585 | AE47: =AI46+AA47 -> 244790.14 | AF47: {=INDEX('msci-indices'!C:C,MATCH($L47,'msci-indices'!$B:$B)+1)} -> 1439.618 | AG47: {=INDEX('msci-indices'!D:D,MATCH($L47,'msci-indices'!$B:$B)+1)} -> 1424.0685 | AH47: =(InvestFees/4)*AE47 -> 152.99383 | AI47: =((AF47/AC47)*GlobalPortfolio+(AG47/AD47)*AusPortfolio)*AE47-AH47 -> 258963.51 | AJ47: =AJ46+AA47 -> 149159.21 | AK47: =AI47-AJ47 -> 109804.3 | AL47: =AJ47*(_xlfn.XLOOKUP(Q_end,cpi!A:A,cpi!B:B)/BH47) -> 195324.33 | AM47: {=SUMPRODUCT($AA$3:AA47,_xlfn.SORTBY($BH$3:BH47,_xlfn.SEQUENCE(ROWS($BH$3:BH47)),-1)/$BH$3)} -> 186343.42 | AN47: =AI47-AM47 -> 72620.097 | AO47: =IF($B$49="Real gains",MAX($B$50*AN47,0),IF($B$49="Discounted nominal gains",MAX($B$50*AK47/2,0),0)) -> 0 | AP47: =AI47-AO47 -> 258963.51 | AR47: =IF($B$10="3BR_H", INDEX('ns-combined'!$C:$D,MATCH($L47,'ns-combined'!$B:$B,0),MATCH(Council_Area,'ns-combined'!$C$1:$D$1,0))*1000, INDEX('s-combined'!$C:$D,MATCH($L47,'s-combined'!$B:$B,0),MATCH(Council_Area,'s-combined'!$C$1:$D$1,0))*1000) -> 451300 | AS47: =AS46+$AS$3 -> 31500 | AT47: 0 | AU47: =SUM($B$28:$B$29)*AR47 -> 9026 | AV47: =AR47*$B$15/4 -> 1297.4875 | AW47: =SUM($AV$3:AV47) -> 49727.725 | AX47: =AR47-AS47-AU47-AW47 -> 361046.28 | AY47: =$B$36*V47 -> 1575 | AZ47: =SUM(AY47:AY47)*4/AR47 -> 0.013959672 | BA47: =SUM(AY47:AY47)/V47 -> 0.35 | BB47: =IF(MortgageRate="Discounted",_xlfn.XLOOKUP(L47,'mortgage-rates'!$A:$A,'mortgage-rates'!$E:$E)/100,_xlfn.XLOOKUP(L47,'mortgage-rates'!$A:$A,'mortgage-rates'!$D:$D)/100) -> 0.0453 | BC47: =BC46-BF46 -> 163624.97 | BD47: =IF($B$16*12/3-Q47+1>0,-PMT($BB47/4,$B$16*12/3-Q47+1,BC47),0) -> 3961.6589 | BE47: =BC47*($BB47/4) -> 1853.0528 | BF47: =BD47-BE47 -> 2108.6061 | BG47: =AT47+AY47+BD47 -> 5536.6589 | BH47: =INDEX(cpi!B:B,MATCH($L47,cpi!A:A)) -> 110.5 | BI47: =100*BH47/BH$3 -> 130.61466 | BJ47: =100*AC47/AC$3 -> 179.53868 | BK47: =100*AD47/AD$3 -> 190.24428 | BL47: =BJ47*GlobalPortfolio+BK47*AusPortfolio -> 182.75036 | BM47: =100*AE47/$AE$3 -> 334.98519 | BN47: =100*AR47/AR$3 -> 161.17857 | BO47: =100*AX47/AX$3 -> 132.30227
A48: Marginal income tax rate on withdrawal | B48: 0.32 | C48: 0.32 | L48: =DATE(YEAR(L47),MONTH(L47)+3,1) -> 42887 | M48: =AP48 -> 265524.81 | N48: =AX48-BC48 -> 196262.16 | O48: =M48/N48 -> 1.3529088 | P48: =X48/BG48 -> 0.8486861 | Q48: 46 | R48: =EOMONTH(L48,0)-EOMONTH(L48,-3) -> 91 | T48: =IF($B$10="3BR_H", INDEX('3BR_H-processed'!$E:$F,MATCH($L48,'3BR_H-processed'!$B:$B,0),MATCH(Council_Area,'3BR_H-processed'!$E$1:$F$1,0)), INDEX('2BR_F-processed'!$E:$F,MATCH($L48,'2BR_F-processed'!$B:$B,0),MATCH(Council_Area,'2BR_F-processed'!$E$1:$F$1,0))) -> 340 | U48: =IF(MOD(Q48,4)=1,T48,U47) -> 350 | V48: =U48*(R48)/7 -> 4550 | W48: =$B$53/4*BH48/_xlfn.XLOOKUP(Q_end,cpi!A:A,cpi!B:B) -> 153.28265 | X48: =V48+W48 -> 4703.2827 | Y48: =BG48-X48 -> 838.55747 | Z48: =Y48*$B$47 -> 0 | AA48: {=(Y48+Z48)*eff_invest} -> 838.55747 | AB48: =AA48*(_xlfn.XLOOKUP(Q_end,cpi!A:A,cpi!B:B)/BH48) -> 1094.1322 | AC48: {=INDEX('msci-indices'!C:C,MATCH($L48,'msci-indices'!$B:$B)-2)} -> 1439.618 | AD48: {=INDEX('msci-indices'!D:D,MATCH($L48,'msci-indices'!$B:$B)-2)} -> 1424.0685 | AE48: =AI47+AA48 -> 259802.07 | AF48: {=INDEX('msci-indices'!C:C,MATCH($L48,'msci-indices'!$B:$B)+1)} -> 1498.0163 | AG48: {=INDEX('msci-indices'!D:D,MATCH($L48,'msci-indices'!$B:$B)+1)} -> 1396.8057 | AH48: =(InvestFees/4)*AE48 -> 162.37629 | AI48: =((AF48/AC48)*GlobalPortfolio+(AG48/AD48)*AusPortfolio)*AE48-AH48 -> 265524.81 | AJ48: =AJ47+AA48 -> 149997.77 | AK48: =AI48-AJ48 -> 115527.04 | AL48: =AJ48*(_xlfn.XLOOKUP(Q_end,cpi!A:A,cpi!B:B)/BH48) -> 195713.95 | AM48: {=SUMPRODUCT($AA$3:AA48,_xlfn.SORTBY($BH$3:BH48,_xlfn.SEQUENCE(ROWS($BH$3:BH48)),-1)/$BH$3)} -> 188017.48 | AN48: =AI48-AM48 -> 77507.333 | AO48: =IF($B$49="Real gains",MAX($B$50*AN48,0),IF($B$49="Discounted nominal gains",MAX($B$50*AK48/2,0),0)) -> 0 | AP48: =AI48-AO48 -> 265524.81 | AR48: =IF($B$10="3BR_H", INDEX('ns-combined'!$C:$D,MATCH($L48,'ns-combined'!$B:$B,0),MATCH(Council_Area,'ns-combined'!$C$1:$D$1,0))*1000, INDEX('s-combined'!$C:$D,MATCH($L48,'s-combined'!$B:$B,0),MATCH(Council_Area,'s-combined'!$C$1:$D$1,0))*1000) -> 450000 | AS48: =AS47+$AS$3 -> 32200 | AT48: 0 | AU48: =SUM($B$28:$B$29)*AR48 -> 9000 | AV48: =AR48*$B$15/4 -> 1293.75 | AW48: =SUM($AV$3:AV48) -> 51021.475 | AX48: =AR48-AS48-AU48-AW48 -> 357778.53 | AY48: =$B$36*V48 -> 1592.5 | AZ48: =SUM(AY48:AY48)*4/AR48 -> 0.014155556 | BA48: =SUM(AY48:AY48)/V48 -> 0.35 | BB48: =IF(MortgageRate="Discounted",_xlfn.XLOOKUP(L48,'mortgage-rates'!$A:$A,'mortgage-rates'!$E:$E)/100,_xlfn.XLOOKUP(L48,'mortgage-rates'!$A:$A,'mortgage-rates'!$D:$D)/100) -> 0.0448 | BC48: =BC47-BF47 -> 161516.36 | BD48: =IF($B$16*12/3-Q48+1>0,-PMT($BB48/4,$B$16*12/3-Q48+1,BC48),0) -> 3949.3401 | BE48: =BC48*($BB48/4) -> 1808.9833 | BF48: =BD48-BE48 -> 2140.3568 | BG48: =AT48+AY48+BD48 -> 5541.8401 | BH48: =INDEX(cpi!B:B,MATCH($L48,cpi!A:A)) -> 110.9 | BI48: =100*BH48/BH$3 -> 131.08747 | BJ48: =100*AC48/AC$3 -> 190.70829 | BK48: =100*AD48/AD$3 -> 199.74136 | BL48: =BJ48*GlobalPortfolio+BK48*AusPortfolio -> 193.41821 | BM48: =100*AE48/$AE$3 -> 355.5284 | BN48: =100*AR48/AR$3 -> 160.71429 | BO48: =100*AX48/AX$3 -> 131.10483
A49: Consider CGT? Note: Unlikely to reflect realistic tax liabilities | B49: No | C49: No | L49: =DATE(YEAR(L48),MONTH(L48)+3,1) -> 42979 | M49: =AP49 -> 276347.08 | N49: =AX49-BC49 -> 197385.89 | O49: =M49/N49 -> 1.4000346 | P49: =X49/BG49 -> 0.85548059 | Q49: 47 | R49: =EOMONTH(L49,0)-EOMONTH(L49,-3) -> 92 | T49: =IF($B$10="3BR_H", INDEX('3BR_H-processed'!$E:$F,MATCH($L49,'3BR_H-processed'!$B:$B,0),MATCH(Council_Area,'3BR_H-processed'!$E$1:$F$1,0)), INDEX('2BR_F-processed'!$E:$F,MATCH($L49,'2BR_F-processed'!$B:$B,0),MATCH(Council_Area,'2BR_F-processed'!$E$1:$F$1,0))) -> 345 | U49: =IF(MOD(Q49,4)=1,T49,U48) -> 350 | V49: =U49*(R49)/7 -> 4600 | W49: =$B$53/4*BH49/_xlfn.XLOOKUP(Q_end,cpi!A:A,cpi!B:B) -> 153.83552 | X49: =V49+W49 -> 4753.8355 | Y49: =BG49-X49 -> 803.08251 | Z49: =Y49*$B$47 -> 0 | AA49: {=(Y49+Z49)*eff_invest} -> 803.08251 | AB49: =AA49*(_xlfn.XLOOKUP(Q_end,cpi!A:A,cpi!B:B)/BH49) -> 1044.0794 | AC49: {=INDEX('msci-indices'!C:C,MATCH($L49,'msci-indices'!$B:$B)-2)} -> 1498.0163 | AD49: {=INDEX('msci-indices'!D:D,MATCH($L49,'msci-indices'!$B:$B)-2)} -> 1396.8057 | AE49: =AI48+AA49 -> 266327.89 | AF49: {=INDEX('msci-indices'!C:C,MATCH($L49,'msci-indices'!$B:$B)+1)} -> 1573.3489 | AG49: {=INDEX('msci-indices'!D:D,MATCH($L49,'msci-indices'!$B:$B)+1)} -> 1410.974 | AH49: =(InvestFees/4)*AE49 -> 166.45493 | AI49: =((AF49/AC49)*GlobalPortfolio+(AG49/AD49)*AusPortfolio)*AE49-AH49 -> 276347.08 | AJ49: =AJ48+AA49 -> 150800.85 | AK49: =AI49-AJ49 -> 125546.23 | AL49: =AJ49*(_xlfn.XLOOKUP(Q_end,cpi!A:A,cpi!B:B)/BH49) -> 196054.66 | AM49: {=SUMPRODUCT($AA$3:AA49,_xlfn.SORTBY($BH$3:BH49,_xlfn.SEQUENCE(ROWS($BH$3:BH49)),-1)/$BH$3)} -> 189660.37 | AN49: =AI49-AM49 -> 86686.708 | AO49: =IF($B$49="Real gains",MAX($B$50*AN49,0),IF($B$49="Discounted nominal gains",MAX($B$50*AK49/2,0),0)) -> 0 | AP49: =AI49-AO49 -> 276347.08 | AR49: =IF($B$10="3BR_H", INDEX('ns-combined'!$C:$D,MATCH($L49,'ns-combined'!$B:$B,0),MATCH(Council_Area,'ns-combined'!$C$1:$D$1,0))*1000, INDEX('s-combined'!$C:$D,MATCH($L49,'s-combined'!$B:$B,0),MATCH(Council_Area,'s-combined'!$C$1:$D$1,0))*1000) -> 451000 | AS49: =AS48+$AS$3 -> 32900 | AT49: 0 | AU49: =SUM($B$28:$B$29)*AR49 -> 9020 | AV49: =AR49*$B$15/4 -> 1296.625 | AW49: =SUM($AV$3:AV49) -> 52318.1 | AX49: =AR49-AS49-AU49-AW49 -> 356761.9 | AY49: =$B$36*V49 -> 1610 | AZ49: =SUM(AY49:AY49)*4/AR49 -> 0.014279379 | BA49: =SUM(AY49:AY49)/V49 -> 0.35 | BB49: =IF(MortgageRate="Discounted",_xlfn.XLOOKUP(L49,'mortgage-rates'!$A:$A,'mortgage-rates'!$E:$E)/100,_xlfn.XLOOKUP(L49,'mortgage-rates'!$A:$A,'mortgage-rates'!$D:$D)/100) -> 0.0447 | BC49: =BC48-BF48 -> 159376.01 | BD49: =IF($B$16*12/3-Q49+1>0,-PMT($BB49/4,$B$16*12/3-Q49+1,BC49),0) -> 3946.918 | BE49: =BC49*($BB49/4) -> 1781.0269 | BF49: =BD49-BE49 -> 2165.8912 | BG49: =AT49+AY49+BD49 -> 5556.918 | BH49: =INDEX(cpi!B:B,MATCH($L49,cpi!A:A)) -> 111.3 | BI49: =100*BH49/BH$3 -> 131.56028 | BJ49: =100*AC49/AC$3 -> 198.4444 | BK49: =100*AD49/AD$3 -> 195.91744 | BL49: =BJ49*GlobalPortfolio+BK49*AusPortfolio -> 197.68631 | BM49: =100*AE49/$AE$3 -> 364.45872 | BN49: =100*AR49/AR$3 -> 161.07143 | BO49: =100*AX49/AX$3 -> 130.7323
A50: Marginal CGT & dividend income tax rate (0% if investing through super) | B50: =IF(OR(B44="Yes",B49="No"),0,MAX(0.3,B48)) -> 0 | C50: 0 | L50: =DATE(YEAR(L49),MONTH(L49)+3,1) -> 43070 | M50: =AP50 -> 294105.63 | N50: =AX50-BC50 -> 216120.53 | O50: =M50/N50 -> 1.3608408 | P50: =X50/BG50 -> 0.85421365 | Q50: 48 | R50: =EOMONTH(L50,0)-EOMONTH(L50,-3) -> 92 | T50: =IF($B$10="3BR_H", INDEX('3BR_H-processed'!$E:$F,MATCH($L50,'3BR_H-processed'!$B:$B,0),MATCH(Council_Area,'3BR_H-processed'!$E$1:$F$1,0)), INDEX('2BR_F-processed'!$E:$F,MATCH($L50,'2BR_F-processed'!$B:$B,0),MATCH(Council_Area,'2BR_F-processed'!$E$1:$F$1,0))) -> 345 | U50: =IF(MOD(Q50,4)=1,T50,U49) -> 350 | V50: =U50*(R50)/7 -> 4600 | W50: =$B$53/4*BH50/_xlfn.XLOOKUP(Q_end,cpi!A:A,cpi!B:B) -> 154.94126 | X50: =V50+W50 -> 4754.9413 | Y50: =BG50-X50 -> 811.51307 | Z50: =Y50*$B$47 -> 0 | AA50: {=(Y50+Z50)*eff_invest} -> 811.51307 | AB50: =AA50*(_xlfn.XLOOKUP(Q_end,cpi!A:A,cpi!B:B)/BH50) -> 1047.5106 | AC50: {=INDEX('msci-indices'!C:C,MATCH($L50,'msci-indices'!$B:$B)-2)} -> 1573.3489 | AD50: {=INDEX('msci-indices'!D:D,MATCH($L50,'msci-indices'!$B:$B)-2)} -> 1410.974 | AE50: =AI49+AA50 -> 277158.59 | AF50: {=INDEX('msci-indices'!C:C,MATCH($L50,'msci-indices'!$B:$B)+1)} -> 1659.3666 | AG50: {=INDEX('msci-indices'!D:D,MATCH($L50,'msci-indices'!$B:$B)+1)} -> 1521.5021 | AH50: =(InvestFees/4)*AE50 -> 173.22412 | AI50: =((AF50/AC50)*GlobalPortfolio+(AG50/AD50)*AusPortfolio)*AE50-AH50 -> 294105.63 | AJ50: =AJ49+AA50 -> 151612.37 | AK50: =AI50-AJ50 -> 142493.26 | AL50: =AJ50*(_xlfn.XLOOKUP(Q_end,cpi!A:A,cpi!B:B)/BH50) -> 195703.03 | AM50: {=SUMPRODUCT($AA$3:AA50,_xlfn.SORTBY($BH$3:BH50,_xlfn.SEQUENCE(ROWS($BH$3:BH50)),-1)/$BH$3)} -> 191662.28 | AN50: =AI50-AM50 -> 102443.35 | AO50: =IF($B$49="Real gains",MAX($B$50*AN50,0),IF($B$49="Discounted nominal gains",MAX($B$50*AK50/2,0),0)) -> 0 | AP50: =AI50-AO50 -> 294105.63 | AR50: =IF($B$10="3BR_H", INDEX('ns-combined'!$C:$D,MATCH($L50,'ns-combined'!$B:$B,0),MATCH(Council_Area,'ns-combined'!$C$1:$D$1,0))*1000, INDEX('s-combined'!$C:$D,MATCH($L50,'s-combined'!$B:$B,0),MATCH(Council_Area,'s-combined'!$C$1:$D$1,0))*1000) -> 470000 | AS50: =AS49+$AS$3 -> 33600 | AT50: 0 | AU50: =SUM($B$28:$B$29)*AR50 -> 9400 | AV50: =AR50*$B$15/4 -> 1351.25 | AW50: =SUM($AV$3:AV50) -> 53669.35 | AX50: =AR50-AS50-AU50-AW50 -> 373330.65 | AY50: =$B$36*V50 -> 1610 | AZ50: =SUM(AY50:AY50)*4/AR50 -> 0.013702128 | BA50: =SUM(AY50:AY50)/V50 -> 0.35 | BB50: =IF(MortgageRate="Discounted",_xlfn.XLOOKUP(L50,'mortgage-rates'!$A:$A,'mortgage-rates'!$E:$E)/100,_xlfn.XLOOKUP(L50,'mortgage-rates'!$A:$A,'mortgage-rates'!$D:$D)/100) -> 0.0451 | BC50: =BC49-BF49 -> 157210.12 | BD50: =IF($B$16*12/3-Q50+1>0,-PMT($BB50/4,$B$16*12/3-Q50+1,BC50),0) -> 3956.4543 | BE50: =BC50*($BB50/4) -> 1772.5441 | BF50: =BD50-BE50 -> 2183.9103 | BG50: =AT50+AY50+BD50 -> 5566.4543 | BH50: =INDEX(cpi!B:B,MATCH($L50,cpi!A:A)) -> 112.1 | BI50: =100*BH50/BH$3 -> 132.50591 | BJ50: =100*AC50/AC$3 -> 208.42381 | BK50: =100*AD50/AD$3 -> 197.90471 | BL50: =BJ50*GlobalPortfolio+BK50*AusPortfolio -> 205.26808 | BM50: =100*AE50/$AE$3 -> 379.28009 | BN50: =100*AR50/AR$3 -> 167.85714 | BO50: =100*AX50/AX$3 -> 136.80377
L51: =DATE(YEAR(L50),MONTH(L50)+3,1) -> 43160 | M51: =AP51 -> 288752.27 | N51: =AX51-BC51 -> 211367.57 | O51: =M51/N51 -> 1.3661144 | P51: =X51/BG51 -> 0.85795412 | Q51: 49 | R51: =EOMONTH(L51,0)-EOMONTH(L51,-3) -> 90 | T51: =IF($B$10="3BR_H", INDEX('3BR_H-processed'!$E:$F,MATCH($L51,'3BR_H-processed'!$B:$B,0),MATCH(Council_Area,'3BR_H-processed'!$E$1:$F$1,0)), INDEX('2BR_F-processed'!$E:$F,MATCH($L51,'2BR_F-processed'!$B:$B,0),MATCH(Council_Area,'2BR_F-processed'!$E$1:$F$1,0))) -> 360 | U51: =IF(MOD(Q51,4)=1,T51,U50) -> 360 | V51: =U51*(R51)/7 -> 4628.5714 | W51: =$B$53/4*BH51/_xlfn.XLOOKUP(Q_end,cpi!A:A,cpi!B:B) -> 155.77056 | X51: =V51+W51 -> 4784.342 | Y51: =BG51-X51 -> 792.11234 | Z51: =Y51*$B$47 -> 0 | AA51: {=(Y51+Z51)*eff_invest} -> 792.11234 | AB51: =AA51*(_xlfn.XLOOKUP(Q_end,cpi!A:A,cpi!B:B)/BH51) -> 1017.0244 | AC51: {=INDEX('msci-indices'!C:C,MATCH($L51,'msci-indices'!$B:$B)-2)} -> 1659.3666 | AD51: {=INDEX('msci-indices'!D:D,MATCH($L51,'msci-indices'!$B:$B)-2)} -> 1521.5021 | AE51: =AI50+AA51 -> 294897.74 | AF51: {=INDEX('msci-indices'!C:C,MATCH($L51,'msci-indices'!$B:$B)+1)} -> 1639.7569 | AG51: {=INDEX('msci-indices'!D:D,MATCH($L51,'msci-indices'!$B:$B)+1)} -> 1460.9363 | AH51: =(InvestFees/4)*AE51 -> 184.31109 | AI51: =((AF51/AC51)*GlobalPortfolio+(AG51/AD51)*AusPortfolio)*AE51-AH51 -> 288752.27 | AJ51: =AJ50+AA51 -> 152404.48 | AK51: =AI51-AJ51 -> 136347.79 | AL51: =AJ51*(_xlfn.XLOOKUP(Q_end,cpi!A:A,cpi!B:B)/BH51) -> 195678.16 | AM51: {=SUMPRODUCT($AA$3:AA51,_xlfn.SORTBY($BH$3:BH51,_xlfn.SEQUENCE(ROWS($BH$3:BH51)),-1)/$BH$3)} -> 193483.29 | AN51: =AI51-AM51 -> 95268.983 | AO51: =IF($B$49="Real gains",MAX($B$50*AN51,0),IF($B$49="Discounted nominal gains",MAX($B$50*AK51/2,0),0)) -> 0 | AP51: =AI51-AO51 -> 288752.27 | AR51: =IF($B$10="3BR_H", INDEX('ns-combined'!$C:$D,MATCH($L51,'ns-combined'!$B:$B,0),MATCH(Council_Area,'ns-combined'!$C$1:$D$1,0))*1000, INDEX('s-combined'!$C:$D,MATCH($L51,'s-combined'!$B:$B,0),MATCH(Council_Area,'s-combined'!$C$1:$D$1,0))*1000) -> 465000 | AS51: =AS50+$AS$3 -> 34300 | AT51: 0 | AU51: =SUM($B$28:$B$29)*AR51 -> 9300 | AV51: =AR51*$B$15/4 -> 1336.875 | AW51: =SUM($AV$3:AV51) -> 55006.225 | AX51: =AR51-AS51-AU51-AW51 -> 366393.78 | AY51: =$B$36*V51 -> 1620 | AZ51: =SUM(AY51:AY51)*4/AR51 -> 0.013935484 | BA51: =SUM(AY51:AY51)/V51 -> 0.35 | BB51: =IF(MortgageRate="Discounted",_xlfn.XLOOKUP(L51,'mortgage-rates'!$A:$A,'mortgage-rates'!$E:$E)/100,_xlfn.XLOOKUP(L51,'mortgage-rates'!$A:$A,'mortgage-rates'!$D:$D)/100) -> 0.0451 | BC51: =BC50-BF50 -> 155026.21 | BD51: =IF($B$16*12/3-Q51+1>0,-PMT($BB51/4,$B$16*12/3-Q51+1,BC51),0) -> 3956.4543 | BE51: =BC51*($BB51/4) -> 1747.9205 | BF51: =BD51-BE51 -> 2208.5339 | BG51: =AT51+AY51+BD51 -> 5576.4543 | BH51: =INDEX(cpi!B:B,MATCH($L51,cpi!A:A)) -> 112.7 | BI51: =100*BH51/BH$3 -> 133.21513 | BJ51: =100*AC51/AC$3 -> 219.81871 | BK51: =100*AD51/AD$3 -> 213.4075 | BL51: =BJ51*GlobalPortfolio+BK51*AusPortfolio -> 217.89535 | BM51: =100*AE51/$AE$3 -> 403.55538 | BN51: =100*AR51/AR$3 -> 166.07143 | BO51: =100*AX51/AX$3 -> 134.26181
A52: Other renter parameters | L52: =DATE(YEAR(L51),MONTH(L51)+3,1) -> 43252 | M52: =AP52 -> 300984.23 | N52: =AX52-BC52 -> 214470.6 | O52: =M52/N52 -> 1.4033822 | P52: =X52/BG52 -> 0.86450999 | Q52: 50 | R52: =EOMONTH(L52,0)-EOMONTH(L52,-3) -> 91 | T52: =IF($B$10="3BR_H", INDEX('3BR_H-processed'!$E:$F,MATCH($L52,'3BR_H-processed'!$B:$B,0),MATCH(Council_Area,'3BR_H-processed'!$E$1:$F$1,0)), INDEX('2BR_F-processed'!$E:$F,MATCH($L52,'2BR_F-processed'!$B:$B,0),MATCH(Council_Area,'2BR_F-processed'!$E$1:$F$1,0))) -> 350 | U52: =IF(MOD(Q52,4)=1,T52,U51) -> 360 | V52: =U52*(R52)/7 -> 4680 | W52: =$B$53/4*BH52/_xlfn.XLOOKUP(Q_end,cpi!A:A,cpi!B:B) -> 156.46164 | X52: =V52+W52 -> 4836.4616 | Y52: =BG52-X52 -> 757.99268 | Z52: =Y52*$B$47 -> 0 | AA52: {=(Y52+Z52)*eff_invest} -> 757.99268 | AB52: =AA52*(_xlfn.XLOOKUP(Q_end,cpi!A:A,cpi!B:B)/BH52) -> 968.91821 | AC52: {=INDEX('msci-indices'!C:C,MATCH($L52,'msci-indices'!$B:$B)-2)} -> 1639.7569 | AD52: {=INDEX('msci-indices'!D:D,MATCH($L52,'msci-indices'!$B:$B)-2)} -> 1460.9363 | AE52: =AI51+AA52 -> 289510.27 | AF52: {=INDEX('msci-indices'!C:C,MATCH($L52,'msci-indices'!$B:$B)+1)} -> 1671.605 | AG52: {=INDEX('msci-indices'!D:D,MATCH($L52,'msci-indices'!$B:$B)+1)} -> 1590.7725 | AH52: =(InvestFees/4)*AE52 -> 180.94392 | AI52: =((AF52/AC52)*GlobalPortfolio+(AG52/AD52)*AusPortfolio)*AE52-AH52 -> 300984.23 | AJ52: =AJ51+AA52 -> 153162.47 | AK52: =AI52-AJ52 -> 147821.76 | AL52: =AJ52*(_xlfn.XLOOKUP(Q_end,cpi!A:A,cpi!B:B)/BH52) -> 195782.77 | AM52: {=SUMPRODUCT($AA$3:AA52,_xlfn.SORTBY($BH$3:BH52,_xlfn.SEQUENCE(ROWS($BH$3:BH52)),-1)/$BH$3)} -> 195194.09 | AN52: =AI52-AM52 -> 105790.15 | AO52: =IF($B$49="Real gains",MAX($B$50*AN52,0),IF($B$49="Discounted nominal gains",MAX($B$50*AK52/2,0),0)) -> 0 | AP52: =AI52-AO52 -> 300984.23 | AR52: =IF($B$10="3BR_H", INDEX('ns-combined'!$C:$D,MATCH($L52,'ns-combined'!$B:$B,0),MATCH(Council_Area,'ns-combined'!$C$1:$D$1,0))*1000, INDEX('s-combined'!$C:$D,MATCH($L52,'s-combined'!$B:$B,0),MATCH(Council_Area,'s-combined'!$C$1:$D$1,0))*1000) -> 468000 | AS52: =AS51+$AS$3 -> 35000 | AT52: 0 | AU52: =SUM($B$28:$B$29)*AR52 -> 9360 | AV52: =AR52*$B$15/4 -> 1345.5 | AW52: =SUM($AV$3:AV52) -> 56351.725 | AX52: =AR52-AS52-AU52-AW52 -> 367288.28 | AY52: =$B$36*V52 -> 1638 | AZ52: =SUM(AY52:AY52)*4/AR52 -> 0.014 | BA52: =SUM(AY52:AY52)/V52 -> 0.35 | BB52: =IF(MortgageRate="Discounted",_xlfn.XLOOKUP(L52,'mortgage-rates'!$A:$A,'mortgage-rates'!$E:$E)/100,_xlfn.XLOOKUP(L52,'mortgage-rates'!$A:$A,'mortgage-rates'!$D:$D)/100) -> 0.0451 | BC52: =BC51-BF51 -> 152817.67 | BD52: =IF($B$16*12/3-Q52+1>0,-PMT($BB52/4,$B$16*12/3-Q52+1,BC52),0) -> 3956.4543 | BE52: =BC52*($BB52/4) -> 1723.0193 | BF52: =BD52-BE52 -> 2233.4351 | BG52: =AT52+AY52+BD52 -> 5594.4543 | BH52: =INDEX(cpi!B:B,MATCH($L52,cpi!A:A)) -> 113.2 | BI52: =100*BH52/BH$3 -> 133.80615 | BJ52: =100*AC52/AC$3 -> 217.22098 | BK52: =100*AD52/AD$3 -> 204.91247 | BL52: =BJ52*GlobalPortfolio+BK52*AusPortfolio -> 213.52842 | BM52: =100*AE52/$AE$3 -> 396.18284 | BN52: =100*AR52/AR$3 -> 167.14286 | BO52: =100*AX52/AX$3 -> 134.58959
A53: Renter's insurance and other costs ($ per year, end-quarter dollars) | B53: 800 | C53: 800 | L53: =DATE(YEAR(L52),MONTH(L52)+3,1) -> 43344 | M53: =AP53 -> 312285.64 | N53: =AX53-BC53 -> 212997.43 | O53: =M53/N53 -> 1.4661475 | P53: =X53/BG53 -> 0.86711495 | Q53: 51 | R53: =EOMONTH(L53,0)-EOMONTH(L53,-3) -> 92 | T53: =IF($B$10="3BR_H", INDEX('3BR_H-processed'!$E:$F,MATCH($L53,'3BR_H-processed'!$B:$B,0),MATCH(Council_Area,'3BR_H-processed'!$E$1:$F$1,0)), INDEX('2BR_F-processed'!$E:$F,MATCH($L53,'2BR_F-processed'!$B:$B,0),MATCH(Council_Area,'2BR_F-processed'!$E$1:$F$1,0))) -> 350 | U53: =IF(MOD(Q53,4)=1,T53,U52) -> 360 | V53: =U53*(R53)/7 -> 4731.4286 | W53: =$B$53/4*BH53/_xlfn.XLOOKUP(Q_end,cpi!A:A,cpi!B:B) -> 156.8763 | X53: =V53+W53 -> 4888.3049 | Y53: =BG53-X53 -> 749.13091 | Z53: =Y53*$B$47 -> 0 | AA53: {=(Y53+Z53)*eff_invest} -> 749.13091 | AB53: =AA53*(_xlfn.XLOOKUP(Q_end,cpi!A:A,cpi!B:B)/BH53) -> 955.05941 | AC53: {=INDEX('msci-indices'!C:C,MATCH($L53,'msci-indices'!$B:$B)-2)} -> 1671.605 | AD53: {=INDEX('msci-indices'!D:D,MATCH($L53,'msci-indices'!$B:$B)-2)} -> 1590.7725 | AE53: =AI52+AA53 -> 301733.36 | AF53: {=INDEX('msci-indices'!C:C,MATCH($L53,'msci-indices'!$B:$B)+1)} -> 1747.8373 | AG53: {=INDEX('msci-indices'!D:D,MATCH($L53,'msci-indices'!$B:$B)+1)} -> 1610.2553 | AH53: =(InvestFees/4)*AE53 -> 188.58335 | AI53: =((AF53/AC53)*GlobalPortfolio+(AG53/AD53)*AusPortfolio)*AE53-AH53 -> 312285.64 | AJ53: =AJ52+AA53 -> 153911.6 | AK53: =AI53-AJ53 -> 158374.04 | AL53: =AJ53*(_xlfn.XLOOKUP(Q_end,cpi!A:A,cpi!B:B)/BH53) -> 196220.34 | AM53: {=SUMPRODUCT($AA$3:AA53,_xlfn.SORTBY($BH$3:BH53,_xlfn.SEQUENCE(ROWS($BH$3:BH53)),-1)/$BH$3)} -> 196728.25 | AN53: =AI53-AM53 -> 115557.39 | AO53: =IF($B$49="Real gains",MAX($B$50*AN53,0),IF($B$49="Discounted nominal gains",MAX($B$50*AK53/2,0),0)) -> 0 | AP53: =AI53-AO53 -> 312285.64 | AR53: =IF($B$10="3BR_H", INDEX('ns-combined'!$C:$D,MATCH($L53,'ns-combined'!$B:$B,0),MATCH(Council_Area,'ns-combined'!$C$1:$D$1,0))*1000, INDEX('s-combined'!$C:$D,MATCH($L53,'s-combined'!$B:$B,0),MATCH(Council_Area,'s-combined'!$C$1:$D$1,0))*1000) -> 466300 | AS53: =AS52+$AS$3 -> 35700 | AT53: 0 | AU53: =SUM($B$28:$B$29)*AR53 -> 9326 | AV53: =AR53*$B$15/4 -> 1340.6125 | AW53: =SUM($AV$3:AV53) -> 57692.338 | AX53: =AR53-AS53-AU53-AW53 -> 363581.66 | AY53: =$B$36*V53 -> 1656 | AZ53: =SUM(AY53:AY53)*4/AR53 -> 0.014205447 | BA53: =SUM(AY53:AY53)/V53 -> 0.35 | BB53: =IF(MortgageRate="Discounted",_xlfn.XLOOKUP(L53,'mortgage-rates'!$A:$A,'mortgage-rates'!$E:$E)/100,_xlfn.XLOOKUP(L53,'mortgage-rates'!$A:$A,'mortgage-rates'!$D:$D)/100) -> 0.0462 | BC53: =BC52-BF52 -> 150584.24 | BD53: =IF($B$16*12/3-Q53+1>0,-PMT($BB53/4,$B$16*12/3-Q53+1,BC53),0) -> 3981.4358 | BE53: =BC53*($BB53/4) -> 1739.2479 | BF53: =BD53-BE53 -> 2242.1878 | BG53: =AT53+AY53+BD53 -> 5637.4358 | BH53: =INDEX(cpi!B:B,MATCH($L53,cpi!A:A)) -> 113.5 | BI53: =100*BH53/BH$3 -> 134.16076 | BJ53: =100*AC53/AC$3 -> 221.43995 | BK53: =100*AD53/AD$3 -> 223.12345 | BL53: =BJ53*GlobalPortfolio+BK53*AusPortfolio -> 221.945 | BM53: =100*AE53/$AE$3 -> 412.90965 | BN53: =100*AR53/AR$3 -> 166.53571 | BO53: =100*AX53/AX$3 -> 133.23134
A54: Investment efficiency | B54: 1 | C54: 1 | L54: =DATE(YEAR(L53),MONTH(L53)+3,1) -> 43435 | M54: =AP54 -> 274461.07 | N54: =AX54-BC54 -> 226585.61 | O54: =M54/N54 -> 1.2112908 | P54: =X54/BG54 -> 0.86620673 | Q54: 52 | R54: =EOMONTH(L54,0)-EOMONTH(L54,-3) -> 92 | T54: =IF($B$10="3BR_H", INDEX('3BR_H-processed'!$E:$F,MATCH($L54,'3BR_H-processed'!$B:$B,0),MATCH(Council_Area,'3BR_H-processed'!$E$1:$F$1,0)), INDEX('2BR_F-processed'!$E:$F,MATCH($L54,'2BR_F-processed'!$B:$B,0),MATCH(Council_Area,'2BR_F-processed'!$E$1:$F$1,0))) -> 355 | U54: =IF(MOD(Q54,4)=1,T54,U53) -> 360 | V54: =U54*(R54)/7 -> 4731.4286 | W54: =$B$53/4*BH54/_xlfn.XLOOKUP(Q_end,cpi!A:A,cpi!B:B) -> 157.56738 | X54: =V54+W54 -> 4888.996 | Y54: =BG54-X54 -> 755.14858 | Z54: =Y54*$B$47 -> 0 | AA54: {=(Y54+Z54)*eff_invest} -> 755.14858 | AB54: =AA54*(_xlfn.XLOOKUP(Q_end,cpi!A:A,cpi!B:B)/BH54) -> 958.50877 | AC54: {=INDEX('msci-indices'!C:C,MATCH($L54,'msci-indices'!$B:$B)-2)} -> 1747.8373 | AD54: {=INDEX('msci-indices'!D:D,MATCH($L54,'msci-indices'!$B:$B)-2)} -> 1610.2553 | AE54: =AI53+AA54 -> 313040.79 | AF54: {=INDEX('msci-indices'!C:C,MATCH($L54,'msci-indices'!$B:$B)+1)} -> 1503.1568 | AG54: {=INDEX('msci-indices'!D:D,MATCH($L54,'msci-indices'!$B:$B)+1)} -> 1478.0882 | AH54: =(InvestFees/4)*AE54 -> 195.65049 | AI54: =((AF54/AC54)*GlobalPortfolio+(AG54/AD54)*AusPortfolio)*AE54-AH54 -> 274461.07 | AJ54: =AJ53+AA54 -> 154666.75 | AK54: =AI54-AJ54 -> 119794.32 | AL54: =AJ54*(_xlfn.XLOOKUP(Q_end,cpi!A:A,cpi!B:B)/BH54) -> 196318.24 | AM54: {=SUMPRODUCT($AA$3:AA54,_xlfn.SORTBY($BH$3:BH54,_xlfn.SEQUENCE(ROWS($BH$3:BH54)),-1)/$BH$3)} -> 198442.22 | AN54: =AI54-AM54 -> 76018.847 | AO54: =IF($B$49="Real gains",MAX($B$50*AN54,0),IF($B$49="Discounted nominal gains",MAX($B$50*AK54/2,0),0)) -> 0 | AP54: =AI54-AO54 -> 274461.07 | AR54: =IF($B$10="3BR_H", INDEX('ns-combined'!$C:$D,MATCH($L54,'ns-combined'!$B:$B,0),MATCH(Council_Area,'ns-combined'!$C$1:$D$1,0))*1000, INDEX('s-combined'!$C:$D,MATCH($L54,'s-combined'!$B:$B,0),MATCH(Council_Area,'s-combined'!$C$1:$D$1,0))*1000) -> 480000 | AS54: =AS53+$AS$3 -> 36400 | AT54: 0 | AU54: =SUM($B$28:$B$29)*AR54 -> 9600 | AV54: =AR54*$B$15/4 -> 1380 | AW54: =SUM($AV$3:AV54) -> 59072.338 | AX54: =AR54-AS54-AU54-AW54 -> 374927.66 | AY54: =$B$36*V54 -> 1656 | AZ54: =SUM(AY54:AY54)*4/AR54 -> 0.0138 | BA54: =SUM(AY54:AY54)/V54 -> 0.35 | BB54: =IF(MortgageRate="Discounted",_xlfn.XLOOKUP(L54,'mortgage-rates'!$A:$A,'mortgage-rates'!$E:$E)/100,_xlfn.XLOOKUP(L54,'mortgage-rates'!$A:$A,'mortgage-rates'!$D:$D)/100) -> 0.0465 | BC54: =BC53-BF53 -> 148342.05 | BD54: =IF($B$16*12/3-Q54+1>0,-PMT($BB54/4,$B$16*12/3-Q54+1,BC54),0) -> 3988.1445 | BE54: =BC54*($BB54/4) -> 1724.4763 | BF54: =BD54-BE54 -> 2263.6682 | BG54: =AT54+AY54+BD54 -> 5644.1445 | BH54: =INDEX(cpi!B:B,MATCH($L54,cpi!A:A)) -> 114 | BI54: =100*BH54/BH$3 -> 134.75177 | BJ54: =100*AC54/AC$3 -> 231.53855 | BK54: =100*AD54/AD$3 -> 225.85612 | BL54: =BJ54*GlobalPortfolio+BK54*AusPortfolio -> 229.83382 | BM54: =100*AE54/$AE$3 -> 428.38339 | BN54: =100*AR54/AR$3 -> 171.42857 | BO54: =100*AX54/AX$3 -> 137.38898
L55: =DATE(YEAR(L54),MONTH(L54)+3,1) -> 43525 | M55: =AP55 -> 308285.41 | N55: =AX55-BC55 -> 221883.66 | O55: =M55/N55 -> 1.3894012 | P55: =X55/BG55 -> 0.8683878 | Q55: 53 | R55: =EOMONTH(L55,0)-EOMONTH(L55,-3) -> 90 | T55: =IF($B$10="3BR_H", INDEX('3BR_H-processed'!$E:$F,MATCH($L55,'3BR_H-processed'!$B:$B,0),MATCH(Council_Area,'3BR_H-processed'!$E$1:$F$1,0)), INDEX('2BR_F-processed'!$E:$F,MATCH($L55,'2BR_F-processed'!$B:$B,0),MATCH(Council_Area,'2BR_F-processed'!$E$1:$F$1,0))) -> 370 | U55: =IF(MOD(Q55,4)=1,T55,U54) -> 370 | V55: =U55*(R55)/7 -> 4757.1429 | W55: =$B$53/4*BH55/_xlfn.XLOOKUP(Q_end,cpi!A:A,cpi!B:B) -> 157.7056 | X55: =V55+W55 -> 4914.8485 | Y55: =BG55-X55 -> 744.8907 | Z55: =Y55*$B$47 -> 0 | AA55: {=(Y55+Z55)*eff_invest} -> 744.8907 | AB55: =AA55*(_xlfn.XLOOKUP(Q_end,cpi!A:A,cpi!B:B)/BH55) -> 944.65981 | AC55: {=INDEX('msci-indices'!C:C,MATCH($L55,'msci-indices'!$B:$B)-2)} -> 1503.1568 | AD55: {=INDEX('msci-indices'!D:D,MATCH($L55,'msci-indices'!$B:$B)-2)} -> 1478.0882 | AE55: =AI54+AA55 -> 275205.96 | AF55: {=INDEX('msci-indices'!C:C,MATCH($L55,'msci-indices'!$B:$B)+1)} -> 1693.1497 | AG55: {=INDEX('msci-indices'!D:D,MATCH($L55,'msci-indices'!$B:$B)+1)} -> 1637.4592 | AH55: =(InvestFees/4)*AE55 -> 172.00373 | AI55: =((AF55/AC55)*GlobalPortfolio+(AG55/AD55)*AusPortfolio)*AE55-AH55 -> 308285.41 | AJ55: =AJ54+AA55 -> 155411.64 | AK55: =AI55-AJ55 -> 152873.77 | AL55: =AJ55*(_xlfn.XLOOKUP(Q_end,cpi!A:A,cpi!B:B)/BH55) -> 197090.84 | AM55: {=SUMPRODUCT($AA$3:AA55,_xlfn.SORTBY($BH$3:BH55,_xlfn.SEQUENCE(ROWS($BH$3:BH55)),-1)/$BH$3)} -> 199807.94 | AN55: =AI55-AM55 -> 108477.46 | AO55: =IF($B$49="Real gains",MAX($B$50*AN55,0),IF($B$49="Discounted nominal gains",MAX($B$50*AK55/2,0),0)) -> 0 | AP55: =AI55-AO55 -> 308285.41 | AR55: =IF($B$10="3BR_H", INDEX('ns-combined'!$C:$D,MATCH($L55,'ns-combined'!$B:$B,0),MATCH(Council_Area,'ns-combined'!$C$1:$D$1,0))*1000, INDEX('s-combined'!$C:$D,MATCH($L55,'s-combined'!$B:$B,0),MATCH(Council_Area,'s-combined'!$C$1:$D$1,0))*1000) -> 475000 | AS55: =AS54+$AS$3 -> 37100 | AT55: 0 | AU55: =SUM($B$28:$B$29)*AR55 -> 9500 | AV55: =AR55*$B$15/4 -> 1365.625 | AW55: =SUM($AV$3:AV55) -> 60437.963 | AX55: =AR55-AS55-AU55-AW55 -> 367962.04 | AY55: =$B$36*V55 -> 1665 | AZ55: =SUM(AY55:AY55)*4/AR55 -> 0.014021053 | BA55: =SUM(AY55:AY55)/V55 -> 0.35 | BB55: =IF(MortgageRate="Discounted",_xlfn.XLOOKUP(L55,'mortgage-rates'!$A:$A,'mortgage-rates'!$E:$E)/100,_xlfn.XLOOKUP(L55,'mortgage-rates'!$A:$A,'mortgage-rates'!$D:$D)/100) -> 0.0468 | BC55: =BC54-BF54 -> 146078.38 | BD55: =IF($B$16*12/3-Q55+1>0,-PMT($BB55/4,$B$16*12/3-Q55+1,BC55),0) -> 3994.7392 | BE55: =BC55*($BB55/4) -> 1709.1171 | BF55: =BD55-BE55 -> 2285.6221 | BG55: =AT55+AY55+BD55 -> 5659.7392 | BH55: =INDEX(cpi!B:B,MATCH($L55,cpi!A:A)) -> 114.1 | BI55: =100*BH55/BH$3 -> 134.86998 | BJ55: =100*AC55/AC$3 -> 199.12537 | BK55: =100*AD55/AD$3 -> 207.31821 | BL55: =BJ55*GlobalPortfolio+BK55*AusPortfolio -> 201.58322 | BM55: =100*AE55/$AE$3 -> 376.60799 | BN55: =100*AR55/AR$3 -> 169.64286 | BO55: =100*AX55/AX$3 -> 134.83649
L56: =DATE(YEAR(L55),MONTH(L55)+3,1) -> 43617 | M56: =AP56 -> 324286.06 | N56: =AX56-BC56 -> 225523.59 | O56: =M56/N56 -> 1.4379252 | P56: =X56/BG56 -> 0.88241772 | Q56: 54 | R56: =EOMONTH(L56,0)-EOMONTH(L56,-3) -> 91 | T56: =IF($B$10="3BR_H", INDEX('3BR_H-processed'!$E:$F,MATCH($L56,'3BR_H-processed'!$B:$B,0),MATCH(Council_Area,'3BR_H-processed'!$E$1:$F$1,0)), INDEX('2BR_F-processed'!$E:$F,MATCH($L56,'2BR_F-processed'!$B:$B,0),MATCH(Council_Area,'2BR_F-processed'!$E$1:$F$1,0))) -> 360 | U56: =IF(MOD(Q56,4)=1,T56,U55) -> 370 | V56: =U56*(R56)/7 -> 4810 | W56: =$B$53/4*BH56/_xlfn.XLOOKUP(Q_end,cpi!A:A,cpi!B:B) -> 158.81133 | X56: =V56+W56 -> 4968.8113 | Y56: =BG56-X56 -> 662.09479 | Z56: =Y56*$B$47 -> 0 | AA56: {=(Y56+Z56)*eff_invest} -> 662.09479 | AB56: =AA56*(_xlfn.XLOOKUP(Q_end,cpi!A:A,cpi!B:B)/BH56) -> 833.81302 | AC56: {=INDEX('msci-indices'!C:C,MATCH($L56,'msci-indices'!$B:$B)-2)} -> 1693.1497 | AD56: {=INDEX('msci-indices'!D:D,MATCH($L56,'msci-indices'!$B:$B)-2)} -> 1637.4592 | AE56: =AI55+AA56 -> 308947.5 | AF56: {=INDEX('msci-indices'!C:C,MATCH($L56,'msci-indices'!$B:$B)+1)} -> 1756.4484 | AG56: {=INDEX('msci-indices'!D:D,MATCH($L56,'msci-indices'!$B:$B)+1)} -> 1769.0189 | AH56: =(InvestFees/4)*AE56 -> 193.09219 | AI56: =((AF56/AC56)*GlobalPortfolio+(AG56/AD56)*AusPortfolio)*AE56-AH56 -> 324286.06 | AJ56: =AJ55+AA56 -> 156073.74 | AK56: =AI56-AJ56 -> 168212.32 | AL56: =AJ56*(_xlfn.XLOOKUP(Q_end,cpi!A:A,cpi!B:B)/BH56) -> 196552.39 | AM56: {=SUMPRODUCT($AA$3:AA56,_xlfn.SORTBY($BH$3:BH56,_xlfn.SEQUENCE(ROWS($BH$3:BH56)),-1)/$BH$3)} -> 201683.64 | AN56: =AI56-AM56 -> 122602.42 | AO56: =IF($B$49="Real gains",MAX($B$50*AN56,0),IF($B$49="Discounted nominal gains",MAX($B$50*AK56/2,0),0)) -> 0 | AP56: =AI56-AO56 -> 324286.06 | AR56: =IF($B$10="3BR_H", INDEX('ns-combined'!$C:$D,MATCH($L56,'ns-combined'!$B:$B,0),MATCH(Council_Area,'ns-combined'!$C$1:$D$1,0))*1000, INDEX('s-combined'!$C:$D,MATCH($L56,'s-combined'!$B:$B,0),MATCH(Council_Area,'s-combined'!$C$1:$D$1,0))*1000) -> 478500 | AS56: =AS55+$AS$3 -> 37800 | AT56: 0 | AU56: =SUM($B$28:$B$29)*AR56 -> 9570 | AV56: =AR56*$B$15/4 -> 1375.6875 | AW56: =SUM($AV$3:AV56) -> 61813.65 | AX56: =AR56-AS56-AU56-AW56 -> 369316.35 | AY56: =$B$36*V56 -> 1683.5 | AZ56: =SUM(AY56:AY56)*4/AR56 -> 0.014073145 | BA56: =SUM(AY56:AY56)/V56 -> 0.35 | BB56: =IF(MortgageRate="Discounted",_xlfn.XLOOKUP(L56,'mortgage-rates'!$A:$A,'mortgage-rates'!$E:$E)/100,_xlfn.XLOOKUP(L56,'mortgage-rates'!$A:$A,'mortgage-rates'!$D:$D)/100) -> 0.0446 | BC56: =BC55-BF55 -> 143792.76 | BD56: =IF($B$16*12/3-Q56+1>0,-PMT($BB56/4,$B$16*12/3-Q56+1,BC56),0) -> 3947.4061 | BE56: =BC56*($BB56/4) -> 1603.2893 | BF56: =BD56-BE56 -> 2344.1169 | BG56: =AT56+AY56+BD56 -> 5630.9061 | BH56: =INDEX(cpi!B:B,MATCH($L56,cpi!A:A)) -> 114.9 | BI56: =100*BH56/BH$3 -> 135.8156 | BJ56: =100*AC56/AC$3 -> 224.294 | BK56: =100*AD56/AD$3 -> 229.67177 | BL56: =BJ56*GlobalPortfolio+BK56*AusPortfolio -> 225.90733 | BM56: =100*AE56/$AE$3 -> 422.7819 | BN56: =100*AR56/AR$3 -> 170.89286 | BO56: =100*AX56/AX$3 -> 135.33277
L57: =DATE(YEAR(L56),MONTH(L56)+3,1) -> 43709 | M57: =AP57 -> 328167.82 | N57: =AX57-BC57 -> 221394.96 | O57: =M57/N57 -> 1.4822732 | P57: =X57/BG57 -> 0.89599017 | Q57: 55 | R57: =EOMONTH(L57,0)-EOMONTH(L57,-3) -> 92 | T57: =IF($B$10="3BR_H", INDEX('3BR_H-processed'!$E:$F,MATCH($L57,'3BR_H-processed'!$B:$B,0),MATCH(Council_Area,'3BR_H-processed'!$E$1:$F$1,0)), INDEX('2BR_F-processed'!$E:$F,MATCH($L57,'2BR_F-processed'!$B:$B,0),MATCH(Council_Area,'2BR_F-processed'!$E$1:$F$1,0))) -> 360 | U57: =IF(MOD(Q57,4)=1,T57,U56) -> 370 | V57: =U57*(R57)/7 -> 4862.8571 | W57: =$B$53/4*BH57/_xlfn.XLOOKUP(Q_end,cpi!A:A,cpi!B:B) -> 159.50242 | X57: =V57+W57 -> 5022.3596 | Y57: =BG57-X57 -> 583.01394 | Z57: =Y57*$B$47 -> 0 | AA57: {=(Y57+Z57)*eff_invest} -> 583.01394 | AB57: =AA57*(_xlfn.XLOOKUP(Q_end,cpi!A:A,cpi!B:B)/BH57) -> 731.04087 | AC57: {=INDEX('msci-indices'!C:C,MATCH($L57,'msci-indices'!$B:$B)-2)} -> 1756.4484 | AD57: {=INDEX('msci-indices'!D:D,MATCH($L57,'msci-indices'!$B:$B)-2)} -> 1769.0189 | AE57: =AI56+AA57 -> 324869.07 | AF57: {=INDEX('msci-indices'!C:C,MATCH($L57,'msci-indices'!$B:$B)+1)} -> 1762.7547 | AG57: {=INDEX('msci-indices'!D:D,MATCH($L57,'msci-indices'!$B:$B)+1)} -> 1817.7602 | AH57: =(InvestFees/4)*AE57 -> 203.04317 | AI57: =((AF57/AC57)*GlobalPortfolio+(AG57/AD57)*AusPortfolio)*AE57-AH57 -> 328167.82 | AJ57: =AJ56+AA57 -> 156656.75 | AK57: =AI57-AJ57 -> 171511.07 | AL57: =AJ57*(_xlfn.XLOOKUP(Q_end,cpi!A:A,cpi!B:B)/BH57) -> 196431.82 | AM57: {=SUMPRODUCT($AA$3:AA57,_xlfn.SORTBY($BH$3:BH57,_xlfn.SEQUENCE(ROWS($BH$3:BH57)),-1)/$BH$3)} -> 203233.08 | AN57: =AI57-AM57 -> 124934.73 | AO57: =IF($B$49="Real gains",MAX($B$50*AN57,0),IF($B$49="Discounted nominal gains",MAX($B$50*AK57/2,0),0)) -> 0 | AP57: =AI57-AO57 -> 328167.82 | AR57: =IF($B$10="3BR_H", INDEX('ns-combined'!$C:$D,MATCH($L57,'ns-combined'!$B:$B,0),MATCH(Council_Area,'ns-combined'!$C$1:$D$1,0))*1000, INDEX('s-combined'!$C:$D,MATCH($L57,'s-combined'!$B:$B,0),MATCH(Council_Area,'s-combined'!$C$1:$D$1,0))*1000) -> 474000 | AS57: =AS56+$AS$3 -> 38500 | AT57: 0 | AU57: =SUM($B$28:$B$29)*AR57 -> 9480 | AV57: =AR57*$B$15/4 -> 1362.75 | AW57: =SUM($AV$3:AV57) -> 63176.4 | AX57: =AR57-AS57-AU57-AW57 -> 362843.6 | AY57: =$B$36*V57 -> 1702 | AZ57: =SUM(AY57:AY57)*4/AR57 -> 0.014362869 | BA57: =SUM(AY57:AY57)/V57 -> 0.35 | BB57: =IF(MortgageRate="Discounted",_xlfn.XLOOKUP(L57,'mortgage-rates'!$A:$A,'mortgage-rates'!$E:$E)/100,_xlfn.XLOOKUP(L57,'mortgage-rates'!$A:$A,'mortgage-rates'!$D:$D)/100) -> 0.0425 | BC57: =BC56-BF56 -> 141448.64 | BD57: =IF($B$16*12/3-Q57+1>0,-PMT($BB57/4,$B$16*12/3-Q57+1,BC57),0) -> 3903.3735 | BE57: =BC57*($BB57/4) -> 1502.8918 | BF57: =BD57-BE57 -> 2400.4817 | BG57: =AT57+AY57+BD57 -> 5605.3735 | BH57: =INDEX(cpi!B:B,MATCH($L57,cpi!A:A)) -> 115.4 | BI57: =100*BH57/BH$3 -> 136.40662 | BJ57: =100*AC57/AC$3 -> 232.67928 | BK57: =100*AD57/AD$3 -> 248.12447 | BL57: =BJ57*GlobalPortfolio+BK57*AusPortfolio -> 237.31283 | BM57: =100*AE57/$AE$3 -> 444.56991 | BN57: =100*AR57/AR$3 -> 169.28571 | BO57: =100*AX57/AX$3 -> 132.96088
L58: =DATE(YEAR(L57),MONTH(L57)+3,1) -> 43800 | M58: =AP58 -> 348656.13 | N58: =AX58-BC58 -> 232481.06 | O58: =M58/N58 -> 1.4997184 | P58: =X58/BG58 -> 0.89944618 | Q58: 56 | R58: =EOMONTH(L58,0)-EOMONTH(L58,-3) -> 92 | T58: =IF($B$10="3BR_H", INDEX('3BR_H-processed'!$E:$F,MATCH($L58,'3BR_H-processed'!$B:$B,0),MATCH(Council_Area,'3BR_H-processed'!$E$1:$F$1,0)), INDEX('2BR_F-processed'!$E:$F,MATCH($L58,'2BR_F-processed'!$B:$B,0),MATCH(Council_Area,'2BR_F-processed'!$E$1:$F$1,0))) -> 370 | U58: =IF(MOD(Q58,4)=1,T58,U57) -> 370 | V58: =U58*(R58)/7 -> 4862.8571 | W58: =$B$53/4*BH58/_xlfn.XLOOKUP(Q_end,cpi!A:A,cpi!B:B) -> 160.46994 | X58: =V58+W58 -> 5023.3271 | Y58: =BG58-X58 -> 561.58417 | Z58: =Y58*$B$47 -> 0 | AA58: {=(Y58+Z58)*eff_invest} -> 561.58417 | AB58: =AA58*(_xlfn.XLOOKUP(Q_end,cpi!A:A,cpi!B:B)/BH58) -> 699.92445 | AC58: {=INDEX('msci-indices'!C:C,MATCH($L58,'msci-indices'!$B:$B)-2)} -> 1762.7547 | AD58: {=INDEX('msci-indices'!D:D,MATCH($L58,'msci-indices'!$B:$B)-2)} -> 1817.7602 | AE58: =AI57+AA58 -> 328729.4 | AF58: {=INDEX('msci-indices'!C:C,MATCH($L58,'msci-indices'!$B:$B)+1)} -> 1916.2448 | AG58: {=INDEX('msci-indices'!D:D,MATCH($L58,'msci-indices'!$B:$B)+1)} -> 1819.5212 | AH58: =(InvestFees/4)*AE58 -> 205.45588 | AI58: =((AF58/AC58)*GlobalPortfolio+(AG58/AD58)*AusPortfolio)*AE58-AH58 -> 348656.13 | AJ58: =AJ57+AA58 -> 157218.34 | AK58: =AI58-AJ58 -> 191437.8 | AL58: =AJ58*(_xlfn.XLOOKUP(Q_end,cpi!A:A,cpi!B:B)/BH58) -> 195947.4 | AM58: {=SUMPRODUCT($AA$3:AA58,_xlfn.SORTBY($BH$3:BH58,_xlfn.SEQUENCE(ROWS($BH$3:BH58)),-1)/$BH$3)} -> 204927.87 | AN58: =AI58-AM58 -> 143728.26 | AO58: =IF($B$49="Real gains",MAX($B$50*AN58,0),IF($B$49="Discounted nominal gains",MAX($B$50*AK58/2,0),0)) -> 0 | AP58: =AI58-AO58 -> 348656.13 | AR58: =IF($B$10="3BR_H", INDEX('ns-combined'!$C:$D,MATCH($L58,'ns-combined'!$B:$B,0),MATCH(Council_Area,'ns-combined'!$C$1:$D$1,0))*1000, INDEX('s-combined'!$C:$D,MATCH($L58,'s-combined'!$B:$B,0),MATCH(Council_Area,'s-combined'!$C$1:$D$1,0))*1000) -> 485000 | AS58: =AS57+$AS$3 -> 39200 | AT58: 0 | AU58: =SUM($B$28:$B$29)*AR58 -> 9700 | AV58: =AR58*$B$15/4 -> 1394.375 | AW58: =SUM($AV$3:AV58) -> 64570.775 | AX58: =AR58-AS58-AU58-AW58 -> 371529.22 | AY58: =$B$36*V58 -> 1702 | AZ58: =SUM(AY58:AY58)*4/AR58 -> 0.014037113 | BA58: =SUM(AY58:AY58)/V58 -> 0.35 | BB58: =IF(MortgageRate="Discounted",_xlfn.XLOOKUP(L58,'mortgage-rates'!$A:$A,'mortgage-rates'!$E:$E)/100,_xlfn.XLOOKUP(L58,'mortgage-rates'!$A:$A,'mortgage-rates'!$D:$D)/100) -> 0.0415 | BC58: =BC57-BF57 -> 139048.16 | BD58: =IF($B$16*12/3-Q58+1>0,-PMT($BB58/4,$B$16*12/3-Q58+1,BC58),0) -> 3882.9112 | BE58: =BC58*($BB58/4) -> 1442.6247 | BF58: =BD58-BE58 -> 2440.2866 | BG58: =AT58+AY58+BD58 -> 5584.9112 | BH58: =INDEX(cpi!B:B,MATCH($L58,cpi!A:A)) -> 116.1 | BI58: =100*BH58/BH$3 -> 137.23404 | BJ58: =100*AC58/AC$3 -> 233.51468 | BK58: =100*AD58/AD$3 -> 254.96098 | BL58: =BJ58*GlobalPortfolio+BK58*AusPortfolio -> 239.94857 | BM58: =100*AE58/$AE$3 -> 449.85261 | BN58: =100*AR58/AR$3 -> 173.21429 | BO58: =100*AX58/AX$3 -> 136.14365
L59: =DATE(YEAR(L58),MONTH(L58)+3,1) -> 43891 | M59: =AP59 -> 269685.29 | N59: =AX59-BC59 -> 220124.35 | O59: =M59/N59 -> 1.2251497 | P59: =X59/BG59 -> 0.91683552 | Q59: 57 | R59: =EOMONTH(L59,0)-EOMONTH(L59,-3) -> 91 | T59: =IF($B$10="3BR_H", INDEX('3BR_H-processed'!$E:$F,MATCH($L59,'3BR_H-processed'!$B:$B,0),MATCH(Council_Area,'3BR_H-processed'!$E$1:$F$1,0)), INDEX('2BR_F-processed'!$E:$F,MATCH($L59,'2BR_F-processed'!$B:$B,0),MATCH(Council_Area,'2BR_F-processed'!$E$1:$F$1,0))) -> 380 | U59: =IF(MOD(Q59,4)=1,T59,U58) -> 380 | V59: =U59*(R59)/7 -> 4940 | W59: =$B$53/4*BH59/_xlfn.XLOOKUP(Q_end,cpi!A:A,cpi!B:B) -> 161.29924 | X59: =V59+W59 -> 5101.2992 | Y59: =BG59-X59 -> 462.72957 | Z59: =Y59*$B$47 -> 0 | AA59: {=(Y59+Z59)*eff_invest} -> 462.72957 | AB59: =AA59*(_xlfn.XLOOKUP(Q_end,cpi!A:A,cpi!B:B)/BH59) -> 573.75294 | AC59: {=INDEX('msci-indices'!C:C,MATCH($L59,'msci-indices'!$B:$B)-2)} -> 1916.2448 | AD59: {=INDEX('msci-indices'!D:D,MATCH($L59,'msci-indices'!$B:$B)-2)} -> 1819.5212 | AE59: =AI58+AA59 -> 349118.86 | AF59: {=INDEX('msci-indices'!C:C,MATCH($L59,'msci-indices'!$B:$B)+1)} -> 1491.4482 | AG59: {=INDEX('msci-indices'!D:D,MATCH($L59,'msci-indices'!$B:$B)+1)} -> 1384.5123 | AH59: =(InvestFees/4)*AE59 -> 218.19929 | AI59: =((AF59/AC59)*GlobalPortfolio+(AG59/AD59)*AusPortfolio)*AE59-AH59 -> 269685.29 | AJ59: =AJ58+AA59 -> 157681.06 | AK59: =AI59-AJ59 -> 112004.22 | AL59: =AJ59*(_xlfn.XLOOKUP(Q_end,cpi!A:A,cpi!B:B)/BH59) -> 195513.71 | AM59: {=SUMPRODUCT($AA$3:AA59,_xlfn.SORTBY($BH$3:BH59,_xlfn.SEQUENCE(ROWS($BH$3:BH59)),-1)/$BH$3)} -> 206446 | AN59: =AI59-AM59 -> 63239.29 | AO59: =IF($B$49="Real gains",MAX($B$50*AN59,0),IF($B$49="Discounted nominal gains",MAX($B$50*AK59/2,0),0)) -> 0 | AP59: =AI59-AO59 -> 269685.29 | AR59: =IF($B$10="3BR_H", INDEX('ns-combined'!$C:$D,MATCH($L59,'ns-combined'!$B:$B,0),MATCH(Council_Area,'ns-combined'!$C$1:$D$1,0))*1000, INDEX('s-combined'!$C:$D,MATCH($L59,'s-combined'!$B:$B,0),MATCH(Council_Area,'s-combined'!$C$1:$D$1,0))*1000) -> 472000 | AS59: =AS58+$AS$3 -> 39900 | AT59: 0 | AU59: =SUM($B$28:$B$29)*AR59 -> 9440 | AV59: =AR59*$B$15/4 -> 1357 | AW59: =SUM($AV$3:AV59) -> 65927.775 | AX59: =AR59-AS59-AU59-AW59 -> 356732.22 | AY59: =$B$36*V59 -> 1729 | AZ59: =SUM(AY59:AY59)*4/AR59 -> 0.014652542 | BA59: =SUM(AY59:AY59)/V59 -> 0.35 | BB59: =IF(MortgageRate="Discounted",_xlfn.XLOOKUP(L59,'mortgage-rates'!$A:$A,'mortgage-rates'!$E:$E)/100,_xlfn.XLOOKUP(L59,'mortgage-rates'!$A:$A,'mortgage-rates'!$D:$D)/100) -> 0.0391 | BC59: =BC58-BF58 -> 136607.87 | BD59: =IF($B$16*12/3-Q59+1>0,-PMT($BB59/4,$B$16*12/3-Q59+1,BC59),0) -> 3835.0288 | BE59: =BC59*($BB59/4) -> 1335.342 | BF59: =BD59-BE59 -> 2499.6868 | BG59: =AT59+AY59+BD59 -> 5564.0288 | BH59: =INDEX(cpi!B:B,MATCH($L59,cpi!A:A)) -> 116.7 | BI59: =100*BH59/BH$3 -> 137.94326 | BJ59: =100*AC59/AC$3 -> 253.84774 | BK59: =100*AD59/AD$3 -> 255.20797 | BL59: =BJ59*GlobalPortfolio+BK59*AusPortfolio -> 254.25581 | BM59: =100*AE59/$AE$3 -> 477.75475 | BN59: =100*AR59/AR$3 -> 168.57143 | BO59: =100*AX59/AX$3 -> 130.72142
L60: =DATE(YEAR(L59),MONTH(L59)+3,1) -> 43983 | M60: =AP60 -> 321503.12 | N60: =AX60-BC60 -> 235712.48 | O60: =M60/N60 -> 1.3639631 | P60: =X60/BG60 -> 0.92466915 | Q60: 58 | R60: =EOMONTH(L60,0)-EOMONTH(L60,-3) -> 91 | T60: =IF($B$10="3BR_H", INDEX('3BR_H-processed'!$E:$F,MATCH($L60,'3BR_H-processed'!$B:$B,0),MATCH(Council_Area,'3BR_H-processed'!$E$1:$F$1,0)), INDEX('2BR_F-processed'!$E:$F,MATCH($L60,'2BR_F-processed'!$B:$B,0),MATCH(Council_Area,'2BR_F-processed'!$E$1:$F$1,0))) -> 360 | U60: =IF(MOD(Q60,4)=1,T60,U59) -> 380 | V60: =U60*(R60)/7 -> 4940 | W60: =$B$53/4*BH60/_xlfn.XLOOKUP(Q_end,cpi!A:A,cpi!B:B) -> 158.25847 | X60: =V60+W60 -> 5098.2585 | Y60: =BG60-X60 -> 415.34442 | Z60: =Y60*$B$47 -> 0 | AA60: {=(Y60+Z60)*eff_invest} -> 415.34442 | AB60: =AA60*(_xlfn.XLOOKUP(Q_end,cpi!A:A,cpi!B:B)/BH60) -> 524.89377 | AC60: {=INDEX('msci-indices'!C:C,MATCH($L60,'msci-indices'!$B:$B)-2)} -> 1491.4482 | AD60: {=INDEX('msci-indices'!D:D,MATCH($L60,'msci-indices'!$B:$B)-2)} -> 1384.5123 | AE60: =AI59+AA60 -> 270100.63 | AF60: {=INDEX('msci-indices'!C:C,MATCH($L60,'msci-indices'!$B:$B)+1)} -> 1788.7914 | AG60: {=INDEX('msci-indices'!D:D,MATCH($L60,'msci-indices'!$B:$B)+1)} -> 1621.6232 | AH60: =(InvestFees/4)*AE60 -> 168.81289 | AI60: =((AF60/AC60)*GlobalPortfolio+(AG60/AD60)*AusPortfolio)*AE60-AH60 -> 321503.12 | AJ60: =AJ59+AA60 -> 158096.41 | AK60: =AI60-AJ60 -> 163406.71 | AL60: =AJ60*(_xlfn.XLOOKUP(Q_end,cpi!A:A,cpi!B:B)/BH60) -> 199795.2 | AM60: {=SUMPRODUCT($AA$3:AA60,_xlfn.SORTBY($BH$3:BH60,_xlfn.SEQUENCE(ROWS($BH$3:BH60)),-1)/$BH$3)} -> 205501.83 | AN60: =AI60-AM60 -> 116001.29 | AO60: =IF($B$49="Real gains",MAX($B$50*AN60,0),IF($B$49="Discounted nominal gains",MAX($B$50*AK60/2,0),0)) -> 0 | AP60: =AI60-AO60 -> 321503.12 | AR60: =IF($B$10="3BR_H", INDEX('ns-combined'!$C:$D,MATCH($L60,'ns-combined'!$B:$B,0),MATCH(Council_Area,'ns-combined'!$C$1:$D$1,0))*1000, INDEX('s-combined'!$C:$D,MATCH($L60,'s-combined'!$B:$B,0),MATCH(Council_Area,'s-combined'!$C$1:$D$1,0))*1000) -> 487500 | AS60: =AS59+$AS$3 -> 40600 | AT60: 0 | AU60: =SUM($B$28:$B$29)*AR60 -> 9750 | AV60: =AR60*$B$15/4 -> 1401.5625 | AW60: =SUM($AV$3:AV60) -> 67329.338 | AX60: =AR60-AS60-AU60-AW60 -> 369820.66 | AY60: =$B$36*V60 -> 1729 | AZ60: =SUM(AY60:AY60)*4/AR60 -> 0.014186667 | BA60: =SUM(AY60:AY60)/V60 -> 0.35 | BB60: =IF(MortgageRate="Discounted",_xlfn.XLOOKUP(L60,'mortgage-rates'!$A:$A,'mortgage-rates'!$E:$E)/100,_xlfn.XLOOKUP(L60,'mortgage-rates'!$A:$A,'mortgage-rates'!$D:$D)/100) -> 0.0365 | BC60: =BC59-BF59 -> 134108.19 | BD60: =IF($B$16*12/3-Q60+1>0,-PMT($BB60/4,$B$16*12/3-Q60+1,BC60),0) -> 3784.6029 | BE60: =BC60*($BB60/4) -> 1223.7372 | BF60: =BD60-BE60 -> 2560.8657 | BG60: =AT60+AY60+BD60 -> 5513.6029 | BH60: =INDEX(cpi!B:B,MATCH($L60,cpi!A:A)) -> 114.5 | BI60: =100*BH60/BH$3 -> 135.34279 | BJ60: =100*AC60/AC$3 -> 197.57431 | BK60: =100*AD60/AD$3 -> 194.19317 | BL60: =BJ60*GlobalPortfolio+BK60*AusPortfolio -> 196.55997 | BM60: =100*AE60/$AE$3 -> 369.62156 | BN60: =100*AR60/AR$3 -> 174.10714 | BO60: =100*AX60/AX$3 -> 135.51757
L61: =DATE(YEAR(L60),MONTH(L60)+3,1) -> 44075 | M61: =AP61 -> 339382.68 | N61: =AX61-BC61 -> 248385.84 | O61: =M61/N61 -> 1.3663528 | P61: =X61/BG61 -> 0.93173032 | Q61: 59 | R61: =EOMONTH(L61,0)-EOMONTH(L61,-3) -> 92 | T61: =IF($B$10="3BR_H", INDEX('3BR_H-processed'!$E:$F,MATCH($L61,'3BR_H-processed'!$B:$B,0),MATCH(Council_Area,'3BR_H-processed'!$E$1:$F$1,0)), INDEX('2BR_F-processed'!$E:$F,MATCH($L61,'2BR_F-processed'!$B:$B,0),MATCH(Council_Area,'2BR_F-processed'!$E$1:$F$1,0))) -> 375 | U61: =IF(MOD(Q61,4)=1,T61,U60) -> 380 | V61: =U61*(R61)/7 -> 4994.2857 | W61: =$B$53/4*BH61/_xlfn.XLOOKUP(Q_end,cpi!A:A,cpi!B:B) -> 160.60815 | X61: =V61+W61 -> 5154.8939 | Y61: =BG61-X61 -> 377.70901 | Z61: =Y61*$B$47 -> 0 | AA61: {=(Y61+Z61)*eff_invest} -> 377.70901 | AB61: =AA61*(_xlfn.XLOOKUP(Q_end,cpi!A:A,cpi!B:B)/BH61) -> 470.34849 | AC61: {=INDEX('msci-indices'!C:C,MATCH($L61,'msci-indices'!$B:$B)-2)} -> 1788.7914 | AD61: {=INDEX('msci-indices'!D:D,MATCH($L61,'msci-indices'!$B:$B)-2)} -> 1621.6232 | AE61: =AI60+AA61 -> 321880.83 | AF61: {=INDEX('msci-indices'!C:C,MATCH($L61,'msci-indices'!$B:$B)+1)} -> 1929.6384 | AG61: {=INDEX('msci-indices'!D:D,MATCH($L61,'msci-indices'!$B:$B)+1)} -> 1620.9838 | AH61: =(InvestFees/4)*AE61 -> 201.17552 | AI61: =((AF61/AC61)*GlobalPortfolio+(AG61/AD61)*AusPortfolio)*AE61-AH61 -> 339382.68 | AJ61: =AJ60+AA61 -> 158474.12 | AK61: =AI61-AJ61 -> 180908.57 | AL61: =AJ61*(_xlfn.XLOOKUP(Q_end,cpi!A:A,cpi!B:B)/BH61) -> 197342.55 | AM61: {=SUMPRODUCT($AA$3:AA61,_xlfn.SORTBY($BH$3:BH61,_xlfn.SEQUENCE(ROWS($BH$3:BH61)),-1)/$BH$3)} -> 207803.94 | AN61: =AI61-AM61 -> 131578.74 | AO61: =IF($B$49="Real gains",MAX($B$50*AN61,0),IF($B$49="Discounted nominal gains",MAX($B$50*AK61/2,0),0)) -> 0 | AP61: =AI61-AO61 -> 339382.68 | AR61: =IF($B$10="3BR_H", INDEX('ns-combined'!$C:$D,MATCH($L61,'ns-combined'!$B:$B,0),MATCH(Council_Area,'ns-combined'!$C$1:$D$1,0))*1000, INDEX('s-combined'!$C:$D,MATCH($L61,'s-combined'!$B:$B,0),MATCH(Council_Area,'s-combined'!$C$1:$D$1,0))*1000) -> 500000 | AS61: =AS60+$AS$3 -> 41300 | AT61: 0 | AU61: =SUM($B$28:$B$29)*AR61 -> 10000 | AV61: =AR61*$B$15/4 -> 1437.5 | AW61: =SUM($AV$3:AV61) -> 68766.838 | AX61: =AR61-AS61-AU61-AW61 -> 379933.16 | AY61: =$B$36*V61 -> 1748 | AZ61: =SUM(AY61:AY61)*4/AR61 -> 0.013984 | BA61: =SUM(AY61:AY61)/V61 -> 0.35 | BB61: =IF(MortgageRate="Discounted",_xlfn.XLOOKUP(L61,'mortgage-rates'!$A:$A,'mortgage-rates'!$E:$E)/100,_xlfn.XLOOKUP(L61,'mortgage-rates'!$A:$A,'mortgage-rates'!$D:$D)/100) -> 0.0365 | BC61: =BC60-BF60 -> 131547.32 | BD61: =IF($B$16*12/3-Q61+1>0,-PMT($BB61/4,$B$16*12/3-Q61+1,BC61),0) -> 3784.6029 | BE61: =BC61*($BB61/4) -> 1200.3693 | BF61: =BD61-BE61 -> 2584.2336 | BG61: =AT61+AY61+BD61 -> 5532.6029 | BH61: =INDEX(cpi!B:B,MATCH($L61,cpi!A:A)) -> 116.2 | BI61: =100*BH61/BH$3 -> 137.35225 | BJ61: =100*AC61/AC$3 -> 236.9638 | BK61: =100*AD61/AD$3 -> 227.4506 | BL61: =BJ61*GlobalPortfolio+BK61*AusPortfolio -> 234.10984 | BM61: =100*AE61/$AE$3 -> 440.48062 | BN61: =100*AR61/AR$3 -> 178.57143 | BO61: =100*AX61/AX$3 -> 139.2232
L62: =DATE(YEAR(L61),MONTH(L61)+3,1) -> 44166 | M62: =AP62 -> 389821.75 | N62: =AX62-BC62 -> 261046.64 | O62: =M62/N62 -> 1.4933031 | P62: =X62/BG62 -> 0.93198015 | Q62: 60 | R62: =EOMONTH(L62,0)-EOMONTH(L62,-3) -> 92 | T62: =IF($B$10="3BR_H", INDEX('3BR_H-processed'!$E:$F,MATCH($L62,'3BR_H-processed'!$B:$B,0),MATCH(Council_Area,'3BR_H-processed'!$E$1:$F$1,0)), INDEX('2BR_F-processed'!$E:$F,MATCH($L62,'2BR_F-processed'!$B:$B,0),MATCH(Council_Area,'2BR_F-processed'!$E$1:$F$1,0))) -> 390 | U62: =IF(MOD(Q62,4)=1,T62,U61) -> 380 | V62: =U62*(R62)/7 -> 4994.2857 | W62: =$B$53/4*BH62/_xlfn.XLOOKUP(Q_end,cpi!A:A,cpi!B:B) -> 161.99032 | X62: =V62+W62 -> 5156.276 | Y62: =BG62-X62 -> 376.32684 | Z62: =Y62*$B$47 -> 0 | AA62: {=(Y62+Z62)*eff_invest} -> 376.32684 | AB62: =AA62*(_xlfn.XLOOKUP(Q_end,cpi!A:A,cpi!B:B)/BH62) -> 464.62879 | AC62: {=INDEX('msci-indices'!C:C,MATCH($L62,'msci-indices'!$B:$B)-2)} -> 1929.6384 | AD62: {=INDEX('msci-indices'!D:D,MATCH($L62,'msci-indices'!$B:$B)-2)} -> 1620.9838 | AE62: =AI61+AA62 -> 339759.01 | AF62: {=INDEX('msci-indices'!C:C,MATCH($L62,'msci-indices'!$B:$B)+1)} -> 2220.9403 | AG62: {=INDEX('msci-indices'!D:D,MATCH($L62,'msci-indices'!$B:$B)+1)} -> 1849.5395 | AH62: =(InvestFees/4)*AE62 -> 212.34938 | AI62: =((AF62/AC62)*GlobalPortfolio+(AG62/AD62)*AusPortfolio)*AE62-AH62 -> 389821.75 | AJ62: =AJ61+AA62 -> 158850.44 | AK62: =AI62-AJ62 -> 230971.3 | AL62: =AJ62*(_xlfn.XLOOKUP(Q_end,cpi!A:A,cpi!B:B)/BH62) -> 196123.37 | AM62: {=SUMPRODUCT($AA$3:AA62,_xlfn.SORTBY($BH$3:BH62,_xlfn.SEQUENCE(ROWS($BH$3:BH62)),-1)/$BH$3)} -> 209532.02 | AN62: =AI62-AM62 -> 180289.73 | AO62: =IF($B$49="Real gains",MAX($B$50*AN62,0),IF($B$49="Discounted nominal gains",MAX($B$50*AK62/2,0),0)) -> 0 | AP62: =AI62-AO62 -> 389821.75 | AR62: =IF($B$10="3BR_H", INDEX('ns-combined'!$C:$D,MATCH($L62,'ns-combined'!$B:$B,0),MATCH(Council_Area,'ns-combined'!$C$1:$D$1,0))*1000, INDEX('s-combined'!$C:$D,MATCH($L62,'s-combined'!$B:$B,0),MATCH(Council_Area,'s-combined'!$C$1:$D$1,0))*1000) -> 512500 | AS62: =AS61+$AS$3 -> 42000 | AT62: 0 | AU62: =SUM($B$28:$B$29)*AR62 -> 10250 | AV62: =AR62*$B$15/4 -> 1473.4375 | AW62: =SUM($AV$3:AV62) -> 70240.275 | AX62: =AR62-AS62-AU62-AW62 -> 390009.72 | AY62: =$B$36*V62 -> 1748 | AZ62: =SUM(AY62:AY62)*4/AR62 -> 0.013642927 | BA62: =SUM(AY62:AY62)/V62 -> 0.35 | BB62: =IF(MortgageRate="Discounted",_xlfn.XLOOKUP(L62,'mortgage-rates'!$A:$A,'mortgage-rates'!$E:$E)/100,_xlfn.XLOOKUP(L62,'mortgage-rates'!$A:$A,'mortgage-rates'!$D:$D)/100) -> 0.0365 | BC62: =BC61-BF61 -> 128963.09 | BD62: =IF($B$16*12/3-Q62+1>0,-PMT($BB62/4,$B$16*12/3-Q62+1,BC62),0) -> 3784.6029 | BE62: =BC62*($BB62/4) -> 1176.7882 | BF62: =BD62-BE62 -> 2607.8147 | BG62: =AT62+AY62+BD62 -> 5532.6029 | BH62: =INDEX(cpi!B:B,MATCH($L62,cpi!A:A)) -> 117.2 | BI62: =100*BH62/BH$3 -> 138.53428 | BJ62: =100*AC62/AC$3 -> 255.622 | BK62: =100*AD62/AD$3 -> 227.36091 | BL62: =BJ62*GlobalPortfolio+BK62*AusPortfolio -> 247.14367 | BM62: =100*AE62/$AE$3 -> 464.94618 | BN62: =100*AR62/AR$3 -> 183.03571 | BO62: =100*AX62/AX$3 -> 142.91567
L63: =DATE(YEAR(L62),MONTH(L62)+3,1) -> 44256 | M63: =AP63 -> 409959.41 | N63: =AX63-BC63 -> 271740.83 | O63: =M63/N63 -> 1.5086412 | P63: =X63/BG63 -> 0.95005444 | Q63: 61 | R63: =EOMONTH(L63,0)-EOMONTH(L63,-3) -> 90 | T63: =IF($B$10="3BR_H", INDEX('3BR_H-processed'!$E:$F,MATCH($L63,'3BR_H-processed'!$B:$B,0),MATCH(Council_Area,'3BR_H-processed'!$E$1:$F$1,0)), INDEX('2BR_F-processed'!$E:$F,MATCH($L63,'2BR_F-processed'!$B:$B,0),MATCH(Council_Area,'2BR_F-processed'!$E$1:$F$1,0))) -> 400 | U63: =IF(MOD(Q63,4)=1,T63,U62) -> 400 | V63: =U63*(R63)/7 -> 5142.8571 | W63: =$B$53/4*BH63/_xlfn.XLOOKUP(Q_end,cpi!A:A,cpi!B:B) -> 162.81963 | X63: =V63+W63 -> 5305.6768 | Y63: =BG63-X63 -> 278.92611 | Z63: =Y63*$B$47 -> 0 | AA63: {=(Y63+Z63)*eff_invest} -> 278.92611 | AB63: =AA63*(_xlfn.XLOOKUP(Q_end,cpi!A:A,cpi!B:B)/BH63) -> 342.61977 | AC63: {=INDEX('msci-indices'!C:C,MATCH($L63,'msci-indices'!$B:$B)-2)} -> 2220.9403 | AD63: {=INDEX('msci-indices'!D:D,MATCH($L63,'msci-indices'!$B:$B)-2)} -> 1849.5395 | AE63: =AI62+AA63 -> 390100.68 | AF63: {=INDEX('msci-indices'!C:C,MATCH($L63,'msci-indices'!$B:$B)+1)} -> 2342.5855 | AG63: {=INDEX('msci-indices'!D:D,MATCH($L63,'msci-indices'!$B:$B)+1)} -> 1930.8659 | AH63: =(InvestFees/4)*AE63 -> 243.81292 | AI63: =((AF63/AC63)*GlobalPortfolio+(AG63/AD63)*AusPortfolio)*AE63-AH63 -> 409959.41 | AJ63: =AJ62+AA63 -> 159129.37 | AK63: =AI63-AJ63 -> 250830.04 | AL63: =AJ63*(_xlfn.XLOOKUP(Q_end,cpi!A:A,cpi!B:B)/BH63) -> 195467.06 | AM63: {=SUMPRODUCT($AA$3:AA63,_xlfn.SORTBY($BH$3:BH63,_xlfn.SEQUENCE(ROWS($BH$3:BH63)),-1)/$BH$3)} -> 210831.34 | AN63: =AI63-AM63 -> 199128.07 | AO63: =IF($B$49="Real gains",MAX($B$50*AN63,0),IF($B$49="Discounted nominal gains",MAX($B$50*AK63/2,0),0)) -> 0 | AP63: =AI63-AO63 -> 409959.41 | AR63: =IF($B$10="3BR_H", INDEX('ns-combined'!$C:$D,MATCH($L63,'ns-combined'!$B:$B,0),MATCH(Council_Area,'ns-combined'!$C$1:$D$1,0))*1000, INDEX('s-combined'!$C:$D,MATCH($L63,'s-combined'!$B:$B,0),MATCH(Council_Area,'s-combined'!$C$1:$D$1,0))*1000) -> 523000 | AS63: =AS62+$AS$3 -> 42700 | AT63: 0 | AU63: =SUM($B$28:$B$29)*AR63 -> 10460 | AV63: =AR63*$B$15/4 -> 1503.625 | AW63: =SUM($AV$3:AV63) -> 71743.9 | AX63: =AR63-AS63-AU63-AW63 -> 398096.1 | AY63: =$B$36*V63 -> 1800 | AZ63: =SUM(AY63:AY63)*4/AR63 -> 0.01376673 | BA63: =SUM(AY63:AY63)/V63 -> 0.35 | BB63: =IF(MortgageRate="Discounted",_xlfn.XLOOKUP(L63,'mortgage-rates'!$A:$A,'mortgage-rates'!$E:$E)/100,_xlfn.XLOOKUP(L63,'mortgage-rates'!$A:$A,'mortgage-rates'!$D:$D)/100) -> 0.0365 | BC63: =BC62-BF62 -> 126355.27 | BD63: =IF($B$16*12/3-Q63+1>0,-PMT($BB63/4,$B$16*12/3-Q63+1,BC63),0) -> 3784.6029 | BE63: =BC63*($BB63/4) -> 1152.9919 | BF63: =BD63-BE63 -> 2631.611 | BG63: =AT63+AY63+BD63 -> 5584.6029 | BH63: =INDEX(cpi!B:B,MATCH($L63,cpi!A:A)) -> 117.8 | BI63: =100*BH63/BH$3 -> 139.2435 | BJ63: =100*AC63/AC$3 -> 294.21119 | BK63: =100*AD63/AD$3 -> 259.41837 | BL63: =BJ63*GlobalPortfolio+BK63*AusPortfolio -> 283.77335 | BM63: =100*AE63/$AE$3 -> 533.83667 | BN63: =100*AR63/AR$3 -> 186.78571 | BO63: =100*AX63/AX$3 -> 145.87885
L64: =DATE(YEAR(L63),MONTH(L63)+3,1) -> 44348 | M64: =AP64 -> 441606.32 | N64: =AX64-BC64 -> 298551.19 | O64: =M64/N64 -> 1.4791645 | P64: =X64/BG64 -> 0.95891948 | Q64: 62 | R64: =EOMONTH(L64,0)-EOMONTH(L64,-3) -> 91 | T64: =IF($B$10="3BR_H", INDEX('3BR_H-processed'!$E:$F,MATCH($L64,'3BR_H-processed'!$B:$B,0),MATCH(Council_Area,'3BR_H-processed'!$E$1:$F$1,0)), INDEX('2BR_F-processed'!$E:$F,MATCH($L64,'2BR_F-processed'!$B:$B,0),MATCH(Council_Area,'2BR_F-processed'!$E$1:$F$1,0))) -> 400 | U64: =IF(MOD(Q64,4)=1,T64,U63) -> 400 | V64: =U64*(R64)/7 -> 5200 | W64: =$B$53/4*BH64/_xlfn.XLOOKUP(Q_end,cpi!A:A,cpi!B:B) -> 164.2018 | X64: =V64+W64 -> 5364.2018 | Y64: =BG64-X64 -> 229.80468 | Z64: =Y64*$B$47 -> 0 | AA64: {=(Y64+Z64)*eff_invest} -> 229.80468 | AB64: =AA64*(_xlfn.XLOOKUP(Q_end,cpi!A:A,cpi!B:B)/BH64) -> 279.90519 | AC64: {=INDEX('msci-indices'!C:C,MATCH($L64,'msci-indices'!$B:$B)-2)} -> 2342.5855 | AD64: {=INDEX('msci-indices'!D:D,MATCH($L64,'msci-indices'!$B:$B)-2)} -> 1930.8659 | AE64: =AI63+AA64 -> 410189.22 | AF64: {=INDEX('msci-indices'!C:C,MATCH($L64,'msci-indices'!$B:$B)+1)} -> 2515.6062 | AG64: {=INDEX('msci-indices'!D:D,MATCH($L64,'msci-indices'!$B:$B)+1)} -> 2095.0894 | AH64: =(InvestFees/4)*AE64 -> 256.36826 | AI64: =((AF64/AC64)*GlobalPortfolio+(AG64/AD64)*AusPortfolio)*AE64-AH64 -> 441606.32 | AJ64: =AJ63+AA64 -> 159359.18 | AK64: =AI64-AJ64 -> 282247.15 | AL64: =AJ64*(_xlfn.XLOOKUP(Q_end,cpi!A:A,cpi!B:B)/BH64) -> 194101.62 | AM64: {=SUMPRODUCT($AA$3:AA64,_xlfn.SORTBY($BH$3:BH64,_xlfn.SEQUENCE(ROWS($BH$3:BH64)),-1)/$BH$3)} -> 212438.98 | AN64: =AI64-AM64 -> 229167.35 | AO64: =IF($B$49="Real gains",MAX($B$50*AN64,0),IF($B$49="Discounted nominal gains",MAX($B$50*AK64/2,0),0)) -> 0 | AP64: =AI64-AO64 -> 441606.32 | AR64: =IF($B$10="3BR_H", INDEX('ns-combined'!$C:$D,MATCH($L64,'ns-combined'!$B:$B,0),MATCH(Council_Area,'ns-combined'!$C$1:$D$1,0))*1000, INDEX('s-combined'!$C:$D,MATCH($L64,'s-combined'!$B:$B,0),MATCH(Council_Area,'s-combined'!$C$1:$D$1,0))*1000) -> 550000 | AS64: =AS63+$AS$3 -> 43400 | AT64: 0 | AU64: =SUM($B$28:$B$29)*AR64 -> 11000 | AV64: =AR64*$B$15/4 -> 1581.25 | AW64: =SUM($AV$3:AV64) -> 73325.15 | AX64: =AR64-AS64-AU64-AW64 -> 422274.85 | AY64: =$B$36*V64 -> 1820 | AZ64: =SUM(AY64:AY64)*4/AR64 -> 0.013236364 | BA64: =SUM(AY64:AY64)/V64 -> 0.35 | BB64: =IF(MortgageRate="Discounted",_xlfn.XLOOKUP(L64,'mortgage-rates'!$A:$A,'mortgage-rates'!$E:$E)/100,_xlfn.XLOOKUP(L64,'mortgage-rates'!$A:$A,'mortgage-rates'!$D:$D)/100) -> 0.0359 | BC64: =BC63-BF63 -> 123723.66 | BD64: =IF($B$16*12/3-Q64+1>0,-PMT($BB64/4,$B$16*12/3-Q64+1,BC64),0) -> 3774.0065 | BE64: =BC64*($BB64/4) -> 1110.4199 | BF64: =BD64-BE64 -> 2663.5866 | BG64: =AT64+AY64+BD64 -> 5594.0065 | BH64: =INDEX(cpi!B:B,MATCH($L64,cpi!A:A)) -> 118.8 | BI64: =100*BH64/BH$3 -> 140.42553 | BJ64: =100*AC64/AC$3 -> 310.3257 | BK64: =100*AD64/AD$3 -> 270.8253 | BL64: =BJ64*GlobalPortfolio+BK64*AusPortfolio -> 298.47558 | BM64: =100*AE64/$AE$3 -> 561.327 | BN64: =100*AR64/AR$3 -> 196.42857 | BO64: =100*AX64/AX$3 -> 154.73895
