Workbook
Name A83728543L: 'ABS-total-value-dwellings'!$AF$1:$AF$10,'ABS-total-value-dwellings'!$AF$11:$AF$106
Name A83728543L_Data: 'ABS-total-value-dwellings'!$AF$11:$AF$106
Name A83728543L_Latest: 'ABS-total-value-dwellings'!$AF$106
Name A83728544R: 'ABS-total-value-dwellings'!$AU$1:$AU$10,'ABS-total-value-dwellings'!$AU$17:$AU$106
Name A83728544R_Data: 'ABS-total-value-dwellings'!$AU$17:$AU$106
Name A83728544R_Latest: 'ABS-total-value-dwellings'!$AU$106
Name A83728545T: 'ABS-total-value-dwellings'!$B$1:$B$10,'ABS-total-value-dwellings'!$B$11:$B$106
Name A83728545T_Data: 'ABS-total-value-dwellings'!$B$11:$B$106
Name A83728545T_Latest: 'ABS-total-value-dwellings'!$B$106
Name A83728546V: 'ABS-total-value-dwellings'!$Q$1:$Q$10,'ABS-total-value-dwellings'!$Q$17:$Q$106
Name A83728546V_Data: 'ABS-total-value-dwellings'!$Q$17:$Q$106
Name A83728546V_Latest: 'ABS-total-value-dwellings'!$Q$106
Name A83728547W: 'ABS-total-value-dwellings'!$AH$1:$AH$10,'ABS-total-value-dwellings'!$AH$11:$AH$106
Name A83728547W_Data: 'ABS-total-value-dwellings'!$AH$11:$AH$106
Name A83728547W_Latest: 'ABS-total-value-dwellings'!$AH$106
Name A83728548X: 'ABS-total-value-dwellings'!$AW$1:$AW$10,'ABS-total-value-dwellings'!$AW$17:$AW$106
Name A83728548X_Data: 'ABS-total-value-dwellings'!$AW$17:$AW$106
Name A83728548X_Latest: 'ABS-total-value-dwellings'!$AW$106
Name A83728549A: 'ABS-total-value-dwellings'!$D$1:$D$10,'ABS-total-value-dwellings'!$D$11:$D$106
Name A83728549A_Data: 'ABS-total-value-dwellings'!$D$11:$D$106
Name A83728549A_Latest: 'ABS-total-value-dwellings'!$D$106
Name A83728550K: 'ABS-total-value-dwellings'!$S$1:$S$10,'ABS-total-value-dwellings'!$S$17:$S$106
Name A83728550K_Data: 'ABS-total-value-dwellings'!$S$17:$S$106
Name A83728550K_Latest: 'ABS-total-value-dwellings'!$S$106
Name A83728551L: 'ABS-total-value-dwellings'!$AJ$1:$AJ$10,'ABS-total-value-dwellings'!$AJ$11:$AJ$106
Name A83728551L_Data: 'ABS-total-value-dwellings'!$AJ$11:$AJ$106
Name A83728551L_Latest: 'ABS-total-value-dwellings'!$AJ$106
Name A83728552R: 'ABS-total-value-dwellings'!$AY$1:$AY$10,'ABS-total-value-dwellings'!$AY$17:$AY$106
Name A83728552R_Data: 'ABS-total-value-dwellings'!$AY$17:$AY$106
Name A83728552R_Latest: 'ABS-total-value-dwellings'!$AY$106
Name A83728553T: 'ABS-total-value-dwellings'!$F$1:$F$10,'ABS-total-value-dwellings'!$F$11:$F$106
Name A83728553T_Data: 'ABS-total-value-dwellings'!$F$11:$F$106
Name A83728553T_Latest: 'ABS-total-value-dwellings'!$F$106
Name A83728554V: 'ABS-total-value-dwellings'!$U$1:$U$10,'ABS-total-value-dwellings'!$U$17:$U$106
Name A83728554V_Data: 'ABS-total-value-dwellings'!$U$17:$U$106
Name A83728554V_Latest: 'ABS-total-value-dwellings'!$U$106
Name A83728555W: 'ABS-total-value-dwellings'!$AL$1:$AL$10,'ABS-total-value-dwellings'!$AL$11:$AL$106
Name A83728555W_Data: 'ABS-total-value-dwellings'!$AL$11:$AL$106
Name A83728555W_Latest: 'ABS-total-value-dwellings'!$AL$106
Name A83728556X: 'ABS-total-value-dwellings'!$BA$1:$BA$10,'ABS-total-value-dwellings'!$BA$17:$BA$106
Name A83728556X_Data: 'ABS-total-value-dwellings'!$BA$17:$BA$106
Name A83728556X_Latest: 'ABS-total-value-dwellings'!$BA$106
Name A83728557A: 'ABS-total-value-dwellings'!$H$1:$H$10,'ABS-total-value-dwellings'!$H$11:$H$106
Name A83728557A_Data: 'ABS-total-value-dwellings'!$H$11:$H$106
Name A83728557A_Latest: 'ABS-total-value-dwellings'!$H$106
Name A83728558C: 'ABS-total-value-dwellings'!$W$1:$W$10,'ABS-total-value-dwellings'!$W$17:$W$106
Name A83728558C_Data: 'ABS-total-value-dwellings'!$W$17:$W$106
Name A83728558C_Latest: 'ABS-total-value-dwellings'!$W$106
Name A83728559F: 'ABS-total-value-dwellings'!$AN$1:$AN$10,'ABS-total-value-dwellings'!$AN$11:$AN$106
Name A83728559F_Data: 'ABS-total-value-dwellings'!$AN$11:$AN$106
Name A83728559F_Latest: 'ABS-total-value-dwellings'!$AN$106
Name A83728560R: 'ABS-total-value-dwellings'!$BC$1:$BC$10,'ABS-total-value-dwellings'!$BC$17:$BC$106
Name A83728560R_Data: 'ABS-total-value-dwellings'!$BC$17:$BC$106
Name A83728560R_Latest: 'ABS-total-value-dwellings'!$BC$106
Name A83728561T: 'ABS-total-value-dwellings'!$J$1:$J$10,'ABS-total-value-dwellings'!$J$11:$J$106
Name A83728561T_Data: 'ABS-total-value-dwellings'!$J$11:$J$106
Name A83728561T_Latest: 'ABS-total-value-dwellings'!$J$106
Name A83728562V: 'ABS-total-value-dwellings'!$Y$1:$Y$10,'ABS-total-value-dwellings'!$Y$17:$Y$106
Name A83728562V_Data: 'ABS-total-value-dwellings'!$Y$17:$Y$106
Name A83728562V_Latest: 'ABS-total-value-dwellings'!$Y$106

Sheet analysis
A1: Rent vs buy analysis - Melbourne | B1: Set values | C1: Default values | T1: Renter calcs >> | X1: {=SUM(_xlfn._xlws.FILTER(X3:X82,ISNUMBER(X3:X82)))} -> 403722.45 | AI1: CGT calcs | AR1: Buyer calcs >> | AY1: Maintenance and renovation | BB1: Mortgage | BG1: {=SUM(_xlfn._xlws.FILTER(BG3:BG82,ISNUMBER(BG3:BG82)))} -> 627152.62 | BH1: Comparison vs inflation
A2: Ending renter-to-owner wealth ratio | B2: =_xlfn.XLOOKUP(Q_end,L:L,O:O) -> 1.5572555 | E2: ="Renter vs owner wealth, "&Council_Area&IF(B10="2BR_F"," 2-bedroom flat"," 3-bedroom house") -> Renter vs owner wealth, Melbourne 3-bedroom house | L2: Quarter ending | M2: Renter's portfolio | N2: Owner's home equity | O2: Renter-to-owner wealth ratio | P2: Renter-to-owner cash needs | Q2: Quarter of analysis | R2: Days in quarter | T2: Median weekly rents, new bonds | U2: Renter's rents | V2: Quarterly rent | W2: Other renter costs | X2: Renter's cashflow costs | Y2: Renter additional cashflow | Z2: Tax concessions | AA2: Renter investment contributions | AB2: Contributions (CPI-adjusted to Q_end) | AC2: MSCI World index, start Q | AD2: MSCI Aus index, start Q | AE2: Portfolio, start Q | AF2: MSCI World index, end Q | AG2: MSCI Aus index, end Q | AH2: Investment fees | AI2: Portfolio, end Q, before CGT | AJ2: Cost base (nominal) | AK2: Nominal gains ($) | AL2: Cost base (CPI-adjusted to Q_end) | AM2: Cost base + CPI to current quarter | AN2: Real gains ($) | AO2: CGT on withdrawals | AP2: Portfolio, end Q | AR2: Median home price | AS2: Depreciation | AT2: Home purchase costs | AU2: Home sale costs | AV2: Renovation | AW2: Renovation, cumulative | AX2: Adjusted home price | AY2: Maintenance | AZ2: Total p.a. as % of home value | BA2: Total p.a. as % of rent | BB2: Mortgage rates | BC2: Loan balance | BD2: Mortgage payment | BE2: Mortgage interest | BF2: Mortgage - principal component | BG2: Owner's cashflow costs | BH2: CPI | BI2: CPI (Q_st art = 100) | BJ2: MSCI World (Q_start=100) | BK2: MSCI Aus (Q_start=100) | BL2: Portfolio index (Q_start=100) | BM2: Portfolio (Q_start=100) | BN2: Median home price (Q_start = 100) | BO2: Adjusted home price (Q_start = 100)
A3: Average renter-to-owner cashflow needs excl. home purchase costs | B3: {=SUM(_xlfn._xlws.FILTER($X$3:$X$82,ISNUMBER($X$3:$X$82)))/(SUM(_xlfn._xlws.FILTER($BG$3:$BG$82,ISNUMBER($BG$3:$BG$82)))-AT3)} -> 0.74660741 | L3: =Q_start -> 38777 | M3: =AP3 -> 96819.448 | N3: =AX3-BC3 -> 57626.25 | O3: =M3/N3 -> 1.6801275 | P3: =X3/BG3 -> 0.033099484 | Q3: 1 | R3: =EOMONTH(L3,0)-EOMONTH(L3,-3) -> 90 | T3: =IF($B$10="3BR_H", INDEX('3BR_H-processed'!$C:$D,MATCH($L3,'3BR_H-processed'!$B:$B,0),MATCH(Council_Area,'3BR_H-processed'!$C$1:$D$1,0)), INDEX('2BR_F-processed'!$C:$D,MATCH($L3,'2BR_F-processed'!$B:$B,0),MATCH(Council_Area,'2BR_F-processed'!$C$1:$D$1,0))) -> 230 | U3: =IF(MOD(Q3,4)=1,T3,U2) -> 230 | V3: =U3*(R3)/7 -> 2957.1429 | W3: =$B$53/4*BH3/_xlfn.XLOOKUP(Q_end,cpi!A:A,cpi!B:B) -> 116.93158 | X3: =V3+W3 -> 3074.0744 | Y3: =BG3-X3 -> 89799.712 | Z3: =MAX(0,Y3*$B$47) -> 0 | AA3: {=(Y3+Z3)*eff_invest} -> 89799.712 | AB3: =AA3*(_xlfn.XLOOKUP(Q_end,cpi!A:A,cpi!B:B)/BH3) -> 153593.6 | AC3: {=INDEX('msci-indices'!C:C,MATCH($L3,'msci-indices'!$B:$B)-2)} -> 754.87961 | AD3: {=INDEX('msci-indices'!D:D,MATCH($L3,'msci-indices'!$B:$B)-2)} -> 712.95625 | AE3: =AA3 -> 89799.712 | AF3: {=INDEX('msci-indices'!C:C,MATCH($L3,'msci-indices'!$B:$B)+1)} -> 809.32012 | AG3: {=INDEX('msci-indices'!D:D,MATCH($L3,'msci-indices'!$B:$B)+1)} -> 780.24347 | AH3: =(InvestFees/4)*AE3 -> 56.12482 | AI3: =((AF3/AC3)*GlobalPortfolio+(AG3/AD3)*AusPortfolio)*AE3-AH3 -> 96819.448 | AJ3: =AA3 -> 89799.712 | AK3: =AI3-AJ3 -> 7019.7355 | AL3: =AJ3*(_xlfn.XLOOKUP(Q_end,cpi!A:A,cpi!B:B)/BH3) -> 153593.6 | AM3: =AA3 -> 89799.712 | AN3: =AI3-AM3 -> 7019.7355 | AO3: =IF($B$49="Real gains",MAX($B$50*AN3,0),IF($B$49="Discounted nominal gains",MAX($B$50*AK3/2,0),0)) -> 0 | AP3: =AI3-AO3 -> 96819.448 | AR3: =IF($B$10="3BR_H", INDEX('ns-combined'!$C:$D,MATCH($L3,'ns-combined'!$B:$B,0),MATCH(Council_Area,'ns-combined'!$C$1:$D$1,0))*1000, INDEX('s-combined'!$C:$D,MATCH($L3,'s-combined'!$B:$B,0),MATCH(Council_Area,'s-combined'!$C$1:$D$1,0))*1000) -> 330000 | AS3: =AR3*$B$14/4 -> 825 | AT3: =SUM(B20:B26)*AR3 -> 86410 | AU3: =SUM($B$28:$B$29)*AR3 -> 6600 | AV3: =AR3*$B$15/4 -> 948.75 | AW3: =SUM($AV$3:AV3) -> 948.75 | AX3: =AR3-AS3-AU3-AW3 -> 321626.25 | AY3: =$B$36*V3 -> 1035 | AZ3: =SUM(AY3:AY3)*4/AR3 -> 0.012545455 | BA3: =SUM(AY3:AY3)/V3 -> 0.35 | BB3: =IF(MortgageRate="Discounted",_xlfn.XLOOKUP(L3,'mortgage-rates'!$A:$A,'mortgage-rates'!$E:$E)/100,_xlfn.XLOOKUP(L3,'mortgage-rates'!$A:$A,'mortgage-rates'!$D:$D)/100) -> 0.0664 | BC3: =(1-B20)*AR3 -> 264000 | BD3: =IF($B$16*12/3-Q3+1>0,-PMT($BB3/4,$B$16*12/3-Q3+1,BC3),0) -> 5428.7868 | BE3: =BC3*($BB3/4) -> 4382.4 | BF3: =BD3-BE3 -> 1046.3868 | BG3: =AT3+AY3+BD3 -> 92873.787 | BH3: =INDEX(cpi!B:B,MATCH($L3,cpi!A:A)) -> 84.6 | BI3: =100*BH3/BH$3 -> 100 | BJ3: =100*AC3/AC$3 -> 100 | BK3: =100*AD3/AD$3 -> 100 | BL3: =BJ3*GlobalPortfolio+BK3*AusPortfolio -> 100 | BM3: =100*AE3/$AE$3 -> 100 | BN3: =100*AR3/AR$3 -> 100 | BO3: =100*AX3/AX$3 -> 100
A4: Median home price growth p.a. | B4: =((_xlfn.XLOOKUP(Q_end,L:L,AR:AR)/_xlfn.XLOOKUP(Q_start,L:L,AR:AR))^(1/YEARFRAC(EOMONTH(Q_start,-3)+1,EOMONTH(Q_end,0))))-1 -> 0.049964718 | L4: =IF(DATE(YEAR(L3),MONTH(L3)+3,1)<=Q_end,DATE(YEAR(L3),MONTH(L3)+3,1),"") -> 38869 | M4: =AP4 -> 99680.292 | N4: =AX4-BC4 -> 71555.762 | O4: =M4/N4 -> 1.3930435 | P4: =X4/BG4 -> 0.46960837 | Q4: 2 | R4: =EOMONTH(L4,0)-EOMONTH(L4,-3) -> 91 | T4: =IF($B$10="3BR_H", INDEX('3BR_H-processed'!$C:$D,MATCH($L4,'3BR_H-processed'!$B:$B,0),MATCH(Council_Area,'3BR_H-processed'!$C$1:$D$1,0)), INDEX('2BR_F-processed'!$C:$D,MATCH($L4,'2BR_F-processed'!$B:$B,0),MATCH(Council_Area,'2BR_F-processed'!$C$1:$D$1,0))) -> 230 | U4: =IF(MOD(Q4,4)=1,T4,U3) -> 230 | V4: =U4*(R4)/7 -> 2990 | W4: =$B$53/4*BH4/_xlfn.XLOOKUP(Q_end,cpi!A:A,cpi!B:B) -> 118.7284 | X4: =V4+W4 -> 3108.7284 | Y4: =BG4-X4 -> 3511.1034 | Z4: =Y4*$B$47 -> 0 | AA4: {=(Y4+Z4)*eff_invest} -> 3511.1034 | AB4: =AA4*(_xlfn.XLOOKUP(Q_end,cpi!A:A,cpi!B:B)/BH4) -> 5914.513 | AC4: {=INDEX('msci-indices'!C:C,MATCH($L4,'msci-indices'!$B:$B)-2)} -> 809.32012 | AD4: {=INDEX('msci-indices'!D:D,MATCH($L4,'msci-indices'!$B:$B)-2)} -> 780.24347 | AE4: =AI3+AA4 -> 100330.55 | AF4: {=INDEX('msci-indices'!C:C,MATCH($L4,'msci-indices'!$B:$B)+1)} -> 802.64573 | AG4: {=INDEX('msci-indices'!D:D,MATCH($L4,'msci-indices'!$B:$B)+1)} -> 780.02674 | AH4: =(InvestFees/4)*AE4 -> 62.706595 | AI4: =((AF4/AC4)*GlobalPortfolio+(AG4/AD4)*AusPortfolio)*AE4-AH4 -> 99680.292 | AJ4: =AJ3+AA4 -> 93310.816 | AK4: =AI4-AJ4 -> 6369.4766 | AL4: =AJ4*(_xlfn.XLOOKUP(Q_end,cpi!A:A,cpi!B:B)/BH4) -> 157183.64 | AM4: {=SUMPRODUCT($AA$3:AA4,_xlfn.SORTBY($BH$3:BH4,_xlfn.SEQUENCE(ROWS($BH$3:BH4)),-1)/$BH$3)} -> 94690.717 | AN4: =AI4-AM4 -> 4989.5756 | AO4: =IF($B$49="Real gains",MAX($B$50*AN4,0),IF($B$49="Discounted nominal gains",MAX($B$50*AK4/2,0),0)) -> 0 | AP4: =AI4-AO4 -> 99680.292 | AR4: =IF($B$10="3BR_H", INDEX('ns-combined'!$C:$D,MATCH($L4,'ns-combined'!$B:$B,0),MATCH(Council_Area,'ns-combined'!$C$1:$D$1,0))*1000, INDEX('s-combined'!$C:$D,MATCH($L4,'s-combined'!$B:$B,0),MATCH(Council_Area,'s-combined'!$C$1:$D$1,0))*1000) -> 345000 | AS4: =AS3+$AS$3 -> 1650 | AT4: 0 | AU4: =SUM($B$28:$B$29)*AR4 -> 6900 | AV4: =AR4*$B$15/4 -> 991.875 | AW4: =SUM($AV$3:AV4) -> 1940.625 | AX4: =AR4-AS4-AU4-AW4 -> 334509.38 | AY4: =$B$36*V4 -> 1046.5 | AZ4: =SUM(AY4:AY4)*4/AR4 -> 0.012133333 | BA4: =SUM(AY4:AY4)/V4 -> 0.35 | BB4: =IF(MortgageRate="Discounted",_xlfn.XLOOKUP(L4,'mortgage-rates'!$A:$A,'mortgage-rates'!$E:$E)/100,_xlfn.XLOOKUP(L4,'mortgage-rates'!$A:$A,'mortgage-rates'!$D:$D)/100) -> 0.0693 | BC4: =BC3-BF3 -> 262953.61 | BD4: =IF($B$16*12/3-Q4+1>0,-PMT($BB4/4,$B$16*12/3-Q4+1,BC4),0) -> 5573.3318 | BE4: =BC4*($BB4/4) -> 4555.6713 | BF4: =BD4-BE4 -> 1017.6605 | BG4: =AT4+AY4+BD4 -> 6619.8318 | BH4: =INDEX(cpi!B:B,MATCH($L4,cpi!A:A)) -> 85.9 | BI4: =100*BH4/BH$3 -> 101.53664 | BJ4: =100*AC4/AC$3 -> 107.21181 | BK4: =100*AD4/AD$3 -> 109.43778 | BL4: =BJ4*GlobalPortfolio+BK4*AusPortfolio -> 107.8796 | BM4: =100*AE4/$AE$3 -> 111.72703 | BN4: =100*AR4/AR$3 -> 104.54545 | BO4: =100*AX4/AX$3 -> 104.00562
A5: Adjusted home price growth p.a. | B5: =((_xlfn.XLOOKUP(Q_end,L:L,AX:AX)/_xlfn.XLOOKUP(Q_start,L:L,AX:AX))^(1/YEARFRAC(EOMONTH(Q_start,-3)+1,EOMONTH(Q_end,0))))-1 -> 0.035744888 | L5: =DATE(YEAR(L4),MONTH(L4)+3,1) -> 38961 | M5: =AP5 -> 107019.95 | N5: =AX5-BC5 -> 71733.672 | O5: =M5/N5 -> 1.4919067 | P5: =X5/BG5 -> 0.46373705 | Q5: 3 | R5: =EOMONTH(L5,0)-EOMONTH(L5,-3) -> 92 | T5: =IF($B$10="3BR_H", INDEX('3BR_H-processed'!$C:$D,MATCH($L5,'3BR_H-processed'!$B:$B,0),MATCH(Council_Area,'3BR_H-processed'!$C$1:$D$1,0)), INDEX('2BR_F-processed'!$C:$D,MATCH($L5,'2BR_F-processed'!$B:$B,0),MATCH(Council_Area,'2BR_F-processed'!$C$1:$D$1,0))) -> 240 | U5: =IF(MOD(Q5,4)=1,T5,U4) -> 230 | V5: =U5*(R5)/7 -> 3022.8571 | W5: =$B$53/4*BH5/_xlfn.XLOOKUP(Q_end,cpi!A:A,cpi!B:B) -> 119.69592 | X5: =V5+W5 -> 3142.5531 | Y5: =BG5-X5 -> 3634.031 | Z5: =Y5*$B$47 -> 0 | AA5: {=(Y5+Z5)*eff_invest} -> 3634.031 | AB5: =AA5*(_xlfn.XLOOKUP(Q_end,cpi!A:A,cpi!B:B)/BH5) -> 6072.1049 | AC5: {=INDEX('msci-indices'!C:C,MATCH($L5,'msci-indices'!$B:$B)-2)} -> 802.64573 | AD5: {=INDEX('msci-indices'!D:D,MATCH($L5,'msci-indices'!$B:$B)-2)} -> 780.02674 | AE5: =AI4+AA5 -> 103314.32 | AF5: {=INDEX('msci-indices'!C:C,MATCH($L5,'msci-indices'!$B:$B)+1)} -> 835.13401 | AG5: {=INDEX('msci-indices'!D:D,MATCH($L5,'msci-indices'!$B:$B)+1)} -> 801.24067 | AH5: =(InvestFees/4)*AE5 -> 64.571452 | AI5: =((AF5/AC5)*GlobalPortfolio+(AG5/AD5)*AusPortfolio)*AE5-AH5 -> 107019.95 | AJ5: =AJ4+AA5 -> 96944.847 | AK5: =AI5-AJ5 -> 10075.1 | AL5: =AJ5*(_xlfn.XLOOKUP(Q_end,cpi!A:A,cpi!B:B)/BH5) -> 161985.21 | AM5: {=SUMPRODUCT($AA$3:AA5,_xlfn.SORTBY($BH$3:BH5,_xlfn.SEQUENCE(ROWS($BH$3:BH5)),-1)/$BH$3)} -> 99121.725 | AN5: =AI5-AM5 -> 7898.2219 | AO5: =IF($B$49="Real gains",MAX($B$50*AN5,0),IF($B$49="Discounted nominal gains",MAX($B$50*AK5/2,0),0)) -> 0 | AP5: =AI5-AO5 -> 107019.95 | AR5: =IF($B$10="3BR_H", INDEX('ns-combined'!$C:$D,MATCH($L5,'ns-combined'!$B:$B,0),MATCH(Council_Area,'ns-combined'!$C$1:$D$1,0))*1000, INDEX('s-combined'!$C:$D,MATCH($L5,'s-combined'!$B:$B,0),MATCH(Council_Area,'s-combined'!$C$1:$D$1,0))*1000) -> 346000 | AS5: =AS4+$AS$3 -> 2475 | AT5: 0 | AU5: =SUM($B$28:$B$29)*AR5 -> 6920 | AV5: =AR5*$B$15/4 -> 994.75 | AW5: =SUM($AV$3:AV5) -> 2935.375 | AX5: =AR5-AS5-AU5-AW5 -> 333669.62 | AY5: =$B$36*V5 -> 1058 | AZ5: =SUM(AY5:AY5)*4/AR5 -> 0.012231214 | BA5: =SUM(AY5:AY5)/V5 -> 0.35 | BB5: =IF(MortgageRate="Discounted",_xlfn.XLOOKUP(L5,'mortgage-rates'!$A:$A,'mortgage-rates'!$E:$E)/100,_xlfn.XLOOKUP(L5,'mortgage-rates'!$A:$A,'mortgage-rates'!$D:$D)/100) -> 0.0722 | BC5: =BC4-BF4 -> 261935.95 | BD5: =IF($B$16*12/3-Q5+1>0,-PMT($BB5/4,$B$16*12/3-Q5+1,BC5),0) -> 5718.584 | BE5: =BC5*($BB5/4) -> 4727.9439 | BF5: =BD5-BE5 -> 990.64009 | BG5: =AT5+AY5+BD5 -> 6776.584 | BH5: =INDEX(cpi!B:B,MATCH($L5,cpi!A:A)) -> 86.6 | BI5: =100*BH5/BH$3 -> 102.36407 | BJ5: =100*AC5/AC$3 -> 106.32765 | BK5: =100*AD5/AD$3 -> 109.40738 | BL5: =BJ5*GlobalPortfolio+BK5*AusPortfolio -> 107.25157 | BM5: =100*AE5/$AE$3 -> 115.04973 | BN5: =100*AR5/AR$3 -> 104.84848 | BO5: =100*AX5/AX$3 -> 103.74452
A6: Rent growth p.a. | B6: =((_xlfn.XLOOKUP(Q_end,L:L,U:U)/_xlfn.XLOOKUP(Q_start,L:L,U:U))^(1/YEARFRAC(EOMONTH(Q_start,-3)+1,EOMONTH(Q_end,0))))-1 -> 0.044556035 | L6: =DATE(YEAR(L5),MONTH(L5)+3,1) -> 39052 | M6: =AP6 -> 120831.87 | N6: =AX6-BC6 -> 84584.312 | O6: =M6/N6 -> 1.4285376 | P6: =X6/BG6 -> 0.4553125 | Q6: 4 | R6: =EOMONTH(L6,0)-EOMONTH(L6,-3) -> 92 | T6: =IF($B$10="3BR_H", INDEX('3BR_H-processed'!$C:$D,MATCH($L6,'3BR_H-processed'!$B:$B,0),MATCH(Council_Area,'3BR_H-processed'!$C$1:$D$1,0)), INDEX('2BR_F-processed'!$C:$D,MATCH($L6,'2BR_F-processed'!$B:$B,0),MATCH(Council_Area,'2BR_F-processed'!$C$1:$D$1,0))) -> 240 | U6: =IF(MOD(Q6,4)=1,T6,U5) -> 230 | V6: =U6*(R6)/7 -> 3022.8571 | W6: =$B$53/4*BH6/_xlfn.XLOOKUP(Q_end,cpi!A:A,cpi!B:B) -> 119.83414 | X6: =V6+W6 -> 3142.6913 | Y6: =BG6-X6 -> 3759.5819 | Z6: =Y6*$B$47 -> 0 | AA6: {=(Y6+Z6)*eff_invest} -> 3759.5819 | AB6: =AA6*(_xlfn.XLOOKUP(Q_end,cpi!A:A,cpi!B:B)/BH6) -> 6274.6424 | AC6: {=INDEX('msci-indices'!C:C,MATCH($L6,'msci-indices'!$B:$B)-2)} -> 835.13401 | AD6: {=INDEX('msci-indices'!D:D,MATCH($L6,'msci-indices'!$B:$B)-2)} -> 801.24067 | AE6: =AI5+AA6 -> 110779.53 | AF6: {=INDEX('msci-indices'!C:C,MATCH($L6,'msci-indices'!$B:$B)+1)} -> 906.58022 | AG6: {=INDEX('msci-indices'!D:D,MATCH($L6,'msci-indices'!$B:$B)+1)} -> 885.32149 | AH6: =(InvestFees/4)*AE6 -> 69.237205 | AI6: =((AF6/AC6)*GlobalPortfolio+(AG6/AD6)*AusPortfolio)*AE6-AH6 -> 120831.87 | AJ6: =AJ5+AA6 -> 100704.43 | AK6: =AI6-AJ6 -> 20127.444 | AL6: =AJ6*(_xlfn.XLOOKUP(Q_end,cpi!A:A,cpi!B:B)/BH6) -> 168073.02 | AM6: {=SUMPRODUCT($AA$3:AA6,_xlfn.SORTBY($BH$3:BH6,_xlfn.SEQUENCE(ROWS($BH$3:BH6)),-1)/$BH$3)} -> 103072.35 | AN6: =AI6-AM6 -> 17759.527 | AO6: =IF($B$49="Real gains",MAX($B$50*AN6,0),IF($B$49="Discounted nominal gains",MAX($B$50*AK6/2,0),0)) -> 0 | AP6: =AI6-AO6 -> 120831.87 | AR6: =IF($B$10="3BR_H", INDEX('ns-combined'!$C:$D,MATCH($L6,'ns-combined'!$B:$B,0),MATCH(Council_Area,'ns-combined'!$C$1:$D$1,0))*1000, INDEX('s-combined'!$C:$D,MATCH($L6,'s-combined'!$B:$B,0),MATCH(Council_Area,'s-combined'!$C$1:$D$1,0))*1000) -> 360000 | AS6: =AS5+$AS$3 -> 3300 | AT6: 0 | AU6: =SUM($B$28:$B$29)*AR6 -> 7200 | AV6: =AR6*$B$15/4 -> 1035 | AW6: =SUM($AV$3:AV6) -> 3970.375 | AX6: =AR6-AS6-AU6-AW6 -> 345529.62 | AY6: =$B$36*V6 -> 1058 | AZ6: =SUM(AY6:AY6)*4/AR6 -> 0.011755556 | BA6: =SUM(AY6:AY6)/V6 -> 0.35 | BB6: =IF(MortgageRate="Discounted",_xlfn.XLOOKUP(L6,'mortgage-rates'!$A:$A,'mortgage-rates'!$E:$E)/100,_xlfn.XLOOKUP(L6,'mortgage-rates'!$A:$A,'mortgage-rates'!$D:$D)/100) -> 0.0747 | BC6: =BC5-BF5 -> 260945.31 | BD6: =IF($B$16*12/3-Q6+1>0,-PMT($BB6/4,$B$16*12/3-Q6+1,BC6),0) -> 5844.2732 | BE6: =BC6*($BB6/4) -> 4873.1537 | BF6: =BD6-BE6 -> 971.11945 | BG6: =AT6+AY6+BD6 -> 6902.2732 | BH6: =INDEX(cpi!B:B,MATCH($L6,cpi!A:A)) -> 86.7 | BI6: =100*BH6/BH$3 -> 102.48227 | BJ6: =100*AC6/AC$3 -> 110.63142 | BK6: =100*AD6/AD$3 -> 112.38287 | BL6: =BJ6*GlobalPortfolio+BK6*AusPortfolio -> 111.15685 | BM6: =100*AE6/$AE$3 -> 123.3629 | BN6: =100*AR6/AR$3 -> 109.09091 | BO6: =100*AX6/AX$3 -> 107.43203
A7: Investment index (country-weighted) growth p.a. | B7: =((_xlfn.XLOOKUP(Q_end,L:L,BL:BL)/_xlfn.XLOOKUP(Q_start,L:L,BL:BL))^(1/YEARFRAC(EOMONTH(Q_start,-3)+1,EOMONTH(Q_end,0))))-1 -> 0.080631422 | L7: =DATE(YEAR(L6),MONTH(L6)+3,1) -> 39142 | M7: =AP7 -> 129404.5 | N7: =AX7-BC7 -> 69038.557 | O7: =M7/N7 -> 1.8743801 | P7: =X7/BG7 -> 0.47840281 | Q7: 5 | R7: =EOMONTH(L7,0)-EOMONTH(L7,-3) -> 90 | T7: =IF($B$10="3BR_H", INDEX('3BR_H-processed'!$C:$D,MATCH($L7,'3BR_H-processed'!$B:$B,0),MATCH(Council_Area,'3BR_H-processed'!$C$1:$D$1,0)), INDEX('2BR_F-processed'!$C:$D,MATCH($L7,'2BR_F-processed'!$B:$B,0),MATCH(Council_Area,'2BR_F-processed'!$C$1:$D$1,0))) -> 250 | U7: =IF(MOD(Q7,4)=1,T7,U6) -> 250 | V7: =U7*(R7)/7 -> 3214.2857 | W7: =$B$53/4*BH7/_xlfn.XLOOKUP(Q_end,cpi!A:A,cpi!B:B) -> 119.83414 | X7: =V7+W7 -> 3334.1199 | Y7: =BG7-X7 -> 3635.1533 | Z7: =Y7*$B$47 -> 0 | AA7: {=(Y7+Z7)*eff_invest} -> 3635.1533 | AB7: =AA7*(_xlfn.XLOOKUP(Q_end,cpi!A:A,cpi!B:B)/BH7) -> 6066.9744 | AC7: {=INDEX('msci-indices'!C:C,MATCH($L7,'msci-indices'!$B:$B)-2)} -> 906.58022 | AD7: {=INDEX('msci-indices'!D:D,MATCH($L7,'msci-indices'!$B:$B)-2)} -> 885.32149 | AE7: =AI6+AA7 -> 124467.03 | AF7: {=INDEX('msci-indices'!C:C,MATCH($L7,'msci-indices'!$B:$B)+1)} -> 932.09759 | AG7: {=INDEX('msci-indices'!D:D,MATCH($L7,'msci-indices'!$B:$B)+1)} -> 946.08734 | AH7: =(InvestFees/4)*AE7 -> 77.791891 | AI7: =((AF7/AC7)*GlobalPortfolio+(AG7/AD7)*AusPortfolio)*AE7-AH7 -> 129404.5 | AJ7: =AJ6+AA7 -> 104339.58 | AK7: =AI7-AJ7 -> 25064.915 | AL7: =AJ7*(_xlfn.XLOOKUP(Q_end,cpi!A:A,cpi!B:B)/BH7) -> 174139.99 | AM7: {=SUMPRODUCT($AA$3:AA7,_xlfn.SORTBY($BH$3:BH7,_xlfn.SEQUENCE(ROWS($BH$3:BH7)),-1)/$BH$3)} -> 106799.49 | AN7: =AI7-AM7 -> 22605.007 | AO7: =IF($B$49="Real gains",MAX($B$50*AN7,0),IF($B$49="Discounted nominal gains",MAX($B$50*AK7/2,0),0)) -> 0 | AP7: =AI7-AO7 -> 129404.5 | AR7: =IF($B$10="3BR_H", INDEX('ns-combined'!$C:$D,MATCH($L7,'ns-combined'!$B:$B,0),MATCH(Council_Area,'ns-combined'!$C$1:$D$1,0))*1000, INDEX('s-combined'!$C:$D,MATCH($L7,'s-combined'!$B:$B,0),MATCH(Council_Area,'s-combined'!$C$1:$D$1,0))*1000) -> 345000 | AS7: =AS6+$AS$3 -> 4125 | AT7: 0 | AU7: =SUM($B$28:$B$29)*AR7 -> 6900 | AV7: =AR7*$B$15/4 -> 991.875 | AW7: =SUM($AV$3:AV7) -> 4962.25 | AX7: =AR7-AS7-AU7-AW7 -> 329012.75 | AY7: =$B$36*V7 -> 1125 | AZ7: =SUM(AY7:AY7)*4/AR7 -> 0.013043478 | BA7: =SUM(AY7:AY7)/V7 -> 0.35 | BB7: =IF(MortgageRate="Discounted",_xlfn.XLOOKUP(L7,'mortgage-rates'!$A:$A,'mortgage-rates'!$E:$E)/100,_xlfn.XLOOKUP(L7,'mortgage-rates'!$A:$A,'mortgage-rates'!$D:$D)/100) -> 0.0747 | BC7: =BC6-BF6 -> 259974.19 | BD7: =IF($B$16*12/3-Q7+1>0,-PMT($BB7/4,$B$16*12/3-Q7+1,BC7),0) -> 5844.2732 | BE7: =BC7*($BB7/4) -> 4855.0181 | BF7: =BD7-BE7 -> 989.25511 | BG7: =AT7+AY7+BD7 -> 6969.2732 | BH7: =INDEX(cpi!B:B,MATCH($L7,cpi!A:A)) -> 86.7 | BI7: =100*BH7/BH$3 -> 102.48227 | BJ7: =100*AC7/AC$3 -> 120.096 | BK7: =100*AD7/AD$3 -> 124.17613 | BL7: =BJ7*GlobalPortfolio+BK7*AusPortfolio -> 121.32004 | BM7: =100*AE7/$AE$3 -> 138.60515 | BN7: =100*AR7/AR$3 -> 104.54545 | BO7: =100*AX7/AX$3 -> 102.29661
A8: CPI growth p.a. | B8: =((_xlfn.XLOOKUP(Q_end,L:L,BI:BI)/_xlfn.XLOOKUP(Q_start,L:L,BI:BI))^(1/YEARFRAC(EOMONTH(Q_start,-3)+1,EOMONTH(Q_end,0))))-1 -> 0.027199758 | L8: =DATE(YEAR(L7),MONTH(L7)+3,1) -> 39234 | M8: =AP8 -> 141201.82 | N8: =AX8-BC8 -> 84822.062 | O8: =M8/N8 -> 1.6646827 | P8: =X8/BG8 -> 0.48285962 | Q8: 6 | R8: =EOMONTH(L8,0)-EOMONTH(L8,-3) -> 91 | T8: =IF($B$10="3BR_H", INDEX('3BR_H-processed'!$C:$D,MATCH($L8,'3BR_H-processed'!$B:$B,0),MATCH(Council_Area,'3BR_H-processed'!$C$1:$D$1,0)), INDEX('2BR_F-processed'!$C:$D,MATCH($L8,'2BR_F-processed'!$B:$B,0),MATCH(Council_Area,'2BR_F-processed'!$C$1:$D$1,0))) -> 250 | U8: =IF(MOD(Q8,4)=1,T8,U7) -> 250 | V8: =U8*(R8)/7 -> 3250 | W8: =$B$53/4*BH8/_xlfn.XLOOKUP(Q_end,cpi!A:A,cpi!B:B) -> 121.21631 | X8: =V8+W8 -> 3371.2163 | Y8: =BG8-X8 -> 3610.5569 | Z8: =Y8*$B$47 -> 0 | AA8: {=(Y8+Z8)*eff_invest} -> 3610.5569 | AB8: =AA8*(_xlfn.XLOOKUP(Q_end,cpi!A:A,cpi!B:B)/BH8) -> 5957.213 | AC8: {=INDEX('msci-indices'!C:C,MATCH($L8,'msci-indices'!$B:$B)-2)} -> 932.09759 | AD8: {=INDEX('msci-indices'!D:D,MATCH($L8,'msci-indices'!$B:$B)-2)} -> 946.08734 | AE8: =AI7+AA8 -> 133015.05 | AF8: {=INDEX('msci-indices'!C:C,MATCH($L8,'msci-indices'!$B:$B)+1)} -> 991.70582 | AG8: {=INDEX('msci-indices'!D:D,MATCH($L8,'msci-indices'!$B:$B)+1)} -> 1000.9831 | AH8: =(InvestFees/4)*AE8 -> 83.134409 | AI8: =((AF8/AC8)*GlobalPortfolio+(AG8/AD8)*AusPortfolio)*AE8-AH8 -> 141201.82 | AJ8: =AJ7+AA8 -> 107950.14 | AK8: =AI8-AJ8 -> 33251.678 | AL8: =AJ8*(_xlfn.XLOOKUP(Q_end,cpi!A:A,cpi!B:B)/BH8) -> 178111.57 | AM8: {=SUMPRODUCT($AA$3:AA8,_xlfn.SORTBY($BH$3:BH8,_xlfn.SEQUENCE(ROWS($BH$3:BH8)),-1)/$BH$3)} -> 111562.77 | AN8: =AI8-AM8 -> 29639.045 | AO8: =IF($B$49="Real gains",MAX($B$50*AN8,0),IF($B$49="Discounted nominal gains",MAX($B$50*AK8/2,0),0)) -> 0 | AP8: =AI8-AO8 -> 141201.82 | AR8: =IF($B$10="3BR_H", INDEX('ns-combined'!$C:$D,MATCH($L8,'ns-combined'!$B:$B,0),MATCH(Council_Area,'ns-combined'!$C$1:$D$1,0))*1000, INDEX('s-combined'!$C:$D,MATCH($L8,'s-combined'!$B:$B,0),MATCH(Council_Area,'s-combined'!$C$1:$D$1,0))*1000) -> 362000 | AS8: =AS7+$AS$3 -> 4950 | AT8: 0 | AU8: =SUM($B$28:$B$29)*AR8 -> 7240 | AV8: =AR8*$B$15/4 -> 1040.75 | AW8: =SUM($AV$3:AV8) -> 6003 | AX8: =AR8-AS8-AU8-AW8 -> 343807 | AY8: =$B$36*V8 -> 1137.5 | AZ8: =SUM(AY8:AY8)*4/AR8 -> 0.012569061 | BA8: =SUM(AY8:AY8)/V8 -> 0.35 | BB8: =IF(MortgageRate="Discounted",_xlfn.XLOOKUP(L8,'mortgage-rates'!$A:$A,'mortgage-rates'!$E:$E)/100,_xlfn.XLOOKUP(L8,'mortgage-rates'!$A:$A,'mortgage-rates'!$D:$D)/100) -> 0.0747 | BC8: =BC7-BF7 -> 258984.94 | BD8: =IF($B$16*12/3-Q8+1>0,-PMT($BB8/4,$B$16*12/3-Q8+1,BC8),0) -> 5844.2732 | BE8: =BC8*($BB8/4) -> 4836.5437 | BF8: =BD8-BE8 -> 1007.7294 | BG8: =AT8+AY8+BD8 -> 6981.7732 | BH8: =INDEX(cpi!B:B,MATCH($L8,cpi!A:A)) -> 87.7 | BI8: =100*BH8/BH$3 -> 103.6643 | BJ8: =100*AC8/AC$3 -> 123.47632 | BK8: =100*AD8/AD$3 -> 132.69921 | BL8: =BJ8*GlobalPortfolio+BK8*AusPortfolio -> 126.24319 | BM8: =100*AE8/$AE$3 -> 148.12414 | BN8: =100*AR8/AR$3 -> 109.69697 | BO8: =100*AX8/AX$3 -> 106.89644
L9: =DATE(YEAR(L8),MONTH(L8)+3,1) -> 39326 | M9: =AP9 -> 149289.73 | N9: =AX9-BC9 -> 91781.041 | O9: =M9/N9 -> 1.6265857 | P9: =X9/BG9 -> 0.47869175 | Q9: 7 | R9: =EOMONTH(L9,0)-EOMONTH(L9,-3) -> 92 | T9: =IF($B$10="3BR_H", INDEX('3BR_H-processed'!$C:$D,MATCH($L9,'3BR_H-processed'!$B:$B,0),MATCH(Council_Area,'3BR_H-processed'!$C$1:$D$1,0)), INDEX('2BR_F-processed'!$C:$D,MATCH($L9,'2BR_F-processed'!$B:$B,0),MATCH(Council_Area,'2BR_F-processed'!$C$1:$D$1,0))) -> 260 | U9: =IF(MOD(Q9,4)=1,T9,U8) -> 250 | V9: =U9*(R9)/7 -> 3285.7143 | W9: =$B$53/4*BH9/_xlfn.XLOOKUP(Q_end,cpi!A:A,cpi!B:B) -> 121.90739 | X9: =V9+W9 -> 3407.6217 | Y9: =BG9-X9 -> 3710.992 | Z9: =Y9*$B$47 -> 0 | AA9: {=(Y9+Z9)*eff_invest} -> 3710.992 | AB9: =AA9*(_xlfn.XLOOKUP(Q_end,cpi!A:A,cpi!B:B)/BH9) -> 6088.2148 | AC9: {=INDEX('msci-indices'!C:C,MATCH($L9,'msci-indices'!$B:$B)-2)} -> 991.70582 | AD9: {=INDEX('msci-indices'!D:D,MATCH($L9,'msci-indices'!$B:$B)-2)} -> 1000.9831 | AE9: =AI8+AA9 -> 144912.81 | AF9: {=INDEX('msci-indices'!C:C,MATCH($L9,'msci-indices'!$B:$B)+1)} -> 1009.8701 | AG9: {=INDEX('msci-indices'!D:D,MATCH($L9,'msci-indices'!$B:$B)+1)} -> 1061.067 | AH9: =(InvestFees/4)*AE9 -> 90.570505 | AI9: =((AF9/AC9)*GlobalPortfolio+(AG9/AD9)*AusPortfolio)*AE9-AH9 -> 149289.73 | AJ9: =AJ8+AA9 -> 111661.13 | AK9: =AI9-AJ9 -> 37628.599 | AL9: =AJ9*(_xlfn.XLOOKUP(Q_end,cpi!A:A,cpi!B:B)/BH9) -> 183190.09 | AM9: {=SUMPRODUCT($AA$3:AA9,_xlfn.SORTBY($BH$3:BH9,_xlfn.SEQUENCE(ROWS($BH$3:BH9)),-1)/$BH$3)} -> 115936 | AN9: =AI9-AM9 -> 33353.729 | AO9: =IF($B$49="Real gains",MAX($B$50*AN9,0),IF($B$49="Discounted nominal gains",MAX($B$50*AK9/2,0),0)) -> 0 | AP9: =AI9-AO9 -> 149289.73 | AR9: =IF($B$10="3BR_H", INDEX('ns-combined'!$C:$D,MATCH($L9,'ns-combined'!$B:$B,0),MATCH(Council_Area,'ns-combined'!$C$1:$D$1,0))*1000, INDEX('s-combined'!$C:$D,MATCH($L9,'s-combined'!$B:$B,0),MATCH(Council_Area,'s-combined'!$C$1:$D$1,0))*1000) -> 370000 | AS9: =AS8+$AS$3 -> 5775 | AT9: 0 | AU9: =SUM($B$28:$B$29)*AR9 -> 7400 | AV9: =AR9*$B$15/4 -> 1063.75 | AW9: =SUM($AV$3:AV9) -> 7066.75 | AX9: =AR9-AS9-AU9-AW9 -> 349758.25 | AY9: =$B$36*V9 -> 1150 | AZ9: =SUM(AY9:AY9)*4/AR9 -> 0.012432432 | BA9: =SUM(AY9:AY9)/V9 -> 0.35 | BB9: =IF(MortgageRate="Discounted",_xlfn.XLOOKUP(L9,'mortgage-rates'!$A:$A,'mortgage-rates'!$E:$E)/100,_xlfn.XLOOKUP(L9,'mortgage-rates'!$A:$A,'mortgage-rates'!$D:$D)/100) -> 0.0772 | BC9: =BC8-BF8 -> 257977.21 | BD9: =IF($B$16*12/3-Q9+1>0,-PMT($BB9/4,$B$16*12/3-Q9+1,BC9),0) -> 5968.6137 | BE9: =BC9*($BB9/4) -> 4978.9601 | BF9: =BD9-BE9 -> 989.65357 | BG9: =AT9+AY9+BD9 -> 7118.6137 | BH9: =INDEX(cpi!B:B,MATCH($L9,cpi!A:A)) -> 88.2 | BI9: =100*BH9/BH$3 -> 104.25532 | BJ9: =100*AC9/AC$3 -> 131.37271 | BK9: =100*AD9/AD$3 -> 140.39895 | BL9: =BJ9*GlobalPortfolio+BK9*AusPortfolio -> 134.08059 | BM9: =100*AE9/$AE$3 -> 161.37335 | BN9: =100*AR9/AR$3 -> 112.12121 | BO9: =100*AX9/AX$3 -> 108.7468
A10: Dwelling type (3br house, 3BR_H; or 2br flat, 2BR_F) | B10: 3BR_H | C10: 3BR_H | L10: =DATE(YEAR(L9),MONTH(L9)+3,1) -> 39417 | M10: =AP10 -> 148889.8 | N10: =AX10-BC10 -> 129966.94 | O10: =M10/N10 -> 1.1455975 | P10: =X10/BG10 -> 0.47066618 | Q10: 8 | R10: =EOMONTH(L10,0)-EOMONTH(L10,-3) -> 92 | T10: =IF($B$10="3BR_H", INDEX('3BR_H-processed'!$C:$D,MATCH($L10,'3BR_H-processed'!$B:$B,0),MATCH(Council_Area,'3BR_H-processed'!$C$1:$D$1,0)), INDEX('2BR_F-processed'!$C:$D,MATCH($L10,'2BR_F-processed'!$B:$B,0),MATCH(Council_Area,'2BR_F-processed'!$C$1:$D$1,0))) -> 270 | U10: =IF(MOD(Q10,4)=1,T10,U9) -> 250 | V10: =U10*(R10)/7 -> 3285.7143 | W10: =$B$53/4*BH10/_xlfn.XLOOKUP(Q_end,cpi!A:A,cpi!B:B) -> 123.42778 | X10: =V10+W10 -> 3409.1421 | Y10: =BG10-X10 -> 3834.0851 | Z10: =Y10*$B$47 -> 0 | AA10: {=(Y10+Z10)*eff_invest} -> 3834.0851 | AB10: =AA10*(_xlfn.XLOOKUP(Q_end,cpi!A:A,cpi!B:B)/BH10) -> 6212.6777 | AC10: {=INDEX('msci-indices'!C:C,MATCH($L10,'msci-indices'!$B:$B)-2)} -> 1009.8701 | AD10: {=INDEX('msci-indices'!D:D,MATCH($L10,'msci-indices'!$B:$B)-2)} -> 1061.067 | AE10: =AI9+AA10 -> 153123.82 | AF10: {=INDEX('msci-indices'!C:C,MATCH($L10,'msci-indices'!$B:$B)+1)} -> 983.50383 | AG10: {=INDEX('msci-indices'!D:D,MATCH($L10,'msci-indices'!$B:$B)+1)} -> 1030.1196 | AH10: =(InvestFees/4)*AE10 -> 95.702384 | AI10: =((AF10/AC10)*GlobalPortfolio+(AG10/AD10)*AusPortfolio)*AE10-AH10 -> 148889.8 | AJ10: =AJ9+AA10 -> 115495.22 | AK10: =AI10-AJ10 -> 33394.587 | AL10: =AJ10*(_xlfn.XLOOKUP(Q_end,cpi!A:A,cpi!B:B)/BH10) -> 187146.22 | AM10: {=SUMPRODUCT($AA$3:AA10,_xlfn.SORTBY($BH$3:BH10,_xlfn.SEQUENCE(ROWS($BH$3:BH10)),-1)/$BH$3)} -> 121092.6 | AN10: =AI10-AM10 -> 27797.206 | AO10: =IF($B$49="Real gains",MAX($B$50*AN10,0),IF($B$49="Discounted nominal gains",MAX($B$50*AK10/2,0),0)) -> 0 | AP10: =AI10-AO10 -> 148889.8 | AR10: =IF($B$10="3BR_H", INDEX('ns-combined'!$C:$D,MATCH($L10,'ns-combined'!$B:$B,0),MATCH(Council_Area,'ns-combined'!$C$1:$D$1,0))*1000, INDEX('s-combined'!$C:$D,MATCH($L10,'s-combined'!$B:$B,0),MATCH(Council_Area,'s-combined'!$C$1:$D$1,0))*1000) -> 410000 | AS10: =AS9+$AS$3 -> 6600 | AT10: 0 | AU10: =SUM($B$28:$B$29)*AR10 -> 8200 | AV10: =AR10*$B$15/4 -> 1178.75 | AW10: =SUM($AV$3:AV10) -> 8245.5 | AX10: =AR10-AS10-AU10-AW10 -> 386954.5 | AY10: =$B$36*V10 -> 1150 | AZ10: =SUM(AY10:AY10)*4/AR10 -> 0.011219512 | BA10: =SUM(AY10:AY10)/V10 -> 0.35 | BB10: =IF(MortgageRate="Discounted",_xlfn.XLOOKUP(L10,'mortgage-rates'!$A:$A,'mortgage-rates'!$E:$E)/100,_xlfn.XLOOKUP(L10,'mortgage-rates'!$A:$A,'mortgage-rates'!$D:$D)/100) -> 0.0797 | BC10: =BC9-BF9 -> 256987.56 | BD10: =IF($B$16*12/3-Q10+1>0,-PMT($BB10/4,$B$16*12/3-Q10+1,BC10),0) -> 6093.2272 | BE10: =BC10*($BB10/4) -> 5120.477 | BF10: =BD10-BE10 -> 972.75017 | BG10: =AT10+AY10+BD10 -> 7243.2272 | BH10: =INDEX(cpi!B:B,MATCH($L10,cpi!A:A)) -> 89.3 | BI10: =100*BH10/BH$3 -> 105.55556 | BJ10: =100*AC10/AC$3 -> 133.77897 | BK10: =100*AD10/AD$3 -> 148.82639 | BL10: =BJ10*GlobalPortfolio+BK10*AusPortfolio -> 138.29319 | BM10: =100*AE10/$AE$3 -> 170.51704 | BN10: =100*AR10/AR$3 -> 124.24242 | BO10: =100*AX10/AX$3 -> 120.31185
A11: Analysis start quarter | B11: 38777 | C11: 38777 | L11: =DATE(YEAR(L10),MONTH(L10)+3,1) -> 39508 | M11: =AP11 -> 136506.14 | N11: =AX11-BC11 -> 104507.82 | O11: =M11/N11 -> 1.3061811 | P11: =X11/BG11 -> 0.48675723 | Q11: 9 | R11: =EOMONTH(L11,0)-EOMONTH(L11,-3) -> 91 | T11: =IF($B$10="3BR_H", INDEX('3BR_H-processed'!$C:$D,MATCH($L11,'3BR_H-processed'!$B:$B,0),MATCH(Council_Area,'3BR_H-processed'!$C$1:$D$1,0)), INDEX('2BR_F-processed'!$C:$D,MATCH($L11,'2BR_F-processed'!$B:$B,0),MATCH(Council_Area,'2BR_F-processed'!$C$1:$D$1,0))) -> 280 | U11: =IF(MOD(Q11,4)=1,T11,U10) -> 280 | V11: =U11*(R11)/7 -> 3640 | W11: =$B$53/4*BH11/_xlfn.XLOOKUP(Q_end,cpi!A:A,cpi!B:B) -> 124.94817 | X11: =V11+W11 -> 3764.9482 | Y11: =BG11-X11 -> 3969.8073 | Z11: =Y11*$B$47 -> 0 | AA11: {=(Y11+Z11)*eff_invest} -> 3969.8073 | AB11: =AA11*(_xlfn.XLOOKUP(Q_end,cpi!A:A,cpi!B:B)/BH11) -> 6354.3265 | AC11: {=INDEX('msci-indices'!C:C,MATCH($L11,'msci-indices'!$B:$B)-2)} -> 983.50383 | AD11: {=INDEX('msci-indices'!D:D,MATCH($L11,'msci-indices'!$B:$B)-2)} -> 1030.1196 | AE11: =AI10+AA11 -> 152859.61 | AF11: {=INDEX('msci-indices'!C:C,MATCH($L11,'msci-indices'!$B:$B)+1)} -> 894.99836 | AG11: {=INDEX('msci-indices'!D:D,MATCH($L11,'msci-indices'!$B:$B)+1)} -> 881.21373 | AH11: =(InvestFees/4)*AE11 -> 95.537257 | AI11: =((AF11/AC11)*GlobalPortfolio+(AG11/AD11)*AusPortfolio)*AE11-AH11 -> 136506.14 | AJ11: =AJ10+AA11 -> 119465.02 | AK11: =AI11-AJ11 -> 17041.117 | AL11: =AJ11*(_xlfn.XLOOKUP(Q_end,cpi!A:A,cpi!B:B)/BH11) -> 191223.33 | AM11: {=SUMPRODUCT($AA$3:AA11,_xlfn.SORTBY($BH$3:BH11,_xlfn.SEQUENCE(ROWS($BH$3:BH11)),-1)/$BH$3)} -> 126435.47 | AN11: =AI11-AM11 -> 10070.668 | AO11: =IF($B$49="Real gains",MAX($B$50*AN11,0),IF($B$49="Discounted nominal gains",MAX($B$50*AK11/2,0),0)) -> 0 | AP11: =AI11-AO11 -> 136506.14 | AR11: =IF($B$10="3BR_H", INDEX('ns-combined'!$C:$D,MATCH($L11,'ns-combined'!$B:$B,0),MATCH(Council_Area,'ns-combined'!$C$1:$D$1,0))*1000, INDEX('s-combined'!$C:$D,MATCH($L11,'s-combined'!$B:$B,0),MATCH(Council_Area,'s-combined'!$C$1:$D$1,0))*1000) -> 385000 | AS11: =AS10+$AS$3 -> 7425 | AT11: 0 | AU11: =SUM($B$28:$B$29)*AR11 -> 7700 | AV11: =AR11*$B$15/4 -> 1106.875 | AW11: =SUM($AV$3:AV11) -> 9352.375 | AX11: =AR11-AS11-AU11-AW11 -> 360522.62 | AY11: =$B$36*V11 -> 1274 | AZ11: =SUM(AY11:AY11)*4/AR11 -> 0.013236364 | BA11: =SUM(AY11:AY11)/V11 -> 0.35 | BB11: =IF(MortgageRate="Discounted",_xlfn.XLOOKUP(L11,'mortgage-rates'!$A:$A,'mortgage-rates'!$E:$E)/100,_xlfn.XLOOKUP(L11,'mortgage-rates'!$A:$A,'mortgage-rates'!$D:$D)/100) -> 0.087 | BC11: =BC10-BF10 -> 256014.8 | BD11: =IF($B$16*12/3-Q11+1>0,-PMT($BB11/4,$B$16*12/3-Q11+1,BC11),0) -> 6460.7554 | BE11: =BC11*($BB11/4) -> 5568.322 | BF11: =BD11-BE11 -> 892.43344 | BG11: =AT11+AY11+BD11 -> 7734.7554 | BH11: =INDEX(cpi!B:B,MATCH($L11,cpi!A:A)) -> 90.4 | BI11: =100*BH11/BH$3 -> 106.85579 | BJ11: =100*AC11/AC$3 -> 130.28618 | BK11: =100*AD11/AD$3 -> 144.48568 | BL11: =BJ11*GlobalPortfolio+BK11*AusPortfolio -> 134.54603 | BM11: =100*AE11/$AE$3 -> 170.22283 | BN11: =100*AR11/AR$3 -> 116.66667 | BO11: =100*AX11/AX$3 -> 112.09366
A12: Analysis end quarter | B12: 45992 | C12: 45992 | L12: =DATE(YEAR(L11),MONTH(L11)+3,1) -> 39600 | M12: =AP12 -> 138345.35 | N12: =AX12-BC12 -> 118125.25 | O12: =M12/N12 -> 1.1711751 | P12: =X12/BG12 -> 0.48254045 | Q12: 10 | R12: =EOMONTH(L12,0)-EOMONTH(L12,-3) -> 91 | T12: =IF($B$10="3BR_H", INDEX('3BR_H-processed'!$C:$D,MATCH($L12,'3BR_H-processed'!$B:$B,0),MATCH(Council_Area,'3BR_H-processed'!$C$1:$D$1,0)), INDEX('2BR_F-processed'!$C:$D,MATCH($L12,'2BR_F-processed'!$B:$B,0),MATCH(Council_Area,'2BR_F-processed'!$C$1:$D$1,0))) -> 290 | U12: =IF(MOD(Q12,4)=1,T12,U11) -> 280 | V12: =U12*(R12)/7 -> 3640 | W12: =$B$53/4*BH12/_xlfn.XLOOKUP(Q_end,cpi!A:A,cpi!B:B) -> 126.60677 | X12: =V12+W12 -> 3766.6068 | Y12: =BG12-X12 -> 4039.1778 | Z12: =Y12*$B$47 -> 0 | AA12: {=(Y12+Z12)*eff_invest} -> 4039.1778 | AB12: =AA12*(_xlfn.XLOOKUP(Q_end,cpi!A:A,cpi!B:B)/BH12) -> 6380.6662 | AC12: {=INDEX('msci-indices'!C:C,MATCH($L12,'msci-indices'!$B:$B)-2)} -> 894.99836 | AD12: {=INDEX('msci-indices'!D:D,MATCH($L12,'msci-indices'!$B:$B)-2)} -> 881.21373 | AE12: =AI11+AA12 -> 140545.32 | AF12: {=INDEX('msci-indices'!C:C,MATCH($L12,'msci-indices'!$B:$B)+1)} -> 881.79174 | AG12: {=INDEX('msci-indices'!D:D,MATCH($L12,'msci-indices'!$B:$B)+1)} -> 867.41147 | AH12: =(InvestFees/4)*AE12 -> 87.840824 | AI12: =((AF12/AC12)*GlobalPortfolio+(AG12/AD12)*AusPortfolio)*AE12-AH12 -> 138345.35 | AJ12: =AJ11+AA12 -> 123504.2 | AK12: =AI12-AJ12 -> 14841.153 | AL12: =AJ12*(_xlfn.XLOOKUP(Q_end,cpi!A:A,cpi!B:B)/BH12) -> 195098.89 | AM12: {=SUMPRODUCT($AA$3:AA12,_xlfn.SORTBY($BH$3:BH12,_xlfn.SEQUENCE(ROWS($BH$3:BH12)),-1)/$BH$3)} -> 132003.61 | AN12: =AI12-AM12 -> 6341.7443 | AO12: =IF($B$49="Real gains",MAX($B$50*AN12,0),IF($B$49="Discounted nominal gains",MAX($B$50*AK12/2,0),0)) -> 0 | AP12: =AI12-AO12 -> 138345.35 | AR12: =IF($B$10="3BR_H", INDEX('ns-combined'!$C:$D,MATCH($L12,'ns-combined'!$B:$B,0),MATCH(Council_Area,'ns-combined'!$C$1:$D$1,0))*1000, INDEX('s-combined'!$C:$D,MATCH($L12,'s-combined'!$B:$B,0),MATCH(Council_Area,'s-combined'!$C$1:$D$1,0))*1000) -> 400000 | AS12: =AS11+$AS$3 -> 8250 | AT12: 0 | AU12: =SUM($B$28:$B$29)*AR12 -> 8000 | AV12: =AR12*$B$15/4 -> 1150 | AW12: =SUM($AV$3:AV12) -> 10502.375 | AX12: =AR12-AS12-AU12-AW12 -> 373247.62 | AY12: =$B$36*V12 -> 1274 | AZ12: =SUM(AY12:AY12)*4/AR12 -> 0.01274 | BA12: =SUM(AY12:AY12)/V12 -> 0.35 | BB12: =IF(MortgageRate="Discounted",_xlfn.XLOOKUP(L12,'mortgage-rates'!$A:$A,'mortgage-rates'!$E:$E)/100,_xlfn.XLOOKUP(L12,'mortgage-rates'!$A:$A,'mortgage-rates'!$D:$D)/100) -> 0.0884 | BC12: =BC11-BF11 -> 255122.37 | BD12: =IF($B$16*12/3-Q12+1>0,-PMT($BB12/4,$B$16*12/3-Q12+1,BC12),0) -> 6531.7846 | BE12: =BC12*($BB12/4) -> 5638.2044 | BF12: =BD12-BE12 -> 893.58016 | BG12: =AT12+AY12+BD12 -> 7805.7846 | BH12: =INDEX(cpi!B:B,MATCH($L12,cpi!A:A)) -> 91.6 | BI12: =100*BH12/BH$3 -> 108.27423 | BJ12: =100*AC12/AC$3 -> 118.56173 | BK12: =100*AD12/AD$3 -> 123.59997 | BL12: =BJ12*GlobalPortfolio+BK12*AusPortfolio -> 120.07321 | BM12: =100*AE12/$AE$3 -> 156.50976 | BN12: =100*AR12/AR$3 -> 121.21212 | BO12: =100*AX12/AX$3 -> 116.05011
A13: Council/Area | B13: Melbourne | C13: Melbourne | L13: =DATE(YEAR(L12),MONTH(L12)+3,1) -> 39692 | M13: =AP13 -> 122562.12 | N13: =AX13-BC13 -> 102386.96 | O13: =M13/N13 -> 1.1970481 | P13: =X13/BG13 -> 0.48949501 | Q13: 11 | R13: =EOMONTH(L13,0)-EOMONTH(L13,-3) -> 92 | T13: =IF($B$10="3BR_H", INDEX('3BR_H-processed'!$C:$D,MATCH($L13,'3BR_H-processed'!$B:$B,0),MATCH(Council_Area,'3BR_H-processed'!$C$1:$D$1,0)), INDEX('2BR_F-processed'!$C:$D,MATCH($L13,'2BR_F-processed'!$B:$B,0),MATCH(Council_Area,'2BR_F-processed'!$C$1:$D$1,0))) -> 300 | U13: =IF(MOD(Q13,4)=1,T13,U12) -> 280 | V13: =U13*(R13)/7 -> 3680 | W13: =$B$53/4*BH13/_xlfn.XLOOKUP(Q_end,cpi!A:A,cpi!B:B) -> 127.98894 | X13: =V13+W13 -> 3807.9889 | Y13: =BG13-X13 -> 3971.4345 | Z13: =Y13*$B$47 -> 0 | AA13: {=(Y13+Z13)*eff_invest} -> 3971.4345 | AB13: =AA13*(_xlfn.XLOOKUP(Q_end,cpi!A:A,cpi!B:B)/BH13) -> 6205.9025 | AC13: {=INDEX('msci-indices'!C:C,MATCH($L13,'msci-indices'!$B:$B)-2)} -> 881.79174 | AD13: {=INDEX('msci-indices'!D:D,MATCH($L13,'msci-indices'!$B:$B)-2)} -> 867.41147 | AE13: =AI12+AA13 -> 142316.79 | AF13: {=INDEX('msci-indices'!C:C,MATCH($L13,'msci-indices'!$B:$B)+1)} -> 747.65998 | AG13: {=INDEX('msci-indices'!D:D,MATCH($L13,'msci-indices'!$B:$B)+1)} -> 775.74397 | AH13: =(InvestFees/4)*AE13 -> 88.947993 | AI13: =((AF13/AC13)*GlobalPortfolio+(AG13/AD13)*AusPortfolio)*AE13-AH13 -> 122562.12 | AJ13: =AJ12+AA13 -> 127475.64 | AK13: =AI13-AJ13 -> -4913.5172 | AL13: =AJ13*(_xlfn.XLOOKUP(Q_end,cpi!A:A,cpi!B:B)/BH13) -> 199197.89 | AM13: {=SUMPRODUCT($AA$3:AA13,_xlfn.SORTBY($BH$3:BH13,_xlfn.SEQUENCE(ROWS($BH$3:BH13)),-1)/$BH$3)} -> 137346.05 | AN13: =AI13-AM13 -> -14783.935 | AO13: =IF($B$49="Real gains",MAX($B$50*AN13,0),IF($B$49="Discounted nominal gains",MAX($B$50*AK13/2,0),0)) -> 0 | AP13: =AI13-AO13 -> 122562.12 | AR13: =IF($B$10="3BR_H", INDEX('ns-combined'!$C:$D,MATCH($L13,'ns-combined'!$B:$B,0),MATCH(Council_Area,'ns-combined'!$C$1:$D$1,0))*1000, INDEX('s-combined'!$C:$D,MATCH($L13,'s-combined'!$B:$B,0),MATCH(Council_Area,'s-combined'!$C$1:$D$1,0))*1000) -> 385000 | AS13: =AS12+$AS$3 -> 9075 | AT13: 0 | AU13: =SUM($B$28:$B$29)*AR13 -> 7700 | AV13: =AR13*$B$15/4 -> 1106.875 | AW13: =SUM($AV$3:AV13) -> 11609.25 | AX13: =AR13-AS13-AU13-AW13 -> 356615.75 | AY13: =$B$36*V13 -> 1288 | AZ13: =SUM(AY13:AY13)*4/AR13 -> 0.013381818 | BA13: =SUM(AY13:AY13)/V13 -> 0.35 | BB13: =IF(MortgageRate="Discounted",_xlfn.XLOOKUP(L13,'mortgage-rates'!$A:$A,'mortgage-rates'!$E:$E)/100,_xlfn.XLOOKUP(L13,'mortgage-rates'!$A:$A,'mortgage-rates'!$D:$D)/100) -> 0.0876 | BC13: =BC12-BF12 -> 254228.79 | BD13: =IF($B$16*12/3-Q13+1>0,-PMT($BB13/4,$B$16*12/3-Q13+1,BC13),0) -> 6491.4234 | BE13: =BC13*($BB13/4) -> 5567.6105 | BF13: =BD13-BE13 -> 923.81288 | BG13: =AT13+AY13+BD13 -> 7779.4234 | BH13: =INDEX(cpi!B:B,MATCH($L13,cpi!A:A)) -> 92.6 | BI13: =100*BH13/BH$3 -> 109.45626 | BJ13: =100*AC13/AC$3 -> 116.81223 | BK13: =100*AD13/AD$3 -> 121.66405 | BL13: =BJ13*GlobalPortfolio+BK13*AusPortfolio -> 118.26778 | BM13: =100*AE13/$AE$3 -> 158.48245 | BN13: =100*AR13/AR$3 -> 116.66667 | BO13: =100*AX13/AX$3 -> 110.87893
A14: Depreciation (% of initial home value per year) | B14: 0.01 | C14: 0.01 | L14: =DATE(YEAR(L13),MONTH(L13)+3,1) -> 39783 | M14: =AP14 -> 98764.91 | N14: =AX14-BC14 -> 101378.9 | O14: =M14/N14 -> 0.97421567 | P14: =X14/BG14 -> 0.58104097 | Q14: 12 | R14: =EOMONTH(L14,0)-EOMONTH(L14,-3) -> 92 | T14: =IF($B$10="3BR_H", INDEX('3BR_H-processed'!$C:$D,MATCH($L14,'3BR_H-processed'!$B:$B,0),MATCH(Council_Area,'3BR_H-processed'!$C$1:$D$1,0)), INDEX('2BR_F-processed'!$C:$D,MATCH($L14,'2BR_F-processed'!$B:$B,0),MATCH(Council_Area,'2BR_F-processed'!$C$1:$D$1,0))) -> 300 | U14: =IF(MOD(Q14,4)=1,T14,U13) -> 280 | V14: =U14*(R14)/7 -> 3680 | W14: =$B$53/4*BH14/_xlfn.XLOOKUP(Q_end,cpi!A:A,cpi!B:B) -> 127.98894 | X14: =V14+W14 -> 3807.9889 | Y14: =BG14-X14 -> 2745.7468 | Z14: =Y14*$B$47 -> 0 | AA14: {=(Y14+Z14)*eff_invest} -> 2745.7468 | AB14: =AA14*(_xlfn.XLOOKUP(Q_end,cpi!A:A,cpi!B:B)/BH14) -> 4290.6 | AC14: {=INDEX('msci-indices'!C:C,MATCH($L14,'msci-indices'!$B:$B)-2)} -> 747.65998 | AD14: {=INDEX('msci-indices'!D:D,MATCH($L14,'msci-indices'!$B:$B)-2)} -> 775.74397 | AE14: =AI13+AA14 -> 125307.87 | AF14: {=INDEX('msci-indices'!C:C,MATCH($L14,'msci-indices'!$B:$B)+1)} -> 582.01082 | AG14: {=INDEX('msci-indices'!D:D,MATCH($L14,'msci-indices'!$B:$B)+1)} -> 630.6613 | AH14: =(InvestFees/4)*AE14 -> 78.317416 | AI14: =((AF14/AC14)*GlobalPortfolio+(AG14/AD14)*AusPortfolio)*AE14-AH14 -> 98764.91 | AJ14: =AJ13+AA14 -> 130221.38 | AK14: =AI14-AJ14 -> -31456.473 | AL14: =AJ14*(_xlfn.XLOOKUP(Q_end,cpi!A:A,cpi!B:B)/BH14) -> 203488.49 | AM14: {=SUMPRODUCT($AA$3:AA14,_xlfn.SORTBY($BH$3:BH14,_xlfn.SEQUENCE(ROWS($BH$3:BH14)),-1)/$BH$3)} -> 140445.34 | AN14: =AI14-AM14 -> -41680.433 | AO14: =IF($B$49="Real gains",MAX($B$50*AN14,0),IF($B$49="Discounted nominal gains",MAX($B$50*AK14/2,0),0)) -> 0 | AP14: =AI14-AO14 -> 98764.91 | AR14: =IF($B$10="3BR_H", INDEX('ns-combined'!$C:$D,MATCH($L14,'ns-combined'!$B:$B,0),MATCH(Council_Area,'ns-combined'!$C$1:$D$1,0))*1000, INDEX('s-combined'!$C:$D,MATCH($L14,'s-combined'!$B:$B,0),MATCH(Council_Area,'s-combined'!$C$1:$D$1,0))*1000) -> 385000 | AS14: =AS13+$AS$3 -> 9900 | AT14: 0 | AU14: =SUM($B$28:$B$29)*AR14 -> 7700 | AV14: =AR14*$B$15/4 -> 1106.875 | AW14: =SUM($AV$3:AV14) -> 12716.125 | AX14: =AR14-AS14-AU14-AW14 -> 354683.88 | AY14: =$B$36*V14 -> 1288 | AZ14: =SUM(AY14:AY14)*4/AR14 -> 0.013381818 | BA14: =SUM(AY14:AY14)/V14 -> 0.35 | BB14: =IF(MortgageRate="Discounted",_xlfn.XLOOKUP(L14,'mortgage-rates'!$A:$A,'mortgage-rates'!$E:$E)/100,_xlfn.XLOOKUP(L14,'mortgage-rates'!$A:$A,'mortgage-rates'!$D:$D)/100) -> 0.062 | BC14: =BC13-BF13 -> 253304.98 | BD14: =IF($B$16*12/3-Q14+1>0,-PMT($BB14/4,$B$16*12/3-Q14+1,BC14),0) -> 5265.7357 | BE14: =BC14*($BB14/4) -> 3926.2272 | BF14: =BD14-BE14 -> 1339.5085 | BG14: =AT14+AY14+BD14 -> 6553.7357 | BH14: =INDEX(cpi!B:B,MATCH($L14,cpi!A:A)) -> 92.6 | BI14: =100*BH14/BH$3 -> 109.45626 | BJ14: =100*AC14/AC$3 -> 99.043605 | BK14: =100*AD14/AD$3 -> 108.80667 | BL14: =BJ14*GlobalPortfolio+BK14*AusPortfolio -> 101.97253 | BM14: =100*AE14/$AE$3 -> 139.5415 | BN14: =100*AR14/AR$3 -> 116.66667 | BO14: =100*AX14/AX$3 -> 110.27827
A15: Renovations, alterations, and additions (% of current home value per year) | B15: 0.0115 | C15: 0.0115 | L15: =DATE(YEAR(L14),MONTH(L14)+3,1) -> 39873 | M15: =AP15 -> 92061.272 | N15: =AX15-BC15 -> 91015.28 | O15: =M15/N15 -> 1.0114925 | P15: =X15/BG15 -> 0.66243986 | Q15: 13 | R15: =EOMONTH(L15,0)-EOMONTH(L15,-3) -> 90 | T15: =IF($B$10="3BR_H", INDEX('3BR_H-processed'!$C:$D,MATCH($L15,'3BR_H-processed'!$B:$B,0),MATCH(Council_Area,'3BR_H-processed'!$C$1:$D$1,0)), INDEX('2BR_F-processed'!$C:$D,MATCH($L15,'2BR_F-processed'!$B:$B,0),MATCH(Council_Area,'2BR_F-processed'!$C$1:$D$1,0))) -> 310 | U15: =IF(MOD(Q15,4)=1,T15,U14) -> 310 | V15: =U15*(R15)/7 -> 3985.7143 | W15: =$B$53/4*BH15/_xlfn.XLOOKUP(Q_end,cpi!A:A,cpi!B:B) -> 127.85073 | X15: =V15+W15 -> 4113.565 | Y15: =BG15-X15 -> 2096.1534 | Z15: =Y15*$B$47 -> 0 | AA15: {=(Y15+Z15)*eff_invest} -> 2096.1534 | AB15: =AA15*(_xlfn.XLOOKUP(Q_end,cpi!A:A,cpi!B:B)/BH15) -> 3279.0638 | AC15: {=INDEX('msci-indices'!C:C,MATCH($L15,'msci-indices'!$B:$B)-2)} -> 582.01082 | AD15: {=INDEX('msci-indices'!D:D,MATCH($L15,'msci-indices'!$B:$B)-2)} -> 630.6613 | AE15: =AI14+AA15 -> 100861.06 | AF15: {=INDEX('msci-indices'!C:C,MATCH($L15,'msci-indices'!$B:$B)+1)} -> 513.55423 | AG15: {=INDEX('msci-indices'!D:D,MATCH($L15,'msci-indices'!$B:$B)+1)} -> 621.64895 | AH15: =(InvestFees/4)*AE15 -> 63.038164 | AI15: =((AF15/AC15)*GlobalPortfolio+(AG15/AD15)*AusPortfolio)*AE15-AH15 -> 92061.272 | AJ15: =AJ14+AA15 -> 132317.54 | AK15: =AI15-AJ15 -> -40256.264 | AL15: =AJ15*(_xlfn.XLOOKUP(Q_end,cpi!A:A,cpi!B:B)/BH15) -> 206987.54 | AM15: {=SUMPRODUCT($AA$3:AA15,_xlfn.SORTBY($BH$3:BH15,_xlfn.SEQUENCE(ROWS($BH$3:BH15)),-1)/$BH$3)} -> 142772.92 | AN15: =AI15-AM15 -> -50711.652 | AO15: =IF($B$49="Real gains",MAX($B$50*AN15,0),IF($B$49="Discounted nominal gains",MAX($B$50*AK15/2,0),0)) -> 0 | AP15: =AI15-AO15 -> 92061.272 | AR15: =IF($B$10="3BR_H", INDEX('ns-combined'!$C:$D,MATCH($L15,'ns-combined'!$B:$B,0),MATCH(Council_Area,'ns-combined'!$C$1:$D$1,0))*1000, INDEX('s-combined'!$C:$D,MATCH($L15,'s-combined'!$B:$B,0),MATCH(Council_Area,'s-combined'!$C$1:$D$1,0))*1000) -> 375000 | AS15: =AS14+$AS$3 -> 10725 | AT15: 0 | AU15: =SUM($B$28:$B$29)*AR15 -> 7500 | AV15: =AR15*$B$15/4 -> 1078.125 | AW15: =SUM($AV$3:AV15) -> 13794.25 | AX15: =AR15-AS15-AU15-AW15 -> 342980.75 | AY15: =$B$36*V15 -> 1395 | AZ15: =SUM(AY15:AY15)*4/AR15 -> 0.01488 | BA15: =SUM(AY15:AY15)/V15 -> 0.35 | BB15: =IF(MortgageRate="Discounted",_xlfn.XLOOKUP(L15,'mortgage-rates'!$A:$A,'mortgage-rates'!$E:$E)/100,_xlfn.XLOOKUP(L15,'mortgage-rates'!$A:$A,'mortgage-rates'!$D:$D)/100) -> 0.0518 | BC15: =BC14-BF14 -> 251965.47 | BD15: =IF($B$16*12/3-Q15+1>0,-PMT($BB15/4,$B$16*12/3-Q15+1,BC15),0) -> 4814.7184 | BE15: =BC15*($BB15/4) -> 3262.9528 | BF15: =BD15-BE15 -> 1551.7656 | BG15: =AT15+AY15+BD15 -> 6209.7184 | BH15: =INDEX(cpi!B:B,MATCH($L15,cpi!A:A)) -> 92.5 | BI15: =100*BH15/BH$3 -> 109.33806 | BJ15: =100*AC15/AC$3 -> 77.099819 | BK15: =100*AD15/AD$3 -> 88.457223 | BL15: =BJ15*GlobalPortfolio+BK15*AusPortfolio -> 80.50704 | BM15: =100*AE15/$AE$3 -> 112.3178 | BN15: =100*AR15/AR$3 -> 113.63636 | BO15: =100*AX15/AX$3 -> 106.63954
A16: Loan term (years) | B16: 25 | C16: 25 | L16: =DATE(YEAR(L15),MONTH(L15)+3,1) -> 39965 | M16: =AP16 -> 111571.45 | N16: =AX16-BC16 -> 115092.05 | O16: =M16/N16 -> 0.9694106 | P16: =X16/BG16 -> 0.66985751 | Q16: 14 | R16: =EOMONTH(L16,0)-EOMONTH(L16,-3) -> 91 | T16: =IF($B$10="3BR_H", INDEX('3BR_H-processed'!$C:$D,MATCH($L16,'3BR_H-processed'!$B:$B,0),MATCH(Council_Area,'3BR_H-processed'!$C$1:$D$1,0)), INDEX('2BR_F-processed'!$C:$D,MATCH($L16,'2BR_F-processed'!$B:$B,0),MATCH(Council_Area,'2BR_F-processed'!$C$1:$D$1,0))) -> 300 | U16: =IF(MOD(Q16,4)=1,T16,U15) -> 310 | V16: =U16*(R16)/7 -> 4030 | W16: =$B$53/4*BH16/_xlfn.XLOOKUP(Q_end,cpi!A:A,cpi!B:B) -> 128.54181 | X16: =V16+W16 -> 4158.5418 | Y16: =BG16-X16 -> 2049.5573 | Z16: =Y16*$B$47 -> 0 | AA16: {=(Y16+Z16)*eff_invest} -> 2049.5573 | AB16: =AA16*(_xlfn.XLOOKUP(Q_end,cpi!A:A,cpi!B:B)/BH16) -> 3188.9348 | AC16: {=INDEX('msci-indices'!C:C,MATCH($L16,'msci-indices'!$B:$B)-2)} -> 513.55423 | AD16: {=INDEX('msci-indices'!D:D,MATCH($L16,'msci-indices'!$B:$B)-2)} -> 621.64895 | AE16: =AI15+AA16 -> 94110.829 | AF16: {=INDEX('msci-indices'!C:C,MATCH($L16,'msci-indices'!$B:$B)+1)} -> 624.35598 | AG16: {=INDEX('msci-indices'!D:D,MATCH($L16,'msci-indices'!$B:$B)+1)} -> 694.44245 | AH16: =(InvestFees/4)*AE16 -> 58.819268 | AI16: =((AF16/AC16)*GlobalPortfolio+(AG16/AD16)*AusPortfolio)*AE16-AH16 -> 111571.45 | AJ16: =AJ15+AA16 -> 134367.09 | AK16: =AI16-AJ16 -> -22795.643 | AL16: =AJ16*(_xlfn.XLOOKUP(Q_end,cpi!A:A,cpi!B:B)/BH16) -> 209063.64 | AM16: {=SUMPRODUCT($AA$3:AA16,_xlfn.SORTBY($BH$3:BH16,_xlfn.SEQUENCE(ROWS($BH$3:BH16)),-1)/$BH$3)} -> 145669.47 | AN16: =AI16-AM16 -> -34098.02 | AO16: =IF($B$49="Real gains",MAX($B$50*AN16,0),IF($B$49="Discounted nominal gains",MAX($B$50*AK16/2,0),0)) -> 0 | AP16: =AI16-AO16 -> 111571.45 | AR16: =IF($B$10="3BR_H", INDEX('ns-combined'!$C:$D,MATCH($L16,'ns-combined'!$B:$B,0),MATCH(Council_Area,'ns-combined'!$C$1:$D$1,0))*1000, INDEX('s-combined'!$C:$D,MATCH($L16,'s-combined'!$B:$B,0),MATCH(Council_Area,'s-combined'!$C$1:$D$1,0))*1000) -> 400000 | AS16: =AS15+$AS$3 -> 11550 | AT16: 0 | AU16: =SUM($B$28:$B$29)*AR16 -> 8000 | AV16: =AR16*$B$15/4 -> 1150 | AW16: =SUM($AV$3:AV16) -> 14944.25 | AX16: =AR16-AS16-AU16-AW16 -> 365505.75 | AY16: =$B$36*V16 -> 1410.5 | AZ16: =SUM(AY16:AY16)*4/AR16 -> 0.014105 | BA16: =SUM(AY16:AY16)/V16 -> 0.35 | BB16: =IF(MortgageRate="Discounted",_xlfn.XLOOKUP(L16,'mortgage-rates'!$A:$A,'mortgage-rates'!$E:$E)/100,_xlfn.XLOOKUP(L16,'mortgage-rates'!$A:$A,'mortgage-rates'!$D:$D)/100) -> 0.0514 | BC16: =BC15-BF15 -> 250413.7 | BD16: =IF($B$16*12/3-Q16+1>0,-PMT($BB16/4,$B$16*12/3-Q16+1,BC16),0) -> 4797.5991 | BE16: =BC16*($BB16/4) -> 3217.8161 | BF16: =BD16-BE16 -> 1579.783 | BG16: =AT16+AY16+BD16 -> 6208.0991 | BH16: =INDEX(cpi!B:B,MATCH($L16,cpi!A:A)) -> 93 | BI16: =100*BH16/BH$3 -> 109.92908 | BJ16: =100*AC16/AC$3 -> 68.031276 | BK16: =100*AD16/AD$3 -> 87.193142 | BL16: =BJ16*GlobalPortfolio+BK16*AusPortfolio -> 73.779836 | BM16: =100*AE16/$AE$3 -> 104.80081 | BN16: =100*AR16/AR$3 -> 121.21212 | BO16: =100*AX16/AX$3 -> 113.64301
L17: =DATE(YEAR(L16),MONTH(L16)+3,1) -> 40057 | M17: =AP17 -> 135451.63 | N17: =AX17-BC17 -> 136193.58 | O17: =M17/N17 -> 0.99455224 | P17: =X17/BG17 -> 0.67546045 | Q17: 15 | R17: =EOMONTH(L17,0)-EOMONTH(L17,-3) -> 92 | T17: =IF($B$10="3BR_H", INDEX('3BR_H-processed'!$C:$D,MATCH($L17,'3BR_H-processed'!$B:$B,0),MATCH(Council_Area,'3BR_H-processed'!$C$1:$D$1,0)), INDEX('2BR_F-processed'!$C:$D,MATCH($L17,'2BR_F-processed'!$B:$B,0),MATCH(Council_Area,'2BR_F-processed'!$C$1:$D$1,0))) -> 310 | U17: =IF(MOD(Q17,4)=1,T17,U16) -> 310 | V17: =U17*(R17)/7 -> 4074.2857 | W17: =$B$53/4*BH17/_xlfn.XLOOKUP(Q_end,cpi!A:A,cpi!B:B) -> 129.50933 | X17: =V17+W17 -> 4203.795 | Y17: =BG17-X17 -> 2019.804 | Z17: =Y17*$B$47 -> 0 | AA17: {=(Y17+Z17)*eff_invest} -> 2019.804 | AB17: =AA17*(_xlfn.XLOOKUP(Q_end,cpi!A:A,cpi!B:B)/BH17) -> 3119.1638 | AC17: {=INDEX('msci-indices'!C:C,MATCH($L17,'msci-indices'!$B:$B)-2)} -> 624.35598 | AD17: {=INDEX('msci-indices'!D:D,MATCH($L17,'msci-indices'!$B:$B)-2)} -> 694.44245 | AE17: =AI16+AA17 -> 113591.25 | AF17: {=INDEX('msci-indices'!C:C,MATCH($L17,'msci-indices'!$B:$B)+1)} -> 736.86333 | AG17: {=INDEX('msci-indices'!D:D,MATCH($L17,'msci-indices'!$B:$B)+1)} -> 849.38296 | AH17: =(InvestFees/4)*AE17 -> 70.994534 | AI17: =((AF17/AC17)*GlobalPortfolio+(AG17/AD17)*AusPortfolio)*AE17-AH17 -> 135451.63 | AJ17: =AJ16+AA17 -> 136386.9 | AK17: =AI17-AJ17 -> -935.26765 | AL17: =AJ17*(_xlfn.XLOOKUP(Q_end,cpi!A:A,cpi!B:B)/BH17) -> 210620.96 | AM17: {=SUMPRODUCT($AA$3:AA17,_xlfn.SORTBY($BH$3:BH17,_xlfn.SEQUENCE(ROWS($BH$3:BH17)),-1)/$BH$3)} -> 148764.33 | AN17: =AI17-AM17 -> -13312.7 | AO17: =IF($B$49="Real gains",MAX($B$50*AN17,0),IF($B$49="Discounted nominal gains",MAX($B$50*AK17/2,0),0)) -> 0 | AP17: =AI17-AO17 -> 135451.63 | AR17: =IF($B$10="3BR_H", INDEX('ns-combined'!$C:$D,MATCH($L17,'ns-combined'!$B:$B,0),MATCH(Council_Area,'ns-combined'!$C$1:$D$1,0))*1000, INDEX('s-combined'!$C:$D,MATCH($L17,'s-combined'!$B:$B,0),MATCH(Council_Area,'s-combined'!$C$1:$D$1,0))*1000) -> 422000 | AS17: =AS16+$AS$3 -> 12375 | AT17: 0 | AU17: =SUM($B$28:$B$29)*AR17 -> 8440 | AV17: =AR17*$B$15/4 -> 1213.25 | AW17: =SUM($AV$3:AV17) -> 16157.5 | AX17: =AR17-AS17-AU17-AW17 -> 385027.5 | AY17: =$B$36*V17 -> 1426 | AZ17: =SUM(AY17:AY17)*4/AR17 -> 0.013516588 | BA17: =SUM(AY17:AY17)/V17 -> 0.35 | BB17: =IF(MortgageRate="Discounted",_xlfn.XLOOKUP(L17,'mortgage-rates'!$A:$A,'mortgage-rates'!$E:$E)/100,_xlfn.XLOOKUP(L17,'mortgage-rates'!$A:$A,'mortgage-rates'!$D:$D)/100) -> 0.0514 | BC17: =BC16-BF16 -> 248833.92 | BD17: =IF($B$16*12/3-Q17+1>0,-PMT($BB17/4,$B$16*12/3-Q17+1,BC17),0) -> 4797.5991 | BE17: =BC17*($BB17/4) -> 3197.5159 | BF17: =BD17-BE17 -> 1600.0832 | BG17: =AT17+AY17+BD17 -> 6223.5991 | BH17: =INDEX(cpi!B:B,MATCH($L17,cpi!A:A)) -> 93.7 | BI17: =100*BH17/BH$3 -> 110.7565 | BJ17: =100*AC17/AC$3 -> 82.709345 | BK17: =100*AD17/AD$3 -> 97.403235 | BL17: =BJ17*GlobalPortfolio+BK17*AusPortfolio -> 87.117512 | BM17: =100*AE17/$AE$3 -> 126.49401 | BN17: =100*AR17/AR$3 -> 127.87879 | BO17: =100*AX17/AX$3 -> 119.71271
A18: Mortgage | L18: =DATE(YEAR(L17),MONTH(L17)+3,1) -> 40148 | M18: =AP18 -> 142943.53 | N18: =AX18-BC18 -> 189985.85 | O18: =M18/N18 -> 0.75239039 | P18: =X18/BG18 -> 0.63790899 | Q18: 16 | R18: =EOMONTH(L18,0)-EOMONTH(L18,-3) -> 92 | T18: =IF($B$10="3BR_H", INDEX('3BR_H-processed'!$C:$D,MATCH($L18,'3BR_H-processed'!$B:$B,0),MATCH(Council_Area,'3BR_H-processed'!$C$1:$D$1,0)), INDEX('2BR_F-processed'!$C:$D,MATCH($L18,'2BR_F-processed'!$B:$B,0),MATCH(Council_Area,'2BR_F-processed'!$C$1:$D$1,0))) -> 320 | U18: =IF(MOD(Q18,4)=1,T18,U17) -> 310 | V18: =U18*(R18)/7 -> 4074.2857 | W18: =$B$53/4*BH18/_xlfn.XLOOKUP(Q_end,cpi!A:A,cpi!B:B) -> 130.61507 | X18: =V18+W18 -> 4204.9008 | Y18: =BG18-X18 -> 2386.7931 | Z18: =Y18*$B$47 -> 0 | AA18: {=(Y18+Z18)*eff_invest} -> 2386.7931 | AB18: =AA18*(_xlfn.XLOOKUP(Q_end,cpi!A:A,cpi!B:B)/BH18) -> 3654.698 | AC18: {=INDEX('msci-indices'!C:C,MATCH($L18,'msci-indices'!$B:$B)-2)} -> 736.86333 | AD18: {=INDEX('msci-indices'!D:D,MATCH($L18,'msci-indices'!$B:$B)-2)} -> 849.38296 | AE18: =AI17+AA18 -> 137838.42 | AF18: {=INDEX('msci-indices'!C:C,MATCH($L18,'msci-indices'!$B:$B)+1)} -> 765.74116 | AG18: {=INDEX('msci-indices'!D:D,MATCH($L18,'msci-indices'!$B:$B)+1)} -> 878.3433 | AH18: =(InvestFees/4)*AE18 -> 86.149014 | AI18: =((AF18/AC18)*GlobalPortfolio+(AG18/AD18)*AusPortfolio)*AE18-AH18 -> 142943.53 | AJ18: =AJ17+AA18 -> 138773.69 | AK18: =AI18-AJ18 -> 4169.8365 | AL18: =AJ18*(_xlfn.XLOOKUP(Q_end,cpi!A:A,cpi!B:B)/BH18) -> 212492.62 | AM18: {=SUMPRODUCT($AA$3:AA18,_xlfn.SORTBY($BH$3:BH18,_xlfn.SEQUENCE(ROWS($BH$3:BH18)),-1)/$BH$3)} -> 152364.45 | AN18: =AI18-AM18 -> -9420.9259 | AO18: =IF($B$49="Real gains",MAX($B$50*AN18,0),IF($B$49="Discounted nominal gains",MAX($B$50*AK18/2,0),0)) -> 0 | AP18: =AI18-AO18 -> 142943.53 | AR18: =IF($B$10="3BR_H", INDEX('ns-combined'!$C:$D,MATCH($L18,'ns-combined'!$B:$B,0),MATCH(Council_Area,'ns-combined'!$C$1:$D$1,0))*1000, INDEX('s-combined'!$C:$D,MATCH($L18,'s-combined'!$B:$B,0),MATCH(Council_Area,'s-combined'!$C$1:$D$1,0))*1000) -> 477500 | AS18: =AS17+$AS$3 -> 13200 | AT18: 0 | AU18: =SUM($B$28:$B$29)*AR18 -> 9550 | AV18: =AR18*$B$15/4 -> 1372.8125 | AW18: =SUM($AV$3:AV18) -> 17530.312 | AX18: =AR18-AS18-AU18-AW18 -> 437219.69 | AY18: =$B$36*V18 -> 1426 | AZ18: =SUM(AY18:AY18)*4/AR18 -> 0.01194555 | BA18: =SUM(AY18:AY18)/V18 -> 0.35 | BB18: =IF(MortgageRate="Discounted",_xlfn.XLOOKUP(L18,'mortgage-rates'!$A:$A,'mortgage-rates'!$E:$E)/100,_xlfn.XLOOKUP(L18,'mortgage-rates'!$A:$A,'mortgage-rates'!$D:$D)/100) -> 0.06 | BC18: =BC17-BF17 -> 247233.84 | BD18: =IF($B$16*12/3-Q18+1>0,-PMT($BB18/4,$B$16*12/3-Q18+1,BC18),0) -> 5165.6938 | BE18: =BC18*($BB18/4) -> 3708.5076 | BF18: =BD18-BE18 -> 1457.1863 | BG18: =AT18+AY18+BD18 -> 6591.6938 | BH18: =INDEX(cpi!B:B,MATCH($L18,cpi!A:A)) -> 94.5 | BI18: =100*BH18/BH$3 -> 111.70213 | BJ18: =100*AC18/AC$3 -> 97.613357 | BK18: =100*AD18/AD$3 -> 119.13536 | BL18: =BJ18*GlobalPortfolio+BK18*AusPortfolio -> 104.06996 | BM18: =100*AE18/$AE$3 -> 153.49539 | BN18: =100*AR18/AR$3 -> 144.69697 | BO18: =100*AX18/AX$3 -> 135.9403
A19: Mortgage rates (Standard/Discounted) | B19: Discounted | C19: Discounted | L19: =DATE(YEAR(L18),MONTH(L18)+3,1) -> 40238 | M19: =AP19 -> 149833.81 | N19: =AX19-BC19 -> 179962.54 | O19: =M19/N19 -> 0.83258333 | P19: =X19/BG19 -> 0.64717371 | Q19: 17 | R19: =EOMONTH(L19,0)-EOMONTH(L19,-3) -> 90 | T19: =IF($B$10="3BR_H", INDEX('3BR_H-processed'!$C:$D,MATCH($L19,'3BR_H-processed'!$B:$B,0),MATCH(Council_Area,'3BR_H-processed'!$C$1:$D$1,0)), INDEX('2BR_F-processed'!$C:$D,MATCH($L19,'2BR_F-processed'!$B:$B,0),MATCH(Council_Area,'2BR_F-processed'!$C$1:$D$1,0))) -> 330 | U19: =IF(MOD(Q19,4)=1,T19,U18) -> 330 | V19: =U19*(R19)/7 -> 4242.8571 | W19: =$B$53/4*BH19/_xlfn.XLOOKUP(Q_end,cpi!A:A,cpi!B:B) -> 131.58258 | X19: =V19+W19 -> 4374.4397 | Y19: =BG19-X19 -> 2384.8579 | Z19: =Y19*$B$47 -> 0 | AA19: {=(Y19+Z19)*eff_invest} -> 2384.8579 | AB19: =AA19*(_xlfn.XLOOKUP(Q_end,cpi!A:A,cpi!B:B)/BH19) -> 3624.8838 | AC19: {=INDEX('msci-indices'!C:C,MATCH($L19,'msci-indices'!$B:$B)-2)} -> 765.74116 | AD19: {=INDEX('msci-indices'!D:D,MATCH($L19,'msci-indices'!$B:$B)-2)} -> 878.3433 | AE19: =AI18+AA19 -> 145328.38 | AF19: {=INDEX('msci-indices'!C:C,MATCH($L19,'msci-indices'!$B:$B)+1)} -> 794.63718 | AG19: {=INDEX('msci-indices'!D:D,MATCH($L19,'msci-indices'!$B:$B)+1)} -> 893.60148 | AH19: =(InvestFees/4)*AE19 -> 90.83024 | AI19: =((AF19/AC19)*GlobalPortfolio+(AG19/AD19)*AusPortfolio)*AE19-AH19 -> 149833.81 | AJ19: =AJ18+AA19 -> 141158.55 | AK19: =AI19-AJ19 -> 8675.259 | AL19: =AJ19*(_xlfn.XLOOKUP(Q_end,cpi!A:A,cpi!B:B)/BH19) -> 214555.06 | AM19: {=SUMPRODUCT($AA$3:AA19,_xlfn.SORTBY($BH$3:BH19,_xlfn.SEQUENCE(ROWS($BH$3:BH19)),-1)/$BH$3)} -> 155887.65 | AN19: =AI19-AM19 -> -6053.8447 | AO19: =IF($B$49="Real gains",MAX($B$50*AN19,0),IF($B$49="Discounted nominal gains",MAX($B$50*AK19/2,0),0)) -> 0 | AP19: =AI19-AO19 -> 149833.81 | AR19: =IF($B$10="3BR_H", INDEX('ns-combined'!$C:$D,MATCH($L19,'ns-combined'!$B:$B,0),MATCH(Council_Area,'ns-combined'!$C$1:$D$1,0))*1000, INDEX('s-combined'!$C:$D,MATCH($L19,'s-combined'!$B:$B,0),MATCH(Council_Area,'s-combined'!$C$1:$D$1,0))*1000) -> 468000 | AS19: =AS18+$AS$3 -> 14025 | AT19: 0 | AU19: =SUM($B$28:$B$29)*AR19 -> 9360 | AV19: =AR19*$B$15/4 -> 1345.5 | AW19: =SUM($AV$3:AV19) -> 18875.812 | AX19: =AR19-AS19-AU19-AW19 -> 425739.19 | AY19: =$B$36*V19 -> 1485 | AZ19: =SUM(AY19:AY19)*4/AR19 -> 0.012692308 | BA19: =SUM(AY19:AY19)/V19 -> 0.35 | BB19: =IF(MortgageRate="Discounted",_xlfn.XLOOKUP(L19,'mortgage-rates'!$A:$A,'mortgage-rates'!$E:$E)/100,_xlfn.XLOOKUP(L19,'mortgage-rates'!$A:$A,'mortgage-rates'!$D:$D)/100) -> 0.0625 | BC19: =BC18-BF18 -> 245776.65 | BD19: =IF($B$16*12/3-Q19+1>0,-PMT($BB19/4,$B$16*12/3-Q19+1,BC19),0) -> 5274.2976 | BE19: =BC19*($BB19/4) -> 3840.2602 | BF19: =BD19-BE19 -> 1434.0374 | BG19: =AT19+AY19+BD19 -> 6759.2976 | BH19: =INDEX(cpi!B:B,MATCH($L19,cpi!A:A)) -> 95.2 | BI19: =100*BH19/BH$3 -> 112.52955 | BJ19: =100*AC19/AC$3 -> 101.43885 | BK19: =100*AD19/AD$3 -> 123.19736 | BL19: =BJ19*GlobalPortfolio+BK19*AusPortfolio -> 107.9664 | BM19: =100*AE19/$AE$3 -> 161.83614 | BN19: =100*AR19/AR$3 -> 141.81818 | BO19: =100*AX19/AX$3 -> 132.37078
A20: Deposit (% of home purchase price) | B20: 0.2 | C20: 0.2 | L20: =DATE(YEAR(L19),MONTH(L19)+3,1) -> 40330 | M20: =AP20 -> 133626.08 | N20: =AX20-BC20 -> 210494.07 | O20: =M20/N20 -> 0.63482111 | P20: =X20/BG20 -> 0.63228131 | Q20: 18 | R20: =EOMONTH(L20,0)-EOMONTH(L20,-3) -> 91 | T20: =IF($B$10="3BR_H", INDEX('3BR_H-processed'!$C:$D,MATCH($L20,'3BR_H-processed'!$B:$B,0),MATCH(Council_Area,'3BR_H-processed'!$C$1:$D$1,0)), INDEX('2BR_F-processed'!$C:$D,MATCH($L20,'2BR_F-processed'!$B:$B,0),MATCH(Council_Area,'2BR_F-processed'!$C$1:$D$1,0))) -> 330 | U20: =IF(MOD(Q20,4)=1,T20,U19) -> 330 | V20: =U20*(R20)/7 -> 4290 | W20: =$B$53/4*BH20/_xlfn.XLOOKUP(Q_end,cpi!A:A,cpi!B:B) -> 132.41189 | X20: =V20+W20 -> 4422.4119 | Y20: =BG20-X20 -> 2571.962 | Z20: =Y20*$B$47 -> 0 | AA20: {=(Y20+Z20)*eff_invest} -> 2571.962 | AB20: =AA20*(_xlfn.XLOOKUP(Q_end,cpi!A:A,cpi!B:B)/BH20) -> 3884.7902 | AC20: {=INDEX('msci-indices'!C:C,MATCH($L20,'msci-indices'!$B:$B)-2)} -> 794.63718 | AD20: {=INDEX('msci-indices'!D:D,MATCH($L20,'msci-indices'!$B:$B)-2)} -> 893.60148 | AE20: =AI19+AA20 -> 152405.77 | AF20: {=INDEX('msci-indices'!C:C,MATCH($L20,'msci-indices'!$B:$B)+1)} -> 696.18018 | AG20: {=INDEX('msci-indices'!D:D,MATCH($L20,'msci-indices'!$B:$B)+1)} -> 786.77037 | AH20: =(InvestFees/4)*AE20 -> 95.253606 | AI20: =((AF20/AC20)*GlobalPortfolio+(AG20/AD20)*AusPortfolio)*AE20-AH20 -> 133626.08 | AJ20: =AJ19+AA20 -> 143730.51 | AK20: =AI20-AJ20 -> -10104.428 | AL20: =AJ20*(_xlfn.XLOOKUP(Q_end,cpi!A:A,cpi!B:B)/BH20) -> 217096.08 | AM20: {=SUMPRODUCT($AA$3:AA20,_xlfn.SORTBY($BH$3:BH20,_xlfn.SEQUENCE(ROWS($BH$3:BH20)),-1)/$BH$3)} -> 159513.81 | AN20: =AI20-AM20 -> -25887.724 | AO20: =IF($B$49="Real gains",MAX($B$50*AN20,0),IF($B$49="Discounted nominal gains",MAX($B$50*AK20/2,0),0)) -> 0 | AP20: =AI20-AO20 -> 133626.08 | AR20: =IF($B$10="3BR_H", INDEX('ns-combined'!$C:$D,MATCH($L20,'ns-combined'!$B:$B,0),MATCH(Council_Area,'ns-combined'!$C$1:$D$1,0))*1000, INDEX('s-combined'!$C:$D,MATCH($L20,'s-combined'!$B:$B,0),MATCH(Council_Area,'s-combined'!$C$1:$D$1,0))*1000) -> 500000 | AS20: =AS19+$AS$3 -> 14850 | AT20: 0 | AU20: =SUM($B$28:$B$29)*AR20 -> 10000 | AV20: =AR20*$B$15/4 -> 1437.5 | AW20: =SUM($AV$3:AV20) -> 20313.312 | AX20: =AR20-AS20-AU20-AW20 -> 454836.69 | AY20: =$B$36*V20 -> 1501.5 | AZ20: =SUM(AY20:AY20)*4/AR20 -> 0.012012 | BA20: =SUM(AY20:AY20)/V20 -> 0.35 | BB20: =IF(MortgageRate="Discounted",_xlfn.XLOOKUP(L20,'mortgage-rates'!$A:$A,'mortgage-rates'!$E:$E)/100,_xlfn.XLOOKUP(L20,'mortgage-rates'!$A:$A,'mortgage-rates'!$D:$D)/100) -> 0.0675 | BC20: =BC19-BF19 -> 244342.61 | BD20: =IF($B$16*12/3-Q20+1>0,-PMT($BB20/4,$B$16*12/3-Q20+1,BC20),0) -> 5492.8739 | BE20: =BC20*($BB20/4) -> 4123.2816 | BF20: =BD20-BE20 -> 1369.5923 | BG20: =AT20+AY20+BD20 -> 6994.3739 | BH20: =INDEX(cpi!B:B,MATCH($L20,cpi!A:A)) -> 95.8 | BI20: =100*BH20/BH$3 -> 113.23877 | BJ20: =100*AC20/AC$3 -> 105.26674 | BK20: =100*AD20/AD$3 -> 125.33749 | BL20: =BJ20*GlobalPortfolio+BK20*AusPortfolio -> 111.28797 | BM20: =100*AE20/$AE$3 -> 169.71744 | BN20: =100*AR20/AR$3 -> 151.51515 | BO20: =100*AX20/AX$3 -> 141.41778
A21: Lenders' mortgage insurance (% of home purchase price) | B21: 0 | C21: 0 | L21: =DATE(YEAR(L20),MONTH(L20)+3,1) -> 40422 | M21: =AP21 -> 152910.45 | N21: =AX21-BC21 -> 198168.8 | O21: =M21/N21 -> 0.77161715 | P21: =X21/BG21 -> 0.63763578 | Q21: 19 | R21: =EOMONTH(L21,0)-EOMONTH(L21,-3) -> 92 | T21: =IF($B$10="3BR_H", INDEX('3BR_H-processed'!$C:$D,MATCH($L21,'3BR_H-processed'!$B:$B,0),MATCH(Council_Area,'3BR_H-processed'!$C$1:$D$1,0)), INDEX('2BR_F-processed'!$C:$D,MATCH($L21,'2BR_F-processed'!$B:$B,0),MATCH(Council_Area,'2BR_F-processed'!$C$1:$D$1,0))) -> 330 | U21: =IF(MOD(Q21,4)=1,T21,U20) -> 330 | V21: =U21*(R21)/7 -> 4337.1429 | W21: =$B$53/4*BH21/_xlfn.XLOOKUP(Q_end,cpi!A:A,cpi!B:B) -> 133.24119 | X21: =V21+W21 -> 4470.384 | Y21: =BG21-X21 -> 2540.4898 | Z21: =Y21*$B$47 -> 0 | AA21: {=(Y21+Z21)*eff_invest} -> 2540.4898 | AB21: =AA21*(_xlfn.XLOOKUP(Q_end,cpi!A:A,cpi!B:B)/BH21) -> 3813.3701 | AC21: {=INDEX('msci-indices'!C:C,MATCH($L21,'msci-indices'!$B:$B)-2)} -> 696.18018 | AD21: {=INDEX('msci-indices'!D:D,MATCH($L21,'msci-indices'!$B:$B)-2)} -> 786.77037 | AE21: =AI20+AA21 -> 136166.57 | AF21: {=INDEX('msci-indices'!C:C,MATCH($L21,'msci-indices'!$B:$B)+1)} -> 792.86986 | AG21: {=INDEX('msci-indices'!D:D,MATCH($L21,'msci-indices'!$B:$B)+1)} -> 855.9299 | AH21: =(InvestFees/4)*AE21 -> 85.104107 | AI21: =((AF21/AC21)*GlobalPortfolio+(AG21/AD21)*AusPortfolio)*AE21-AH21 -> 152910.45 | AJ21: =AJ20+AA21 -> 146271 | AK21: =AI21-AJ21 -> 6639.4463 | AL21: =AJ21*(_xlfn.XLOOKUP(Q_end,cpi!A:A,cpi!B:B)/BH21) -> 219558.23 | AM21: {=SUMPRODUCT($AA$3:AA21,_xlfn.SORTBY($BH$3:BH21,_xlfn.SEQUENCE(ROWS($BH$3:BH21)),-1)/$BH$3)} -> 163118.97 | AN21: =AI21-AM21 -> -10208.527 | AO21: =IF($B$49="Real gains",MAX($B$50*AN21,0),IF($B$49="Discounted nominal gains",MAX($B$50*AK21/2,0),0)) -> 0 | AP21: =AI21-AO21 -> 152910.45 | AR21: =IF($B$10="3BR_H", INDEX('ns-combined'!$C:$D,MATCH($L21,'ns-combined'!$B:$B,0),MATCH(Council_Area,'ns-combined'!$C$1:$D$1,0))*1000, INDEX('s-combined'!$C:$D,MATCH($L21,'s-combined'!$B:$B,0),MATCH(Council_Area,'s-combined'!$C$1:$D$1,0))*1000) -> 488300 | AS21: =AS20+$AS$3 -> 15675 | AT21: 0 | AU21: =SUM($B$28:$B$29)*AR21 -> 9766 | AV21: =AR21*$B$15/4 -> 1403.8625 | AW21: =SUM($AV$3:AV21) -> 21717.175 | AX21: =AR21-AS21-AU21-AW21 -> 441141.83 | AY21: =$B$36*V21 -> 1518 | AZ21: =SUM(AY21:AY21)*4/AR21 -> 0.012434978 | BA21: =SUM(AY21:AY21)/V21 -> 0.35 | BB21: =IF(MortgageRate="Discounted",_xlfn.XLOOKUP(L21,'mortgage-rates'!$A:$A,'mortgage-rates'!$E:$E)/100,_xlfn.XLOOKUP(L21,'mortgage-rates'!$A:$A,'mortgage-rates'!$D:$D)/100) -> 0.0675 | BC21: =BC20-BF20 -> 242973.02 | BD21: =IF($B$16*12/3-Q21+1>0,-PMT($BB21/4,$B$16*12/3-Q21+1,BC21),0) -> 5492.8739 | BE21: =BC21*($BB21/4) -> 4100.1697 | BF21: =BD21-BE21 -> 1392.7041 | BG21: =AT21+AY21+BD21 -> 7010.8739 | BH21: =INDEX(cpi!B:B,MATCH($L21,cpi!A:A)) -> 96.4 | BI21: =100*BH21/BH$3 -> 113.94799 | BJ21: =100*AC21/AC$3 -> 92.224001 | BK21: =100*AD21/AD$3 -> 110.35325 | BL21: =BJ21*GlobalPortfolio+BK21*AusPortfolio -> 97.662775 | BM21: =100*AE21/$AE$3 -> 151.63364 | BN21: =100*AR21/AR$3 -> 147.9697 | BO21: =100*AX21/AX$3 -> 137.15977
L22: =DATE(YEAR(L21),MONTH(L21)+3,1) -> 40513 | M22: =AP22 -> 168163.19 | N22: =AX22-BC22 -> 228307.51 | O22: =M22/N22 -> 0.73656445 | P22: =X22/BG22 -> 0.62223797 | Q22: 20 | R22: =EOMONTH(L22,0)-EOMONTH(L22,-3) -> 92 | T22: =IF($B$10="3BR_H", INDEX('3BR_H-processed'!$C:$D,MATCH($L22,'3BR_H-processed'!$B:$B,0),MATCH(Council_Area,'3BR_H-processed'!$C$1:$D$1,0)), INDEX('2BR_F-processed'!$C:$D,MATCH($L22,'2BR_F-processed'!$B:$B,0),MATCH(Council_Area,'2BR_F-processed'!$C$1:$D$1,0))) -> 330 | U22: =IF(MOD(Q22,4)=1,T22,U21) -> 330 | V22: =U22*(R22)/7 -> 4337.1429 | W22: =$B$53/4*BH22/_xlfn.XLOOKUP(Q_end,cpi!A:A,cpi!B:B) -> 134.07049 | X22: =V22+W22 -> 4471.2133 | Y22: =BG22-X22 -> 2714.4834 | Z22: =Y22*$B$47 -> 0 | AA22: {=(Y22+Z22)*eff_invest} -> 2714.4834 | AB22: =AA22*(_xlfn.XLOOKUP(Q_end,cpi!A:A,cpi!B:B)/BH22) -> 4049.3376 | AC22: {=INDEX('msci-indices'!C:C,MATCH($L22,'msci-indices'!$B:$B)-2)} -> 792.86986 | AD22: {=INDEX('msci-indices'!D:D,MATCH($L22,'msci-indices'!$B:$B)-2)} -> 855.9299 | AE22: =AI21+AA22 -> 155624.93 | AF22: {=INDEX('msci-indices'!C:C,MATCH($L22,'msci-indices'!$B:$B)+1)} -> 869.42368 | AG22: {=INDEX('msci-indices'!D:D,MATCH($L22,'msci-indices'!$B:$B)+1)} -> 894.74694 | AH22: =(InvestFees/4)*AE22 -> 97.265581 | AI22: =((AF22/AC22)*GlobalPortfolio+(AG22/AD22)*AusPortfolio)*AE22-AH22 -> 168163.19 | AJ22: =AJ21+AA22 -> 148985.48 | AK22: =AI22-AJ22 -> 19177.709 | AL22: =AJ22*(_xlfn.XLOOKUP(Q_end,cpi!A:A,cpi!B:B)/BH22) -> 222249.48 | AM22: {=SUMPRODUCT($AA$3:AA22,_xlfn.SORTBY($BH$3:BH22,_xlfn.SEQUENCE(ROWS($BH$3:BH22)),-1)/$BH$3)} -> 166899.93 | AN22: =AI22-AM22 -> 1263.2665 | AO22: =IF($B$49="Real gains",MAX($B$50*AN22,0),IF($B$49="Discounted nominal gains",MAX($B$50*AK22/2,0),0)) -> 0 | AP22: =AI22-AO22 -> 168163.19 | AR22: =IF($B$10="3BR_H", INDEX('ns-combined'!$C:$D,MATCH($L22,'ns-combined'!$B:$B,0),MATCH(Council_Area,'ns-combined'!$C$1:$D$1,0))*1000, INDEX('s-combined'!$C:$D,MATCH($L22,'s-combined'!$B:$B,0),MATCH(Council_Area,'s-combined'!$C$1:$D$1,0))*1000) -> 520000 | AS22: =AS21+$AS$3 -> 16500 | AT22: 0 | AU22: =SUM($B$28:$B$29)*AR22 -> 10400 | AV22: =AR22*$B$15/4 -> 1495 | AW22: =SUM($AV$3:AV22) -> 23212.175 | AX22: =AR22-AS22-AU22-AW22 -> 469887.83 | AY22: =$B$36*V22 -> 1518 | AZ22: =SUM(AY22:AY22)*4/AR22 -> 0.011676923 | BA22: =SUM(AY22:AY22)/V22 -> 0.35 | BB22: =IF(MortgageRate="Discounted",_xlfn.XLOOKUP(L22,'mortgage-rates'!$A:$A,'mortgage-rates'!$E:$E)/100,_xlfn.XLOOKUP(L22,'mortgage-rates'!$A:$A,'mortgage-rates'!$D:$D)/100) -> 0.0715 | BC22: =BC21-BF21 -> 241580.32 | BD22: =IF($B$16*12/3-Q22+1>0,-PMT($BB22/4,$B$16*12/3-Q22+1,BC22),0) -> 5667.6967 | BE22: =BC22*($BB22/4) -> 4318.2482 | BF22: =BD22-BE22 -> 1349.4486 | BG22: =AT22+AY22+BD22 -> 7185.6967 | BH22: =INDEX(cpi!B:B,MATCH($L22,cpi!A:A)) -> 97 | BI22: =100*BH22/BH$3 -> 114.65721 | BJ22: =100*AC22/AC$3 -> 105.03262 | BK22: =100*AD22/AD$3 -> 120.05364 | BL22: =BJ22*GlobalPortfolio+BK22*AusPortfolio -> 109.53893 | BM22: =100*AE22/$AE$3 -> 173.30226 | BN22: =100*AR22/AR$3 -> 157.57576 | BO22: =100*AX22/AX$3 -> 146.09747
A23: Home transaction costs (% of home value) | L23: =DATE(YEAR(L22),MONTH(L22)+3,1) -> 40603 | M23: =AP23 -> 178409.87 | N23: =AX23-BC23 -> 193137.58 | O23: =M23/N23 -> 0.92374497 | P23: =X23/BG23 -> 0.6277544 | Q23: 21 | R23: =EOMONTH(L23,0)-EOMONTH(L23,-3) -> 90 | T23: =IF($B$10="3BR_H", INDEX('3BR_H-processed'!$C:$D,MATCH($L23,'3BR_H-processed'!$B:$B,0),MATCH(Council_Area,'3BR_H-processed'!$C$1:$D$1,0)), INDEX('2BR_F-processed'!$C:$D,MATCH($L23,'2BR_F-processed'!$B:$B,0),MATCH(Council_Area,'2BR_F-processed'!$C$1:$D$1,0))) -> 340 | U23: =IF(MOD(Q23,4)=1,T23,U22) -> 340 | V23: =U23*(R23)/7 -> 4371.4286 | W23: =$B$53/4*BH23/_xlfn.XLOOKUP(Q_end,cpi!A:A,cpi!B:B) -> 136.00553 | X23: =V23+W23 -> 4507.4341 | Y23: =BG23-X23 -> 2672.8168 | Z23: =Y23*$B$47 -> 0 | AA23: {=(Y23+Z23)*eff_invest} -> 2672.8168 | AB23: =AA23*(_xlfn.XLOOKUP(Q_end,cpi!A:A,cpi!B:B)/BH23) -> 3930.4532 | AC23: {=INDEX('msci-indices'!C:C,MATCH($L23,'msci-indices'!$B:$B)-2)} -> 869.42368 | AD23: {=INDEX('msci-indices'!D:D,MATCH($L23,'msci-indices'!$B:$B)-2)} -> 894.74694 | AE23: =AI22+AA23 -> 170836.01 | AF23: {=INDEX('msci-indices'!C:C,MATCH($L23,'msci-indices'!$B:$B)+1)} -> 912.83804 | AG23: {=INDEX('msci-indices'!D:D,MATCH($L23,'msci-indices'!$B:$B)+1)} -> 924.58629 | AH23: =(InvestFees/4)*AE23 -> 106.77251 | AI23: =((AF23/AC23)*GlobalPortfolio+(AG23/AD23)*AusPortfolio)*AE23-AH23 -> 178409.87 | AJ23: =AJ22+AA23 -> 151658.3 | AK23: =AI23-AJ23 -> 26751.569 | AL23: =AJ23*(_xlfn.XLOOKUP(Q_end,cpi!A:A,cpi!B:B)/BH23) -> 223017.85 | AM23: {=SUMPRODUCT($AA$3:AA23,_xlfn.SORTBY($BH$3:BH23,_xlfn.SEQUENCE(ROWS($BH$3:BH23)),-1)/$BH$3)} -> 171494.74 | AN23: =AI23-AM23 -> 6915.13 | AO23: =IF($B$49="Real gains",MAX($B$50*AN23,0),IF($B$49="Discounted nominal gains",MAX($B$50*AK23/2,0),0)) -> 0 | AP23: =AI23-AO23 -> 178409.87 | AR23: =IF($B$10="3BR_H", INDEX('ns-combined'!$C:$D,MATCH($L23,'ns-combined'!$B:$B,0),MATCH(Council_Area,'ns-combined'!$C$1:$D$1,0))*1000, INDEX('s-combined'!$C:$D,MATCH($L23,'s-combined'!$B:$B,0),MATCH(Council_Area,'s-combined'!$C$1:$D$1,0))*1000) -> 485000 | AS23: =AS22+$AS$3 -> 17325 | AT23: 0 | AU23: =SUM($B$28:$B$29)*AR23 -> 9700 | AV23: =AR23*$B$15/4 -> 1394.375 | AW23: =SUM($AV$3:AV23) -> 24606.55 | AX23: =AR23-AS23-AU23-AW23 -> 433368.45 | AY23: =$B$36*V23 -> 1530 | AZ23: =SUM(AY23:AY23)*4/AR23 -> 0.012618557 | BA23: =SUM(AY23:AY23)/V23 -> 0.35 | BB23: =IF(MortgageRate="Discounted",_xlfn.XLOOKUP(L23,'mortgage-rates'!$A:$A,'mortgage-rates'!$E:$E)/100,_xlfn.XLOOKUP(L23,'mortgage-rates'!$A:$A,'mortgage-rates'!$D:$D)/100) -> 0.0711 | BC23: =BC22-BF22 -> 240230.87 | BD23: =IF($B$16*12/3-Q23+1>0,-PMT($BB23/4,$B$16*12/3-Q23+1,BC23),0) -> 5650.2509 | BE23: =BC23*($BB23/4) -> 4270.1037 | BF23: =BD23-BE23 -> 1380.1472 | BG23: =AT23+AY23+BD23 -> 7180.2509 | BH23: =INDEX(cpi!B:B,MATCH($L23,cpi!A:A)) -> 98.4 | BI23: =100*BH23/BH$3 -> 116.31206 | BJ23: =100*AC23/AC$3 -> 115.17382 | BK23: =100*AD23/AD$3 -> 125.49816 | BL23: =BJ23*GlobalPortfolio+BK23*AusPortfolio -> 118.27112 | BM23: =100*AE23/$AE$3 -> 190.24115 | BN23: =100*AR23/AR$3 -> 146.9697 | BO23: =100*AX23/AX$3 -> 134.74287
A24: When buying the house (cashflow costs) | L24: =DATE(YEAR(L23),MONTH(L23)+3,1) -> 40695 | M24: =AP24 -> 178942.06 | N24: =AX24-BC24 -> 209398.04 | O24: =M24/N24 -> 0.85455463 | P24: =X24/BG24 -> 0.63586083 | Q24: 22 | R24: =EOMONTH(L24,0)-EOMONTH(L24,-3) -> 91 | T24: =IF($B$10="3BR_H", INDEX('3BR_H-processed'!$C:$D,MATCH($L24,'3BR_H-processed'!$B:$B,0),MATCH(Council_Area,'3BR_H-processed'!$C$1:$D$1,0)), INDEX('2BR_F-processed'!$C:$D,MATCH($L24,'2BR_F-processed'!$B:$B,0),MATCH(Council_Area,'2BR_F-processed'!$C$1:$D$1,0))) -> 340 | U24: =IF(MOD(Q24,4)=1,T24,U23) -> 340 | V24: =U24*(R24)/7 -> 4420 | W24: =$B$53/4*BH24/_xlfn.XLOOKUP(Q_end,cpi!A:A,cpi!B:B) -> 137.24948 | X24: =V24+W24 -> 4557.2495 | Y24: =BG24-X24 -> 2609.8054 | Z24: =Y24*$B$47 -> 0 | AA24: {=(Y24+Z24)*eff_invest} -> 2609.8054 | AB24: =AA24*(_xlfn.XLOOKUP(Q_end,cpi!A:A,cpi!B:B)/BH24) -> 3803.0095 | AC24: {=INDEX('msci-indices'!C:C,MATCH($L24,'msci-indices'!$B:$B)-2)} -> 912.83804 | AD24: {=INDEX('msci-indices'!D:D,MATCH($L24,'msci-indices'!$B:$B)-2)} -> 924.58629 | AE24: =AI23+AA24 -> 181019.67 | AF24: {=INDEX('msci-indices'!C:C,MATCH($L24,'msci-indices'!$B:$B)+1)} -> 915.80494 | AG24: {=INDEX('msci-indices'!D:D,MATCH($L24,'msci-indices'!$B:$B)+1)} -> 884.12823 | AH24: =(InvestFees/4)*AE24 -> 113.1373 | AI24: =((AF24/AC24)*GlobalPortfolio+(AG24/AD24)*AusPortfolio)*AE24-AH24 -> 178942.06 | AJ24: =AJ23+AA24 -> 154268.11 | AK24: =AI24-AJ24 -> 24673.959 | AL24: =AJ24*(_xlfn.XLOOKUP(Q_end,cpi!A:A,cpi!B:B)/BH24) -> 224799.55 | AM24: {=SUMPRODUCT($AA$3:AA24,_xlfn.SORTBY($BH$3:BH24,_xlfn.SEQUENCE(ROWS($BH$3:BH24)),-1)/$BH$3)} -> 175535.49 | AN24: =AI24-AM24 -> 3406.5722 | AO24: =IF($B$49="Real gains",MAX($B$50*AN24,0),IF($B$49="Discounted nominal gains",MAX($B$50*AK24/2,0),0)) -> 0 | AP24: =AI24-AO24 -> 178942.06 | AR24: =IF($B$10="3BR_H", INDEX('ns-combined'!$C:$D,MATCH($L24,'ns-combined'!$B:$B,0),MATCH(Council_Area,'ns-combined'!$C$1:$D$1,0))*1000, INDEX('s-combined'!$C:$D,MATCH($L24,'s-combined'!$B:$B,0),MATCH(Council_Area,'s-combined'!$C$1:$D$1,0))*1000) -> 502500 | AS24: =AS23+$AS$3 -> 18150 | AT24: 0 | AU24: =SUM($B$28:$B$29)*AR24 -> 10050 | AV24: =AR24*$B$15/4 -> 1444.6875 | AW24: =SUM($AV$3:AV24) -> 26051.237 | AX24: =AR24-AS24-AU24-AW24 -> 448248.76 | AY24: =$B$36*V24 -> 1547 | AZ24: =SUM(AY24:AY24)*4/AR24 -> 0.012314428 | BA24: =SUM(AY24:AY24)/V24 -> 0.35 | BB24: =IF(MortgageRate="Discounted",_xlfn.XLOOKUP(L24,'mortgage-rates'!$A:$A,'mortgage-rates'!$E:$E)/100,_xlfn.XLOOKUP(L24,'mortgage-rates'!$A:$A,'mortgage-rates'!$D:$D)/100) -> 0.0704 | BC24: =BC23-BF23 -> 238850.72 | BD24: =IF($B$16*12/3-Q24+1>0,-PMT($BB24/4,$B$16*12/3-Q24+1,BC24),0) -> 5620.0549 | BE24: =BC24*($BB24/4) -> 4203.7727 | BF24: =BD24-BE24 -> 1416.2822 | BG24: =AT24+AY24+BD24 -> 7167.0549 | BH24: =INDEX(cpi!B:B,MATCH($L24,cpi!A:A)) -> 99.3 | BI24: =100*BH24/BH$3 -> 117.37589 | BJ24: =100*AC24/AC$3 -> 120.92498 | BK24: =100*AD24/AD$3 -> 129.68345 | BL24: =BJ24*GlobalPortfolio+BK24*AusPortfolio -> 123.55252 | BM24: =100*AE24/$AE$3 -> 201.58158 | BN24: =100*AR24/AR$3 -> 152.27273 | BO24: =100*AX24/AX$3 -> 139.36946
A25: Real estate agent commissions (purchase) | B25: 0.015 | C25: 0.015 | L25: =DATE(YEAR(L24),MONTH(L24)+3,1) -> 40787 | M25: =AP25 -> 152968.34 | N25: =AX25-BC25 -> 193399.2 | O25: =M25/N25 -> 0.79094607 | P25: =X25/BG25 -> 0.64157528 | Q25: 23 | R25: =EOMONTH(L25,0)-EOMONTH(L25,-3) -> 92 | T25: =IF($B$10="3BR_H", INDEX('3BR_H-processed'!$C:$D,MATCH($L25,'3BR_H-processed'!$B:$B,0),MATCH(Council_Area,'3BR_H-processed'!$C$1:$D$1,0)), INDEX('2BR_F-processed'!$C:$D,MATCH($L25,'2BR_F-processed'!$B:$B,0),MATCH(Council_Area,'2BR_F-processed'!$C$1:$D$1,0))) -> 339 | U25: =IF(MOD(Q25,4)=1,T25,U24) -> 340 | V25: =U25*(R25)/7 -> 4468.5714 | W25: =$B$53/4*BH25/_xlfn.XLOOKUP(Q_end,cpi!A:A,cpi!B:B) -> 137.80235 | X25: =V25+W25 -> 4606.3738 | Y25: =BG25-X25 -> 2573.4131 | Z25: =Y25*$B$47 -> 0 | AA25: {=(Y25+Z25)*eff_invest} -> 2573.4131 | AB25: =AA25*(_xlfn.XLOOKUP(Q_end,cpi!A:A,cpi!B:B)/BH25) -> 3734.9335 | AC25: {=INDEX('msci-indices'!C:C,MATCH($L25,'msci-indices'!$B:$B)-2)} -> 915.80494 | AD25: {=INDEX('msci-indices'!D:D,MATCH($L25,'msci-indices'!$B:$B)-2)} -> 884.12823 | AE25: =AI24+AA25 -> 181515.48 | AF25: {=INDEX('msci-indices'!C:C,MATCH($L25,'msci-indices'!$B:$B)+1)} -> 758.74852 | AG25: {=INDEX('msci-indices'!D:D,MATCH($L25,'msci-indices'!$B:$B)+1)} -> 776.26676 | AH25: =(InvestFees/4)*AE25 -> 113.44717 | AI25: =((AF25/AC25)*GlobalPortfolio+(AG25/AD25)*AusPortfolio)*AE25-AH25 -> 152968.34 | AJ25: =AJ24+AA25 -> 156841.52 | AK25: =AI25-AJ25 -> -3873.1826 | AL25: =AJ25*(_xlfn.XLOOKUP(Q_end,cpi!A:A,cpi!B:B)/BH25) -> 227632.58 | AM25: {=SUMPRODUCT($AA$3:AA25,_xlfn.SORTBY($BH$3:BH25,_xlfn.SEQUENCE(ROWS($BH$3:BH25)),-1)/$BH$3)} -> 179049.09 | AN25: =AI25-AM25 -> -26080.751 | AO25: =IF($B$49="Real gains",MAX($B$50*AN25,0),IF($B$49="Discounted nominal gains",MAX($B$50*AK25/2,0),0)) -> 0 | AP25: =AI25-AO25 -> 152968.34 | AR25: =IF($B$10="3BR_H", INDEX('ns-combined'!$C:$D,MATCH($L25,'ns-combined'!$B:$B,0),MATCH(Council_Area,'ns-combined'!$C$1:$D$1,0))*1000, INDEX('s-combined'!$C:$D,MATCH($L25,'s-combined'!$B:$B,0),MATCH(Council_Area,'s-combined'!$C$1:$D$1,0))*1000) -> 487000 | AS25: =AS24+$AS$3 -> 18975 | AT25: 0 | AU25: =SUM($B$28:$B$29)*AR25 -> 9740 | AV25: =AR25*$B$15/4 -> 1400.125 | AW25: =SUM($AV$3:AV25) -> 27451.362 | AX25: =AR25-AS25-AU25-AW25 -> 430833.64 | AY25: =$B$36*V25 -> 1564 | AZ25: =SUM(AY25:AY25)*4/AR25 -> 0.012845996 | BA25: =SUM(AY25:AY25)/V25 -> 0.35 | BB25: =IF(MortgageRate="Discounted",_xlfn.XLOOKUP(L25,'mortgage-rates'!$A:$A,'mortgage-rates'!$E:$E)/100,_xlfn.XLOOKUP(L25,'mortgage-rates'!$A:$A,'mortgage-rates'!$D:$D)/100) -> 0.0703 | BC25: =BC24-BF24 -> 237434.44 | BD25: =IF($B$16*12/3-Q25+1>0,-PMT($BB25/4,$B$16*12/3-Q25+1,BC25),0) -> 5615.7869 | BE25: =BC25*($BB25/4) -> 4172.9103 | BF25: =BD25-BE25 -> 1442.8766 | BG25: =AT25+AY25+BD25 -> 7179.7869 | BH25: =INDEX(cpi!B:B,MATCH($L25,cpi!A:A)) -> 99.7 | BI25: =100*BH25/BH$3 -> 117.8487 | BJ25: =100*AC25/AC$3 -> 121.31801 | BK25: =100*AD25/AD$3 -> 124.00876 | BL25: =BJ25*GlobalPortfolio+BK25*AusPortfolio -> 122.12524 | BM25: =100*AE25/$AE$3 -> 202.1337 | BN25: =100*AR25/AR$3 -> 147.57576 | BO25: =100*AX25/AX$3 -> 133.95475
A26: Stamp duty (purchase) | B26: =(2560+(0.06*(AR3-115000)))/AR3 -> 0.046848485 | C26: 0.03 | L26: =DATE(YEAR(L25),MONTH(L25)+3,1) -> 40878 | M26: =AP26 -> 164437.77 | N26: =AX26-BC26 -> 200433.95 | O26: =M26/N26 -> 0.82040875 | P26: =X26/BG26 -> 0.66049822 | Q26: 24 | R26: =EOMONTH(L26,0)-EOMONTH(L26,-3) -> 92 | T26: =IF($B$10="3BR_H", INDEX('3BR_H-processed'!$C:$D,MATCH($L26,'3BR_H-processed'!$B:$B,0),MATCH(Council_Area,'3BR_H-processed'!$C$1:$D$1,0)), INDEX('2BR_F-processed'!$C:$D,MATCH($L26,'2BR_F-processed'!$B:$B,0),MATCH(Council_Area,'2BR_F-processed'!$C$1:$D$1,0))) -> 340 | U26: =IF(MOD(Q26,4)=1,T26,U25) -> 340 | V26: =U26*(R26)/7 -> 4468.5714 | W26: =$B$53/4*BH26/_xlfn.XLOOKUP(Q_end,cpi!A:A,cpi!B:B) -> 138.07878 | X26: =V26+W26 -> 4606.6502 | Y26: =BG26-X26 -> 2367.8579 | Z26: =Y26*$B$47 -> 0 | AA26: {=(Y26+Z26)*eff_invest} -> 2367.8579 | AB26: =AA26*(_xlfn.XLOOKUP(Q_end,cpi!A:A,cpi!B:B)/BH26) -> 3429.7201 | AC26: {=INDEX('msci-indices'!C:C,MATCH($L26,'msci-indices'!$B:$B)-2)} -> 758.74852 | AD26: {=INDEX('msci-indices'!D:D,MATCH($L26,'msci-indices'!$B:$B)-2)} -> 776.26676 | AE26: =AI25+AA26 -> 155336.19 | AF26: {=INDEX('msci-indices'!C:C,MATCH($L26,'msci-indices'!$B:$B)+1)} -> 816.9754 | AG26: {=INDEX('msci-indices'!D:D,MATCH($L26,'msci-indices'!$B:$B)+1)} -> 790.49635 | AH26: =(InvestFees/4)*AE26 -> 97.085121 | AI26: =((AF26/AC26)*GlobalPortfolio+(AG26/AD26)*AusPortfolio)*AE26-AH26 -> 164437.77 | AJ26: =AJ25+AA26 -> 159209.38 | AK26: =AI26-AJ26 -> 5228.3886 | AL26: =AJ26*(_xlfn.XLOOKUP(Q_end,cpi!A:A,cpi!B:B)/BH26) -> 230606.57 | AM26: {=SUMPRODUCT($AA$3:AA26,_xlfn.SORTBY($BH$3:BH26,_xlfn.SEQUENCE(ROWS($BH$3:BH26)),-1)/$BH$3)} -> 182171.78 | AN26: =AI26-AM26 -> -17734.013 | AO26: =IF($B$49="Real gains",MAX($B$50*AN26,0),IF($B$49="Discounted nominal gains",MAX($B$50*AK26/2,0),0)) -> 0 | AP26: =AI26-AO26 -> 164437.77 | AR26: =IF($B$10="3BR_H", INDEX('ns-combined'!$C:$D,MATCH($L26,'ns-combined'!$B:$B,0),MATCH(Council_Area,'ns-combined'!$C$1:$D$1,0))*1000, INDEX('s-combined'!$C:$D,MATCH($L26,'s-combined'!$B:$B,0),MATCH(Council_Area,'s-combined'!$C$1:$D$1,0))*1000) -> 495000 | AS26: =AS25+$AS$3 -> 19800 | AT26: 0 | AU26: =SUM($B$28:$B$29)*AR26 -> 9900 | AV26: =AR26*$B$15/4 -> 1423.125 | AW26: =SUM($AV$3:AV26) -> 28874.487 | AX26: =AR26-AS26-AU26-AW26 -> 436425.51 | AY26: =$B$36*V26 -> 1564 | AZ26: =SUM(AY26:AY26)*4/AR26 -> 0.012638384 | BA26: =SUM(AY26:AY26)/V26 -> 0.35 | BB26: =IF(MortgageRate="Discounted",_xlfn.XLOOKUP(L26,'mortgage-rates'!$A:$A,'mortgage-rates'!$E:$E)/100,_xlfn.XLOOKUP(L26,'mortgage-rates'!$A:$A,'mortgage-rates'!$D:$D)/100) -> 0.0654 | BC26: =BC25-BF25 -> 235991.56 | BD26: =IF($B$16*12/3-Q26+1>0,-PMT($BB26/4,$B$16*12/3-Q26+1,BC26),0) -> 5410.5081 | BE26: =BC26*($BB26/4) -> 3858.4621 | BF26: =BD26-BE26 -> 1552.0461 | BG26: =AT26+AY26+BD26 -> 6974.5081 | BH26: =INDEX(cpi!B:B,MATCH($L26,cpi!A:A)) -> 99.9 | BI26: =100*BH26/BH$3 -> 118.08511 | BJ26: =100*AC26/AC$3 -> 100.51252 | BK26: =100*AD26/AD$3 -> 108.88 | BL26: =BJ26*GlobalPortfolio+BK26*AusPortfolio -> 103.02276 | BM26: =100*AE26/$AE$3 -> 172.98073 | BN26: =100*AR26/AR$3 -> 150 | BO26: =100*AX26/AX$3 -> 135.69337
A27: When selling the house (derating of home value) | L27: =DATE(YEAR(L26),MONTH(L26)+3,1) -> 40969 | M27: =AP27 -> 184928.92 | N27: =AX27-BC27 -> 183126.75 | O27: =M27/N27 -> 1.0098411 | P27: =X27/BG27 -> 0.64859573 | Q27: 25 | R27: =EOMONTH(L27,0)-EOMONTH(L27,-3) -> 91 | T27: =IF($B$10="3BR_H", INDEX('3BR_H-processed'!$C:$D,MATCH($L27,'3BR_H-processed'!$B:$B,0),MATCH(Council_Area,'3BR_H-processed'!$C$1:$D$1,0)), INDEX('2BR_F-processed'!$C:$D,MATCH($L27,'2BR_F-processed'!$B:$B,0),MATCH(Council_Area,'2BR_F-processed'!$C$1:$D$1,0))) -> 340 | U27: =IF(MOD(Q27,4)=1,T27,U26) -> 340 | V27: =U27*(R27)/7 -> 4420 | W27: =$B$53/4*BH27/_xlfn.XLOOKUP(Q_end,cpi!A:A,cpi!B:B) -> 138.07878 | X27: =V27+W27 -> 4558.0788 | Y27: =BG27-X27 -> 2469.5327 | Z27: =Y27*$B$47 -> 0 | AA27: {=(Y27+Z27)*eff_invest} -> 2469.5327 | AB27: =AA27*(_xlfn.XLOOKUP(Q_end,cpi!A:A,cpi!B:B)/BH27) -> 3576.9908 | AC27: {=INDEX('msci-indices'!C:C,MATCH($L27,'msci-indices'!$B:$B)-2)} -> 816.9754 | AD27: {=INDEX('msci-indices'!D:D,MATCH($L27,'msci-indices'!$B:$B)-2)} -> 790.49635 | AE27: =AI26+AA27 -> 166907.3 | AF27: {=INDEX('msci-indices'!C:C,MATCH($L27,'msci-indices'!$B:$B)+1)} -> 913.58723 | AG27: {=INDEX('msci-indices'!D:D,MATCH($L27,'msci-indices'!$B:$B)+1)} -> 858.5317 | AH27: =(InvestFees/4)*AE27 -> 104.31706 | AI27: =((AF27/AC27)*GlobalPortfolio+(AG27/AD27)*AusPortfolio)*AE27-AH27 -> 184928.92 | AJ27: =AJ26+AA27 -> 161678.91 | AK27: =AI27-AJ27 -> 23250.009 | AL27: =AJ27*(_xlfn.XLOOKUP(Q_end,cpi!A:A,cpi!B:B)/BH27) -> 234183.57 | AM27: {=SUMPRODUCT($AA$3:AA27,_xlfn.SORTBY($BH$3:BH27,_xlfn.SEQUENCE(ROWS($BH$3:BH27)),-1)/$BH$3)} -> 185193.76 | AN27: =AI27-AM27 -> -264.84295 | AO27: =IF($B$49="Real gains",MAX($B$50*AN27,0),IF($B$49="Discounted nominal gains",MAX($B$50*AK27/2,0),0)) -> 0 | AP27: =AI27-AO27 -> 184928.92 | AR27: =IF($B$10="3BR_H", INDEX('ns-combined'!$C:$D,MATCH($L27,'ns-combined'!$B:$B,0),MATCH(Council_Area,'ns-combined'!$C$1:$D$1,0))*1000, INDEX('s-combined'!$C:$D,MATCH($L27,'s-combined'!$B:$B,0),MATCH(Council_Area,'s-combined'!$C$1:$D$1,0))*1000) -> 478000 | AS27: =AS26+$AS$3 -> 20625 | AT27: 0 | AU27: =SUM($B$28:$B$29)*AR27 -> 9560 | AV27: =AR27*$B$15/4 -> 1374.25 | AW27: =SUM($AV$3:AV27) -> 30248.737 | AX27: =AR27-AS27-AU27-AW27 -> 417566.26 | AY27: =$B$36*V27 -> 1547 | AZ27: =SUM(AY27:AY27)*4/AR27 -> 0.012945607 | BA27: =SUM(AY27:AY27)/V27 -> 0.35 | BB27: =IF(MortgageRate="Discounted",_xlfn.XLOOKUP(L27,'mortgage-rates'!$A:$A,'mortgage-rates'!$E:$E)/100,_xlfn.XLOOKUP(L27,'mortgage-rates'!$A:$A,'mortgage-rates'!$D:$D)/100) -> 0.0671 | BC27: =BC26-BF26 -> 234439.52 | BD27: =IF($B$16*12/3-Q27+1>0,-PMT($BB27/4,$B$16*12/3-Q27+1,BC27),0) -> 5480.6115 | BE27: =BC27*($BB27/4) -> 3932.7229 | BF27: =BD27-BE27 -> 1547.8886 | BG27: =AT27+AY27+BD27 -> 7027.6115 | BH27: =INDEX(cpi!B:B,MATCH($L27,cpi!A:A)) -> 99.9 | BI27: =100*BH27/BH$3 -> 118.08511 | BJ27: =100*AC27/AC$3 -> 108.22592 | BK27: =100*AD27/AD$3 -> 110.87586 | BL27: =BJ27*GlobalPortfolio+BK27*AusPortfolio -> 109.0209 | BM27: =100*AE27/$AE$3 -> 185.86618 | BN27: =100*AR27/AR$3 -> 144.84848 | BO27: =100*AX27/AX$3 -> 129.82966
A28: Real estate agent commissions (sale) | B28: 0.015 | C28: 0.015 | L28: =DATE(YEAR(L27),MONTH(L27)+3,1) -> 41061 | M28: =AP28 -> 177221.91 | N28: =AX28-BC28 -> 189315.26 | O28: =M28/N28 -> 0.9361206 | P28: =X28/BG28 -> 0.67115728 | Q28: 26 | R28: =EOMONTH(L28,0)-EOMONTH(L28,-3) -> 91 | T28: =IF($B$10="3BR_H", INDEX('3BR_H-processed'!$C:$D,MATCH($L28,'3BR_H-processed'!$B:$B,0),MATCH(Council_Area,'3BR_H-processed'!$C$1:$D$1,0)), INDEX('2BR_F-processed'!$C:$D,MATCH($L28,'2BR_F-processed'!$B:$B,0),MATCH(Council_Area,'2BR_F-processed'!$C$1:$D$1,0))) -> 335 | U28: =IF(MOD(Q28,4)=1,T28,U27) -> 340 | V28: =U28*(R28)/7 -> 4420 | W28: =$B$53/4*BH28/_xlfn.XLOOKUP(Q_end,cpi!A:A,cpi!B:B) -> 138.90809 | X28: =V28+W28 -> 4558.9081 | Y28: =BG28-X28 -> 2233.6996 | Z28: =Y28*$B$47 -> 0 | AA28: {=(Y28+Z28)*eff_invest} -> 2233.6996 | AB28: =AA28*(_xlfn.XLOOKUP(Q_end,cpi!A:A,cpi!B:B)/BH28) -> 3216.0829 | AC28: {=INDEX('msci-indices'!C:C,MATCH($L28,'msci-indices'!$B:$B)-2)} -> 913.58723 | AD28: {=INDEX('msci-indices'!D:D,MATCH($L28,'msci-indices'!$B:$B)-2)} -> 858.5317 | AE28: =AI27+AA28 -> 187162.62 | AF28: {=INDEX('msci-indices'!C:C,MATCH($L28,'msci-indices'!$B:$B)+1)} -> 865.80589 | AG28: {=INDEX('msci-indices'!D:D,MATCH($L28,'msci-indices'!$B:$B)+1)} -> 813.09506 | AH28: =(InvestFees/4)*AE28 -> 116.97664 | AI28: =((AF28/AC28)*GlobalPortfolio+(AG28/AD28)*AusPortfolio)*AE28-AH28 -> 177221.91 | AJ28: =AJ27+AA28 -> 163912.61 | AK28: =AI28-AJ28 -> 13309.305 | AL28: =AJ28*(_xlfn.XLOOKUP(Q_end,cpi!A:A,cpi!B:B)/BH28) -> 236001.54 | AM28: {=SUMPRODUCT($AA$3:AA28,_xlfn.SORTBY($BH$3:BH28,_xlfn.SEQUENCE(ROWS($BH$3:BH28)),-1)/$BH$3)} -> 188611.19 | AN28: =AI28-AM28 -> -11389.272 | AO28: =IF($B$49="Real gains",MAX($B$50*AN28,0),IF($B$49="Discounted nominal gains",MAX($B$50*AK28/2,0),0)) -> 0 | AP28: =AI28-AO28 -> 177221.91 | AR28: =IF($B$10="3BR_H", INDEX('ns-combined'!$C:$D,MATCH($L28,'ns-combined'!$B:$B,0),MATCH(Council_Area,'ns-combined'!$C$1:$D$1,0))*1000, INDEX('s-combined'!$C:$D,MATCH($L28,'s-combined'!$B:$B,0),MATCH(Council_Area,'s-combined'!$C$1:$D$1,0))*1000) -> 485000 | AS28: =AS27+$AS$3 -> 21450 | AT28: 0 | AU28: =SUM($B$28:$B$29)*AR28 -> 9700 | AV28: =AR28*$B$15/4 -> 1394.375 | AW28: =SUM($AV$3:AV28) -> 31643.112 | AX28: =AR28-AS28-AU28-AW28 -> 422206.89 | AY28: =$B$36*V28 -> 1547 | AZ28: =SUM(AY28:AY28)*4/AR28 -> 0.012758763 | BA28: =SUM(AY28:AY28)/V28 -> 0.35 | BB28: =IF(MortgageRate="Discounted",_xlfn.XLOOKUP(L28,'mortgage-rates'!$A:$A,'mortgage-rates'!$E:$E)/100,_xlfn.XLOOKUP(L28,'mortgage-rates'!$A:$A,'mortgage-rates'!$D:$D)/100) -> 0.0613 | BC28: =BC27-BF27 -> 232891.63 | BD28: =IF($B$16*12/3-Q28+1>0,-PMT($BB28/4,$B$16*12/3-Q28+1,BC28),0) -> 5245.6077 | BE28: =BC28*($BB28/4) -> 3569.0642 | BF28: =BD28-BE28 -> 1676.5435 | BG28: =AT28+AY28+BD28 -> 6792.6077 | BH28: =INDEX(cpi!B:B,MATCH($L28,cpi!A:A)) -> 100.5 | BI28: =100*BH28/BH$3 -> 118.79433 | BJ28: =100*AC28/AC$3 -> 121.02423 | BK28: =100*AD28/AD$3 -> 120.41857 | BL28: =BJ28*GlobalPortfolio+BK28*AusPortfolio -> 120.84253 | BM28: =100*AE28/$AE$3 -> 208.42229 | BN28: =100*AR28/AR$3 -> 146.9697 | BO28: =100*AX28/AX$3 -> 131.27252
A29: Other selling costs | B29: 0.005 | C29: 0.005 | L29: =DATE(YEAR(L28),MONTH(L28)+3,1) -> 41153 | M29: =AP29 -> 192366.3 | N29: =AX29-BC29 -> 183886.8 | O29: =M29/N29 -> 1.0461126 | P29: =X29/BG29 -> 0.67881246 | Q29: 27 | R29: =EOMONTH(L29,0)-EOMONTH(L29,-3) -> 92 | T29: =IF($B$10="3BR_H", INDEX('3BR_H-processed'!$C:$D,MATCH($L29,'3BR_H-processed'!$B:$B,0),MATCH(Council_Area,'3BR_H-processed'!$C$1:$D$1,0)), INDEX('2BR_F-processed'!$C:$D,MATCH($L29,'2BR_F-processed'!$B:$B,0),MATCH(Council_Area,'2BR_F-processed'!$C$1:$D$1,0))) -> 340 | U29: =IF(MOD(Q29,4)=1,T29,U28) -> 340 | V29: =U29*(R29)/7 -> 4468.5714 | W29: =$B$53/4*BH29/_xlfn.XLOOKUP(Q_end,cpi!A:A,cpi!B:B) -> 140.42847 | X29: =V29+W29 -> 4608.9999 | Y29: =BG29-X29 -> 2180.7987 | Z29: =Y29*$B$47 -> 0 | AA29: {=(Y29+Z29)*eff_invest} -> 2180.7987 | AB29: =AA29*(_xlfn.XLOOKUP(Q_end,cpi!A:A,cpi!B:B)/BH29) -> 3105.9211 | AC29: {=INDEX('msci-indices'!C:C,MATCH($L29,'msci-indices'!$B:$B)-2)} -> 865.80589 | AD29: {=INDEX('msci-indices'!D:D,MATCH($L29,'msci-indices'!$B:$B)-2)} -> 813.09506 | AE29: =AI28+AA29 -> 179402.71 | AF29: {=INDEX('msci-indices'!C:C,MATCH($L29,'msci-indices'!$B:$B)+1)} -> 923.8995 | AG29: {=INDEX('msci-indices'!D:D,MATCH($L29,'msci-indices'!$B:$B)+1)} -> 883.33647 | AH29: =(InvestFees/4)*AE29 -> 112.1267 | AI29: =((AF29/AC29)*GlobalPortfolio+(AG29/AD29)*AusPortfolio)*AE29-AH29 -> 192366.3 | AJ29: =AJ28+AA29 -> 166093.41 | AK29: =AI29-AJ29 -> 26272.896 | AL29: =AJ29*(_xlfn.XLOOKUP(Q_end,cpi!A:A,cpi!B:B)/BH29) -> 236552.32 | AM29: {=SUMPRODUCT($AA$3:AA29,_xlfn.SORTBY($BH$3:BH29,_xlfn.SEQUENCE(ROWS($BH$3:BH29)),-1)/$BH$3)} -> 192517.48 | AN29: =AI29-AM29 -> -151.17728 | AO29: =IF($B$49="Real gains",MAX($B$50*AN29,0),IF($B$49="Discounted nominal gains",MAX($B$50*AK29/2,0),0)) -> 0 | AP29: =AI29-AO29 -> 192366.3 | AR29: =IF($B$10="3BR_H", INDEX('ns-combined'!$C:$D,MATCH($L29,'ns-combined'!$B:$B,0),MATCH(Council_Area,'ns-combined'!$C$1:$D$1,0))*1000, INDEX('s-combined'!$C:$D,MATCH($L29,'s-combined'!$B:$B,0),MATCH(Council_Area,'s-combined'!$C$1:$D$1,0))*1000) -> 480000 | AS29: =AS28+$AS$3 -> 22275 | AT29: 0 | AU29: =SUM($B$28:$B$29)*AR29 -> 9600 | AV29: =AR29*$B$15/4 -> 1380 | AW29: =SUM($AV$3:AV29) -> 33023.113 | AX29: =AR29-AS29-AU29-AW29 -> 415101.89 | AY29: =$B$36*V29 -> 1564 | AZ29: =SUM(AY29:AY29)*4/AR29 -> 0.013033333 | BA29: =SUM(AY29:AY29)/V29 -> 0.35 | BB29: =IF(MortgageRate="Discounted",_xlfn.XLOOKUP(L29,'mortgage-rates'!$A:$A,'mortgage-rates'!$E:$E)/100,_xlfn.XLOOKUP(L29,'mortgage-rates'!$A:$A,'mortgage-rates'!$D:$D)/100) -> 0.0608 | BC29: =BC28-BF28 -> 231215.09 | BD29: =IF($B$16*12/3-Q29+1>0,-PMT($BB29/4,$B$16*12/3-Q29+1,BC29),0) -> 5225.7987 | BE29: =BC29*($BB29/4) -> 3514.4693 | BF29: =BD29-BE29 -> 1711.3294 | BG29: =AT29+AY29+BD29 -> 6789.7987 | BH29: =INDEX(cpi!B:B,MATCH($L29,cpi!A:A)) -> 101.6 | BI29: =100*BH29/BH$3 -> 120.09456 | BJ29: =100*AC29/AC$3 -> 114.69457 | BK29: =100*AD29/AD$3 -> 114.04558 | BL29: =BJ29*GlobalPortfolio+BK29*AusPortfolio -> 114.49987 | BM29: =100*AE29/$AE$3 -> 199.78094 | BN29: =100*AR29/AR$3 -> 145.45455 | BO29: =100*AX29/AX$3 -> 129.06344
L30: =DATE(YEAR(L29),MONTH(L29)+3,1) -> 41244 | M30: =AP30 -> 201826.42 | N30: =AX30-BC30 -> 210752.63 | O30: =M30/N30 -> 0.95764603 | P30: =X30/BG30 -> 0.6948002 | Q30: 28 | R30: =EOMONTH(L30,0)-EOMONTH(L30,-3) -> 92 | T30: =IF($B$10="3BR_H", INDEX('3BR_H-processed'!$C:$D,MATCH($L30,'3BR_H-processed'!$B:$B,0),MATCH(Council_Area,'3BR_H-processed'!$C$1:$D$1,0)), INDEX('2BR_F-processed'!$C:$D,MATCH($L30,'2BR_F-processed'!$B:$B,0),MATCH(Council_Area,'2BR_F-processed'!$C$1:$D$1,0))) -> 340 | U30: =IF(MOD(Q30,4)=1,T30,U29) -> 340 | V30: =U30*(R30)/7 -> 4468.5714 | W30: =$B$53/4*BH30/_xlfn.XLOOKUP(Q_end,cpi!A:A,cpi!B:B) -> 140.98134 | X30: =V30+W30 -> 4609.5528 | Y30: =BG30-X30 -> 2024.8045 | Z30: =Y30*$B$47 -> 0 | AA30: {=(Y30+Z30)*eff_invest} -> 2024.8045 | AB30: =AA30*(_xlfn.XLOOKUP(Q_end,cpi!A:A,cpi!B:B)/BH30) -> 2872.4433 | AC30: {=INDEX('msci-indices'!C:C,MATCH($L30,'msci-indices'!$B:$B)-2)} -> 923.8995 | AD30: {=INDEX('msci-indices'!D:D,MATCH($L30,'msci-indices'!$B:$B)-2)} -> 883.33647 | AE30: =AI29+AA30 -> 194391.11 | AF30: {=INDEX('msci-indices'!C:C,MATCH($L30,'msci-indices'!$B:$B)+1)} -> 948.15111 | AG30: {=INDEX('msci-indices'!D:D,MATCH($L30,'msci-indices'!$B:$B)+1)} -> 943.69729 | AH30: =(InvestFees/4)*AE30 -> 121.49444 | AI30: =((AF30/AC30)*GlobalPortfolio+(AG30/AD30)*AusPortfolio)*AE30-AH30 -> 201826.42 | AJ30: =AJ29+AA30 -> 168118.21 | AK30: =AI30-AJ30 -> 33708.21 | AL30: =AJ30*(_xlfn.XLOOKUP(Q_end,cpi!A:A,cpi!B:B)/BH30) -> 238497.11 | AM30: {=SUMPRODUCT($AA$3:AA30,_xlfn.SORTBY($BH$3:BH30,_xlfn.SEQUENCE(ROWS($BH$3:BH30)),-1)/$BH$3)} -> 195557.71 | AN30: =AI30-AM30 -> 6268.7119 | AO30: =IF($B$49="Real gains",MAX($B$50*AN30,0),IF($B$49="Discounted nominal gains",MAX($B$50*AK30/2,0),0)) -> 0 | AP30: =AI30-AO30 -> 201826.42 | AR30: =IF($B$10="3BR_H", INDEX('ns-combined'!$C:$D,MATCH($L30,'ns-combined'!$B:$B,0),MATCH(Council_Area,'ns-combined'!$C$1:$D$1,0))*1000, INDEX('s-combined'!$C:$D,MATCH($L30,'s-combined'!$B:$B,0),MATCH(Council_Area,'s-combined'!$C$1:$D$1,0))*1000) -> 508000 | AS30: =AS29+$AS$3 -> 23100 | AT30: 0 | AU30: =SUM($B$28:$B$29)*AR30 -> 10160 | AV30: =AR30*$B$15/4 -> 1460.5 | AW30: =SUM($AV$3:AV30) -> 34483.613 | AX30: =AR30-AS30-AU30-AW30 -> 440256.39 | AY30: =$B$36*V30 -> 1564 | AZ30: =SUM(AY30:AY30)*4/AR30 -> 0.012314961 | BA30: =SUM(AY30:AY30)/V30 -> 0.35 | BB30: =IF(MortgageRate="Discounted",_xlfn.XLOOKUP(L30,'mortgage-rates'!$A:$A,'mortgage-rates'!$E:$E)/100,_xlfn.XLOOKUP(L30,'mortgage-rates'!$A:$A,'mortgage-rates'!$D:$D)/100) -> 0.0568 | BC30: =BC29-BF29 -> 229503.76 | BD30: =IF($B$16*12/3-Q30+1>0,-PMT($BB30/4,$B$16*12/3-Q30+1,BC30),0) -> 5070.3573 | BE30: =BC30*($BB30/4) -> 3258.9533 | BF30: =BD30-BE30 -> 1811.4039 | BG30: =AT30+AY30+BD30 -> 6634.3573 | BH30: =INDEX(cpi!B:B,MATCH($L30,cpi!A:A)) -> 102 | BI30: =100*BH30/BH$3 -> 120.56738 | BJ30: =100*AC30/AC$3 -> 122.39031 | BK30: =100*AD30/AD$3 -> 123.89771 | BL30: =BJ30*GlobalPortfolio+BK30*AusPortfolio -> 122.84253 | BM30: =100*AE30/$AE$3 -> 216.47186 | BN30: =100*AR30/AR$3 -> 153.93939 | BO30: =100*AX30/AX$3 -> 136.88447
A31: Home ownership running costs (% of gross rents) | L31: =DATE(YEAR(L30),MONTH(L30)+3,1) -> 41334 | M31: =AP31 -> 220253.1 | N31: =AX31-BC31 -> 188781.79 | O31: =M31/N31 -> 1.1667074 | P31: =X31/BG31 -> 0.69940688 | Q31: 29 | R31: =EOMONTH(L31,0)-EOMONTH(L31,-3) -> 90 | T31: =IF($B$10="3BR_H", INDEX('3BR_H-processed'!$C:$D,MATCH($L31,'3BR_H-processed'!$B:$B,0),MATCH(Council_Area,'3BR_H-processed'!$C$1:$D$1,0)), INDEX('2BR_F-processed'!$C:$D,MATCH($L31,'2BR_F-processed'!$B:$B,0),MATCH(Council_Area,'2BR_F-processed'!$C$1:$D$1,0))) -> 349 | U31: =IF(MOD(Q31,4)=1,T31,U30) -> 349 | V31: =U31*(R31)/7 -> 4487.1429 | W31: =$B$53/4*BH31/_xlfn.XLOOKUP(Q_end,cpi!A:A,cpi!B:B) -> 141.53421 | X31: =V31+W31 -> 4628.6771 | Y31: =BG31-X31 -> 1989.3263 | Z31: =Y31*$B$47 -> 0 | AA31: {=(Y31+Z31)*eff_invest} -> 1989.3263 | AB31: =AA31*(_xlfn.XLOOKUP(Q_end,cpi!A:A,cpi!B:B)/BH31) -> 2811.089 | AC31: {=INDEX('msci-indices'!C:C,MATCH($L31,'msci-indices'!$B:$B)-2)} -> 948.15111 | AD31: {=INDEX('msci-indices'!D:D,MATCH($L31,'msci-indices'!$B:$B)-2)} -> 943.69729 | AE31: =AI30+AA31 -> 203815.75 | AF31: {=INDEX('msci-indices'!C:C,MATCH($L31,'msci-indices'!$B:$B)+1)} -> 1024.7053 | AG31: {=INDEX('msci-indices'!D:D,MATCH($L31,'msci-indices'!$B:$B)+1)} -> 1021.5673 | AH31: =(InvestFees/4)*AE31 -> 127.38484 | AI31: =((AF31/AC31)*GlobalPortfolio+(AG31/AD31)*AusPortfolio)*AE31-AH31 -> 220253.1 | AJ31: =AJ30+AA31 -> 170107.54 | AK31: =AI31-AJ31 -> 50145.561 | AL31: =AJ31*(_xlfn.XLOOKUP(Q_end,cpi!A:A,cpi!B:B)/BH31) -> 240376.57 | AM31: {=SUMPRODUCT($AA$3:AA31,_xlfn.SORTBY($BH$3:BH31,_xlfn.SEQUENCE(ROWS($BH$3:BH31)),-1)/$BH$3)} -> 198567.93 | AN31: =AI31-AM31 -> 21685.172 | AO31: =IF($B$49="Real gains",MAX($B$50*AN31,0),IF($B$49="Discounted nominal gains",MAX($B$50*AK31/2,0),0)) -> 0 | AP31: =AI31-AO31 -> 220253.1 | AR31: =IF($B$10="3BR_H", INDEX('ns-combined'!$C:$D,MATCH($L31,'ns-combined'!$B:$B,0),MATCH(Council_Area,'ns-combined'!$C$1:$D$1,0))*1000, INDEX('s-combined'!$C:$D,MATCH($L31,'s-combined'!$B:$B,0),MATCH(Council_Area,'s-combined'!$C$1:$D$1,0))*1000) -> 486000 | AS31: =AS30+$AS$3 -> 23925 | AT31: 0 | AU31: =SUM($B$28:$B$29)*AR31 -> 9720 | AV31: =AR31*$B$15/4 -> 1397.25 | AW31: =SUM($AV$3:AV31) -> 35880.863 | AX31: =AR31-AS31-AU31-AW31 -> 416474.14 | AY31: =$B$36*V31 -> 1570.5 | AZ31: =SUM(AY31:AY31)*4/AR31 -> 0.012925926 | BA31: =SUM(AY31:AY31)/V31 -> 0.35 | BB31: =IF(MortgageRate="Discounted",_xlfn.XLOOKUP(L31,'mortgage-rates'!$A:$A,'mortgage-rates'!$E:$E)/100,_xlfn.XLOOKUP(L31,'mortgage-rates'!$A:$A,'mortgage-rates'!$D:$D)/100) -> 0.0562 | BC31: =BC30-BF30 -> 227692.35 | BD31: =IF($B$16*12/3-Q31+1>0,-PMT($BB31/4,$B$16*12/3-Q31+1,BC31),0) -> 5047.5033 | BE31: =BC31*($BB31/4) -> 3199.0775 | BF31: =BD31-BE31 -> 1848.4258 | BG31: =AT31+AY31+BD31 -> 6618.0033 | BH31: =INDEX(cpi!B:B,MATCH($L31,cpi!A:A)) -> 102.4 | BI31: =100*BH31/BH$3 -> 121.04019 | BJ31: =100*AC31/AC$3 -> 125.60296 | BK31: =100*AD31/AD$3 -> 132.36398 | BL31: =BJ31*GlobalPortfolio+BK31*AusPortfolio -> 127.63126 | BM31: =100*AE31/$AE$3 -> 226.96704 | BN31: =100*AR31/AR$3 -> 147.27273 | BO31: =100*AX31/AX$3 -> 129.4901
A32: Council rates | B32: 0.07 | C32: 0.07 | L32: =DATE(YEAR(L31),MONTH(L31)+3,1) -> 41426 | M32: =AP32 -> 220688.65 | N32: =AX32-BC32 -> 202087.71 | O32: =M32/N32 -> 1.0920439 | P32: =X32/BG32 -> 0.71568167 | Q32: 30 | R32: =EOMONTH(L32,0)-EOMONTH(L32,-3) -> 91 | T32: =IF($B$10="3BR_H", INDEX('3BR_H-processed'!$C:$D,MATCH($L32,'3BR_H-processed'!$B:$B,0),MATCH(Council_Area,'3BR_H-processed'!$C$1:$D$1,0)), INDEX('2BR_F-processed'!$C:$D,MATCH($L32,'2BR_F-processed'!$B:$B,0),MATCH(Council_Area,'2BR_F-processed'!$C$1:$D$1,0))) -> 340 | U32: =IF(MOD(Q32,4)=1,T32,U31) -> 349 | V32: =U32*(R32)/7 -> 4537 | W32: =$B$53/4*BH32/_xlfn.XLOOKUP(Q_end,cpi!A:A,cpi!B:B) -> 142.22529 | X32: =V32+W32 -> 4679.2253 | Y32: =BG32-X32 -> 1858.9124 | Z32: =Y32*$B$47 -> 0 | AA32: {=(Y32+Z32)*eff_invest} -> 1858.9124 | AB32: =AA32*(_xlfn.XLOOKUP(Q_end,cpi!A:A,cpi!B:B)/BH32) -> 2614.0391 | AC32: {=INDEX('msci-indices'!C:C,MATCH($L32,'msci-indices'!$B:$B)-2)} -> 1024.7053 | AD32: {=INDEX('msci-indices'!D:D,MATCH($L32,'msci-indices'!$B:$B)-2)} -> 1021.5673 | AE32: =AI31+AA32 -> 222112.01 | AF32: {=INDEX('msci-indices'!C:C,MATCH($L32,'msci-indices'!$B:$B)+1)} -> 1030.5184 | AG32: {=INDEX('msci-indices'!D:D,MATCH($L32,'msci-indices'!$B:$B)+1)} -> 988.35138 | AH32: =(InvestFees/4)*AE32 -> 138.82001 | AI32: =((AF32/AC32)*GlobalPortfolio+(AG32/AD32)*AusPortfolio)*AE32-AH32 -> 220688.65 | AJ32: =AJ31+AA32 -> 171966.45 | AK32: =AI32-AJ32 -> 48722.196 | AL32: =AJ32*(_xlfn.XLOOKUP(Q_end,cpi!A:A,cpi!B:B)/BH32) -> 241822.6 | AM32: {=SUMPRODUCT($AA$3:AA32,_xlfn.SORTBY($BH$3:BH32,_xlfn.SEQUENCE(ROWS($BH$3:BH32)),-1)/$BH$3)} -> 201561.84 | AN32: =AI32-AM32 -> 19126.806 | AO32: =IF($B$49="Real gains",MAX($B$50*AN32,0),IF($B$49="Discounted nominal gains",MAX($B$50*AK32/2,0),0)) -> 0 | AP32: =AI32-AO32 -> 220688.65 | AR32: =IF($B$10="3BR_H", INDEX('ns-combined'!$C:$D,MATCH($L32,'ns-combined'!$B:$B,0),MATCH(Council_Area,'ns-combined'!$C$1:$D$1,0))*1000, INDEX('s-combined'!$C:$D,MATCH($L32,'s-combined'!$B:$B,0),MATCH(Council_Area,'s-combined'!$C$1:$D$1,0))*1000) -> 500000 | AS32: =AS31+$AS$3 -> 24750 | AT32: 0 | AU32: =SUM($B$28:$B$29)*AR32 -> 10000 | AV32: =AR32*$B$15/4 -> 1437.5 | AW32: =SUM($AV$3:AV32) -> 37318.363 | AX32: =AR32-AS32-AU32-AW32 -> 427931.64 | AY32: =$B$36*V32 -> 1587.95 | AZ32: =SUM(AY32:AY32)*4/AR32 -> 0.0127036 | BA32: =SUM(AY32:AY32)/V32 -> 0.35 | BB32: =IF(MortgageRate="Discounted",_xlfn.XLOOKUP(L32,'mortgage-rates'!$A:$A,'mortgage-rates'!$E:$E)/100,_xlfn.XLOOKUP(L32,'mortgage-rates'!$A:$A,'mortgage-rates'!$D:$D)/100) -> 0.0536 | BC32: =BC31-BF31 -> 225843.93 | BD32: =IF($B$16*12/3-Q32+1>0,-PMT($BB32/4,$B$16*12/3-Q32+1,BC32),0) -> 4950.1877 | BE32: =BC32*($BB32/4) -> 3026.3086 | BF32: =BD32-BE32 -> 1923.8791 | BG32: =AT32+AY32+BD32 -> 6538.1377 | BH32: =INDEX(cpi!B:B,MATCH($L32,cpi!A:A)) -> 102.9 | BI32: =100*BH32/BH$3 -> 121.63121 | BJ32: =100*AC32/AC$3 -> 135.7442 | BK32: =100*AD32/AD$3 -> 143.28611 | BL32: =BJ32*GlobalPortfolio+BK32*AusPortfolio -> 138.00677 | BM32: =100*AE32/$AE$3 -> 247.34156 | BN32: =100*AR32/AR$3 -> 151.51515 | BO32: =100*AX32/AX$3 -> 133.05246
A33: Maintenance incl. body corporate fees | B33: 0.16 | C33: 0.16 | L33: =DATE(YEAR(L32),MONTH(L32)+3,1) -> 41518 | M33: =AP33 -> 242464.05 | N33: =AX33-BC33 -> 221291.59 | O33: =M33/N33 -> 1.0956768 | P33: =X33/BG33 -> 0.73305335 | Q33: 31 | R33: =EOMONTH(L33,0)-EOMONTH(L33,-3) -> 92 | T33: =IF($B$10="3BR_H", INDEX('3BR_H-processed'!$C:$D,MATCH($L33,'3BR_H-processed'!$B:$B,0),MATCH(Council_Area,'3BR_H-processed'!$C$1:$D$1,0)), INDEX('2BR_F-processed'!$C:$D,MATCH($L33,'2BR_F-processed'!$B:$B,0),MATCH(Council_Area,'2BR_F-processed'!$C$1:$D$1,0))) -> 345 | U33: =IF(MOD(Q33,4)=1,T33,U32) -> 349 | V33: =U33*(R33)/7 -> 4586.8571 | W33: =$B$53/4*BH33/_xlfn.XLOOKUP(Q_end,cpi!A:A,cpi!B:B) -> 143.60746 | X33: =V33+W33 -> 4730.4646 | Y33: =BG33-X33 -> 1722.6327 | Z33: =Y33*$B$47 -> 0 | AA33: {=(Y33+Z33)*eff_invest} -> 1722.6327 | AB33: =AA33*(_xlfn.XLOOKUP(Q_end,cpi!A:A,cpi!B:B)/BH33) -> 2399.0852 | AC33: {=INDEX('msci-indices'!C:C,MATCH($L33,'msci-indices'!$B:$B)-2)} -> 1030.5184 | AD33: {=INDEX('msci-indices'!D:D,MATCH($L33,'msci-indices'!$B:$B)-2)} -> 988.35138 | AE33: =AI32+AA33 -> 222411.28 | AF33: {=INDEX('msci-indices'!C:C,MATCH($L33,'msci-indices'!$B:$B)+1)} -> 1119.4371 | AG33: {=INDEX('msci-indices'!D:D,MATCH($L33,'msci-indices'!$B:$B)+1)} -> 1088.4582 | AH33: =(InvestFees/4)*AE33 -> 139.00705 | AI33: =((AF33/AC33)*GlobalPortfolio+(AG33/AD33)*AusPortfolio)*AE33-AH33 -> 242464.05 | AJ33: =AJ32+AA33 -> 173689.08 | AK33: =AI33-AJ33 -> 68774.969 | AL33: =AJ33*(_xlfn.XLOOKUP(Q_end,cpi!A:A,cpi!B:B)/BH33) -> 241894.23 | AM33: {=SUMPRODUCT($AA$3:AA33,_xlfn.SORTBY($BH$3:BH33,_xlfn.SEQUENCE(ROWS($BH$3:BH33)),-1)/$BH$3)} -> 204952.41 | AN33: =AI33-AM33 -> 37511.644 | AO33: =IF($B$49="Real gains",MAX($B$50*AN33,0),IF($B$49="Discounted nominal gains",MAX($B$50*AK33/2,0),0)) -> 0 | AP33: =AI33-AO33 -> 242464.05 | AR33: =IF($B$10="3BR_H", INDEX('ns-combined'!$C:$D,MATCH($L33,'ns-combined'!$B:$B,0),MATCH(Council_Area,'ns-combined'!$C$1:$D$1,0))*1000, INDEX('s-combined'!$C:$D,MATCH($L33,'s-combined'!$B:$B,0),MATCH(Council_Area,'s-combined'!$C$1:$D$1,0))*1000) -> 520000 | AS33: =AS32+$AS$3 -> 25575 | AT33: 0 | AU33: =SUM($B$28:$B$29)*AR33 -> 10400 | AV33: =AR33*$B$15/4 -> 1495 | AW33: =SUM($AV$3:AV33) -> 38813.363 | AX33: =AR33-AS33-AU33-AW33 -> 445211.64 | AY33: =$B$36*V33 -> 1605.4 | AZ33: =SUM(AY33:AY33)*4/AR33 -> 0.012349231 | BA33: =SUM(AY33:AY33)/V33 -> 0.35 | BB33: =IF(MortgageRate="Discounted",_xlfn.XLOOKUP(L33,'mortgage-rates'!$A:$A,'mortgage-rates'!$E:$E)/100,_xlfn.XLOOKUP(L33,'mortgage-rates'!$A:$A,'mortgage-rates'!$D:$D)/100) -> 0.0508 | BC33: =BC32-BF32 -> 223920.05 | BD33: =IF($B$16*12/3-Q33+1>0,-PMT($BB33/4,$B$16*12/3-Q33+1,BC33),0) -> 4847.6973 | BE33: =BC33*($BB33/4) -> 2843.7846 | BF33: =BD33-BE33 -> 2003.9127 | BG33: =AT33+AY33+BD33 -> 6453.0973 | BH33: =INDEX(cpi!B:B,MATCH($L33,cpi!A:A)) -> 103.9 | BI33: =100*BH33/BH$3 -> 122.81324 | BJ33: =100*AC33/AC$3 -> 136.51427 | BK33: =100*AD33/AD$3 -> 138.62721 | BL33: =BJ33*GlobalPortfolio+BK33*AusPortfolio -> 137.14815 | BM33: =100*AE33/$AE$3 -> 247.67482 | BN33: =100*AR33/AR$3 -> 157.57576 | BO33: =100*AX33/AX$3 -> 138.42516
A34: Plant depreciation | B34: 0.07 | C34: 0.07 | L34: =DATE(YEAR(L33),MONTH(L33)+3,1) -> 41609 | M34: =AP34 -> 260023.62 | N34: =AX34-BC34 -> 261037.63 | O34: =M34/N34 -> 0.99611547 | P34: =X34/BG34 -> 0.7324079 | Q34: 32 | R34: =EOMONTH(L34,0)-EOMONTH(L34,-3) -> 92 | T34: =IF($B$10="3BR_H", INDEX('3BR_H-processed'!$C:$D,MATCH($L34,'3BR_H-processed'!$B:$B,0),MATCH(Council_Area,'3BR_H-processed'!$C$1:$D$1,0)), INDEX('2BR_F-processed'!$C:$D,MATCH($L34,'2BR_F-processed'!$B:$B,0),MATCH(Council_Area,'2BR_F-processed'!$C$1:$D$1,0))) -> 350 | U34: =IF(MOD(Q34,4)=1,T34,U33) -> 349 | V34: =U34*(R34)/7 -> 4586.8571 | W34: =$B$53/4*BH34/_xlfn.XLOOKUP(Q_end,cpi!A:A,cpi!B:B) -> 144.7132 | X34: =V34+W34 -> 4731.5703 | Y34: =BG34-X34 -> 1728.7236 | Z34: =Y34*$B$47 -> 0 | AA34: {=(Y34+Z34)*eff_invest} -> 1728.7236 | AB34: =AA34*(_xlfn.XLOOKUP(Q_end,cpi!A:A,cpi!B:B)/BH34) -> 2389.172 | AC34: {=INDEX('msci-indices'!C:C,MATCH($L34,'msci-indices'!$B:$B)-2)} -> 1119.4371 | AD34: {=INDEX('msci-indices'!D:D,MATCH($L34,'msci-indices'!$B:$B)-2)} -> 1088.4582 | AE34: =AI33+AA34 -> 244192.78 | AF34: {=INDEX('msci-indices'!C:C,MATCH($L34,'msci-indices'!$B:$B)+1)} -> 1208.1074 | AG34: {=INDEX('msci-indices'!D:D,MATCH($L34,'msci-indices'!$B:$B)+1)} -> 1124.7671 | AH34: =(InvestFees/4)*AE34 -> 152.62048 | AI34: =((AF34/AC34)*GlobalPortfolio+(AG34/AD34)*AusPortfolio)*AE34-AH34 -> 260023.62 | AJ34: =AJ33+AA34 -> 175417.81 | AK34: =AI34-AJ34 -> 84605.813 | AL34: =AJ34*(_xlfn.XLOOKUP(Q_end,cpi!A:A,cpi!B:B)/BH34) -> 242435.12 | AM34: {=SUMPRODUCT($AA$3:AA34,_xlfn.SORTBY($BH$3:BH34,_xlfn.SEQUENCE(ROWS($BH$3:BH34)),-1)/$BH$3)} -> 208150.23 | AN34: =AI34-AM34 -> 51873.395 | AO34: =IF($B$49="Real gains",MAX($B$50*AN34,0),IF($B$49="Discounted nominal gains",MAX($B$50*AK34/2,0),0)) -> 0 | AP34: =AI34-AO34 -> 260023.62 | AR34: =IF($B$10="3BR_H", INDEX('ns-combined'!$C:$D,MATCH($L34,'ns-combined'!$B:$B,0),MATCH(Council_Area,'ns-combined'!$C$1:$D$1,0))*1000, INDEX('s-combined'!$C:$D,MATCH($L34,'s-combined'!$B:$B,0),MATCH(Council_Area,'s-combined'!$C$1:$D$1,0))*1000) -> 561000 | AS34: =AS33+$AS$3 -> 26400 | AT34: 0 | AU34: =SUM($B$28:$B$29)*AR34 -> 11220 | AV34: =AR34*$B$15/4 -> 1612.875 | AW34: =SUM($AV$3:AV34) -> 40426.238 | AX34: =AR34-AS34-AU34-AW34 -> 482953.76 | AY34: =$B$36*V34 -> 1605.4 | AZ34: =SUM(AY34:AY34)*4/AR34 -> 0.011446702 | BA34: =SUM(AY34:AY34)/V34 -> 0.35 | BB34: =IF(MortgageRate="Discounted",_xlfn.XLOOKUP(L34,'mortgage-rates'!$A:$A,'mortgage-rates'!$E:$E)/100,_xlfn.XLOOKUP(L34,'mortgage-rates'!$A:$A,'mortgage-rates'!$D:$D)/100) -> 0.051 | BC34: =BC33-BF33 -> 221916.13 | BD34: =IF($B$16*12/3-Q34+1>0,-PMT($BB34/4,$B$16*12/3-Q34+1,BC34),0) -> 4854.894 | BE34: =BC34*($BB34/4) -> 2829.4307 | BF34: =BD34-BE34 -> 2025.4633 | BG34: =AT34+AY34+BD34 -> 6460.294 | BH34: =INDEX(cpi!B:B,MATCH($L34,cpi!A:A)) -> 104.7 | BI34: =100*BH34/BH$3 -> 123.75887 | BJ34: =100*AC34/AC$3 -> 148.29346 | BK34: =100*AD34/AD$3 -> 152.6683 | BL34: =BJ34*GlobalPortfolio+BK34*AusPortfolio -> 149.60591 | BM34: =100*AE34/$AE$3 -> 271.93047 | BN34: =100*AR34/AR$3 -> 170 | BO34: =100*AX34/AX$3 -> 150.15993
A35: Other expenses | B35: 0.05 | C35: 0.05 | L35: =DATE(YEAR(L34),MONTH(L34)+3,1) -> 41699 | M35: =AP35 -> 266068.86 | N35: =AX35-BC35 -> 204929.09 | O35: =M35/N35 -> 1.298346 | P35: =X35/BG35 -> 0.72331271 | Q35: 33 | R35: =EOMONTH(L35,0)-EOMONTH(L35,-3) -> 90 | T35: =IF($B$10="3BR_H", INDEX('3BR_H-processed'!$C:$D,MATCH($L35,'3BR_H-processed'!$B:$B,0),MATCH(Council_Area,'3BR_H-processed'!$C$1:$D$1,0)), INDEX('2BR_F-processed'!$C:$D,MATCH($L35,'2BR_F-processed'!$B:$B,0),MATCH(Council_Area,'2BR_F-processed'!$C$1:$D$1,0))) -> 350 | U35: =IF(MOD(Q35,4)=1,T35,U34) -> 350 | V35: =U35*(R35)/7 -> 4500 | W35: =$B$53/4*BH35/_xlfn.XLOOKUP(Q_end,cpi!A:A,cpi!B:B) -> 145.68072 | X35: =V35+W35 -> 4645.6807 | Y35: =BG35-X35 -> 1777.1025 | Z35: =Y35*$B$47 -> 0 | AA35: {=(Y35+Z35)*eff_invest} -> 1777.1025 | AB35: =AA35*(_xlfn.XLOOKUP(Q_end,cpi!A:A,cpi!B:B)/BH35) -> 2439.7223 | AC35: {=INDEX('msci-indices'!C:C,MATCH($L35,'msci-indices'!$B:$B)-2)} -> 1208.1074 | AD35: {=INDEX('msci-indices'!D:D,MATCH($L35,'msci-indices'!$B:$B)-2)} -> 1124.7671 | AE35: =AI34+AA35 -> 261800.72 | AF35: {=INDEX('msci-indices'!C:C,MATCH($L35,'msci-indices'!$B:$B)+1)} -> 1225.92 | AG35: {=INDEX('msci-indices'!D:D,MATCH($L35,'msci-indices'!$B:$B)+1)} -> 1149.5384 | AH35: =(InvestFees/4)*AE35 -> 163.62545 | AI35: =((AF35/AC35)*GlobalPortfolio+(AG35/AD35)*AusPortfolio)*AE35-AH35 -> 266068.86 | AJ35: =AJ34+AA35 -> 177194.91 | AK35: =AI35-AJ35 -> 88873.947 | AL35: =AJ35*(_xlfn.XLOOKUP(Q_end,cpi!A:A,cpi!B:B)/BH35) -> 243264.74 | AM35: {=SUMPRODUCT($AA$3:AA35,_xlfn.SORTBY($BH$3:BH35,_xlfn.SEQUENCE(ROWS($BH$3:BH35)),-1)/$BH$3)} -> 211299.4 | AN35: =AI35-AM35 -> 54769.458 | AO35: =IF($B$49="Real gains",MAX($B$50*AN35,0),IF($B$49="Discounted nominal gains",MAX($B$50*AK35/2,0),0)) -> 0 | AP35: =AI35-AO35 -> 266068.86 | AR35: =IF($B$10="3BR_H", INDEX('ns-combined'!$C:$D,MATCH($L35,'ns-combined'!$B:$B,0),MATCH(Council_Area,'ns-combined'!$C$1:$D$1,0))*1000, INDEX('s-combined'!$C:$D,MATCH($L35,'s-combined'!$B:$B,0),MATCH(Council_Area,'s-combined'!$C$1:$D$1,0))*1000) -> 504000 | AS35: =AS34+$AS$3 -> 27225 | AT35: 0 | AU35: =SUM($B$28:$B$29)*AR35 -> 10080 | AV35: =AR35*$B$15/4 -> 1449 | AW35: =SUM($AV$3:AV35) -> 41875.238 | AX35: =AR35-AS35-AU35-AW35 -> 424819.76 | AY35: =$B$36*V35 -> 1575 | AZ35: =SUM(AY35:AY35)*4/AR35 -> 0.0125 | BA35: =SUM(AY35:AY35)/V35 -> 0.35 | BB35: =IF(MortgageRate="Discounted",_xlfn.XLOOKUP(L35,'mortgage-rates'!$A:$A,'mortgage-rates'!$E:$E)/100,_xlfn.XLOOKUP(L35,'mortgage-rates'!$A:$A,'mortgage-rates'!$D:$D)/100) -> 0.0508 | BC35: =BC34-BF34 -> 219890.67 | BD35: =IF($B$16*12/3-Q35+1>0,-PMT($BB35/4,$B$16*12/3-Q35+1,BC35),0) -> 4847.7832 | BE35: =BC35*($BB35/4) -> 2792.6115 | BF35: =BD35-BE35 -> 2055.1717 | BG35: =AT35+AY35+BD35 -> 6422.7832 | BH35: =INDEX(cpi!B:B,MATCH($L35,cpi!A:A)) -> 105.4 | BI35: =100*BH35/BH$3 -> 124.58629 | BJ35: =100*AC35/AC$3 -> 160.03975 | BK35: =100*AD35/AD$3 -> 157.76103 | BL35: =BJ35*GlobalPortfolio+BK35*AusPortfolio -> 159.35613 | BM35: =100*AE35/$AE$3 -> 291.53849 | BN35: =100*AR35/AR$3 -> 152.72727 | BO35: =100*AX35/AX$3 -> 132.08492
A36: Total home ownership running costs | B36: =SUM(B32:B35) -> 0.35 | C36: 0.35 | L36: =DATE(YEAR(L35),MONTH(L35)+3,1) -> 41791 | M36: =AP36 -> 276977.86 | N36: =AX36-BC36 -> 229040.68 | O36: =M36/N36 -> 1.2092955 | P36: =X36/BG36 -> 0.72926113 | Q36: 34 | R36: =EOMONTH(L36,0)-EOMONTH(L36,-3) -> 91 | T36: =IF($B$10="3BR_H", INDEX('3BR_H-processed'!$C:$D,MATCH($L36,'3BR_H-processed'!$B:$B,0),MATCH(Council_Area,'3BR_H-processed'!$C$1:$D$1,0)), INDEX('2BR_F-processed'!$C:$D,MATCH($L36,'2BR_F-processed'!$B:$B,0),MATCH(Council_Area,'2BR_F-processed'!$C$1:$D$1,0))) -> 350 | U36: =IF(MOD(Q36,4)=1,T36,U35) -> 350 | V36: =U36*(R36)/7 -> 4550 | W36: =$B$53/4*BH36/_xlfn.XLOOKUP(Q_end,cpi!A:A,cpi!B:B) -> 146.64824 | X36: =V36+W36 -> 4696.6482 | Y36: =BG36-X36 -> 1743.635 | Z36: =Y36*$B$47 -> 0 | AA36: {=(Y36+Z36)*eff_invest} -> 1743.635 | AB36: =AA36*(_xlfn.XLOOKUP(Q_end,cpi!A:A,cpi!B:B)/BH36) -> 2377.9829 | AC36: {=INDEX('msci-indices'!C:C,MATCH($L36,'msci-indices'!$B:$B)-2)} -> 1225.92 | AD36: {=INDEX('msci-indices'!D:D,MATCH($L36,'msci-indices'!$B:$B)-2)} -> 1149.5384 | AE36: =AI35+AA36 -> 267812.49 | AF36: {=INDEX('msci-indices'!C:C,MATCH($L36,'msci-indices'!$B:$B)+1)} -> 1282.9431 | AG36: {=INDEX('msci-indices'!D:D,MATCH($L36,'msci-indices'!$B:$B)+1)} -> 1158.3053 | AH36: =(InvestFees/4)*AE36 -> 167.38281 | AI36: =((AF36/AC36)*GlobalPortfolio+(AG36/AD36)*AusPortfolio)*AE36-AH36 -> 276977.86 | AJ36: =AJ35+AA36 -> 178938.54 | AK36: =AI36-AJ36 -> 98039.315 | AL36: =AJ36*(_xlfn.XLOOKUP(Q_end,cpi!A:A,cpi!B:B)/BH36) -> 244037.77 | AM36: {=SUMPRODUCT($AA$3:AA36,_xlfn.SORTBY($BH$3:BH36,_xlfn.SEQUENCE(ROWS($BH$3:BH36)),-1)/$BH$3)} -> 214434.8 | AN36: =AI36-AM36 -> 62543.062 | AO36: =IF($B$49="Real gains",MAX($B$50*AN36,0),IF($B$49="Discounted nominal gains",MAX($B$50*AK36/2,0),0)) -> 0 | AP36: =AI36-AO36 -> 276977.86 | AR36: =IF($B$10="3BR_H", INDEX('ns-combined'!$C:$D,MATCH($L36,'ns-combined'!$B:$B,0),MATCH(Council_Area,'ns-combined'!$C$1:$D$1,0))*1000, INDEX('s-combined'!$C:$D,MATCH($L36,'s-combined'!$B:$B,0),MATCH(Council_Area,'s-combined'!$C$1:$D$1,0))*1000) -> 528900 | AS36: =AS35+$AS$3 -> 28050 | AT36: 0 | AU36: =SUM($B$28:$B$29)*AR36 -> 10578 | AV36: =AR36*$B$15/4 -> 1520.5875 | AW36: =SUM($AV$3:AV36) -> 43395.825 | AX36: =AR36-AS36-AU36-AW36 -> 446876.17 | AY36: =$B$36*V36 -> 1592.5 | AZ36: =SUM(AY36:AY36)*4/AR36 -> 0.012043865 | BA36: =SUM(AY36:AY36)/V36 -> 0.35 | BB36: =IF(MortgageRate="Discounted",_xlfn.XLOOKUP(L36,'mortgage-rates'!$A:$A,'mortgage-rates'!$E:$E)/100,_xlfn.XLOOKUP(L36,'mortgage-rates'!$A:$A,'mortgage-rates'!$D:$D)/100) -> 0.0508 | BC36: =BC35-BF35 -> 217835.5 | BD36: =IF($B$16*12/3-Q36+1>0,-PMT($BB36/4,$B$16*12/3-Q36+1,BC36),0) -> 4847.7832 | BE36: =BC36*($BB36/4) -> 2766.5108 | BF36: =BD36-BE36 -> 2081.2724 | BG36: =AT36+AY36+BD36 -> 6440.2832 | BH36: =INDEX(cpi!B:B,MATCH($L36,cpi!A:A)) -> 106.1 | BI36: =100*BH36/BH$3 -> 125.41371 | BJ36: =100*AC36/AC$3 -> 162.39941 | BK36: =100*AD36/AD$3 -> 161.23548 | BL36: =BJ36*GlobalPortfolio+BK36*AusPortfolio -> 162.05023 | BM36: =100*AE36/$AE$3 -> 298.23313 | BN36: =100*AR36/AR$3 -> 160.27273 | BO36: =100*AX36/AX$3 -> 138.94269
A37: Average maint + reno spending (% home value) | B37: {=AVERAGE(_xlfn._xlws.FILTER($AZ$3:$AZ$82,ISNUMBER($AZ$3:$AZ$82)))} -> 0.011405453 | C37: 0.011405453 | L37: =DATE(YEAR(L36),MONTH(L36)+3,1) -> 41883 | M37: =AP37 -> 272539.14 | N37: =AX37-BC37 -> 205423.07 | O37: =M37/N37 -> 1.3267212 | P37: =X37/BG37 -> 0.7350703 | Q37: 35 | R37: =EOMONTH(L37,0)-EOMONTH(L37,-3) -> 92 | T37: =IF($B$10="3BR_H", INDEX('3BR_H-processed'!$C:$D,MATCH($L37,'3BR_H-processed'!$B:$B,0),MATCH(Council_Area,'3BR_H-processed'!$C$1:$D$1,0)), INDEX('2BR_F-processed'!$C:$D,MATCH($L37,'2BR_F-processed'!$B:$B,0),MATCH(Council_Area,'2BR_F-processed'!$C$1:$D$1,0))) -> 350 | U37: =IF(MOD(Q37,4)=1,T37,U36) -> 350 | V37: =U37*(R37)/7 -> 4600 | W37: =$B$53/4*BH37/_xlfn.XLOOKUP(Q_end,cpi!A:A,cpi!B:B) -> 146.92467 | X37: =V37+W37 -> 4746.9247 | Y37: =BG37-X37 -> 1710.8586 | Z37: =Y37*$B$47 -> 0 | AA37: {=(Y37+Z37)*eff_invest} -> 1710.8586 | AB37: =AA37*(_xlfn.XLOOKUP(Q_end,cpi!A:A,cpi!B:B)/BH37) -> 2328.8921 | AC37: {=INDEX('msci-indices'!C:C,MATCH($L37,'msci-indices'!$B:$B)-2)} -> 1282.9431 | AD37: {=INDEX('msci-indices'!D:D,MATCH($L37,'msci-indices'!$B:$B)-2)} -> 1158.3053 | AE37: =AI36+AA37 -> 278688.72 | AF37: {=INDEX('msci-indices'!C:C,MATCH($L37,'msci-indices'!$B:$B)+1)} -> 1247.2922 | AG37: {=INDEX('msci-indices'!D:D,MATCH($L37,'msci-indices'!$B:$B)+1)} -> 1150.6246 | AH37: =(InvestFees/4)*AE37 -> 174.18045 | AI37: =((AF37/AC37)*GlobalPortfolio+(AG37/AD37)*AusPortfolio)*AE37-AH37 -> 272539.14 | AJ37: =AJ36+AA37 -> 180649.4 | AK37: =AI37-AJ37 -> 91889.736 | AL37: =AJ37*(_xlfn.XLOOKUP(Q_end,cpi!A:A,cpi!B:B)/BH37) -> 245907.51 | AM37: {=SUMPRODUCT($AA$3:AA37,_xlfn.SORTBY($BH$3:BH37,_xlfn.SEQUENCE(ROWS($BH$3:BH37)),-1)/$BH$3)} -> 217030.59 | AN37: =AI37-AM37 -> 55508.544 | AO37: =IF($B$49="Real gains",MAX($B$50*AN37,0),IF($B$49="Discounted nominal gains",MAX($B$50*AK37/2,0),0)) -> 0 | AP37: =AI37-AO37 -> 272539.14 | AR37: =IF($B$10="3BR_H", INDEX('ns-combined'!$C:$D,MATCH($L37,'ns-combined'!$B:$B,0),MATCH(Council_Area,'ns-combined'!$C$1:$D$1,0))*1000, INDEX('s-combined'!$C:$D,MATCH($L37,'s-combined'!$B:$B,0),MATCH(Council_Area,'s-combined'!$C$1:$D$1,0))*1000) -> 505000 | AS37: =AS36+$AS$3 -> 28875 | AT37: 0 | AU37: =SUM($B$28:$B$29)*AR37 -> 10100 | AV37: =AR37*$B$15/4 -> 1451.875 | AW37: =SUM($AV$3:AV37) -> 44847.7 | AX37: =AR37-AS37-AU37-AW37 -> 421177.3 | AY37: =$B$36*V37 -> 1610 | AZ37: =SUM(AY37:AY37)*4/AR37 -> 0.012752475 | BA37: =SUM(AY37:AY37)/V37 -> 0.35 | BB37: =IF(MortgageRate="Discounted",_xlfn.XLOOKUP(L37,'mortgage-rates'!$A:$A,'mortgage-rates'!$E:$E)/100,_xlfn.XLOOKUP(L37,'mortgage-rates'!$A:$A,'mortgage-rates'!$D:$D)/100) -> 0.0508 | BC37: =BC36-BF36 -> 215754.23 | BD37: =IF($B$16*12/3-Q37+1>0,-PMT($BB37/4,$B$16*12/3-Q37+1,BC37),0) -> 4847.7832 | BE37: =BC37*($BB37/4) -> 2740.0787 | BF37: =BD37-BE37 -> 2107.7046 | BG37: =AT37+AY37+BD37 -> 6457.7832 | BH37: =INDEX(cpi!B:B,MATCH($L37,cpi!A:A)) -> 106.3 | BI37: =100*BH37/BH$3 -> 125.65012 | BJ37: =100*AC37/AC$3 -> 169.95334 | BK37: =100*AD37/AD$3 -> 162.46513 | BL37: =BJ37*GlobalPortfolio+BK37*AusPortfolio -> 167.70687 | BM37: =100*AE37/$AE$3 -> 310.34478 | BN37: =100*AR37/AR$3 -> 153.0303 | BO37: =100*AX37/AX$3 -> 130.9524
A38: Average maint + reno spending (% rents) | B38: {=AVERAGE(_xlfn._xlws.FILTER($BA$3:$BA$82,ISNUMBER($BA$3:$BA$82)))} -> 0.35 | C38: 0.35 | L38: =DATE(YEAR(L37),MONTH(L37)+3,1) -> 41974 | M38: =AP38 -> 278644.19 | N38: =AX38-BC38 -> 251667.34 | O38: =M38/N38 -> 1.1071925 | P38: =X38/BG38 -> 0.73511311 | Q38: 36 | R38: =EOMONTH(L38,0)-EOMONTH(L38,-3) -> 92 | T38: =IF($B$10="3BR_H", INDEX('3BR_H-processed'!$C:$D,MATCH($L38,'3BR_H-processed'!$B:$B,0),MATCH(Council_Area,'3BR_H-processed'!$C$1:$D$1,0)), INDEX('2BR_F-processed'!$C:$D,MATCH($L38,'2BR_F-processed'!$B:$B,0),MATCH(Council_Area,'2BR_F-processed'!$C$1:$D$1,0))) -> 360 | U38: =IF(MOD(Q38,4)=1,T38,U37) -> 350 | V38: =U38*(R38)/7 -> 4600 | W38: =$B$53/4*BH38/_xlfn.XLOOKUP(Q_end,cpi!A:A,cpi!B:B) -> 147.20111 | X38: =V38+W38 -> 4747.2011 | Y38: =BG38-X38 -> 1710.5821 | Z38: =Y38*$B$47 -> 0 | AA38: {=(Y38+Z38)*eff_invest} -> 1710.5821 | AB38: =AA38*(_xlfn.XLOOKUP(Q_end,cpi!A:A,cpi!B:B)/BH38) -> 2324.143 | AC38: {=INDEX('msci-indices'!C:C,MATCH($L38,'msci-indices'!$B:$B)-2)} -> 1247.2922 | AD38: {=INDEX('msci-indices'!D:D,MATCH($L38,'msci-indices'!$B:$B)-2)} -> 1150.6246 | AE38: =AI37+AA38 -> 274249.72 | AF38: {=INDEX('msci-indices'!C:C,MATCH($L38,'msci-indices'!$B:$B)+1)} -> 1262.6926 | AG38: {=INDEX('msci-indices'!D:D,MATCH($L38,'msci-indices'!$B:$B)+1)} -> 1181.3297 | AH38: =(InvestFees/4)*AE38 -> 171.40608 | AI38: =((AF38/AC38)*GlobalPortfolio+(AG38/AD38)*AusPortfolio)*AE38-AH38 -> 278644.19 | AJ38: =AJ37+AA38 -> 182359.99 | AK38: =AI38-AJ38 -> 96284.206 | AL38: =AJ38*(_xlfn.XLOOKUP(Q_end,cpi!A:A,cpi!B:B)/BH38) -> 247769.86 | AM38: {=SUMPRODUCT($AA$3:AA38,_xlfn.SORTBY($BH$3:BH38,_xlfn.SEQUENCE(ROWS($BH$3:BH38)),-1)/$BH$3)} -> 219633.75 | AN38: =AI38-AM38 -> 59010.438 | AO38: =IF($B$49="Real gains",MAX($B$50*AN38,0),IF($B$49="Discounted nominal gains",MAX($B$50*AK38/2,0),0)) -> 0 | AP38: =AI38-AO38 -> 278644.19 | AR38: =IF($B$10="3BR_H", INDEX('ns-combined'!$C:$D,MATCH($L38,'ns-combined'!$B:$B,0),MATCH(Council_Area,'ns-combined'!$C$1:$D$1,0))*1000, INDEX('s-combined'!$C:$D,MATCH($L38,'s-combined'!$B:$B,0),MATCH(Council_Area,'s-combined'!$C$1:$D$1,0))*1000) -> 552500 | AS38: =AS37+$AS$3 -> 29700 | AT38: 0 | AU38: =SUM($B$28:$B$29)*AR38 -> 11050 | AV38: =AR38*$B$15/4 -> 1588.4375 | AW38: =SUM($AV$3:AV38) -> 46436.138 | AX38: =AR38-AS38-AU38-AW38 -> 465313.86 | AY38: =$B$36*V38 -> 1610 | AZ38: =SUM(AY38:AY38)*4/AR38 -> 0.011656109 | BA38: =SUM(AY38:AY38)/V38 -> 0.35 | BB38: =IF(MortgageRate="Discounted",_xlfn.XLOOKUP(L38,'mortgage-rates'!$A:$A,'mortgage-rates'!$E:$E)/100,_xlfn.XLOOKUP(L38,'mortgage-rates'!$A:$A,'mortgage-rates'!$D:$D)/100) -> 0.0508 | BC38: =BC37-BF37 -> 213646.52 | BD38: =IF($B$16*12/3-Q38+1>0,-PMT($BB38/4,$B$16*12/3-Q38+1,BC38),0) -> 4847.7832 | BE38: =BC38*($BB38/4) -> 2713.3108 | BF38: =BD38-BE38 -> 2134.4724 | BG38: =AT38+AY38+BD38 -> 6457.7832 | BH38: =INDEX(cpi!B:B,MATCH($L38,cpi!A:A)) -> 106.5 | BI38: =100*BH38/BH$3 -> 125.88652 | BJ38: =100*AC38/AC$3 -> 165.23062 | BK38: =100*AD38/AD$3 -> 161.38783 | BL38: =BJ38*GlobalPortfolio+BK38*AusPortfolio -> 164.07778 | BM38: =100*AE38/$AE$3 -> 305.40156 | BN38: =100*AR38/AR$3 -> 167.42424 | BO38: =100*AX38/AX$3 -> 144.67534
L39: =DATE(YEAR(L38),MONTH(L38)+3,1) -> 42064 | M39: =AP39 -> 293754.37 | N39: =AX39-BC39 -> 224517.44 | O39: =M39/N39 -> 1.3083811 | P39: =X39/BG39 -> 0.74857714 | Q39: 37 | R39: =EOMONTH(L39,0)-EOMONTH(L39,-3) -> 90 | T39: =IF($B$10="3BR_H", INDEX('3BR_H-processed'!$C:$D,MATCH($L39,'3BR_H-processed'!$B:$B,0),MATCH(Council_Area,'3BR_H-processed'!$C$1:$D$1,0)), INDEX('2BR_F-processed'!$C:$D,MATCH($L39,'2BR_F-processed'!$B:$B,0),MATCH(Council_Area,'2BR_F-processed'!$C$1:$D$1,0))) -> 360 | U39: =IF(MOD(Q39,4)=1,T39,U38) -> 360 | V39: =U39*(R39)/7 -> 4628.5714 | W39: =$B$53/4*BH39/_xlfn.XLOOKUP(Q_end,cpi!A:A,cpi!B:B) -> 147.61576 | X39: =V39+W39 -> 4776.1872 | Y39: =BG39-X39 -> 1604.1668 | Z39: =Y39*$B$47 -> 0 | AA39: {=(Y39+Z39)*eff_invest} -> 1604.1668 | AB39: =AA39*(_xlfn.XLOOKUP(Q_end,cpi!A:A,cpi!B:B)/BH39) -> 2173.4358 | AC39: {=INDEX('msci-indices'!C:C,MATCH($L39,'msci-indices'!$B:$B)-2)} -> 1262.6926 | AD39: {=INDEX('msci-indices'!D:D,MATCH($L39,'msci-indices'!$B:$B)-2)} -> 1181.3297 | AE39: =AI38+AA39 -> 280248.36 | AF39: {=INDEX('msci-indices'!C:C,MATCH($L39,'msci-indices'!$B:$B)+1)} -> 1295.5073 | AG39: {=INDEX('msci-indices'!D:D,MATCH($L39,'msci-indices'!$B:$B)+1)} -> 1301.9298 | AH39: =(InvestFees/4)*AE39 -> 175.15522 | AI39: =((AF39/AC39)*GlobalPortfolio+(AG39/AD39)*AusPortfolio)*AE39-AH39 -> 293754.37 | AJ39: =AJ38+AA39 -> 183964.15 | AK39: =AI39-AJ39 -> 109790.22 | AL39: =AJ39*(_xlfn.XLOOKUP(Q_end,cpi!A:A,cpi!B:B)/BH39) -> 249247.31 | AM39: {=SUMPRODUCT($AA$3:AA39,_xlfn.SORTBY($BH$3:BH39,_xlfn.SEQUENCE(ROWS($BH$3:BH39)),-1)/$BH$3)} -> 222235.66 | AN39: =AI39-AM39 -> 71518.711 | AO39: =IF($B$49="Real gains",MAX($B$50*AN39,0),IF($B$49="Discounted nominal gains",MAX($B$50*AK39/2,0),0)) -> 0 | AP39: =AI39-AO39 -> 293754.37 | AR39: =IF($B$10="3BR_H", INDEX('ns-combined'!$C:$D,MATCH($L39,'ns-combined'!$B:$B,0),MATCH(Council_Area,'ns-combined'!$C$1:$D$1,0))*1000, INDEX('s-combined'!$C:$D,MATCH($L39,'s-combined'!$B:$B,0),MATCH(Council_Area,'s-combined'!$C$1:$D$1,0))*1000) -> 525000 | AS39: =AS38+$AS$3 -> 30525 | AT39: 0 | AU39: =SUM($B$28:$B$29)*AR39 -> 10500 | AV39: =AR39*$B$15/4 -> 1509.375 | AW39: =SUM($AV$3:AV39) -> 47945.513 | AX39: =AR39-AS39-AU39-AW39 -> 436029.49 | AY39: =$B$36*V39 -> 1620 | AZ39: =SUM(AY39:AY39)*4/AR39 -> 0.012342857 | BA39: =SUM(AY39:AY39)/V39 -> 0.35 | BB39: =IF(MortgageRate="Discounted",_xlfn.XLOOKUP(L39,'mortgage-rates'!$A:$A,'mortgage-rates'!$E:$E)/100,_xlfn.XLOOKUP(L39,'mortgage-rates'!$A:$A,'mortgage-rates'!$D:$D)/100) -> 0.0482 | BC39: =BC38-BF38 -> 211512.05 | BD39: =IF($B$16*12/3-Q39+1>0,-PMT($BB39/4,$B$16*12/3-Q39+1,BC39),0) -> 4760.354 | BE39: =BC39*($BB39/4) -> 2548.7202 | BF39: =BD39-BE39 -> 2211.6338 | BG39: =AT39+AY39+BD39 -> 6380.354 | BH39: =INDEX(cpi!B:B,MATCH($L39,cpi!A:A)) -> 106.8 | BI39: =100*BH39/BH$3 -> 126.24113 | BJ39: =100*AC39/AC$3 -> 167.27073 | BK39: =100*AD39/AD$3 -> 165.69455 | BL39: =BJ39*GlobalPortfolio+BK39*AusPortfolio -> 166.79788 | BM39: =100*AE39/$AE$3 -> 312.08158 | BN39: =100*AR39/AR$3 -> 159.09091 | BO39: =100*AX39/AX$3 -> 135.57024
A40: Renter investment parameters | L40: =DATE(YEAR(L39),MONTH(L39)+3,1) -> 42156 | M40: =AP40 -> 290143.81 | N40: =AX40-BC40 -> 259571.2 | O40: =M40/N40 -> 1.1177812 | P40: =X40/BG40 -> 0.7605732 | Q40: 38 | R40: =EOMONTH(L40,0)-EOMONTH(L40,-3) -> 91 | T40: =IF($B$10="3BR_H", INDEX('3BR_H-processed'!$C:$D,MATCH($L40,'3BR_H-processed'!$B:$B,0),MATCH(Council_Area,'3BR_H-processed'!$C$1:$D$1,0)), INDEX('2BR_F-processed'!$C:$D,MATCH($L40,'2BR_F-processed'!$B:$B,0),MATCH(Council_Area,'2BR_F-processed'!$C$1:$D$1,0))) -> 360 | U40: =IF(MOD(Q40,4)=1,T40,U39) -> 360 | V40: =U40*(R40)/7 -> 4680 | W40: =$B$53/4*BH40/_xlfn.XLOOKUP(Q_end,cpi!A:A,cpi!B:B) -> 148.85971 | X40: =V40+W40 -> 4828.8597 | Y40: =BG40-X40 -> 1520.1146 | Z40: =Y40*$B$47 -> 0 | AA40: {=(Y40+Z40)*eff_invest} -> 1520.1146 | AB40: =AA40*(_xlfn.XLOOKUP(Q_end,cpi!A:A,cpi!B:B)/BH40) -> 2042.3452 | AC40: {=INDEX('msci-indices'!C:C,MATCH($L40,'msci-indices'!$B:$B)-2)} -> 1295.5073 | AD40: {=INDEX('msci-indices'!D:D,MATCH($L40,'msci-indices'!$B:$B)-2)} -> 1301.9298 | AE40: =AI39+AA40 -> 295274.49 | AF40: {=INDEX('msci-indices'!C:C,MATCH($L40,'msci-indices'!$B:$B)+1)} -> 1301.507 | AG40: {=INDEX('msci-indices'!D:D,MATCH($L40,'msci-indices'!$B:$B)+1)} -> 1215.1659 | AH40: =(InvestFees/4)*AE40 -> 184.54655 | AI40: =((AF40/AC40)*GlobalPortfolio+(AG40/AD40)*AusPortfolio)*AE40-AH40 -> 290143.81 | AJ40: =AJ39+AA40 -> 185484.27 | AK40: =AI40-AJ40 -> 104659.55 | AL40: =AJ40*(_xlfn.XLOOKUP(Q_end,cpi!A:A,cpi!B:B)/BH40) -> 249206.81 | AM40: {=SUMPRODUCT($AA$3:AA40,_xlfn.SORTBY($BH$3:BH40,_xlfn.SEQUENCE(ROWS($BH$3:BH40)),-1)/$BH$3)} -> 225381.76 | AN40: =AI40-AM40 -> 64762.059 | AO40: =IF($B$49="Real gains",MAX($B$50*AN40,0),IF($B$49="Discounted nominal gains",MAX($B$50*AK40/2,0),0)) -> 0 | AP40: =AI40-AO40 -> 290143.81 | AR40: =IF($B$10="3BR_H", INDEX('ns-combined'!$C:$D,MATCH($L40,'ns-combined'!$B:$B,0),MATCH(Council_Area,'ns-combined'!$C$1:$D$1,0))*1000, INDEX('s-combined'!$C:$D,MATCH($L40,'s-combined'!$B:$B,0),MATCH(Council_Area,'s-combined'!$C$1:$D$1,0))*1000) -> 561000 | AS40: =AS39+$AS$3 -> 31350 | AT40: 0 | AU40: =SUM($B$28:$B$29)*AR40 -> 11220 | AV40: =AR40*$B$15/4 -> 1612.875 | AW40: =SUM($AV$3:AV40) -> 49558.388 | AX40: =AR40-AS40-AU40-AW40 -> 468871.61 | AY40: =$B$36*V40 -> 1638 | AZ40: =SUM(AY40:AY40)*4/AR40 -> 0.011679144 | BA40: =SUM(AY40:AY40)/V40 -> 0.35 | BB40: =IF(MortgageRate="Discounted",_xlfn.XLOOKUP(L40,'mortgage-rates'!$A:$A,'mortgage-rates'!$E:$E)/100,_xlfn.XLOOKUP(L40,'mortgage-rates'!$A:$A,'mortgage-rates'!$D:$D)/100) -> 0.0467 | BC40: =BC39-BF39 -> 209300.42 | BD40: =IF($B$16*12/3-Q40+1>0,-PMT($BB40/4,$B$16*12/3-Q40+1,BC40),0) -> 4710.9743 | BE40: =BC40*($BB40/4) -> 2443.5824 | BF40: =BD40-BE40 -> 2267.3919 | BG40: =AT40+AY40+BD40 -> 6348.9743 | BH40: =INDEX(cpi!B:B,MATCH($L40,cpi!A:A)) -> 107.7 | BI40: =100*BH40/BH$3 -> 127.30496 | BJ40: =100*AC40/AC$3 -> 171.61773 | BK40: =100*AD40/AD$3 -> 182.61006 | BL40: =BJ40*GlobalPortfolio+BK40*AusPortfolio -> 174.91543 | BM40: =100*AE40/$AE$3 -> 328.81451 | BN40: =100*AR40/AR$3 -> 170 | BO40: =100*AX40/AX$3 -> 145.78151
A41: % of portfolio in global equities | B41: 0.7 | C41: 0.7 | L41: =DATE(YEAR(L40),MONTH(L40)+3,1) -> 42248 | M41: =AP41 -> 267800.07 | N41: =AX41-BC41 -> 277966.09 | O41: =M41/N41 -> 0.96342711 | P41: =X41/BG41 -> 0.76691205 | Q41: 39 | R41: =EOMONTH(L41,0)-EOMONTH(L41,-3) -> 92 | T41: =IF($B$10="3BR_H", INDEX('3BR_H-processed'!$C:$D,MATCH($L41,'3BR_H-processed'!$B:$B,0),MATCH(Council_Area,'3BR_H-processed'!$C$1:$D$1,0)), INDEX('2BR_F-processed'!$C:$D,MATCH($L41,'2BR_F-processed'!$B:$B,0),MATCH(Council_Area,'2BR_F-processed'!$C$1:$D$1,0))) -> 360 | U41: =IF(MOD(Q41,4)=1,T41,U40) -> 360 | V41: =U41*(R41)/7 -> 4731.4286 | W41: =$B$53/4*BH41/_xlfn.XLOOKUP(Q_end,cpi!A:A,cpi!B:B) -> 148.99793 | X41: =V41+W41 -> 4880.4265 | Y41: =BG41-X41 -> 1483.3104 | Z41: =Y41*$B$47 -> 0 | AA41: {=(Y41+Z41)*eff_invest} -> 1483.3104 | AB41: =AA41*(_xlfn.XLOOKUP(Q_end,cpi!A:A,cpi!B:B)/BH41) -> 1991.0484 | AC41: {=INDEX('msci-indices'!C:C,MATCH($L41,'msci-indices'!$B:$B)-2)} -> 1301.507 | AD41: {=INDEX('msci-indices'!D:D,MATCH($L41,'msci-indices'!$B:$B)-2)} -> 1215.1659 | AE41: =AI40+AA41 -> 291627.12 | AF41: {=INDEX('msci-indices'!C:C,MATCH($L41,'msci-indices'!$B:$B)+1)} -> 1189.2855 | AG41: {=INDEX('msci-indices'!D:D,MATCH($L41,'msci-indices'!$B:$B)+1)} -> 1131.2309 | AH41: =(InvestFees/4)*AE41 -> 182.26695 | AI41: =((AF41/AC41)*GlobalPortfolio+(AG41/AD41)*AusPortfolio)*AE41-AH41 -> 267800.07 | AJ41: =AJ40+AA41 -> 186967.58 | AK41: =AI41-AJ41 -> 80832.489 | AL41: =AJ41*(_xlfn.XLOOKUP(Q_end,cpi!A:A,cpi!B:B)/BH41) -> 250966.68 | AM41: {=SUMPRODUCT($AA$3:AA41,_xlfn.SORTBY($BH$3:BH41,_xlfn.SEQUENCE(ROWS($BH$3:BH41)),-1)/$BH$3)} -> 227662.42 | AN41: =AI41-AM41 -> 40137.646 | AO41: =IF($B$49="Real gains",MAX($B$50*AN41,0),IF($B$49="Discounted nominal gains",MAX($B$50*AK41/2,0),0)) -> 0 | AP41: =AI41-AO41 -> 267800.07 | AR41: =IF($B$10="3BR_H", INDEX('ns-combined'!$C:$D,MATCH($L41,'ns-combined'!$B:$B,0),MATCH(Council_Area,'ns-combined'!$C$1:$D$1,0))*1000, INDEX('s-combined'!$C:$D,MATCH($L41,'s-combined'!$B:$B,0),MATCH(Council_Area,'s-combined'!$C$1:$D$1,0))*1000) -> 580000 | AS41: =AS40+$AS$3 -> 32175 | AT41: 0 | AU41: =SUM($B$28:$B$29)*AR41 -> 11600 | AV41: =AR41*$B$15/4 -> 1667.5 | AW41: =SUM($AV$3:AV41) -> 51225.888 | AX41: =AR41-AS41-AU41-AW41 -> 484999.11 | AY41: =$B$36*V41 -> 1656 | AZ41: =SUM(AY41:AY41)*4/AR41 -> 0.01142069 | BA41: =SUM(AY41:AY41)/V41 -> 0.35 | BB41: =IF(MortgageRate="Discounted",_xlfn.XLOOKUP(L41,'mortgage-rates'!$A:$A,'mortgage-rates'!$E:$E)/100,_xlfn.XLOOKUP(L41,'mortgage-rates'!$A:$A,'mortgage-rates'!$D:$D)/100) -> 0.0466 | BC41: =BC40-BF40 -> 207033.02 | BD41: =IF($B$16*12/3-Q41+1>0,-PMT($BB41/4,$B$16*12/3-Q41+1,BC41),0) -> 4707.7369 | BE41: =BC41*($BB41/4) -> 2411.9347 | BF41: =BD41-BE41 -> 2295.8022 | BG41: =AT41+AY41+BD41 -> 6363.7369 | BH41: =INDEX(cpi!B:B,MATCH($L41,cpi!A:A)) -> 107.8 | BI41: =100*BH41/BH$3 -> 127.42317 | BJ41: =100*AC41/AC$3 -> 172.41252 | BK41: =100*AD41/AD$3 -> 170.44046 | BL41: =BJ41*GlobalPortfolio+BK41*AusPortfolio -> 171.8209 | BM41: =100*AE41/$AE$3 -> 324.75285 | BN41: =100*AR41/AR$3 -> 175.75758 | BO41: =100*AX41/AX$3 -> 150.79587
A42: % of portfolio in Australian equities | B42: =1-GlobalPortfolio -> 0.3 | C42: 0.3 | L42: =DATE(YEAR(L41),MONTH(L41)+3,1) -> 42339 | M42: =AP42 -> 284422.8 | N42: =AX42-BC42 -> 309330.53 | O42: =M42/N42 -> 0.91947858 | P42: =X42/BG42 -> 0.76051433 | Q42: 40 | R42: =EOMONTH(L42,0)-EOMONTH(L42,-3) -> 92 | T42: =IF($B$10="3BR_H", INDEX('3BR_H-processed'!$C:$D,MATCH($L42,'3BR_H-processed'!$B:$B,0),MATCH(Council_Area,'3BR_H-processed'!$C$1:$D$1,0)), INDEX('2BR_F-processed'!$C:$D,MATCH($L42,'2BR_F-processed'!$B:$B,0),MATCH(Council_Area,'2BR_F-processed'!$C$1:$D$1,0))) -> 370 | U42: =IF(MOD(Q42,4)=1,T42,U41) -> 360 | V42: =U42*(R42)/7 -> 4731.4286 | W42: =$B$53/4*BH42/_xlfn.XLOOKUP(Q_end,cpi!A:A,cpi!B:B) -> 149.68901 | X42: =V42+W42 -> 4881.1176 | Y42: =BG42-X42 -> 1537.062 | Z42: =Y42*$B$47 -> 0 | AA42: {=(Y42+Z42)*eff_invest} -> 1537.062 | AB42: =AA42*(_xlfn.XLOOKUP(Q_end,cpi!A:A,cpi!B:B)/BH42) -> 2053.6738 | AC42: {=INDEX('msci-indices'!C:C,MATCH($L42,'msci-indices'!$B:$B)-2)} -> 1189.2855 | AD42: {=INDEX('msci-indices'!D:D,MATCH($L42,'msci-indices'!$B:$B)-2)} -> 1131.2309 | AE42: =AI41+AA42 -> 269337.13 | AF42: {=INDEX('msci-indices'!C:C,MATCH($L42,'msci-indices'!$B:$B)+1)} -> 1252.6491 | AG42: {=INDEX('msci-indices'!D:D,MATCH($L42,'msci-indices'!$B:$B)+1)} -> 1204.1585 | AH42: =(InvestFees/4)*AE42 -> 168.3357 | AI42: =((AF42/AC42)*GlobalPortfolio+(AG42/AD42)*AusPortfolio)*AE42-AH42 -> 284422.8 | AJ42: =AJ41+AA42 -> 188504.64 | AK42: =AI42-AJ42 -> 95918.157 | AL42: =AJ42*(_xlfn.XLOOKUP(Q_end,cpi!A:A,cpi!B:B)/BH42) -> 251861.69 | AM42: {=SUMPRODUCT($AA$3:AA42,_xlfn.SORTBY($BH$3:BH42,_xlfn.SEQUENCE(ROWS($BH$3:BH42)),-1)/$BH$3)} -> 230415.71 | AN42: =AI42-AM42 -> 54007.088 | AO42: =IF($B$49="Real gains",MAX($B$50*AN42,0),IF($B$49="Discounted nominal gains",MAX($B$50*AK42/2,0),0)) -> 0 | AP42: =AI42-AO42 -> 284422.8 | AR42: =IF($B$10="3BR_H", INDEX('ns-combined'!$C:$D,MATCH($L42,'ns-combined'!$B:$B,0),MATCH(Council_Area,'ns-combined'!$C$1:$D$1,0))*1000, INDEX('s-combined'!$C:$D,MATCH($L42,'s-combined'!$B:$B,0),MATCH(Council_Area,'s-combined'!$C$1:$D$1,0))*1000) -> 612300 | AS42: =AS41+$AS$3 -> 33000 | AT42: 0 | AU42: =SUM($B$28:$B$29)*AR42 -> 12246 | AV42: =AR42*$B$15/4 -> 1760.3625 | AW42: =SUM($AV$3:AV42) -> 52986.25 | AX42: =AR42-AS42-AU42-AW42 -> 514067.75 | AY42: =$B$36*V42 -> 1656 | AZ42: =SUM(AY42:AY42)*4/AR42 -> 0.010818226 | BA42: =SUM(AY42:AY42)/V42 -> 0.35 | BB42: =IF(MortgageRate="Discounted",_xlfn.XLOOKUP(L42,'mortgage-rates'!$A:$A,'mortgage-rates'!$E:$E)/100,_xlfn.XLOOKUP(L42,'mortgage-rates'!$A:$A,'mortgage-rates'!$D:$D)/100) -> 0.0483 | BC42: =BC41-BF41 -> 204737.22 | BD42: =IF($B$16*12/3-Q42+1>0,-PMT($BB42/4,$B$16*12/3-Q42+1,BC42),0) -> 4762.1796 | BE42: =BC42*($BB42/4) -> 2472.202 | BF42: =BD42-BE42 -> 2289.9777 | BG42: =AT42+AY42+BD42 -> 6418.1796 | BH42: =INDEX(cpi!B:B,MATCH($L42,cpi!A:A)) -> 108.3 | BI42: =100*BH42/BH$3 -> 128.01418 | BJ42: =100*AC42/AC$3 -> 157.54638 | BK42: =100*AD42/AD$3 -> 158.66765 | BL42: =BJ42*GlobalPortfolio+BK42*AusPortfolio -> 157.88276 | BM42: =100*AE42/$AE$3 -> 299.93095 | BN42: =100*AR42/AR$3 -> 185.54545 | BO42: =100*AX42/AX$3 -> 159.83389
A43: Investment fees (% of investment value per year) | B43: 0.0025 | C43: 0.0025 | L43: =DATE(YEAR(L42),MONTH(L42)+3,1) -> 42430 | M43: =AP43 -> 282861.82 | N43: =AX43-BC43 -> 265748.51 | O43: =M43/N43 -> 1.0643967 | P43: =X43/BG43 -> 0.78407179 | Q43: 41 | R43: =EOMONTH(L43,0)-EOMONTH(L43,-3) -> 91 | T43: =IF($B$10="3BR_H", INDEX('3BR_H-processed'!$C:$D,MATCH($L43,'3BR_H-processed'!$B:$B,0),MATCH(Council_Area,'3BR_H-processed'!$C$1:$D$1,0)), INDEX('2BR_F-processed'!$C:$D,MATCH($L43,'2BR_F-processed'!$B:$B,0),MATCH(Council_Area,'2BR_F-processed'!$C$1:$D$1,0))) -> 380 | U43: =IF(MOD(Q43,4)=1,T43,U42) -> 380 | V43: =U43*(R43)/7 -> 4940 | W43: =$B$53/4*BH43/_xlfn.XLOOKUP(Q_end,cpi!A:A,cpi!B:B) -> 149.55079 | X43: =V43+W43 -> 5089.5508 | Y43: =BG43-X43 -> 1401.6288 | Z43: =Y43*$B$47 -> 0 | AA43: {=(Y43+Z43)*eff_invest} -> 1401.6288 | AB43: =AA43*(_xlfn.XLOOKUP(Q_end,cpi!A:A,cpi!B:B)/BH43) -> 1874.4518 | AC43: {=INDEX('msci-indices'!C:C,MATCH($L43,'msci-indices'!$B:$B)-2)} -> 1252.6491 | AD43: {=INDEX('msci-indices'!D:D,MATCH($L43,'msci-indices'!$B:$B)-2)} -> 1204.1585 | AE43: =AI42+AA43 -> 285824.42 | AF43: {=INDEX('msci-indices'!C:C,MATCH($L43,'msci-indices'!$B:$B)+1)} -> 1249.9269 | AG43: {=INDEX('msci-indices'!D:D,MATCH($L43,'msci-indices'!$B:$B)+1)} -> 1171.169 | AH43: =(InvestFees/4)*AE43 -> 178.64027 | AI43: =((AF43/AC43)*GlobalPortfolio+(AG43/AD43)*AusPortfolio)*AE43-AH43 -> 282861.82 | AJ43: =AJ42+AA43 -> 189906.27 | AK43: =AI43-AJ43 -> 92955.554 | AL43: =AJ43*(_xlfn.XLOOKUP(Q_end,cpi!A:A,cpi!B:B)/BH43) -> 253968.92 | AM43: {=SUMPRODUCT($AA$3:AA43,_xlfn.SORTBY($BH$3:BH43,_xlfn.SEQUENCE(ROWS($BH$3:BH43)),-1)/$BH$3)} -> 232407.81 | AN43: =AI43-AM43 -> 50454.009 | AO43: =IF($B$49="Real gains",MAX($B$50*AN43,0),IF($B$49="Discounted nominal gains",MAX($B$50*AK43/2,0),0)) -> 0 | AP43: =AI43-AO43 -> 282861.82 | AR43: =IF($B$10="3BR_H", INDEX('ns-combined'!$C:$D,MATCH($L43,'ns-combined'!$B:$B,0),MATCH(Council_Area,'ns-combined'!$C$1:$D$1,0))*1000, INDEX('s-combined'!$C:$D,MATCH($L43,'s-combined'!$B:$B,0),MATCH(Council_Area,'s-combined'!$C$1:$D$1,0))*1000) -> 568000 | AS43: =AS42+$AS$3 -> 33825 | AT43: 0 | AU43: =SUM($B$28:$B$29)*AR43 -> 11360 | AV43: =AR43*$B$15/4 -> 1633 | AW43: =SUM($AV$3:AV43) -> 54619.25 | AX43: =AR43-AS43-AU43-AW43 -> 468195.75 | AY43: =$B$36*V43 -> 1729 | AZ43: =SUM(AY43:AY43)*4/AR43 -> 0.012176056 | BA43: =SUM(AY43:AY43)/V43 -> 0.35 | BB43: =IF(MortgageRate="Discounted",_xlfn.XLOOKUP(L43,'mortgage-rates'!$A:$A,'mortgage-rates'!$E:$E)/100,_xlfn.XLOOKUP(L43,'mortgage-rates'!$A:$A,'mortgage-rates'!$D:$D)/100) -> 0.0483 | BC43: =BC42-BF42 -> 202447.24 | BD43: =IF($B$16*12/3-Q43+1>0,-PMT($BB43/4,$B$16*12/3-Q43+1,BC43),0) -> 4762.1796 | BE43: =BC43*($BB43/4) -> 2444.5505 | BF43: =BD43-BE43 -> 2317.6291 | BG43: =AT43+AY43+BD43 -> 6491.1796 | BH43: =INDEX(cpi!B:B,MATCH($L43,cpi!A:A)) -> 108.2 | BI43: =100*BH43/BH$3 -> 127.89598 | BJ43: =100*AC43/AC$3 -> 165.94025 | BK43: =100*AD43/AD$3 -> 168.89654 | BL43: =BJ43*GlobalPortfolio+BK43*AusPortfolio -> 166.82714 | BM43: =100*AE43/$AE$3 -> 318.29102 | BN43: =100*AR43/AR$3 -> 172.12121 | BO43: =100*AX43/AX$3 -> 145.57137
A44: Investing through superannuation? | B44: No | C44: No | L44: =DATE(YEAR(L43),MONTH(L43)+3,1) -> 42522 | M44: =AP44 -> 289617.74 | N44: =AX44-BC44 -> 306647.38 | O44: =M44/N44 -> 0.94446507 | P44: =X44/BG44 -> 0.79331913 | Q44: 42 | R44: =EOMONTH(L44,0)-EOMONTH(L44,-3) -> 91 | T44: =IF($B$10="3BR_H", INDEX('3BR_H-processed'!$C:$D,MATCH($L44,'3BR_H-processed'!$B:$B,0),MATCH(Council_Area,'3BR_H-processed'!$C$1:$D$1,0)), INDEX('2BR_F-processed'!$C:$D,MATCH($L44,'2BR_F-processed'!$B:$B,0),MATCH(Council_Area,'2BR_F-processed'!$C$1:$D$1,0))) -> 370 | U44: =IF(MOD(Q44,4)=1,T44,U43) -> 380 | V44: =U44*(R44)/7 -> 4940 | W44: =$B$53/4*BH44/_xlfn.XLOOKUP(Q_end,cpi!A:A,cpi!B:B) -> 150.3801 | X44: =V44+W44 -> 5090.3801 | Y44: =BG44-X44 -> 1326.1803 | Z44: =Y44*$B$47 -> 0 | AA44: {=(Y44+Z44)*eff_invest} -> 1326.1803 | AB44: =AA44*(_xlfn.XLOOKUP(Q_end,cpi!A:A,cpi!B:B)/BH44) -> 1763.771 | AC44: {=INDEX('msci-indices'!C:C,MATCH($L44,'msci-indices'!$B:$B)-2)} -> 1249.9269 | AD44: {=INDEX('msci-indices'!D:D,MATCH($L44,'msci-indices'!$B:$B)-2)} -> 1171.169 | AE44: =AI43+AA44 -> 284188 | AF44: {=INDEX('msci-indices'!C:C,MATCH($L44,'msci-indices'!$B:$B)+1)} -> 1263.5195 | AG44: {=INDEX('msci-indices'!D:D,MATCH($L44,'msci-indices'!$B:$B)+1)} -> 1218.4798 | AH44: =(InvestFees/4)*AE44 -> 177.6175 | AI44: =((AF44/AC44)*GlobalPortfolio+(AG44/AD44)*AusPortfolio)*AE44-AH44 -> 289617.74 | AJ44: =AJ43+AA44 -> 191232.45 | AK44: =AI44-AJ44 -> 98385.297 | AL44: =AJ44*(_xlfn.XLOOKUP(Q_end,cpi!A:A,cpi!B:B)/BH44) -> 254332.13 | AM44: {=SUMPRODUCT($AA$3:AA44,_xlfn.SORTBY($BH$3:BH44,_xlfn.SEQUENCE(ROWS($BH$3:BH44)),-1)/$BH$3)} -> 235041.89 | AN44: =AI44-AM44 -> 54575.856 | AO44: =IF($B$49="Real gains",MAX($B$50*AN44,0),IF($B$49="Discounted nominal gains",MAX($B$50*AK44/2,0),0)) -> 0 | AP44: =AI44-AO44 -> 289617.74 | AR44: =IF($B$10="3BR_H", INDEX('ns-combined'!$C:$D,MATCH($L44,'ns-combined'!$B:$B,0),MATCH(Council_Area,'ns-combined'!$C$1:$D$1,0))*1000, INDEX('s-combined'!$C:$D,MATCH($L44,'s-combined'!$B:$B,0),MATCH(Council_Area,'s-combined'!$C$1:$D$1,0))*1000) -> 610000 | AS44: =AS43+$AS$3 -> 34650 | AT44: 0 | AU44: =SUM($B$28:$B$29)*AR44 -> 12200 | AV44: =AR44*$B$15/4 -> 1753.75 | AW44: =SUM($AV$3:AV44) -> 56373 | AX44: =AR44-AS44-AU44-AW44 -> 506777 | AY44: =$B$36*V44 -> 1729 | AZ44: =SUM(AY44:AY44)*4/AR44 -> 0.011337705 | BA44: =SUM(AY44:AY44)/V44 -> 0.35 | BB44: =IF(MortgageRate="Discounted",_xlfn.XLOOKUP(L44,'mortgage-rates'!$A:$A,'mortgage-rates'!$E:$E)/100,_xlfn.XLOOKUP(L44,'mortgage-rates'!$A:$A,'mortgage-rates'!$D:$D)/100) -> 0.0459 | BC44: =BC43-BF43 -> 200129.62 | BD44: =IF($B$16*12/3-Q44+1>0,-PMT($BB44/4,$B$16*12/3-Q44+1,BC44),0) -> 4687.5604 | BE44: =BC44*($BB44/4) -> 2296.4873 | BF44: =BD44-BE44 -> 2391.0731 | BG44: =AT44+AY44+BD44 -> 6416.5604 | BH44: =INDEX(cpi!B:B,MATCH($L44,cpi!A:A)) -> 108.8 | BI44: =100*BH44/BH$3 -> 128.6052 | BJ44: =100*AC44/AC$3 -> 165.57963 | BK44: =100*AD44/AD$3 -> 164.26941 | BL44: =BJ44*GlobalPortfolio+BK44*AusPortfolio -> 165.18657 | BM44: =100*AE44/$AE$3 -> 316.46872 | BN44: =100*AR44/AR$3 -> 184.84848 | BO44: =100*AX44/AX$3 -> 157.56705
A45: Marginal income tax rate (including Medicare levy) | B45: 0.32 | C45: 0.32 | L45: =DATE(YEAR(L44),MONTH(L44)+3,1) -> 42614 | M45: =AP45 -> 305984.91 | N45: =AX45-BC45 -> 301574.08 | O45: =M45/N45 -> 1.014626 | P45: =X45/BG45 -> 0.80255806 | Q45: 43 | R45: =EOMONTH(L45,0)-EOMONTH(L45,-3) -> 92 | T45: =IF($B$10="3BR_H", INDEX('3BR_H-processed'!$C:$D,MATCH($L45,'3BR_H-processed'!$B:$B,0),MATCH(Council_Area,'3BR_H-processed'!$C$1:$D$1,0)), INDEX('2BR_F-processed'!$C:$D,MATCH($L45,'2BR_F-processed'!$B:$B,0),MATCH(Council_Area,'2BR_F-processed'!$C$1:$D$1,0))) -> 375 | U45: =IF(MOD(Q45,4)=1,T45,U44) -> 380 | V45: =U45*(R45)/7 -> 4994.2857 | W45: =$B$53/4*BH45/_xlfn.XLOOKUP(Q_end,cpi!A:A,cpi!B:B) -> 151.07118 | X45: =V45+W45 -> 5145.3569 | Y45: =BG45-X45 -> 1265.839 | Z45: =Y45*$B$47 -> 0 | AA45: {=(Y45+Z45)*eff_invest} -> 1265.839 | AB45: =AA45*(_xlfn.XLOOKUP(Q_end,cpi!A:A,cpi!B:B)/BH45) -> 1675.8179 | AC45: {=INDEX('msci-indices'!C:C,MATCH($L45,'msci-indices'!$B:$B)-2)} -> 1263.5195 | AD45: {=INDEX('msci-indices'!D:D,MATCH($L45,'msci-indices'!$B:$B)-2)} -> 1218.4798 | AE45: =AI44+AA45 -> 290883.58 | AF45: {=INDEX('msci-indices'!C:C,MATCH($L45,'msci-indices'!$B:$B)+1)} -> 1329.0259 | AG45: {=INDEX('msci-indices'!D:D,MATCH($L45,'msci-indices'!$B:$B)+1)} -> 1284.478 | AH45: =(InvestFees/4)*AE45 -> 181.80224 | AI45: =((AF45/AC45)*GlobalPortfolio+(AG45/AD45)*AusPortfolio)*AE45-AH45 -> 305984.91 | AJ45: =AJ44+AA45 -> 192498.29 | AK45: =AI45-AJ45 -> 113486.63 | AL45: =AJ45*(_xlfn.XLOOKUP(Q_end,cpi!A:A,cpi!B:B)/BH45) -> 254844.48 | AM45: {=SUMPRODUCT($AA$3:AA45,_xlfn.SORTBY($BH$3:BH45,_xlfn.SEQUENCE(ROWS($BH$3:BH45)),-1)/$BH$3)} -> 237508.44 | AN45: =AI45-AM45 -> 68476.469 | AO45: =IF($B$49="Real gains",MAX($B$50*AN45,0),IF($B$49="Discounted nominal gains",MAX($B$50*AK45/2,0),0)) -> 0 | AP45: =AI45-AO45 -> 305984.91 | AR45: =IF($B$10="3BR_H", INDEX('ns-combined'!$C:$D,MATCH($L45,'ns-combined'!$B:$B,0),MATCH(Council_Area,'ns-combined'!$C$1:$D$1,0))*1000, INDEX('s-combined'!$C:$D,MATCH($L45,'s-combined'!$B:$B,0),MATCH(Council_Area,'s-combined'!$C$1:$D$1,0))*1000) -> 605000 | AS45: =AS44+$AS$3 -> 35475 | AT45: 0 | AU45: =SUM($B$28:$B$29)*AR45 -> 12100 | AV45: =AR45*$B$15/4 -> 1739.375 | AW45: =SUM($AV$3:AV45) -> 58112.375 | AX45: =AR45-AS45-AU45-AW45 -> 499312.62 | AY45: =$B$36*V45 -> 1748 | AZ45: =SUM(AY45:AY45)*4/AR45 -> 0.011557025 | BA45: =SUM(AY45:AY45)/V45 -> 0.35 | BB45: =IF(MortgageRate="Discounted",_xlfn.XLOOKUP(L45,'mortgage-rates'!$A:$A,'mortgage-rates'!$E:$E)/100,_xlfn.XLOOKUP(L45,'mortgage-rates'!$A:$A,'mortgage-rates'!$D:$D)/100) -> 0.0451 | BC45: =BC44-BF44 -> 197738.54 | BD45: =IF($B$16*12/3-Q45+1>0,-PMT($BB45/4,$B$16*12/3-Q45+1,BC45),0) -> 4663.1959 | BE45: =BC45*($BB45/4) -> 2229.5021 | BF45: =BD45-BE45 -> 2433.6938 | BG45: =AT45+AY45+BD45 -> 6411.1959 | BH45: =INDEX(cpi!B:B,MATCH($L45,cpi!A:A)) -> 109.3 | BI45: =100*BH45/BH$3 -> 129.19622 | BJ45: =100*AC45/AC$3 -> 167.38027 | BK45: =100*AD45/AD$3 -> 170.90526 | BL45: =BJ45*GlobalPortfolio+BK45*AusPortfolio -> 168.43777 | BM45: =100*AE45/$AE$3 -> 323.92485 | BN45: =100*AR45/AR$3 -> 183.33333 | BO45: =100*AX45/AX$3 -> 155.24623
A46: Concessional super contributions tax rate | B46: 0.15 | C46: 0.15 | L46: =DATE(YEAR(L45),MONTH(L45)+3,1) -> 42705 | M46: =AP46 -> 316468.29 | N46: =AX46-BC46 -> 369842.15 | O46: =M46/N46 -> 0.85568475 | P46: =X46/BG46 -> 0.80266585 | Q46: 44 | R46: =EOMONTH(L46,0)-EOMONTH(L46,-3) -> 92 | T46: =IF($B$10="3BR_H", INDEX('3BR_H-processed'!$C:$D,MATCH($L46,'3BR_H-processed'!$B:$B,0),MATCH(Council_Area,'3BR_H-processed'!$C$1:$D$1,0)), INDEX('2BR_F-processed'!$C:$D,MATCH($L46,'2BR_F-processed'!$B:$B,0),MATCH(Council_Area,'2BR_F-processed'!$C$1:$D$1,0))) -> 380 | U46: =IF(MOD(Q46,4)=1,T46,U45) -> 380 | V46: =U46*(R46)/7 -> 4994.2857 | W46: =$B$53/4*BH46/_xlfn.XLOOKUP(Q_end,cpi!A:A,cpi!B:B) -> 151.76227 | X46: =V46+W46 -> 5146.048 | Y46: =BG46-X46 -> 1265.1479 | Z46: =Y46*$B$47 -> 0 | AA46: {=(Y46+Z46)*eff_invest} -> 1265.1479 | AB46: =AA46*(_xlfn.XLOOKUP(Q_end,cpi!A:A,cpi!B:B)/BH46) -> 1667.2759 | AC46: {=INDEX('msci-indices'!C:C,MATCH($L46,'msci-indices'!$B:$B)-2)} -> 1329.0259 | AD46: {=INDEX('msci-indices'!D:D,MATCH($L46,'msci-indices'!$B:$B)-2)} -> 1284.478 | AE46: =AI45+AA46 -> 307250.06 | AF46: {=INDEX('msci-indices'!C:C,MATCH($L46,'msci-indices'!$B:$B)+1)} -> 1355.3009 | AG46: {=INDEX('msci-indices'!D:D,MATCH($L46,'msci-indices'!$B:$B)+1)} -> 1356.3585 | AH46: =(InvestFees/4)*AE46 -> 192.03129 | AI46: =((AF46/AC46)*GlobalPortfolio+(AG46/AD46)*AusPortfolio)*AE46-AH46 -> 316468.29 | AJ46: =AJ45+AA46 -> 193763.44 | AK46: =AI46-AJ46 -> 122704.85 | AL46: =AJ46*(_xlfn.XLOOKUP(Q_end,cpi!A:A,cpi!B:B)/BH46) -> 255351.27 | AM46: {=SUMPRODUCT($AA$3:AA46,_xlfn.SORTBY($BH$3:BH46,_xlfn.SEQUENCE(ROWS($BH$3:BH46)),-1)/$BH$3)} -> 239969.45 | AN46: =AI46-AM46 -> 76498.836 | AO46: =IF($B$49="Real gains",MAX($B$50*AN46,0),IF($B$49="Discounted nominal gains",MAX($B$50*AK46/2,0),0)) -> 0 | AP46: =AI46-AO46 -> 316468.29 | AR46: =IF($B$10="3BR_H", INDEX('ns-combined'!$C:$D,MATCH($L46,'ns-combined'!$B:$B,0),MATCH(Council_Area,'ns-combined'!$C$1:$D$1,0))*1000, INDEX('s-combined'!$C:$D,MATCH($L46,'s-combined'!$B:$B,0),MATCH(Council_Area,'s-combined'!$C$1:$D$1,0))*1000) -> 675000 | AS46: =AS45+$AS$3 -> 36300 | AT46: 0 | AU46: =SUM($B$28:$B$29)*AR46 -> 13500 | AV46: =AR46*$B$15/4 -> 1940.625 | AW46: =SUM($AV$3:AV46) -> 60053 | AX46: =AR46-AS46-AU46-AW46 -> 565147 | AY46: =$B$36*V46 -> 1748 | AZ46: =SUM(AY46:AY46)*4/AR46 -> 0.010358519 | BA46: =SUM(AY46:AY46)/V46 -> 0.35 | BB46: =IF(MortgageRate="Discounted",_xlfn.XLOOKUP(L46,'mortgage-rates'!$A:$A,'mortgage-rates'!$E:$E)/100,_xlfn.XLOOKUP(L46,'mortgage-rates'!$A:$A,'mortgage-rates'!$D:$D)/100) -> 0.0451 | BC46: =BC45-BF45 -> 195304.85 | BD46: =IF($B$16*12/3-Q46+1>0,-PMT($BB46/4,$B$16*12/3-Q46+1,BC46),0) -> 4663.1959 | BE46: =BC46*($BB46/4) -> 2202.0622 | BF46: =BD46-BE46 -> 2461.1337 | BG46: =AT46+AY46+BD46 -> 6411.1959 | BH46: =INDEX(cpi!B:B,MATCH($L46,cpi!A:A)) -> 109.8 | BI46: =100*BH46/BH$3 -> 129.78723 | BJ46: =100*AC46/AC$3 -> 176.05799 | BK46: =100*AD46/AD$3 -> 180.16225 | BL46: =BJ46*GlobalPortfolio+BK46*AusPortfolio -> 177.28927 | BM46: =100*AE46/$AE$3 -> 342.15039 | BN46: =100*AR46/AR$3 -> 204.54545 | BO46: =100*AX46/AX$3 -> 175.71545
A47: Tax concessions on contributions (0% if not investing through super) | B47: =IF(B44="Yes",B45-B46,0) -> 0 | C47: 0 | L47: =DATE(YEAR(L46),MONTH(L46)+3,1) -> 42795 | M47: =AP47 -> 336121.71 | N47: =AX47-BC47 -> 352437.97 | O47: =M47/N47 -> 0.95370457 | P47: =X47/BG47 -> 0.80431766 | Q47: 45 | R47: =EOMONTH(L47,0)-EOMONTH(L47,-3) -> 90 | T47: =IF($B$10="3BR_H", INDEX('3BR_H-processed'!$C:$D,MATCH($L47,'3BR_H-processed'!$B:$B,0),MATCH(Council_Area,'3BR_H-processed'!$C$1:$D$1,0)), INDEX('2BR_F-processed'!$C:$D,MATCH($L47,'2BR_F-processed'!$B:$B,0),MATCH(Council_Area,'2BR_F-processed'!$C$1:$D$1,0))) -> 390 | U47: =IF(MOD(Q47,4)=1,T47,U46) -> 390 | V47: =U47*(R47)/7 -> 5014.2857 | W47: =$B$53/4*BH47/_xlfn.XLOOKUP(Q_end,cpi!A:A,cpi!B:B) -> 152.72979 | X47: =V47+W47 -> 5167.0155 | Y47: =BG47-X47 -> 1257.0825 | Z47: =Y47*$B$47 -> 0 | AA47: {=(Y47+Z47)*eff_invest} -> 1257.0825 | AB47: =AA47*(_xlfn.XLOOKUP(Q_end,cpi!A:A,cpi!B:B)/BH47) -> 1646.1524 | AC47: {=INDEX('msci-indices'!C:C,MATCH($L47,'msci-indices'!$B:$B)-2)} -> 1355.3009 | AD47: {=INDEX('msci-indices'!D:D,MATCH($L47,'msci-indices'!$B:$B)-2)} -> 1356.3585 | AE47: =AI46+AA47 -> 317725.37 | AF47: {=INDEX('msci-indices'!C:C,MATCH($L47,'msci-indices'!$B:$B)+1)} -> 1439.618 | AG47: {=INDEX('msci-indices'!D:D,MATCH($L47,'msci-indices'!$B:$B)+1)} -> 1424.0685 | AH47: =(InvestFees/4)*AE47 -> 198.57836 | AI47: =((AF47/AC47)*GlobalPortfolio+(AG47/AD47)*AusPortfolio)*AE47-AH47 -> 336121.71 | AJ47: =AJ46+AA47 -> 195020.52 | AK47: =AI47-AJ47 -> 141101.19 | AL47: =AJ47*(_xlfn.XLOOKUP(Q_end,cpi!A:A,cpi!B:B)/BH47) -> 255379.81 | AM47: {=SUMPRODUCT($AA$3:AA47,_xlfn.SORTBY($BH$3:BH47,_xlfn.SEQUENCE(ROWS($BH$3:BH47)),-1)/$BH$3)} -> 242636.83 | AN47: =AI47-AM47 -> 93484.879 | AO47: =IF($B$49="Real gains",MAX($B$50*AN47,0),IF($B$49="Discounted nominal gains",MAX($B$50*AK47/2,0),0)) -> 0 | AP47: =AI47-AO47 -> 336121.71 | AR47: =IF($B$10="3BR_H", INDEX('ns-combined'!$C:$D,MATCH($L47,'ns-combined'!$B:$B,0),MATCH(Council_Area,'ns-combined'!$C$1:$D$1,0))*1000, INDEX('s-combined'!$C:$D,MATCH($L47,'s-combined'!$B:$B,0),MATCH(Council_Area,'s-combined'!$C$1:$D$1,0))*1000) -> 657500 | AS47: =AS46+$AS$3 -> 37125 | AT47: 0 | AU47: =SUM($B$28:$B$29)*AR47 -> 13150 | AV47: =AR47*$B$15/4 -> 1890.3125 | AW47: =SUM($AV$3:AV47) -> 61943.313 | AX47: =AR47-AS47-AU47-AW47 -> 545281.69 | AY47: =$B$36*V47 -> 1755 | AZ47: =SUM(AY47:AY47)*4/AR47 -> 0.010676806 | BA47: =SUM(AY47:AY47)/V47 -> 0.35 | BB47: =IF(MortgageRate="Discounted",_xlfn.XLOOKUP(L47,'mortgage-rates'!$A:$A,'mortgage-rates'!$E:$E)/100,_xlfn.XLOOKUP(L47,'mortgage-rates'!$A:$A,'mortgage-rates'!$D:$D)/100) -> 0.0453 | BC47: =BC46-BF46 -> 192843.71 | BD47: =IF($B$16*12/3-Q47+1>0,-PMT($BB47/4,$B$16*12/3-Q47+1,BC47),0) -> 4669.098 | BE47: =BC47*($BB47/4) -> 2183.9551 | BF47: =BD47-BE47 -> 2485.1429 | BG47: =AT47+AY47+BD47 -> 6424.098 | BH47: =INDEX(cpi!B:B,MATCH($L47,cpi!A:A)) -> 110.5 | BI47: =100*BH47/BH$3 -> 130.61466 | BJ47: =100*AC47/AC$3 -> 179.53868 | BK47: =100*AD47/AD$3 -> 190.24428 | BL47: =BJ47*GlobalPortfolio+BK47*AusPortfolio -> 182.75036 | BM47: =100*AE47/$AE$3 -> 353.81558 | BN47: =100*AR47/AR$3 -> 199.24242 | BO47: =100*AX47/AX$3 -> 169.53893
A48: Marginal income tax rate on withdrawal | B48: 0.32 | C48: 0.32 | L48: =DATE(YEAR(L47),MONTH(L47)+3,1) -> 42887 | M48: =AP48 -> 344757.92 | N48: =AX48-BC48 -> 413278.12 | O48: =M48/N48 -> 0.83420318 | P48: =X48/BG48 -> 0.81244643 | Q48: 46 | R48: =EOMONTH(L48,0)-EOMONTH(L48,-3) -> 91 | T48: =IF($B$10="3BR_H", INDEX('3BR_H-processed'!$C:$D,MATCH($L48,'3BR_H-processed'!$B:$B,0),MATCH(Council_Area,'3BR_H-processed'!$C$1:$D$1,0)), INDEX('2BR_F-processed'!$C:$D,MATCH($L48,'2BR_F-processed'!$B:$B,0),MATCH(Council_Area,'2BR_F-processed'!$C$1:$D$1,0))) -> 380 | U48: =IF(MOD(Q48,4)=1,T48,U47) -> 390 | V48: =U48*(R48)/7 -> 5070 | W48: =$B$53/4*BH48/_xlfn.XLOOKUP(Q_end,cpi!A:A,cpi!B:B) -> 153.28265 | X48: =V48+W48 -> 5223.2827 | Y48: =BG48-X48 -> 1205.7968 | Z48: =Y48*$B$47 -> 0 | AA48: {=(Y48+Z48)*eff_invest} -> 1205.7968 | AB48: =AA48*(_xlfn.XLOOKUP(Q_end,cpi!A:A,cpi!B:B)/BH48) -> 1573.2984 | AC48: {=INDEX('msci-indices'!C:C,MATCH($L48,'msci-indices'!$B:$B)-2)} -> 1439.618 | AD48: {=INDEX('msci-indices'!D:D,MATCH($L48,'msci-indices'!$B:$B)-2)} -> 1424.0685 | AE48: =AI47+AA48 -> 337327.5 | AF48: {=INDEX('msci-indices'!C:C,MATCH($L48,'msci-indices'!$B:$B)+1)} -> 1498.0163 | AG48: {=INDEX('msci-indices'!D:D,MATCH($L48,'msci-indices'!$B:$B)+1)} -> 1396.8057 | AH48: =(InvestFees/4)*AE48 -> 210.82969 | AI48: =((AF48/AC48)*GlobalPortfolio+(AG48/AD48)*AusPortfolio)*AE48-AH48 -> 344757.92 | AJ48: =AJ47+AA48 -> 196226.31 | AK48: =AI48-AJ48 -> 148531.6 | AL48: =AJ48*(_xlfn.XLOOKUP(Q_end,cpi!A:A,cpi!B:B)/BH48) -> 256031.99 | AM48: {=SUMPRODUCT($AA$3:AA48,_xlfn.SORTBY($BH$3:BH48,_xlfn.SEQUENCE(ROWS($BH$3:BH48)),-1)/$BH$3)} -> 244952.33 | AN48: =AI48-AM48 -> 99805.587 | AO48: =IF($B$49="Real gains",MAX($B$50*AN48,0),IF($B$49="Discounted nominal gains",MAX($B$50*AK48/2,0),0)) -> 0 | AP48: =AI48-AO48 -> 344757.92 | AR48: =IF($B$10="3BR_H", INDEX('ns-combined'!$C:$D,MATCH($L48,'ns-combined'!$B:$B,0),MATCH(Council_Area,'ns-combined'!$C$1:$D$1,0))*1000, INDEX('s-combined'!$C:$D,MATCH($L48,'s-combined'!$B:$B,0),MATCH(Council_Area,'s-combined'!$C$1:$D$1,0))*1000) -> 720000 | AS48: =AS47+$AS$3 -> 37950 | AT48: 0 | AU48: =SUM($B$28:$B$29)*AR48 -> 14400 | AV48: =AR48*$B$15/4 -> 2070 | AW48: =SUM($AV$3:AV48) -> 64013.313 | AX48: =AR48-AS48-AU48-AW48 -> 603636.69 | AY48: =$B$36*V48 -> 1774.5 | AZ48: =SUM(AY48:AY48)*4/AR48 -> 0.0098583333 | BA48: =SUM(AY48:AY48)/V48 -> 0.35 | BB48: =IF(MortgageRate="Discounted",_xlfn.XLOOKUP(L48,'mortgage-rates'!$A:$A,'mortgage-rates'!$E:$E)/100,_xlfn.XLOOKUP(L48,'mortgage-rates'!$A:$A,'mortgage-rates'!$D:$D)/100) -> 0.0448 | BC48: =BC47-BF47 -> 190358.57 | BD48: =IF($B$16*12/3-Q48+1>0,-PMT($BB48/4,$B$16*12/3-Q48+1,BC48),0) -> 4654.5794 | BE48: =BC48*($BB48/4) -> 2132.016 | BF48: =BD48-BE48 -> 2522.5634 | BG48: =AT48+AY48+BD48 -> 6429.0794 | BH48: =INDEX(cpi!B:B,MATCH($L48,cpi!A:A)) -> 110.9 | BI48: =100*BH48/BH$3 -> 131.08747 | BJ48: =100*AC48/AC$3 -> 190.70829 | BK48: =100*AD48/AD$3 -> 199.74136 | BL48: =BJ48*GlobalPortfolio+BK48*AusPortfolio -> 193.41821 | BM48: =100*AE48/$AE$3 -> 375.6443 | BN48: =100*AR48/AR$3 -> 218.18182 | BO48: =100*AX48/AX$3 -> 187.68266
A49: Consider CGT? Note: Unlikely to reflect realistic tax liabilities | B49: No | C49: No | L49: =DATE(YEAR(L48),MONTH(L48)+3,1) -> 42979 | M49: =AP49 -> 358937.67 | N49: =AX49-BC49 -> 385546.18 | O49: =M49/N49 -> 0.93098491 | P49: =X49/BG49 -> 0.81907775 | Q49: 47 | R49: =EOMONTH(L49,0)-EOMONTH(L49,-3) -> 92 | T49: =IF($B$10="3BR_H", INDEX('3BR_H-processed'!$C:$D,MATCH($L49,'3BR_H-processed'!$B:$B,0),MATCH(Council_Area,'3BR_H-processed'!$C$1:$D$1,0)), INDEX('2BR_F-processed'!$C:$D,MATCH($L49,'2BR_F-processed'!$B:$B,0),MATCH(Council_Area,'2BR_F-processed'!$C$1:$D$1,0))) -> 385 | U49: =IF(MOD(Q49,4)=1,T49,U48) -> 390 | V49: =U49*(R49)/7 -> 5125.7143 | W49: =$B$53/4*BH49/_xlfn.XLOOKUP(Q_end,cpi!A:A,cpi!B:B) -> 153.83552 | X49: =V49+W49 -> 5279.5498 | Y49: =BG49-X49 -> 1166.175 | Z49: =Y49*$B$47 -> 0 | AA49: {=(Y49+Z49)*eff_invest} -> 1166.175 | AB49: =AA49*(_xlfn.XLOOKUP(Q_end,cpi!A:A,cpi!B:B)/BH49) -> 1516.1323 | AC49: {=INDEX('msci-indices'!C:C,MATCH($L49,'msci-indices'!$B:$B)-2)} -> 1498.0163 | AD49: {=INDEX('msci-indices'!D:D,MATCH($L49,'msci-indices'!$B:$B)-2)} -> 1396.8057 | AE49: =AI48+AA49 -> 345924.09 | AF49: {=INDEX('msci-indices'!C:C,MATCH($L49,'msci-indices'!$B:$B)+1)} -> 1573.3489 | AG49: {=INDEX('msci-indices'!D:D,MATCH($L49,'msci-indices'!$B:$B)+1)} -> 1410.974 | AH49: =(InvestFees/4)*AE49 -> 216.20256 | AI49: =((AF49/AC49)*GlobalPortfolio+(AG49/AD49)*AusPortfolio)*AE49-AH49 -> 358937.67 | AJ49: =AJ48+AA49 -> 197392.49 | AK49: =AI49-AJ49 -> 161545.18 | AL49: =AJ49*(_xlfn.XLOOKUP(Q_end,cpi!A:A,cpi!B:B)/BH49) -> 256627.97 | AM49: {=SUMPRODUCT($AA$3:AA49,_xlfn.SORTBY($BH$3:BH49,_xlfn.SEQUENCE(ROWS($BH$3:BH49)),-1)/$BH$3)} -> 247234.82 | AN49: =AI49-AM49 -> 111702.85 | AO49: =IF($B$49="Real gains",MAX($B$50*AN49,0),IF($B$49="Discounted nominal gains",MAX($B$50*AK49/2,0),0)) -> 0 | AP49: =AI49-AO49 -> 358937.67 | AR49: =IF($B$10="3BR_H", INDEX('ns-combined'!$C:$D,MATCH($L49,'ns-combined'!$B:$B,0),MATCH(Council_Area,'ns-combined'!$C$1:$D$1,0))*1000, INDEX('s-combined'!$C:$D,MATCH($L49,'s-combined'!$B:$B,0),MATCH(Council_Area,'s-combined'!$C$1:$D$1,0))*1000) -> 692000 | AS49: =AS48+$AS$3 -> 38775 | AT49: 0 | AU49: =SUM($B$28:$B$29)*AR49 -> 13840 | AV49: =AR49*$B$15/4 -> 1989.5 | AW49: =SUM($AV$3:AV49) -> 66002.812 | AX49: =AR49-AS49-AU49-AW49 -> 573382.19 | AY49: =$B$36*V49 -> 1794 | AZ49: =SUM(AY49:AY49)*4/AR49 -> 0.010369942 | BA49: =SUM(AY49:AY49)/V49 -> 0.35 | BB49: =IF(MortgageRate="Discounted",_xlfn.XLOOKUP(L49,'mortgage-rates'!$A:$A,'mortgage-rates'!$E:$E)/100,_xlfn.XLOOKUP(L49,'mortgage-rates'!$A:$A,'mortgage-rates'!$D:$D)/100) -> 0.0447 | BC49: =BC48-BF48 -> 187836.01 | BD49: =IF($B$16*12/3-Q49+1>0,-PMT($BB49/4,$B$16*12/3-Q49+1,BC49),0) -> 4651.7248 | BE49: =BC49*($BB49/4) -> 2099.0674 | BF49: =BD49-BE49 -> 2552.6574 | BG49: =AT49+AY49+BD49 -> 6445.7248 | BH49: =INDEX(cpi!B:B,MATCH($L49,cpi!A:A)) -> 111.3 | BI49: =100*BH49/BH$3 -> 131.56028 | BJ49: =100*AC49/AC$3 -> 198.4444 | BK49: =100*AD49/AD$3 -> 195.91744 | BL49: =BJ49*GlobalPortfolio+BK49*AusPortfolio -> 197.68631 | BM49: =100*AE49/$AE$3 -> 385.21737 | BN49: =100*AR49/AR$3 -> 209.69697 | BO49: =100*AX49/AX$3 -> 178.27593
A50: Marginal CGT & dividend income tax rate (0% if investing through super) | B50: =IF(OR(B44="Yes",B49="No"),0,MAX(0.3,B48)) -> 0 | C50: 0 | L50: =DATE(YEAR(L49),MONTH(L49)+3,1) -> 43070 | M50: =AP50 -> 382133.38 | N50: =AX50-BC50 -> 441957.59 | O50: =M50/N50 -> 0.86463812 | P50: =X50/BG50 -> 0.81782329 | Q50: 48 | R50: =EOMONTH(L50,0)-EOMONTH(L50,-3) -> 92 | T50: =IF($B$10="3BR_H", INDEX('3BR_H-processed'!$C:$D,MATCH($L50,'3BR_H-processed'!$B:$B,0),MATCH(Council_Area,'3BR_H-processed'!$C$1:$D$1,0)), INDEX('2BR_F-processed'!$C:$D,MATCH($L50,'2BR_F-processed'!$B:$B,0),MATCH(Council_Area,'2BR_F-processed'!$C$1:$D$1,0))) -> 395 | U50: =IF(MOD(Q50,4)=1,T50,U49) -> 390 | V50: =U50*(R50)/7 -> 5125.7143 | W50: =$B$53/4*BH50/_xlfn.XLOOKUP(Q_end,cpi!A:A,cpi!B:B) -> 154.94126 | X50: =V50+W50 -> 5280.6555 | Y50: =BG50-X50 -> 1176.3085 | Z50: =Y50*$B$47 -> 0 | AA50: {=(Y50+Z50)*eff_invest} -> 1176.3085 | AB50: =AA50*(_xlfn.XLOOKUP(Q_end,cpi!A:A,cpi!B:B)/BH50) -> 1518.3928 | AC50: {=INDEX('msci-indices'!C:C,MATCH($L50,'msci-indices'!$B:$B)-2)} -> 1573.3489 | AD50: {=INDEX('msci-indices'!D:D,MATCH($L50,'msci-indices'!$B:$B)-2)} -> 1410.974 | AE50: =AI49+AA50 -> 360113.98 | AF50: {=INDEX('msci-indices'!C:C,MATCH($L50,'msci-indices'!$B:$B)+1)} -> 1659.3666 | AG50: {=INDEX('msci-indices'!D:D,MATCH($L50,'msci-indices'!$B:$B)+1)} -> 1521.5021 | AH50: =(InvestFees/4)*AE50 -> 225.07124 | AI50: =((AF50/AC50)*GlobalPortfolio+(AG50/AD50)*AusPortfolio)*AE50-AH50 -> 382133.38 | AJ50: =AJ49+AA50 -> 198568.8 | AK50: =AI50-AJ50 -> 183564.58 | AL50: =AJ50*(_xlfn.XLOOKUP(Q_end,cpi!A:A,cpi!B:B)/BH50) -> 256314.94 | AM50: {=SUMPRODUCT($AA$3:AA50,_xlfn.SORTBY($BH$3:BH50,_xlfn.SEQUENCE(ROWS($BH$3:BH50)),-1)/$BH$3)} -> 249957.56 | AN50: =AI50-AM50 -> 132175.82 | AO50: =IF($B$49="Real gains",MAX($B$50*AN50,0),IF($B$49="Discounted nominal gains",MAX($B$50*AK50/2,0),0)) -> 0 | AP50: =AI50-AO50 -> 382133.38 | AR50: =IF($B$10="3BR_H", INDEX('ns-combined'!$C:$D,MATCH($L50,'ns-combined'!$B:$B,0),MATCH(Council_Area,'ns-combined'!$C$1:$D$1,0))*1000, INDEX('s-combined'!$C:$D,MATCH($L50,'s-combined'!$B:$B,0),MATCH(Council_Area,'s-combined'!$C$1:$D$1,0))*1000) -> 750000 | AS50: =AS49+$AS$3 -> 39600 | AT50: 0 | AU50: =SUM($B$28:$B$29)*AR50 -> 15000 | AV50: =AR50*$B$15/4 -> 2156.25 | AW50: =SUM($AV$3:AV50) -> 68159.062 | AX50: =AR50-AS50-AU50-AW50 -> 627240.94 | AY50: =$B$36*V50 -> 1794 | AZ50: =SUM(AY50:AY50)*4/AR50 -> 0.009568 | BA50: =SUM(AY50:AY50)/V50 -> 0.35 | BB50: =IF(MortgageRate="Discounted",_xlfn.XLOOKUP(L50,'mortgage-rates'!$A:$A,'mortgage-rates'!$E:$E)/100,_xlfn.XLOOKUP(L50,'mortgage-rates'!$A:$A,'mortgage-rates'!$D:$D)/100) -> 0.0451 | BC50: =BC49-BF49 -> 185283.35 | BD50: =IF($B$16*12/3-Q50+1>0,-PMT($BB50/4,$B$16*12/3-Q50+1,BC50),0) -> 4662.964 | BE50: =BC50*($BB50/4) -> 2089.0698 | BF50: =BD50-BE50 -> 2573.8942 | BG50: =AT50+AY50+BD50 -> 6456.964 | BH50: =INDEX(cpi!B:B,MATCH($L50,cpi!A:A)) -> 112.1 | BI50: =100*BH50/BH$3 -> 132.50591 | BJ50: =100*AC50/AC$3 -> 208.42381 | BK50: =100*AD50/AD$3 -> 197.90471 | BL50: =BJ50*GlobalPortfolio+BK50*AusPortfolio -> 205.26808 | BM50: =100*AE50/$AE$3 -> 401.01908 | BN50: =100*AR50/AR$3 -> 227.27273 | BO50: =100*AX50/AX$3 -> 195.02169
L51: =DATE(YEAR(L50),MONTH(L50)+3,1) -> 43160 | M51: =AP51 -> 375310.05 | N51: =AX51-BC51 -> 422984.86 | O51: =M51/N51 -> 0.88728956 | P51: =X51/BG51 -> 0.81984484 | Q51: 49 | R51: =EOMONTH(L51,0)-EOMONTH(L51,-3) -> 90 | T51: =IF($B$10="3BR_H", INDEX('3BR_H-processed'!$C:$D,MATCH($L51,'3BR_H-processed'!$B:$B,0),MATCH(Council_Area,'3BR_H-processed'!$C$1:$D$1,0)), INDEX('2BR_F-processed'!$C:$D,MATCH($L51,'2BR_F-processed'!$B:$B,0),MATCH(Council_Area,'2BR_F-processed'!$C$1:$D$1,0))) -> 400 | U51: =IF(MOD(Q51,4)=1,T51,U50) -> 400 | V51: =U51*(R51)/7 -> 5142.8571 | W51: =$B$53/4*BH51/_xlfn.XLOOKUP(Q_end,cpi!A:A,cpi!B:B) -> 155.77056 | X51: =V51+W51 -> 5298.6277 | Y51: =BG51-X51 -> 1164.3363 | Z51: =Y51*$B$47 -> 0 | AA51: {=(Y51+Z51)*eff_invest} -> 1164.3363 | AB51: =AA51*(_xlfn.XLOOKUP(Q_end,cpi!A:A,cpi!B:B)/BH51) -> 1494.9376 | AC51: {=INDEX('msci-indices'!C:C,MATCH($L51,'msci-indices'!$B:$B)-2)} -> 1659.3666 | AD51: {=INDEX('msci-indices'!D:D,MATCH($L51,'msci-indices'!$B:$B)-2)} -> 1521.5021 | AE51: =AI50+AA51 -> 383297.71 | AF51: {=INDEX('msci-indices'!C:C,MATCH($L51,'msci-indices'!$B:$B)+1)} -> 1639.7569 | AG51: {=INDEX('msci-indices'!D:D,MATCH($L51,'msci-indices'!$B:$B)+1)} -> 1460.9363 | AH51: =(InvestFees/4)*AE51 -> 239.56107 | AI51: =((AF51/AC51)*GlobalPortfolio+(AG51/AD51)*AusPortfolio)*AE51-AH51 -> 375310.05 | AJ51: =AJ50+AA51 -> 199733.13 | AK51: =AI51-AJ51 -> 175576.91 | AL51: =AJ51*(_xlfn.XLOOKUP(Q_end,cpi!A:A,cpi!B:B)/BH51) -> 256445.29 | AM51: {=SUMPRODUCT($AA$3:AA51,_xlfn.SORTBY($BH$3:BH51,_xlfn.SEQUENCE(ROWS($BH$3:BH51)),-1)/$BH$3)} -> 252470.38 | AN51: =AI51-AM51 -> 122839.67 | AO51: =IF($B$49="Real gains",MAX($B$50*AN51,0),IF($B$49="Discounted nominal gains",MAX($B$50*AK51/2,0),0)) -> 0 | AP51: =AI51-AO51 -> 375310.05 | AR51: =IF($B$10="3BR_H", INDEX('ns-combined'!$C:$D,MATCH($L51,'ns-combined'!$B:$B,0),MATCH(Council_Area,'ns-combined'!$C$1:$D$1,0))*1000, INDEX('s-combined'!$C:$D,MATCH($L51,'s-combined'!$B:$B,0),MATCH(Council_Area,'s-combined'!$C$1:$D$1,0))*1000) -> 731000 | AS51: =AS50+$AS$3 -> 40425 | AT51: 0 | AU51: =SUM($B$28:$B$29)*AR51 -> 14620 | AV51: =AR51*$B$15/4 -> 2101.625 | AW51: =SUM($AV$3:AV51) -> 70260.688 | AX51: =AR51-AS51-AU51-AW51 -> 605694.31 | AY51: =$B$36*V51 -> 1800 | AZ51: =SUM(AY51:AY51)*4/AR51 -> 0.0098495212 | BA51: =SUM(AY51:AY51)/V51 -> 0.35 | BB51: =IF(MortgageRate="Discounted",_xlfn.XLOOKUP(L51,'mortgage-rates'!$A:$A,'mortgage-rates'!$E:$E)/100,_xlfn.XLOOKUP(L51,'mortgage-rates'!$A:$A,'mortgage-rates'!$D:$D)/100) -> 0.0451 | BC51: =BC50-BF50 -> 182709.46 | BD51: =IF($B$16*12/3-Q51+1>0,-PMT($BB51/4,$B$16*12/3-Q51+1,BC51),0) -> 4662.964 | BE51: =BC51*($BB51/4) -> 2060.0491 | BF51: =BD51-BE51 -> 2602.9149 | BG51: =AT51+AY51+BD51 -> 6462.964 | BH51: =INDEX(cpi!B:B,MATCH($L51,cpi!A:A)) -> 112.7 | BI51: =100*BH51/BH$3 -> 133.21513 | BJ51: =100*AC51/AC$3 -> 219.81871 | BK51: =100*AD51/AD$3 -> 213.4075 | BL51: =BJ51*GlobalPortfolio+BK51*AusPortfolio -> 217.89535 | BM51: =100*AE51/$AE$3 -> 426.83624 | BN51: =100*AR51/AR$3 -> 221.51515 | BO51: =100*AX51/AX$3 -> 188.32241
A52: Other renter parameters | L52: =DATE(YEAR(L51),MONTH(L51)+3,1) -> 43252 | M52: =AP52 -> 391355.61 | N52: =AX52-BC52 -> 441226.52 | O52: =M52/N52 -> 0.88697209 | P52: =X52/BG52 -> 0.82623652 | Q52: 50 | R52: =EOMONTH(L52,0)-EOMONTH(L52,-3) -> 91 | T52: =IF($B$10="3BR_H", INDEX('3BR_H-processed'!$C:$D,MATCH($L52,'3BR_H-processed'!$B:$B,0),MATCH(Council_Area,'3BR_H-processed'!$C$1:$D$1,0)), INDEX('2BR_F-processed'!$C:$D,MATCH($L52,'2BR_F-processed'!$B:$B,0),MATCH(Council_Area,'2BR_F-processed'!$C$1:$D$1,0))) -> 395 | U52: =IF(MOD(Q52,4)=1,T52,U51) -> 400 | V52: =U52*(R52)/7 -> 5200 | W52: =$B$53/4*BH52/_xlfn.XLOOKUP(Q_end,cpi!A:A,cpi!B:B) -> 156.46164 | X52: =V52+W52 -> 5356.4616 | Y52: =BG52-X52 -> 1126.5024 | Z52: =Y52*$B$47 -> 0 | AA52: {=(Y52+Z52)*eff_invest} -> 1126.5024 | AB52: =AA52*(_xlfn.XLOOKUP(Q_end,cpi!A:A,cpi!B:B)/BH52) -> 1439.9726 | AC52: {=INDEX('msci-indices'!C:C,MATCH($L52,'msci-indices'!$B:$B)-2)} -> 1639.7569 | AD52: {=INDEX('msci-indices'!D:D,MATCH($L52,'msci-indices'!$B:$B)-2)} -> 1460.9363 | AE52: =AI51+AA52 -> 376436.55 | AF52: {=INDEX('msci-indices'!C:C,MATCH($L52,'msci-indices'!$B:$B)+1)} -> 1671.605 | AG52: {=INDEX('msci-indices'!D:D,MATCH($L52,'msci-indices'!$B:$B)+1)} -> 1590.7725 | AH52: =(InvestFees/4)*AE52 -> 235.27284 | AI52: =((AF52/AC52)*GlobalPortfolio+(AG52/AD52)*AusPortfolio)*AE52-AH52 -> 391355.61 | AJ52: =AJ51+AA52 -> 200859.64 | AK52: =AI52-AJ52 -> 190495.97 | AL52: =AJ52*(_xlfn.XLOOKUP(Q_end,cpi!A:A,cpi!B:B)/BH52) -> 256752.56 | AM52: {=SUMPRODUCT($AA$3:AA52,_xlfn.SORTBY($BH$3:BH52,_xlfn.SEQUENCE(ROWS($BH$3:BH52)),-1)/$BH$3)} -> 254851.39 | AN52: =AI52-AM52 -> 136504.22 | AO52: =IF($B$49="Real gains",MAX($B$50*AN52,0),IF($B$49="Discounted nominal gains",MAX($B$50*AK52/2,0),0)) -> 0 | AP52: =AI52-AO52 -> 391355.61 | AR52: =IF($B$10="3BR_H", INDEX('ns-combined'!$C:$D,MATCH($L52,'ns-combined'!$B:$B,0),MATCH(Council_Area,'ns-combined'!$C$1:$D$1,0))*1000, INDEX('s-combined'!$C:$D,MATCH($L52,'s-combined'!$B:$B,0),MATCH(Council_Area,'s-combined'!$C$1:$D$1,0))*1000) -> 750000 | AS52: =AS51+$AS$3 -> 41250 | AT52: 0 | AU52: =SUM($B$28:$B$29)*AR52 -> 15000 | AV52: =AR52*$B$15/4 -> 2156.25 | AW52: =SUM($AV$3:AV52) -> 72416.938 | AX52: =AR52-AS52-AU52-AW52 -> 621333.06 | AY52: =$B$36*V52 -> 1820 | AZ52: =SUM(AY52:AY52)*4/AR52 -> 0.0097066667 | BA52: =SUM(AY52:AY52)/V52 -> 0.35 | BB52: =IF(MortgageRate="Discounted",_xlfn.XLOOKUP(L52,'mortgage-rates'!$A:$A,'mortgage-rates'!$E:$E)/100,_xlfn.XLOOKUP(L52,'mortgage-rates'!$A:$A,'mortgage-rates'!$D:$D)/100) -> 0.0451 | BC52: =BC51-BF51 -> 180106.54 | BD52: =IF($B$16*12/3-Q52+1>0,-PMT($BB52/4,$B$16*12/3-Q52+1,BC52),0) -> 4662.964 | BE52: =BC52*($BB52/4) -> 2030.7013 | BF52: =BD52-BE52 -> 2632.2628 | BG52: =AT52+AY52+BD52 -> 6482.964 | BH52: =INDEX(cpi!B:B,MATCH($L52,cpi!A:A)) -> 113.2 | BI52: =100*BH52/BH$3 -> 133.80615 | BJ52: =100*AC52/AC$3 -> 217.22098 | BK52: =100*AD52/AD$3 -> 204.91247 | BL52: =BJ52*GlobalPortfolio+BK52*AusPortfolio -> 213.52842 | BM52: =100*AE52/$AE$3 -> 419.19572 | BN52: =100*AR52/AR$3 -> 227.27273 | BO52: =100*AX52/AX$3 -> 193.18481
A53: Renter's insurance and other costs ($ per year, end-quarter dollars) | B53: 800 | C53: 800 | L53: =DATE(YEAR(L52),MONTH(L52)+3,1) -> 43344 | M53: =AP53 -> 406199.67 | N53: =AX53-BC53 -> 411563.78 | O53: =M53/N53 -> 0.98696651 | P53: =X53/BG53 -> 0.82879398 | Q53: 51 | R53: =EOMONTH(L53,0)-EOMONTH(L53,-3) -> 92 | T53: =IF($B$10="3BR_H", INDEX('3BR_H-processed'!$C:$D,MATCH($L53,'3BR_H-processed'!$B:$B,0),MATCH(Council_Area,'3BR_H-processed'!$C$1:$D$1,0)), INDEX('2BR_F-processed'!$C:$D,MATCH($L53,'2BR_F-processed'!$B:$B,0),MATCH(Council_Area,'2BR_F-processed'!$C$1:$D$1,0))) -> 400 | U53: =IF(MOD(Q53,4)=1,T53,U52) -> 400 | V53: =U53*(R53)/7 -> 5257.1429 | W53: =$B$53/4*BH53/_xlfn.XLOOKUP(Q_end,cpi!A:A,cpi!B:B) -> 156.8763 | X53: =V53+W53 -> 5414.0192 | Y53: =BG53-X53 -> 1118.3873 | Z53: =Y53*$B$47 -> 0 | AA53: {=(Y53+Z53)*eff_invest} -> 1118.3873 | AB53: =AA53*(_xlfn.XLOOKUP(Q_end,cpi!A:A,cpi!B:B)/BH53) -> 1425.8206 | AC53: {=INDEX('msci-indices'!C:C,MATCH($L53,'msci-indices'!$B:$B)-2)} -> 1671.605 | AD53: {=INDEX('msci-indices'!D:D,MATCH($L53,'msci-indices'!$B:$B)-2)} -> 1590.7725 | AE53: =AI52+AA53 -> 392474 | AF53: {=INDEX('msci-indices'!C:C,MATCH($L53,'msci-indices'!$B:$B)+1)} -> 1747.8373 | AG53: {=INDEX('msci-indices'!D:D,MATCH($L53,'msci-indices'!$B:$B)+1)} -> 1610.2553 | AH53: =(InvestFees/4)*AE53 -> 245.29625 | AI53: =((AF53/AC53)*GlobalPortfolio+(AG53/AD53)*AusPortfolio)*AE53-AH53 -> 406199.67 | AJ53: =AJ52+AA53 -> 201978.02 | AK53: =AI53-AJ53 -> 204221.65 | AL53: =AJ53*(_xlfn.XLOOKUP(Q_end,cpi!A:A,cpi!B:B)/BH53) -> 257499.74 | AM53: {=SUMPRODUCT($AA$3:AA53,_xlfn.SORTBY($BH$3:BH53,_xlfn.SEQUENCE(ROWS($BH$3:BH53)),-1)/$BH$3)} -> 257019.44 | AN53: =AI53-AM53 -> 149180.24 | AO53: =IF($B$49="Real gains",MAX($B$50*AN53,0),IF($B$49="Discounted nominal gains",MAX($B$50*AK53/2,0),0)) -> 0 | AP53: =AI53-AO53 -> 406199.67 | AR53: =IF($B$10="3BR_H", INDEX('ns-combined'!$C:$D,MATCH($L53,'ns-combined'!$B:$B,0),MATCH(Council_Area,'ns-combined'!$C$1:$D$1,0))*1000, INDEX('s-combined'!$C:$D,MATCH($L53,'s-combined'!$B:$B,0),MATCH(Council_Area,'s-combined'!$C$1:$D$1,0))*1000) -> 720000 | AS53: =AS52+$AS$3 -> 42075 | AT53: 0 | AU53: =SUM($B$28:$B$29)*AR53 -> 14400 | AV53: =AR53*$B$15/4 -> 2070 | AW53: =SUM($AV$3:AV53) -> 74486.938 | AX53: =AR53-AS53-AU53-AW53 -> 589038.06 | AY53: =$B$36*V53 -> 1840 | AZ53: =SUM(AY53:AY53)*4/AR53 -> 0.010222222 | BA53: =SUM(AY53:AY53)/V53 -> 0.35 | BB53: =IF(MortgageRate="Discounted",_xlfn.XLOOKUP(L53,'mortgage-rates'!$A:$A,'mortgage-rates'!$E:$E)/100,_xlfn.XLOOKUP(L53,'mortgage-rates'!$A:$A,'mortgage-rates'!$D:$D)/100) -> 0.0462 | BC53: =BC52-BF52 -> 177474.28 | BD53: =IF($B$16*12/3-Q53+1>0,-PMT($BB53/4,$B$16*12/3-Q53+1,BC53),0) -> 4692.4065 | BE53: =BC53*($BB53/4) -> 2049.8279 | BF53: =BD53-BE53 -> 2642.5785 | BG53: =AT53+AY53+BD53 -> 6532.4065 | BH53: =INDEX(cpi!B:B,MATCH($L53,cpi!A:A)) -> 113.5 | BI53: =100*BH53/BH$3 -> 134.16076 | BJ53: =100*AC53/AC$3 -> 221.43995 | BK53: =100*AD53/AD$3 -> 223.12345 | BL53: =BJ53*GlobalPortfolio+BK53*AusPortfolio -> 221.945 | BM53: =100*AE53/$AE$3 -> 437.05485 | BN53: =100*AR53/AR$3 -> 218.18182 | BO53: =100*AX53/AX$3 -> 183.14365
A54: Investment efficiency | B54: 1 | C54: 1 | L54: =DATE(YEAR(L53),MONTH(L53)+3,1) -> 43435 | M54: =AP54 -> 357125.76 | N54: =AX54-BC54 -> 425968.24 | O54: =M54/N54 -> 0.8383859 | P54: =X54/BG54 -> 0.8278977 | Q54: 52 | R54: =EOMONTH(L54,0)-EOMONTH(L54,-3) -> 92 | T54: =IF($B$10="3BR_H", INDEX('3BR_H-processed'!$C:$D,MATCH($L54,'3BR_H-processed'!$B:$B,0),MATCH(Council_Area,'3BR_H-processed'!$C$1:$D$1,0)), INDEX('2BR_F-processed'!$C:$D,MATCH($L54,'2BR_F-processed'!$B:$B,0),MATCH(Council_Area,'2BR_F-processed'!$C$1:$D$1,0))) -> 400 | U54: =IF(MOD(Q54,4)=1,T54,U53) -> 400 | V54: =U54*(R54)/7 -> 5257.1429 | W54: =$B$53/4*BH54/_xlfn.XLOOKUP(Q_end,cpi!A:A,cpi!B:B) -> 157.56738 | X54: =V54+W54 -> 5414.7102 | Y54: =BG54-X54 -> 1125.603 | Z54: =Y54*$B$47 -> 0 | AA54: {=(Y54+Z54)*eff_invest} -> 1125.603 | AB54: =AA54*(_xlfn.XLOOKUP(Q_end,cpi!A:A,cpi!B:B)/BH54) -> 1428.7259 | AC54: {=INDEX('msci-indices'!C:C,MATCH($L54,'msci-indices'!$B:$B)-2)} -> 1747.8373 | AD54: {=INDEX('msci-indices'!D:D,MATCH($L54,'msci-indices'!$B:$B)-2)} -> 1610.2553 | AE54: =AI53+AA54 -> 407325.27 | AF54: {=INDEX('msci-indices'!C:C,MATCH($L54,'msci-indices'!$B:$B)+1)} -> 1503.1568 | AG54: {=INDEX('msci-indices'!D:D,MATCH($L54,'msci-indices'!$B:$B)+1)} -> 1478.0882 | AH54: =(InvestFees/4)*AE54 -> 254.5783 | AI54: =((AF54/AC54)*GlobalPortfolio+(AG54/AD54)*AusPortfolio)*AE54-AH54 -> 357125.76 | AJ54: =AJ53+AA54 -> 203103.63 | AK54: =AI54-AJ54 -> 154022.14 | AL54: =AJ54*(_xlfn.XLOOKUP(Q_end,cpi!A:A,cpi!B:B)/BH54) -> 257799.08 | AM54: {=SUMPRODUCT($AA$3:AA54,_xlfn.SORTBY($BH$3:BH54,_xlfn.SEQUENCE(ROWS($BH$3:BH54)),-1)/$BH$3)} -> 259409.61 | AN54: =AI54-AM54 -> 97716.153 | AO54: =IF($B$49="Real gains",MAX($B$50*AN54,0),IF($B$49="Discounted nominal gains",MAX($B$50*AK54/2,0),0)) -> 0 | AP54: =AI54-AO54 -> 357125.76 | AR54: =IF($B$10="3BR_H", INDEX('ns-combined'!$C:$D,MATCH($L54,'ns-combined'!$B:$B,0),MATCH(Council_Area,'ns-combined'!$C$1:$D$1,0))*1000, INDEX('s-combined'!$C:$D,MATCH($L54,'s-combined'!$B:$B,0),MATCH(Council_Area,'s-combined'!$C$1:$D$1,0))*1000) -> 735000 | AS54: =AS53+$AS$3 -> 42900 | AT54: 0 | AU54: =SUM($B$28:$B$29)*AR54 -> 14700 | AV54: =AR54*$B$15/4 -> 2113.125 | AW54: =SUM($AV$3:AV54) -> 76600.062 | AX54: =AR54-AS54-AU54-AW54 -> 600799.94 | AY54: =$B$36*V54 -> 1840 | AZ54: =SUM(AY54:AY54)*4/AR54 -> 0.010013605 | BA54: =SUM(AY54:AY54)/V54 -> 0.35 | BB54: =IF(MortgageRate="Discounted",_xlfn.XLOOKUP(L54,'mortgage-rates'!$A:$A,'mortgage-rates'!$E:$E)/100,_xlfn.XLOOKUP(L54,'mortgage-rates'!$A:$A,'mortgage-rates'!$D:$D)/100) -> 0.0465 | BC54: =BC53-BF53 -> 174831.7 | BD54: =IF($B$16*12/3-Q54+1>0,-PMT($BB54/4,$B$16*12/3-Q54+1,BC54),0) -> 4700.3132 | BE54: =BC54*($BB54/4) -> 2032.4185 | BF54: =BD54-BE54 -> 2667.8947 | BG54: =AT54+AY54+BD54 -> 6540.3132 | BH54: =INDEX(cpi!B:B,MATCH($L54,cpi!A:A)) -> 114 | BI54: =100*BH54/BH$3 -> 134.75177 | BJ54: =100*AC54/AC$3 -> 231.53855 | BK54: =100*AD54/AD$3 -> 225.85612 | BL54: =BJ54*GlobalPortfolio+BK54*AusPortfolio -> 229.83382 | BM54: =100*AE54/$AE$3 -> 453.59307 | BN54: =100*AR54/AR$3 -> 222.72727 | BO54: =100*AX54/AX$3 -> 186.80065
L55: =DATE(YEAR(L54),MONTH(L54)+3,1) -> 43525 | M55: =AP55 -> 401404.55 | N55: =AX55-BC55 -> 376841.76 | O55: =M55/N55 -> 1.0651806 | P55: =X55/BG55 -> 0.81445808 | Q55: 53 | R55: =EOMONTH(L55,0)-EOMONTH(L55,-3) -> 90 | T55: =IF($B$10="3BR_H", INDEX('3BR_H-processed'!$C:$D,MATCH($L55,'3BR_H-processed'!$B:$B,0),MATCH(Council_Area,'3BR_H-processed'!$C$1:$D$1,0)), INDEX('2BR_F-processed'!$C:$D,MATCH($L55,'2BR_F-processed'!$B:$B,0),MATCH(Council_Area,'2BR_F-processed'!$C$1:$D$1,0))) -> 400 | U55: =IF(MOD(Q55,4)=1,T55,U54) -> 400 | V55: =U55*(R55)/7 -> 5142.8571 | W55: =$B$53/4*BH55/_xlfn.XLOOKUP(Q_end,cpi!A:A,cpi!B:B) -> 157.7056 | X55: =V55+W55 -> 5300.5627 | Y55: =BG55-X55 -> 1207.5227 | Z55: =Y55*$B$47 -> 0 | AA55: {=(Y55+Z55)*eff_invest} -> 1207.5227 | AB55: =AA55*(_xlfn.XLOOKUP(Q_end,cpi!A:A,cpi!B:B)/BH55) -> 1531.3631 | AC55: {=INDEX('msci-indices'!C:C,MATCH($L55,'msci-indices'!$B:$B)-2)} -> 1503.1568 | AD55: {=INDEX('msci-indices'!D:D,MATCH($L55,'msci-indices'!$B:$B)-2)} -> 1478.0882 | AE55: =AI54+AA55 -> 358333.29 | AF55: {=INDEX('msci-indices'!C:C,MATCH($L55,'msci-indices'!$B:$B)+1)} -> 1693.1497 | AG55: {=INDEX('msci-indices'!D:D,MATCH($L55,'msci-indices'!$B:$B)+1)} -> 1637.4592 | AH55: =(InvestFees/4)*AE55 -> 223.9583 | AI55: =((AF55/AC55)*GlobalPortfolio+(AG55/AD55)*AusPortfolio)*AE55-AH55 -> 401404.55 | AJ55: =AJ54+AA55 -> 204311.15 | AK55: =AI55-AJ55 -> 197093.4 | AL55: =AJ55*(_xlfn.XLOOKUP(Q_end,cpi!A:A,cpi!B:B)/BH55) -> 259104.5 | AM55: {=SUMPRODUCT($AA$3:AA55,_xlfn.SORTBY($BH$3:BH55,_xlfn.SEQUENCE(ROWS($BH$3:BH55)),-1)/$BH$3)} -> 261468.91 | AN55: =AI55-AM55 -> 139935.64 | AO55: =IF($B$49="Real gains",MAX($B$50*AN55,0),IF($B$49="Discounted nominal gains",MAX($B$50*AK55/2,0),0)) -> 0 | AP55: =AI55-AO55 -> 401404.55 | AR55: =IF($B$10="3BR_H", INDEX('ns-combined'!$C:$D,MATCH($L55,'ns-combined'!$B:$B,0),MATCH(Council_Area,'ns-combined'!$C$1:$D$1,0))*1000, INDEX('s-combined'!$C:$D,MATCH($L55,'s-combined'!$B:$B,0),MATCH(Council_Area,'s-combined'!$C$1:$D$1,0))*1000) -> 685000 | AS55: =AS54+$AS$3 -> 43725 | AT55: 0 | AU55: =SUM($B$28:$B$29)*AR55 -> 13700 | AV55: =AR55*$B$15/4 -> 1969.375 | AW55: =SUM($AV$3:AV55) -> 78569.438 | AX55: =AR55-AS55-AU55-AW55 -> 549005.56 | AY55: =$B$36*V55 -> 1800 | AZ55: =SUM(AY55:AY55)*4/AR55 -> 0.010510949 | BA55: =SUM(AY55:AY55)/V55 -> 0.35 | BB55: =IF(MortgageRate="Discounted",_xlfn.XLOOKUP(L55,'mortgage-rates'!$A:$A,'mortgage-rates'!$E:$E)/100,_xlfn.XLOOKUP(L55,'mortgage-rates'!$A:$A,'mortgage-rates'!$D:$D)/100) -> 0.0468 | BC55: =BC54-BF54 -> 172163.81 | BD55: =IF($B$16*12/3-Q55+1>0,-PMT($BB55/4,$B$16*12/3-Q55+1,BC55),0) -> 4708.0854 | BE55: =BC55*($BB55/4) -> 2014.3165 | BF55: =BD55-BE55 -> 2693.7689 | BG55: =AT55+AY55+BD55 -> 6508.0854 | BH55: =INDEX(cpi!B:B,MATCH($L55,cpi!A:A)) -> 114.1 | BI55: =100*BH55/BH$3 -> 134.86998 | BJ55: =100*AC55/AC$3 -> 199.12537 | BK55: =100*AD55/AD$3 -> 207.31821 | BL55: =BJ55*GlobalPortfolio+BK55*AusPortfolio -> 201.58322 | BM55: =100*AE55/$AE$3 -> 399.03612 | BN55: =100*AR55/AR$3 -> 207.57576 | BO55: =100*AX55/AX$3 -> 170.69675
L56: =DATE(YEAR(L55),MONTH(L55)+3,1) -> 43617 | M56: =AP56 -> 422502.16 | N56: =AX56-BC56 -> 391398.03 | O56: =M56/N56 -> 1.0794693 | P56: =X56/BG56 -> 0.82796089 | Q56: 54 | R56: =EOMONTH(L56,0)-EOMONTH(L56,-3) -> 91 | T56: =IF($B$10="3BR_H", INDEX('3BR_H-processed'!$C:$D,MATCH($L56,'3BR_H-processed'!$B:$B,0),MATCH(Council_Area,'3BR_H-processed'!$C$1:$D$1,0)), INDEX('2BR_F-processed'!$C:$D,MATCH($L56,'2BR_F-processed'!$B:$B,0),MATCH(Council_Area,'2BR_F-processed'!$C$1:$D$1,0))) -> 400 | U56: =IF(MOD(Q56,4)=1,T56,U55) -> 400 | V56: =U56*(R56)/7 -> 5200 | W56: =$B$53/4*BH56/_xlfn.XLOOKUP(Q_end,cpi!A:A,cpi!B:B) -> 158.81133 | X56: =V56+W56 -> 5358.8113 | Y56: =BG56-X56 -> 1113.4887 | Z56: =Y56*$B$47 -> 0 | AA56: {=(Y56+Z56)*eff_invest} -> 1113.4887 | AB56: =AA56*(_xlfn.XLOOKUP(Q_end,cpi!A:A,cpi!B:B)/BH56) -> 1402.2787 | AC56: {=INDEX('msci-indices'!C:C,MATCH($L56,'msci-indices'!$B:$B)-2)} -> 1693.1497 | AD56: {=INDEX('msci-indices'!D:D,MATCH($L56,'msci-indices'!$B:$B)-2)} -> 1637.4592 | AE56: =AI55+AA56 -> 402518.03 | AF56: {=INDEX('msci-indices'!C:C,MATCH($L56,'msci-indices'!$B:$B)+1)} -> 1756.4484 | AG56: {=INDEX('msci-indices'!D:D,MATCH($L56,'msci-indices'!$B:$B)+1)} -> 1769.0189 | AH56: =(InvestFees/4)*AE56 -> 251.57377 | AI56: =((AF56/AC56)*GlobalPortfolio+(AG56/AD56)*AusPortfolio)*AE56-AH56 -> 422502.16 | AJ56: =AJ55+AA56 -> 205424.64 | AK56: =AI56-AJ56 -> 217077.52 | AL56: =AJ56*(_xlfn.XLOOKUP(Q_end,cpi!A:A,cpi!B:B)/BH56) -> 258702.74 | AM56: {=SUMPRODUCT($AA$3:AA56,_xlfn.SORTBY($BH$3:BH56,_xlfn.SEQUENCE(ROWS($BH$3:BH56)),-1)/$BH$3)} -> 264164 | AN56: =AI56-AM56 -> 158338.16 | AO56: =IF($B$49="Real gains",MAX($B$50*AN56,0),IF($B$49="Discounted nominal gains",MAX($B$50*AK56/2,0),0)) -> 0 | AP56: =AI56-AO56 -> 422502.16 | AR56: =IF($B$10="3BR_H", INDEX('ns-combined'!$C:$D,MATCH($L56,'ns-combined'!$B:$B,0),MATCH(Council_Area,'ns-combined'!$C$1:$D$1,0))*1000, INDEX('s-combined'!$C:$D,MATCH($L56,'s-combined'!$B:$B,0),MATCH(Council_Area,'s-combined'!$C$1:$D$1,0))*1000) -> 700000 | AS56: =AS55+$AS$3 -> 44550 | AT56: 0 | AU56: =SUM($B$28:$B$29)*AR56 -> 14000 | AV56: =AR56*$B$15/4 -> 2012.5 | AW56: =SUM($AV$3:AV56) -> 80581.938 | AX56: =AR56-AS56-AU56-AW56 -> 560868.06 | AY56: =$B$36*V56 -> 1820 | AZ56: =SUM(AY56:AY56)*4/AR56 -> 0.0104 | BA56: =SUM(AY56:AY56)/V56 -> 0.35 | BB56: =IF(MortgageRate="Discounted",_xlfn.XLOOKUP(L56,'mortgage-rates'!$A:$A,'mortgage-rates'!$E:$E)/100,_xlfn.XLOOKUP(L56,'mortgage-rates'!$A:$A,'mortgage-rates'!$D:$D)/100) -> 0.0446 | BC56: =BC55-BF55 -> 169470.04 | BD56: =IF($B$16*12/3-Q56+1>0,-PMT($BB56/4,$B$16*12/3-Q56+1,BC56),0) -> 4652.3001 | BE56: =BC56*($BB56/4) -> 1889.5909 | BF56: =BD56-BE56 -> 2762.7092 | BG56: =AT56+AY56+BD56 -> 6472.3001 | BH56: =INDEX(cpi!B:B,MATCH($L56,cpi!A:A)) -> 114.9 | BI56: =100*BH56/BH$3 -> 135.8156 | BJ56: =100*AC56/AC$3 -> 224.294 | BK56: =100*AD56/AD$3 -> 229.67177 | BL56: =BJ56*GlobalPortfolio+BK56*AusPortfolio -> 225.90733 | BM56: =100*AE56/$AE$3 -> 448.23978 | BN56: =100*AR56/AR$3 -> 212.12121 | BO56: =100*AX56/AX$3 -> 174.38504
L57: =DATE(YEAR(L56),MONTH(L56)+3,1) -> 43709 | M57: =AP57 -> 427826.43 | N57: =AX57-BC57 -> 396208.86 | O57: =M57/N57 -> 1.0798003 | P57: =X57/BG57 -> 0.84104116 | Q57: 55 | R57: =EOMONTH(L57,0)-EOMONTH(L57,-3) -> 92 | T57: =IF($B$10="3BR_H", INDEX('3BR_H-processed'!$C:$D,MATCH($L57,'3BR_H-processed'!$B:$B,0),MATCH(Council_Area,'3BR_H-processed'!$C$1:$D$1,0)), INDEX('2BR_F-processed'!$C:$D,MATCH($L57,'2BR_F-processed'!$B:$B,0),MATCH(Council_Area,'2BR_F-processed'!$C$1:$D$1,0))) -> 400 | U57: =IF(MOD(Q57,4)=1,T57,U56) -> 400 | V57: =U57*(R57)/7 -> 5257.1429 | W57: =$B$53/4*BH57/_xlfn.XLOOKUP(Q_end,cpi!A:A,cpi!B:B) -> 159.50242 | X57: =V57+W57 -> 5416.6453 | Y57: =BG57-X57 -> 1023.7592 | Z57: =Y57*$B$47 -> 0 | AA57: {=(Y57+Z57)*eff_invest} -> 1023.7592 | AB57: =AA57*(_xlfn.XLOOKUP(Q_end,cpi!A:A,cpi!B:B)/BH57) -> 1283.6911 | AC57: {=INDEX('msci-indices'!C:C,MATCH($L57,'msci-indices'!$B:$B)-2)} -> 1756.4484 | AD57: {=INDEX('msci-indices'!D:D,MATCH($L57,'msci-indices'!$B:$B)-2)} -> 1769.0189 | AE57: =AI56+AA57 -> 423525.92 | AF57: {=INDEX('msci-indices'!C:C,MATCH($L57,'msci-indices'!$B:$B)+1)} -> 1762.7547 | AG57: {=INDEX('msci-indices'!D:D,MATCH($L57,'msci-indices'!$B:$B)+1)} -> 1817.7602 | AH57: =(InvestFees/4)*AE57 -> 264.7037 | AI57: =((AF57/AC57)*GlobalPortfolio+(AG57/AD57)*AusPortfolio)*AE57-AH57 -> 427826.43 | AJ57: =AJ56+AA57 -> 206448.4 | AK57: =AI57-AJ57 -> 221378.03 | AL57: =AJ57*(_xlfn.XLOOKUP(Q_end,cpi!A:A,cpi!B:B)/BH57) -> 258865.54 | AM57: {=SUMPRODUCT($AA$3:AA57,_xlfn.SORTBY($BH$3:BH57,_xlfn.SEQUENCE(ROWS($BH$3:BH57)),-1)/$BH$3)} -> 266468.58 | AN57: =AI57-AM57 -> 161357.85 | AO57: =IF($B$49="Real gains",MAX($B$50*AN57,0),IF($B$49="Discounted nominal gains",MAX($B$50*AK57/2,0),0)) -> 0 | AP57: =AI57-AO57 -> 427826.43 | AR57: =IF($B$10="3BR_H", INDEX('ns-combined'!$C:$D,MATCH($L57,'ns-combined'!$B:$B,0),MATCH(Council_Area,'ns-combined'!$C$1:$D$1,0))*1000, INDEX('s-combined'!$C:$D,MATCH($L57,'s-combined'!$B:$B,0),MATCH(Council_Area,'s-combined'!$C$1:$D$1,0))*1000) -> 705000 | AS57: =AS56+$AS$3 -> 45375 | AT57: 0 | AU57: =SUM($B$28:$B$29)*AR57 -> 14100 | AV57: =AR57*$B$15/4 -> 2026.875 | AW57: =SUM($AV$3:AV57) -> 82608.812 | AX57: =AR57-AS57-AU57-AW57 -> 562916.19 | AY57: =$B$36*V57 -> 1840 | AZ57: =SUM(AY57:AY57)*4/AR57 -> 0.010439716 | BA57: =SUM(AY57:AY57)/V57 -> 0.35 | BB57: =IF(MortgageRate="Discounted",_xlfn.XLOOKUP(L57,'mortgage-rates'!$A:$A,'mortgage-rates'!$E:$E)/100,_xlfn.XLOOKUP(L57,'mortgage-rates'!$A:$A,'mortgage-rates'!$D:$D)/100) -> 0.0425 | BC57: =BC56-BF56 -> 166707.33 | BD57: =IF($B$16*12/3-Q57+1>0,-PMT($BB57/4,$B$16*12/3-Q57+1,BC57),0) -> 4600.4045 | BE57: =BC57*($BB57/4) -> 1771.2654 | BF57: =BD57-BE57 -> 2829.1391 | BG57: =AT57+AY57+BD57 -> 6440.4045 | BH57: =INDEX(cpi!B:B,MATCH($L57,cpi!A:A)) -> 115.4 | BI57: =100*BH57/BH$3 -> 136.40662 | BJ57: =100*AC57/AC$3 -> 232.67928 | BK57: =100*AD57/AD$3 -> 248.12447 | BL57: =BJ57*GlobalPortfolio+BK57*AusPortfolio -> 237.31283 | BM57: =100*AE57/$AE$3 -> 471.63393 | BN57: =100*AR57/AR$3 -> 213.63636 | BO57: =100*AX57/AX$3 -> 175.02184
L58: =DATE(YEAR(L57),MONTH(L57)+3,1) -> 43800 | M58: =AP58 -> 454819.38 | N58: =AX58-BC58 -> 449928 | O58: =M58/N58 -> 1.0108715 | P58: =X58/BG58 -> 0.84435309 | Q58: 56 | R58: =EOMONTH(L58,0)-EOMONTH(L58,-3) -> 92 | T58: =IF($B$10="3BR_H", INDEX('3BR_H-processed'!$C:$D,MATCH($L58,'3BR_H-processed'!$B:$B,0),MATCH(Council_Area,'3BR_H-processed'!$C$1:$D$1,0)), INDEX('2BR_F-processed'!$C:$D,MATCH($L58,'2BR_F-processed'!$B:$B,0),MATCH(Council_Area,'2BR_F-processed'!$C$1:$D$1,0))) -> 400 | U58: =IF(MOD(Q58,4)=1,T58,U57) -> 400 | V58: =U58*(R58)/7 -> 5257.1429 | W58: =$B$53/4*BH58/_xlfn.XLOOKUP(Q_end,cpi!A:A,cpi!B:B) -> 160.46994 | X58: =V58+W58 -> 5417.6128 | Y58: =BG58-X58 -> 998.67546 | Z58: =Y58*$B$47 -> 0 | AA58: {=(Y58+Z58)*eff_invest} -> 998.67546 | AB58: =AA58*(_xlfn.XLOOKUP(Q_end,cpi!A:A,cpi!B:B)/BH58) -> 1244.6885 | AC58: {=INDEX('msci-indices'!C:C,MATCH($L58,'msci-indices'!$B:$B)-2)} -> 1762.7547 | AD58: {=INDEX('msci-indices'!D:D,MATCH($L58,'msci-indices'!$B:$B)-2)} -> 1817.7602 | AE58: =AI57+AA58 -> 428825.11 | AF58: {=INDEX('msci-indices'!C:C,MATCH($L58,'msci-indices'!$B:$B)+1)} -> 1916.2448 | AG58: {=INDEX('msci-indices'!D:D,MATCH($L58,'msci-indices'!$B:$B)+1)} -> 1819.5212 | AH58: =(InvestFees/4)*AE58 -> 268.01569 | AI58: =((AF58/AC58)*GlobalPortfolio+(AG58/AD58)*AusPortfolio)*AE58-AH58 -> 454819.38 | AJ58: =AJ57+AA58 -> 207447.07 | AK58: =AI58-AJ58 -> 247372.31 | AL58: =AJ58*(_xlfn.XLOOKUP(Q_end,cpi!A:A,cpi!B:B)/BH58) -> 258549.45 | AM58: {=SUMPRODUCT($AA$3:AA58,_xlfn.SORTBY($BH$3:BH58,_xlfn.SEQUENCE(ROWS($BH$3:BH58)),-1)/$BH$3)} -> 268954.6 | AN58: =AI58-AM58 -> 185864.78 | AO58: =IF($B$49="Real gains",MAX($B$50*AN58,0),IF($B$49="Discounted nominal gains",MAX($B$50*AK58/2,0),0)) -> 0 | AP58: =AI58-AO58 -> 454819.38 | AR58: =IF($B$10="3BR_H", INDEX('ns-combined'!$C:$D,MATCH($L58,'ns-combined'!$B:$B,0),MATCH(Council_Area,'ns-combined'!$C$1:$D$1,0))*1000, INDEX('s-combined'!$C:$D,MATCH($L58,'s-combined'!$B:$B,0),MATCH(Council_Area,'s-combined'!$C$1:$D$1,0))*1000) -> 760000 | AS58: =AS57+$AS$3 -> 46200 | AT58: 0 | AU58: =SUM($B$28:$B$29)*AR58 -> 15200 | AV58: =AR58*$B$15/4 -> 2185 | AW58: =SUM($AV$3:AV58) -> 84793.812 | AX58: =AR58-AS58-AU58-AW58 -> 613806.19 | AY58: =$B$36*V58 -> 1840 | AZ58: =SUM(AY58:AY58)*4/AR58 -> 0.0096842105 | BA58: =SUM(AY58:AY58)/V58 -> 0.35 | BB58: =IF(MortgageRate="Discounted",_xlfn.XLOOKUP(L58,'mortgage-rates'!$A:$A,'mortgage-rates'!$E:$E)/100,_xlfn.XLOOKUP(L58,'mortgage-rates'!$A:$A,'mortgage-rates'!$D:$D)/100) -> 0.0415 | BC58: =BC57-BF57 -> 163878.19 | BD58: =IF($B$16*12/3-Q58+1>0,-PMT($BB58/4,$B$16*12/3-Q58+1,BC58),0) -> 4576.2883 | BE58: =BC58*($BB58/4) -> 1700.2362 | BF58: =BD58-BE58 -> 2876.052 | BG58: =AT58+AY58+BD58 -> 6416.2883 | BH58: =INDEX(cpi!B:B,MATCH($L58,cpi!A:A)) -> 116.1 | BI58: =100*BH58/BH$3 -> 137.23404 | BJ58: =100*AC58/AC$3 -> 233.51468 | BK58: =100*AD58/AD$3 -> 254.96098 | BL58: =BJ58*GlobalPortfolio+BK58*AusPortfolio -> 239.94857 | BM58: =100*AE58/$AE$3 -> 477.53505 | BN58: =100*AR58/AR$3 -> 230.30303 | BO58: =100*AX58/AX$3 -> 190.84456
L59: =DATE(YEAR(L58),MONTH(L58)+3,1) -> 43891 | M59: =AP59 -> 352026.84 | N59: =AX59-BC59 -> 420480.3 | O59: =M59/N59 -> 0.83720173 | P59: =X59/BG59 -> 0.85998334 | Q59: 57 | R59: =EOMONTH(L59,0)-EOMONTH(L59,-3) -> 91 | T59: =IF($B$10="3BR_H", INDEX('3BR_H-processed'!$C:$D,MATCH($L59,'3BR_H-processed'!$B:$B,0),MATCH(Council_Area,'3BR_H-processed'!$C$1:$D$1,0)), INDEX('2BR_F-processed'!$C:$D,MATCH($L59,'2BR_F-processed'!$B:$B,0),MATCH(Council_Area,'2BR_F-processed'!$C$1:$D$1,0))) -> 410 | U59: =IF(MOD(Q59,4)=1,T59,U58) -> 410 | V59: =U59*(R59)/7 -> 5330 | W59: =$B$53/4*BH59/_xlfn.XLOOKUP(Q_end,cpi!A:A,cpi!B:B) -> 161.29924 | X59: =V59+W59 -> 5491.2992 | Y59: =BG59-X59 -> 894.05614 | Z59: =Y59*$B$47 -> 0 | AA59: {=(Y59+Z59)*eff_invest} -> 894.05614 | AB59: =AA59*(_xlfn.XLOOKUP(Q_end,cpi!A:A,cpi!B:B)/BH59) -> 1108.5683 | AC59: {=INDEX('msci-indices'!C:C,MATCH($L59,'msci-indices'!$B:$B)-2)} -> 1916.2448 | AD59: {=INDEX('msci-indices'!D:D,MATCH($L59,'msci-indices'!$B:$B)-2)} -> 1819.5212 | AE59: =AI58+AA59 -> 455713.44 | AF59: {=INDEX('msci-indices'!C:C,MATCH($L59,'msci-indices'!$B:$B)+1)} -> 1491.4482 | AG59: {=INDEX('msci-indices'!D:D,MATCH($L59,'msci-indices'!$B:$B)+1)} -> 1384.5123 | AH59: =(InvestFees/4)*AE59 -> 284.8209 | AI59: =((AF59/AC59)*GlobalPortfolio+(AG59/AD59)*AusPortfolio)*AE59-AH59 -> 352026.84 | AJ59: =AJ58+AA59 -> 208341.13 | AK59: =AI59-AJ59 -> 143685.71 | AL59: =AJ59*(_xlfn.XLOOKUP(Q_end,cpi!A:A,cpi!B:B)/BH59) -> 258328.72 | AM59: {=SUMPRODUCT($AA$3:AA59,_xlfn.SORTBY($BH$3:BH59,_xlfn.SEQUENCE(ROWS($BH$3:BH59)),-1)/$BH$3)} -> 271242.31 | AN59: =AI59-AM59 -> 80784.527 | AO59: =IF($B$49="Real gains",MAX($B$50*AN59,0),IF($B$49="Discounted nominal gains",MAX($B$50*AK59/2,0),0)) -> 0 | AP59: =AI59-AO59 -> 352026.84 | AR59: =IF($B$10="3BR_H", INDEX('ns-combined'!$C:$D,MATCH($L59,'ns-combined'!$B:$B,0),MATCH(Council_Area,'ns-combined'!$C$1:$D$1,0))*1000, INDEX('s-combined'!$C:$D,MATCH($L59,'s-combined'!$B:$B,0),MATCH(Council_Area,'s-combined'!$C$1:$D$1,0))*1000) -> 730000 | AS59: =AS58+$AS$3 -> 47025 | AT59: 0 | AU59: =SUM($B$28:$B$29)*AR59 -> 14600 | AV59: =AR59*$B$15/4 -> 2098.75 | AW59: =SUM($AV$3:AV59) -> 86892.562 | AX59: =AR59-AS59-AU59-AW59 -> 581482.44 | AY59: =$B$36*V59 -> 1865.5 | AZ59: =SUM(AY59:AY59)*4/AR59 -> 0.010221918 | BA59: =SUM(AY59:AY59)/V59 -> 0.35 | BB59: =IF(MortgageRate="Discounted",_xlfn.XLOOKUP(L59,'mortgage-rates'!$A:$A,'mortgage-rates'!$E:$E)/100,_xlfn.XLOOKUP(L59,'mortgage-rates'!$A:$A,'mortgage-rates'!$D:$D)/100) -> 0.0391 | BC59: =BC58-BF58 -> 161002.14 | BD59: =IF($B$16*12/3-Q59+1>0,-PMT($BB59/4,$B$16*12/3-Q59+1,BC59),0) -> 4519.8554 | BE59: =BC59*($BB59/4) -> 1573.7959 | BF59: =BD59-BE59 -> 2946.0595 | BG59: =AT59+AY59+BD59 -> 6385.3554 | BH59: =INDEX(cpi!B:B,MATCH($L59,cpi!A:A)) -> 116.7 | BI59: =100*BH59/BH$3 -> 137.94326 | BJ59: =100*AC59/AC$3 -> 253.84774 | BK59: =100*AD59/AD$3 -> 255.20797 | BL59: =BJ59*GlobalPortfolio+BK59*AusPortfolio -> 254.25581 | BM59: =100*AE59/$AE$3 -> 507.47761 | BN59: =100*AR59/AR$3 -> 221.21212 | BO59: =100*AX59/AX$3 -> 180.79446
L60: =DATE(YEAR(L59),MONTH(L59)+3,1) -> 43983 | M60: =AP60 -> 420017.67 | N60: =AX60-BC60 -> 410731.36 | O60: =M60/N60 -> 1.0226092 | P60: =X60/BG60 -> 0.86758199 | Q60: 58 | R60: =EOMONTH(L60,0)-EOMONTH(L60,-3) -> 91 | T60: =IF($B$10="3BR_H", INDEX('3BR_H-processed'!$C:$D,MATCH($L60,'3BR_H-processed'!$B:$B,0),MATCH(Council_Area,'3BR_H-processed'!$C$1:$D$1,0)), INDEX('2BR_F-processed'!$C:$D,MATCH($L60,'2BR_F-processed'!$B:$B,0),MATCH(Council_Area,'2BR_F-processed'!$C$1:$D$1,0))) -> 400 | U60: =IF(MOD(Q60,4)=1,T60,U59) -> 410 | V60: =U60*(R60)/7 -> 5330 | W60: =$B$53/4*BH60/_xlfn.XLOOKUP(Q_end,cpi!A:A,cpi!B:B) -> 158.25847 | X60: =V60+W60 -> 5488.2585 | Y60: =BG60-X60 -> 837.66636 | Z60: =Y60*$B$47 -> 0 | AA60: {=(Y60+Z60)*eff_invest} -> 837.66636 | AB60: =AA60*(_xlfn.XLOOKUP(Q_end,cpi!A:A,cpi!B:B)/BH60) -> 1058.6054 | AC60: {=INDEX('msci-indices'!C:C,MATCH($L60,'msci-indices'!$B:$B)-2)} -> 1491.4482 | AD60: {=INDEX('msci-indices'!D:D,MATCH($L60,'msci-indices'!$B:$B)-2)} -> 1384.5123 | AE60: =AI59+AA60 -> 352864.5 | AF60: {=INDEX('msci-indices'!C:C,MATCH($L60,'msci-indices'!$B:$B)+1)} -> 1788.7914 | AG60: {=INDEX('msci-indices'!D:D,MATCH($L60,'msci-indices'!$B:$B)+1)} -> 1621.6232 | AH60: =(InvestFees/4)*AE60 -> 220.54031 | AI60: =((AF60/AC60)*GlobalPortfolio+(AG60/AD60)*AusPortfolio)*AE60-AH60 -> 420017.67 | AJ60: =AJ59+AA60 -> 209178.8 | AK60: =AI60-AJ60 -> 210838.87 | AL60: =AJ60*(_xlfn.XLOOKUP(Q_end,cpi!A:A,cpi!B:B)/BH60) -> 264350.84 | AM60: {=SUMPRODUCT($AA$3:AA60,_xlfn.SORTBY($BH$3:BH60,_xlfn.SEQUENCE(ROWS($BH$3:BH60)),-1)/$BH$3)} -> 270509.27 | AN60: =AI60-AM60 -> 149508.4 | AO60: =IF($B$49="Real gains",MAX($B$50*AN60,0),IF($B$49="Discounted nominal gains",MAX($B$50*AK60/2,0),0)) -> 0 | AP60: =AI60-AO60 -> 420017.67 | AR60: =IF($B$10="3BR_H", INDEX('ns-combined'!$C:$D,MATCH($L60,'ns-combined'!$B:$B,0),MATCH(Council_Area,'ns-combined'!$C$1:$D$1,0))*1000, INDEX('s-combined'!$C:$D,MATCH($L60,'s-combined'!$B:$B,0),MATCH(Council_Area,'s-combined'!$C$1:$D$1,0))*1000) -> 720000 | AS60: =AS59+$AS$3 -> 47850 | AT60: 0 | AU60: =SUM($B$28:$B$29)*AR60 -> 14400 | AV60: =AR60*$B$15/4 -> 2070 | AW60: =SUM($AV$3:AV60) -> 88962.562 | AX60: =AR60-AS60-AU60-AW60 -> 568787.44 | AY60: =$B$36*V60 -> 1865.5 | AZ60: =SUM(AY60:AY60)*4/AR60 -> 0.010363889 | BA60: =SUM(AY60:AY60)/V60 -> 0.35 | BB60: =IF(MortgageRate="Discounted",_xlfn.XLOOKUP(L60,'mortgage-rates'!$A:$A,'mortgage-rates'!$E:$E)/100,_xlfn.XLOOKUP(L60,'mortgage-rates'!$A:$A,'mortgage-rates'!$D:$D)/100) -> 0.0365 | BC60: =BC59-BF59 -> 158056.08 | BD60: =IF($B$16*12/3-Q60+1>0,-PMT($BB60/4,$B$16*12/3-Q60+1,BC60),0) -> 4460.4248 | BE60: =BC60*($BB60/4) -> 1442.2617 | BF60: =BD60-BE60 -> 3018.1631 | BG60: =AT60+AY60+BD60 -> 6325.9248 | BH60: =INDEX(cpi!B:B,MATCH($L60,cpi!A:A)) -> 114.5 | BI60: =100*BH60/BH$3 -> 135.34279 | BJ60: =100*AC60/AC$3 -> 197.57431 | BK60: =100*AD60/AD$3 -> 194.19317 | BL60: =BJ60*GlobalPortfolio+BK60*AusPortfolio -> 196.55997 | BM60: =100*AE60/$AE$3 -> 392.94614 | BN60: =100*AR60/AR$3 -> 218.18182 | BO60: =100*AX60/AX$3 -> 176.84733
L61: =DATE(YEAR(L60),MONTH(L60)+3,1) -> 44075 | M61: =AP61 -> 443696.19 | N61: =AX61-BC61 -> 401083.27 | O61: =M61/N61 -> 1.1062446 | P61: =X61/BG61 -> 0.87437884 | Q61: 59 | R61: =EOMONTH(L61,0)-EOMONTH(L61,-3) -> 92 | T61: =IF($B$10="3BR_H", INDEX('3BR_H-processed'!$C:$D,MATCH($L61,'3BR_H-processed'!$B:$B,0),MATCH(Council_Area,'3BR_H-processed'!$C$1:$D$1,0)), INDEX('2BR_F-processed'!$C:$D,MATCH($L61,'2BR_F-processed'!$B:$B,0),MATCH(Council_Area,'2BR_F-processed'!$C$1:$D$1,0))) -> 400 | U61: =IF(MOD(Q61,4)=1,T61,U60) -> 410 | V61: =U61*(R61)/7 -> 5388.5714 | W61: =$B$53/4*BH61/_xlfn.XLOOKUP(Q_end,cpi!A:A,cpi!B:B) -> 160.60815 | X61: =V61+W61 -> 5549.1796 | Y61: =BG61-X61 -> 797.24524 | Z61: =Y61*$B$47 -> 0 | AA61: {=(Y61+Z61)*eff_invest} -> 797.24524 | AB61: =AA61*(_xlfn.XLOOKUP(Q_end,cpi!A:A,cpi!B:B)/BH61) -> 992.78302 | AC61: {=INDEX('msci-indices'!C:C,MATCH($L61,'msci-indices'!$B:$B)-2)} -> 1788.7914 | AD61: {=INDEX('msci-indices'!D:D,MATCH($L61,'msci-indices'!$B:$B)-2)} -> 1621.6232 | AE61: =AI60+AA61 -> 420814.91 | AF61: {=INDEX('msci-indices'!C:C,MATCH($L61,'msci-indices'!$B:$B)+1)} -> 1929.6384 | AG61: {=INDEX('msci-indices'!D:D,MATCH($L61,'msci-indices'!$B:$B)+1)} -> 1620.9838 | AH61: =(InvestFees/4)*AE61 -> 263.00932 | AI61: =((AF61/AC61)*GlobalPortfolio+(AG61/AD61)*AusPortfolio)*AE61-AH61 -> 443696.19 | AJ61: =AJ60+AA61 -> 209976.04 | AK61: =AI61-AJ61 -> 233720.15 | AL61: =AJ61*(_xlfn.XLOOKUP(Q_end,cpi!A:A,cpi!B:B)/BH61) -> 261476.19 | AM61: {=SUMPRODUCT($AA$3:AA61,_xlfn.SORTBY($BH$3:BH61,_xlfn.SEQUENCE(ROWS($BH$3:BH61)),-1)/$BH$3)} -> 273762.42 | AN61: =AI61-AM61 -> 169933.77 | AO61: =IF($B$49="Real gains",MAX($B$50*AN61,0),IF($B$49="Discounted nominal gains",MAX($B$50*AK61/2,0),0)) -> 0 | AP61: =AI61-AO61 -> 443696.19 | AR61: =IF($B$10="3BR_H", INDEX('ns-combined'!$C:$D,MATCH($L61,'ns-combined'!$B:$B,0),MATCH(Council_Area,'ns-combined'!$C$1:$D$1,0))*1000, INDEX('s-combined'!$C:$D,MATCH($L61,'s-combined'!$B:$B,0),MATCH(Council_Area,'s-combined'!$C$1:$D$1,0))*1000) -> 710000 | AS61: =AS60+$AS$3 -> 48675 | AT61: 0 | AU61: =SUM($B$28:$B$29)*AR61 -> 14200 | AV61: =AR61*$B$15/4 -> 2041.25 | AW61: =SUM($AV$3:AV61) -> 91003.812 | AX61: =AR61-AS61-AU61-AW61 -> 556121.19 | AY61: =$B$36*V61 -> 1886 | AZ61: =SUM(AY61:AY61)*4/AR61 -> 0.010625352 | BA61: =SUM(AY61:AY61)/V61 -> 0.35 | BB61: =IF(MortgageRate="Discounted",_xlfn.XLOOKUP(L61,'mortgage-rates'!$A:$A,'mortgage-rates'!$E:$E)/100,_xlfn.XLOOKUP(L61,'mortgage-rates'!$A:$A,'mortgage-rates'!$D:$D)/100) -> 0.0365 | BC61: =BC60-BF60 -> 155037.91 | BD61: =IF($B$16*12/3-Q61+1>0,-PMT($BB61/4,$B$16*12/3-Q61+1,BC61),0) -> 4460.4248 | BE61: =BC61*($BB61/4) -> 1414.721 | BF61: =BD61-BE61 -> 3045.7039 | BG61: =AT61+AY61+BD61 -> 6346.4248 | BH61: =INDEX(cpi!B:B,MATCH($L61,cpi!A:A)) -> 116.2 | BI61: =100*BH61/BH$3 -> 137.35225 | BJ61: =100*AC61/AC$3 -> 236.9638 | BK61: =100*AD61/AD$3 -> 227.4506 | BL61: =BJ61*GlobalPortfolio+BK61*AusPortfolio -> 234.10984 | BM61: =100*AE61/$AE$3 -> 468.61499 | BN61: =100*AR61/AR$3 -> 215.15152 | BO61: =100*AX61/AX$3 -> 172.90914
L62: =DATE(YEAR(L61),MONTH(L61)+3,1) -> 44166 | M62: =AP62 -> 509986.97 | N62: =AX62-BC62 -> 450118.98 | O62: =M62/N62 -> 1.1330048 | P62: =X62/BG62 -> 0.87459663 | Q62: 60 | R62: =EOMONTH(L62,0)-EOMONTH(L62,-3) -> 92 | T62: =IF($B$10="3BR_H", INDEX('3BR_H-processed'!$C:$D,MATCH($L62,'3BR_H-processed'!$B:$B,0),MATCH(Council_Area,'3BR_H-processed'!$C$1:$D$1,0)), INDEX('2BR_F-processed'!$C:$D,MATCH($L62,'2BR_F-processed'!$B:$B,0),MATCH(Council_Area,'2BR_F-processed'!$C$1:$D$1,0))) -> 400 | U62: =IF(MOD(Q62,4)=1,T62,U61) -> 410 | V62: =U62*(R62)/7 -> 5388.5714 | W62: =$B$53/4*BH62/_xlfn.XLOOKUP(Q_end,cpi!A:A,cpi!B:B) -> 161.99032 | X62: =V62+W62 -> 5550.5618 | Y62: =BG62-X62 -> 795.86307 | Z62: =Y62*$B$47 -> 0 | AA62: {=(Y62+Z62)*eff_invest} -> 795.86307 | AB62: =AA62*(_xlfn.XLOOKUP(Q_end,cpi!A:A,cpi!B:B)/BH62) -> 982.60569 | AC62: {=INDEX('msci-indices'!C:C,MATCH($L62,'msci-indices'!$B:$B)-2)} -> 1929.6384 | AD62: {=INDEX('msci-indices'!D:D,MATCH($L62,'msci-indices'!$B:$B)-2)} -> 1620.9838 | AE62: =AI61+AA62 -> 444492.05 | AF62: {=INDEX('msci-indices'!C:C,MATCH($L62,'msci-indices'!$B:$B)+1)} -> 2220.9403 | AG62: {=INDEX('msci-indices'!D:D,MATCH($L62,'msci-indices'!$B:$B)+1)} -> 1849.5395 | AH62: =(InvestFees/4)*AE62 -> 277.80753 | AI62: =((AF62/AC62)*GlobalPortfolio+(AG62/AD62)*AusPortfolio)*AE62-AH62 -> 509986.97 | AJ62: =AJ61+AA62 -> 210771.9 | AK62: =AI62-AJ62 -> 299215.07 | AL62: =AJ62*(_xlfn.XLOOKUP(Q_end,cpi!A:A,cpi!B:B)/BH62) -> 260227.77 | AM62: {=SUMPRODUCT($AA$3:AA62,_xlfn.SORTBY($BH$3:BH62,_xlfn.SEQUENCE(ROWS($BH$3:BH62)),-1)/$BH$3)} -> 276316.86 | AN62: =AI62-AM62 -> 233670.11 | AO62: =IF($B$49="Real gains",MAX($B$50*AN62,0),IF($B$49="Discounted nominal gains",MAX($B$50*AK62/2,0),0)) -> 0 | AP62: =AI62-AO62 -> 509986.97 | AR62: =IF($B$10="3BR_H", INDEX('ns-combined'!$C:$D,MATCH($L62,'ns-combined'!$B:$B,0),MATCH(Council_Area,'ns-combined'!$C$1:$D$1,0))*1000, INDEX('s-combined'!$C:$D,MATCH($L62,'s-combined'!$B:$B,0),MATCH(Council_Area,'s-combined'!$C$1:$D$1,0))*1000) -> 760000 | AS62: =AS61+$AS$3 -> 49500 | AT62: 0 | AU62: =SUM($B$28:$B$29)*AR62 -> 15200 | AV62: =AR62*$B$15/4 -> 2185 | AW62: =SUM($AV$3:AV62) -> 93188.812 | AX62: =AR62-AS62-AU62-AW62 -> 602111.19 | AY62: =$B$36*V62 -> 1886 | AZ62: =SUM(AY62:AY62)*4/AR62 -> 0.0099263158 | BA62: =SUM(AY62:AY62)/V62 -> 0.35 | BB62: =IF(MortgageRate="Discounted",_xlfn.XLOOKUP(L62,'mortgage-rates'!$A:$A,'mortgage-rates'!$E:$E)/100,_xlfn.XLOOKUP(L62,'mortgage-rates'!$A:$A,'mortgage-rates'!$D:$D)/100) -> 0.0365 | BC62: =BC61-BF61 -> 151992.21 | BD62: =IF($B$16*12/3-Q62+1>0,-PMT($BB62/4,$B$16*12/3-Q62+1,BC62),0) -> 4460.4248 | BE62: =BC62*($BB62/4) -> 1386.9289 | BF62: =BD62-BE62 -> 3073.4959 | BG62: =AT62+AY62+BD62 -> 6346.4248 | BH62: =INDEX(cpi!B:B,MATCH($L62,cpi!A:A)) -> 117.2 | BI62: =100*BH62/BH$3 -> 138.53428 | BJ62: =100*AC62/AC$3 -> 255.622 | BK62: =100*AD62/AD$3 -> 227.36091 | BL62: =BJ62*GlobalPortfolio+BK62*AusPortfolio -> 247.14367 | BM62: =100*AE62/$AE$3 -> 494.9816 | BN62: =100*AR62/AR$3 -> 230.30303 | BO62: =100*AX62/AX$3 -> 187.20835
L63: =DATE(YEAR(L62),MONTH(L62)+3,1) -> 44256 | M63: =AP63 -> 536864.25 | N63: =AX63-BC63 -> 489267.47 | O63: =M63/N63 -> 1.0972817 | P63: =X63/BG63 -> 0.86183697 | Q63: 61 | R63: =EOMONTH(L63,0)-EOMONTH(L63,-3) -> 90 | T63: =IF($B$10="3BR_H", INDEX('3BR_H-processed'!$C:$D,MATCH($L63,'3BR_H-processed'!$B:$B,0),MATCH(Council_Area,'3BR_H-processed'!$C$1:$D$1,0)), INDEX('2BR_F-processed'!$C:$D,MATCH($L63,'2BR_F-processed'!$B:$B,0),MATCH(Council_Area,'2BR_F-processed'!$C$1:$D$1,0))) -> 410 | U63: =IF(MOD(Q63,4)=1,T63,U62) -> 410 | V63: =U63*(R63)/7 -> 5271.4286 | W63: =$B$53/4*BH63/_xlfn.XLOOKUP(Q_end,cpi!A:A,cpi!B:B) -> 162.81963 | X63: =V63+W63 -> 5434.2482 | Y63: =BG63-X63 -> 871.17663 | Z63: =Y63*$B$47 -> 0 | AA63: {=(Y63+Z63)*eff_invest} -> 871.17663 | AB63: =AA63*(_xlfn.XLOOKUP(Q_end,cpi!A:A,cpi!B:B)/BH63) -> 1070.1125 | AC63: {=INDEX('msci-indices'!C:C,MATCH($L63,'msci-indices'!$B:$B)-2)} -> 2220.9403 | AD63: {=INDEX('msci-indices'!D:D,MATCH($L63,'msci-indices'!$B:$B)-2)} -> 1849.5395 | AE63: =AI62+AA63 -> 510858.15 | AF63: {=INDEX('msci-indices'!C:C,MATCH($L63,'msci-indices'!$B:$B)+1)} -> 2342.5855 | AG63: {=INDEX('msci-indices'!D:D,MATCH($L63,'msci-indices'!$B:$B)+1)} -> 1930.8659 | AH63: =(InvestFees/4)*AE63 -> 319.28634 | AI63: =((AF63/AC63)*GlobalPortfolio+(AG63/AD63)*AusPortfolio)*AE63-AH63 -> 536864.25 | AJ63: =AJ62+AA63 -> 211643.08 | AK63: =AI63-AJ63 -> 325221.17 | AL63: =AJ63*(_xlfn.XLOOKUP(Q_end,cpi!A:A,cpi!B:B)/BH63) -> 259972.44 | AM63: {=SUMPRODUCT($AA$3:AA63,_xlfn.SORTBY($BH$3:BH63,_xlfn.SEQUENCE(ROWS($BH$3:BH63)),-1)/$BH$3)} -> 278542.33 | AN63: =AI63-AM63 -> 258321.91 | AO63: =IF($B$49="Real gains",MAX($B$50*AN63,0),IF($B$49="Discounted nominal gains",MAX($B$50*AK63/2,0),0)) -> 0 | AP63: =AI63-AO63 -> 536864.25 | AR63: =IF($B$10="3BR_H", INDEX('ns-combined'!$C:$D,MATCH($L63,'ns-combined'!$B:$B,0),MATCH(Council_Area,'ns-combined'!$C$1:$D$1,0))*1000, INDEX('s-combined'!$C:$D,MATCH($L63,'s-combined'!$B:$B,0),MATCH(Council_Area,'s-combined'!$C$1:$D$1,0))*1000) -> 800000 | AS63: =AS62+$AS$3 -> 50325 | AT63: 0 | AU63: =SUM($B$28:$B$29)*AR63 -> 16000 | AV63: =AR63*$B$15/4 -> 2300 | AW63: =SUM($AV$3:AV63) -> 95488.812 | AX63: =AR63-AS63-AU63-AW63 -> 638186.19 | AY63: =$B$36*V63 -> 1845 | AZ63: =SUM(AY63:AY63)*4/AR63 -> 0.009225 | BA63: =SUM(AY63:AY63)/V63 -> 0.35 | BB63: =IF(MortgageRate="Discounted",_xlfn.XLOOKUP(L63,'mortgage-rates'!$A:$A,'mortgage-rates'!$E:$E)/100,_xlfn.XLOOKUP(L63,'mortgage-rates'!$A:$A,'mortgage-rates'!$D:$D)/100) -> 0.0365 | BC63: =BC62-BF62 -> 148918.71 | BD63: =IF($B$16*12/3-Q63+1>0,-PMT($BB63/4,$B$16*12/3-Q63+1,BC63),0) -> 4460.4248 | BE63: =BC63*($BB63/4) -> 1358.8833 | BF63: =BD63-BE63 -> 3101.5416 | BG63: =AT63+AY63+BD63 -> 6305.4248 | BH63: =INDEX(cpi!B:B,MATCH($L63,cpi!A:A)) -> 117.8 | BI63: =100*BH63/BH$3 -> 139.2435 | BJ63: =100*AC63/AC$3 -> 294.21119 | BK63: =100*AD63/AD$3 -> 259.41837 | BL63: =BJ63*GlobalPortfolio+BK63*AusPortfolio -> 283.77335 | BM63: =100*AE63/$AE$3 -> 568.88618 | BN63: =100*AR63/AR$3 -> 242.42424 | BO63: =100*AX63/AX$3 -> 198.42478
L64: =DATE(YEAR(L63),MONTH(L63)+3,1) -> 44348 | M64: =AP64 -> 578865.6 | N64: =AX64-BC64 -> 518557.76 | O64: =M64/N64 -> 1.1162992 | P64: =X64/BG64 -> 0.87023954 | Q64: 62 | R64: =EOMONTH(L64,0)-EOMONTH(L64,-3) -> 91 | T64: =IF($B$10="3BR_H", INDEX('3BR_H-processed'!$C:$D,MATCH($L64,'3BR_H-processed'!$B:$B,0),MATCH(Council_Area,'3BR_H-processed'!$C$1:$D$1,0)), INDEX('2BR_F-processed'!$C:$D,MATCH($L64,'2BR_F-processed'!$B:$B,0),MATCH(Council_Area,'2BR_F-processed'!$C$1:$D$1,0))) -> 410 | U64: =IF(MOD(Q64,4)=1,T64,U63) -> 410 | V64: =U64*(R64)/7 -> 5330 | W64: =$B$53/4*BH64/_xlfn.XLOOKUP(Q_end,cpi!A:A,cpi!B:B) -> 164.2018 | X64: =V64+W64 -> 5494.2018 | Y64: =BG64-X64 -> 819.2344 | Z64: =Y64*$B$47 -> 0 | AA64: {=(Y64+Z64)*eff_invest} -> 819.2344 | AB64: =AA64*(_xlfn.XLOOKUP(Q_end,cpi!A:A,cpi!B:B)/BH64) -> 997.83854 | AC64: {=INDEX('msci-indices'!C:C,MATCH($L64,'msci-indices'!$B:$B)-2)} -> 2342.5855 | AD64: {=INDEX('msci-indices'!D:D,MATCH($L64,'msci-indices'!$B:$B)-2)} -> 1930.8659 | AE64: =AI63+AA64 -> 537683.48 | AF64: {=INDEX('msci-indices'!C:C,MATCH($L64,'msci-indices'!$B:$B)+1)} -> 2515.6062 | AG64: {=INDEX('msci-indices'!D:D,MATCH($L64,'msci-indices'!$B:$B)+1)} -> 2095.0894 | AH64: =(InvestFees/4)*AE64 -> 336.05218 | AI64: =((AF64/AC64)*GlobalPortfolio+(AG64/AD64)*AusPortfolio)*AE64-AH64 -> 578865.6 | AJ64: =AJ63+AA64 -> 212462.31 | AK64: =AI64-AJ64 -> 366403.28 | AL64: =AJ64*(_xlfn.XLOOKUP(Q_end,cpi!A:A,cpi!B:B)/BH64) -> 258781.96 | AM64: {=SUMPRODUCT($AA$3:AA64,_xlfn.SORTBY($BH$3:BH64,_xlfn.SEQUENCE(ROWS($BH$3:BH64)),-1)/$BH$3)} -> 281160.75 | AN64: =AI64-AM64 -> 297704.85 | AO64: =IF($B$49="Real gains",MAX($B$50*AN64,0),IF($B$49="Discounted nominal gains",MAX($B$50*AK64/2,0),0)) -> 0 | AP64: =AI64-AO64 -> 578865.6 | AR64: =IF($B$10="3BR_H", INDEX('ns-combined'!$C:$D,MATCH($L64,'ns-combined'!$B:$B,0),MATCH(Council_Area,'ns-combined'!$C$1:$D$1,0))*1000, INDEX('s-combined'!$C:$D,MATCH($L64,'s-combined'!$B:$B,0),MATCH(Council_Area,'s-combined'!$C$1:$D$1,0))*1000) -> 830000 | AS64: =AS63+$AS$3 -> 51150 | AT64: 0 | AU64: =SUM($B$28:$B$29)*AR64 -> 16600 | AV64: =AR64*$B$15/4 -> 2386.25 | AW64: =SUM($AV$3:AV64) -> 97875.062 | AX64: =AR64-AS64-AU64-AW64 -> 664374.94 | AY64: =$B$36*V64 -> 1865.5 | AZ64: =SUM(AY64:AY64)*4/AR64 -> 0.0089903614 | BA64: =SUM(AY64:AY64)/V64 -> 0.35 | BB64: =IF(MortgageRate="Discounted",_xlfn.XLOOKUP(L64,'mortgage-rates'!$A:$A,'mortgage-rates'!$E:$E)/100,_xlfn.XLOOKUP(L64,'mortgage-rates'!$A:$A,'mortgage-rates'!$D:$D)/100) -> 0.0359 | BC64: =BC63-BF63 -> 145817.17 | BD64: =IF($B$16*12/3-Q64+1>0,-PMT($BB64/4,$B$16*12/3-Q64+1,BC64),0) -> 4447.9362 | BE64: =BC64*($BB64/4) -> 1308.7091 | BF64: =BD64-BE64 -> 3139.2271 | BG64: =AT64+AY64+BD64 -> 6313.4362 | BH64: =INDEX(cpi!B:B,MATCH($L64,cpi!A:A)) -> 118.8 | BI64: =100*BH64/BH$3 -> 140.42553 | BJ64: =100*AC64/AC$3 -> 310.3257 | BK64: =100*AD64/AD$3 -> 270.8253 | BL64: =BJ64*GlobalPortfolio+BK64*AusPortfolio -> 298.47558 | BM64: =100*AE64/$AE$3 -> 598.75858 | BN64: =100*AR64/AR$3 -> 251.51515 | BO64: =100*AX64/AX$3 -> 206.56739
